/*    */ package com.claro.dao;
/*    */ 
/*    */ /*    */ import org.apache.log4j.Logger;

import com.claro.util.ServiceLocator;
/*    */ 
/*    */ 
/*    */ 
/*    */ 
/*    */ 
/*    */ 
/*    */ 
/*    */ 
/*    */ 
/*    */ 
/*    */ 
/*    */ 
/*    */ public class AdministracionDAO
/*    */ {
/* 19 */   protected final Logger logger = Logger.getLogger("loggerCirculoAzul");
/* 20 */   protected final Logger error = Logger.getLogger("loggerCirculoAzulError");
/*    */   
/*    */   private String schema_database;
/*    */   
/*    */ 
/*    */   public AdministracionDAO()
/*    */   {
/*    */     try
/*    */     {
/* 29 */       this.schema_database = ServiceLocator.getInstance().getVariable(ServiceLocator.schema_database);
/*    */     } catch (Exception e) {
/* 31 */       this.error.error("AdministracionDAO", e);
/*    */     }
/*    */   }
/*    */   
/*    */   /* Error */
/*    */   public com.claro.transfer.MensajeTO actualizarPassword(String _usuario, String _passActual, String _passNuevo, String _passConfirm)
/*    */     throws com.claro.exception.CAException
/*    */   {
	//TODO se cambia para compilacion
		return null;
/*    */     // Byte code:
/*    */     //   0: aconst_null
/*    */     //   1: astore 5
/*    */     //   3: aconst_null
/*    */     //   4: astore 6
/*    */     //   6: aconst_null
/*    */     //   7: astore 7
/*    */     //   9: new 61	java/lang/StringBuilder
/*    */     //   12: dup
/*    */     //   13: ldc 63
/*    */     //   15: invokespecial 65	java/lang/StringBuilder:<init>	(Ljava/lang/String;)V
/*    */     //   18: aload_0
/*    */     //   19: getfield 41	com/claro/dao/AdministracionDAO:schema_database	Ljava/lang/String;
/*    */     //   22: invokevirtual 68	java/lang/StringBuilder:append	(Ljava/lang/String;)Ljava/lang/StringBuilder;
/*    */     //   25: ldc 72
/*    */     //   27: invokevirtual 68	java/lang/StringBuilder:append	(Ljava/lang/String;)Ljava/lang/StringBuilder;
/*    */     //   30: ldc 74
/*    */     //   32: invokevirtual 68	java/lang/StringBuilder:append	(Ljava/lang/String;)Ljava/lang/StringBuilder;
/*    */     //   35: ldc 76
/*    */     //   37: invokevirtual 68	java/lang/StringBuilder:append	(Ljava/lang/String;)Ljava/lang/StringBuilder;
/*    */     //   40: ldc 78
/*    */     //   42: invokevirtual 68	java/lang/StringBuilder:append	(Ljava/lang/String;)Ljava/lang/StringBuilder;
/*    */     //   45: invokevirtual 80	java/lang/StringBuilder:toString	()Ljava/lang/String;
/*    */     //   48: astore 8
/*    */     //   50: iconst_0
/*    */     //   51: istore 9
/*    */     //   53: invokestatic 84	java/lang/System:currentTimeMillis	()J
/*    */     //   56: lstore 10
/*    */     //   58: aload_0
/*    */     //   59: getfield 23	com/claro/dao/AdministracionDAO:logger	Lorg/apache/log4j/Logger;
/*    */     //   62: new 61	java/lang/StringBuilder
/*    */     //   65: dup
/*    */     //   66: ldc 90
/*    */     //   68: invokespecial 65	java/lang/StringBuilder:<init>	(Ljava/lang/String;)V
/*    */     //   71: getstatic 92	com/claro/util/Constantes:DATEFORMTALog	Ljava/text/SimpleDateFormat;
/*    */     //   74: new 98	java/util/Date
/*    */     //   77: dup
/*    */     //   78: invokespecial 100	java/util/Date:<init>	()V
/*    */     //   81: invokevirtual 101	java/text/SimpleDateFormat:format	(Ljava/util/Date;)Ljava/lang/String;
/*    */     //   84: invokevirtual 68	java/lang/StringBuilder:append	(Ljava/lang/String;)Ljava/lang/StringBuilder;
/*    */     //   87: ldc 107
/*    */     //   89: invokevirtual 68	java/lang/StringBuilder:append	(Ljava/lang/String;)Ljava/lang/StringBuilder;
/*    */     //   92: lload 10
/*    */     //   94: invokevirtual 109	java/lang/StringBuilder:append	(J)Ljava/lang/StringBuilder;
/*    */     //   97: invokevirtual 80	java/lang/StringBuilder:toString	()Ljava/lang/String;
/*    */     //   100: invokevirtual 112	org/apache/log4j/Logger:info	(Ljava/lang/Object;)V
/*    */     //   103: aload_3
/*    */     //   104: ifnull +10 -> 114
/*    */     //   107: aload_3
/*    */     //   108: invokevirtual 116	java/lang/String:length	()I
/*    */     //   111: ifgt +14 -> 125
/*    */     //   114: new 59	com/claro/exception/CAException
/*    */     //   117: dup
/*    */     //   118: iconst_m1
/*    */     //   119: ldc 122
/*    */     //   121: invokespecial 124	com/claro/exception/CAException:<init>	(ILjava/lang/String;)V
/*    */     //   124: athrow
/*    */     //   125: aload 4
/*    */     //   127: ifnull +11 -> 138
/*    */     //   130: aload 4
/*    */     //   132: invokevirtual 116	java/lang/String:length	()I
/*    */     //   135: ifgt +14 -> 149
/*    */     //   138: new 59	com/claro/exception/CAException
/*    */     //   141: dup
/*    */     //   142: iconst_m1
/*    */     //   143: ldc 127
/*    */     //   145: invokespecial 124	com/claro/exception/CAException:<init>	(ILjava/lang/String;)V
/*    */     //   148: athrow
/*    */     //   149: aload_3
/*    */     //   150: aload 4
/*    */     //   152: invokevirtual 129	java/lang/String:equals	(Ljava/lang/Object;)Z
/*    */     //   155: ifne +14 -> 169
/*    */     //   158: new 59	com/claro/exception/CAException
/*    */     //   161: dup
/*    */     //   162: iconst_m1
/*    */     //   163: ldc -123
/*    */     //   165: invokespecial 124	com/claro/exception/CAException:<init>	(ILjava/lang/String;)V
/*    */     //   168: athrow
/*    */     //   169: aload_0
/*    */     //   170: getfield 23	com/claro/dao/AdministracionDAO:logger	Lorg/apache/log4j/Logger;
/*    */     //   173: new 61	java/lang/StringBuilder
/*    */     //   176: dup
/*    */     //   177: ldc -121
/*    */     //   179: invokespecial 65	java/lang/StringBuilder:<init>	(Ljava/lang/String;)V
/*    */     //   182: getstatic 92	com/claro/util/Constantes:DATEFORMTALog	Ljava/text/SimpleDateFormat;
/*    */     //   185: new 98	java/util/Date
/*    */     //   188: dup
/*    */     //   189: invokespecial 100	java/util/Date:<init>	()V
/*    */     //   192: invokevirtual 101	java/text/SimpleDateFormat:format	(Ljava/util/Date;)Ljava/lang/String;
/*    */     //   195: invokevirtual 68	java/lang/StringBuilder:append	(Ljava/lang/String;)Ljava/lang/StringBuilder;
/*    */     //   198: ldc 107
/*    */     //   200: invokevirtual 68	java/lang/StringBuilder:append	(Ljava/lang/String;)Ljava/lang/StringBuilder;
/*    */     //   203: lload 10
/*    */     //   205: invokevirtual 109	java/lang/StringBuilder:append	(J)Ljava/lang/StringBuilder;
/*    */     //   208: invokevirtual 80	java/lang/StringBuilder:toString	()Ljava/lang/String;
/*    */     //   211: invokevirtual 112	org/apache/log4j/Logger:info	(Ljava/lang/Object;)V
/*    */     //   214: invokestatic 29	com/claro/util/ServiceLocator:getInstance	()Lcom/claro/util/ServiceLocator;
/*    */     //   217: getstatic 137	com/claro/util/ServiceLocator:jdbcCirculoAzul	Ljava/lang/String;
/*    */     //   220: invokevirtual 140	com/claro/util/ServiceLocator:getConnection	(Ljava/lang/String;)Ljava/sql/Connection;
/*    */     //   223: astore 5
/*    */     //   225: aload_0
/*    */     //   226: getfield 23	com/claro/dao/AdministracionDAO:logger	Lorg/apache/log4j/Logger;
/*    */     //   229: new 61	java/lang/StringBuilder
/*    */     //   232: dup
/*    */     //   233: ldc -112
/*    */     //   235: invokespecial 65	java/lang/StringBuilder:<init>	(Ljava/lang/String;)V
/*    */     //   238: getstatic 92	com/claro/util/Constantes:DATEFORMTALog	Ljava/text/SimpleDateFormat;
/*    */     //   241: new 98	java/util/Date
/*    */     //   244: dup
/*    */     //   245: invokespecial 100	java/util/Date:<init>	()V
/*    */     //   248: invokevirtual 101	java/text/SimpleDateFormat:format	(Ljava/util/Date;)Ljava/lang/String;
/*    */     //   251: invokevirtual 68	java/lang/StringBuilder:append	(Ljava/lang/String;)Ljava/lang/StringBuilder;
/*    */     //   254: ldc 107
/*    */     //   256: invokevirtual 68	java/lang/StringBuilder:append	(Ljava/lang/String;)Ljava/lang/StringBuilder;
/*    */     //   259: invokestatic 84	java/lang/System:currentTimeMillis	()J
/*    */     //   262: lload 10
/*    */     //   264: lsub
/*    */     //   265: invokevirtual 109	java/lang/StringBuilder:append	(J)Ljava/lang/StringBuilder;
/*    */     //   268: invokevirtual 80	java/lang/StringBuilder:toString	()Ljava/lang/String;
/*    */     //   271: invokevirtual 112	org/apache/log4j/Logger:info	(Ljava/lang/Object;)V
/*    */     //   274: aload 5
/*    */     //   276: aload 8
/*    */     //   278: invokeinterface 146 2 0
/*    */     //   283: astore 6
/*    */     //   285: aload 6
/*    */     //   287: iconst_1
/*    */     //   288: aload_3
/*    */     //   289: invokevirtual 152	java/lang/String:trim	()Ljava/lang/String;
/*    */     //   292: invokestatic 155	com/claro/util/Utils:getMD5Encrypted	(Ljava/lang/String;)Ljava/lang/String;
/*    */     //   295: invokeinterface 160 3 0
/*    */     //   300: aload 6
/*    */     //   302: iconst_2
/*    */     //   303: aload_1
/*    */     //   304: invokevirtual 165	java/lang/String:toUpperCase	()Ljava/lang/String;
/*    */     //   307: invokeinterface 160 3 0
/*    */     //   312: aload 6
/*    */     //   314: invokeinterface 168 1 0
/*    */     //   319: istore 9
/*    */     //   321: iload 9
/*    */     //   323: ifle +18 -> 341
/*    */     //   326: new 171	com/claro/transfer/MensajeTO
/*    */     //   329: dup
/*    */     //   330: iconst_0
/*    */     //   331: ldc -83
/*    */     //   333: invokespecial 175	com/claro/transfer/MensajeTO:<init>	(ILjava/lang/String;)V
/*    */     //   336: astore 7
/*    */     //   338: goto +15 -> 353
/*    */     //   341: new 171	com/claro/transfer/MensajeTO
/*    */     //   344: dup
/*    */     //   345: iconst_m1
/*    */     //   346: ldc -80
/*    */     //   348: invokespecial 175	com/claro/transfer/MensajeTO:<init>	(ILjava/lang/String;)V
/*    */     //   351: astore 7
/*    */     //   353: aload_0
/*    */     //   354: getfield 23	com/claro/dao/AdministracionDAO:logger	Lorg/apache/log4j/Logger;
/*    */     //   357: new 61	java/lang/StringBuilder
/*    */     //   360: dup
/*    */     //   361: ldc -78
/*    */     //   363: invokespecial 65	java/lang/StringBuilder:<init>	(Ljava/lang/String;)V
/*    */     //   366: getstatic 92	com/claro/util/Constantes:DATEFORMTALog	Ljava/text/SimpleDateFormat;
/*    */     //   369: new 98	java/util/Date
/*    */     //   372: dup
/*    */     //   373: invokespecial 100	java/util/Date:<init>	()V
/*    */     //   376: invokevirtual 101	java/text/SimpleDateFormat:format	(Ljava/util/Date;)Ljava/lang/String;
/*    */     //   379: invokevirtual 68	java/lang/StringBuilder:append	(Ljava/lang/String;)Ljava/lang/StringBuilder;
/*    */     //   382: ldc 107
/*    */     //   384: invokevirtual 68	java/lang/StringBuilder:append	(Ljava/lang/String;)Ljava/lang/StringBuilder;
/*    */     //   387: invokestatic 84	java/lang/System:currentTimeMillis	()J
/*    */     //   390: lload 10
/*    */     //   392: lsub
/*    */     //   393: invokevirtual 109	java/lang/StringBuilder:append	(J)Ljava/lang/StringBuilder;
/*    */     //   396: invokevirtual 80	java/lang/StringBuilder:toString	()Ljava/lang/String;
/*    */     //   399: invokevirtual 112	org/apache/log4j/Logger:info	(Ljava/lang/Object;)V
/*    */     //   402: goto +213 -> 615
/*    */     //   405: astore 10
/*    */     //   407: aload_0
/*    */     //   408: getfield 27	com/claro/dao/AdministracionDAO:error	Lorg/apache/log4j/Logger;
/*    */     //   411: ldc -76
/*    */     //   413: aload 10
/*    */     //   415: invokevirtual 182	org/apache/log4j/Logger:info	(Ljava/lang/Object;Ljava/lang/Throwable;)V
/*    */     //   418: new 171	com/claro/transfer/MensajeTO
/*    */     //   421: dup
/*    */     //   422: iconst_m1
/*    */     //   423: new 61	java/lang/StringBuilder
/*    */     //   426: dup
/*    */     //   427: ldc -72
/*    */     //   429: invokespecial 65	java/lang/StringBuilder:<init>	(Ljava/lang/String;)V
/*    */     //   432: aload 10
/*    */     //   434: invokevirtual 186	java/sql/SQLException:toString	()Ljava/lang/String;
/*    */     //   437: invokevirtual 68	java/lang/StringBuilder:append	(Ljava/lang/String;)Ljava/lang/StringBuilder;
/*    */     //   440: ldc -67
/*    */     //   442: invokevirtual 68	java/lang/StringBuilder:append	(Ljava/lang/String;)Ljava/lang/StringBuilder;
/*    */     //   445: invokevirtual 80	java/lang/StringBuilder:toString	()Ljava/lang/String;
/*    */     //   448: invokespecial 175	com/claro/transfer/MensajeTO:<init>	(ILjava/lang/String;)V
/*    */     //   451: astore 7
/*    */     //   453: new 59	com/claro/exception/CAException
/*    */     //   456: dup
/*    */     //   457: iconst_m1
/*    */     //   458: new 61	java/lang/StringBuilder
/*    */     //   461: dup
/*    */     //   462: ldc -72
/*    */     //   464: invokespecial 65	java/lang/StringBuilder:<init>	(Ljava/lang/String;)V
/*    */     //   467: aload 10
/*    */     //   469: invokevirtual 186	java/sql/SQLException:toString	()Ljava/lang/String;
/*    */     //   472: invokevirtual 68	java/lang/StringBuilder:append	(Ljava/lang/String;)Ljava/lang/StringBuilder;
/*    */     //   475: ldc -67
/*    */     //   477: invokevirtual 68	java/lang/StringBuilder:append	(Ljava/lang/String;)Ljava/lang/StringBuilder;
/*    */     //   480: invokevirtual 80	java/lang/StringBuilder:toString	()Ljava/lang/String;
/*    */     //   483: aload 10
/*    */     //   485: invokespecial 191	com/claro/exception/CAException:<init>	(ILjava/lang/String;Ljava/lang/Exception;)V
/*    */     //   488: athrow
/*    */     //   489: astore 10
/*    */     //   491: aload_0
/*    */     //   492: getfield 27	com/claro/dao/AdministracionDAO:error	Lorg/apache/log4j/Logger;
/*    */     //   495: ldc -62
/*    */     //   497: aload 10
/*    */     //   499: invokevirtual 182	org/apache/log4j/Logger:info	(Ljava/lang/Object;Ljava/lang/Throwable;)V
/*    */     //   502: new 171	com/claro/transfer/MensajeTO
/*    */     //   505: dup
/*    */     //   506: iconst_m1
/*    */     //   507: new 61	java/lang/StringBuilder
/*    */     //   510: dup
/*    */     //   511: ldc -60
/*    */     //   513: invokespecial 65	java/lang/StringBuilder:<init>	(Ljava/lang/String;)V
/*    */     //   516: aload 10
/*    */     //   518: invokevirtual 198	java/lang/Exception:toString	()Ljava/lang/String;
/*    */     //   521: invokevirtual 68	java/lang/StringBuilder:append	(Ljava/lang/String;)Ljava/lang/StringBuilder;
/*    */     //   524: ldc -67
/*    */     //   526: invokevirtual 68	java/lang/StringBuilder:append	(Ljava/lang/String;)Ljava/lang/StringBuilder;
/*    */     //   529: invokevirtual 80	java/lang/StringBuilder:toString	()Ljava/lang/String;
/*    */     //   532: invokespecial 175	com/claro/transfer/MensajeTO:<init>	(ILjava/lang/String;)V
/*    */     //   535: astore 7
/*    */     //   537: new 59	com/claro/exception/CAException
/*    */     //   540: dup
/*    */     //   541: iconst_m1
/*    */     //   542: new 61	java/lang/StringBuilder
/*    */     //   545: dup
/*    */     //   546: ldc -57
/*    */     //   548: invokespecial 65	java/lang/StringBuilder:<init>	(Ljava/lang/String;)V
/*    */     //   551: aload 10
/*    */     //   553: invokevirtual 198	java/lang/Exception:toString	()Ljava/lang/String;
/*    */     //   556: invokevirtual 68	java/lang/StringBuilder:append	(Ljava/lang/String;)Ljava/lang/StringBuilder;
/*    */     //   559: ldc -67
/*    */     //   561: invokevirtual 68	java/lang/StringBuilder:append	(Ljava/lang/String;)Ljava/lang/StringBuilder;
/*    */     //   564: invokevirtual 80	java/lang/StringBuilder:toString	()Ljava/lang/String;
/*    */     //   567: aload 10
/*    */     //   569: invokespecial 191	com/claro/exception/CAException:<init>	(ILjava/lang/String;Ljava/lang/Exception;)V
/*    */     //   572: athrow
/*    */     //   573: astore 12
/*    */     //   575: aload 6
/*    */     //   577: ifnull +15 -> 592
/*    */     //   580: aload 6
/*    */     //   582: invokeinterface 201 1 0
/*    */     //   587: goto +5 -> 592
/*    */     //   590: astore 13
/*    */     //   592: aload 5
/*    */     //   594: ifnull +18 -> 612
/*    */     //   597: aload 5
/*    */     //   599: invokeinterface 204 1 0
/*    */     //   604: aconst_null
/*    */     //   605: astore 5
/*    */     //   607: goto +5 -> 612
/*    */     //   610: astore 13
/*    */     //   612: aload 12
/*    */     //   614: athrow
/*    */     //   615: aload 6
/*    */     //   617: ifnull +15 -> 632
/*    */     //   620: aload 6
/*    */     //   622: invokeinterface 201 1 0
/*    */     //   627: goto +5 -> 632
/*    */     //   630: astore 13
/*    */     //   632: aload 5
/*    */     //   634: ifnull +18 -> 652
/*    */     //   637: aload 5
/*    */     //   639: invokeinterface 204 1 0
/*    */     //   644: aconst_null
/*    */     //   645: astore 5
/*    */     //   647: goto +5 -> 652
/*    */     //   650: astore 13
/*    */     //   652: aload 7
/*    */     //   654: areturn
/*    */     // Line number table:
/*    */     //   Java source line #43	-> byte code offset #0
/*    */     //   Java source line #44	-> byte code offset #3
/*    */     //   Java source line #45	-> byte code offset #6
/*    */     //   Java source line #52	-> byte code offset #9
/*    */     //   Java source line #53	-> byte code offset #30
/*    */     //   Java source line #54	-> byte code offset #35
/*    */     //   Java source line #55	-> byte code offset #40
/*    */     //   Java source line #52	-> byte code offset #45
/*    */     //   Java source line #51	-> byte code offset #48
/*    */     //   Java source line #56	-> byte code offset #50
/*    */     //   Java source line #59	-> byte code offset #53
/*    */     //   Java source line #61	-> byte code offset #58
/*    */     //   Java source line #63	-> byte code offset #103
/*    */     //   Java source line #64	-> byte code offset #114
/*    */     //   Java source line #65	-> byte code offset #125
/*    */     //   Java source line #66	-> byte code offset #138
/*    */     //   Java source line #67	-> byte code offset #149
/*    */     //   Java source line #68	-> byte code offset #158
/*    */     //   Java source line #70	-> byte code offset #169
/*    */     //   Java source line #71	-> byte code offset #214
/*    */     //   Java source line #72	-> byte code offset #225
/*    */     //   Java source line #74	-> byte code offset #274
/*    */     //   Java source line #80	-> byte code offset #285
/*    */     //   Java source line #81	-> byte code offset #300
/*    */     //   Java source line #83	-> byte code offset #312
/*    */     //   Java source line #85	-> byte code offset #321
/*    */     //   Java source line #86	-> byte code offset #326
/*    */     //   Java source line #88	-> byte code offset #341
/*    */     //   Java source line #91	-> byte code offset #353
/*    */     //   Java source line #93	-> byte code offset #405
/*    */     //   Java source line #94	-> byte code offset #407
/*    */     //   Java source line #95	-> byte code offset #418
/*    */     //   Java source line #96	-> byte code offset #453
/*    */     //   Java source line #97	-> byte code offset #489
/*    */     //   Java source line #98	-> byte code offset #491
/*    */     //   Java source line #99	-> byte code offset #502
/*    */     //   Java source line #100	-> byte code offset #537
/*    */     //   Java source line #101	-> byte code offset #573
/*    */     //   Java source line #102	-> byte code offset #575
/*    */     //   Java source line #103	-> byte code offset #592
/*    */     //   Java source line #105	-> byte code offset #612
/*    */     //   Java source line #102	-> byte code offset #615
/*    */     //   Java source line #103	-> byte code offset #632
/*    */     //   Java source line #106	-> byte code offset #652
/*    */     // Local variable table:
/*    */     //   start	length	slot	name	signature
/*    */     //   0	655	0	this	AdministracionDAO
/*    */     //   0	655	1	_usuario	String
/*    */     //   0	655	2	_passActual	String
/*    */     //   0	655	3	_passNuevo	String
/*    */     //   0	655	4	_passConfirm	String
/*    */     //   1	645	5	cnx	java.sql.Connection
/*    */     //   4	617	6	ps	java.sql.PreparedStatement
/*    */     //   7	646	7	oMensaje	com.claro.transfer.MensajeTO
/*    */     //   48	229	8	qryUpdatePass	String
/*    */     //   51	271	9	rows	int
/*    */     //   56	335	10	inicioProceso	long
/*    */     //   405	79	10	e	java.sql.SQLException
/*    */     //   489	79	10	e	Exception
/*    */     //   573	40	12	localObject	Object
/*    */     //   590	1	13	localException1	Exception
/*    */     //   610	1	13	localException2	Exception
/*    */     //   630	1	13	localException3	Exception
/*    */     //   650	1	13	localException4	Exception
/*    */     // Exception table:
/*    */     //   from	to	target	type
/*    */     //   53	402	405	java/sql/SQLException
/*    */     //   53	402	489	java/lang/Exception
/*    */     //   53	573	573	finally
/*    */     //   580	587	590	java/lang/Exception
/*    */     //   597	607	610	java/lang/Exception
/*    */     //   620	627	630	java/lang/Exception
/*    */     //   637	647	650	java/lang/Exception
/*    */   }
/*    */ }


/* Location:              /opt/trabajo/claro/Guatemala/IS/CO/ClaroClub.ear!/ClaroClubEJB.jar!/com/claro/dao/AdministracionDAO.class
 * Java compiler version: 6 (50.0)
 * JD-Core Version:       0.7.1
 */