/*      */package com.claro.dao;

/*      */
/*      *//*      */
import java.sql.Connection;
/*      */
import java.sql.PreparedStatement;
/*      */
import java.sql.ResultSet;
/*      */
import java.sql.SQLException;
/*      */
import java.text.SimpleDateFormat;
/*      */
import java.util.ArrayList;
/*      */
import java.util.Calendar;
/*      */
import java.util.Hashtable;
/*      */
import java.util.Iterator;

/*      */
import org.apache.log4j.Logger;

import com.claro.catalogo.Catalogo;
/*      */
import com.claro.exception.CAException;
/*      */
import com.claro.redencion.sms.NotificaSMS;
/*      */
import com.claro.transfer.AlianzasTO;
/*      */
import com.claro.transfer.FactorTO;
/*      */
import com.claro.transfer.MensajeTO;
/*      */
import com.claro.transfer.ParametrosTO;
/*      */
import com.claro.transfer.PuntosRedimidosTO;
/*      */
import com.claro.transfer.PuntosTO;
/*      */
import com.claro.transfer.TelefonoTO;
/*      */
import com.claro.util.Constantes;
/*      */
import com.claro.util.ServiceLocator;
/*      */
import com.claro.util.Utils;

/*      */
/*      */
/*      */
/*      */
/*      */
/*      */
/*      */
/*      */public class AlianzasDAO
/*      */{
	/* 35 */protected final Logger logger = Logger
			.getLogger("loggerCirculoAzul");
	/* 36 */protected final Logger error = Logger
			.getLogger("loggerCirculoAzulError");
	/*      */private String schema_database;

	/*      */
	/*      */public AlianzasDAO() {
		/*      */try {
			/* 41 */this.schema_database = ServiceLocator.getInstance()
					.getVariable(ServiceLocator.schema_database);
			/*      */} catch (Exception e) {
			/* 43 */this.error.error("AlianzasDAO", e);
			/*      */}
		/*      */}

	/*      */
	/*      *//* Error */
	/*      */public ArrayList<AlianzasTO> consultaCanjesAlianzas(String cuenta,
			String secuencia)
	/*      */throws CAException
	/*      */{
		return null;
		/*      */// Byte code:
		/*      */// 0: new 63 java/util/ArrayList
		/*      */// 3: dup
		/*      */// 4: invokespecial 65 java/util/ArrayList:<init> ()V
		/*      */// 7: astore_3
		/*      */// 8: aconst_null
		/*      */// 9: astore 4
		/*      */// 11: aconst_null
		/*      */// 12: astore 5
		/*      */// 14: aconst_null
		/*      */// 15: astore 6
		/*      */// 17: new 66 java/lang/StringBuffer
		/*      */// 20: dup
		/*      */// 21: invokespecial 68 java/lang/StringBuffer:<init> ()V
		/*      */// 24: astore 7
		/*      */// 26: aload 7
		/*      */// 28: ldc 69
		/*      */// 30: invokevirtual 71 java/lang/StringBuffer:append
				// (Ljava/lang/String;)Ljava/lang/StringBuffer;
		/*      */// 33: pop
		/*      */// 34: aload 7
		/*      */// 36: ldc 75
		/*      */// 38: invokevirtual 71 java/lang/StringBuffer:append
				// (Ljava/lang/String;)Ljava/lang/StringBuffer;
		/*      */// 41: pop
		/*      */// 42: aload 7
		/*      */// 44: ldc 77
		/*      */// 46: invokevirtual 71 java/lang/StringBuffer:append
				// (Ljava/lang/String;)Ljava/lang/StringBuffer;
		/*      */// 49: aload_0
		/*      */// 50: getfield 41 com/claro/dao/AlianzasDAO:schema_database
				// Ljava/lang/String;
		/*      */// 53: invokevirtual 71 java/lang/StringBuffer:append
				// (Ljava/lang/String;)Ljava/lang/StringBuffer;
		/*      */// 56: ldc 79
		/*      */// 58: invokevirtual 71 java/lang/StringBuffer:append
				// (Ljava/lang/String;)Ljava/lang/StringBuffer;
		/*      */// 61: aload_0
		/*      */// 62: getfield 41 com/claro/dao/AlianzasDAO:schema_database
				// Ljava/lang/String;
		/*      */// 65: invokevirtual 71 java/lang/StringBuffer:append
				// (Ljava/lang/String;)Ljava/lang/StringBuffer;
		/*      */// 68: ldc 81
		/*      */// 70: invokevirtual 71 java/lang/StringBuffer:append
				// (Ljava/lang/String;)Ljava/lang/StringBuffer;
		/*      */// 73: pop
		/*      */// 74: aload 7
		/*      */// 76: ldc 83
		/*      */// 78: invokevirtual 71 java/lang/StringBuffer:append
				// (Ljava/lang/String;)Ljava/lang/StringBuffer;
		/*      */// 81: ldc 85
		/*      */// 83: invokevirtual 71 java/lang/StringBuffer:append
				// (Ljava/lang/String;)Ljava/lang/StringBuffer;
		/*      */// 86: pop
		/*      */// 87: aload 7
		/*      */// 89: ldc 87
		/*      */// 91: invokevirtual 71 java/lang/StringBuffer:append
				// (Ljava/lang/String;)Ljava/lang/StringBuffer;
		/*      */// 94: pop
		/*      */// 95: aload 7
		/*      */// 97: ldc 89
		/*      */// 99: invokevirtual 71 java/lang/StringBuffer:append
				// (Ljava/lang/String;)Ljava/lang/StringBuffer;
		/*      */// 102: pop
		/*      */// 103: aload 7
		/*      */// 105: ldc 91
		/*      */// 107: invokevirtual 71 java/lang/StringBuffer:append
				// (Ljava/lang/String;)Ljava/lang/StringBuffer;
		/*      */// 110: pop
		/*      */// 111: invokestatic 29 com/claro/util/ServiceLocator:getInstance
				// ()Lcom/claro/util/ServiceLocator;
		/*      */// 114: getstatic 93 com/claro/util/ServiceLocator:jdbcCirculoAzul
				// Ljava/lang/String;
		/*      */// 117: invokevirtual 96
				// com/claro/util/ServiceLocator:getConnection
				// (Ljava/lang/String;)Ljava/sql/Connection;
		/*      */// 120: astore 4
		/*      */// 122: aload 4
		/*      */// 124: aload 7
		/*      */// 126: invokevirtual 100 java/lang/StringBuffer:toString
				// ()Ljava/lang/String;
		/*      */// 129: invokeinterface 104 2 0
		/*      */// 134: astore 5
		/*      */// 136: aload 5
		/*      */// 138: iconst_1
		/*      */// 139: aload_1
		/*      */// 140: invokeinterface 110 3 0
		/*      */// 145: aload 5
		/*      */// 147: iconst_2
		/*      */// 148: aload_2
		/*      */// 149: invokestatic 116 java/lang/Integer:parseInt
				// (Ljava/lang/String;)I
		/*      */// 152: invokeinterface 122 3 0
		/*      */// 157: aload 5
		/*      */// 159: invokeinterface 126 1 0
		/*      */// 164: astore 6
		/*      */// 166: goto +191 -> 357
		/*      */// 169: new 130 com/claro/transfer/AlianzasTO
		/*      */// 172: dup
		/*      */// 173: invokespecial 132 com/claro/transfer/AlianzasTO:<init> ()V
		/*      */// 176: astore 8
		/*      */// 178: new 133 com/claro/transfer/TelefonoSimpleTO
		/*      */// 181: dup
		/*      */// 182: invokespecial 135
				// com/claro/transfer/TelefonoSimpleTO:<init> ()V
		/*      */// 185: astore 9
		/*      */// 187: new 136 com/claro/transfer/PuntosRedimidosTO
		/*      */// 190: dup
		/*      */// 191: invokespecial 138
				// com/claro/transfer/PuntosRedimidosTO:<init> ()V
		/*      */// 194: astore 10
		/*      */// 196: aload 9
		/*      */// 198: aload 6
		/*      */// 200: ldc -117
		/*      */// 202: invokeinterface 141 2 0
		/*      */// 207: invokevirtual 146
				// com/claro/transfer/TelefonoSimpleTO:setCuenta
				// (Ljava/lang/String;)V
		/*      */// 210: aload 9
		/*      */// 212: aload 6
		/*      */// 214: ldc -106
		/*      */// 216: invokeinterface 141 2 0
		/*      */// 221: invokevirtual 152
				// com/claro/transfer/TelefonoSimpleTO:setLinea
				// (Ljava/lang/String;)V
		/*      */// 224: aload 8
		/*      */// 226: aload 6
		/*      */// 228: ldc -101
		/*      */// 230: invokeinterface 157 2 0
		/*      */// 235: invokevirtual 161
				// com/claro/transfer/AlianzasTO:setFechaOperacion
				// (Ljava/sql/Date;)V
		/*      */// 238: aload 8
		/*      */// 240: aload 6
		/*      */// 242: ldc -91
		/*      */// 244: invokeinterface 141 2 0
		/*      */// 249: invokevirtual 167
				// com/claro/transfer/AlianzasTO:setCuentaAlianza
				// (Ljava/lang/String;)V
		/*      */// 252: aload 10
		/*      */// 254: aload 6
		/*      */// 256: ldc -86
		/*      */// 258: invokeinterface 172 2 0
		/*      */// 263: invokevirtual 175
				// com/claro/transfer/PuntosRedimidosTO:setPtsCanjeados (I)V
		/*      */// 266: aload 8
		/*      */// 268: aload 6
		/*      */// 270: ldc -77
		/*      */// 272: invokeinterface 172 2 0
		/*      */// 277: invokevirtual 181 com/claro/transfer/AlianzasTO:setMillas
				// (I)V
		/*      */// 280: aload 8
		/*      */// 282: aload 6
		/*      */// 284: ldc -72
		/*      */// 286: invokeinterface 141 2 0
		/*      */// 291: invokevirtual 186 com/claro/transfer/AlianzasTO:setUsuario
				// (Ljava/lang/String;)V
		/*      */// 294: aload 8
		/*      */// 296: aload 6
		/*      */// 298: ldc -67
		/*      */// 300: invokeinterface 141 2 0
		/*      */// 305: invokevirtual 191
				// com/claro/transfer/AlianzasTO:setComentario
				// (Ljava/lang/String;)V
		/*      */// 308: aload 8
		/*      */// 310: aload 6
		/*      */// 312: ldc -62
		/*      */// 314: invokeinterface 172 2 0
		/*      */// 319: invokevirtual 196
				// com/claro/transfer/AlianzasTO:setIdCuentaAlianza (I)V
		/*      */// 322: aload 8
		/*      */// 324: aload 6
		/*      */// 326: ldc -57
		/*      */// 328: invokeinterface 172 2 0
		/*      */// 333: invokevirtual 201
				// com/claro/transfer/AlianzasTO:setValorCuponOrig (I)V
		/*      */// 336: aload 8
		/*      */// 338: aload 9
		/*      */// 340: invokevirtual 204
				// com/claro/transfer/AlianzasTO:setTelefonoSimpleTO
				// (Lcom/claro/transfer/TelefonoSimpleTO;)V
		/*      */// 343: aload 8
		/*      */// 345: aload 10
		/*      */// 347: invokevirtual 208
				// com/claro/transfer/AlianzasTO:setPuntosRedimidosTO
				// (Lcom/claro/transfer/PuntosRedimidosTO;)V
		/*      */// 350: aload_3
		/*      */// 351: aload 8
		/*      */// 353: invokevirtual 212 java/util/ArrayList:add
				// (Ljava/lang/Object;)Z
		/*      */// 356: pop
		/*      */// 357: aload 6
		/*      */// 359: invokeinterface 216 1 0
		/*      */// 364: ifne -195 -> 169
		/*      */// 367: goto +113 -> 480
		/*      */// 370: astore 8
		/*      */// 372: new 59 com/claro/exception/CAException
		/*      */// 375: dup
		/*      */// 376: iconst_m1
		/*      */// 377: ldc -36
		/*      */// 379: aload 8
		/*      */// 381: invokespecial 222 com/claro/exception/CAException:<init>
				// (ILjava/lang/String;Ljava/lang/Exception;)V
		/*      */// 384: athrow
		/*      */// 385: astore 8
		/*      */// 387: new 59 com/claro/exception/CAException
		/*      */// 390: dup
		/*      */// 391: iconst_m1
		/*      */// 392: ldc -31
		/*      */// 394: aload 8
		/*      */// 396: invokespecial 222 com/claro/exception/CAException:<init>
				// (ILjava/lang/String;Ljava/lang/Exception;)V
		/*      */// 399: athrow
		/*      */// 400: astore 8
		/*      */// 402: new 59 com/claro/exception/CAException
		/*      */// 405: dup
		/*      */// 406: iconst_m1
		/*      */// 407: ldc -29
		/*      */// 409: aload 8
		/*      */// 411: invokespecial 222 com/claro/exception/CAException:<init>
				// (ILjava/lang/String;Ljava/lang/Exception;)V
		/*      */// 414: athrow
		/*      */// 415: astore 11
		/*      */// 417: aload 6
		/*      */// 419: ifnull +18 -> 437
		/*      */// 422: aload 6
		/*      */// 424: invokeinterface 229 1 0
		/*      */// 429: aconst_null
		/*      */// 430: astore 6
		/*      */// 432: goto +5 -> 437
		/*      */// 435: astore 12
		/*      */// 437: aload 5
		/*      */// 439: ifnull +18 -> 457
		/*      */// 442: aload 5
		/*      */// 444: invokeinterface 232 1 0
		/*      */// 449: aconst_null
		/*      */// 450: astore 5
		/*      */// 452: goto +5 -> 457
		/*      */// 455: astore 12
		/*      */// 457: aload 4
		/*      */// 459: ifnull +18 -> 477
		/*      */// 462: aload 4
		/*      */// 464: invokeinterface 233 1 0
		/*      */// 469: aconst_null
		/*      */// 470: astore 4
		/*      */// 472: goto +5 -> 477
		/*      */// 475: astore 12
		/*      */// 477: aload 11
		/*      */// 479: athrow
		/*      */// 480: aload 6
		/*      */// 482: ifnull +18 -> 500
		/*      */// 485: aload 6
		/*      */// 487: invokeinterface 229 1 0
		/*      */// 492: aconst_null
		/*      */// 493: astore 6
		/*      */// 495: goto +5 -> 500
		/*      */// 498: astore 12
		/*      */// 500: aload 5
		/*      */// 502: ifnull +18 -> 520
		/*      */// 505: aload 5
		/*      */// 507: invokeinterface 232 1 0
		/*      */// 512: aconst_null
		/*      */// 513: astore 5
		/*      */// 515: goto +5 -> 520
		/*      */// 518: astore 12
		/*      */// 520: aload 4
		/*      */// 522: ifnull +18 -> 540
		/*      */// 525: aload 4
		/*      */// 527: invokeinterface 233 1 0
		/*      */// 532: aconst_null
		/*      */// 533: astore 4
		/*      */// 535: goto +5 -> 540
		/*      */// 538: astore 12
		/*      */// 540: aload_3
		/*      */// 541: areturn
		/*      */// Line number table:
		/*      */// Java source line #48 -> byte code offset #0
		/*      */// Java source line #49 -> byte code offset #8
		/*      */// Java source line #50 -> byte code offset #11
		/*      */// Java source line #51 -> byte code offset #14
		/*      */// Java source line #53 -> byte code offset #17
		/*      */// Java source line #54 -> byte code offset #26
		/*      */// Java source line #55 -> byte code offset #34
		/*      */// Java source line #56 -> byte code offset #42
		/*      */// Java source line #57 -> byte code offset #74
		/*      */// Java source line #58 -> byte code offset #87
		/*      */// Java source line #59 -> byte code offset #95
		/*      */// Java source line #60 -> byte code offset #103
		/*      */// Java source line #62 -> byte code offset #111
		/*      */// Java source line #63 -> byte code offset #122
		/*      */// Java source line #64 -> byte code offset #136
		/*      */// Java source line #65 -> byte code offset #145
		/*      */// Java source line #66 -> byte code offset #157
		/*      */// Java source line #68 -> byte code offset #166
		/*      */// Java source line #70 -> byte code offset #169
		/*      */// Java source line #71 -> byte code offset #178
		/*      */// Java source line #72 -> byte code offset #187
		/*      */// Java source line #74 -> byte code offset #196
		/*      */// Java source line #75 -> byte code offset #210
		/*      */// Java source line #76 -> byte code offset #224
		/*      */// Java source line #77 -> byte code offset #238
		/*      */// Java source line #78 -> byte code offset #252
		/*      */// Java source line #79 -> byte code offset #266
		/*      */// Java source line #80 -> byte code offset #280
		/*      */// Java source line #81 -> byte code offset #294
		/*      */// Java source line #82 -> byte code offset #308
		/*      */// Java source line #83 -> byte code offset #322
		/*      */// Java source line #85 -> byte code offset #336
		/*      */// Java source line #86 -> byte code offset #343
		/*      */// Java source line #88 -> byte code offset #350
		/*      */// Java source line #68 -> byte code offset #357
		/*      */// Java source line #90 -> byte code offset #370
		/*      */// Java source line #91 -> byte code offset #372
		/*      */// Java source line #92 -> byte code offset #385
		/*      */// Java source line #93 -> byte code offset #387
		/*      */// Java source line #94 -> byte code offset #400
		/*      */// Java source line #95 -> byte code offset #402
		/*      */// Java source line #96 -> byte code offset #415
		/*      */// Java source line #97 -> byte code offset #417
		/*      */// Java source line #98 -> byte code offset #437
		/*      */// Java source line #99 -> byte code offset #457
		/*      */// Java source line #100 -> byte code offset #477
		/*      */// Java source line #97 -> byte code offset #480
		/*      */// Java source line #98 -> byte code offset #500
		/*      */// Java source line #99 -> byte code offset #520
		/*      */// Java source line #101 -> byte code offset #540
		/*      */// Local variable table:
		/*      */// start length slot name signature
		/*      */// 0 542 0 this AlianzasDAO
		/*      */// 0 542 1 cuenta String
		/*      */// 0 542 2 secuencia String
		/*      */// 7 534 3 canjesAlianzas ArrayList<AlianzasTO>
		/*      */// 9 525 4 connection Connection
		/*      */// 12 502 5 preparedStatement PreparedStatement
		/*      */// 15 479 6 resultSet ResultSet
		/*      */// 24 101 7 query StringBuffer
		/*      */// 176 176 8 alianzas AlianzasTO
		/*      */// 370 10 8 e SQLException
		/*      */// 385 10 8 e NumberFormatException
		/*      */// 400 10 8 e Exception
		/*      */// 185 154 9 telefonoSimpleTO com.claro.transfer.TelefonoSimpleTO
		/*      */// 194 152 10 puntosRedimidosTO PuntosRedimidosTO
		/*      */// 415 63 11 localObject Object
		/*      */// 435 1 12 localException1 Exception
		/*      */// 455 1 12 localException2 Exception
		/*      */// 475 1 12 localException3 Exception
		/*      */// 498 1 12 localException4 Exception
		/*      */// 518 1 12 localException5 Exception
		/*      */// 538 1 12 localException6 Exception
		/*      */// Exception table:
		/*      */// from to target type
		/*      */// 111 367 370 java/sql/SQLException
		/*      */// 111 367 385 java/lang/NumberFormatException
		/*      */// 111 367 400 java/lang/Exception
		/*      */// 111 415 415 finally
		/*      */// 422 432 435 java/lang/Exception
		/*      */// 442 452 455 java/lang/Exception
		/*      */// 462 472 475 java/lang/Exception
		/*      */// 485 495 498 java/lang/Exception
		/*      */// 505 515 518 java/lang/Exception
		/*      */// 525 535 538 java/lang/Exception
		/*      */}

	/*      */
	/*      */public ArrayList<AlianzasTO> consultaConfirmaCanje(
			TelefonoTO telefonoTO, Connection connection, String usuario)
	/*      */throws CAException
	/*      */{
		/*      */try
		/*      */{
			/* 108 */ArrayList<AlianzasTO> alianzas = obtieneAliazasPendientes(
					telefonoTO.getCuenta(), telefonoTO.getSecuencia(), true,
					connection);
			/* 109 */if ((alianzas != null) && (alianzas.size() > 0)) {
				/* 110 */expiraCertificados(telefonoTO.getCuenta(),
						telefonoTO.getSecuencia(), telefonoTO.getTelefono(),
						alianzas, telefonoTO.getRegion(), connection, usuario);
				/*      */}
			/* 112 */return obtieneAliazasPendientes(telefonoTO.getCuenta(),
					telefonoTO.getSecuencia(), false, connection);
			/*      */}
		/*      */catch (Exception e) {
			/* 115 */throw new CAException(-1,
					"AlianzasDAO.consultaConfirmaCanje[" + e.toString() + "]",
					e);
			/*      */}
		/*      */}

	/*      */
	/*      */
	/*      */private ArrayList<AlianzasTO> obtieneAliazasPendientes(String cuenta,
			String secuencia, boolean bVigencia, Connection connection)
	/*      */throws CAException
	/*      */{
		/* 123 */PreparedStatement statement = null;
		/* 124 */ResultSet resultSet = null;
		/*      */
		/* 126 */String sQuery =
		/* 127 */" SELECT a.Folio, a.VigenciaMax ,a.FechaOper, a.PTransf, a.ValCuponOrig FROM "
				+
				/* 128 */this.schema_database
				+ "PTO_TBLALIANZAS a, "
				+ this.schema_database
				+ "PTO_TBLLINEAS b "
				+
				/* 129 */" WHERE a.Cuenta =? and a.Secuencia = ?"
				+
				/* 130 */"\tand a.cuenta = b.cuenta and a.secuencia = b.secuencia and a.Idcuenta = 2 AND Statustrans = 4 "
				+
				/* 131 */" \tand a.Estatus = 'A'";
		/* 132 */if (bVigencia) {
			/* 133 */sQuery = sQuery + " and ? > VigenciaMax ";
			/*      */}
		/* 135 */sQuery = sQuery + " ORDER BY a.fechaoper DESC";
		/*      */try {
			/* 137 */long inicioConsulta = System.currentTimeMillis();
			/* 138 */this.logger
					.info("obtieneAliazasPendientes|InicioConsulta|"
							+ Constantes.DATEFORMTALog
									.format(new java.util.Date()) + "|"
							+ inicioConsulta);
			/*      */
			/* 140 */statement = connection.prepareStatement(sQuery);
			/* 141 */statement.setString(1, cuenta);
			/* 142 */statement.setString(2, secuencia);
			/*      */
			/* 144 */if (bVigencia) {
				statement.setDate(3,
						new java.sql.Date(System.currentTimeMillis()));
				/*      */}
			/* 146 */resultSet = statement.executeQuery();
			/*      */
			/* 148 */ArrayList<AlianzasTO> alianzas = new ArrayList();
			/*      */
			/* 150 */while (resultSet.next()) {
				/* 151 */AlianzasTO alianzasTO = new AlianzasTO();
				/* 152 */alianzasTO.setFolio(resultSet.getString(1));
				/* 153 */alianzasTO.setVigenciaMax(resultSet.getDate(2));
				/* 154 */alianzasTO.setFechaOperacion(resultSet.getDate(3));
				/* 155 */alianzasTO.setPtsTransferidos(resultSet.getInt(4));
				/* 156 */alianzasTO.setValorCuponOrig(resultSet.getInt(5));
				/* 157 */alianzas.add(alianzasTO);
				/*      */}
			/* 159 */this.logger.info("obtieneAliazasPendientes|FinConsulta|"
					+ Constantes.DATEFORMTALog.format(new java.util.Date())
					+ "|" + (System.currentTimeMillis() - inicioConsulta));
			/* 160 */return alianzas;
			/*      */} catch (SQLException e) {
			/* 162 */this.error.info("SQLException.obtieneAliazasPendientes:",
					e);
			/* 163 */throw new CAException(-1,
					"SQLException.obtieneAliazasPendientes", e);
			/*      */} catch (Exception e) {
			/* 165 */this.error.info("Exception.obtieneAliazasPendientes:", e);
			/* 166 */throw new CAException(-1,
					"AlianzasDAO.obtieneAliazasPendientes", e);
			/*      */} finally {
			/* 168 */if (resultSet != null)
				try {
					resultSet.close();
					resultSet = null;
				} catch (Exception localException3) {
				}
			/* 169 */if (statement != null)
				try {
					statement.close();
					statement = null;
					/*      */}
				/*      */catch (Exception localException4) {
				}
			/*      */}
		/*      */}

	/*      */
	/*      *//* Error */
	/*      */private void expiraCertificados(String cuenta, String secuencia,
			String telefono, ArrayList<AlianzasTO> alianzas, int region,
			Connection connection, String usuario)
	/*      */throws CAException
	/*      */{
		/*      */// Byte code:
		/*      */// 0: aconst_null
		/*      */// 1: astore 8
		/*      */// 3: aconst_null
		/*      */// 4: astore 9
		/*      */// 6: aconst_null
		/*      */// 7: astore 10
		/*      */// 9: new 293 java/lang/StringBuilder
		/*      */// 12: dup
		/*      */// 13: ldc_w 409
		/*      */// 16: invokespecial 297 java/lang/StringBuilder:<init>
				// (Ljava/lang/String;)V
		/*      */// 19: aload_0
		/*      */// 20: getfield 41 com/claro/dao/AlianzasDAO:schema_database
				// Ljava/lang/String;
		/*      */// 23: invokevirtual 300 java/lang/StringBuilder:append
				// (Ljava/lang/String;)Ljava/lang/StringBuilder;
		/*      */// 26: ldc_w 411
		/*      */// 29: invokevirtual 300 java/lang/StringBuilder:append
				// (Ljava/lang/String;)Ljava/lang/StringBuilder;
		/*      */// 32: ldc_w 413
		/*      */// 35: invokevirtual 300 java/lang/StringBuilder:append
				// (Ljava/lang/String;)Ljava/lang/StringBuilder;
		/*      */// 38: invokevirtual 305 java/lang/StringBuilder:toString
				// ()Ljava/lang/String;
		/*      */// 41: astore 11
		/*      */// 43: new 293 java/lang/StringBuilder
		/*      */// 46: dup
		/*      */// 47: ldc_w 415
		/*      */// 50: invokespecial 297 java/lang/StringBuilder:<init>
				// (Ljava/lang/String;)V
		/*      */// 53: aload_0
		/*      */// 54: getfield 41 com/claro/dao/AlianzasDAO:schema_database
				// Ljava/lang/String;
		/*      */// 57: invokevirtual 300 java/lang/StringBuilder:append
				// (Ljava/lang/String;)Ljava/lang/StringBuilder;
		/*      */// 60: ldc_w 417
		/*      */// 63: invokevirtual 300 java/lang/StringBuilder:append
				// (Ljava/lang/String;)Ljava/lang/StringBuilder;
		/*      */// 66: ldc_w 419
		/*      */// 69: invokevirtual 300 java/lang/StringBuilder:append
				// (Ljava/lang/String;)Ljava/lang/StringBuilder;
		/*      */// 72: ldc_w 421
		/*      */// 75: invokevirtual 300 java/lang/StringBuilder:append
				// (Ljava/lang/String;)Ljava/lang/StringBuilder;
		/*      */// 78: invokevirtual 305 java/lang/StringBuilder:toString
				// ()Ljava/lang/String;
		/*      */// 81: astore 12
		/*      */// 83: new 293 java/lang/StringBuilder
		/*      */// 86: dup
		/*      */// 87: ldc_w 415
		/*      */// 90: invokespecial 297 java/lang/StringBuilder:<init>
				// (Ljava/lang/String;)V
		/*      */// 93: aload_0
		/*      */// 94: getfield 41 com/claro/dao/AlianzasDAO:schema_database
				// Ljava/lang/String;
		/*      */// 97: invokevirtual 300 java/lang/StringBuilder:append
				// (Ljava/lang/String;)Ljava/lang/StringBuilder;
		/*      */// 100: ldc_w 423
		/*      */// 103: invokevirtual 300 java/lang/StringBuilder:append
				// (Ljava/lang/String;)Ljava/lang/StringBuilder;
		/*      */// 106: ldc_w 425
		/*      */// 109: invokevirtual 300 java/lang/StringBuilder:append
				// (Ljava/lang/String;)Ljava/lang/StringBuilder;
		/*      */// 112: invokevirtual 305 java/lang/StringBuilder:toString
				// ()Ljava/lang/String;
		/*      */// 115: astore 13
		/*      */// 117: invokestatic 330 java/lang/System:currentTimeMillis ()J
		/*      */// 120: lstore 14
		/*      */// 122: aload_0
		/*      */// 123: getfield 23 com/claro/dao/AlianzasDAO:logger
				// Lorg/apache/log4j/Logger;
		/*      */// 126: new 293 java/lang/StringBuilder
		/*      */// 129: dup
		/*      */// 130: ldc_w 427
		/*      */// 133: invokespecial 297 java/lang/StringBuilder:<init>
				// (Ljava/lang/String;)V
		/*      */// 136: getstatic 338 com/claro/util/Constantes:DATEFORMTALog
				// Ljava/text/SimpleDateFormat;
		/*      */// 139: new 344 java/util/Date
		/*      */// 142: dup
		/*      */// 143: invokespecial 346 java/util/Date:<init> ()V
		/*      */// 146: invokevirtual 347 java/text/SimpleDateFormat:format
				// (Ljava/util/Date;)Ljava/lang/String;
		/*      */// 149: invokevirtual 300 java/lang/StringBuilder:append
				// (Ljava/lang/String;)Ljava/lang/StringBuilder;
		/*      */// 152: ldc_w 353
		/*      */// 155: invokevirtual 300 java/lang/StringBuilder:append
				// (Ljava/lang/String;)Ljava/lang/StringBuilder;
		/*      */// 158: lload 14
		/*      */// 160: invokevirtual 355 java/lang/StringBuilder:append
				// (J)Ljava/lang/StringBuilder;
		/*      */// 163: invokevirtual 305 java/lang/StringBuilder:toString
				// ()Ljava/lang/String;
		/*      */// 166: invokevirtual 358 org/apache/log4j/Logger:info
				// (Ljava/lang/Object;)V
		/*      */// 169: aload 6
		/*      */// 171: iconst_0
		/*      */// 172: invokeinterface 429 2 0
		/*      */// 177: aload 6
		/*      */// 179: aload 11
		/*      */// 181: invokeinterface 104 2 0
		/*      */// 186: astore 8
		/*      */// 188: aload 6
		/*      */// 190: aload 12
		/*      */// 192: invokeinterface 104 2 0
		/*      */// 197: astore 9
		/*      */// 199: aload 6
		/*      */// 201: aload 13
		/*      */// 203: invokeinterface 104 2 0
		/*      */// 208: astore 10
		/*      */// 210: aload 4
		/*      */// 212: invokevirtual 433 java/util/ArrayList:listIterator
				// ()Ljava/util/ListIterator;
		/*      */// 215: astore 16
		/*      */// 217: goto +300 -> 517
		/*      */// 220: new 437 java/sql/Timestamp
		/*      */// 223: dup
		/*      */// 224: invokestatic 330 java/lang/System:currentTimeMillis ()J
		/*      */// 227: invokespecial 439 java/sql/Timestamp:<init> (J)V
		/*      */// 230: astore 17
		/*      */// 232: aload 16
		/*      */// 234: invokeinterface 440 1 0
		/*      */// 239: checkcast 130 com/claro/transfer/AlianzasTO
		/*      */// 242: astore 18
		/*      */// 244: new 293 java/lang/StringBuilder
		/*      */// 247: dup
		/*      */// 248: ldc_w 445
		/*      */// 251: invokespecial 297 java/lang/StringBuilder:<init>
				// (Ljava/lang/String;)V
		/*      */// 254: aload 18
		/*      */// 256: invokevirtual 447 com/claro/transfer/AlianzasTO:getFolio
				// ()Ljava/lang/String;
		/*      */// 259: invokevirtual 300 java/lang/StringBuilder:append
				// (Ljava/lang/String;)Ljava/lang/StringBuilder;
		/*      */// 262: ldc_w 450
		/*      */// 265: invokevirtual 300 java/lang/StringBuilder:append
				// (Ljava/lang/String;)Ljava/lang/StringBuilder;
		/*      */// 268: aload 18
		/*      */// 270: invokevirtual 452
				// com/claro/transfer/AlianzasTO:getVigenciaMax
				// ()Ljava/sql/Date;
		/*      */// 273: invokevirtual 456 java/lang/StringBuilder:append
				// (Ljava/lang/Object;)Ljava/lang/StringBuilder;
		/*      */// 276: invokevirtual 305 java/lang/StringBuilder:toString
				// ()Ljava/lang/String;
		/*      */// 279: astore 19
		/*      */// 281: new 293 java/lang/StringBuilder
		/*      */// 284: dup
		/*      */// 285: ldc_w 459
		/*      */// 288: invokespecial 297 java/lang/StringBuilder:<init>
				// (Ljava/lang/String;)V
		/*      */// 291: aload 18
		/*      */// 293: invokevirtual 447 com/claro/transfer/AlianzasTO:getFolio
				// ()Ljava/lang/String;
		/*      */// 296: invokevirtual 300 java/lang/StringBuilder:append
				// (Ljava/lang/String;)Ljava/lang/StringBuilder;
		/*      */// 299: ldc_w 461
		/*      */// 302: invokevirtual 300 java/lang/StringBuilder:append
				// (Ljava/lang/String;)Ljava/lang/StringBuilder;
		/*      */// 305: aload 18
		/*      */// 307: invokevirtual 452
				// com/claro/transfer/AlianzasTO:getVigenciaMax
				// ()Ljava/sql/Date;
		/*      */// 310: invokevirtual 456 java/lang/StringBuilder:append
				// (Ljava/lang/Object;)Ljava/lang/StringBuilder;
		/*      */// 313: invokevirtual 305 java/lang/StringBuilder:toString
				// ()Ljava/lang/String;
		/*      */// 316: astore 20
		/*      */// 318: aload 8
		/*      */// 320: invokeinterface 463 1 0
		/*      */// 325: aload 8
		/*      */// 327: iconst_1
		/*      */// 328: aload 18
		/*      */// 330: invokevirtual 447 com/claro/transfer/AlianzasTO:getFolio
				// ()Ljava/lang/String;
		/*      */// 333: invokeinterface 110 3 0
		/*      */// 338: aload 8
		/*      */// 340: invokeinterface 466 1 0
		/*      */// 345: pop
		/*      */// 346: aload 9
		/*      */// 348: invokeinterface 463 1 0
		/*      */// 353: aload 9
		/*      */// 355: iconst_1
		/*      */// 356: aload_1
		/*      */// 357: invokeinterface 110 3 0
		/*      */// 362: aload 9
		/*      */// 364: iconst_2
		/*      */// 365: aload_2
		/*      */// 366: invokestatic 116 java/lang/Integer:parseInt
				// (Ljava/lang/String;)I
		/*      */// 369: invokeinterface 122 3 0
		/*      */// 374: aload 9
		/*      */// 376: iconst_3
		/*      */// 377: aload_3
		/*      */// 378: invokeinterface 110 3 0
		/*      */// 383: aload 9
		/*      */// 385: iconst_4
		/*      */// 386: new 362 java/sql/Date
		/*      */// 389: dup
		/*      */// 390: aload 17
		/*      */// 392: invokevirtual 469 java/sql/Timestamp:getTime ()J
		/*      */// 395: invokespecial 364 java/sql/Date:<init> (J)V
		/*      */// 398: invokeinterface 367 3 0
		/*      */// 403: aload 9
		/*      */// 405: iconst_5
		/*      */// 406: new 362 java/sql/Date
		/*      */// 409: dup
		/*      */// 410: aload 17
		/*      */// 412: invokevirtual 469 java/sql/Timestamp:getTime ()J
		/*      */// 415: invokespecial 364 java/sql/Date:<init> (J)V
		/*      */// 418: invokeinterface 367 3 0
		/*      */// 423: aload 9
		/*      */// 425: bipush 6
		/*      */// 427: aload 7
		/*      */// 429: invokeinterface 110 3 0
		/*      */// 434: aload 9
		/*      */// 436: bipush 7
		/*      */// 438: aload 19
		/*      */// 440: invokeinterface 110 3 0
		/*      */// 445: aload 9
		/*      */// 447: invokeinterface 466 1 0
		/*      */// 452: pop
		/*      */// 453: aload 10
		/*      */// 455: invokeinterface 463 1 0
		/*      */// 460: aload 10
		/*      */// 462: iconst_1
		/*      */// 463: iload 5
		/*      */// 465: invokeinterface 122 3 0
		/*      */// 470: aload 10
		/*      */// 472: iconst_2
		/*      */// 473: aload 17
		/*      */// 475: invokeinterface 472 3 0
		/*      */// 480: aload 10
		/*      */// 482: iconst_3
		/*      */// 483: aload_1
		/*      */// 484: invokeinterface 110 3 0
		/*      */// 489: aload 10
		/*      */// 491: iconst_4
		/*      */// 492: aload 7
		/*      */// 494: invokeinterface 110 3 0
		/*      */// 499: aload 10
		/*      */// 501: iconst_5
		/*      */// 502: aload 20
		/*      */// 504: invokeinterface 110 3 0
		/*      */// 509: aload 10
		/*      */// 511: invokeinterface 466 1 0
		/*      */// 516: pop
		/*      */// 517: aload 16
		/*      */// 519: invokeinterface 476 1 0
		/*      */// 524: ifne -304 -> 220
		/*      */// 527: aload 6
		/*      */// 529: invokeinterface 479 1 0
		/*      */// 534: aload_0
		/*      */// 535: getfield 23 com/claro/dao/AlianzasDAO:logger
				// Lorg/apache/log4j/Logger;
		/*      */// 538: new 293 java/lang/StringBuilder
		/*      */// 541: dup
		/*      */// 542: ldc_w 482
		/*      */// 545: invokespecial 297 java/lang/StringBuilder:<init>
				// (Ljava/lang/String;)V
		/*      */// 548: getstatic 338 com/claro/util/Constantes:DATEFORMTALog
				// Ljava/text/SimpleDateFormat;
		/*      */// 551: new 344 java/util/Date
		/*      */// 554: dup
		/*      */// 555: invokespecial 346 java/util/Date:<init> ()V
		/*      */// 558: invokevirtual 347 java/text/SimpleDateFormat:format
				// (Ljava/util/Date;)Ljava/lang/String;
		/*      */// 561: invokevirtual 300 java/lang/StringBuilder:append
				// (Ljava/lang/String;)Ljava/lang/StringBuilder;
		/*      */// 564: ldc_w 353
		/*      */// 567: invokevirtual 300 java/lang/StringBuilder:append
				// (Ljava/lang/String;)Ljava/lang/StringBuilder;
		/*      */// 570: invokestatic 330 java/lang/System:currentTimeMillis ()J
		/*      */// 573: lload 14
		/*      */// 575: lsub
		/*      */// 576: invokevirtual 355 java/lang/StringBuilder:append
				// (J)Ljava/lang/StringBuilder;
		/*      */// 579: invokevirtual 305 java/lang/StringBuilder:toString
				// ()Ljava/lang/String;
		/*      */// 582: invokevirtual 358 org/apache/log4j/Logger:info
				// (Ljava/lang/Object;)V
		/*      */// 585: goto +207 -> 792
		/*      */// 588: astore 11
		/*      */// 590: aload_0
		/*      */// 591: getfield 27 com/claro/dao/AlianzasDAO:error
				// Lorg/apache/log4j/Logger;
		/*      */// 594: ldc_w 484
		/*      */// 597: aload 11
		/*      */// 599: invokevirtual 393 org/apache/log4j/Logger:info
				// (Ljava/lang/Object;Ljava/lang/Throwable;)V
		/*      */// 602: aload 6
		/*      */// 604: ifnull +15 -> 619
		/*      */// 607: aload 6
		/*      */// 609: invokeinterface 486 1 0
		/*      */// 614: goto +5 -> 619
		/*      */// 617: astore 12
		/*      */// 619: new 59 com/claro/exception/CAException
		/*      */// 622: dup
		/*      */// 623: iconst_m1
		/*      */// 624: new 293 java/lang/StringBuilder
		/*      */// 627: dup
		/*      */// 628: ldc_w 489
		/*      */// 631: invokespecial 297 java/lang/StringBuilder:<init>
				// (Ljava/lang/String;)V
		/*      */// 634: aload 11
		/*      */// 636: invokevirtual 491 java/sql/SQLException:toString
				// ()Ljava/lang/String;
		/*      */// 639: invokevirtual 300 java/lang/StringBuilder:append
				// (Ljava/lang/String;)Ljava/lang/StringBuilder;
		/*      */// 642: ldc_w 303
		/*      */// 645: invokevirtual 300 java/lang/StringBuilder:append
				// (Ljava/lang/String;)Ljava/lang/StringBuilder;
		/*      */// 648: invokevirtual 305 java/lang/StringBuilder:toString
				// ()Ljava/lang/String;
		/*      */// 651: aload 11
		/*      */// 653: invokespecial 222 com/claro/exception/CAException:<init>
				// (ILjava/lang/String;Ljava/lang/Exception;)V
		/*      */// 656: athrow
		/*      */// 657: astore 11
		/*      */// 659: aload_0
		/*      */// 660: getfield 27 com/claro/dao/AlianzasDAO:error
				// Lorg/apache/log4j/Logger;
		/*      */// 663: ldc_w 484
		/*      */// 666: aload 11
		/*      */// 668: invokevirtual 393 org/apache/log4j/Logger:info
				// (Ljava/lang/Object;Ljava/lang/Throwable;)V
		/*      */// 671: new 59 com/claro/exception/CAException
		/*      */// 674: dup
		/*      */// 675: iconst_m1
		/*      */// 676: new 293 java/lang/StringBuilder
		/*      */// 679: dup
		/*      */// 680: ldc_w 492
		/*      */// 683: invokespecial 297 java/lang/StringBuilder:<init>
				// (Ljava/lang/String;)V
		/*      */// 686: aload 11
		/*      */// 688: invokevirtual 299 java/lang/Exception:toString
				// ()Ljava/lang/String;
		/*      */// 691: invokevirtual 300 java/lang/StringBuilder:append
				// (Ljava/lang/String;)Ljava/lang/StringBuilder;
		/*      */// 694: ldc_w 303
		/*      */// 697: invokevirtual 300 java/lang/StringBuilder:append
				// (Ljava/lang/String;)Ljava/lang/StringBuilder;
		/*      */// 700: invokevirtual 305 java/lang/StringBuilder:toString
				// ()Ljava/lang/String;
		/*      */// 703: aload 11
		/*      */// 705: invokespecial 222 com/claro/exception/CAException:<init>
				// (ILjava/lang/String;Ljava/lang/Exception;)V
		/*      */// 708: athrow
		/*      */// 709: astore 21
		/*      */// 711: aload 8
		/*      */// 713: ifnull +18 -> 731
		/*      */// 716: aload 8
		/*      */// 718: invokeinterface 232 1 0
		/*      */// 723: aconst_null
		/*      */// 724: astore 8
		/*      */// 726: goto +5 -> 731
		/*      */// 729: astore 22
		/*      */// 731: aload 9
		/*      */// 733: ifnull +18 -> 751
		/*      */// 736: aload 9
		/*      */// 738: invokeinterface 232 1 0
		/*      */// 743: aconst_null
		/*      */// 744: astore 9
		/*      */// 746: goto +5 -> 751
		/*      */// 749: astore 22
		/*      */// 751: aload 10
		/*      */// 753: ifnull +18 -> 771
		/*      */// 756: aload 10
		/*      */// 758: invokeinterface 232 1 0
		/*      */// 763: aconst_null
		/*      */// 764: astore 10
		/*      */// 766: goto +5 -> 771
		/*      */// 769: astore 22
		/*      */// 771: aload 6
		/*      */// 773: ifnull +16 -> 789
		/*      */// 776: aload 6
		/*      */// 778: iconst_1
		/*      */// 779: invokeinterface 429 2 0
		/*      */// 784: goto +5 -> 789
		/*      */// 787: astore 22
		/*      */// 789: aload 21
		/*      */// 791: athrow
		/*      */// 792: aload 8
		/*      */// 794: ifnull +18 -> 812
		/*      */// 797: aload 8
		/*      */// 799: invokeinterface 232 1 0
		/*      */// 804: aconst_null
		/*      */// 805: astore 8
		/*      */// 807: goto +5 -> 812
		/*      */// 810: astore 22
		/*      */// 812: aload 9
		/*      */// 814: ifnull +18 -> 832
		/*      */// 817: aload 9
		/*      */// 819: invokeinterface 232 1 0
		/*      */// 824: aconst_null
		/*      */// 825: astore 9
		/*      */// 827: goto +5 -> 832
		/*      */// 830: astore 22
		/*      */// 832: aload 10
		/*      */// 834: ifnull +18 -> 852
		/*      */// 837: aload 10
		/*      */// 839: invokeinterface 232 1 0
		/*      */// 844: aconst_null
		/*      */// 845: astore 10
		/*      */// 847: goto +5 -> 852
		/*      */// 850: astore 22
		/*      */// 852: aload 6
		/*      */// 854: ifnull +16 -> 870
		/*      */// 857: aload 6
		/*      */// 859: iconst_1
		/*      */// 860: invokeinterface 429 2 0
		/*      */// 865: goto +5 -> 870
		/*      */// 868: astore 22
		/*      */// 870: return
		/*      */// Line number table:
		/*      */// Java source line #177 -> byte code offset #0
		/*      */// Java source line #180 -> byte code offset #9
		/*      */// Java source line #181 -> byte code offset #32
		/*      */// Java source line #180 -> byte code offset #38
		/*      */// Java source line #182 -> byte code offset #43
		/*      */// Java source line #183 -> byte code offset #66
		/*      */// Java source line #184 -> byte code offset #72
		/*      */// Java source line #182 -> byte code offset #78
		/*      */// Java source line #186 -> byte code offset #83
		/*      */// Java source line #187 -> byte code offset #106
		/*      */// Java source line #186 -> byte code offset #112
		/*      */// Java source line #189 -> byte code offset #117
		/*      */// Java source line #190 -> byte code offset #122
		/*      */// Java source line #193 -> byte code offset #169
		/*      */// Java source line #194 -> byte code offset #177
		/*      */// Java source line #195 -> byte code offset #188
		/*      */// Java source line #196 -> byte code offset #199
		/*      */// Java source line #198 -> byte code offset #210
		/*      */// Java source line #199 -> byte code offset #217
		/*      */// Java source line #201 -> byte code offset #220
		/*      */// Java source line #202 -> byte code offset #232
		/*      */// Java source line #204 -> byte code offset #244
		/*      */// Java source line #205 -> byte code offset #281
		/*      */// Java source line #208 -> byte code offset #318
		/*      */// Java source line #209 -> byte code offset #325
		/*      */// Java source line #210 -> byte code offset #338
		/*      */// Java source line #213 -> byte code offset #346
		/*      */// Java source line #214 -> byte code offset #353
		/*      */// Java source line #215 -> byte code offset #362
		/*      */// Java source line #216 -> byte code offset #374
		/*      */// Java source line #217 -> byte code offset #383
		/*      */// Java source line #218 -> byte code offset #403
		/*      */// Java source line #219 -> byte code offset #423
		/*      */// Java source line #220 -> byte code offset #434
		/*      */// Java source line #221 -> byte code offset #445
		/*      */// Java source line #223 -> byte code offset #453
		/*      */// Java source line #224 -> byte code offset #460
		/*      */// Java source line #225 -> byte code offset #470
		/*      */// Java source line #226 -> byte code offset #480
		/*      */// Java source line #227 -> byte code offset #489
		/*      */// Java source line #228 -> byte code offset #499
		/*      */// Java source line #229 -> byte code offset #509
		/*      */// Java source line #199 -> byte code offset #517
		/*      */// Java source line #233 -> byte code offset #527
		/*      */// Java source line #234 -> byte code offset #534
		/*      */// Java source line #236 -> byte code offset #588
		/*      */// Java source line #237 -> byte code offset #590
		/*      */// Java source line #238 -> byte code offset #602
		/*      */// Java source line #239 -> byte code offset #619
		/*      */// Java source line #240 -> byte code offset #657
		/*      */// Java source line #241 -> byte code offset #659
		/*      */// Java source line #242 -> byte code offset #671
		/*      */// Java source line #243 -> byte code offset #709
		/*      */// Java source line #244 -> byte code offset #711
		/*      */// Java source line #245 -> byte code offset #731
		/*      */// Java source line #246 -> byte code offset #751
		/*      */// Java source line #247 -> byte code offset #771
		/*      */// Java source line #248 -> byte code offset #789
		/*      */// Java source line #244 -> byte code offset #792
		/*      */// Java source line #245 -> byte code offset #812
		/*      */// Java source line #246 -> byte code offset #832
		/*      */// Java source line #247 -> byte code offset #852
		/*      */// Java source line #249 -> byte code offset #870
		/*      */// Local variable table:
		/*      */// start length slot name signature
		/*      */// 0 871 0 this AlianzasDAO
		/*      */// 0 871 1 cuenta String
		/*      */// 0 871 2 secuencia String
		/*      */// 0 871 3 telefono String
		/*      */// 0 871 4 alianzas ArrayList<AlianzasTO>
		/*      */// 0 871 5 region int
		/*      */// 0 871 6 connection Connection
		/*      */// 0 871 7 usuario String
		/*      */// 1 805 8 updateAlianza PreparedStatement
		/*      */// 4 822 9 insertDetalle PreparedStatement
		/*      */// 7 839 10 insertComentario PreparedStatement
		/*      */// 41 139 11 queryUpdateAlianza String
		/*      */// 588 64 11 e SQLException
		/*      */// 657 47 11 e Exception
		/*      */// 81 110 12 queryInsertDetalle String
		/*      */// 617 1 12 localException1 Exception
		/*      */// 115 87 13 queryInsertComentario String
		/*      */// 120 454 14 inicioConsulta long
		/*      */// 215 303 16 iterator java.util.ListIterator<AlianzasTO>
		/*      */// 230 244 17 fechaTransaccion java.sql.Timestamp
		/*      */// 242 87 18 alianza AlianzasTO
		/*      */// 279 160 19 comentarioInsertaDetalle String
		/*      */// 316 187 20 comentarioInsertComentario String
		/*      */// 709 81 21 localObject Object
		/*      */// 729 1 22 localException2 Exception
		/*      */// 749 1 22 localException3 Exception
		/*      */// 769 1 22 localException4 Exception
		/*      */// 787 1 22 localException5 Exception
		/*      */// 810 1 22 localException6 Exception
		/*      */// 830 1 22 localException7 Exception
		/*      */// 850 1 22 localException8 Exception
		/*      */// 868 1 22 localException9 Exception
		/*      */// Exception table:
		/*      */// from to target type
		/*      */// 9 585 588 java/sql/SQLException
		/*      */// 607 614 617 java/lang/Exception
		/*      */// 9 585 657 java/lang/Exception
		/*      */// 9 709 709 finally
		/*      */// 716 726 729 java/lang/Exception
		/*      */// 736 746 749 java/lang/Exception
		/*      */// 756 766 769 java/lang/Exception
		/*      */// 776 784 787 java/lang/Exception
		/*      */// 797 807 810 java/lang/Exception
		/*      */// 817 827 830 java/lang/Exception
		/*      */// 837 847 850 java/lang/Exception
		/*      */// 857 865 868 java/lang/Exception
		/*      */}

	/*      */
	/*      */public FactorTO consultaFactor(int idAlianza, int nPtsDisp)
	/*      */throws CAException
	/*      */{
		/* 253 */PreparedStatement statement = null;
		/* 254 */ResultSet resultSet = null;
		/* 255 */Connection connection = null;
		/*      */
		/*      */
		/* 258 */String sQuery = " SELECT idcuenta,Factor,fechaActiva,Status,Millasmin FROM "
				+ this.schema_database
				+ "PTO_TBLFACTORALIANZA "
				+
				/* 259 */" WHERE Idcuenta=? AND Status='A' ORDER BY FechaActiva desc";
		/*      */try
		/*      */{
			/* 262 */connection = ServiceLocator.getInstance().getConnection(
					ServiceLocator.jdbcCirculoAzul);
			/* 263 */statement = connection.prepareStatement(sQuery);
			/* 264 */statement.setInt(1, idAlianza);
			/* 265 */resultSet = statement.executeQuery();
			/*      */
			/* 267 */if (resultSet.next()) {
				/* 268 */FactorTO factorTO = new FactorTO();
				/* 269 */factorTO.setIdcuenta(resultSet.getInt(1));
				/* 270 */factorTO.setFactor(resultSet.getInt(2));
				/* 271 */factorTO.setFechaActiva(resultSet.getDate(3));
				/* 272 */factorTO.setEstatus(resultSet.getString(4));
				/* 273 */factorTO.setMillanMin(resultSet.getInt(5));
				/* 274 */return factorTO;
			}
			/* 275 */throw new CAException(-1,
					"No se encontro el factor de la Alianza");
			/*      */}
		/*      */catch (SQLException e) {
			/* 278 */throw new CAException(-1, "SQLException.consultaFactor["
					+ e.toString() + "]", e);
			/*      */} catch (Exception e) {
			/* 280 */throw new CAException(-1, "AlianzasDAO.consultaFactor["
					+ e.toString() + "]", e);
			/*      */} finally {
			/* 282 */if (statement != null)
				try {
					statement.close();
					statement = null;
				} catch (Exception localException4) {
				}
			/* 283 */if (resultSet != null)
				try {
					resultSet.close();
					resultSet = null;
				} catch (Exception localException5) {
				}
			/* 284 */if (connection != null)
				try {
					connection.close();
					connection = null;
					/*      */}
				/*      */catch (Exception localException6) {
				}
			/*      */}
		/*      */}

	/*      */
	/*      *//* Error */
	/*      */public ArrayList<AlianzasTO> consultaCuponesAmex(String sCuenta,
			int iSecuncia)
	/*      */throws CAException
	/*      */{
		return null;
		/*      */// Byte code:
		/*      */// 0: aconst_null
		/*      */// 1: astore_3
		/*      */// 2: aconst_null
		/*      */// 3: astore 4
		/*      */// 5: aconst_null
		/*      */// 6: astore 5
		/*      */// 8: new 66 java/lang/StringBuffer
		/*      */// 11: dup
		/*      */// 12: invokespecial 68 java/lang/StringBuffer:<init> ()V
		/*      */// 15: astore 6
		/*      */// 17: aload 6
		/*      */// 19: ldc_w 553
		/*      */// 22: invokevirtual 71 java/lang/StringBuffer:append
				// (Ljava/lang/String;)Ljava/lang/StringBuffer;
		/*      */// 25: pop
		/*      */// 26: aload 6
		/*      */// 28: ldc_w 555
		/*      */// 31: invokevirtual 71 java/lang/StringBuffer:append
				// (Ljava/lang/String;)Ljava/lang/StringBuffer;
		/*      */// 34: aload_0
		/*      */// 35: getfield 41 com/claro/dao/AlianzasDAO:schema_database
				// Ljava/lang/String;
		/*      */// 38: invokevirtual 71 java/lang/StringBuffer:append
				// (Ljava/lang/String;)Ljava/lang/StringBuffer;
		/*      */// 41: ldc_w 557
		/*      */// 44: invokevirtual 71 java/lang/StringBuffer:append
				// (Ljava/lang/String;)Ljava/lang/StringBuffer;
		/*      */// 47: pop
		/*      */// 48: aload 6
		/*      */// 50: ldc_w 559
		/*      */// 53: invokevirtual 71 java/lang/StringBuffer:append
				// (Ljava/lang/String;)Ljava/lang/StringBuffer;
		/*      */// 56: pop
		/*      */// 57: aload 6
		/*      */// 59: ldc_w 561
		/*      */// 62: invokevirtual 71 java/lang/StringBuffer:append
				// (Ljava/lang/String;)Ljava/lang/StringBuffer;
		/*      */// 65: pop
		/*      */// 66: new 63 java/util/ArrayList
		/*      */// 69: dup
		/*      */// 70: invokespecial 65 java/util/ArrayList:<init> ()V
		/*      */// 73: astore 7
		/*      */// 75: invokestatic 29 com/claro/util/ServiceLocator:getInstance
				// ()Lcom/claro/util/ServiceLocator;
		/*      */// 78: getstatic 93 com/claro/util/ServiceLocator:jdbcCirculoAzul
				// Ljava/lang/String;
		/*      */// 81: invokevirtual 96 com/claro/util/ServiceLocator:getConnection
				// (Ljava/lang/String;)Ljava/sql/Connection;
		/*      */// 84: astore_3
		/*      */// 85: aload_3
		/*      */// 86: aload 6
		/*      */// 88: invokevirtual 100 java/lang/StringBuffer:toString
				// ()Ljava/lang/String;
		/*      */// 91: invokeinterface 104 2 0
		/*      */// 96: astore 4
		/*      */// 98: aload 4
		/*      */// 100: iconst_1
		/*      */// 101: aload_1
		/*      */// 102: invokeinterface 110 3 0
		/*      */// 107: aload 4
		/*      */// 109: iconst_2
		/*      */// 110: iload_2
		/*      */// 111: invokeinterface 122 3 0
		/*      */// 116: aload 4
		/*      */// 118: invokeinterface 126 1 0
		/*      */// 123: astore 5
		/*      */// 125: goto +122 -> 247
		/*      */// 128: new 130 com/claro/transfer/AlianzasTO
		/*      */// 131: dup
		/*      */// 132: invokespecial 132 com/claro/transfer/AlianzasTO:<init> ()V
		/*      */// 135: astore 8
		/*      */// 137: aload 8
		/*      */// 139: aload 5
		/*      */// 141: ldc_w 563
		/*      */// 144: invokeinterface 141 2 0
		/*      */// 149: invokevirtual 374 com/claro/transfer/AlianzasTO:setFolio
				// (Ljava/lang/String;)V
		/*      */// 152: aload 8
		/*      */// 154: aload 5
		/*      */// 156: ldc_w 565
		/*      */// 159: invokeinterface 172 2 0
		/*      */// 164: invokevirtual 567
				// com/claro/transfer/AlianzasTO:setSecuencia (I)V
		/*      */// 167: aload 8
		/*      */// 169: aload 5
		/*      */// 171: ldc -57
		/*      */// 173: invokeinterface 172 2 0
		/*      */// 178: invokevirtual 201
				// com/claro/transfer/AlianzasTO:setValorCuponOrig (I)V
		/*      */// 181: aload 8
		/*      */// 183: aload 5
		/*      */// 185: ldc -86
		/*      */// 187: invokeinterface 172 2 0
		/*      */// 192: invokevirtual 386
				// com/claro/transfer/AlianzasTO:setPtsTransferidos (I)V
		/*      */// 195: aload 8
		/*      */// 197: aload 5
		/*      */// 199: ldc_w 570
		/*      */// 202: invokeinterface 157 2 0
		/*      */// 207: invokevirtual 380
				// com/claro/transfer/AlianzasTO:setVigenciaMax
				// (Ljava/sql/Date;)V
		/*      */// 210: aload 8
		/*      */// 212: aload 5
		/*      */// 214: ldc_w 572
		/*      */// 217: invokeinterface 172 2 0
		/*      */// 222: invokevirtual 574
				// com/claro/transfer/AlianzasTO:setStatusTrans (I)V
		/*      */// 225: aload 8
		/*      */// 227: aload 5
		/*      */// 229: ldc -101
		/*      */// 231: invokeinterface 157 2 0
		/*      */// 236: invokevirtual 161
				// com/claro/transfer/AlianzasTO:setFechaOperacion
				// (Ljava/sql/Date;)V
		/*      */// 239: aload 7
		/*      */// 241: aload 8
		/*      */// 243: invokevirtual 212 java/util/ArrayList:add
				// (Ljava/lang/Object;)Z
		/*      */// 246: pop
		/*      */// 247: aload 5
		/*      */// 249: invokeinterface 216 1 0
		/*      */// 254: ifne -126 -> 128
		/*      */// 257: goto +145 -> 402
		/*      */// 260: astore 8
		/*      */// 262: new 59 com/claro/exception/CAException
		/*      */// 265: dup
		/*      */// 266: iconst_m1
		/*      */// 267: new 293 java/lang/StringBuilder
		/*      */// 270: dup
		/*      */// 271: ldc_w 577
		/*      */// 274: invokespecial 297 java/lang/StringBuilder:<init>
				// (Ljava/lang/String;)V
		/*      */// 277: aload 8
		/*      */// 279: invokevirtual 491 java/sql/SQLException:toString
				// ()Ljava/lang/String;
		/*      */// 282: invokevirtual 300 java/lang/StringBuilder:append
				// (Ljava/lang/String;)Ljava/lang/StringBuilder;
		/*      */// 285: ldc_w 303
		/*      */// 288: invokevirtual 300 java/lang/StringBuilder:append
				// (Ljava/lang/String;)Ljava/lang/StringBuilder;
		/*      */// 291: invokevirtual 305 java/lang/StringBuilder:toString
				// ()Ljava/lang/String;
		/*      */// 294: aload 8
		/*      */// 296: invokespecial 222 com/claro/exception/CAException:<init>
				// (ILjava/lang/String;Ljava/lang/Exception;)V
		/*      */// 299: athrow
		/*      */// 300: astore 8
		/*      */// 302: new 59 com/claro/exception/CAException
		/*      */// 305: dup
		/*      */// 306: iconst_m1
		/*      */// 307: new 293 java/lang/StringBuilder
		/*      */// 310: dup
		/*      */// 311: ldc_w 579
		/*      */// 314: invokespecial 297 java/lang/StringBuilder:<init>
				// (Ljava/lang/String;)V
		/*      */// 317: aload 8
		/*      */// 319: invokevirtual 299 java/lang/Exception:toString
				// ()Ljava/lang/String;
		/*      */// 322: invokevirtual 300 java/lang/StringBuilder:append
				// (Ljava/lang/String;)Ljava/lang/StringBuilder;
		/*      */// 325: ldc_w 303
		/*      */// 328: invokevirtual 300 java/lang/StringBuilder:append
				// (Ljava/lang/String;)Ljava/lang/StringBuilder;
		/*      */// 331: invokevirtual 305 java/lang/StringBuilder:toString
				// ()Ljava/lang/String;
		/*      */// 334: aload 8
		/*      */// 336: invokespecial 222 com/claro/exception/CAException:<init>
				// (ILjava/lang/String;Ljava/lang/Exception;)V
		/*      */// 339: athrow
		/*      */// 340: astore 9
		/*      */// 342: aload 5
		/*      */// 344: ifnull +18 -> 362
		/*      */// 347: aload 5
		/*      */// 349: invokeinterface 229 1 0
		/*      */// 354: aconst_null
		/*      */// 355: astore 5
		/*      */// 357: goto +5 -> 362
		/*      */// 360: astore 10
		/*      */// 362: aload 4
		/*      */// 364: ifnull +18 -> 382
		/*      */// 367: aload 4
		/*      */// 369: invokeinterface 232 1 0
		/*      */// 374: aconst_null
		/*      */// 375: astore 4
		/*      */// 377: goto +5 -> 382
		/*      */// 380: astore 10
		/*      */// 382: aload_3
		/*      */// 383: ifnull +16 -> 399
		/*      */// 386: aload_3
		/*      */// 387: invokeinterface 233 1 0
		/*      */// 392: aconst_null
		/*      */// 393: astore_3
		/*      */// 394: goto +5 -> 399
		/*      */// 397: astore 10
		/*      */// 399: aload 9
		/*      */// 401: athrow
		/*      */// 402: aload 5
		/*      */// 404: ifnull +18 -> 422
		/*      */// 407: aload 5
		/*      */// 409: invokeinterface 229 1 0
		/*      */// 414: aconst_null
		/*      */// 415: astore 5
		/*      */// 417: goto +5 -> 422
		/*      */// 420: astore 10
		/*      */// 422: aload 4
		/*      */// 424: ifnull +18 -> 442
		/*      */// 427: aload 4
		/*      */// 429: invokeinterface 232 1 0
		/*      */// 434: aconst_null
		/*      */// 435: astore 4
		/*      */// 437: goto +5 -> 442
		/*      */// 440: astore 10
		/*      */// 442: aload_3
		/*      */// 443: ifnull +16 -> 459
		/*      */// 446: aload_3
		/*      */// 447: invokeinterface 233 1 0
		/*      */// 452: aconst_null
		/*      */// 453: astore_3
		/*      */// 454: goto +5 -> 459
		/*      */// 457: astore 10
		/*      */// 459: aload 7
		/*      */// 461: areturn
		/*      */// Line number table:
		/*      */// Java source line #292 -> byte code offset #0
		/*      */// Java source line #293 -> byte code offset #2
		/*      */// Java source line #294 -> byte code offset #5
		/*      */// Java source line #296 -> byte code offset #8
		/*      */// Java source line #298 -> byte code offset #17
		/*      */// Java source line #299 -> byte code offset #26
		/*      */// Java source line #300 -> byte code offset #48
		/*      */// Java source line #301 -> byte code offset #57
		/*      */// Java source line #303 -> byte code offset #66
		/*      */// Java source line #306 -> byte code offset #75
		/*      */// Java source line #307 -> byte code offset #85
		/*      */// Java source line #308 -> byte code offset #98
		/*      */// Java source line #309 -> byte code offset #107
		/*      */// Java source line #311 -> byte code offset #116
		/*      */// Java source line #313 -> byte code offset #125
		/*      */// Java source line #314 -> byte code offset #128
		/*      */// Java source line #315 -> byte code offset #137
		/*      */// Java source line #316 -> byte code offset #152
		/*      */// Java source line #317 -> byte code offset #167
		/*      */// Java source line #318 -> byte code offset #181
		/*      */// Java source line #319 -> byte code offset #195
		/*      */// Java source line #320 -> byte code offset #210
		/*      */// Java source line #321 -> byte code offset #225
		/*      */// Java source line #322 -> byte code offset #239
		/*      */// Java source line #313 -> byte code offset #247
		/*      */// Java source line #324 -> byte code offset #260
		/*      */// Java source line #325 -> byte code offset #262
		/*      */// Java source line #326 -> byte code offset #300
		/*      */// Java source line #327 -> byte code offset #302
		/*      */// Java source line #328 -> byte code offset #340
		/*      */// Java source line #329 -> byte code offset #342
		/*      */// Java source line #330 -> byte code offset #362
		/*      */// Java source line #331 -> byte code offset #382
		/*      */// Java source line #332 -> byte code offset #399
		/*      */// Java source line #329 -> byte code offset #402
		/*      */// Java source line #330 -> byte code offset #422
		/*      */// Java source line #331 -> byte code offset #442
		/*      */// Java source line #333 -> byte code offset #459
		/*      */// Local variable table:
		/*      */// start length slot name signature
		/*      */// 0 462 0 this AlianzasDAO
		/*      */// 0 462 1 sCuenta String
		/*      */// 0 462 2 iSecuncia int
		/*      */// 1 453 3 connection Connection
		/*      */// 3 433 4 statement PreparedStatement
		/*      */// 6 410 5 resultSet ResultSet
		/*      */// 15 72 6 query StringBuffer
		/*      */// 73 387 7 cuponesAmex ArrayList<AlianzasTO>
		/*      */// 135 107 8 alianzasTO AlianzasTO
		/*      */// 260 35 8 e SQLException
		/*      */// 300 35 8 e Exception
		/*      */// 340 60 9 localObject Object
		/*      */// 360 1 10 localException1 Exception
		/*      */// 380 1 10 localException2 Exception
		/*      */// 397 1 10 localException3 Exception
		/*      */// 420 1 10 localException4 Exception
		/*      */// 440 1 10 localException5 Exception
		/*      */// 457 1 10 localException6 Exception
		/*      */// Exception table:
		/*      */// from to target type
		/*      */// 75 257 260 java/sql/SQLException
		/*      */// 75 257 300 java/lang/Exception
		/*      */// 75 340 340 finally
		/*      */// 347 357 360 java/lang/Exception
		/*      */// 367 377 380 java/lang/Exception
		/*      */// 386 394 397 java/lang/Exception
		/*      */// 407 417 420 java/lang/Exception
		/*      */// 427 437 440 java/lang/Exception
		/*      */// 446 454 457 java/lang/Exception
		/*      */}

	/*      */
	/*      *//* Error */
	/*      */public MensajeTO actualizaPromoAlianza(String sCuentaAl, int iCveAl,
			String sCuenta, int iSecuencia, String sNombre, String sApePat,
			String sApeMat, String sUsrCve, String sTel)
	/*      */throws CAException
	/*      */{
		return null;
		/*      */// Byte code:
		/*      */// 0: aconst_null
		/*      */// 1: astore 10
		/*      */// 3: aconst_null
		/*      */// 4: astore 11
		/*      */// 6: invokestatic 29 com/claro/util/ServiceLocator:getInstance
				// ()Lcom/claro/util/ServiceLocator;
		/*      */// 9: getstatic 93 com/claro/util/ServiceLocator:jdbcCirculoAzul
				// Ljava/lang/String;
		/*      */// 12: invokevirtual 96 com/claro/util/ServiceLocator:getConnection
				// (Ljava/lang/String;)Ljava/sql/Connection;
		/*      */// 15: astore 11
		/*      */// 17: getstatic 586 com/claro/util/Constantes:DATEFORMATyyyy_MM_dd
				// Ljava/text/SimpleDateFormat;
		/*      */// 20: new 344 java/util/Date
		/*      */// 23: dup
		/*      */// 24: invokespecial 346 java/util/Date:<init> ()V
		/*      */// 27: invokevirtual 347 java/text/SimpleDateFormat:format
				// (Ljava/util/Date;)Ljava/lang/String;
		/*      */// 30: astore 12
		/*      */// 32: aload_1
		/*      */// 33: invokevirtual 589 java/lang/String:length ()I
		/*      */// 36: bipush 12
		/*      */// 38: if_icmpge +10 -> 48
		/*      */// 41: bipush 12
		/*      */// 43: aload_1
		/*      */// 44: invokestatic 592 com/claro/util/Utils:anexarCeros
				// (ILjava/lang/String;)Ljava/lang/String;
		/*      */// 47: astore_1
		/*      */// 48: iload_2
		/*      */// 49: iconst_2
		/*      */// 50: if_icmpne +22 -> 72
		/*      */// 53: new 293 java/lang/StringBuilder
		/*      */// 56: dup
		/*      */// 57: ldc_w 598
		/*      */// 60: invokespecial 297 java/lang/StringBuilder:<init>
				// (Ljava/lang/String;)V
		/*      */// 63: aload 9
		/*      */// 65: invokevirtual 300 java/lang/StringBuilder:append
				// (Ljava/lang/String;)Ljava/lang/StringBuilder;
		/*      */// 68: invokevirtual 305 java/lang/StringBuilder:toString
				// ()Ljava/lang/String;
		/*      */// 71: astore_1
		/*      */// 72: aload_0
		/*      */// 73: aload 11
		/*      */// 75: aload 12
		/*      */// 77: aload_1
		/*      */// 78: iload_2
		/*      */// 79: aload_3
		/*      */// 80: iload 4
		/*      */// 82: aload 5
		/*      */// 84: aload 6
		/*      */// 86: aload 7
		/*      */// 88: aload 8
		/*      */// 90: aload 9
		/*      */// 92: invokespecial 600 com/claro/dao/AlianzasDAO:actualizaAlianza
				// (Ljava/sql/Connection;Ljava/lang/String;Ljava/lang/String;ILjava/lang/String;ILjava/lang/String;Ljava/lang/String;Ljava/lang/String;Ljava/lang/String;Ljava/lang/String;)Lcom/claro/transfer/MensajeTO;
		/*      */// 95: astore 10
		/*      */// 97: aload 10
		/*      */// 99: invokevirtual 604 com/claro/transfer/MensajeTO:getIdMensaje
				// ()I
		/*      */// 102: ifeq +13 -> 115
		/*      */// 105: aload 11
		/*      */// 107: invokeinterface 486 1 0
		/*      */// 112: goto +142 -> 254
		/*      */// 115: aload 11
		/*      */// 117: invokeinterface 479 1 0
		/*      */// 122: goto +132 -> 254
		/*      */// 125: astore 12
		/*      */// 127: aload_0
		/*      */// 128: getfield 27 com/claro/dao/AlianzasDAO:error
				// Lorg/apache/log4j/Logger;
		/*      */// 131: ldc_w 609
		/*      */// 134: aload 12
		/*      */// 136: invokevirtual 393 org/apache/log4j/Logger:info
				// (Ljava/lang/Object;Ljava/lang/Throwable;)V
		/*      */// 139: new 59 com/claro/exception/CAException
		/*      */// 142: dup
		/*      */// 143: iconst_m1
		/*      */// 144: new 293 java/lang/StringBuilder
		/*      */// 147: dup
		/*      */// 148: ldc_w 611
		/*      */// 151: invokespecial 297 java/lang/StringBuilder:<init>
				// (Ljava/lang/String;)V
		/*      */// 154: aload 12
		/*      */// 156: invokevirtual 491 java/sql/SQLException:toString
				// ()Ljava/lang/String;
		/*      */// 159: invokevirtual 300 java/lang/StringBuilder:append
				// (Ljava/lang/String;)Ljava/lang/StringBuilder;
		/*      */// 162: ldc_w 303
		/*      */// 165: invokevirtual 300 java/lang/StringBuilder:append
				// (Ljava/lang/String;)Ljava/lang/StringBuilder;
		/*      */// 168: invokevirtual 305 java/lang/StringBuilder:toString
				// ()Ljava/lang/String;
		/*      */// 171: aload 12
		/*      */// 173: invokespecial 222 com/claro/exception/CAException:<init>
				// (ILjava/lang/String;Ljava/lang/Exception;)V
		/*      */// 176: athrow
		/*      */// 177: astore 12
		/*      */// 179: aload_0
		/*      */// 180: getfield 27 com/claro/dao/AlianzasDAO:error
				// Lorg/apache/log4j/Logger;
		/*      */// 183: ldc_w 613
		/*      */// 186: aload 12
		/*      */// 188: invokevirtual 393 org/apache/log4j/Logger:info
				// (Ljava/lang/Object;Ljava/lang/Throwable;)V
		/*      */// 191: new 59 com/claro/exception/CAException
		/*      */// 194: dup
		/*      */// 195: iconst_m1
		/*      */// 196: new 293 java/lang/StringBuilder
		/*      */// 199: dup
		/*      */// 200: ldc_w 615
		/*      */// 203: invokespecial 297 java/lang/StringBuilder:<init>
				// (Ljava/lang/String;)V
		/*      */// 206: aload 12
		/*      */// 208: invokevirtual 299 java/lang/Exception:toString
				// ()Ljava/lang/String;
		/*      */// 211: invokevirtual 300 java/lang/StringBuilder:append
				// (Ljava/lang/String;)Ljava/lang/StringBuilder;
		/*      */// 214: ldc_w 303
		/*      */// 217: invokevirtual 300 java/lang/StringBuilder:append
				// (Ljava/lang/String;)Ljava/lang/StringBuilder;
		/*      */// 220: invokevirtual 305 java/lang/StringBuilder:toString
				// ()Ljava/lang/String;
		/*      */// 223: aload 12
		/*      */// 225: invokespecial 222 com/claro/exception/CAException:<init>
				// (ILjava/lang/String;Ljava/lang/Exception;)V
		/*      */// 228: athrow
		/*      */// 229: astore 13
		/*      */// 231: aload 11
		/*      */// 233: ifnull +18 -> 251
		/*      */// 236: aload 11
		/*      */// 238: invokeinterface 233 1 0
		/*      */// 243: aconst_null
		/*      */// 244: astore 11
		/*      */// 246: goto +5 -> 251
		/*      */// 249: astore 14
		/*      */// 251: aload 13
		/*      */// 253: athrow
		/*      */// 254: aload 11
		/*      */// 256: ifnull +18 -> 274
		/*      */// 259: aload 11
		/*      */// 261: invokeinterface 233 1 0
		/*      */// 266: aconst_null
		/*      */// 267: astore 11
		/*      */// 269: goto +5 -> 274
		/*      */// 272: astore 14
		/*      */// 274: aload 10
		/*      */// 276: areturn
		/*      */// Line number table:
		/*      */// Java source line #337 -> byte code offset #0
		/*      */// Java source line #338 -> byte code offset #3
		/*      */// Java source line #340 -> byte code offset #6
		/*      */// Java source line #341 -> byte code offset #17
		/*      */// Java source line #343 -> byte code offset #32
		/*      */// Java source line #344 -> byte code offset #41
		/*      */// Java source line #346 -> byte code offset #48
		/*      */// Java source line #347 -> byte code offset #53
		/*      */// Java source line #350 -> byte code offset #72
		/*      */// Java source line #352 -> byte code offset #97
		/*      */// Java source line #353 -> byte code offset #105
		/*      */// Java source line #354 -> byte code offset #115
		/*      */// Java source line #356 -> byte code offset #125
		/*      */// Java source line #357 -> byte code offset #127
		/*      */// Java source line #358 -> byte code offset #139
		/*      */// Java source line #359 -> byte code offset #177
		/*      */// Java source line #360 -> byte code offset #179
		/*      */// Java source line #361 -> byte code offset #191
		/*      */// Java source line #362 -> byte code offset #229
		/*      */// Java source line #363 -> byte code offset #231
		/*      */// Java source line #364 -> byte code offset #251
		/*      */// Java source line #363 -> byte code offset #254
		/*      */// Java source line #365 -> byte code offset #274
		/*      */// Local variable table:
		/*      */// start length slot name signature
		/*      */// 0 277 0 this AlianzasDAO
		/*      */// 0 277 1 sCuentaAl String
		/*      */// 0 277 2 iCveAl int
		/*      */// 0 277 3 sCuenta String
		/*      */// 0 277 4 iSecuencia int
		/*      */// 0 277 5 sNombre String
		/*      */// 0 277 6 sApePat String
		/*      */// 0 277 7 sApeMat String
		/*      */// 0 277 8 sUsrCve String
		/*      */// 0 277 9 sTel String
		/*      */// 1 274 10 mensajeTO MensajeTO
		/*      */// 4 264 11 connection Connection
		/*      */// 30 46 12 fechaTransaccion String
		/*      */// 125 47 12 e SQLException
		/*      */// 177 47 12 e Exception
		/*      */// 229 23 13 localObject Object
		/*      */// 249 1 14 localException1 Exception
		/*      */// 272 1 14 localException2 Exception
		/*      */// Exception table:
		/*      */// from to target type
		/*      */// 6 122 125 java/sql/SQLException
		/*      */// 6 122 177 java/lang/Exception
		/*      */// 6 229 229 finally
		/*      */// 236 246 249 java/lang/Exception
		/*      */// 259 269 272 java/lang/Exception
		/*      */}

	/*      */
	/*      *//* Error */
	/*      */public MensajeTO altaPromoAlianza(String sCuentaAl, int iCveAl,
			String sCuenta, int iSecuencia, String sNombre, String sApePat,
			String sApeMat, String sUsrCve, String sTel)
	/*      */throws CAException
	/*      */{
		return null;
		/*      */// Byte code:
		/*      */// 0: new 605 com/claro/transfer/MensajeTO
		/*      */// 3: dup
		/*      */// 4: invokespecial 628 com/claro/transfer/MensajeTO:<init> ()V
		/*      */// 7: astore 10
		/*      */// 9: aconst_null
		/*      */// 10: astore 11
		/*      */// 12: getstatic 586 com/claro/util/Constantes:DATEFORMATyyyy_MM_dd
				// Ljava/text/SimpleDateFormat;
		/*      */// 15: new 344 java/util/Date
		/*      */// 18: dup
		/*      */// 19: invokespecial 346 java/util/Date:<init> ()V
		/*      */// 22: invokevirtual 347 java/text/SimpleDateFormat:format
				// (Ljava/util/Date;)Ljava/lang/String;
		/*      */// 25: astore 13
		/*      */// 27: aload_1
		/*      */// 28: invokevirtual 589 java/lang/String:length ()I
		/*      */// 31: bipush 12
		/*      */// 33: if_icmpge +10 -> 43
		/*      */// 36: bipush 12
		/*      */// 38: aload_1
		/*      */// 39: invokestatic 592 com/claro/util/Utils:anexarCeros
				// (ILjava/lang/String;)Ljava/lang/String;
		/*      */// 42: astore_1
		/*      */// 43: iload_2
		/*      */// 44: iconst_2
		/*      */// 45: if_icmpne +22 -> 67
		/*      */// 48: new 293 java/lang/StringBuilder
		/*      */// 51: dup
		/*      */// 52: ldc_w 598
		/*      */// 55: invokespecial 297 java/lang/StringBuilder:<init>
				// (Ljava/lang/String;)V
		/*      */// 58: aload 9
		/*      */// 60: invokevirtual 300 java/lang/StringBuilder:append
				// (Ljava/lang/String;)Ljava/lang/StringBuilder;
		/*      */// 63: invokevirtual 305 java/lang/StringBuilder:toString
				// ()Ljava/lang/String;
		/*      */// 66: astore_1
		/*      */// 67: new 629 com/claro/dao/CatalogoDAO
		/*      */// 70: dup
		/*      */// 71: invokespecial 631 com/claro/dao/CatalogoDAO:<init> ()V
		/*      */// 74: astore 14
		/*      */// 76: ldc_w 632
		/*      */// 79: astore 12
		/*      */// 81: aload 14
		/*      */// 83: iload_2
		/*      */// 84: aload_3
		/*      */// 85: iload 4
		/*      */// 87: aload 12
		/*      */// 89: aload_1
		/*      */// 90: invokevirtual 634 com/claro/dao/CatalogoDAO:consultaAlianzas
				// (ILjava/lang/String;ILjava/lang/String;Ljava/lang/String;)Ljava/util/ArrayList;
		/*      */// 93: astore 15
		/*      */// 95: invokestatic 29 com/claro/util/ServiceLocator:getInstance
				// ()Lcom/claro/util/ServiceLocator;
		/*      */// 98: getstatic 93 com/claro/util/ServiceLocator:jdbcCirculoAzul
				// Ljava/lang/String;
		/*      */// 101: invokevirtual 96
				// com/claro/util/ServiceLocator:getConnection
				// (Ljava/lang/String;)Ljava/sql/Connection;
		/*      */// 104: astore 11
		/*      */// 106: aload 15
		/*      */// 108: ifnull +11 -> 119
		/*      */// 111: aload 15
		/*      */// 113: invokevirtual 638 java/util/ArrayList:isEmpty ()Z
		/*      */// 116: ifeq +31 -> 147
		/*      */// 119: aload_0
		/*      */// 120: aload 11
		/*      */// 122: aload 13
		/*      */// 124: aload_1
		/*      */// 125: iload_2
		/*      */// 126: aload_3
		/*      */// 127: iload 4
		/*      */// 129: aload 5
		/*      */// 131: aload 6
		/*      */// 133: aload 7
		/*      */// 135: aload 8
		/*      */// 137: aload 9
		/*      */// 139: invokespecial 641 com/claro/dao/AlianzasDAO:altaAlianza
				// (Ljava/sql/Connection;Ljava/lang/String;Ljava/lang/String;ILjava/lang/String;ILjava/lang/String;Ljava/lang/String;Ljava/lang/String;Ljava/lang/String;Ljava/lang/String;)Lcom/claro/transfer/MensajeTO;
		/*      */// 142: astore 10
		/*      */// 144: goto +160 -> 304
		/*      */// 147: aload_0
		/*      */// 148: aload 11
		/*      */// 150: aload 13
		/*      */// 152: aload_1
		/*      */// 153: iload_2
		/*      */// 154: aload_3
		/*      */// 155: iload 4
		/*      */// 157: aload 5
		/*      */// 159: aload 6
		/*      */// 161: aload 7
		/*      */// 163: aload 8
		/*      */// 165: aload 9
		/*      */// 167: invokespecial 600
				// com/claro/dao/AlianzasDAO:actualizaAlianza
				// (Ljava/sql/Connection;Ljava/lang/String;Ljava/lang/String;ILjava/lang/String;ILjava/lang/String;Ljava/lang/String;Ljava/lang/String;Ljava/lang/String;Ljava/lang/String;)Lcom/claro/transfer/MensajeTO;
		/*      */// 170: astore 10
		/*      */// 172: goto +132 -> 304
		/*      */// 175: astore 13
		/*      */// 177: aload_0
		/*      */// 178: getfield 27 com/claro/dao/AlianzasDAO:error
				// Lorg/apache/log4j/Logger;
		/*      */// 181: ldc_w 644
		/*      */// 184: aload 13
		/*      */// 186: invokevirtual 393 org/apache/log4j/Logger:info
				// (Ljava/lang/Object;Ljava/lang/Throwable;)V
		/*      */// 189: new 59 com/claro/exception/CAException
		/*      */// 192: dup
		/*      */// 193: iconst_m1
		/*      */// 194: new 293 java/lang/StringBuilder
		/*      */// 197: dup
		/*      */// 198: ldc_w 646
		/*      */// 201: invokespecial 297 java/lang/StringBuilder:<init>
				// (Ljava/lang/String;)V
		/*      */// 204: aload 13
		/*      */// 206: invokevirtual 491 java/sql/SQLException:toString
				// ()Ljava/lang/String;
		/*      */// 209: invokevirtual 300 java/lang/StringBuilder:append
				// (Ljava/lang/String;)Ljava/lang/StringBuilder;
		/*      */// 212: ldc_w 303
		/*      */// 215: invokevirtual 300 java/lang/StringBuilder:append
				// (Ljava/lang/String;)Ljava/lang/StringBuilder;
		/*      */// 218: invokevirtual 305 java/lang/StringBuilder:toString
				// ()Ljava/lang/String;
		/*      */// 221: aload 13
		/*      */// 223: invokespecial 222 com/claro/exception/CAException:<init>
				// (ILjava/lang/String;Ljava/lang/Exception;)V
		/*      */// 226: athrow
		/*      */// 227: astore 13
		/*      */// 229: aload_0
		/*      */// 230: getfield 27 com/claro/dao/AlianzasDAO:error
				// Lorg/apache/log4j/Logger;
		/*      */// 233: ldc_w 648
		/*      */// 236: aload 13
		/*      */// 238: invokevirtual 393 org/apache/log4j/Logger:info
				// (Ljava/lang/Object;Ljava/lang/Throwable;)V
		/*      */// 241: new 59 com/claro/exception/CAException
		/*      */// 244: dup
		/*      */// 245: iconst_m1
		/*      */// 246: new 293 java/lang/StringBuilder
		/*      */// 249: dup
		/*      */// 250: ldc_w 650
		/*      */// 253: invokespecial 297 java/lang/StringBuilder:<init>
				// (Ljava/lang/String;)V
		/*      */// 256: aload 13
		/*      */// 258: invokevirtual 299 java/lang/Exception:toString
				// ()Ljava/lang/String;
		/*      */// 261: invokevirtual 300 java/lang/StringBuilder:append
				// (Ljava/lang/String;)Ljava/lang/StringBuilder;
		/*      */// 264: ldc_w 303
		/*      */// 267: invokevirtual 300 java/lang/StringBuilder:append
				// (Ljava/lang/String;)Ljava/lang/StringBuilder;
		/*      */// 270: invokevirtual 305 java/lang/StringBuilder:toString
				// ()Ljava/lang/String;
		/*      */// 273: aload 13
		/*      */// 275: invokespecial 222 com/claro/exception/CAException:<init>
				// (ILjava/lang/String;Ljava/lang/Exception;)V
		/*      */// 278: athrow
		/*      */// 279: astore 16
		/*      */// 281: aload 11
		/*      */// 283: ifnull +18 -> 301
		/*      */// 286: aload 11
		/*      */// 288: invokeinterface 233 1 0
		/*      */// 293: aconst_null
		/*      */// 294: astore 11
		/*      */// 296: goto +5 -> 301
		/*      */// 299: astore 17
		/*      */// 301: aload 16
		/*      */// 303: athrow
		/*      */// 304: aload 11
		/*      */// 306: ifnull +18 -> 324
		/*      */// 309: aload 11
		/*      */// 311: invokeinterface 233 1 0
		/*      */// 316: aconst_null
		/*      */// 317: astore 11
		/*      */// 319: goto +5 -> 324
		/*      */// 322: astore 17
		/*      */// 324: aload 10
		/*      */// 326: areturn
		/*      */// Line number table:
		/*      */// Java source line #369 -> byte code offset #0
		/*      */// Java source line #370 -> byte code offset #9
		/*      */// Java source line #374 -> byte code offset #12
		/*      */// Java source line #376 -> byte code offset #27
		/*      */// Java source line #377 -> byte code offset #36
		/*      */// Java source line #379 -> byte code offset #43
		/*      */// Java source line #380 -> byte code offset #48
		/*      */// Java source line #382 -> byte code offset #67
		/*      */// Java source line #383 -> byte code offset #76
		/*      */// Java source line #385 -> byte code offset #81
		/*      */// Java source line #386 -> byte code offset #95
		/*      */// Java source line #387 -> byte code offset #106
		/*      */// Java source line #388 -> byte code offset #119
		/*      */// Java source line #390 -> byte code offset #147
		/*      */// Java source line #394 -> byte code offset #175
		/*      */// Java source line #395 -> byte code offset #177
		/*      */// Java source line #396 -> byte code offset #189
		/*      */// Java source line #397 -> byte code offset #227
		/*      */// Java source line #398 -> byte code offset #229
		/*      */// Java source line #399 -> byte code offset #241
		/*      */// Java source line #400 -> byte code offset #279
		/*      */// Java source line #401 -> byte code offset #281
		/*      */// Java source line #402 -> byte code offset #301
		/*      */// Java source line #401 -> byte code offset #304
		/*      */// Java source line #403 -> byte code offset #324
		/*      */// Local variable table:
		/*      */// start length slot name signature
		/*      */// 0 327 0 this AlianzasDAO
		/*      */// 0 327 1 sCuentaAl String
		/*      */// 0 327 2 iCveAl int
		/*      */// 0 327 3 sCuenta String
		/*      */// 0 327 4 iSecuencia int
		/*      */// 0 327 5 sNombre String
		/*      */// 0 327 6 sApePat String
		/*      */// 0 327 7 sApeMat String
		/*      */// 0 327 8 sUsrCve String
		/*      */// 0 327 9 sTel String
		/*      */// 7 318 10 mensajeTO MensajeTO
		/*      */// 10 308 11 connection Connection
		/*      */// 79 9 12 estatus String
		/*      */// 304 1 12 estatus String
		/*      */// 25 126 13 FechaActual String
		/*      */// 175 47 13 e SQLException
		/*      */// 227 47 13 e Exception
		/*      */// 74 8 14 catalogoDAO CatalogoDAO
		/*      */// 93 19 15 alianzasArreglo ArrayList<AlianzasTO>
		/*      */// 279 23 16 localObject Object
		/*      */// 299 1 17 localException1 Exception
		/*      */// 322 1 17 localException2 Exception
		/*      */// Exception table:
		/*      */// from to target type
		/*      */// 12 172 175 java/sql/SQLException
		/*      */// 12 172 227 java/lang/Exception
		/*      */// 12 279 279 finally
		/*      */// 286 296 299 java/lang/Exception
		/*      */// 309 319 322 java/lang/Exception
		/*      */}

	/*      */
	/*      *//* Error */
	/*      */private MensajeTO actualizaAlianza(Connection connection,
			String fechaTransaccion, String sCuentaAl, int iCveAl,
			String sCuenta, int iSecuencia, String sNombre, String sApePat,
			String sApeMat, String sUsrCve, String sTel)
	/*      */throws CAException
	/*      */{
		return null;
		/*      */// Byte code:
		/*      */// 0: aconst_null
		/*      */// 1: astore 12
		/*      */// 3: aconst_null
		/*      */// 4: astore 13
		/*      */// 6: aconst_null
		/*      */// 7: astore 14
		/*      */// 9: aload_1
		/*      */// 10: ifnonnull +17 -> 27
		/*      */// 13: invokestatic 29 com/claro/util/ServiceLocator:getInstance
				// ()Lcom/claro/util/ServiceLocator;
		/*      */// 16: getstatic 93 com/claro/util/ServiceLocator:jdbcCirculoAzul
				// Ljava/lang/String;
		/*      */// 19: invokevirtual 96 com/claro/util/ServiceLocator:getConnection
				// (Ljava/lang/String;)Ljava/sql/Connection;
		/*      */// 22: astore 12
		/*      */// 24: goto +6 -> 30
		/*      */// 27: aload_1
		/*      */// 28: astore 12
		/*      */// 30: new 66 java/lang/StringBuffer
		/*      */// 33: dup
		/*      */// 34: invokespecial 68 java/lang/StringBuffer:<init> ()V
		/*      */// 37: astore 15
		/*      */// 39: aload 15
		/*      */// 41: ldc_w 657
		/*      */// 44: invokevirtual 71 java/lang/StringBuffer:append
				// (Ljava/lang/String;)Ljava/lang/StringBuffer;
		/*      */// 47: aload_0
		/*      */// 48: getfield 41 com/claro/dao/AlianzasDAO:schema_database
				// Ljava/lang/String;
		/*      */// 51: invokevirtual 71 java/lang/StringBuffer:append
				// (Ljava/lang/String;)Ljava/lang/StringBuffer;
		/*      */// 54: ldc_w 659
		/*      */// 57: invokevirtual 71 java/lang/StringBuffer:append
				// (Ljava/lang/String;)Ljava/lang/StringBuffer;
		/*      */// 60: pop
		/*      */// 61: aload 15
		/*      */// 63: ldc_w 661
		/*      */// 66: invokevirtual 71 java/lang/StringBuffer:append
				// (Ljava/lang/String;)Ljava/lang/StringBuffer;
		/*      */// 69: pop
		/*      */// 70: aload 15
		/*      */// 72: ldc_w 663
		/*      */// 75: invokevirtual 71 java/lang/StringBuffer:append
				// (Ljava/lang/String;)Ljava/lang/StringBuffer;
		/*      */// 78: pop
		/*      */// 79: aload 15
		/*      */// 81: ldc_w 665
		/*      */// 84: invokevirtual 71 java/lang/StringBuffer:append
				// (Ljava/lang/String;)Ljava/lang/StringBuffer;
		/*      */// 87: pop
		/*      */// 88: aload 15
		/*      */// 90: ldc_w 667
		/*      */// 93: invokevirtual 71 java/lang/StringBuffer:append
				// (Ljava/lang/String;)Ljava/lang/StringBuffer;
		/*      */// 96: pop
		/*      */// 97: aload_2
		/*      */// 98: ifnull +21 -> 119
		/*      */// 101: aload 15
		/*      */// 103: ldc_w 669
		/*      */// 106: invokevirtual 71 java/lang/StringBuffer:append
				// (Ljava/lang/String;)Ljava/lang/StringBuffer;
		/*      */// 109: pop
		/*      */// 110: aload 15
		/*      */// 112: ldc_w 671
		/*      */// 115: invokevirtual 71 java/lang/StringBuffer:append
				// (Ljava/lang/String;)Ljava/lang/StringBuffer;
		/*      */// 118: pop
		/*      */// 119: aload 15
		/*      */// 121: ldc_w 673
		/*      */// 124: invokevirtual 71 java/lang/StringBuffer:append
				// (Ljava/lang/String;)Ljava/lang/StringBuffer;
		/*      */// 127: pop
		/*      */// 128: aload 15
		/*      */// 130: ldc_w 675
		/*      */// 133: invokevirtual 71 java/lang/StringBuffer:append
				// (Ljava/lang/String;)Ljava/lang/StringBuffer;
		/*      */// 136: pop
		/*      */// 137: aload 15
		/*      */// 139: ldc_w 677
		/*      */// 142: invokevirtual 71 java/lang/StringBuffer:append
				// (Ljava/lang/String;)Ljava/lang/StringBuffer;
		/*      */// 145: pop
		/*      */// 146: aload 15
		/*      */// 148: ldc_w 679
		/*      */// 151: invokevirtual 71 java/lang/StringBuffer:append
				// (Ljava/lang/String;)Ljava/lang/StringBuffer;
		/*      */// 154: pop
		/*      */// 155: aload 12
		/*      */// 157: aload 15
		/*      */// 159: invokevirtual 100 java/lang/StringBuffer:toString
				// ()Ljava/lang/String;
		/*      */// 162: invokeinterface 104 2 0
		/*      */// 167: astore 13
		/*      */// 169: aload 13
		/*      */// 171: iconst_1
		/*      */// 172: aload 7
		/*      */// 174: invokeinterface 110 3 0
		/*      */// 179: aload 13
		/*      */// 181: iconst_2
		/*      */// 182: aload 8
		/*      */// 184: invokeinterface 110 3 0
		/*      */// 189: aload 13
		/*      */// 191: iconst_3
		/*      */// 192: aload 9
		/*      */// 194: invokeinterface 110 3 0
		/*      */// 199: aload_2
		/*      */// 200: ifnull +60 -> 260
		/*      */// 203: aload 13
		/*      */// 205: iconst_4
		/*      */// 206: aload_2
		/*      */// 207: invokestatic 681 java/sql/Date:valueOf
				// (Ljava/lang/String;)Ljava/sql/Date;
		/*      */// 210: invokeinterface 367 3 0
		/*      */// 215: aload 13
		/*      */// 217: iconst_5
		/*      */// 218: aload 5
		/*      */// 220: invokeinterface 110 3 0
		/*      */// 225: aload 13
		/*      */// 227: bipush 6
		/*      */// 229: iload 6
		/*      */// 231: invokeinterface 122 3 0
		/*      */// 236: aload 13
		/*      */// 238: bipush 7
		/*      */// 240: iload 4
		/*      */// 242: invokeinterface 122 3 0
		/*      */// 247: aload 13
		/*      */// 249: bipush 8
		/*      */// 251: aload_3
		/*      */// 252: invokeinterface 110 3 0
		/*      */// 257: goto +44 -> 301
		/*      */// 260: aload 13
		/*      */// 262: iconst_4
		/*      */// 263: aload 5
		/*      */// 265: invokeinterface 110 3 0
		/*      */// 270: aload 13
		/*      */// 272: iconst_5
		/*      */// 273: iload 6
		/*      */// 275: invokeinterface 122 3 0
		/*      */// 280: aload 13
		/*      */// 282: bipush 6
		/*      */// 284: iload 4
		/*      */// 286: invokeinterface 122 3 0
		/*      */// 291: aload 13
		/*      */// 293: bipush 7
		/*      */// 295: aload_3
		/*      */// 296: invokeinterface 110 3 0
		/*      */// 301: new 605 com/claro/transfer/MensajeTO
		/*      */// 304: dup
		/*      */// 305: invokespecial 628 com/claro/transfer/MensajeTO:<init> ()V
		/*      */// 308: astore 14
		/*      */// 310: aload 13
		/*      */// 312: invokeinterface 466 1 0
		/*      */// 317: ifle +15 -> 332
		/*      */// 320: aload 14
		/*      */// 322: iconst_0
		/*      */// 323: ldc_w 683
		/*      */// 326: invokevirtual 685
				// com/claro/transfer/MensajeTO:agregaMensaje
				// (ILjava/lang/String;)V
		/*      */// 329: goto +168 -> 497
		/*      */// 332: aload 14
		/*      */// 334: iconst_m1
		/*      */// 335: ldc_w 688
		/*      */// 338: invokevirtual 685
				// com/claro/transfer/MensajeTO:agregaMensaje
				// (ILjava/lang/String;)V
		/*      */// 341: goto +156 -> 497
		/*      */// 344: astore 15
		/*      */// 346: aload_0
		/*      */// 347: getfield 27 com/claro/dao/AlianzasDAO:error
				// Lorg/apache/log4j/Logger;
		/*      */// 350: ldc_w 609
		/*      */// 353: aload 15
		/*      */// 355: invokevirtual 393 org/apache/log4j/Logger:info
				// (Ljava/lang/Object;Ljava/lang/Throwable;)V
		/*      */// 358: new 59 com/claro/exception/CAException
		/*      */// 361: dup
		/*      */// 362: iconst_m1
		/*      */// 363: new 293 java/lang/StringBuilder
		/*      */// 366: dup
		/*      */// 367: ldc_w 611
		/*      */// 370: invokespecial 297 java/lang/StringBuilder:<init>
				// (Ljava/lang/String;)V
		/*      */// 373: aload 15
		/*      */// 375: invokevirtual 491 java/sql/SQLException:toString
				// ()Ljava/lang/String;
		/*      */// 378: invokevirtual 300 java/lang/StringBuilder:append
				// (Ljava/lang/String;)Ljava/lang/StringBuilder;
		/*      */// 381: ldc_w 303
		/*      */// 384: invokevirtual 300 java/lang/StringBuilder:append
				// (Ljava/lang/String;)Ljava/lang/StringBuilder;
		/*      */// 387: invokevirtual 305 java/lang/StringBuilder:toString
				// ()Ljava/lang/String;
		/*      */// 390: aload 15
		/*      */// 392: invokespecial 222 com/claro/exception/CAException:<init>
				// (ILjava/lang/String;Ljava/lang/Exception;)V
		/*      */// 395: athrow
		/*      */// 396: astore 15
		/*      */// 398: aload_0
		/*      */// 399: getfield 27 com/claro/dao/AlianzasDAO:error
				// Lorg/apache/log4j/Logger;
		/*      */// 402: ldc_w 613
		/*      */// 405: aload 15
		/*      */// 407: invokevirtual 393 org/apache/log4j/Logger:info
				// (Ljava/lang/Object;Ljava/lang/Throwable;)V
		/*      */// 410: new 59 com/claro/exception/CAException
		/*      */// 413: dup
		/*      */// 414: iconst_m1
		/*      */// 415: new 293 java/lang/StringBuilder
		/*      */// 418: dup
		/*      */// 419: ldc_w 611
		/*      */// 422: invokespecial 297 java/lang/StringBuilder:<init>
				// (Ljava/lang/String;)V
		/*      */// 425: aload 15
		/*      */// 427: invokevirtual 299 java/lang/Exception:toString
				// ()Ljava/lang/String;
		/*      */// 430: invokevirtual 300 java/lang/StringBuilder:append
				// (Ljava/lang/String;)Ljava/lang/StringBuilder;
		/*      */// 433: ldc_w 303
		/*      */// 436: invokevirtual 300 java/lang/StringBuilder:append
				// (Ljava/lang/String;)Ljava/lang/StringBuilder;
		/*      */// 439: invokevirtual 305 java/lang/StringBuilder:toString
				// ()Ljava/lang/String;
		/*      */// 442: aload 15
		/*      */// 444: invokespecial 222 com/claro/exception/CAException:<init>
				// (ILjava/lang/String;Ljava/lang/Exception;)V
		/*      */// 447: athrow
		/*      */// 448: astore 16
		/*      */// 450: aload 13
		/*      */// 452: ifnull +18 -> 470
		/*      */// 455: aload 13
		/*      */// 457: invokeinterface 232 1 0
		/*      */// 462: aconst_null
		/*      */// 463: astore 13
		/*      */// 465: goto +5 -> 470
		/*      */// 468: astore 17
		/*      */// 470: aload_1
		/*      */// 471: ifnonnull +23 -> 494
		/*      */// 474: aload 12
		/*      */// 476: ifnull +18 -> 494
		/*      */// 479: aload 12
		/*      */// 481: invokeinterface 233 1 0
		/*      */// 486: aconst_null
		/*      */// 487: astore 12
		/*      */// 489: goto +5 -> 494
		/*      */// 492: astore 17
		/*      */// 494: aload 16
		/*      */// 496: athrow
		/*      */// 497: aload 13
		/*      */// 499: ifnull +18 -> 517
		/*      */// 502: aload 13
		/*      */// 504: invokeinterface 232 1 0
		/*      */// 509: aconst_null
		/*      */// 510: astore 13
		/*      */// 512: goto +5 -> 517
		/*      */// 515: astore 17
		/*      */// 517: aload_1
		/*      */// 518: ifnonnull +23 -> 541
		/*      */// 521: aload 12
		/*      */// 523: ifnull +18 -> 541
		/*      */// 526: aload 12
		/*      */// 528: invokeinterface 233 1 0
		/*      */// 533: aconst_null
		/*      */// 534: astore 12
		/*      */// 536: goto +5 -> 541
		/*      */// 539: astore 17
		/*      */// 541: aload 14
		/*      */// 543: areturn
		/*      */// Line number table:
		/*      */// Java source line #409 -> byte code offset #0
		/*      */// Java source line #410 -> byte code offset #3
		/*      */// Java source line #411 -> byte code offset #6
		/*      */// Java source line #414 -> byte code offset #9
		/*      */// Java source line #415 -> byte code offset #27
		/*      */// Java source line #417 -> byte code offset #30
		/*      */// Java source line #419 -> byte code offset #39
		/*      */// Java source line #420 -> byte code offset #61
		/*      */// Java source line #421 -> byte code offset #70
		/*      */// Java source line #422 -> byte code offset #79
		/*      */// Java source line #423 -> byte code offset #88
		/*      */// Java source line #424 -> byte code offset #97
		/*      */// Java source line #425 -> byte code offset #101
		/*      */// Java source line #426 -> byte code offset #110
		/*      */// Java source line #428 -> byte code offset #119
		/*      */// Java source line #429 -> byte code offset #128
		/*      */// Java source line #430 -> byte code offset #137
		/*      */// Java source line #431 -> byte code offset #146
		/*      */// Java source line #433 -> byte code offset #155
		/*      */// Java source line #435 -> byte code offset #169
		/*      */// Java source line #436 -> byte code offset #179
		/*      */// Java source line #437 -> byte code offset #189
		/*      */// Java source line #439 -> byte code offset #199
		/*      */// Java source line #440 -> byte code offset #203
		/*      */// Java source line #441 -> byte code offset #215
		/*      */// Java source line #442 -> byte code offset #225
		/*      */// Java source line #443 -> byte code offset #236
		/*      */// Java source line #444 -> byte code offset #247
		/*      */// Java source line #446 -> byte code offset #260
		/*      */// Java source line #447 -> byte code offset #270
		/*      */// Java source line #448 -> byte code offset #280
		/*      */// Java source line #449 -> byte code offset #291
		/*      */// Java source line #451 -> byte code offset #301
		/*      */// Java source line #452 -> byte code offset #310
		/*      */// Java source line #453 -> byte code offset #320
		/*      */// Java source line #454 -> byte code offset #332
		/*      */// Java source line #456 -> byte code offset #344
		/*      */// Java source line #457 -> byte code offset #346
		/*      */// Java source line #458 -> byte code offset #358
		/*      */// Java source line #459 -> byte code offset #396
		/*      */// Java source line #460 -> byte code offset #398
		/*      */// Java source line #461 -> byte code offset #410
		/*      */// Java source line #462 -> byte code offset #448
		/*      */// Java source line #463 -> byte code offset #450
		/*      */// Java source line #464 -> byte code offset #470
		/*      */// Java source line #465 -> byte code offset #494
		/*      */// Java source line #463 -> byte code offset #497
		/*      */// Java source line #464 -> byte code offset #517
		/*      */// Java source line #466 -> byte code offset #541
		/*      */// Local variable table:
		/*      */// start length slot name signature
		/*      */// 0 544 0 this AlianzasDAO
		/*      */// 0 544 1 connection Connection
		/*      */// 0 544 2 fechaTransaccion String
		/*      */// 0 544 3 sCuentaAl String
		/*      */// 0 544 4 iCveAl int
		/*      */// 0 544 5 sCuenta String
		/*      */// 0 544 6 iSecuencia int
		/*      */// 0 544 7 sNombre String
		/*      */// 0 544 8 sApePat String
		/*      */// 0 544 9 sApeMat String
		/*      */// 0 544 10 sUsrCve String
		/*      */// 0 544 11 sTel String
		/*      */// 1 534 12 lConn Connection
		/*      */// 4 507 13 statement PreparedStatement
		/*      */// 7 535 14 mensajeTO MensajeTO
		/*      */// 37 121 15 sUpdate StringBuffer
		/*      */// 344 47 15 e SQLException
		/*      */// 396 47 15 e Exception
		/*      */// 448 47 16 localObject Object
		/*      */// 468 1 17 localException1 Exception
		/*      */// 492 1 17 localException2 Exception
		/*      */// 515 1 17 localException3 Exception
		/*      */// 539 1 17 localException4 Exception
		/*      */// Exception table:
		/*      */// from to target type
		/*      */// 9 341 344 java/sql/SQLException
		/*      */// 9 341 396 java/lang/Exception
		/*      */// 9 448 448 finally
		/*      */// 455 465 468 java/lang/Exception
		/*      */// 479 489 492 java/lang/Exception
		/*      */// 502 512 515 java/lang/Exception
		/*      */// 526 536 539 java/lang/Exception
		/*      */}

	/*      */
	/*      *//* Error */
	/*      */private MensajeTO altaAlianza(Connection connection,
			String fechaTransaccion, String sCuentaAl, int iCveAl,
			String sCuenta, int iSecuencia, String sNombre, String sApePat,
			String sApeMat, String sUsrCve, String sTel)
	/*      */throws CAException
	/*      */{
		return null;
		/*      */// Byte code:
		/*      */// 0: aconst_null
		/*      */// 1: astore 12
		/*      */// 3: aconst_null
		/*      */// 4: astore 13
		/*      */// 6: new 605 com/claro/transfer/MensajeTO
		/*      */// 9: dup
		/*      */// 10: invokespecial 628 com/claro/transfer/MensajeTO:<init> ()V
		/*      */// 13: astore 14
		/*      */// 15: aload_1
		/*      */// 16: ifnonnull +17 -> 33
		/*      */// 19: invokestatic 29 com/claro/util/ServiceLocator:getInstance
				// ()Lcom/claro/util/ServiceLocator;
		/*      */// 22: getstatic 93 com/claro/util/ServiceLocator:jdbcCirculoAzul
				// Ljava/lang/String;
		/*      */// 25: invokevirtual 96 com/claro/util/ServiceLocator:getConnection
				// (Ljava/lang/String;)Ljava/sql/Connection;
		/*      */// 28: astore 12
		/*      */// 30: goto +6 -> 36
		/*      */// 33: aload_1
		/*      */// 34: astore 12
		/*      */// 36: new 66 java/lang/StringBuffer
		/*      */// 39: dup
		/*      */// 40: invokespecial 68 java/lang/StringBuffer:<init> ()V
		/*      */// 43: astore 15
		/*      */// 45: aconst_null
		/*      */// 46: astore 16
		/*      */// 48: aload 15
		/*      */// 50: ldc_w 692
		/*      */// 53: invokevirtual 71 java/lang/StringBuffer:append
				// (Ljava/lang/String;)Ljava/lang/StringBuffer;
		/*      */// 56: aload_0
		/*      */// 57: getfield 41 com/claro/dao/AlianzasDAO:schema_database
				// Ljava/lang/String;
		/*      */// 60: invokevirtual 71 java/lang/StringBuffer:append
				// (Ljava/lang/String;)Ljava/lang/StringBuffer;
		/*      */// 63: ldc_w 659
		/*      */// 66: invokevirtual 71 java/lang/StringBuffer:append
				// (Ljava/lang/String;)Ljava/lang/StringBuffer;
		/*      */// 69: pop
		/*      */// 70: aload 15
		/*      */// 72: ldc_w 694
		/*      */// 75: invokevirtual 71 java/lang/StringBuffer:append
				// (Ljava/lang/String;)Ljava/lang/StringBuffer;
		/*      */// 78: pop
		/*      */// 79: aload 15
		/*      */// 81: ldc_w 696
		/*      */// 84: invokevirtual 71 java/lang/StringBuffer:append
				// (Ljava/lang/String;)Ljava/lang/StringBuffer;
		/*      */// 87: pop
		/*      */// 88: aload 12
		/*      */// 90: aload 15
		/*      */// 92: invokevirtual 100 java/lang/StringBuffer:toString
				// ()Ljava/lang/String;
		/*      */// 95: invokeinterface 104 2 0
		/*      */// 100: astore 13
		/*      */// 102: aload 13
		/*      */// 104: iconst_1
		/*      */// 105: aload_3
		/*      */// 106: invokeinterface 110 3 0
		/*      */// 111: aload 13
		/*      */// 113: iconst_2
		/*      */// 114: iload 4
		/*      */// 116: invokeinterface 122 3 0
		/*      */// 121: aload 13
		/*      */// 123: iconst_3
		/*      */// 124: aload 5
		/*      */// 126: invokeinterface 110 3 0
		/*      */// 131: aload 13
		/*      */// 133: iconst_4
		/*      */// 134: iload 6
		/*      */// 136: invokeinterface 122 3 0
		/*      */// 141: aload 13
		/*      */// 143: iconst_5
		/*      */// 144: aload 7
		/*      */// 146: invokeinterface 110 3 0
		/*      */// 151: aload 13
		/*      */// 153: bipush 6
		/*      */// 155: aload 8
		/*      */// 157: invokeinterface 110 3 0
		/*      */// 162: aload 13
		/*      */// 164: bipush 7
		/*      */// 166: aload 9
		/*      */// 168: invokeinterface 110 3 0
		/*      */// 173: aload 13
		/*      */// 175: bipush 8
		/*      */// 177: aload_2
		/*      */// 178: invokestatic 681 java/sql/Date:valueOf
				// (Ljava/lang/String;)Ljava/sql/Date;
		/*      */// 181: invokeinterface 367 3 0
		/*      */// 186: aload 13
		/*      */// 188: bipush 9
		/*      */// 190: aload 10
		/*      */// 192: invokeinterface 110 3 0
		/*      */// 197: aload 13
		/*      */// 199: bipush 10
		/*      */// 201: ldc_w 632
		/*      */// 204: invokeinterface 110 3 0
		/*      */// 209: aload 13
		/*      */// 211: invokeinterface 466 1 0
		/*      */// 216: ifle +15 -> 231
		/*      */// 219: aload 14
		/*      */// 221: iconst_0
		/*      */// 222: ldc_w 683
		/*      */// 225: invokevirtual 685
				// com/claro/transfer/MensajeTO:agregaMensaje
				// (ILjava/lang/String;)V
		/*      */// 228: goto +168 -> 396
		/*      */// 231: aload 14
		/*      */// 233: iconst_m1
		/*      */// 234: ldc_w 698
		/*      */// 237: invokevirtual 685
				// com/claro/transfer/MensajeTO:agregaMensaje
				// (ILjava/lang/String;)V
		/*      */// 240: goto +156 -> 396
		/*      */// 243: astore 15
		/*      */// 245: aload_0
		/*      */// 246: getfield 27 com/claro/dao/AlianzasDAO:error
				// Lorg/apache/log4j/Logger;
		/*      */// 249: ldc_w 700
		/*      */// 252: aload 15
		/*      */// 254: invokevirtual 393 org/apache/log4j/Logger:info
				// (Ljava/lang/Object;Ljava/lang/Throwable;)V
		/*      */// 257: new 59 com/claro/exception/CAException
		/*      */// 260: dup
		/*      */// 261: iconst_m1
		/*      */// 262: new 293 java/lang/StringBuilder
		/*      */// 265: dup
		/*      */// 266: ldc_w 702
		/*      */// 269: invokespecial 297 java/lang/StringBuilder:<init>
				// (Ljava/lang/String;)V
		/*      */// 272: aload 15
		/*      */// 274: invokevirtual 491 java/sql/SQLException:toString
				// ()Ljava/lang/String;
		/*      */// 277: invokevirtual 300 java/lang/StringBuilder:append
				// (Ljava/lang/String;)Ljava/lang/StringBuilder;
		/*      */// 280: ldc_w 303
		/*      */// 283: invokevirtual 300 java/lang/StringBuilder:append
				// (Ljava/lang/String;)Ljava/lang/StringBuilder;
		/*      */// 286: invokevirtual 305 java/lang/StringBuilder:toString
				// ()Ljava/lang/String;
		/*      */// 289: aload 15
		/*      */// 291: invokespecial 222 com/claro/exception/CAException:<init>
				// (ILjava/lang/String;Ljava/lang/Exception;)V
		/*      */// 294: athrow
		/*      */// 295: astore 15
		/*      */// 297: aload_0
		/*      */// 298: getfield 27 com/claro/dao/AlianzasDAO:error
				// Lorg/apache/log4j/Logger;
		/*      */// 301: ldc_w 704
		/*      */// 304: aload 15
		/*      */// 306: invokevirtual 393 org/apache/log4j/Logger:info
				// (Ljava/lang/Object;Ljava/lang/Throwable;)V
		/*      */// 309: new 59 com/claro/exception/CAException
		/*      */// 312: dup
		/*      */// 313: iconst_m1
		/*      */// 314: new 293 java/lang/StringBuilder
		/*      */// 317: dup
		/*      */// 318: ldc_w 706
		/*      */// 321: invokespecial 297 java/lang/StringBuilder:<init>
				// (Ljava/lang/String;)V
		/*      */// 324: aload 15
		/*      */// 326: invokevirtual 299 java/lang/Exception:toString
				// ()Ljava/lang/String;
		/*      */// 329: invokevirtual 300 java/lang/StringBuilder:append
				// (Ljava/lang/String;)Ljava/lang/StringBuilder;
		/*      */// 332: ldc_w 303
		/*      */// 335: invokevirtual 300 java/lang/StringBuilder:append
				// (Ljava/lang/String;)Ljava/lang/StringBuilder;
		/*      */// 338: invokevirtual 305 java/lang/StringBuilder:toString
				// ()Ljava/lang/String;
		/*      */// 341: aload 15
		/*      */// 343: invokespecial 222 com/claro/exception/CAException:<init>
				// (ILjava/lang/String;Ljava/lang/Exception;)V
		/*      */// 346: athrow
		/*      */// 347: astore 17
		/*      */// 349: aload 13
		/*      */// 351: ifnull +18 -> 369
		/*      */// 354: aload 13
		/*      */// 356: invokeinterface 232 1 0
		/*      */// 361: aconst_null
		/*      */// 362: astore 13
		/*      */// 364: goto +5 -> 369
		/*      */// 367: astore 18
		/*      */// 369: aload_1
		/*      */// 370: ifnonnull +23 -> 393
		/*      */// 373: aload 12
		/*      */// 375: ifnull +18 -> 393
		/*      */// 378: aload 12
		/*      */// 380: invokeinterface 233 1 0
		/*      */// 385: aconst_null
		/*      */// 386: astore 12
		/*      */// 388: goto +5 -> 393
		/*      */// 391: astore 18
		/*      */// 393: aload 17
		/*      */// 395: athrow
		/*      */// 396: aload 13
		/*      */// 398: ifnull +18 -> 416
		/*      */// 401: aload 13
		/*      */// 403: invokeinterface 232 1 0
		/*      */// 408: aconst_null
		/*      */// 409: astore 13
		/*      */// 411: goto +5 -> 416
		/*      */// 414: astore 18
		/*      */// 416: aload_1
		/*      */// 417: ifnonnull +23 -> 440
		/*      */// 420: aload 12
		/*      */// 422: ifnull +18 -> 440
		/*      */// 425: aload 12
		/*      */// 427: invokeinterface 233 1 0
		/*      */// 432: aconst_null
		/*      */// 433: astore 12
		/*      */// 435: goto +5 -> 440
		/*      */// 438: astore 18
		/*      */// 440: aload 14
		/*      */// 442: areturn
		/*      */// Line number table:
		/*      */// Java source line #472 -> byte code offset #0
		/*      */// Java source line #473 -> byte code offset #3
		/*      */// Java source line #474 -> byte code offset #6
		/*      */// Java source line #477 -> byte code offset #15
		/*      */// Java source line #478 -> byte code offset #33
		/*      */// Java source line #480 -> byte code offset #36
		/*      */// Java source line #482 -> byte code offset #45
		/*      */// Java source line #484 -> byte code offset #48
		/*      */// Java source line #485 -> byte code offset #70
		/*      */// Java source line #486 -> byte code offset #79
		/*      */// Java source line #488 -> byte code offset #88
		/*      */// Java source line #490 -> byte code offset #102
		/*      */// Java source line #491 -> byte code offset #111
		/*      */// Java source line #492 -> byte code offset #121
		/*      */// Java source line #493 -> byte code offset #131
		/*      */// Java source line #494 -> byte code offset #141
		/*      */// Java source line #495 -> byte code offset #151
		/*      */// Java source line #496 -> byte code offset #162
		/*      */// Java source line #497 -> byte code offset #173
		/*      */// Java source line #499 -> byte code offset #186
		/*      */// Java source line #500 -> byte code offset #197
		/*      */// Java source line #502 -> byte code offset #209
		/*      */// Java source line #503 -> byte code offset #219
		/*      */// Java source line #504 -> byte code offset #231
		/*      */// Java source line #506 -> byte code offset #243
		/*      */// Java source line #507 -> byte code offset #245
		/*      */// Java source line #508 -> byte code offset #257
		/*      */// Java source line #509 -> byte code offset #295
		/*      */// Java source line #510 -> byte code offset #297
		/*      */// Java source line #511 -> byte code offset #309
		/*      */// Java source line #512 -> byte code offset #347
		/*      */// Java source line #513 -> byte code offset #349
		/*      */// Java source line #514 -> byte code offset #369
		/*      */// Java source line #515 -> byte code offset #393
		/*      */// Java source line #513 -> byte code offset #396
		/*      */// Java source line #514 -> byte code offset #416
		/*      */// Java source line #516 -> byte code offset #440
		/*      */// Local variable table:
		/*      */// start length slot name signature
		/*      */// 0 443 0 this AlianzasDAO
		/*      */// 0 443 1 connection Connection
		/*      */// 0 443 2 fechaTransaccion String
		/*      */// 0 443 3 sCuentaAl String
		/*      */// 0 443 4 iCveAl int
		/*      */// 0 443 5 sCuenta String
		/*      */// 0 443 6 iSecuencia int
		/*      */// 0 443 7 sNombre String
		/*      */// 0 443 8 sApePat String
		/*      */// 0 443 9 sApeMat String
		/*      */// 0 443 10 sUsrCve String
		/*      */// 0 443 11 sTel String
		/*      */// 1 433 12 lConn Connection
		/*      */// 4 406 13 statement PreparedStatement
		/*      */// 13 428 14 mensajeTO MensajeTO
		/*      */// 43 48 15 sInsert StringBuffer
		/*      */// 243 47 15 e SQLException
		/*      */// 295 47 15 e Exception
		/*      */// 46 3 16 dFechaTransaccion java.util.Date
		/*      */// 347 47 17 localObject Object
		/*      */// 367 1 18 localException1 Exception
		/*      */// 391 1 18 localException2 Exception
		/*      */// 414 1 18 localException3 Exception
		/*      */// 438 1 18 localException4 Exception
		/*      */// Exception table:
		/*      */// from to target type
		/*      */// 15 240 243 java/sql/SQLException
		/*      */// 15 240 295 java/lang/Exception
		/*      */// 15 347 347 finally
		/*      */// 354 364 367 java/lang/Exception
		/*      */// 378 388 391 java/lang/Exception
		/*      */// 401 411 414 java/lang/Exception
		/*      */// 425 435 438 java/lang/Exception
		/*      */}

	/*      */
	/*      *//* Error */
	/*      */private MensajeTO inhabilitaAlianza(Connection connection,
			String sCuentaAl, int iCveAl)
	/*      */throws CAException
	/*      */{
		return null;
		/*      */// Byte code:
		/*      */// 0: aconst_null
		/*      */// 1: astore 4
		/*      */// 3: aconst_null
		/*      */// 4: astore 5
		/*      */// 6: new 605 com/claro/transfer/MensajeTO
		/*      */// 9: dup
		/*      */// 10: invokespecial 628 com/claro/transfer/MensajeTO:<init> ()V
		/*      */// 13: astore 6
		/*      */// 15: aload_1
		/*      */// 16: ifnonnull +17 -> 33
		/*      */// 19: invokestatic 29 com/claro/util/ServiceLocator:getInstance
				// ()Lcom/claro/util/ServiceLocator;
		/*      */// 22: getstatic 93 com/claro/util/ServiceLocator:jdbcCirculoAzul
				// Ljava/lang/String;
		/*      */// 25: invokevirtual 96 com/claro/util/ServiceLocator:getConnection
				// (Ljava/lang/String;)Ljava/sql/Connection;
		/*      */// 28: astore 4
		/*      */// 30: goto +6 -> 36
		/*      */// 33: aload_1
		/*      */// 34: astore 4
		/*      */// 36: new 66 java/lang/StringBuffer
		/*      */// 39: dup
		/*      */// 40: invokespecial 68 java/lang/StringBuffer:<init> ()V
		/*      */// 43: astore 7
		/*      */// 45: aload 7
		/*      */// 47: ldc_w 657
		/*      */// 50: invokevirtual 71 java/lang/StringBuffer:append
				// (Ljava/lang/String;)Ljava/lang/StringBuffer;
		/*      */// 53: aload_0
		/*      */// 54: getfield 41 com/claro/dao/AlianzasDAO:schema_database
				// Ljava/lang/String;
		/*      */// 57: invokevirtual 71 java/lang/StringBuffer:append
				// (Ljava/lang/String;)Ljava/lang/StringBuffer;
		/*      */// 60: ldc_w 659
		/*      */// 63: invokevirtual 71 java/lang/StringBuffer:append
				// (Ljava/lang/String;)Ljava/lang/StringBuffer;
		/*      */// 66: pop
		/*      */// 67: aload 7
		/*      */// 69: ldc_w 713
		/*      */// 72: invokevirtual 71 java/lang/StringBuffer:append
				// (Ljava/lang/String;)Ljava/lang/StringBuffer;
		/*      */// 75: pop
		/*      */// 76: aload 7
		/*      */// 78: ldc_w 715
		/*      */// 81: invokevirtual 71 java/lang/StringBuffer:append
				// (Ljava/lang/String;)Ljava/lang/StringBuffer;
		/*      */// 84: pop
		/*      */// 85: aload 7
		/*      */// 87: ldc_w 717
		/*      */// 90: invokevirtual 71 java/lang/StringBuffer:append
				// (Ljava/lang/String;)Ljava/lang/StringBuffer;
		/*      */// 93: pop
		/*      */// 94: aload 4
		/*      */// 96: aload 7
		/*      */// 98: invokevirtual 100 java/lang/StringBuffer:toString
				// ()Ljava/lang/String;
		/*      */// 101: invokeinterface 104 2 0
		/*      */// 106: astore 5
		/*      */// 108: aload 5
		/*      */// 110: iconst_1
		/*      */// 111: aload_2
		/*      */// 112: invokeinterface 110 3 0
		/*      */// 117: aload 5
		/*      */// 119: iconst_2
		/*      */// 120: iload_3
		/*      */// 121: invokeinterface 122 3 0
		/*      */// 126: aload 5
		/*      */// 128: invokeinterface 466 1 0
		/*      */// 133: ifle +15 -> 148
		/*      */// 136: aload 6
		/*      */// 138: iconst_0
		/*      */// 139: ldc_w 683
		/*      */// 142: invokevirtual 685
				// com/claro/transfer/MensajeTO:agregaMensaje
				// (ILjava/lang/String;)V
		/*      */// 145: goto +168 -> 313
		/*      */// 148: aload 6
		/*      */// 150: iconst_m1
		/*      */// 151: ldc_w 719
		/*      */// 154: invokevirtual 685
				// com/claro/transfer/MensajeTO:agregaMensaje
				// (ILjava/lang/String;)V
		/*      */// 157: goto +156 -> 313
		/*      */// 160: astore 7
		/*      */// 162: aload_0
		/*      */// 163: getfield 27 com/claro/dao/AlianzasDAO:error
				// Lorg/apache/log4j/Logger;
		/*      */// 166: ldc_w 721
		/*      */// 169: aload 7
		/*      */// 171: invokevirtual 393 org/apache/log4j/Logger:info
				// (Ljava/lang/Object;Ljava/lang/Throwable;)V
		/*      */// 174: new 59 com/claro/exception/CAException
		/*      */// 177: dup
		/*      */// 178: iconst_m1
		/*      */// 179: new 293 java/lang/StringBuilder
		/*      */// 182: dup
		/*      */// 183: ldc_w 723
		/*      */// 186: invokespecial 297 java/lang/StringBuilder:<init>
				// (Ljava/lang/String;)V
		/*      */// 189: aload 7
		/*      */// 191: invokevirtual 491 java/sql/SQLException:toString
				// ()Ljava/lang/String;
		/*      */// 194: invokevirtual 300 java/lang/StringBuilder:append
				// (Ljava/lang/String;)Ljava/lang/StringBuilder;
		/*      */// 197: ldc_w 303
		/*      */// 200: invokevirtual 300 java/lang/StringBuilder:append
				// (Ljava/lang/String;)Ljava/lang/StringBuilder;
		/*      */// 203: invokevirtual 305 java/lang/StringBuilder:toString
				// ()Ljava/lang/String;
		/*      */// 206: aload 7
		/*      */// 208: invokespecial 222 com/claro/exception/CAException:<init>
				// (ILjava/lang/String;Ljava/lang/Exception;)V
		/*      */// 211: athrow
		/*      */// 212: astore 7
		/*      */// 214: aload_0
		/*      */// 215: getfield 27 com/claro/dao/AlianzasDAO:error
				// Lorg/apache/log4j/Logger;
		/*      */// 218: ldc_w 725
		/*      */// 221: aload 7
		/*      */// 223: invokevirtual 393 org/apache/log4j/Logger:info
				// (Ljava/lang/Object;Ljava/lang/Throwable;)V
		/*      */// 226: new 59 com/claro/exception/CAException
		/*      */// 229: dup
		/*      */// 230: iconst_m1
		/*      */// 231: new 293 java/lang/StringBuilder
		/*      */// 234: dup
		/*      */// 235: ldc_w 723
		/*      */// 238: invokespecial 297 java/lang/StringBuilder:<init>
				// (Ljava/lang/String;)V
		/*      */// 241: aload 7
		/*      */// 243: invokevirtual 299 java/lang/Exception:toString
				// ()Ljava/lang/String;
		/*      */// 246: invokevirtual 300 java/lang/StringBuilder:append
				// (Ljava/lang/String;)Ljava/lang/StringBuilder;
		/*      */// 249: ldc_w 303
		/*      */// 252: invokevirtual 300 java/lang/StringBuilder:append
				// (Ljava/lang/String;)Ljava/lang/StringBuilder;
		/*      */// 255: invokevirtual 305 java/lang/StringBuilder:toString
				// ()Ljava/lang/String;
		/*      */// 258: aload 7
		/*      */// 260: invokespecial 222 com/claro/exception/CAException:<init>
				// (ILjava/lang/String;Ljava/lang/Exception;)V
		/*      */// 263: athrow
		/*      */// 264: astore 8
		/*      */// 266: aload 5
		/*      */// 268: ifnull +18 -> 286
		/*      */// 271: aload 5
		/*      */// 273: invokeinterface 232 1 0
		/*      */// 278: aconst_null
		/*      */// 279: astore 5
		/*      */// 281: goto +5 -> 286
		/*      */// 284: astore 9
		/*      */// 286: aload_1
		/*      */// 287: ifnonnull +23 -> 310
		/*      */// 290: aload 4
		/*      */// 292: ifnull +18 -> 310
		/*      */// 295: aload 4
		/*      */// 297: invokeinterface 233 1 0
		/*      */// 302: aconst_null
		/*      */// 303: astore 4
		/*      */// 305: goto +5 -> 310
		/*      */// 308: astore 9
		/*      */// 310: aload 8
		/*      */// 312: athrow
		/*      */// 313: aload 5
		/*      */// 315: ifnull +18 -> 333
		/*      */// 318: aload 5
		/*      */// 320: invokeinterface 232 1 0
		/*      */// 325: aconst_null
		/*      */// 326: astore 5
		/*      */// 328: goto +5 -> 333
		/*      */// 331: astore 9
		/*      */// 333: aload_1
		/*      */// 334: ifnonnull +23 -> 357
		/*      */// 337: aload 4
		/*      */// 339: ifnull +18 -> 357
		/*      */// 342: aload 4
		/*      */// 344: invokeinterface 233 1 0
		/*      */// 349: aconst_null
		/*      */// 350: astore 4
		/*      */// 352: goto +5 -> 357
		/*      */// 355: astore 9
		/*      */// 357: aload 6
		/*      */// 359: areturn
		/*      */// Line number table:
		/*      */// Java source line #522 -> byte code offset #0
		/*      */// Java source line #523 -> byte code offset #3
		/*      */// Java source line #524 -> byte code offset #6
		/*      */// Java source line #527 -> byte code offset #15
		/*      */// Java source line #528 -> byte code offset #33
		/*      */// Java source line #530 -> byte code offset #36
		/*      */// Java source line #532 -> byte code offset #45
		/*      */// Java source line #533 -> byte code offset #67
		/*      */// Java source line #534 -> byte code offset #76
		/*      */// Java source line #535 -> byte code offset #85
		/*      */// Java source line #537 -> byte code offset #94
		/*      */// Java source line #539 -> byte code offset #108
		/*      */// Java source line #540 -> byte code offset #117
		/*      */// Java source line #542 -> byte code offset #126
		/*      */// Java source line #543 -> byte code offset #136
		/*      */// Java source line #544 -> byte code offset #148
		/*      */// Java source line #546 -> byte code offset #160
		/*      */// Java source line #547 -> byte code offset #162
		/*      */// Java source line #548 -> byte code offset #174
		/*      */// Java source line #549 -> byte code offset #212
		/*      */// Java source line #550 -> byte code offset #214
		/*      */// Java source line #551 -> byte code offset #226
		/*      */// Java source line #552 -> byte code offset #264
		/*      */// Java source line #553 -> byte code offset #266
		/*      */// Java source line #554 -> byte code offset #286
		/*      */// Java source line #555 -> byte code offset #310
		/*      */// Java source line #553 -> byte code offset #313
		/*      */// Java source line #554 -> byte code offset #333
		/*      */// Java source line #556 -> byte code offset #357
		/*      */// Local variable table:
		/*      */// start length slot name signature
		/*      */// 0 360 0 this AlianzasDAO
		/*      */// 0 360 1 connection Connection
		/*      */// 0 360 2 sCuentaAl String
		/*      */// 0 360 3 iCveAl int
		/*      */// 1 350 4 lConn Connection
		/*      */// 4 323 5 statement PreparedStatement
		/*      */// 13 345 6 mensajeTO MensajeTO
		/*      */// 43 54 7 sUpdate StringBuffer
		/*      */// 160 47 7 e SQLException
		/*      */// 212 47 7 e Exception
		/*      */// 264 47 8 localObject Object
		/*      */// 284 1 9 localException1 Exception
		/*      */// 308 1 9 localException2 Exception
		/*      */// 331 1 9 localException3 Exception
		/*      */// 355 1 9 localException4 Exception
		/*      */// Exception table:
		/*      */// from to target type
		/*      */// 15 157 160 java/sql/SQLException
		/*      */// 15 157 212 java/lang/Exception
		/*      */// 15 264 264 finally
		/*      */// 271 281 284 java/lang/Exception
		/*      */// 295 305 308 java/lang/Exception
		/*      */// 318 328 331 java/lang/Exception
		/*      */// 342 352 355 java/lang/Exception
		/*      */}

	/*      */
	/*      *//* Error */
	/*      */public MensajeTO cancelaAlianza(String sCuenta, String sCuentaAl,
			int iCveAl)
	/*      */throws CAException
	/*      */{
		return null;
		/*      */// Byte code:
		/*      */// 0: aconst_null
		/*      */// 1: astore 4
		/*      */// 3: aconst_null
		/*      */// 4: astore 5
		/*      */// 6: aconst_null
		/*      */// 7: astore 6
		/*      */// 9: aconst_null
		/*      */// 10: astore 7
		/*      */// 12: iconst_0
		/*      */// 13: istore 8
		/*      */// 15: new 63 java/util/ArrayList
		/*      */// 18: dup
		/*      */// 19: invokespecial 65 java/util/ArrayList:<init> ()V
		/*      */// 22: astore 9
		/*      */// 24: new 66 java/lang/StringBuffer
		/*      */// 27: dup
		/*      */// 28: invokespecial 68 java/lang/StringBuffer:<init> ()V
		/*      */// 31: astore 10
		/*      */// 33: aload 10
		/*      */// 35: ldc_w 729
		/*      */// 38: invokevirtual 71 java/lang/StringBuffer:append
				// (Ljava/lang/String;)Ljava/lang/StringBuffer;
		/*      */// 41: pop
		/*      */// 42: aload 10
		/*      */// 44: ldc_w 731
		/*      */// 47: invokevirtual 71 java/lang/StringBuffer:append
				// (Ljava/lang/String;)Ljava/lang/StringBuffer;
		/*      */// 50: aload_0
		/*      */// 51: getfield 41 com/claro/dao/AlianzasDAO:schema_database
				// Ljava/lang/String;
		/*      */// 54: invokevirtual 71 java/lang/StringBuffer:append
				// (Ljava/lang/String;)Ljava/lang/StringBuffer;
		/*      */// 57: ldc_w 557
		/*      */// 60: invokevirtual 71 java/lang/StringBuffer:append
				// (Ljava/lang/String;)Ljava/lang/StringBuffer;
		/*      */// 63: pop
		/*      */// 64: aload 10
		/*      */// 66: ldc_w 733
		/*      */// 69: invokevirtual 71 java/lang/StringBuffer:append
				// (Ljava/lang/String;)Ljava/lang/StringBuffer;
		/*      */// 72: pop
		/*      */// 73: aload 10
		/*      */// 75: ldc_w 735
		/*      */// 78: invokevirtual 71 java/lang/StringBuffer:append
				// (Ljava/lang/String;)Ljava/lang/StringBuffer;
		/*      */// 81: pop
		/*      */// 82: invokestatic 29 com/claro/util/ServiceLocator:getInstance
				// ()Lcom/claro/util/ServiceLocator;
		/*      */// 85: getstatic 93 com/claro/util/ServiceLocator:jdbcCirculoAzul
				// Ljava/lang/String;
		/*      */// 88: invokevirtual 96 com/claro/util/ServiceLocator:getConnection
				// (Ljava/lang/String;)Ljava/sql/Connection;
		/*      */// 91: astore 5
		/*      */// 93: aload 5
		/*      */// 95: aload 10
		/*      */// 97: invokevirtual 100 java/lang/StringBuffer:toString
				// ()Ljava/lang/String;
		/*      */// 100: sipush 1004
		/*      */// 103: sipush 1007
		/*      */// 106: invokeinterface 737 4 0
		/*      */// 111: astore 6
		/*      */// 113: aload 6
		/*      */// 115: iconst_1
		/*      */// 116: aload_2
		/*      */// 117: invokeinterface 110 3 0
		/*      */// 122: aload 6
		/*      */// 124: invokeinterface 126 1 0
		/*      */// 129: astore 7
		/*      */// 131: aload 7
		/*      */// 133: invokeinterface 216 1 0
		/*      */// 138: ifeq +335 -> 473
		/*      */// 141: aload 7
		/*      */// 143: invokeinterface 740 1 0
		/*      */// 148: goto +80 -> 228
		/*      */// 151: aload 7
		/*      */// 153: iconst_1
		/*      */// 154: invokeinterface 371 2 0
		/*      */// 159: invokevirtual 743 java/lang/String:trim
				// ()Ljava/lang/String;
		/*      */// 162: aload_1
		/*      */// 163: invokevirtual 743 java/lang/String:trim
				// ()Ljava/lang/String;
		/*      */// 166: invokevirtual 746 java/lang/String:equals
				// (Ljava/lang/Object;)Z
		/*      */// 169: ifeq +26 -> 195
		/*      */// 172: aload 7
		/*      */// 174: iconst_2
		/*      */// 175: invokeinterface 371 2 0
		/*      */// 180: ldc_w 749
		/*      */// 183: invokevirtual 746 java/lang/String:equals
				// (Ljava/lang/Object;)Z
		/*      */// 186: ifeq +9 -> 195
		/*      */// 189: iconst_1
		/*      */// 190: istore 8
		/*      */// 192: goto +46 -> 238
		/*      */// 195: aload 7
		/*      */// 197: iconst_2
		/*      */// 198: invokeinterface 371 2 0
		/*      */// 203: ldc_w 749
		/*      */// 206: invokevirtual 746 java/lang/String:equals
				// (Ljava/lang/Object;)Z
		/*      */// 209: ifeq +19 -> 228
		/*      */// 212: aload 9
		/*      */// 214: aload 7
		/*      */// 216: iconst_1
		/*      */// 217: invokeinterface 371 2 0
		/*      */// 222: invokeinterface 751 2 0
		/*      */// 227: pop
		/*      */// 228: aload 7
		/*      */// 230: invokeinterface 216 1 0
		/*      */// 235: ifne -84 -> 151
		/*      */// 238: new 605 com/claro/transfer/MensajeTO
		/*      */// 241: dup
		/*      */// 242: invokespecial 628 com/claro/transfer/MensajeTO:<init> ()V
		/*      */// 245: astore 4
		/*      */// 247: iload 8
		/*      */// 249: ifeq +15 -> 264
		/*      */// 252: aload 4
		/*      */// 254: iconst_2
		/*      */// 255: ldc_w 754
		/*      */// 258: invokevirtual 685
				// com/claro/transfer/MensajeTO:agregaMensaje
				// (ILjava/lang/String;)V
		/*      */// 261: goto +379 -> 640
		/*      */// 264: aload 9
		/*      */// 266: invokeinterface 756 1 0
		/*      */// 271: ifle +190 -> 461
		/*      */// 274: aload 9
		/*      */// 276: invokeinterface 756 1 0
		/*      */// 281: iconst_1
		/*      */// 282: if_icmpne +51 -> 333
		/*      */// 285: aload 4
		/*      */// 287: iconst_2
		/*      */// 288: new 293 java/lang/StringBuilder
		/*      */// 291: dup
		/*      */// 292: ldc_w 757
		/*      */// 295: invokespecial 297 java/lang/StringBuilder:<init>
				// (Ljava/lang/String;)V
		/*      */// 298: aload 9
		/*      */// 300: iconst_0
		/*      */// 301: invokeinterface 759 2 0
		/*      */// 306: checkcast 260 java/lang/String
		/*      */// 309: invokevirtual 300 java/lang/StringBuilder:append
				// (Ljava/lang/String;)Ljava/lang/StringBuilder;
		/*      */// 312: ldc_w 763
		/*      */// 315: invokevirtual 300 java/lang/StringBuilder:append
				// (Ljava/lang/String;)Ljava/lang/StringBuilder;
		/*      */// 318: ldc_w 765
		/*      */// 321: invokevirtual 300 java/lang/StringBuilder:append
				// (Ljava/lang/String;)Ljava/lang/StringBuilder;
		/*      */// 324: invokevirtual 305 java/lang/StringBuilder:toString
				// ()Ljava/lang/String;
		/*      */// 327: invokevirtual 685
				// com/claro/transfer/MensajeTO:agregaMensaje
				// (ILjava/lang/String;)V
		/*      */// 330: goto +310 -> 640
		/*      */// 333: ldc_w 767
		/*      */// 336: astore 11
		/*      */// 338: iconst_0
		/*      */// 339: istore 12
		/*      */// 341: goto +44 -> 385
		/*      */// 344: new 293 java/lang/StringBuilder
		/*      */// 347: dup
		/*      */// 348: aload 11
		/*      */// 350: invokestatic 322 java/lang/String:valueOf
				// (Ljava/lang/Object;)Ljava/lang/String;
		/*      */// 353: invokespecial 297 java/lang/StringBuilder:<init>
				// (Ljava/lang/String;)V
		/*      */// 356: aload 9
		/*      */// 358: iload 12
		/*      */// 360: invokeinterface 759 2 0
		/*      */// 365: checkcast 260 java/lang/String
		/*      */// 368: invokevirtual 300 java/lang/StringBuilder:append
				// (Ljava/lang/String;)Ljava/lang/StringBuilder;
		/*      */// 371: ldc_w 769
		/*      */// 374: invokevirtual 300 java/lang/StringBuilder:append
				// (Ljava/lang/String;)Ljava/lang/StringBuilder;
		/*      */// 377: invokevirtual 305 java/lang/StringBuilder:toString
				// ()Ljava/lang/String;
		/*      */// 380: astore 11
		/*      */// 382: iinc 12 1
		/*      */// 385: iload 12
		/*      */// 387: aload 9
		/*      */// 389: invokeinterface 756 1 0
		/*      */// 394: iconst_1
		/*      */// 395: isub
		/*      */// 396: if_icmplt -52 -> 344
		/*      */// 399: new 293 java/lang/StringBuilder
		/*      */// 402: dup
		/*      */// 403: aload 11
		/*      */// 405: invokestatic 322 java/lang/String:valueOf
				// (Ljava/lang/Object;)Ljava/lang/String;
		/*      */// 408: invokespecial 297 java/lang/StringBuilder:<init>
				// (Ljava/lang/String;)V
		/*      */// 411: aload 9
		/*      */// 413: aload 9
		/*      */// 415: invokeinterface 756 1 0
		/*      */// 420: iconst_1
		/*      */// 421: isub
		/*      */// 422: invokeinterface 759 2 0
		/*      */// 427: checkcast 260 java/lang/String
		/*      */// 430: invokevirtual 300 java/lang/StringBuilder:append
				// (Ljava/lang/String;)Ljava/lang/StringBuilder;
		/*      */// 433: ldc_w 771
		/*      */// 436: invokevirtual 300 java/lang/StringBuilder:append
				// (Ljava/lang/String;)Ljava/lang/StringBuilder;
		/*      */// 439: ldc_w 773
		/*      */// 442: invokevirtual 300 java/lang/StringBuilder:append
				// (Ljava/lang/String;)Ljava/lang/StringBuilder;
		/*      */// 445: invokevirtual 305 java/lang/StringBuilder:toString
				// ()Ljava/lang/String;
		/*      */// 448: astore 11
		/*      */// 450: aload 4
		/*      */// 452: iconst_2
		/*      */// 453: aload 11
		/*      */// 455: invokevirtual 685
				// com/claro/transfer/MensajeTO:agregaMensaje
				// (ILjava/lang/String;)V
		/*      */// 458: goto +182 -> 640
		/*      */// 461: aload 4
		/*      */// 463: iconst_2
		/*      */// 464: ldc_w 775
		/*      */// 467: invokevirtual 685
				// com/claro/transfer/MensajeTO:agregaMensaje
				// (ILjava/lang/String;)V
		/*      */// 470: goto +170 -> 640
		/*      */// 473: aload_0
		/*      */// 474: aload 5
		/*      */// 476: aload_2
		/*      */// 477: iload_3
		/*      */// 478: invokespecial 777
				// com/claro/dao/AlianzasDAO:inhabilitaAlianza
				// (Ljava/sql/Connection;Ljava/lang/String;I)Lcom/claro/transfer/MensajeTO;
		/*      */// 481: astore 4
		/*      */// 483: aload 4
		/*      */// 485: invokevirtual 604 com/claro/transfer/MensajeTO:getIdMensaje
				// ()I
		/*      */// 488: ifeq +13 -> 501
		/*      */// 491: aload 5
		/*      */// 493: invokeinterface 486 1 0
		/*      */// 498: goto +142 -> 640
		/*      */// 501: aload 5
		/*      */// 503: invokeinterface 479 1 0
		/*      */// 508: goto +132 -> 640
		/*      */// 511: astore 11
		/*      */// 513: aload_0
		/*      */// 514: getfield 27 com/claro/dao/AlianzasDAO:error
				// Lorg/apache/log4j/Logger;
		/*      */// 517: ldc_w 779
		/*      */// 520: aload 11
		/*      */// 522: invokevirtual 393 org/apache/log4j/Logger:info
				// (Ljava/lang/Object;Ljava/lang/Throwable;)V
		/*      */// 525: new 59 com/claro/exception/CAException
		/*      */// 528: dup
		/*      */// 529: iconst_m1
		/*      */// 530: new 293 java/lang/StringBuilder
		/*      */// 533: dup
		/*      */// 534: ldc_w 781
		/*      */// 537: invokespecial 297 java/lang/StringBuilder:<init>
				// (Ljava/lang/String;)V
		/*      */// 540: aload 11
		/*      */// 542: invokevirtual 491 java/sql/SQLException:toString
				// ()Ljava/lang/String;
		/*      */// 545: invokevirtual 300 java/lang/StringBuilder:append
				// (Ljava/lang/String;)Ljava/lang/StringBuilder;
		/*      */// 548: ldc_w 303
		/*      */// 551: invokevirtual 300 java/lang/StringBuilder:append
				// (Ljava/lang/String;)Ljava/lang/StringBuilder;
		/*      */// 554: invokevirtual 305 java/lang/StringBuilder:toString
				// ()Ljava/lang/String;
		/*      */// 557: aload 11
		/*      */// 559: invokespecial 222 com/claro/exception/CAException:<init>
				// (ILjava/lang/String;Ljava/lang/Exception;)V
		/*      */// 562: athrow
		/*      */// 563: astore 11
		/*      */// 565: aload_0
		/*      */// 566: getfield 27 com/claro/dao/AlianzasDAO:error
				// Lorg/apache/log4j/Logger;
		/*      */// 569: ldc_w 783
		/*      */// 572: aload 11
		/*      */// 574: invokevirtual 393 org/apache/log4j/Logger:info
				// (Ljava/lang/Object;Ljava/lang/Throwable;)V
		/*      */// 577: new 59 com/claro/exception/CAException
		/*      */// 580: dup
		/*      */// 581: iconst_m1
		/*      */// 582: new 293 java/lang/StringBuilder
		/*      */// 585: dup
		/*      */// 586: ldc_w 785
		/*      */// 589: invokespecial 297 java/lang/StringBuilder:<init>
				// (Ljava/lang/String;)V
		/*      */// 592: aload 11
		/*      */// 594: invokevirtual 299 java/lang/Exception:toString
				// ()Ljava/lang/String;
		/*      */// 597: invokevirtual 300 java/lang/StringBuilder:append
				// (Ljava/lang/String;)Ljava/lang/StringBuilder;
		/*      */// 600: ldc_w 303
		/*      */// 603: invokevirtual 300 java/lang/StringBuilder:append
				// (Ljava/lang/String;)Ljava/lang/StringBuilder;
		/*      */// 606: invokevirtual 305 java/lang/StringBuilder:toString
				// ()Ljava/lang/String;
		/*      */// 609: aload 11
		/*      */// 611: invokespecial 222 com/claro/exception/CAException:<init>
				// (ILjava/lang/String;Ljava/lang/Exception;)V
		/*      */// 614: athrow
		/*      */// 615: astore 13
		/*      */// 617: aload 5
		/*      */// 619: ifnull +18 -> 637
		/*      */// 622: aload 5
		/*      */// 624: invokeinterface 233 1 0
		/*      */// 629: aconst_null
		/*      */// 630: astore 5
		/*      */// 632: goto +5 -> 637
		/*      */// 635: astore 14
		/*      */// 637: aload 13
		/*      */// 639: athrow
		/*      */// 640: aload 5
		/*      */// 642: ifnull +18 -> 660
		/*      */// 645: aload 5
		/*      */// 647: invokeinterface 233 1 0
		/*      */// 652: aconst_null
		/*      */// 653: astore 5
		/*      */// 655: goto +5 -> 660
		/*      */// 658: astore 14
		/*      */// 660: aload 4
		/*      */// 662: areturn
		/*      */// Line number table:
		/*      */// Java source line #560 -> byte code offset #0
		/*      */// Java source line #561 -> byte code offset #3
		/*      */// Java source line #562 -> byte code offset #6
		/*      */// Java source line #563 -> byte code offset #9
		/*      */// Java source line #564 -> byte code offset #12
		/*      */// Java source line #567 -> byte code offset #15
		/*      */// Java source line #569 -> byte code offset #24
		/*      */// Java source line #571 -> byte code offset #33
		/*      */// Java source line #572 -> byte code offset #42
		/*      */// Java source line #573 -> byte code offset #64
		/*      */// Java source line #574 -> byte code offset #73
		/*      */// Java source line #577 -> byte code offset #82
		/*      */// Java source line #578 -> byte code offset #93
		/*      */// Java source line #580 -> byte code offset #113
		/*      */// Java source line #583 -> byte code offset #122
		/*      */// Java source line #585 -> byte code offset #131
		/*      */// Java source line #586 -> byte code offset #141
		/*      */// Java source line #587 -> byte code offset #148
		/*      */// Java source line #588 -> byte code offset #151
		/*      */// Java source line #589 -> byte code offset #189
		/*      */// Java source line #590 -> byte code offset #192
		/*      */// Java source line #592 -> byte code offset #195
		/*      */// Java source line #593 -> byte code offset #212
		/*      */// Java source line #587 -> byte code offset #228
		/*      */// Java source line #597 -> byte code offset #238
		/*      */// Java source line #598 -> byte code offset #247
		/*      */// Java source line #599 -> byte code offset #252
		/*      */// Java source line #600 -> byte code offset #264
		/*      */// Java source line #601 -> byte code offset #274
		/*      */// Java source line #602 -> byte code offset #285
		/*      */// Java source line #603 -> byte code offset #318
		/*      */// Java source line #602 -> byte code offset #327
		/*      */// Java source line #605 -> byte code offset #333
		/*      */// Java source line #606 -> byte code offset #338
		/*      */// Java source line #607 -> byte code offset #344
		/*      */// Java source line #606 -> byte code offset #382
		/*      */// Java source line #609 -> byte code offset #399
		/*      */// Java source line #610 -> byte code offset #439
		/*      */// Java source line #609 -> byte code offset #445
		/*      */// Java source line #611 -> byte code offset #450
		/*      */// Java source line #614 -> byte code offset #461
		/*      */// Java source line #619 -> byte code offset #473
		/*      */// Java source line #620 -> byte code offset #483
		/*      */// Java source line #621 -> byte code offset #491
		/*      */// Java source line #622 -> byte code offset #501
		/*      */// Java source line #625 -> byte code offset #511
		/*      */// Java source line #626 -> byte code offset #513
		/*      */// Java source line #627 -> byte code offset #525
		/*      */// Java source line #628 -> byte code offset #563
		/*      */// Java source line #629 -> byte code offset #565
		/*      */// Java source line #630 -> byte code offset #577
		/*      */// Java source line #631 -> byte code offset #615
		/*      */// Java source line #632 -> byte code offset #617
		/*      */// Java source line #633 -> byte code offset #637
		/*      */// Java source line #632 -> byte code offset #640
		/*      */// Java source line #634 -> byte code offset #660
		/*      */// Local variable table:
		/*      */// start length slot name signature
		/*      */// 0 663 0 this AlianzasDAO
		/*      */// 0 663 1 sCuenta String
		/*      */// 0 663 2 sCuentaAl String
		/*      */// 0 663 3 iCveAl int
		/*      */// 1 660 4 mensajeTO MensajeTO
		/*      */// 4 650 5 connection Connection
		/*      */// 7 116 6 statement PreparedStatement
		/*      */// 10 219 7 resultSet ResultSet
		/*      */// 13 235 8 valor boolean
		/*      */// 22 392 9 canjesPend java.util.List<String>
		/*      */// 31 65 10 sQuery StringBuffer
		/*      */// 336 118 11 sCad String
		/*      */// 511 47 11 e SQLException
		/*      */// 563 47 11 e Exception
		/*      */// 339 47 12 i int
		/*      */// 615 23 13 localObject Object
		/*      */// 635 1 14 localException1 Exception
		/*      */// 658 1 14 localException2 Exception
		/*      */// Exception table:
		/*      */// from to target type
		/*      */// 82 508 511 java/sql/SQLException
		/*      */// 82 508 563 java/lang/Exception
		/*      */// 82 615 615 finally
		/*      */// 622 632 635 java/lang/Exception
		/*      */// 645 655 658 java/lang/Exception
		/*      */}

	/*      */
	/*      *//* Error */
	/*      */public MensajeTO actualizaDatos(String sCuentaAl, int iCveAl,
			String sCuenta, int iSecuencia, String sNombre, String sApePat,
			String sApeMat)
	/*      */throws Exception
	/*      */{
		return null;
		/*      */// Byte code:
		/*      */// 0: aconst_null
		/*      */// 1: astore 8
		/*      */// 3: aconst_null
		/*      */// 4: astore 9
		/*      */// 6: aconst_null
		/*      */// 7: astore 10
		/*      */// 9: aconst_null
		/*      */// 10: astore 11
		/*      */// 12: new 66 java/lang/StringBuffer
		/*      */// 15: dup
		/*      */// 16: invokespecial 68 java/lang/StringBuffer:<init> ()V
		/*      */// 19: astore 12
		/*      */// 21: aload 12
		/*      */// 23: ldc_w 729
		/*      */// 26: invokevirtual 71 java/lang/StringBuffer:append
				// (Ljava/lang/String;)Ljava/lang/StringBuffer;
		/*      */// 29: pop
		/*      */// 30: aload 12
		/*      */// 32: ldc_w 731
		/*      */// 35: invokevirtual 71 java/lang/StringBuffer:append
				// (Ljava/lang/String;)Ljava/lang/StringBuffer;
		/*      */// 38: aload_0
		/*      */// 39: getfield 41 com/claro/dao/AlianzasDAO:schema_database
				// Ljava/lang/String;
		/*      */// 42: invokevirtual 71 java/lang/StringBuffer:append
				// (Ljava/lang/String;)Ljava/lang/StringBuffer;
		/*      */// 45: ldc_w 557
		/*      */// 48: invokevirtual 71 java/lang/StringBuffer:append
				// (Ljava/lang/String;)Ljava/lang/StringBuffer;
		/*      */// 51: pop
		/*      */// 52: aload 12
		/*      */// 54: ldc_w 733
		/*      */// 57: invokevirtual 71 java/lang/StringBuffer:append
				// (Ljava/lang/String;)Ljava/lang/StringBuffer;
		/*      */// 60: pop
		/*      */// 61: aload 12
		/*      */// 63: ldc_w 795
		/*      */// 66: invokevirtual 71 java/lang/StringBuffer:append
				// (Ljava/lang/String;)Ljava/lang/StringBuffer;
		/*      */// 69: pop
		/*      */// 70: invokestatic 29 com/claro/util/ServiceLocator:getInstance
				// ()Lcom/claro/util/ServiceLocator;
		/*      */// 73: getstatic 93 com/claro/util/ServiceLocator:jdbcCirculoAzul
				// Ljava/lang/String;
		/*      */// 76: invokevirtual 96 com/claro/util/ServiceLocator:getConnection
				// (Ljava/lang/String;)Ljava/sql/Connection;
		/*      */// 79: astore 9
		/*      */// 81: aload 9
		/*      */// 83: aload 12
		/*      */// 85: invokevirtual 100 java/lang/StringBuffer:toString
				// ()Ljava/lang/String;
		/*      */// 88: invokeinterface 104 2 0
		/*      */// 93: astore 10
		/*      */// 95: aload 10
		/*      */// 97: iconst_1
		/*      */// 98: aload_1
		/*      */// 99: invokeinterface 110 3 0
		/*      */// 104: aload 10
		/*      */// 106: invokeinterface 126 1 0
		/*      */// 111: astore 11
		/*      */// 113: aload 11
		/*      */// 115: invokeinterface 216 1 0
		/*      */// 120: ifeq +15 -> 135
		/*      */// 123: aload 8
		/*      */// 125: iconst_2
		/*      */// 126: ldc_w 797
		/*      */// 129: invokevirtual 685
				// com/claro/transfer/MensajeTO:agregaMensaje
				// (ILjava/lang/String;)V
		/*      */// 132: goto +182 -> 314
		/*      */// 135: aload_0
		/*      */// 136: aload 9
		/*      */// 138: aconst_null
		/*      */// 139: aload_1
		/*      */// 140: iload_2
		/*      */// 141: aload_3
		/*      */// 142: iload 4
		/*      */// 144: aload 5
		/*      */// 146: aload 6
		/*      */// 148: aload 7
		/*      */// 150: aconst_null
		/*      */// 151: aconst_null
		/*      */// 152: invokespecial 600
				// com/claro/dao/AlianzasDAO:actualizaAlianza
				// (Ljava/sql/Connection;Ljava/lang/String;Ljava/lang/String;ILjava/lang/String;ILjava/lang/String;Ljava/lang/String;Ljava/lang/String;Ljava/lang/String;Ljava/lang/String;)Lcom/claro/transfer/MensajeTO;
		/*      */// 155: astore 8
		/*      */// 157: aload 8
		/*      */// 159: invokevirtual 604 com/claro/transfer/MensajeTO:getIdMensaje
				// ()I
		/*      */// 162: ifeq +13 -> 175
		/*      */// 165: aload 9
		/*      */// 167: invokeinterface 486 1 0
		/*      */// 172: goto +142 -> 314
		/*      */// 175: aload 9
		/*      */// 177: invokeinterface 479 1 0
		/*      */// 182: goto +132 -> 314
		/*      */// 185: astore 13
		/*      */// 187: aload_0
		/*      */// 188: getfield 27 com/claro/dao/AlianzasDAO:error
				// Lorg/apache/log4j/Logger;
		/*      */// 191: ldc_w 799
		/*      */// 194: aload 13
		/*      */// 196: invokevirtual 393 org/apache/log4j/Logger:info
				// (Ljava/lang/Object;Ljava/lang/Throwable;)V
		/*      */// 199: new 59 com/claro/exception/CAException
		/*      */// 202: dup
		/*      */// 203: iconst_m1
		/*      */// 204: new 293 java/lang/StringBuilder
		/*      */// 207: dup
		/*      */// 208: ldc_w 801
		/*      */// 211: invokespecial 297 java/lang/StringBuilder:<init>
				// (Ljava/lang/String;)V
		/*      */// 214: aload 13
		/*      */// 216: invokevirtual 491 java/sql/SQLException:toString
				// ()Ljava/lang/String;
		/*      */// 219: invokevirtual 300 java/lang/StringBuilder:append
				// (Ljava/lang/String;)Ljava/lang/StringBuilder;
		/*      */// 222: ldc_w 303
		/*      */// 225: invokevirtual 300 java/lang/StringBuilder:append
				// (Ljava/lang/String;)Ljava/lang/StringBuilder;
		/*      */// 228: invokevirtual 305 java/lang/StringBuilder:toString
				// ()Ljava/lang/String;
		/*      */// 231: aload 13
		/*      */// 233: invokespecial 222 com/claro/exception/CAException:<init>
				// (ILjava/lang/String;Ljava/lang/Exception;)V
		/*      */// 236: athrow
		/*      */// 237: astore 13
		/*      */// 239: aload_0
		/*      */// 240: getfield 27 com/claro/dao/AlianzasDAO:error
				// Lorg/apache/log4j/Logger;
		/*      */// 243: ldc_w 803
		/*      */// 246: aload 13
		/*      */// 248: invokevirtual 393 org/apache/log4j/Logger:info
				// (Ljava/lang/Object;Ljava/lang/Throwable;)V
		/*      */// 251: new 59 com/claro/exception/CAException
		/*      */// 254: dup
		/*      */// 255: iconst_m1
		/*      */// 256: new 293 java/lang/StringBuilder
		/*      */// 259: dup
		/*      */// 260: ldc_w 805
		/*      */// 263: invokespecial 297 java/lang/StringBuilder:<init>
				// (Ljava/lang/String;)V
		/*      */// 266: aload 13
		/*      */// 268: invokevirtual 299 java/lang/Exception:toString
				// ()Ljava/lang/String;
		/*      */// 271: invokevirtual 300 java/lang/StringBuilder:append
				// (Ljava/lang/String;)Ljava/lang/StringBuilder;
		/*      */// 274: ldc_w 303
		/*      */// 277: invokevirtual 300 java/lang/StringBuilder:append
				// (Ljava/lang/String;)Ljava/lang/StringBuilder;
		/*      */// 280: invokevirtual 305 java/lang/StringBuilder:toString
				// ()Ljava/lang/String;
		/*      */// 283: aload 13
		/*      */// 285: invokespecial 222 com/claro/exception/CAException:<init>
				// (ILjava/lang/String;Ljava/lang/Exception;)V
		/*      */// 288: athrow
		/*      */// 289: astore 14
		/*      */// 291: aload 9
		/*      */// 293: ifnull +18 -> 311
		/*      */// 296: aload 9
		/*      */// 298: invokeinterface 233 1 0
		/*      */// 303: aconst_null
		/*      */// 304: astore 9
		/*      */// 306: goto +5 -> 311
		/*      */// 309: astore 15
		/*      */// 311: aload 14
		/*      */// 313: athrow
		/*      */// 314: aload 9
		/*      */// 316: ifnull +18 -> 334
		/*      */// 319: aload 9
		/*      */// 321: invokeinterface 233 1 0
		/*      */// 326: aconst_null
		/*      */// 327: astore 9
		/*      */// 329: goto +5 -> 334
		/*      */// 332: astore 15
		/*      */// 334: aload 8
		/*      */// 336: areturn
		/*      */// Line number table:
		/*      */// Java source line #639 -> byte code offset #0
		/*      */// Java source line #640 -> byte code offset #3
		/*      */// Java source line #641 -> byte code offset #6
		/*      */// Java source line #642 -> byte code offset #9
		/*      */// Java source line #644 -> byte code offset #12
		/*      */// Java source line #646 -> byte code offset #21
		/*      */// Java source line #647 -> byte code offset #30
		/*      */// Java source line #648 -> byte code offset #52
		/*      */// Java source line #649 -> byte code offset #61
		/*      */// Java source line #652 -> byte code offset #70
		/*      */// Java source line #653 -> byte code offset #81
		/*      */// Java source line #655 -> byte code offset #95
		/*      */// Java source line #658 -> byte code offset #104
		/*      */// Java source line #660 -> byte code offset #113
		/*      */// Java source line #661 -> byte code offset #123
		/*      */// Java source line #663 -> byte code offset #135
		/*      */// Java source line #665 -> byte code offset #157
		/*      */// Java source line #666 -> byte code offset #165
		/*      */// Java source line #667 -> byte code offset #175
		/*      */// Java source line #669 -> byte code offset #185
		/*      */// Java source line #670 -> byte code offset #187
		/*      */// Java source line #671 -> byte code offset #199
		/*      */// Java source line #672 -> byte code offset #237
		/*      */// Java source line #673 -> byte code offset #239
		/*      */// Java source line #674 -> byte code offset #251
		/*      */// Java source line #675 -> byte code offset #289
		/*      */// Java source line #676 -> byte code offset #291
		/*      */// Java source line #677 -> byte code offset #311
		/*      */// Java source line #676 -> byte code offset #314
		/*      */// Java source line #678 -> byte code offset #334
		/*      */// Local variable table:
		/*      */// start length slot name signature
		/*      */// 0 337 0 this AlianzasDAO
		/*      */// 0 337 1 sCuentaAl String
		/*      */// 0 337 2 iCveAl int
		/*      */// 0 337 3 sCuenta String
		/*      */// 0 337 4 iSecuencia int
		/*      */// 0 337 5 sNombre String
		/*      */// 0 337 6 sApePat String
		/*      */// 0 337 7 sApeMat String
		/*      */// 1 334 8 mensajeTO MensajeTO
		/*      */// 4 324 9 connection Connection
		/*      */// 7 98 10 statement PreparedStatement
		/*      */// 10 104 11 resultSet ResultSet
		/*      */// 19 65 12 sQuery StringBuffer
		/*      */// 185 47 13 e SQLException
		/*      */// 237 47 13 e Exception
		/*      */// 289 23 14 localObject Object
		/*      */// 309 1 15 localException1 Exception
		/*      */// 332 1 15 localException2 Exception
		/*      */// Exception table:
		/*      */// from to target type
		/*      */// 70 182 185 java/sql/SQLException
		/*      */// 70 182 237 java/lang/Exception
		/*      */// 70 289 289 finally
		/*      */// 296 306 309 java/lang/Exception
		/*      */// 319 329 332 java/lang/Exception
		/*      */}

	/*      */
	/*      *//* Error */
	/*      */private MensajeTO actualizaConfCanjeAlianza(Connection connection,
			int lValViaje, String sFolio, int lNumAcomp, String lIdCanje)
	/*      */throws CAException
	/*      */{
		return null;
		/*      */// Byte code:
		/*      */// 0: aconst_null
		/*      */// 1: astore 6
		/*      */// 3: aconst_null
		/*      */// 4: astore 7
		/*      */// 6: new 605 com/claro/transfer/MensajeTO
		/*      */// 9: dup
		/*      */// 10: invokespecial 628 com/claro/transfer/MensajeTO:<init> ()V
		/*      */// 13: astore 8
		/*      */// 15: aload_1
		/*      */// 16: ifnonnull +17 -> 33
		/*      */// 19: invokestatic 29 com/claro/util/ServiceLocator:getInstance
				// ()Lcom/claro/util/ServiceLocator;
		/*      */// 22: getstatic 93 com/claro/util/ServiceLocator:jdbcCirculoAzul
				// Ljava/lang/String;
		/*      */// 25: invokevirtual 96 com/claro/util/ServiceLocator:getConnection
				// (Ljava/lang/String;)Ljava/sql/Connection;
		/*      */// 28: astore 6
		/*      */// 30: goto +6 -> 36
		/*      */// 33: aload_1
		/*      */// 34: astore 6
		/*      */// 36: new 293 java/lang/StringBuilder
		/*      */// 39: dup
		/*      */// 40: ldc_w 409
		/*      */// 43: invokespecial 297 java/lang/StringBuilder:<init>
				// (Ljava/lang/String;)V
		/*      */// 46: aload_0
		/*      */// 47: getfield 41 com/claro/dao/AlianzasDAO:schema_database
				// Ljava/lang/String;
		/*      */// 50: invokevirtual 300 java/lang/StringBuilder:append
				// (Ljava/lang/String;)Ljava/lang/StringBuilder;
		/*      */// 53: ldc_w 809
		/*      */// 56: invokevirtual 300 java/lang/StringBuilder:append
				// (Ljava/lang/String;)Ljava/lang/StringBuilder;
		/*      */// 59: ldc_w 811
		/*      */// 62: invokevirtual 300 java/lang/StringBuilder:append
				// (Ljava/lang/String;)Ljava/lang/StringBuilder;
		/*      */// 65: ldc_w 813
		/*      */// 68: invokevirtual 300 java/lang/StringBuilder:append
				// (Ljava/lang/String;)Ljava/lang/StringBuilder;
		/*      */// 71: invokevirtual 305 java/lang/StringBuilder:toString
				// ()Ljava/lang/String;
		/*      */// 74: astore 9
		/*      */// 76: aload 6
		/*      */// 78: aload 9
		/*      */// 80: invokeinterface 104 2 0
		/*      */// 85: astore 7
		/*      */// 87: aload 7
		/*      */// 89: iconst_1
		/*      */// 90: iload_2
		/*      */// 91: invokeinterface 122 3 0
		/*      */// 96: aload 7
		/*      */// 98: iconst_2
		/*      */// 99: aload_3
		/*      */// 100: invokeinterface 110 3 0
		/*      */// 105: aload 7
		/*      */// 107: iconst_3
		/*      */// 108: iload 4
		/*      */// 110: invokeinterface 122 3 0
		/*      */// 115: aload 7
		/*      */// 117: iconst_4
		/*      */// 118: aload 5
		/*      */// 120: invokeinterface 110 3 0
		/*      */// 125: aload 7
		/*      */// 127: invokeinterface 466 1 0
		/*      */// 132: ifle +15 -> 147
		/*      */// 135: aload 8
		/*      */// 137: iconst_0
		/*      */// 138: ldc_w 683
		/*      */// 141: invokevirtual 685
				// com/claro/transfer/MensajeTO:agregaMensaje
				// (ILjava/lang/String;)V
		/*      */// 144: goto +168 -> 312
		/*      */// 147: aload 8
		/*      */// 149: iconst_1
		/*      */// 150: ldc_w 815
		/*      */// 153: invokevirtual 685
				// com/claro/transfer/MensajeTO:agregaMensaje
				// (ILjava/lang/String;)V
		/*      */// 156: goto +156 -> 312
		/*      */// 159: astore 9
		/*      */// 161: aload_0
		/*      */// 162: getfield 27 com/claro/dao/AlianzasDAO:error
				// Lorg/apache/log4j/Logger;
		/*      */// 165: ldc_w 817
		/*      */// 168: aload 9
		/*      */// 170: invokevirtual 393 org/apache/log4j/Logger:info
				// (Ljava/lang/Object;Ljava/lang/Throwable;)V
		/*      */// 173: new 59 com/claro/exception/CAException
		/*      */// 176: dup
		/*      */// 177: iconst_m1
		/*      */// 178: new 293 java/lang/StringBuilder
		/*      */// 181: dup
		/*      */// 182: ldc_w 819
		/*      */// 185: invokespecial 297 java/lang/StringBuilder:<init>
				// (Ljava/lang/String;)V
		/*      */// 188: aload 9
		/*      */// 190: invokevirtual 491 java/sql/SQLException:toString
				// ()Ljava/lang/String;
		/*      */// 193: invokevirtual 300 java/lang/StringBuilder:append
				// (Ljava/lang/String;)Ljava/lang/StringBuilder;
		/*      */// 196: ldc_w 821
		/*      */// 199: invokevirtual 300 java/lang/StringBuilder:append
				// (Ljava/lang/String;)Ljava/lang/StringBuilder;
		/*      */// 202: invokevirtual 305 java/lang/StringBuilder:toString
				// ()Ljava/lang/String;
		/*      */// 205: aload 9
		/*      */// 207: invokespecial 222 com/claro/exception/CAException:<init>
				// (ILjava/lang/String;Ljava/lang/Exception;)V
		/*      */// 210: athrow
		/*      */// 211: astore 9
		/*      */// 213: aload_0
		/*      */// 214: getfield 27 com/claro/dao/AlianzasDAO:error
				// Lorg/apache/log4j/Logger;
		/*      */// 217: ldc_w 823
		/*      */// 220: aload 9
		/*      */// 222: invokevirtual 393 org/apache/log4j/Logger:info
				// (Ljava/lang/Object;Ljava/lang/Throwable;)V
		/*      */// 225: new 59 com/claro/exception/CAException
		/*      */// 228: dup
		/*      */// 229: iconst_m1
		/*      */// 230: new 293 java/lang/StringBuilder
		/*      */// 233: dup
		/*      */// 234: ldc_w 825
		/*      */// 237: invokespecial 297 java/lang/StringBuilder:<init>
				// (Ljava/lang/String;)V
		/*      */// 240: aload 9
		/*      */// 242: invokevirtual 299 java/lang/Exception:toString
				// ()Ljava/lang/String;
		/*      */// 245: invokevirtual 300 java/lang/StringBuilder:append
				// (Ljava/lang/String;)Ljava/lang/StringBuilder;
		/*      */// 248: ldc_w 821
		/*      */// 251: invokevirtual 300 java/lang/StringBuilder:append
				// (Ljava/lang/String;)Ljava/lang/StringBuilder;
		/*      */// 254: invokevirtual 305 java/lang/StringBuilder:toString
				// ()Ljava/lang/String;
		/*      */// 257: aload 9
		/*      */// 259: invokespecial 222 com/claro/exception/CAException:<init>
				// (ILjava/lang/String;Ljava/lang/Exception;)V
		/*      */// 262: athrow
		/*      */// 263: astore 10
		/*      */// 265: aload 7
		/*      */// 267: ifnull +18 -> 285
		/*      */// 270: aload 7
		/*      */// 272: invokeinterface 232 1 0
		/*      */// 277: aconst_null
		/*      */// 278: astore 7
		/*      */// 280: goto +5 -> 285
		/*      */// 283: astore 11
		/*      */// 285: aload_1
		/*      */// 286: ifnonnull +23 -> 309
		/*      */// 289: aload 6
		/*      */// 291: ifnull +18 -> 309
		/*      */// 294: aload 6
		/*      */// 296: invokeinterface 233 1 0
		/*      */// 301: aconst_null
		/*      */// 302: astore 6
		/*      */// 304: goto +5 -> 309
		/*      */// 307: astore 11
		/*      */// 309: aload 10
		/*      */// 311: athrow
		/*      */// 312: aload 7
		/*      */// 314: ifnull +18 -> 332
		/*      */// 317: aload 7
		/*      */// 319: invokeinterface 232 1 0
		/*      */// 324: aconst_null
		/*      */// 325: astore 7
		/*      */// 327: goto +5 -> 332
		/*      */// 330: astore 11
		/*      */// 332: aload_1
		/*      */// 333: ifnonnull +23 -> 356
		/*      */// 336: aload 6
		/*      */// 338: ifnull +18 -> 356
		/*      */// 341: aload 6
		/*      */// 343: invokeinterface 233 1 0
		/*      */// 348: aconst_null
		/*      */// 349: astore 6
		/*      */// 351: goto +5 -> 356
		/*      */// 354: astore 11
		/*      */// 356: aload 8
		/*      */// 358: areturn
		/*      */// Line number table:
		/*      */// Java source line #682 -> byte code offset #0
		/*      */// Java source line #683 -> byte code offset #3
		/*      */// Java source line #684 -> byte code offset #6
		/*      */// Java source line #687 -> byte code offset #15
		/*      */// Java source line #688 -> byte code offset #33
		/*      */// Java source line #690 -> byte code offset #36
		/*      */// Java source line #691 -> byte code offset #59
		/*      */// Java source line #692 -> byte code offset #65
		/*      */// Java source line #690 -> byte code offset #71
		/*      */// Java source line #694 -> byte code offset #76
		/*      */// Java source line #695 -> byte code offset #87
		/*      */// Java source line #696 -> byte code offset #96
		/*      */// Java source line #697 -> byte code offset #105
		/*      */// Java source line #698 -> byte code offset #115
		/*      */// Java source line #700 -> byte code offset #125
		/*      */// Java source line #701 -> byte code offset #147
		/*      */// Java source line #703 -> byte code offset #159
		/*      */// Java source line #704 -> byte code offset #161
		/*      */// Java source line #705 -> byte code offset #173
		/*      */// Java source line #706 -> byte code offset #211
		/*      */// Java source line #707 -> byte code offset #213
		/*      */// Java source line #708 -> byte code offset #225
		/*      */// Java source line #709 -> byte code offset #263
		/*      */// Java source line #710 -> byte code offset #265
		/*      */// Java source line #711 -> byte code offset #285
		/*      */// Java source line #712 -> byte code offset #309
		/*      */// Java source line #710 -> byte code offset #312
		/*      */// Java source line #711 -> byte code offset #332
		/*      */// Java source line #713 -> byte code offset #356
		/*      */// Local variable table:
		/*      */// start length slot name signature
		/*      */// 0 359 0 this AlianzasDAO
		/*      */// 0 359 1 connection Connection
		/*      */// 0 359 2 lValViaje int
		/*      */// 0 359 3 sFolio String
		/*      */// 0 359 4 lNumAcomp int
		/*      */// 0 359 5 lIdCanje String
		/*      */// 1 349 6 lConn Connection
		/*      */// 4 322 7 statement PreparedStatement
		/*      */// 13 344 8 mensajeTO MensajeTO
		/*      */// 74 5 9 queryUpdateAlianza String
		/*      */// 159 47 9 e SQLException
		/*      */// 211 47 9 e Exception
		/*      */// 263 47 10 localObject Object
		/*      */// 283 1 11 localException1 Exception
		/*      */// 307 1 11 localException2 Exception
		/*      */// 330 1 11 localException3 Exception
		/*      */// 354 1 11 localException4 Exception
		/*      */// Exception table:
		/*      */// from to target type
		/*      */// 15 156 159 java/sql/SQLException
		/*      */// 15 156 211 java/lang/Exception
		/*      */// 15 263 263 finally
		/*      */// 270 280 283 java/lang/Exception
		/*      */// 294 304 307 java/lang/Exception
		/*      */// 317 327 330 java/lang/Exception
		/*      */// 341 351 354 java/lang/Exception
		/*      */}

	/*      */
	/*      *//* Error */
	/*      */private MensajeTO insertaDetalleConfCanje(Connection connection,
			long fechaTransaccion, String sCuenta, int isecuencia,
			String sTelefono, String sUsuario, String sFolio)
	/*      */throws CAException
	/*      */{
		return null;
		/*      */// Byte code:
		/*      */// 0: aconst_null
		/*      */// 1: astore 9
		/*      */// 3: aconst_null
		/*      */// 4: astore 10
		/*      */// 6: new 605 com/claro/transfer/MensajeTO
		/*      */// 9: dup
		/*      */// 10: invokespecial 628 com/claro/transfer/MensajeTO:<init> ()V
		/*      */// 13: astore 11
		/*      */// 15: aload_1
		/*      */// 16: ifnonnull +17 -> 33
		/*      */// 19: invokestatic 29 com/claro/util/ServiceLocator:getInstance
				// ()Lcom/claro/util/ServiceLocator;
		/*      */// 22: getstatic 93 com/claro/util/ServiceLocator:jdbcCirculoAzul
				// Ljava/lang/String;
		/*      */// 25: invokevirtual 96 com/claro/util/ServiceLocator:getConnection
				// (Ljava/lang/String;)Ljava/sql/Connection;
		/*      */// 28: astore 9
		/*      */// 30: goto +6 -> 36
		/*      */// 33: aload_1
		/*      */// 34: astore 9
		/*      */// 36: new 293 java/lang/StringBuilder
		/*      */// 39: dup
		/*      */// 40: ldc_w 415
		/*      */// 43: invokespecial 297 java/lang/StringBuilder:<init>
				// (Ljava/lang/String;)V
		/*      */// 46: aload_0
		/*      */// 47: getfield 41 com/claro/dao/AlianzasDAO:schema_database
				// Ljava/lang/String;
		/*      */// 50: invokevirtual 300 java/lang/StringBuilder:append
				// (Ljava/lang/String;)Ljava/lang/StringBuilder;
		/*      */// 53: ldc_w 417
		/*      */// 56: invokevirtual 300 java/lang/StringBuilder:append
				// (Ljava/lang/String;)Ljava/lang/StringBuilder;
		/*      */// 59: ldc_w 419
		/*      */// 62: invokevirtual 300 java/lang/StringBuilder:append
				// (Ljava/lang/String;)Ljava/lang/StringBuilder;
		/*      */// 65: ldc_w 833
		/*      */// 68: invokevirtual 300 java/lang/StringBuilder:append
				// (Ljava/lang/String;)Ljava/lang/StringBuilder;
		/*      */// 71: invokevirtual 305 java/lang/StringBuilder:toString
				// ()Ljava/lang/String;
		/*      */// 74: astore 12
		/*      */// 76: new 293 java/lang/StringBuilder
		/*      */// 79: dup
		/*      */// 80: ldc_w 835
		/*      */// 83: invokespecial 297 java/lang/StringBuilder:<init>
				// (Ljava/lang/String;)V
		/*      */// 86: aload 7
		/*      */// 88: invokevirtual 837 java/lang/String:toUpperCase
				// ()Ljava/lang/String;
		/*      */// 91: invokevirtual 300 java/lang/StringBuilder:append
				// (Ljava/lang/String;)Ljava/lang/StringBuilder;
		/*      */// 94: ldc_w 840
		/*      */// 97: invokevirtual 300 java/lang/StringBuilder:append
				// (Ljava/lang/String;)Ljava/lang/StringBuilder;
		/*      */// 100: aload 8
		/*      */// 102: invokevirtual 743 java/lang/String:trim
				// ()Ljava/lang/String;
		/*      */// 105: invokevirtual 300 java/lang/StringBuilder:append
				// (Ljava/lang/String;)Ljava/lang/StringBuilder;
		/*      */// 108: invokevirtual 305 java/lang/StringBuilder:toString
				// ()Ljava/lang/String;
		/*      */// 111: astore 13
		/*      */// 113: aload 9
		/*      */// 115: aload 12
		/*      */// 117: invokeinterface 104 2 0
		/*      */// 122: astore 10
		/*      */// 124: aload 10
		/*      */// 126: iconst_1
		/*      */// 127: aload 4
		/*      */// 129: invokeinterface 110 3 0
		/*      */// 134: aload 10
		/*      */// 136: iconst_2
		/*      */// 137: iload 5
		/*      */// 139: invokeinterface 122 3 0
		/*      */// 144: aload 10
		/*      */// 146: iconst_3
		/*      */// 147: aload 6
		/*      */// 149: invokeinterface 110 3 0
		/*      */// 154: aload 10
		/*      */// 156: iconst_4
		/*      */// 157: new 362 java/sql/Date
		/*      */// 160: dup
		/*      */// 161: lload_2
		/*      */// 162: invokespecial 364 java/sql/Date:<init> (J)V
		/*      */// 165: invokeinterface 367 3 0
		/*      */// 170: aload 10
		/*      */// 172: iconst_5
		/*      */// 173: new 362 java/sql/Date
		/*      */// 176: dup
		/*      */// 177: lload_2
		/*      */// 178: invokespecial 364 java/sql/Date:<init> (J)V
		/*      */// 181: invokeinterface 367 3 0
		/*      */// 186: aload 10
		/*      */// 188: bipush 6
		/*      */// 190: aload 7
		/*      */// 192: invokeinterface 110 3 0
		/*      */// 197: aload 10
		/*      */// 199: bipush 7
		/*      */// 201: aload 13
		/*      */// 203: invokeinterface 110 3 0
		/*      */// 208: aload 10
		/*      */// 210: invokeinterface 466 1 0
		/*      */// 215: ifle +15 -> 230
		/*      */// 218: aload 11
		/*      */// 220: iconst_0
		/*      */// 221: ldc_w 683
		/*      */// 224: invokevirtual 685
				// com/claro/transfer/MensajeTO:agregaMensaje
				// (ILjava/lang/String;)V
		/*      */// 227: goto +168 -> 395
		/*      */// 230: aload 11
		/*      */// 232: iconst_1
		/*      */// 233: ldc_w 842
		/*      */// 236: invokevirtual 685
				// com/claro/transfer/MensajeTO:agregaMensaje
				// (ILjava/lang/String;)V
		/*      */// 239: goto +156 -> 395
		/*      */// 242: astore 12
		/*      */// 244: aload_0
		/*      */// 245: getfield 27 com/claro/dao/AlianzasDAO:error
				// Lorg/apache/log4j/Logger;
		/*      */// 248: ldc_w 844
		/*      */// 251: aload 12
		/*      */// 253: invokevirtual 393 org/apache/log4j/Logger:info
				// (Ljava/lang/Object;Ljava/lang/Throwable;)V
		/*      */// 256: new 59 com/claro/exception/CAException
		/*      */// 259: dup
		/*      */// 260: iconst_m1
		/*      */// 261: new 293 java/lang/StringBuilder
		/*      */// 264: dup
		/*      */// 265: ldc_w 819
		/*      */// 268: invokespecial 297 java/lang/StringBuilder:<init>
				// (Ljava/lang/String;)V
		/*      */// 271: aload 12
		/*      */// 273: invokevirtual 491 java/sql/SQLException:toString
				// ()Ljava/lang/String;
		/*      */// 276: invokevirtual 300 java/lang/StringBuilder:append
				// (Ljava/lang/String;)Ljava/lang/StringBuilder;
		/*      */// 279: ldc_w 846
		/*      */// 282: invokevirtual 300 java/lang/StringBuilder:append
				// (Ljava/lang/String;)Ljava/lang/StringBuilder;
		/*      */// 285: invokevirtual 305 java/lang/StringBuilder:toString
				// ()Ljava/lang/String;
		/*      */// 288: aload 12
		/*      */// 290: invokespecial 222 com/claro/exception/CAException:<init>
				// (ILjava/lang/String;Ljava/lang/Exception;)V
		/*      */// 293: athrow
		/*      */// 294: astore 12
		/*      */// 296: aload_0
		/*      */// 297: getfield 27 com/claro/dao/AlianzasDAO:error
				// Lorg/apache/log4j/Logger;
		/*      */// 300: ldc_w 848
		/*      */// 303: aload 12
		/*      */// 305: invokevirtual 393 org/apache/log4j/Logger:info
				// (Ljava/lang/Object;Ljava/lang/Throwable;)V
		/*      */// 308: new 59 com/claro/exception/CAException
		/*      */// 311: dup
		/*      */// 312: iconst_m1
		/*      */// 313: new 293 java/lang/StringBuilder
		/*      */// 316: dup
		/*      */// 317: ldc_w 825
		/*      */// 320: invokespecial 297 java/lang/StringBuilder:<init>
				// (Ljava/lang/String;)V
		/*      */// 323: aload 12
		/*      */// 325: invokevirtual 299 java/lang/Exception:toString
				// ()Ljava/lang/String;
		/*      */// 328: invokevirtual 300 java/lang/StringBuilder:append
				// (Ljava/lang/String;)Ljava/lang/StringBuilder;
		/*      */// 331: ldc_w 846
		/*      */// 334: invokevirtual 300 java/lang/StringBuilder:append
				// (Ljava/lang/String;)Ljava/lang/StringBuilder;
		/*      */// 337: invokevirtual 305 java/lang/StringBuilder:toString
				// ()Ljava/lang/String;
		/*      */// 340: aload 12
		/*      */// 342: invokespecial 222 com/claro/exception/CAException:<init>
				// (ILjava/lang/String;Ljava/lang/Exception;)V
		/*      */// 345: athrow
		/*      */// 346: astore 14
		/*      */// 348: aload 10
		/*      */// 350: ifnull +18 -> 368
		/*      */// 353: aload 10
		/*      */// 355: invokeinterface 232 1 0
		/*      */// 360: aconst_null
		/*      */// 361: astore 10
		/*      */// 363: goto +5 -> 368
		/*      */// 366: astore 15
		/*      */// 368: aload_1
		/*      */// 369: ifnonnull +23 -> 392
		/*      */// 372: aload 9
		/*      */// 374: ifnull +18 -> 392
		/*      */// 377: aload 9
		/*      */// 379: invokeinterface 233 1 0
		/*      */// 384: aconst_null
		/*      */// 385: astore 9
		/*      */// 387: goto +5 -> 392
		/*      */// 390: astore 15
		/*      */// 392: aload 14
		/*      */// 394: athrow
		/*      */// 395: aload 10
		/*      */// 397: ifnull +18 -> 415
		/*      */// 400: aload 10
		/*      */// 402: invokeinterface 232 1 0
		/*      */// 407: aconst_null
		/*      */// 408: astore 10
		/*      */// 410: goto +5 -> 415
		/*      */// 413: astore 15
		/*      */// 415: aload_1
		/*      */// 416: ifnonnull +23 -> 439
		/*      */// 419: aload 9
		/*      */// 421: ifnull +18 -> 439
		/*      */// 424: aload 9
		/*      */// 426: invokeinterface 233 1 0
		/*      */// 431: aconst_null
		/*      */// 432: astore 9
		/*      */// 434: goto +5 -> 439
		/*      */// 437: astore 15
		/*      */// 439: aload 11
		/*      */// 441: areturn
		/*      */// Line number table:
		/*      */// Java source line #717 -> byte code offset #0
		/*      */// Java source line #718 -> byte code offset #3
		/*      */// Java source line #719 -> byte code offset #6
		/*      */// Java source line #722 -> byte code offset #15
		/*      */// Java source line #723 -> byte code offset #33
		/*      */// Java source line #725 -> byte code offset #36
		/*      */// Java source line #726 -> byte code offset #59
		/*      */// Java source line #727 -> byte code offset #65
		/*      */// Java source line #725 -> byte code offset #71
		/*      */// Java source line #729 -> byte code offset #76
		/*      */// Java source line #730 -> byte code offset #113
		/*      */// Java source line #731 -> byte code offset #124
		/*      */// Java source line #732 -> byte code offset #134
		/*      */// Java source line #733 -> byte code offset #144
		/*      */// Java source line #734 -> byte code offset #154
		/*      */// Java source line #735 -> byte code offset #170
		/*      */// Java source line #736 -> byte code offset #186
		/*      */// Java source line #737 -> byte code offset #197
		/*      */// Java source line #739 -> byte code offset #208
		/*      */// Java source line #740 -> byte code offset #230
		/*      */// Java source line #742 -> byte code offset #242
		/*      */// Java source line #743 -> byte code offset #244
		/*      */// Java source line #744 -> byte code offset #256
		/*      */// Java source line #745 -> byte code offset #294
		/*      */// Java source line #746 -> byte code offset #296
		/*      */// Java source line #747 -> byte code offset #308
		/*      */// Java source line #748 -> byte code offset #346
		/*      */// Java source line #749 -> byte code offset #348
		/*      */// Java source line #750 -> byte code offset #368
		/*      */// Java source line #751 -> byte code offset #392
		/*      */// Java source line #749 -> byte code offset #395
		/*      */// Java source line #750 -> byte code offset #415
		/*      */// Java source line #752 -> byte code offset #439
		/*      */// Local variable table:
		/*      */// start length slot name signature
		/*      */// 0 442 0 this AlianzasDAO
		/*      */// 0 442 1 connection Connection
		/*      */// 0 442 2 fechaTransaccion long
		/*      */// 0 442 4 sCuenta String
		/*      */// 0 442 5 isecuencia int
		/*      */// 0 442 6 sTelefono String
		/*      */// 0 442 7 sUsuario String
		/*      */// 0 442 8 sFolio String
		/*      */// 1 432 9 lConn Connection
		/*      */// 4 405 10 statement PreparedStatement
		/*      */// 13 427 11 mensajeTO MensajeTO
		/*      */// 74 42 12 queryInsertDetalle String
		/*      */// 242 47 12 e SQLException
		/*      */// 294 47 12 e Exception
		/*      */// 111 91 13 mensaje String
		/*      */// 346 47 14 localObject Object
		/*      */// 366 1 15 localException1 Exception
		/*      */// 390 1 15 localException2 Exception
		/*      */// 413 1 15 localException3 Exception
		/*      */// 437 1 15 localException4 Exception
		/*      */// Exception table:
		/*      */// from to target type
		/*      */// 15 239 242 java/sql/SQLException
		/*      */// 15 239 294 java/lang/Exception
		/*      */// 15 346 346 finally
		/*      */// 353 363 366 java/lang/Exception
		/*      */// 377 387 390 java/lang/Exception
		/*      */// 400 410 413 java/lang/Exception
		/*      */// 424 434 437 java/lang/Exception
		/*      */}

	/*      */
	/*      *//* Error */
	/*      */private MensajeTO insertaComntConfCanje(Connection connection,
			long fechaTransaccion, String sCuenta, String lIdCanje,
			int iRegion, String sUsuario, String sFolio)
	/*      */throws CAException
	/*      */{
		return null;
		/*      */// Byte code:
		/*      */// 0: aconst_null
		/*      */// 1: astore 9
		/*      */// 3: aconst_null
		/*      */// 4: astore 10
		/*      */// 6: new 605 com/claro/transfer/MensajeTO
		/*      */// 9: dup
		/*      */// 10: invokespecial 628 com/claro/transfer/MensajeTO:<init> ()V
		/*      */// 13: astore 11
		/*      */// 15: aload_1
		/*      */// 16: ifnonnull +17 -> 33
		/*      */// 19: invokestatic 29 com/claro/util/ServiceLocator:getInstance
				// ()Lcom/claro/util/ServiceLocator;
		/*      */// 22: getstatic 93 com/claro/util/ServiceLocator:jdbcCirculoAzul
				// Ljava/lang/String;
		/*      */// 25: invokevirtual 96 com/claro/util/ServiceLocator:getConnection
				// (Ljava/lang/String;)Ljava/sql/Connection;
		/*      */// 28: astore 9
		/*      */// 30: goto +6 -> 36
		/*      */// 33: aload_1
		/*      */// 34: astore 9
		/*      */// 36: new 293 java/lang/StringBuilder
		/*      */// 39: dup
		/*      */// 40: ldc_w 415
		/*      */// 43: invokespecial 297 java/lang/StringBuilder:<init>
				// (Ljava/lang/String;)V
		/*      */// 46: aload_0
		/*      */// 47: getfield 41 com/claro/dao/AlianzasDAO:schema_database
				// Ljava/lang/String;
		/*      */// 50: invokevirtual 300 java/lang/StringBuilder:append
				// (Ljava/lang/String;)Ljava/lang/StringBuilder;
		/*      */// 53: ldc_w 423
		/*      */// 56: invokevirtual 300 java/lang/StringBuilder:append
				// (Ljava/lang/String;)Ljava/lang/StringBuilder;
		/*      */// 59: ldc_w 425
		/*      */// 62: invokevirtual 300 java/lang/StringBuilder:append
				// (Ljava/lang/String;)Ljava/lang/StringBuilder;
		/*      */// 65: invokevirtual 305 java/lang/StringBuilder:toString
				// ()Ljava/lang/String;
		/*      */// 68: astore 12
		/*      */// 70: new 293 java/lang/StringBuilder
		/*      */// 73: dup
		/*      */// 74: ldc_w 856
		/*      */// 77: invokespecial 297 java/lang/StringBuilder:<init>
				// (Ljava/lang/String;)V
		/*      */// 80: aload 5
		/*      */// 82: invokevirtual 743 java/lang/String:trim ()Ljava/lang/String;
		/*      */// 85: invokevirtual 300 java/lang/StringBuilder:append
				// (Ljava/lang/String;)Ljava/lang/StringBuilder;
		/*      */// 88: ldc_w 858
		/*      */// 91: invokevirtual 300 java/lang/StringBuilder:append
				// (Ljava/lang/String;)Ljava/lang/StringBuilder;
		/*      */// 94: aload 8
		/*      */// 96: invokevirtual 743 java/lang/String:trim ()Ljava/lang/String;
		/*      */// 99: invokevirtual 300 java/lang/StringBuilder:append
				// (Ljava/lang/String;)Ljava/lang/StringBuilder;
		/*      */// 102: invokevirtual 305 java/lang/StringBuilder:toString
				// ()Ljava/lang/String;
		/*      */// 105: astore 13
		/*      */// 107: aload 9
		/*      */// 109: aload 12
		/*      */// 111: invokeinterface 104 2 0
		/*      */// 116: astore 10
		/*      */// 118: aload 10
		/*      */// 120: iconst_1
		/*      */// 121: iload 6
		/*      */// 123: invokeinterface 122 3 0
		/*      */// 128: aload 10
		/*      */// 130: iconst_2
		/*      */// 131: new 437 java/sql/Timestamp
		/*      */// 134: dup
		/*      */// 135: lload_2
		/*      */// 136: invokespecial 439 java/sql/Timestamp:<init> (J)V
		/*      */// 139: invokeinterface 472 3 0
		/*      */// 144: aload 10
		/*      */// 146: iconst_3
		/*      */// 147: aload 4
		/*      */// 149: invokeinterface 110 3 0
		/*      */// 154: aload 10
		/*      */// 156: iconst_4
		/*      */// 157: aload 7
		/*      */// 159: invokeinterface 110 3 0
		/*      */// 164: aload 10
		/*      */// 166: iconst_5
		/*      */// 167: aload 13
		/*      */// 169: invokeinterface 110 3 0
		/*      */// 174: aload 10
		/*      */// 176: invokeinterface 466 1 0
		/*      */// 181: ifle +15 -> 196
		/*      */// 184: aload 11
		/*      */// 186: iconst_0
		/*      */// 187: ldc_w 683
		/*      */// 190: invokevirtual 685
				// com/claro/transfer/MensajeTO:agregaMensaje
				// (ILjava/lang/String;)V
		/*      */// 193: goto +168 -> 361
		/*      */// 196: aload 11
		/*      */// 198: iconst_1
		/*      */// 199: ldc_w 860
		/*      */// 202: invokevirtual 685
				// com/claro/transfer/MensajeTO:agregaMensaje
				// (ILjava/lang/String;)V
		/*      */// 205: goto +156 -> 361
		/*      */// 208: astore 12
		/*      */// 210: aload_0
		/*      */// 211: getfield 27 com/claro/dao/AlianzasDAO:error
				// Lorg/apache/log4j/Logger;
		/*      */// 214: ldc_w 862
		/*      */// 217: aload 12
		/*      */// 219: invokevirtual 393 org/apache/log4j/Logger:info
				// (Ljava/lang/Object;Ljava/lang/Throwable;)V
		/*      */// 222: new 59 com/claro/exception/CAException
		/*      */// 225: dup
		/*      */// 226: iconst_m1
		/*      */// 227: new 293 java/lang/StringBuilder
		/*      */// 230: dup
		/*      */// 231: ldc_w 819
		/*      */// 234: invokespecial 297 java/lang/StringBuilder:<init>
				// (Ljava/lang/String;)V
		/*      */// 237: aload 12
		/*      */// 239: invokevirtual 491 java/sql/SQLException:toString
				// ()Ljava/lang/String;
		/*      */// 242: invokevirtual 300 java/lang/StringBuilder:append
				// (Ljava/lang/String;)Ljava/lang/StringBuilder;
		/*      */// 245: ldc_w 846
		/*      */// 248: invokevirtual 300 java/lang/StringBuilder:append
				// (Ljava/lang/String;)Ljava/lang/StringBuilder;
		/*      */// 251: invokevirtual 305 java/lang/StringBuilder:toString
				// ()Ljava/lang/String;
		/*      */// 254: aload 12
		/*      */// 256: invokespecial 222 com/claro/exception/CAException:<init>
				// (ILjava/lang/String;Ljava/lang/Exception;)V
		/*      */// 259: athrow
		/*      */// 260: astore 12
		/*      */// 262: aload_0
		/*      */// 263: getfield 27 com/claro/dao/AlianzasDAO:error
				// Lorg/apache/log4j/Logger;
		/*      */// 266: ldc_w 864
		/*      */// 269: aload 12
		/*      */// 271: invokevirtual 393 org/apache/log4j/Logger:info
				// (Ljava/lang/Object;Ljava/lang/Throwable;)V
		/*      */// 274: new 59 com/claro/exception/CAException
		/*      */// 277: dup
		/*      */// 278: iconst_m1
		/*      */// 279: new 293 java/lang/StringBuilder
		/*      */// 282: dup
		/*      */// 283: ldc_w 825
		/*      */// 286: invokespecial 297 java/lang/StringBuilder:<init>
				// (Ljava/lang/String;)V
		/*      */// 289: aload 12
		/*      */// 291: invokevirtual 299 java/lang/Exception:toString
				// ()Ljava/lang/String;
		/*      */// 294: invokevirtual 300 java/lang/StringBuilder:append
				// (Ljava/lang/String;)Ljava/lang/StringBuilder;
		/*      */// 297: ldc_w 846
		/*      */// 300: invokevirtual 300 java/lang/StringBuilder:append
				// (Ljava/lang/String;)Ljava/lang/StringBuilder;
		/*      */// 303: invokevirtual 305 java/lang/StringBuilder:toString
				// ()Ljava/lang/String;
		/*      */// 306: aload 12
		/*      */// 308: invokespecial 222 com/claro/exception/CAException:<init>
				// (ILjava/lang/String;Ljava/lang/Exception;)V
		/*      */// 311: athrow
		/*      */// 312: astore 14
		/*      */// 314: aload 10
		/*      */// 316: ifnull +18 -> 334
		/*      */// 319: aload 10
		/*      */// 321: invokeinterface 232 1 0
		/*      */// 326: aconst_null
		/*      */// 327: astore 10
		/*      */// 329: goto +5 -> 334
		/*      */// 332: astore 15
		/*      */// 334: aload_1
		/*      */// 335: ifnonnull +23 -> 358
		/*      */// 338: aload 9
		/*      */// 340: ifnull +18 -> 358
		/*      */// 343: aload 9
		/*      */// 345: invokeinterface 233 1 0
		/*      */// 350: aconst_null
		/*      */// 351: astore 9
		/*      */// 353: goto +5 -> 358
		/*      */// 356: astore 15
		/*      */// 358: aload 14
		/*      */// 360: athrow
		/*      */// 361: aload 10
		/*      */// 363: ifnull +18 -> 381
		/*      */// 366: aload 10
		/*      */// 368: invokeinterface 232 1 0
		/*      */// 373: aconst_null
		/*      */// 374: astore 10
		/*      */// 376: goto +5 -> 381
		/*      */// 379: astore 15
		/*      */// 381: aload_1
		/*      */// 382: ifnonnull +23 -> 405
		/*      */// 385: aload 9
		/*      */// 387: ifnull +18 -> 405
		/*      */// 390: aload 9
		/*      */// 392: invokeinterface 233 1 0
		/*      */// 397: aconst_null
		/*      */// 398: astore 9
		/*      */// 400: goto +5 -> 405
		/*      */// 403: astore 15
		/*      */// 405: aload 11
		/*      */// 407: areturn
		/*      */// Line number table:
		/*      */// Java source line #756 -> byte code offset #0
		/*      */// Java source line #757 -> byte code offset #3
		/*      */// Java source line #758 -> byte code offset #6
		/*      */// Java source line #761 -> byte code offset #15
		/*      */// Java source line #762 -> byte code offset #33
		/*      */// Java source line #764 -> byte code offset #36
		/*      */// Java source line #765 -> byte code offset #59
		/*      */// Java source line #764 -> byte code offset #65
		/*      */// Java source line #767 -> byte code offset #70
		/*      */// Java source line #768 -> byte code offset #107
		/*      */// Java source line #769 -> byte code offset #118
		/*      */// Java source line #770 -> byte code offset #128
		/*      */// Java source line #771 -> byte code offset #144
		/*      */// Java source line #772 -> byte code offset #154
		/*      */// Java source line #773 -> byte code offset #164
		/*      */// Java source line #775 -> byte code offset #174
		/*      */// Java source line #776 -> byte code offset #196
		/*      */// Java source line #778 -> byte code offset #208
		/*      */// Java source line #779 -> byte code offset #210
		/*      */// Java source line #780 -> byte code offset #222
		/*      */// Java source line #781 -> byte code offset #260
		/*      */// Java source line #782 -> byte code offset #262
		/*      */// Java source line #783 -> byte code offset #274
		/*      */// Java source line #784 -> byte code offset #312
		/*      */// Java source line #785 -> byte code offset #314
		/*      */// Java source line #786 -> byte code offset #334
		/*      */// Java source line #787 -> byte code offset #358
		/*      */// Java source line #785 -> byte code offset #361
		/*      */// Java source line #786 -> byte code offset #381
		/*      */// Java source line #788 -> byte code offset #405
		/*      */// Local variable table:
		/*      */// start length slot name signature
		/*      */// 0 408 0 this AlianzasDAO
		/*      */// 0 408 1 connection Connection
		/*      */// 0 408 2 fechaTransaccion long
		/*      */// 0 408 4 sCuenta String
		/*      */// 0 408 5 lIdCanje String
		/*      */// 0 408 6 iRegion int
		/*      */// 0 408 7 sUsuario String
		/*      */// 0 408 8 sFolio String
		/*      */// 1 398 9 lConn Connection
		/*      */// 4 371 10 statement PreparedStatement
		/*      */// 13 393 11 mensajeTO MensajeTO
		/*      */// 68 42 12 queryInsertComentario String
		/*      */// 208 47 12 e SQLException
		/*      */// 260 47 12 e Exception
		/*      */// 105 63 13 mensaje String
		/*      */// 312 47 14 localObject Object
		/*      */// 332 1 15 localException1 Exception
		/*      */// 356 1 15 localException2 Exception
		/*      */// 379 1 15 localException3 Exception
		/*      */// 403 1 15 localException4 Exception
		/*      */// Exception table:
		/*      */// from to target type
		/*      */// 15 205 208 java/sql/SQLException
		/*      */// 15 205 260 java/lang/Exception
		/*      */// 15 312 312 finally
		/*      */// 319 329 332 java/lang/Exception
		/*      */// 343 353 356 java/lang/Exception
		/*      */// 366 376 379 java/lang/Exception
		/*      */// 390 400 403 java/lang/Exception
		/*      */}

	/*      */
	/*      *//* Error */
	/*      */public MensajeTO confirmaCanje(int lValViaje,
			com.claro.transfer.FolioLiberacionTO folioLiberacion,
			int lNumAcomp, String lIdCanje, String sCuenta, int isecuencia,
			String sTelefono, String sUsuario, int iRegion)
	/*      */throws CAException
	/*      */{
		return folioLiberacion;
		/*      */// Byte code:
		/*      */// 0: aconst_null
		/*      */// 1: astore 10
		/*      */// 3: new 605 com/claro/transfer/MensajeTO
		/*      */// 6: dup
		/*      */// 7: invokespecial 628 com/claro/transfer/MensajeTO:<init> ()V
		/*      */// 10: astore 11
		/*      */// 12: invokestatic 29 com/claro/util/ServiceLocator:getInstance
				// ()Lcom/claro/util/ServiceLocator;
		/*      */// 15: getstatic 93 com/claro/util/ServiceLocator:jdbcCirculoAzul
				// Ljava/lang/String;
		/*      */// 18: invokevirtual 96 com/claro/util/ServiceLocator:getConnection
				// (Ljava/lang/String;)Ljava/sql/Connection;
		/*      */// 21: astore 10
		/*      */// 23: aload 10
		/*      */// 25: iconst_0
		/*      */// 26: invokeinterface 429 2 0
		/*      */// 31: invokestatic 330 java/lang/System:currentTimeMillis ()J
		/*      */// 34: lstore 12
		/*      */// 36: aload_2
		/*      */// 37: aload 7
		/*      */// 39: invokestatic 869 com/claro/util/Utils:generaFolioAlianza
				// (Ljava/lang/String;)Ljava/lang/String;
		/*      */// 42: invokevirtual 872
				// com/claro/transfer/FolioLiberacionTO:setFolio
				// (Ljava/lang/String;)V
		/*      */// 45: aload_0
		/*      */// 46: aload 10
		/*      */// 48: iload_1
		/*      */// 49: aload_2
		/*      */// 50: invokevirtual 875
				// com/claro/transfer/FolioLiberacionTO:getFolio
				// ()Ljava/lang/String;
		/*      */// 53: iload_3
		/*      */// 54: aload 4
		/*      */// 56: invokespecial 876
				// com/claro/dao/AlianzasDAO:actualizaConfCanjeAlianza
				// (Ljava/sql/Connection;ILjava/lang/String;ILjava/lang/String;)Lcom/claro/transfer/MensajeTO;
		/*      */// 59: astore 11
		/*      */// 61: aload 11
		/*      */// 63: invokevirtual 604 com/claro/transfer/MensajeTO:getIdMensaje
				// ()I
		/*      */// 66: ifne +25 -> 91
		/*      */// 69: aload_0
		/*      */// 70: aload 10
		/*      */// 72: lload 12
		/*      */// 74: aload 5
		/*      */// 76: iload 6
		/*      */// 78: aload 7
		/*      */// 80: aload 8
		/*      */// 82: aload_2
		/*      */// 83: invokevirtual 875
				// com/claro/transfer/FolioLiberacionTO:getFolio
				// ()Ljava/lang/String;
		/*      */// 86: invokespecial 878
				// com/claro/dao/AlianzasDAO:insertaDetalleConfCanje
				// (Ljava/sql/Connection;JLjava/lang/String;ILjava/lang/String;Ljava/lang/String;Ljava/lang/String;)Lcom/claro/transfer/MensajeTO;
		/*      */// 89: astore 11
		/*      */// 91: aload 11
		/*      */// 93: invokevirtual 604 com/claro/transfer/MensajeTO:getIdMensaje
				// ()I
		/*      */// 96: ifne +25 -> 121
		/*      */// 99: aload_0
		/*      */// 100: aload 10
		/*      */// 102: lload 12
		/*      */// 104: aload 5
		/*      */// 106: aload 4
		/*      */// 108: iload 9
		/*      */// 110: aload 8
		/*      */// 112: aload_2
		/*      */// 113: invokevirtual 875
				// com/claro/transfer/FolioLiberacionTO:getFolio
				// ()Ljava/lang/String;
		/*      */// 116: invokespecial 880
				// com/claro/dao/AlianzasDAO:insertaComntConfCanje
				// (Ljava/sql/Connection;JLjava/lang/String;Ljava/lang/String;ILjava/lang/String;Ljava/lang/String;)Lcom/claro/transfer/MensajeTO;
		/*      */// 119: astore 11
		/*      */// 121: aload 11
		/*      */// 123: invokevirtual 604 com/claro/transfer/MensajeTO:getIdMensaje
				// ()I
		/*      */// 126: ifeq +13 -> 139
		/*      */// 129: aload 10
		/*      */// 131: invokeinterface 486 1 0
		/*      */// 136: goto +184 -> 320
		/*      */// 139: aload 10
		/*      */// 141: invokeinterface 479 1 0
		/*      */// 146: goto +174 -> 320
		/*      */// 149: astore 12
		/*      */// 151: aload_0
		/*      */// 152: getfield 27 com/claro/dao/AlianzasDAO:error
				// Lorg/apache/log4j/Logger;
		/*      */// 155: ldc_w 882
		/*      */// 158: aload 12
		/*      */// 160: invokevirtual 393 org/apache/log4j/Logger:info
				// (Ljava/lang/Object;Ljava/lang/Throwable;)V
		/*      */// 163: aload 10
		/*      */// 165: ifnull +15 -> 180
		/*      */// 168: aload 10
		/*      */// 170: invokeinterface 486 1 0
		/*      */// 175: goto +5 -> 180
		/*      */// 178: astore 13
		/*      */// 180: new 59 com/claro/exception/CAException
		/*      */// 183: dup
		/*      */// 184: iconst_m1
		/*      */// 185: new 293 java/lang/StringBuilder
		/*      */// 188: dup
		/*      */// 189: ldc_w 819
		/*      */// 192: invokespecial 297 java/lang/StringBuilder:<init>
				// (Ljava/lang/String;)V
		/*      */// 195: aload 12
		/*      */// 197: invokevirtual 491 java/sql/SQLException:toString
				// ()Ljava/lang/String;
		/*      */// 200: invokevirtual 300 java/lang/StringBuilder:append
				// (Ljava/lang/String;)Ljava/lang/StringBuilder;
		/*      */// 203: ldc_w 821
		/*      */// 206: invokevirtual 300 java/lang/StringBuilder:append
				// (Ljava/lang/String;)Ljava/lang/StringBuilder;
		/*      */// 209: invokevirtual 305 java/lang/StringBuilder:toString
				// ()Ljava/lang/String;
		/*      */// 212: aload 12
		/*      */// 214: invokespecial 222 com/claro/exception/CAException:<init>
				// (ILjava/lang/String;Ljava/lang/Exception;)V
		/*      */// 217: athrow
		/*      */// 218: astore 12
		/*      */// 220: aload_0
		/*      */// 221: getfield 27 com/claro/dao/AlianzasDAO:error
				// Lorg/apache/log4j/Logger;
		/*      */// 224: ldc_w 884
		/*      */// 227: aload 12
		/*      */// 229: invokevirtual 393 org/apache/log4j/Logger:info
				// (Ljava/lang/Object;Ljava/lang/Throwable;)V
		/*      */// 232: aload 10
		/*      */// 234: ifnull +15 -> 249
		/*      */// 237: aload 10
		/*      */// 239: invokeinterface 486 1 0
		/*      */// 244: goto +5 -> 249
		/*      */// 247: astore 13
		/*      */// 249: new 59 com/claro/exception/CAException
		/*      */// 252: dup
		/*      */// 253: iconst_m1
		/*      */// 254: new 293 java/lang/StringBuilder
		/*      */// 257: dup
		/*      */// 258: ldc_w 825
		/*      */// 261: invokespecial 297 java/lang/StringBuilder:<init>
				// (Ljava/lang/String;)V
		/*      */// 264: aload 12
		/*      */// 266: invokevirtual 299 java/lang/Exception:toString
				// ()Ljava/lang/String;
		/*      */// 269: invokevirtual 300 java/lang/StringBuilder:append
				// (Ljava/lang/String;)Ljava/lang/StringBuilder;
		/*      */// 272: ldc_w 821
		/*      */// 275: invokevirtual 300 java/lang/StringBuilder:append
				// (Ljava/lang/String;)Ljava/lang/StringBuilder;
		/*      */// 278: invokevirtual 305 java/lang/StringBuilder:toString
				// ()Ljava/lang/String;
		/*      */// 281: aload 12
		/*      */// 283: invokespecial 222 com/claro/exception/CAException:<init>
				// (ILjava/lang/String;Ljava/lang/Exception;)V
		/*      */// 286: athrow
		/*      */// 287: astore 14
		/*      */// 289: aload 10
		/*      */// 291: ifnull +26 -> 317
		/*      */// 294: aload 10
		/*      */// 296: iconst_1
		/*      */// 297: invokeinterface 429 2 0
		/*      */// 302: aload 10
		/*      */// 304: invokeinterface 233 1 0
		/*      */// 309: aconst_null
		/*      */// 310: astore 10
		/*      */// 312: goto +5 -> 317
		/*      */// 315: astore 15
		/*      */// 317: aload 14
		/*      */// 319: athrow
		/*      */// 320: aload 10
		/*      */// 322: ifnull +26 -> 348
		/*      */// 325: aload 10
		/*      */// 327: iconst_1
		/*      */// 328: invokeinterface 429 2 0
		/*      */// 333: aload 10
		/*      */// 335: invokeinterface 233 1 0
		/*      */// 340: aconst_null
		/*      */// 341: astore 10
		/*      */// 343: goto +5 -> 348
		/*      */// 346: astore 15
		/*      */// 348: aload 11
		/*      */// 350: areturn
		/*      */// Line number table:
		/*      */// Java source line #791 -> byte code offset #0
		/*      */// Java source line #792 -> byte code offset #3
		/*      */// Java source line #794 -> byte code offset #12
		/*      */// Java source line #795 -> byte code offset #23
		/*      */// Java source line #796 -> byte code offset #31
		/*      */// Java source line #799 -> byte code offset #36
		/*      */// Java source line #801 -> byte code offset #45
		/*      */// Java source line #804 -> byte code offset #61
		/*      */// Java source line #805 -> byte code offset #69
		/*      */// Java source line #808 -> byte code offset #91
		/*      */// Java source line #809 -> byte code offset #99
		/*      */// Java source line #811 -> byte code offset #121
		/*      */// Java source line #812 -> byte code offset #129
		/*      */// Java source line #813 -> byte code offset #139
		/*      */// Java source line #815 -> byte code offset #149
		/*      */// Java source line #816 -> byte code offset #151
		/*      */// Java source line #817 -> byte code offset #163
		/*      */// Java source line #818 -> byte code offset #180
		/*      */// Java source line #819 -> byte code offset #218
		/*      */// Java source line #820 -> byte code offset #220
		/*      */// Java source line #821 -> byte code offset #232
		/*      */// Java source line #822 -> byte code offset #249
		/*      */// Java source line #823 -> byte code offset #287
		/*      */// Java source line #824 -> byte code offset #289
		/*      */// Java source line #825 -> byte code offset #317
		/*      */// Java source line #824 -> byte code offset #320
		/*      */// Java source line #826 -> byte code offset #348
		/*      */// Local variable table:
		/*      */// start length slot name signature
		/*      */// 0 351 0 this AlianzasDAO
		/*      */// 0 351 1 lValViaje int
		/*      */// 0 351 2 folioLiberacion com.claro.transfer.FolioLiberacionTO
		/*      */// 0 351 3 lNumAcomp int
		/*      */// 0 351 4 lIdCanje String
		/*      */// 0 351 5 sCuenta String
		/*      */// 0 351 6 isecuencia int
		/*      */// 0 351 7 sTelefono String
		/*      */// 0 351 8 sUsuario String
		/*      */// 0 351 9 iRegion int
		/*      */// 1 341 10 connection Connection
		/*      */// 10 339 11 mensajeTO MensajeTO
		/*      */// 34 69 12 fechaTransaccion long
		/*      */// 149 64 12 e SQLException
		/*      */// 218 64 12 e Exception
		/*      */// 178 1 13 localException1 Exception
		/*      */// 247 1 13 localException2 Exception
		/*      */// 287 31 14 localObject Object
		/*      */// 315 1 15 localException3 Exception
		/*      */// 346 1 15 localException4 Exception
		/*      */// Exception table:
		/*      */// from to target type
		/*      */// 12 146 149 java/sql/SQLException
		/*      */// 168 175 178 java/lang/Exception
		/*      */// 12 146 218 java/lang/Exception
		/*      */// 237 244 247 java/lang/Exception
		/*      */// 12 287 287 finally
		/*      */// 294 312 315 java/lang/Exception
		/*      */// 325 343 346 java/lang/Exception
		/*      */}

	/*      */
	/*      */public int consultaPtosTransferir(String sIdViaje, int iRegion)
	/*      */throws Exception
	/*      */{
		/* 887 */PreparedStatement statement = null;
		/* 888 */ResultSet resultSet = null;
		/* 889 */Connection connection = null;
		/* 890 */int nPuntos = 0;
		/*      */
		/* 892 */String sQuery = " SELECT DISTINCT A.VALORPUNTOS FROM  "
				+ this.schema_database + "PTO_CTLPROMOCIONES " +
				/* 893 */" WHERE IDPRODUCTO = ? AND A.ESTATUS = 'A' " +
				/* 894 */" AND IDREGION = ? AND FZAVENTAS = 'TELCEL' ";
		/*      */try {
			/* 896 */connection = ServiceLocator.getInstance().getConnection(
					ServiceLocator.jdbcCirculoAzul);
			/* 897 */statement = connection.prepareStatement(sQuery);
			/* 898 */statement.setString(1, sIdViaje);
			/* 899 */statement.setInt(2, iRegion);
			/* 900 */resultSet = statement.executeQuery();
			/*      */
			/* 902 */if (resultSet.next()) {
				/* 903 */nPuntos = resultSet.getInt(1);
				/*      */} else {
				/* 905 */nPuntos = 0;
				/*      */}
			/*      */
			/* 908 */return nPuntos;
			/*      */}
		/*      */catch (SQLException e) {
			/* 911 */throw new CAException(
					-1,
					"SQLException.consultaPtosTransferir[" + e.toString() + "]",
					e);
			/*      */} catch (Exception e) {
			/* 913 */throw new CAException(-1,
					"AlianzasDAO.consultaPtosTransferir[" + e.toString() + "]",
					e);
			/*      */} finally {
			/* 915 */if (statement != null)
				try {
					statement.close();
					statement = null;
				} catch (Exception localException4) {
				}
			/* 916 */if (resultSet != null)
				try {
					resultSet.close();
					resultSet = null;
				} catch (Exception localException5) {
				}
			/* 917 */if (connection != null)
				try {
					connection.close();
					connection = null;
					/*      */}
				/*      */catch (Exception localException6) {
				}
			/*      */}
		/*      */}

	/*      */
	/*      */public MensajeTO realizaCancelacion(ParametrosTO parametrosTO,
			int estatusTrans) throws CAException {
		/* 924 */Connection connection = null;
		/* 925 */MensajeTO mensajeTO = new MensajeTO();
		/*      */try {
			/* 927 */ConsultasDAO consultasDAO = new ConsultasDAO();
			/* 928 */PuntosRedimidosTO redimidosTO = consultasDAO
					.consultaPuntosRedimAlianza(parametrosTO.getFolio());
			/*      */MensajeTO localMensajeTO1;
			/* 930 */if (redimidosTO.getIdMensaje() != 0) {
				/* 931 */mensajeTO = redimidosTO.obtieneMensajeTO();
				/* 932 */return mensajeTO;
				/*      */}
			/* 934 */PuntosTO puntosTO = consultasDAO.obtienePuntos(
					parametrosTO.getCuenta(), parametrosTO.getSecuencia());
			/*      */
			/* 936 */if (puntosTO.getIdMensaje() != 0) {
				/* 937 */mensajeTO = puntosTO.obtieneMensajeTO();
				/* 938 */return mensajeTO;
				/*      */}
			/*      */
			/* 941 */connection = ServiceLocator.getInstance().getConnection(
					ServiceLocator.jdbcCirculoAzul);
			/* 942 */connection.setAutoCommit(false);
			/* 943 */long fechaTransaccion = System.currentTimeMillis();
			/* 944 */PuntosDAO puntosDAO = new PuntosDAO();
			/* 945 */String referencia = "Cancelacion de Canje Realizo:"
					+ parametrosTO.getUsuariMovimiento() + " -> "
					+ parametrosTO.getComentario();
			/*      */
			/* 947 */mensajeTO = puntosDAO.insertaDetalle(connection,
					fechaTransaccion, referencia, 20,
					redimidosTO.getPtsTransferidos(), null,
					parametrosTO.getCuenta(), parametrosTO.getSecuencia(),
					parametrosTO.getTelefono(),
					parametrosTO.getUsuariMovimiento());
			/*      */
			/*      */
			/* 950 */referencia = "CIR -CANCELA -"
					+ redimidosTO.getPtsTransferidos() + " PTOS. A PET. DE "
					+ parametrosTO.getUsuariMovimiento() + " "
					+ parametrosTO.getComentario();
			/* 951 */if (mensajeTO.getIdMensaje() == 0) {
				/* 952 */mensajeTO = puntosDAO.insertaComentarioTMP(connection,
						parametrosTO.getRegion(), parametrosTO.getCuenta(),
						parametrosTO.getUsuariMovimiento(), fechaTransaccion,
						referencia);
				/*      */}
			/*      */
			/*      */
			/* 956 */if (mensajeTO.getIdMensaje() == 0) {
				/* 957 */redimidosTO.setPtsAcumulados(0);
				/* 958 */redimidosTO.setPtsExcedentes(puntosTO
						.getPtsExcedentes()
						+ redimidosTO.getPtsExcedentesRedimidos());
				/* 959 */redimidosTO.setPtsPorVencer(redimidosTO
						.getPtsPorVencerRedimidos()
						+ puntosTO.getPtsPorVencer());
				/* 960 */redimidosTO.setPtsPorVencer1(redimidosTO
						.getPtsPorVencer1Redimidos()
						+ puntosTO.getPtsPorVencer1());
				/* 961 */redimidosTO.setPtsPorVencer2(redimidosTO
						.getPtsPorVencer2Redimidos()
						+ puntosTO.getPtsPorVencer2());
				/* 962 */redimidosTO.setPtsTransferidos(puntosTO
						.getPtsTransferidos()
						- redimidosTO.getPtsTransferidos());
				/* 963 */redimidosTO.setPtsRenta(puntosTO.getPtsRenta()
						+ redimidosTO.getPtsRentaRedimidos());
				/* 964 */redimidosTO.setPtsPromocion(puntosTO.getPtsPromocion()
						+ redimidosTO.getPtsPromocionRedimidos());
				/* 965 */redimidosTO.setPtsAntiguedad(puntosTO
						.getPtsAntiguedad()
						+ redimidosTO.getPtsPorAntiguedadRedimidos());
				/* 966 */mensajeTO = puntosDAO.actualizaPuntos(redimidosTO,
						connection, null, parametrosTO.getCuenta(),
						parametrosTO.getSecuencia(), false);
				/*      */}
			/*      */
			/*      */
			/* 970 */if (mensajeTO.getIdMensaje() == 0) {
				/* 971 */AlianzasTO alianzasTO = new AlianzasTO();
				/* 972 */alianzasTO.setEstatus("I");
				/* 973 */alianzasTO.setUsuario(parametrosTO
						.getUsuariMovimiento());
				/* 974 */if (parametrosTO.getOpcion() == 2) {
					/* 975 */alianzasTO.setStatusTrans(1);
					/*      */} else
					/* 977 */alianzasTO.setStatusTrans(estatusTrans);
				/* 978 */alianzasTO.setFolio(parametrosTO.getFolio());
				/* 979 */mensajeTO = actualizaAlianza(connection, alianzasTO,
						fechaTransaccion);
				/*      */}
			/* 981 */if (mensajeTO.getIdMensaje() == 0)
				/* 982 */connection.commit();
			else {
				/* 983 */connection.rollback();
				/*      */}
			/*      */} catch (SQLException e) {
			/* 986 */if (connection != null)
				try {
					connection.rollback();
				} catch (Exception localException3) {
				}
			/* 987 */this.error.info("SQLException.realizaCancelacion:", e);
			/* 988 */throw new CAException(-1,
					"[realizaCancelacion] SQLError: " + e.toString()
							+ "Actualizar Inf", e);
			/*      */} catch (Exception e) {
			/* 990 */this.error.info("Exception.realizaCancelacion:", e);
			/* 991 */throw new CAException(-1, "[realizaCancelacion] Error: "
					+ e.toString() + "Actualizar Inf", e);
			/*      */} finally {
			/* 993 */if (connection != null)
				try {
					connection.setAutoCommit(true);
					connection.close();
					connection = null;
				} catch (Exception localException4) {
				}
		}
		if (connection != null)
			try {
				connection.setAutoCommit(true);
				connection.close();
				connection = null;
				/*      */} catch (Exception localException5) {
			}
		/* 995 */return mensajeTO;
		/*      */}

	/*      */
	/*      *//* Error */
	/*      */private MensajeTO actualizaAlianza(Connection connection,
			AlianzasTO alianzasTO, long fechaActualizacion)
	/*      */throws CAException
	/*      */{
		return null;
		/*      */// Byte code:
		/*      */// 0: aconst_null
		/*      */// 1: astore 5
		/*      */// 3: new 605 com/claro/transfer/MensajeTO
		/*      */// 6: dup
		/*      */// 7: invokespecial 628 com/claro/transfer/MensajeTO:<init> ()V
		/*      */// 10: astore 6
		/*      */// 12: aconst_null
		/*      */// 13: astore 7
		/*      */// 15: new 293 java/lang/StringBuilder
		/*      */// 18: dup
		/*      */// 19: ldc_w 409
		/*      */// 22: invokespecial 297 java/lang/StringBuilder:<init>
				// (Ljava/lang/String;)V
		/*      */// 25: aload_0
		/*      */// 26: getfield 41 com/claro/dao/AlianzasDAO:schema_database
				// Ljava/lang/String;
		/*      */// 29: invokevirtual 300 java/lang/StringBuilder:append
				// (Ljava/lang/String;)Ljava/lang/StringBuilder;
		/*      */// 32: ldc_w 557
		/*      */// 35: invokevirtual 300 java/lang/StringBuilder:append
				// (Ljava/lang/String;)Ljava/lang/StringBuilder;
		/*      */// 38: ldc_w 1066
		/*      */// 41: invokevirtual 300 java/lang/StringBuilder:append
				// (Ljava/lang/String;)Ljava/lang/StringBuilder;
		/*      */// 44: invokevirtual 305 java/lang/StringBuilder:toString
				// ()Ljava/lang/String;
		/*      */// 47: astore 8
		/*      */// 49: aload_1
		/*      */// 50: ifnull +9 -> 59
		/*      */// 53: aload_1
		/*      */// 54: astore 5
		/*      */// 56: goto +14 -> 70
		/*      */// 59: invokestatic 29 com/claro/util/ServiceLocator:getInstance
				// ()Lcom/claro/util/ServiceLocator;
		/*      */// 62: getstatic 93 com/claro/util/ServiceLocator:jdbcCirculoAzul
				// Ljava/lang/String;
		/*      */// 65: invokevirtual 96 com/claro/util/ServiceLocator:getConnection
				// (Ljava/lang/String;)Ljava/sql/Connection;
		/*      */// 68: astore 5
		/*      */// 70: aload 5
		/*      */// 72: aload 8
		/*      */// 74: invokeinterface 104 2 0
		/*      */// 79: astore 7
		/*      */// 81: aload 7
		/*      */// 83: iconst_1
		/*      */// 84: aload_2
		/*      */// 85: invokevirtual 1068 com/claro/transfer/AlianzasTO:getEstatus
				// ()Ljava/lang/String;
		/*      */// 88: invokeinterface 110 3 0
		/*      */// 93: aload 7
		/*      */// 95: iconst_2
		/*      */// 96: new 362 java/sql/Date
		/*      */// 99: dup
		/*      */// 100: lload_3
		/*      */// 101: invokespecial 364 java/sql/Date:<init> (J)V
		/*      */// 104: invokeinterface 367 3 0
		/*      */// 109: aload 7
		/*      */// 111: iconst_3
		/*      */// 112: aload_2
		/*      */// 113: invokevirtual 1071 com/claro/transfer/AlianzasTO:getUsuario
				// ()Ljava/lang/String;
		/*      */// 116: invokeinterface 110 3 0
		/*      */// 121: aload 7
		/*      */// 123: iconst_4
		/*      */// 124: aload_2
		/*      */// 125: invokevirtual 1074
				// com/claro/transfer/AlianzasTO:getStatusTrans ()I
		/*      */// 128: invokeinterface 122 3 0
		/*      */// 133: aload 7
		/*      */// 135: iconst_5
		/*      */// 136: aload_2
		/*      */// 137: invokevirtual 447 com/claro/transfer/AlianzasTO:getFolio
				// ()Ljava/lang/String;
		/*      */// 140: invokeinterface 110 3 0
		/*      */// 145: aload 7
		/*      */// 147: invokeinterface 466 1 0
		/*      */// 152: ifle +15 -> 167
		/*      */// 155: aload 6
		/*      */// 157: iconst_0
		/*      */// 158: ldc_w 1077
		/*      */// 161: invokevirtual 685
				// com/claro/transfer/MensajeTO:agregaMensaje
				// (ILjava/lang/String;)V
		/*      */// 164: goto +163 -> 327
		/*      */// 167: aload 6
		/*      */// 169: iconst_1
		/*      */// 170: ldc_w 1079
		/*      */// 173: invokevirtual 685
				// com/claro/transfer/MensajeTO:agregaMensaje
				// (ILjava/lang/String;)V
		/*      */// 176: goto +151 -> 327
		/*      */// 179: astore 8
		/*      */// 181: aload_1
		/*      */// 182: ifnull +14 -> 196
		/*      */// 185: aload_1
		/*      */// 186: invokeinterface 486 1 0
		/*      */// 191: goto +5 -> 196
		/*      */// 194: astore 9
		/*      */// 196: aload_0
		/*      */// 197: getfield 27 com/claro/dao/AlianzasDAO:error
				// Lorg/apache/log4j/Logger;
		/*      */// 200: ldc_w 1081
		/*      */// 203: aload 8
		/*      */// 205: invokevirtual 393 org/apache/log4j/Logger:info
				// (Ljava/lang/Object;Ljava/lang/Throwable;)V
		/*      */// 208: new 59 com/claro/exception/CAException
		/*      */// 211: dup
		/*      */// 212: iconst_m1
		/*      */// 213: new 293 java/lang/StringBuilder
		/*      */// 216: dup
		/*      */// 217: ldc_w 1049
		/*      */// 220: invokespecial 297 java/lang/StringBuilder:<init>
				// (Ljava/lang/String;)V
		/*      */// 223: aload 8
		/*      */// 225: invokevirtual 491 java/sql/SQLException:toString
				// ()Ljava/lang/String;
		/*      */// 228: invokevirtual 300 java/lang/StringBuilder:append
				// (Ljava/lang/String;)Ljava/lang/StringBuilder;
		/*      */// 231: ldc_w 821
		/*      */// 234: invokevirtual 300 java/lang/StringBuilder:append
				// (Ljava/lang/String;)Ljava/lang/StringBuilder;
		/*      */// 237: invokevirtual 305 java/lang/StringBuilder:toString
				// ()Ljava/lang/String;
		/*      */// 240: aload 8
		/*      */// 242: invokespecial 222 com/claro/exception/CAException:<init>
				// (ILjava/lang/String;Ljava/lang/Exception;)V
		/*      */// 245: athrow
		/*      */// 246: astore 8
		/*      */// 248: aload_0
		/*      */// 249: getfield 27 com/claro/dao/AlianzasDAO:error
				// Lorg/apache/log4j/Logger;
		/*      */// 252: ldc_w 1083
		/*      */// 255: aload 8
		/*      */// 257: invokevirtual 393 org/apache/log4j/Logger:info
				// (Ljava/lang/Object;Ljava/lang/Throwable;)V
		/*      */// 260: new 59 com/claro/exception/CAException
		/*      */// 263: dup
		/*      */// 264: iconst_m1
		/*      */// 265: new 293 java/lang/StringBuilder
		/*      */// 268: dup
		/*      */// 269: ldc_w 1053
		/*      */// 272: invokespecial 297 java/lang/StringBuilder:<init>
				// (Ljava/lang/String;)V
		/*      */// 275: aload 8
		/*      */// 277: invokevirtual 299 java/lang/Exception:toString
				// ()Ljava/lang/String;
		/*      */// 280: invokevirtual 300 java/lang/StringBuilder:append
				// (Ljava/lang/String;)Ljava/lang/StringBuilder;
		/*      */// 283: ldc_w 821
		/*      */// 286: invokevirtual 300 java/lang/StringBuilder:append
				// (Ljava/lang/String;)Ljava/lang/StringBuilder;
		/*      */// 289: invokevirtual 305 java/lang/StringBuilder:toString
				// ()Ljava/lang/String;
		/*      */// 292: aload 8
		/*      */// 294: invokespecial 222 com/claro/exception/CAException:<init>
				// (ILjava/lang/String;Ljava/lang/Exception;)V
		/*      */// 297: athrow
		/*      */// 298: astore 10
		/*      */// 300: aload 5
		/*      */// 302: ifnull +22 -> 324
		/*      */// 305: aload_1
		/*      */// 306: ifnonnull +18 -> 324
		/*      */// 309: aload 5
		/*      */// 311: invokeinterface 233 1 0
		/*      */// 316: aconst_null
		/*      */// 317: astore 5
		/*      */// 319: goto +5 -> 324
		/*      */// 322: astore 11
		/*      */// 324: aload 10
		/*      */// 326: athrow
		/*      */// 327: aload 5
		/*      */// 329: ifnull +22 -> 351
		/*      */// 332: aload_1
		/*      */// 333: ifnonnull +18 -> 351
		/*      */// 336: aload 5
		/*      */// 338: invokeinterface 233 1 0
		/*      */// 343: aconst_null
		/*      */// 344: astore 5
		/*      */// 346: goto +5 -> 351
		/*      */// 349: astore 11
		/*      */// 351: aload 6
		/*      */// 353: areturn
		/*      */// Line number table:
		/*      */// Java source line #999 -> byte code offset #0
		/*      */// Java source line #1000 -> byte code offset #3
		/*      */// Java source line #1001 -> byte code offset #12
		/*      */// Java source line #1004 -> byte code offset #15
		/*      */// Java source line #1005 -> byte code offset #38
		/*      */// Java source line #1004 -> byte code offset #44
		/*      */// Java source line #1006 -> byte code offset #49
		/*      */// Java source line #1007 -> byte code offset #59
		/*      */// Java source line #1009 -> byte code offset #70
		/*      */// Java source line #1010 -> byte code offset #81
		/*      */// Java source line #1011 -> byte code offset #93
		/*      */// Java source line #1012 -> byte code offset #109
		/*      */// Java source line #1013 -> byte code offset #121
		/*      */// Java source line #1014 -> byte code offset #133
		/*      */// Java source line #1016 -> byte code offset #145
		/*      */// Java source line #1017 -> byte code offset #167
		/*      */// Java source line #1019 -> byte code offset #179
		/*      */// Java source line #1020 -> byte code offset #181
		/*      */// Java source line #1021 -> byte code offset #196
		/*      */// Java source line #1022 -> byte code offset #208
		/*      */// Java source line #1023 -> byte code offset #246
		/*      */// Java source line #1024 -> byte code offset #248
		/*      */// Java source line #1025 -> byte code offset #260
		/*      */// Java source line #1026 -> byte code offset #298
		/*      */// Java source line #1027 -> byte code offset #300
		/*      */// Java source line #1028 -> byte code offset #324
		/*      */// Java source line #1027 -> byte code offset #327
		/*      */// Java source line #1029 -> byte code offset #351
		/*      */// Local variable table:
		/*      */// start length slot name signature
		/*      */// 0 354 0 this AlianzasDAO
		/*      */// 0 354 1 connection Connection
		/*      */// 0 354 2 alianzasTO AlianzasTO
		/*      */// 0 354 3 fechaActualizacion long
		/*      */// 1 344 5 lConn Connection
		/*      */// 10 342 6 mensajeTO MensajeTO
		/*      */// 13 133 7 statement PreparedStatement
		/*      */// 47 26 8 query String
		/*      */// 179 62 8 e SQLException
		/*      */// 246 47 8 e Exception
		/*      */// 194 1 9 localException1 Exception
		/*      */// 298 27 10 localObject Object
		/*      */// 322 1 11 localException2 Exception
		/*      */// 349 1 11 localException3 Exception
		/*      */// Exception table:
		/*      */// from to target type
		/*      */// 15 176 179 java/sql/SQLException
		/*      */// 185 191 194 java/lang/Exception
		/*      */// 15 176 246 java/lang/Exception
		/*      */// 15 298 298 finally
		/*      */// 309 319 322 java/lang/Exception
		/*      */// 336 346 349 java/lang/Exception
		/*      */}

	/*      */
	/*      */public MensajeTO realizaCanje(ParametrosTO parametrosTO,
			int millasPorTranferir, int valorPuntos, String descAlianza,
			String cuentaAlianza, int ptsTransferir, int valorCertificado,
			String puntoVenta, String numEmpleado, String dirIP,
			String idViaje, int valorPesos, String referencia, int opcion)
	/*      */throws CAException
	/*      */{
		/* 1035 */Connection connection = null;
		/* 1036 */MensajeTO mensajeTO = new MensajeTO();
		/* 1037 */String comentario = null;
		/* 1038 */int movimiento = 0;
		/*      */try
		/*      */{
			/* 1041 */ConsultasDAO consultasDAO = new ConsultasDAO();
			/* 1042 */PuntosTO puntosTO = consultasDAO.obtienePuntos(
					parametrosTO.getCuenta(), parametrosTO.getSecuencia());
			/*      */
			/* 1044 */if (puntosTO.getIdMensaje() != 0) {
				/* 1045 */return puntosTO.obtieneMensajeTO();
				/*      */}
			/* 1047 */PuntosRedimidosTO redimidosTO = Utils.canjePuntos(
					puntosTO, valorPuntos, 7);
			/*      */
			/* 1049 */redimidosTO.setPtsTransferidos(valorPuntos);
			/*      */
			/* 1051 */PuntosDAO puntosDAO = new PuntosDAO();
			/* 1052 */long fechaTransaccion = System.currentTimeMillis();
			/*      */
			/* 1054 */String folio = Utils.generaFolio(parametrosTO
					.getTelefono());
			/*      */
			/*      */
			/*      */
			/* 1058 */AlianzasTO alianzasTO = new AlianzasTO();
			/* 1059 */alianzasTO.setFolio(folio);
			/* 1060 */alianzasTO.setSecuencia(parametrosTO.getSecuencia());
			/* 1061 */alianzasTO.setCuenta(parametrosTO.getCuenta());
			/* 1062 */alianzasTO.setStatusTrans(4);
			/* 1063 */alianzasTO.setUsuario(parametrosTO.getUsuariMovimiento());
			/* 1064 */alianzasTO.setEstatus("A");
			/* 1065 */alianzasTO.setCveAlianza(Integer.toString(parametrosTO
					.getOpcion()));
			/* 1066 */alianzasTO.setPuntosRedimidosTO(redimidosTO);
			/* 1067 */alianzasTO.setNumeroCanje(-1);
			/*      */
			/* 1069 */if (parametrosTO.getOpcion() == 2) {
				/* 1070 */opcion = -1;
				/*      */
				/* 1072 */alianzasTO.setIdCuentaAlianza(2);
				/* 1073 */alianzasTO.setCuentaAlianza(cuentaAlianza);
				/* 1074 */alianzasTO.setComentario("Canjeados a:" + descAlianza
						+ "," + parametrosTO.getComentario());
				/* 1075 */alianzasTO.setMillas(0);
				/* 1076 */alianzasTO.setArchivoSalida(idViaje);
				/* 1077 */alianzasTO.setValorCuponOrig(valorCertificado);
				/* 1078 */Calendar calendar = Calendar.getInstance();
				/* 1079 */calendar.setTimeInMillis(fechaTransaccion);
				/* 1080 */calendar.add(1, 1);
				/* 1081 */alianzasTO.setVigenciaMax(new java.sql.Date(calendar
						.getTimeInMillis()));
				/* 1082 */alianzasTO.setIdPuntoVenta(puntoVenta);
				/* 1083 */movimiento = 19;
				/* 1084 */alianzasTO.setNumeroCanje(-1);
				/*      */}
			/*      */
			/* 1087 */connection = ServiceLocator.getInstance().getConnection(
					ServiceLocator.jdbcCirculoAzul);
			/* 1088 */connection.setAutoCommit(false);
			/*      */
			/* 1090 */mensajeTO = insertaAlianza(connection, alianzasTO,
					puntosTO, fechaTransaccion);
			/*      */
			/* 1092 */if (mensajeTO.getIdMensaje() == 0)
			/*      */{
				/* 1094 */comentario = "Canjeados a:" + descAlianza + "->"
						+ parametrosTO.getComentario() + ", atendio: "
						+ numEmpleado + " IP: " + dirIP;
				/* 1095 */if (comentario.length() > 100)
					/* 1096 */comentario = comentario.substring(0, 100);
				/* 1097 */mensajeTO = puntosDAO.insertaDetalle(connection,
						fechaTransaccion, comentario, movimiento, ptsTransferir
								* -1, null, parametrosTO.getCuenta(),
						parametrosTO.getSecuencia(),
						parametrosTO.getTelefono(),
						parametrosTO.getUsuariMovimiento());
				/*      */}
			/*      */
			/* 1100 */if (mensajeTO.getIdMensaje() == 0) {
				/* 1101 */redimidosTO.setPtsTransferidos(puntosTO
						.getPtsTransferidos() + valorPuntos);
				/* 1102 */mensajeTO = puntosDAO.actualizaPuntos(redimidosTO,
						connection, null, parametrosTO.getCuenta(),
						parametrosTO.getSecuencia(), false);
				/*      */}
			/*      */
			/* 1105 */if (mensajeTO.getIdMensaje() == 0) {
				/* 1106 */comentario = "CIR - CANJE DE -" + valorPuntos
						+ " PTOS. A " + "AMEX " + "A PET. DE "
						+ parametrosTO.getUsuariMovimiento() + " "
						+ parametrosTO.getComentario().toUpperCase();
				/*      */
				/* 1108 */comentario = "PTO.VTA:" + puntoVenta + "-"
						+ comentario;
				/* 1109 */mensajeTO = puntosDAO.insertaComentarioTMP(
						connection, parametrosTO.getRegion(),
						parametrosTO.getCuenta(),
						parametrosTO.getUsuariMovimiento(), fechaTransaccion,
						comentario);
				/*      */}
			/*      */
			/* 1112 */if (mensajeTO.getIdMensaje() == 0) {
				/* 1113 */Catalogo properties = new Catalogo();
				/*      */
				/* 1115 */properties.setTabla("propiedades");
				/* 1116 */properties.cargaCatalogo();
				/*      */
				/*      */
				/*      */
				/* 1120 */String linea = parametrosTO.getTelefono();
				/*      */
				/* 1122 */SimpleDateFormat sdf = new SimpleDateFormat(
						"dd-MM-yy");
				/* 1123 */String fechaHoy = sdf.format(new java.util.Date());
				/*      */
				/* 1125 */String mensajeSMS = fechaHoy
						+ " Redencion de "
						+ ptsTransferir
						+ " Puntos por CERTIFICADO AMEX. Para cualquier aclaracion marca *111 desde tu Telcel.";
				/* 1126 */NotificaSMS notificaSMS = new NotificaSMS();
				/* 1127 */notificaSMS.enviaSMSRedencionCA(linea, mensajeSMS,
						properties);
				/*      */
				/* 1129 */connection.commit();
				/*      */} else {
				/* 1131 */connection.rollback();
				/*      */}
			/*      */} catch (SQLException e) {
			/* 1134 */if (connection != null)
				try {
					connection.rollback();
				} catch (Exception localException2) {
				}
			/* 1135 */this.error.info("SQLException.realizaCanje:", e);
			/* 1136 */throw new CAException(-1, "[realizaCanje] SQLError: "
					+ e.toString() + "Actualizar Inf", e);
			/*      */} catch (Exception e) {
			/* 1138 */if (connection != null)
				try {
					connection.rollback();
				} catch (Exception localException3) {
				}
			/* 1139 */this.error.info("Exception.realizaCanje:", e);
			/* 1140 */throw new CAException(-1, "[realizaCanje] Error: "
					+ e.toString() + "Actualizar Inf", e);
			/*      */} finally {
			/* 1142 */if (connection != null)
				try {
					connection.setAutoCommit(true);
					connection.close();
					connection = null;
				} catch (Exception localException4) {
				}
		}
		if (connection != null)
			try {
				connection.setAutoCommit(true);
				connection.close();
				connection = null;
				/*      */} catch (Exception localException5) {
			}
		/* 1144 */return mensajeTO;
		/*      */}

	/*      */
	/*      *//* Error */
	/*      */private MensajeTO insertaAlianza(Connection connection,
			AlianzasTO alianzasTO, PuntosTO puntosTO, long fechaOperacion)
	/*      */throws CAException
	/*      */{
		return null;
		/*      */// Byte code:
		/*      */// 0: aconst_null
		/*      */// 1: astore 6
		/*      */// 3: new 605 com/claro/transfer/MensajeTO
		/*      */// 6: dup
		/*      */// 7: invokespecial 628 com/claro/transfer/MensajeTO:<init> ()V
		/*      */// 10: astore 7
		/*      */// 12: new 293 java/lang/StringBuilder
		/*      */// 15: dup
		/*      */// 16: ldc_w 415
		/*      */// 19: invokespecial 297 java/lang/StringBuilder:<init>
				// (Ljava/lang/String;)V
		/*      */// 22: aload_0
		/*      */// 23: getfield 41 com/claro/dao/AlianzasDAO:schema_database
				// Ljava/lang/String;
		/*      */// 26: invokevirtual 300 java/lang/StringBuilder:append
				// (Ljava/lang/String;)Ljava/lang/StringBuilder;
		/*      */// 29: ldc_w 1211
		/*      */// 32: invokevirtual 300 java/lang/StringBuilder:append
				// (Ljava/lang/String;)Ljava/lang/StringBuilder;
		/*      */// 35: ldc_w 1213
		/*      */// 38: invokevirtual 300 java/lang/StringBuilder:append
				// (Ljava/lang/String;)Ljava/lang/StringBuilder;
		/*      */// 41: ldc_w 1215
		/*      */// 44: invokevirtual 300 java/lang/StringBuilder:append
				// (Ljava/lang/String;)Ljava/lang/StringBuilder;
		/*      */// 47: ldc_w 1217
		/*      */// 50: invokevirtual 300 java/lang/StringBuilder:append
				// (Ljava/lang/String;)Ljava/lang/StringBuilder;
		/*      */// 53: ldc_w 1219
		/*      */// 56: invokevirtual 300 java/lang/StringBuilder:append
				// (Ljava/lang/String;)Ljava/lang/StringBuilder;
		/*      */// 59: invokevirtual 305 java/lang/StringBuilder:toString
				// ()Ljava/lang/String;
		/*      */// 62: astore 8
		/*      */// 64: aload_1
		/*      */// 65: aload 8
		/*      */// 67: invokeinterface 104 2 0
		/*      */// 72: astore 6
		/*      */// 74: aload 6
		/*      */// 76: iconst_1
		/*      */// 77: aload_2
		/*      */// 78: invokevirtual 447 com/claro/transfer/AlianzasTO:getFolio
				// ()Ljava/lang/String;
		/*      */// 81: invokeinterface 110 3 0
		/*      */// 86: aload 6
		/*      */// 88: iconst_2
		/*      */// 89: aload_2
		/*      */// 90: invokevirtual 1221
				// com/claro/transfer/AlianzasTO:getCuentaAlianza
				// ()Ljava/lang/String;
		/*      */// 93: invokeinterface 110 3 0
		/*      */// 98: aload 6
		/*      */// 100: iconst_3
		/*      */// 101: aload_2
		/*      */// 102: invokevirtual 1224
				// com/claro/transfer/AlianzasTO:getIdCuentaAlianza ()I
		/*      */// 105: invokeinterface 122 3 0
		/*      */// 110: aload 6
		/*      */// 112: iconst_4
		/*      */// 113: aload_2
		/*      */// 114: invokevirtual 1074
				// com/claro/transfer/AlianzasTO:getStatusTrans ()I
		/*      */// 117: invokeinterface 122 3 0
		/*      */// 122: aload 6
		/*      */// 124: iconst_5
		/*      */// 125: aload_2
		/*      */// 126: invokevirtual 1227
				// com/claro/transfer/AlianzasTO:getSecuencia ()I
		/*      */// 129: invokeinterface 122 3 0
		/*      */// 134: aload 6
		/*      */// 136: bipush 6
		/*      */// 138: aload_2
		/*      */// 139: invokevirtual 1228
				// com/claro/transfer/AlianzasTO:getPuntosRedimidosTO
				// ()Lcom/claro/transfer/PuntosRedimidosTO;
		/*      */// 142: invokevirtual 979
				// com/claro/transfer/PuntosRedimidosTO:getPtsPorVencerRedimidos
				// ()I
		/*      */// 145: invokeinterface 122 3 0
		/*      */// 150: aload 6
		/*      */// 152: bipush 7
		/*      */// 154: aload_2
		/*      */// 155: invokevirtual 1228
				// com/claro/transfer/AlianzasTO:getPuntosRedimidosTO
				// ()Lcom/claro/transfer/PuntosRedimidosTO;
		/*      */// 158: invokevirtual 988
				// com/claro/transfer/PuntosRedimidosTO:getPtsPorVencer1Redimidos
				// ()I
		/*      */// 161: invokeinterface 122 3 0
		/*      */// 166: aload 6
		/*      */// 168: bipush 8
		/*      */// 170: aload_2
		/*      */// 171: invokevirtual 1228
				// com/claro/transfer/AlianzasTO:getPuntosRedimidosTO
				// ()Lcom/claro/transfer/PuntosRedimidosTO;
		/*      */// 174: invokevirtual 997
				// com/claro/transfer/PuntosRedimidosTO:getPtsPorVencer2Redimidos
				// ()I
		/*      */// 177: invokeinterface 122 3 0
		/*      */// 182: aload 6
		/*      */// 184: bipush 9
		/*      */// 186: aload_2
		/*      */// 187: invokevirtual 1228
				// com/claro/transfer/AlianzasTO:getPuntosRedimidosTO
				// ()Lcom/claro/transfer/PuntosRedimidosTO;
		/*      */// 190: invokevirtual 1011
				// com/claro/transfer/PuntosRedimidosTO:getPtsRentaRedimidos ()I
		/*      */// 193: invokeinterface 122 3 0
		/*      */// 198: aload 6
		/*      */// 200: bipush 10
		/*      */// 202: aload_2
		/*      */// 203: invokevirtual 1228
				// com/claro/transfer/AlianzasTO:getPuntosRedimidosTO
				// ()Lcom/claro/transfer/PuntosRedimidosTO;
		/*      */// 206: invokevirtual 973
				// com/claro/transfer/PuntosRedimidosTO:getPtsExcedentesRedimidos
				// ()I
		/*      */// 209: invokeinterface 122 3 0
		/*      */// 214: aload 6
		/*      */// 216: bipush 11
		/*      */// 218: aload_2
		/*      */// 219: invokevirtual 1228
				// com/claro/transfer/AlianzasTO:getPuntosRedimidosTO
				// ()Lcom/claro/transfer/PuntosRedimidosTO;
		/*      */// 222: invokevirtual 945
				// com/claro/transfer/PuntosRedimidosTO:getPtsTransferidos ()I
		/*      */// 225: invokeinterface 122 3 0
		/*      */// 230: aload 6
		/*      */// 232: bipush 12
		/*      */// 234: new 362 java/sql/Date
		/*      */// 237: dup
		/*      */// 238: lload 4
		/*      */// 240: invokespecial 364 java/sql/Date:<init> (J)V
		/*      */// 243: invokeinterface 367 3 0
		/*      */// 248: aload 6
		/*      */// 250: bipush 13
		/*      */// 252: aload_2
		/*      */// 253: invokevirtual 1232 com/claro/transfer/AlianzasTO:getCuenta
				// ()Ljava/lang/String;
		/*      */// 256: invokeinterface 110 3 0
		/*      */// 261: aload 6
		/*      */// 263: bipush 14
		/*      */// 265: aload_2
		/*      */// 266: invokevirtual 1233
				// com/claro/transfer/AlianzasTO:getComentario
				// ()Ljava/lang/String;
		/*      */// 269: invokeinterface 110 3 0
		/*      */// 274: aload 6
		/*      */// 276: bipush 15
		/*      */// 278: aload_2
		/*      */// 279: invokevirtual 1071 com/claro/transfer/AlianzasTO:getUsuario
				// ()Ljava/lang/String;
		/*      */// 282: invokeinterface 110 3 0
		/*      */// 287: aload 6
		/*      */// 289: bipush 16
		/*      */// 291: aload_2
		/*      */// 292: invokevirtual 1068 com/claro/transfer/AlianzasTO:getEstatus
				// ()Ljava/lang/String;
		/*      */// 295: invokeinterface 110 3 0
		/*      */// 300: aload 6
		/*      */// 302: bipush 17
		/*      */// 304: aload_2
		/*      */// 305: invokevirtual 1234 com/claro/transfer/AlianzasTO:getMillas
				// ()I
		/*      */// 308: invokeinterface 122 3 0
		/*      */// 313: aload 6
		/*      */// 315: bipush 18
		/*      */// 317: aload_3
		/*      */// 318: invokevirtual 1237
				// com/claro/transfer/PuntosTO:getPtosDisponibles ()I
		/*      */// 321: invokeinterface 122 3 0
		/*      */// 326: aload_2
		/*      */// 327: invokevirtual 1240
				// com/claro/transfer/AlianzasTO:getArchivoSalida
				// ()Ljava/lang/String;
		/*      */// 330: ifnonnull +17 -> 347
		/*      */// 333: aload 6
		/*      */// 335: bipush 19
		/*      */// 337: bipush 12
		/*      */// 339: invokeinterface 1243 3 0
		/*      */// 344: goto +16 -> 360
		/*      */// 347: aload 6
		/*      */// 349: bipush 19
		/*      */// 351: aload_2
		/*      */// 352: invokevirtual 1240
				// com/claro/transfer/AlianzasTO:getArchivoSalida
				// ()Ljava/lang/String;
		/*      */// 355: invokeinterface 110 3 0
		/*      */// 360: aload 6
		/*      */// 362: bipush 20
		/*      */// 364: aload_2
		/*      */// 365: invokevirtual 1246
				// com/claro/transfer/AlianzasTO:getNumeroCanje ()I
		/*      */// 368: invokeinterface 122 3 0
		/*      */// 373: aload 6
		/*      */// 375: bipush 21
		/*      */// 377: aload_2
		/*      */// 378: invokevirtual 1249
				// com/claro/transfer/AlianzasTO:getIdPuntoVenta
				// ()Ljava/lang/String;
		/*      */// 381: invokeinterface 110 3 0
		/*      */// 386: aload 6
		/*      */// 388: bipush 22
		/*      */// 390: aload_2
		/*      */// 391: invokevirtual 1228
				// com/claro/transfer/AlianzasTO:getPuntosRedimidosTO
				// ()Lcom/claro/transfer/PuntosRedimidosTO;
		/*      */// 394: invokevirtual 1029
				// com/claro/transfer/PuntosRedimidosTO:getPtsPorAntiguedadRedimidos
				// ()I
		/*      */// 397: invokeinterface 122 3 0
		/*      */// 402: aload 6
		/*      */// 404: bipush 23
		/*      */// 406: aload_2
		/*      */// 407: invokevirtual 1228
				// com/claro/transfer/AlianzasTO:getPuntosRedimidosTO
				// ()Lcom/claro/transfer/PuntosRedimidosTO;
		/*      */// 410: invokevirtual 1020
				// com/claro/transfer/PuntosRedimidosTO:getPtsPromocionRedimidos
				// ()I
		/*      */// 413: invokeinterface 122 3 0
		/*      */// 418: aload_2
		/*      */// 419: invokevirtual 1252
				// com/claro/transfer/AlianzasTO:getValorCuponOrig ()I
		/*      */// 422: ifle +19 -> 441
		/*      */// 425: aload 6
		/*      */// 427: bipush 24
		/*      */// 429: aload_2
		/*      */// 430: invokevirtual 1252
				// com/claro/transfer/AlianzasTO:getValorCuponOrig ()I
		/*      */// 433: invokeinterface 122 3 0
		/*      */// 438: goto +13 -> 451
		/*      */// 441: aload 6
		/*      */// 443: bipush 24
		/*      */// 445: iconst_4
		/*      */// 446: invokeinterface 1243 3 0
		/*      */// 451: aload_2
		/*      */// 452: invokevirtual 452
				// com/claro/transfer/AlianzasTO:getVigenciaMax
				// ()Ljava/sql/Date;
		/*      */// 455: ifnonnull +17 -> 472
		/*      */// 458: aload 6
		/*      */// 460: bipush 25
		/*      */// 462: bipush 91
		/*      */// 464: invokeinterface 1243 3 0
		/*      */// 469: goto +16 -> 485
		/*      */// 472: aload 6
		/*      */// 474: bipush 25
		/*      */// 476: aload_2
		/*      */// 477: invokevirtual 452
				// com/claro/transfer/AlianzasTO:getVigenciaMax
				// ()Ljava/sql/Date;
		/*      */// 480: invokeinterface 367 3 0
		/*      */// 485: aload_2
		/*      */// 486: invokevirtual 1255
				// com/claro/transfer/AlianzasTO:getIdReferencia
				// ()Ljava/lang/String;
		/*      */// 489: ifnonnull +17 -> 506
		/*      */// 492: aload 6
		/*      */// 494: bipush 26
		/*      */// 496: bipush 12
		/*      */// 498: invokeinterface 1243 3 0
		/*      */// 503: goto +16 -> 519
		/*      */// 506: aload 6
		/*      */// 508: bipush 26
		/*      */// 510: aload_2
		/*      */// 511: invokevirtual 1255
				// com/claro/transfer/AlianzasTO:getIdReferencia
				// ()Ljava/lang/String;
		/*      */// 514: invokeinterface 110 3 0
		/*      */// 519: aload_2
		/*      */// 520: invokevirtual 1258
				// com/claro/transfer/AlianzasTO:getFechaFolio
				// ()Ljava/sql/Timestamp;
		/*      */// 523: ifnonnull +17 -> 540
		/*      */// 526: aload 6
		/*      */// 528: bipush 27
		/*      */// 530: bipush 93
		/*      */// 532: invokeinterface 1243 3 0
		/*      */// 537: goto +16 -> 553
		/*      */// 540: aload 6
		/*      */// 542: bipush 27
		/*      */// 544: aload_2
		/*      */// 545: invokevirtual 1258
				// com/claro/transfer/AlianzasTO:getFechaFolio
				// ()Ljava/sql/Timestamp;
		/*      */// 548: invokeinterface 472 3 0
		/*      */// 553: aload_2
		/*      */// 554: invokevirtual 1262 com/claro/transfer/AlianzasTO:getOpcion
				// ()I
		/*      */// 557: iconst_m1
		/*      */// 558: if_icmpne +16 -> 574
		/*      */// 561: aload 6
		/*      */// 563: bipush 28
		/*      */// 565: iconst_4
		/*      */// 566: invokeinterface 1243 3 0
		/*      */// 571: goto +16 -> 587
		/*      */// 574: aload 6
		/*      */// 576: bipush 28
		/*      */// 578: aload_2
		/*      */// 579: invokevirtual 1262 com/claro/transfer/AlianzasTO:getOpcion
				// ()I
		/*      */// 582: invokeinterface 122 3 0
		/*      */// 587: aload 6
		/*      */// 589: bipush 29
		/*      */// 591: aload_2
		/*      */// 592: invokevirtual 1228
				// com/claro/transfer/AlianzasTO:getPuntosRedimidosTO
				// ()Lcom/claro/transfer/PuntosRedimidosTO;
		/*      */// 595: invokevirtual 1263
				// com/claro/transfer/PuntosRedimidosTO:getPtosDisponibles ()I
		/*      */// 598: invokeinterface 122 3 0
		/*      */// 603: aload 6
		/*      */// 605: bipush 30
		/*      */// 607: aload_3
		/*      */// 608: invokevirtual 1237
				// com/claro/transfer/PuntosTO:getPtosDisponibles ()I
		/*      */// 611: invokeinterface 122 3 0
		/*      */// 616: aload 6
		/*      */// 618: invokeinterface 466 1 0
		/*      */// 623: ifle +15 -> 638
		/*      */// 626: aload 7
		/*      */// 628: iconst_0
		/*      */// 629: ldc_w 683
		/*      */// 632: invokevirtual 685
				// com/claro/transfer/MensajeTO:agregaMensaje
				// (ILjava/lang/String;)V
		/*      */// 635: goto +144 -> 779
		/*      */// 638: aload 7
		/*      */// 640: iconst_1
		/*      */// 641: ldc_w 1264
		/*      */// 644: invokevirtual 685
				// com/claro/transfer/MensajeTO:agregaMensaje
				// (ILjava/lang/String;)V
		/*      */// 647: goto +132 -> 779
		/*      */// 650: astore 8
		/*      */// 652: aload_0
		/*      */// 653: getfield 27 com/claro/dao/AlianzasDAO:error
				// Lorg/apache/log4j/Logger;
		/*      */// 656: ldc_w 1266
		/*      */// 659: aload 8
		/*      */// 661: invokevirtual 393 org/apache/log4j/Logger:info
				// (Ljava/lang/Object;Ljava/lang/Throwable;)V
		/*      */// 664: new 59 com/claro/exception/CAException
		/*      */// 667: dup
		/*      */// 668: iconst_m1
		/*      */// 669: new 293 java/lang/StringBuilder
		/*      */// 672: dup
		/*      */// 673: ldc_w 1268
		/*      */// 676: invokespecial 297 java/lang/StringBuilder:<init>
				// (Ljava/lang/String;)V
		/*      */// 679: aload 8
		/*      */// 681: invokevirtual 491 java/sql/SQLException:toString
				// ()Ljava/lang/String;
		/*      */// 684: invokevirtual 300 java/lang/StringBuilder:append
				// (Ljava/lang/String;)Ljava/lang/StringBuilder;
		/*      */// 687: ldc_w 846
		/*      */// 690: invokevirtual 300 java/lang/StringBuilder:append
				// (Ljava/lang/String;)Ljava/lang/StringBuilder;
		/*      */// 693: invokevirtual 305 java/lang/StringBuilder:toString
				// ()Ljava/lang/String;
		/*      */// 696: aload 8
		/*      */// 698: invokespecial 222 com/claro/exception/CAException:<init>
				// (ILjava/lang/String;Ljava/lang/Exception;)V
		/*      */// 701: athrow
		/*      */// 702: astore 8
		/*      */// 704: aload_0
		/*      */// 705: getfield 27 com/claro/dao/AlianzasDAO:error
				// Lorg/apache/log4j/Logger;
		/*      */// 708: ldc_w 1270
		/*      */// 711: aload 8
		/*      */// 713: invokevirtual 393 org/apache/log4j/Logger:info
				// (Ljava/lang/Object;Ljava/lang/Throwable;)V
		/*      */// 716: new 59 com/claro/exception/CAException
		/*      */// 719: dup
		/*      */// 720: iconst_m1
		/*      */// 721: new 293 java/lang/StringBuilder
		/*      */// 724: dup
		/*      */// 725: ldc_w 1272
		/*      */// 728: invokespecial 297 java/lang/StringBuilder:<init>
				// (Ljava/lang/String;)V
		/*      */// 731: aload 8
		/*      */// 733: invokevirtual 299 java/lang/Exception:toString
				// ()Ljava/lang/String;
		/*      */// 736: invokevirtual 300 java/lang/StringBuilder:append
				// (Ljava/lang/String;)Ljava/lang/StringBuilder;
		/*      */// 739: ldc_w 846
		/*      */// 742: invokevirtual 300 java/lang/StringBuilder:append
				// (Ljava/lang/String;)Ljava/lang/StringBuilder;
		/*      */// 745: invokevirtual 305 java/lang/StringBuilder:toString
				// ()Ljava/lang/String;
		/*      */// 748: aload 8
		/*      */// 750: invokespecial 222 com/claro/exception/CAException:<init>
				// (ILjava/lang/String;Ljava/lang/Exception;)V
		/*      */// 753: athrow
		/*      */// 754: astore 9
		/*      */// 756: aload 6
		/*      */// 758: ifnull +18 -> 776
		/*      */// 761: aload 6
		/*      */// 763: invokeinterface 232 1 0
		/*      */// 768: aconst_null
		/*      */// 769: astore 6
		/*      */// 771: goto +5 -> 776
		/*      */// 774: astore 10
		/*      */// 776: aload 9
		/*      */// 778: athrow
		/*      */// 779: aload 6
		/*      */// 781: ifnull +18 -> 799
		/*      */// 784: aload 6
		/*      */// 786: invokeinterface 232 1 0
		/*      */// 791: aconst_null
		/*      */// 792: astore 6
		/*      */// 794: goto +5 -> 799
		/*      */// 797: astore 10
		/*      */// 799: aload 7
		/*      */// 801: areturn
		/*      */// Line number table:
		/*      */// Java source line #1148 -> byte code offset #0
		/*      */// Java source line #1149 -> byte code offset #3
		/*      */// Java source line #1152 -> byte code offset #12
		/*      */// Java source line #1153 -> byte code offset #35
		/*      */// Java source line #1154 -> byte code offset #41
		/*      */// Java source line #1155 -> byte code offset #47
		/*      */// Java source line #1156 -> byte code offset #53
		/*      */// Java source line #1152 -> byte code offset #59
		/*      */// Java source line #1151 -> byte code offset #62
		/*      */// Java source line #1157 -> byte code offset #64
		/*      */// Java source line #1158 -> byte code offset #74
		/*      */// Java source line #1159 -> byte code offset #86
		/*      */// Java source line #1160 -> byte code offset #98
		/*      */// Java source line #1161 -> byte code offset #110
		/*      */// Java source line #1162 -> byte code offset #122
		/*      */// Java source line #1163 -> byte code offset #134
		/*      */// Java source line #1164 -> byte code offset #150
		/*      */// Java source line #1165 -> byte code offset #166
		/*      */// Java source line #1166 -> byte code offset #182
		/*      */// Java source line #1167 -> byte code offset #198
		/*      */// Java source line #1168 -> byte code offset #214
		/*      */// Java source line #1169 -> byte code offset #230
		/*      */// Java source line #1170 -> byte code offset #248
		/*      */// Java source line #1171 -> byte code offset #261
		/*      */// Java source line #1172 -> byte code offset #274
		/*      */// Java source line #1173 -> byte code offset #287
		/*      */// Java source line #1174 -> byte code offset #300
		/*      */// Java source line #1175 -> byte code offset #313
		/*      */// Java source line #1176 -> byte code offset #326
		/*      */// Java source line #1177 -> byte code offset #333
		/*      */// Java source line #1179 -> byte code offset #347
		/*      */// Java source line #1180 -> byte code offset #360
		/*      */// Java source line #1181 -> byte code offset #373
		/*      */// Java source line #1182 -> byte code offset #386
		/*      */// Java source line #1183 -> byte code offset #402
		/*      */// Java source line #1185 -> byte code offset #418
		/*      */// Java source line #1186 -> byte code offset #441
		/*      */// Java source line #1188 -> byte code offset #451
		/*      */// Java source line #1189 -> byte code offset #472
		/*      */// Java source line #1191 -> byte code offset #485
		/*      */// Java source line #1192 -> byte code offset #506
		/*      */// Java source line #1194 -> byte code offset #519
		/*      */// Java source line #1195 -> byte code offset #540
		/*      */// Java source line #1197 -> byte code offset #553
		/*      */// Java source line #1198 -> byte code offset #574
		/*      */// Java source line #1200 -> byte code offset #587
		/*      */// Java source line #1201 -> byte code offset #603
		/*      */// Java source line #1204 -> byte code offset #616
		/*      */// Java source line #1205 -> byte code offset #638
		/*      */// Java source line #1206 -> byte code offset #650
		/*      */// Java source line #1207 -> byte code offset #652
		/*      */// Java source line #1208 -> byte code offset #664
		/*      */// Java source line #1209 -> byte code offset #702
		/*      */// Java source line #1210 -> byte code offset #704
		/*      */// Java source line #1211 -> byte code offset #716
		/*      */// Java source line #1212 -> byte code offset #754
		/*      */// Java source line #1213 -> byte code offset #756
		/*      */// Java source line #1214 -> byte code offset #776
		/*      */// Java source line #1213 -> byte code offset #779
		/*      */// Java source line #1215 -> byte code offset #799
		/*      */// Local variable table:
		/*      */// start length slot name signature
		/*      */// 0 802 0 this AlianzasDAO
		/*      */// 0 802 1 connection Connection
		/*      */// 0 802 2 alianzasTO AlianzasTO
		/*      */// 0 802 3 puntosTO PuntosTO
		/*      */// 0 802 4 fechaOperacion long
		/*      */// 1 792 6 statement PreparedStatement
		/*      */// 10 790 7 mensajeTO MensajeTO
		/*      */// 62 4 8 squery String
		/*      */// 650 47 8 e SQLException
		/*      */// 702 47 8 e Exception
		/*      */// 754 23 9 localObject Object
		/*      */// 774 1 10 localException1 Exception
		/*      */// 797 1 10 localException2 Exception
		/*      */// Exception table:
		/*      */// from to target type
		/*      */// 12 647 650 java/sql/SQLException
		/*      */// 12 647 702 java/lang/Exception
		/*      */// 12 754 754 finally
		/*      */// 761 771 774 java/lang/Exception
		/*      */// 784 794 797 java/lang/Exception
		/*      */}

	/*      */
	/*      */public Hashtable<String, AlianzasTO> consultaInicialAlianzas(
			int iRegion, String sCuenta, int nPtsDisp, int iSecuencia)
	/*      */throws CAException
	/*      */{
		/*      */try
		/*      */{
			/* 1222 */CatalogoDAO catalogoDAO = new CatalogoDAO();
			/* 1223 */ArrayList<AlianzasTO> alianzas = catalogoDAO
					.consultaAlianzas(0, sCuenta, iSecuencia, "A", null);
			/*      */
			/* 1225 */if (alianzas != null) {
				/* 1226 */Iterator<AlianzasTO> iterator = alianzas.iterator();
				/* 1227 */Hashtable<String, AlianzasTO> hashtable = new Hashtable();
				/* 1228 */while (iterator.hasNext()) {
					/* 1229 */AlianzasTO alianzasTO = (AlianzasTO) iterator
							.next();
					/*      */
					/* 1231 */if (alianzasTO.getIdCuentaAlianza() == 2) {
						/* 1232 */alianzasTO.setCupones(consultaCuponesAmex(
								sCuenta, iSecuencia));
						/* 1233 */alianzasTO.setProductos(catalogoDAO
								.listaPromociones(iRegion, nPtsDisp, null,
										1086, "TELCEL", "TELCEL", null, null));
						/* 1234 */hashtable.put("AMEX", alianzasTO);
						/*      */}
					/*      */}
				/* 1237 */return hashtable;
				/*      */}
			/*      */}
		/*      */catch (Exception e) {
			/* 1241 */throw new CAException(
					-1,
					"AlianzasDAO.consultaInicialAlianzas[" + e.toString() + "]",
					e);
			/*      */}
		/* 1243 */return null;
		/*      */}

	/*      */
	/*      */public AlianzasTO consultaPromocionesAmex(int alianza, int iRegion,
			String linea, int iSecuencia, int ptosDisponibles)
	/*      */throws CAException
	/*      */{
		/*      */try
		/*      */{
			/* 1251 */CatalogoDAO catalogoDAO = new CatalogoDAO();
			/* 1252 */AlianzasTO alianzasTO = catalogoDAO.consultaAlianza(
					alianza, linea, iSecuencia, "A");
			/*      */
			/* 1254 */if (alianzasTO != null)
			/*      */{
				/* 1256 */if (alianzasTO.getIdCuentaAlianza() == 2) {
					/* 1257 */alianzasTO.setProductos(catalogoDAO
							.listaPromociones(iRegion, ptosDisponibles, null,
									1086, "TELCEL", "TELCEL", null, null));
					/*      */}
				/*      */}
			/* 1260 */return alianzasTO;
			/*      */} catch (Exception e) {
			/* 1262 */throw new CAException(
					-1,
					"AlianzasDAO.consultaInicialAlianzas[" + e.toString() + "]",
					e);
			/*      */}
		/*      */}

	/*      */
	/*      */public AlianzasTO consultaPromocionesTicketMaster(int region,
			int ptsDisp) throws CAException {
		/* 1267 */AlianzasTO alianzasTO = new AlianzasTO();
		/* 1268 */CatalogoDAO catalogoDAO = new CatalogoDAO();
		/* 1269 */alianzasTO.setProductos(catalogoDAO.listaPromociones(region,
				ptsDisp, null, 1086, "TELCEL", "TELCEL", null, null));
		/* 1270 */return alianzasTO;
		/*      */}
	/*      */
}

/*
 * Location:
 * /opt/trabajo/claro/Guatemala/IS/CO/ClaroClub.ear!/ClaroClubEJB.jar!/
 * com/claro/dao/AlianzasDAO.class Java compiler version: 6 (50.0) JD-Core
 * Version: 0.7.1
 */