/*    */ package com.claro.dao;
/*    */ 
/*    */ import com.claro.util.ServiceLocator;
/*    */ import org.apache.log4j.Logger;
/*    */ 
/*    */ 
/*    */ 
/*    */ 
/*    */ 
/*    */ 
/*    */ 
/*    */ 
/*    */ 
/*    */ 
/*    */ 
/*    */ 
/*    */ 
/*    */ public class AsignacionPorErrorAplicaDAO
/*    */ {
/* 20 */   protected final Logger logger = Logger.getLogger("loggerCirculoAzul");
/* 21 */   protected final Logger error = Logger.getLogger("loggerCirculoAzulError");
/*    */   private String schema_database;
/*    */   
/*    */   public AsignacionPorErrorAplicaDAO() {
/*    */     try {
/* 26 */       this.schema_database = ServiceLocator.getInstance().getVariable(ServiceLocator.schema_database);
/*    */     } catch (Exception e) {
/* 28 */       this.error.error("ReactivaDAO", e);
/*    */     }
/*    */   }
/*    */   
/*    */   /* Error */
/*    */   public void AsignacionPorErrorAplic(com.claro.transfer.AsignaPorErrorTO asignaPorErrorTO, String Cuenta, String Telefono, String numempleado)
/*    */     throws com.claro.exception.CAException
/*    */   {
/*    */     // Byte code:
/*    */     //   0: aconst_null
/*    */     //   1: astore 5
/*    */     //   3: aconst_null
/*    */     //   4: astore 6
/*    */     //   6: aconst_null
/*    */     //   7: astore 7
/*    */     //   9: aconst_null
/*    */     //   10: astore 8
/*    */     //   12: aconst_null
/*    */     //   13: astore 9
/*    */     //   15: invokestatic 29	com/claro/util/ServiceLocator:getInstance	()Lcom/claro/util/ServiceLocator;
/*    */     //   18: getstatic 61	com/claro/util/ServiceLocator:jdbcCirculoAzul	Ljava/lang/String;
/*    */     //   21: invokevirtual 64	com/claro/util/ServiceLocator:getConnection	(Ljava/lang/String;)Ljava/sql/Connection;
/*    */     //   24: astore 5
/*    */     //   26: new 68	java/lang/StringBuffer
/*    */     //   29: dup
/*    */     //   30: invokespecial 70	java/lang/StringBuffer:<init>	()V
/*    */     //   33: astore 10
/*    */     //   35: aload 10
/*    */     //   37: ldc 71
/*    */     //   39: invokevirtual 73	java/lang/StringBuffer:append	(Ljava/lang/String;)Ljava/lang/StringBuffer;
/*    */     //   42: pop
/*    */     //   43: aload 10
/*    */     //   45: aload_0
/*    */     //   46: getfield 41	com/claro/dao/AsignacionPorErrorAplicaDAO:schema_database	Ljava/lang/String;
/*    */     //   49: invokevirtual 73	java/lang/StringBuffer:append	(Ljava/lang/String;)Ljava/lang/StringBuffer;
/*    */     //   52: ldc 77
/*    */     //   54: invokevirtual 73	java/lang/StringBuffer:append	(Ljava/lang/String;)Ljava/lang/StringBuffer;
/*    */     //   57: pop
/*    */     //   58: aload 10
/*    */     //   60: ldc 79
/*    */     //   62: invokevirtual 73	java/lang/StringBuffer:append	(Ljava/lang/String;)Ljava/lang/StringBuffer;
/*    */     //   65: pop
/*    */     //   66: aload 5
/*    */     //   68: aload 10
/*    */     //   70: invokevirtual 81	java/lang/StringBuffer:toString	()Ljava/lang/String;
/*    */     //   73: invokeinterface 85 2 0
/*    */     //   78: astore 6
/*    */     //   80: aload 6
/*    */     //   82: iconst_1
/*    */     //   83: aload_2
/*    */     //   84: invokeinterface 91 3 0
/*    */     //   89: aload 6
/*    */     //   91: iconst_2
/*    */     //   92: aload_1
/*    */     //   93: invokevirtual 97	com/claro/transfer/AsignaPorErrorTO:getSecuencia	()Ljava/lang/String;
/*    */     //   96: invokeinterface 91 3 0
/*    */     //   101: aload 6
/*    */     //   103: invokeinterface 102 1 0
/*    */     //   108: astore 9
/*    */     //   110: iconst_0
/*    */     //   111: istore 11
/*    */     //   113: goto +14 -> 127
/*    */     //   116: aload 9
/*    */     //   118: ldc 106
/*    */     //   120: invokeinterface 108 2 0
/*    */     //   125: istore 11
/*    */     //   127: aload 9
/*    */     //   129: invokeinterface 114 1 0
/*    */     //   134: ifne -18 -> 116
/*    */     //   137: iload 11
/*    */     //   139: aload_1
/*    */     //   140: invokevirtual 118	com/claro/transfer/AsignaPorErrorTO:getPuntos	()Ljava/lang/String;
/*    */     //   143: invokestatic 121	java/lang/Integer:parseInt	(Ljava/lang/String;)I
/*    */     //   146: iadd
/*    */     //   147: istore 11
/*    */     //   149: new 68	java/lang/StringBuffer
/*    */     //   152: dup
/*    */     //   153: invokespecial 70	java/lang/StringBuffer:<init>	()V
/*    */     //   156: astore 12
/*    */     //   158: aload 12
/*    */     //   160: ldc 126
/*    */     //   162: invokevirtual 73	java/lang/StringBuffer:append	(Ljava/lang/String;)Ljava/lang/StringBuffer;
/*    */     //   165: aload_0
/*    */     //   166: getfield 41	com/claro/dao/AsignacionPorErrorAplicaDAO:schema_database	Ljava/lang/String;
/*    */     //   169: invokevirtual 73	java/lang/StringBuffer:append	(Ljava/lang/String;)Ljava/lang/StringBuffer;
/*    */     //   172: ldc 77
/*    */     //   174: invokevirtual 73	java/lang/StringBuffer:append	(Ljava/lang/String;)Ljava/lang/StringBuffer;
/*    */     //   177: pop
/*    */     //   178: aload 12
/*    */     //   180: ldc -128
/*    */     //   182: invokevirtual 73	java/lang/StringBuffer:append	(Ljava/lang/String;)Ljava/lang/StringBuffer;
/*    */     //   185: pop
/*    */     //   186: aload 5
/*    */     //   188: aload 12
/*    */     //   190: invokevirtual 81	java/lang/StringBuffer:toString	()Ljava/lang/String;
/*    */     //   193: invokeinterface 85 2 0
/*    */     //   198: astore 7
/*    */     //   200: aload 7
/*    */     //   202: iconst_1
/*    */     //   203: iload 11
/*    */     //   205: invokeinterface 130 3 0
/*    */     //   210: aload 7
/*    */     //   212: iconst_2
/*    */     //   213: aload_2
/*    */     //   214: invokeinterface 91 3 0
/*    */     //   219: aload 7
/*    */     //   221: iconst_3
/*    */     //   222: aload_1
/*    */     //   223: invokevirtual 97	com/claro/transfer/AsignaPorErrorTO:getSecuencia	()Ljava/lang/String;
/*    */     //   226: invokeinterface 91 3 0
/*    */     //   231: aload 7
/*    */     //   233: invokeinterface 134 1 0
/*    */     //   238: pop
/*    */     //   239: new 138	java/lang/StringBuilder
/*    */     //   242: dup
/*    */     //   243: ldc -116
/*    */     //   245: invokespecial 142	java/lang/StringBuilder:<init>	(Ljava/lang/String;)V
/*    */     //   248: aload 4
/*    */     //   250: invokevirtual 145	java/lang/StringBuilder:append	(Ljava/lang/String;)Ljava/lang/StringBuilder;
/*    */     //   253: ldc -108
/*    */     //   255: invokevirtual 145	java/lang/StringBuilder:append	(Ljava/lang/String;)Ljava/lang/StringBuilder;
/*    */     //   258: invokevirtual 150	java/lang/StringBuilder:toString	()Ljava/lang/String;
/*    */     //   261: astore 13
/*    */     //   263: new 68	java/lang/StringBuffer
/*    */     //   266: dup
/*    */     //   267: invokespecial 70	java/lang/StringBuffer:<init>	()V
/*    */     //   270: astore 14
/*    */     //   272: aload 14
/*    */     //   274: ldc -105
/*    */     //   276: invokevirtual 73	java/lang/StringBuffer:append	(Ljava/lang/String;)Ljava/lang/StringBuffer;
/*    */     //   279: aload_0
/*    */     //   280: getfield 41	com/claro/dao/AsignacionPorErrorAplicaDAO:schema_database	Ljava/lang/String;
/*    */     //   283: invokevirtual 73	java/lang/StringBuffer:append	(Ljava/lang/String;)Ljava/lang/StringBuffer;
/*    */     //   286: ldc -103
/*    */     //   288: invokevirtual 73	java/lang/StringBuffer:append	(Ljava/lang/String;)Ljava/lang/StringBuffer;
/*    */     //   291: pop
/*    */     //   292: aload 14
/*    */     //   294: ldc -101
/*    */     //   296: invokevirtual 73	java/lang/StringBuffer:append	(Ljava/lang/String;)Ljava/lang/StringBuffer;
/*    */     //   299: pop
/*    */     //   300: aload 14
/*    */     //   302: ldc -99
/*    */     //   304: invokevirtual 73	java/lang/StringBuffer:append	(Ljava/lang/String;)Ljava/lang/StringBuffer;
/*    */     //   307: pop
/*    */     //   308: aload 14
/*    */     //   310: ldc -97
/*    */     //   312: invokevirtual 73	java/lang/StringBuffer:append	(Ljava/lang/String;)Ljava/lang/StringBuffer;
/*    */     //   315: pop
/*    */     //   316: aload 14
/*    */     //   318: ldc -95
/*    */     //   320: invokevirtual 73	java/lang/StringBuffer:append	(Ljava/lang/String;)Ljava/lang/StringBuffer;
/*    */     //   323: pop
/*    */     //   324: aload 5
/*    */     //   326: aload 14
/*    */     //   328: invokevirtual 81	java/lang/StringBuffer:toString	()Ljava/lang/String;
/*    */     //   331: invokeinterface 85 2 0
/*    */     //   336: astore 8
/*    */     //   338: aload 8
/*    */     //   340: iconst_1
/*    */     //   341: aload_2
/*    */     //   342: invokeinterface 91 3 0
/*    */     //   347: aload 8
/*    */     //   349: iconst_2
/*    */     //   350: aload_1
/*    */     //   351: invokevirtual 97	com/claro/transfer/AsignaPorErrorTO:getSecuencia	()Ljava/lang/String;
/*    */     //   354: invokeinterface 91 3 0
/*    */     //   359: aload 8
/*    */     //   361: iconst_3
/*    */     //   362: aload_3
/*    */     //   363: invokeinterface 91 3 0
/*    */     //   368: aload 8
/*    */     //   370: iconst_4
/*    */     //   371: aload_1
/*    */     //   372: invokevirtual 118	com/claro/transfer/AsignaPorErrorTO:getPuntos	()Ljava/lang/String;
/*    */     //   375: invokestatic 121	java/lang/Integer:parseInt	(Ljava/lang/String;)I
/*    */     //   378: invokeinterface 130 3 0
/*    */     //   383: aload 8
/*    */     //   385: iconst_5
/*    */     //   386: aload 13
/*    */     //   388: invokeinterface 91 3 0
/*    */     //   393: aload 8
/*    */     //   395: invokeinterface 134 1 0
/*    */     //   400: pop
/*    */     //   401: goto +166 -> 567
/*    */     //   404: astore 10
/*    */     //   406: aload_0
/*    */     //   407: getfield 27	com/claro/dao/AsignacionPorErrorAplicaDAO:error	Lorg/apache/log4j/Logger;
/*    */     //   410: ldc -93
/*    */     //   412: aload 10
/*    */     //   414: invokevirtual 165	org/apache/log4j/Logger:info	(Ljava/lang/Object;Ljava/lang/Throwable;)V
/*    */     //   417: new 59	com/claro/exception/CAException
/*    */     //   420: dup
/*    */     //   421: iconst_m1
/*    */     //   422: new 138	java/lang/StringBuilder
/*    */     //   425: dup
/*    */     //   426: ldc -88
/*    */     //   428: invokespecial 142	java/lang/StringBuilder:<init>	(Ljava/lang/String;)V
/*    */     //   431: aload 10
/*    */     //   433: invokevirtual 170	java/sql/SQLException:toString	()Ljava/lang/String;
/*    */     //   436: invokevirtual 145	java/lang/StringBuilder:append	(Ljava/lang/String;)Ljava/lang/StringBuilder;
/*    */     //   439: ldc -83
/*    */     //   441: invokevirtual 145	java/lang/StringBuilder:append	(Ljava/lang/String;)Ljava/lang/StringBuilder;
/*    */     //   444: invokevirtual 150	java/lang/StringBuilder:toString	()Ljava/lang/String;
/*    */     //   447: aload 10
/*    */     //   449: invokespecial 175	com/claro/exception/CAException:<init>	(ILjava/lang/String;Ljava/lang/Exception;)V
/*    */     //   452: athrow
/*    */     //   453: astore 10
/*    */     //   455: aload_0
/*    */     //   456: getfield 27	com/claro/dao/AsignacionPorErrorAplicaDAO:error	Lorg/apache/log4j/Logger;
/*    */     //   459: ldc -78
/*    */     //   461: aload 10
/*    */     //   463: invokevirtual 165	org/apache/log4j/Logger:info	(Ljava/lang/Object;Ljava/lang/Throwable;)V
/*    */     //   466: new 59	com/claro/exception/CAException
/*    */     //   469: dup
/*    */     //   470: iconst_m1
/*    */     //   471: new 138	java/lang/StringBuilder
/*    */     //   474: dup
/*    */     //   475: ldc -76
/*    */     //   477: invokespecial 142	java/lang/StringBuilder:<init>	(Ljava/lang/String;)V
/*    */     //   480: aload 10
/*    */     //   482: invokevirtual 182	java/lang/Exception:toString	()Ljava/lang/String;
/*    */     //   485: invokevirtual 145	java/lang/StringBuilder:append	(Ljava/lang/String;)Ljava/lang/StringBuilder;
/*    */     //   488: ldc -83
/*    */     //   490: invokevirtual 145	java/lang/StringBuilder:append	(Ljava/lang/String;)Ljava/lang/StringBuilder;
/*    */     //   493: invokevirtual 150	java/lang/StringBuilder:toString	()Ljava/lang/String;
/*    */     //   496: aload 10
/*    */     //   498: invokespecial 175	com/claro/exception/CAException:<init>	(ILjava/lang/String;Ljava/lang/Exception;)V
/*    */     //   501: athrow
/*    */     //   502: astore 15
/*    */     //   504: aload 6
/*    */     //   506: ifnull +18 -> 524
/*    */     //   509: aload 6
/*    */     //   511: invokeinterface 183 1 0
/*    */     //   516: aconst_null
/*    */     //   517: astore 6
/*    */     //   519: goto +5 -> 524
/*    */     //   522: astore 16
/*    */     //   524: aload 9
/*    */     //   526: ifnull +18 -> 544
/*    */     //   529: aload 9
/*    */     //   531: invokeinterface 186 1 0
/*    */     //   536: aconst_null
/*    */     //   537: astore 9
/*    */     //   539: goto +5 -> 544
/*    */     //   542: astore 16
/*    */     //   544: aload 5
/*    */     //   546: ifnull +18 -> 564
/*    */     //   549: aload 5
/*    */     //   551: invokeinterface 187 1 0
/*    */     //   556: aconst_null
/*    */     //   557: astore 5
/*    */     //   559: goto +5 -> 564
/*    */     //   562: astore 16
/*    */     //   564: aload 15
/*    */     //   566: athrow
/*    */     //   567: aload 6
/*    */     //   569: ifnull +18 -> 587
/*    */     //   572: aload 6
/*    */     //   574: invokeinterface 183 1 0
/*    */     //   579: aconst_null
/*    */     //   580: astore 6
/*    */     //   582: goto +5 -> 587
/*    */     //   585: astore 16
/*    */     //   587: aload 9
/*    */     //   589: ifnull +18 -> 607
/*    */     //   592: aload 9
/*    */     //   594: invokeinterface 186 1 0
/*    */     //   599: aconst_null
/*    */     //   600: astore 9
/*    */     //   602: goto +5 -> 607
/*    */     //   605: astore 16
/*    */     //   607: aload 5
/*    */     //   609: ifnull +18 -> 627
/*    */     //   612: aload 5
/*    */     //   614: invokeinterface 187 1 0
/*    */     //   619: aconst_null
/*    */     //   620: astore 5
/*    */     //   622: goto +5 -> 627
/*    */     //   625: astore 16
/*    */     //   627: return
/*    */     // Line number table:
/*    */     //   Java source line #33	-> byte code offset #0
/*    */     //   Java source line #34	-> byte code offset #3
/*    */     //   Java source line #35	-> byte code offset #12
/*    */     //   Java source line #39	-> byte code offset #15
/*    */     //   Java source line #41	-> byte code offset #26
/*    */     //   Java source line #42	-> byte code offset #35
/*    */     //   Java source line #43	-> byte code offset #43
/*    */     //   Java source line #44	-> byte code offset #58
/*    */     //   Java source line #47	-> byte code offset #66
/*    */     //   Java source line #48	-> byte code offset #80
/*    */     //   Java source line #49	-> byte code offset #89
/*    */     //   Java source line #50	-> byte code offset #101
/*    */     //   Java source line #53	-> byte code offset #110
/*    */     //   Java source line #54	-> byte code offset #113
/*    */     //   Java source line #55	-> byte code offset #116
/*    */     //   Java source line #54	-> byte code offset #127
/*    */     //   Java source line #58	-> byte code offset #137
/*    */     //   Java source line #60	-> byte code offset #149
/*    */     //   Java source line #61	-> byte code offset #158
/*    */     //   Java source line #62	-> byte code offset #178
/*    */     //   Java source line #64	-> byte code offset #186
/*    */     //   Java source line #65	-> byte code offset #200
/*    */     //   Java source line #66	-> byte code offset #210
/*    */     //   Java source line #67	-> byte code offset #219
/*    */     //   Java source line #68	-> byte code offset #231
/*    */     //   Java source line #71	-> byte code offset #239
/*    */     //   Java source line #72	-> byte code offset #263
/*    */     //   Java source line #73	-> byte code offset #272
/*    */     //   Java source line #74	-> byte code offset #292
/*    */     //   Java source line #75	-> byte code offset #300
/*    */     //   Java source line #76	-> byte code offset #308
/*    */     //   Java source line #77	-> byte code offset #316
/*    */     //   Java source line #79	-> byte code offset #324
/*    */     //   Java source line #80	-> byte code offset #338
/*    */     //   Java source line #81	-> byte code offset #347
/*    */     //   Java source line #82	-> byte code offset #359
/*    */     //   Java source line #83	-> byte code offset #368
/*    */     //   Java source line #84	-> byte code offset #383
/*    */     //   Java source line #85	-> byte code offset #393
/*    */     //   Java source line #88	-> byte code offset #404
/*    */     //   Java source line #89	-> byte code offset #406
/*    */     //   Java source line #90	-> byte code offset #417
/*    */     //   Java source line #91	-> byte code offset #453
/*    */     //   Java source line #92	-> byte code offset #455
/*    */     //   Java source line #93	-> byte code offset #466
/*    */     //   Java source line #95	-> byte code offset #502
/*    */     //   Java source line #96	-> byte code offset #504
/*    */     //   Java source line #97	-> byte code offset #524
/*    */     //   Java source line #98	-> byte code offset #544
/*    */     //   Java source line #99	-> byte code offset #564
/*    */     //   Java source line #96	-> byte code offset #567
/*    */     //   Java source line #97	-> byte code offset #587
/*    */     //   Java source line #98	-> byte code offset #607
/*    */     //   Java source line #101	-> byte code offset #627
/*    */     // Local variable table:
/*    */     //   start	length	slot	name	signature
/*    */     //   0	628	0	this	AsignacionPorErrorAplicaDAO
/*    */     //   0	628	1	asignaPorErrorTO	com.claro.transfer.AsignaPorErrorTO
/*    */     //   0	628	2	Cuenta	String
/*    */     //   0	628	3	Telefono	String
/*    */     //   0	628	4	numempleado	String
/*    */     //   1	620	5	conn	java.sql.Connection
/*    */     //   4	577	6	statement	java.sql.PreparedStatement
/*    */     //   7	225	7	updatepuntos	java.sql.PreparedStatement
/*    */     //   10	384	8	insertamovimiento	java.sql.PreparedStatement
/*    */     //   13	588	9	resultSet	java.sql.ResultSet
/*    */     //   33	36	10	query	StringBuffer
/*    */     //   404	44	10	e	java.sql.SQLException
/*    */     //   453	44	10	e	Exception
/*    */     //   111	93	11	puntosexc	int
/*    */     //   156	33	12	queryupdate	StringBuffer
/*    */     //   261	126	13	comentario	String
/*    */     //   270	57	14	queryinsert	StringBuffer
/*    */     //   502	63	15	localObject	Object
/*    */     //   522	1	16	localException1	Exception
/*    */     //   542	1	16	localException2	Exception
/*    */     //   562	1	16	localException3	Exception
/*    */     //   585	1	16	localException4	Exception
/*    */     //   605	1	16	localException5	Exception
/*    */     //   625	1	16	localException6	Exception
/*    */     // Exception table:
/*    */     //   from	to	target	type
/*    */     //   15	401	404	java/sql/SQLException
/*    */     //   15	401	453	java/lang/Exception
/*    */     //   15	502	502	finally
/*    */     //   509	519	522	java/lang/Exception
/*    */     //   529	539	542	java/lang/Exception
/*    */     //   549	559	562	java/lang/Exception
/*    */     //   572	582	585	java/lang/Exception
/*    */     //   592	602	605	java/lang/Exception
/*    */     //   612	622	625	java/lang/Exception
/*    */   }
/*    */   
/*    */   /* Error */
/*    */   public boolean VerificasiexisteAPTOE(String Cuenta, String Telefono)
/*    */     throws com.claro.exception.CAException
/*    */   {
	return false;
/*    */     // Byte code:
/*    */     //   0: aconst_null
/*    */     //   1: astore_3
/*    */     //   2: aconst_null
/*    */     //   3: astore 4
/*    */     //   5: aconst_null
/*    */     //   6: astore 5
/*    */     //   8: iconst_0
/*    */     //   9: istore 6
/*    */     //   11: invokestatic 29	com/claro/util/ServiceLocator:getInstance	()Lcom/claro/util/ServiceLocator;
/*    */     //   14: getstatic 61	com/claro/util/ServiceLocator:jdbcCirculoAzul	Ljava/lang/String;
/*    */     //   17: invokevirtual 64	com/claro/util/ServiceLocator:getConnection	(Ljava/lang/String;)Ljava/sql/Connection;
/*    */     //   20: astore_3
/*    */     //   21: new 68	java/lang/StringBuffer
/*    */     //   24: dup
/*    */     //   25: invokespecial 70	java/lang/StringBuffer:<init>	()V
/*    */     //   28: astore 7
/*    */     //   30: aload 7
/*    */     //   32: ldc -41
/*    */     //   34: invokevirtual 73	java/lang/StringBuffer:append	(Ljava/lang/String;)Ljava/lang/StringBuffer;
/*    */     //   37: pop
/*    */     //   38: aload 7
/*    */     //   40: aload_0
/*    */     //   41: getfield 41	com/claro/dao/AsignacionPorErrorAplicaDAO:schema_database	Ljava/lang/String;
/*    */     //   44: invokevirtual 73	java/lang/StringBuffer:append	(Ljava/lang/String;)Ljava/lang/StringBuffer;
/*    */     //   47: ldc -103
/*    */     //   49: invokevirtual 73	java/lang/StringBuffer:append	(Ljava/lang/String;)Ljava/lang/StringBuffer;
/*    */     //   52: pop
/*    */     //   53: aload 7
/*    */     //   55: ldc -39
/*    */     //   57: invokevirtual 73	java/lang/StringBuffer:append	(Ljava/lang/String;)Ljava/lang/StringBuffer;
/*    */     //   60: pop
/*    */     //   61: aload_3
/*    */     //   62: aload 7
/*    */     //   64: invokevirtual 81	java/lang/StringBuffer:toString	()Ljava/lang/String;
/*    */     //   67: invokeinterface 85 2 0
/*    */     //   72: astore 4
/*    */     //   74: aload 4
/*    */     //   76: iconst_1
/*    */     //   77: aload_1
/*    */     //   78: invokeinterface 91 3 0
/*    */     //   83: aload 4
/*    */     //   85: iconst_2
/*    */     //   86: aload_2
/*    */     //   87: invokeinterface 91 3 0
/*    */     //   92: aload 4
/*    */     //   94: invokeinterface 102 1 0
/*    */     //   99: astore 5
/*    */     //   101: aload 5
/*    */     //   103: invokeinterface 114 1 0
/*    */     //   108: ifeq +169 -> 277
/*    */     //   111: iconst_1
/*    */     //   112: istore 6
/*    */     //   114: goto +163 -> 277
/*    */     //   117: astore 7
/*    */     //   119: aload_0
/*    */     //   120: getfield 27	com/claro/dao/AsignacionPorErrorAplicaDAO:error	Lorg/apache/log4j/Logger;
/*    */     //   123: ldc -37
/*    */     //   125: aload 7
/*    */     //   127: invokevirtual 165	org/apache/log4j/Logger:info	(Ljava/lang/Object;Ljava/lang/Throwable;)V
/*    */     //   130: new 59	com/claro/exception/CAException
/*    */     //   133: dup
/*    */     //   134: iconst_m1
/*    */     //   135: new 138	java/lang/StringBuilder
/*    */     //   138: dup
/*    */     //   139: ldc -35
/*    */     //   141: invokespecial 142	java/lang/StringBuilder:<init>	(Ljava/lang/String;)V
/*    */     //   144: aload 7
/*    */     //   146: invokevirtual 170	java/sql/SQLException:toString	()Ljava/lang/String;
/*    */     //   149: invokevirtual 145	java/lang/StringBuilder:append	(Ljava/lang/String;)Ljava/lang/StringBuilder;
/*    */     //   152: ldc -83
/*    */     //   154: invokevirtual 145	java/lang/StringBuilder:append	(Ljava/lang/String;)Ljava/lang/StringBuilder;
/*    */     //   157: invokevirtual 150	java/lang/StringBuilder:toString	()Ljava/lang/String;
/*    */     //   160: aload 7
/*    */     //   162: invokespecial 175	com/claro/exception/CAException:<init>	(ILjava/lang/String;Ljava/lang/Exception;)V
/*    */     //   165: athrow
/*    */     //   166: astore 7
/*    */     //   168: aload_0
/*    */     //   169: getfield 27	com/claro/dao/AsignacionPorErrorAplicaDAO:error	Lorg/apache/log4j/Logger;
/*    */     //   172: ldc -33
/*    */     //   174: aload 7
/*    */     //   176: invokevirtual 165	org/apache/log4j/Logger:info	(Ljava/lang/Object;Ljava/lang/Throwable;)V
/*    */     //   179: new 59	com/claro/exception/CAException
/*    */     //   182: dup
/*    */     //   183: iconst_m1
/*    */     //   184: new 138	java/lang/StringBuilder
/*    */     //   187: dup
/*    */     //   188: ldc -31
/*    */     //   190: invokespecial 142	java/lang/StringBuilder:<init>	(Ljava/lang/String;)V
/*    */     //   193: aload 7
/*    */     //   195: invokevirtual 182	java/lang/Exception:toString	()Ljava/lang/String;
/*    */     //   198: invokevirtual 145	java/lang/StringBuilder:append	(Ljava/lang/String;)Ljava/lang/StringBuilder;
/*    */     //   201: ldc -83
/*    */     //   203: invokevirtual 145	java/lang/StringBuilder:append	(Ljava/lang/String;)Ljava/lang/StringBuilder;
/*    */     //   206: invokevirtual 150	java/lang/StringBuilder:toString	()Ljava/lang/String;
/*    */     //   209: aload 7
/*    */     //   211: invokespecial 175	com/claro/exception/CAException:<init>	(ILjava/lang/String;Ljava/lang/Exception;)V
/*    */     //   214: athrow
/*    */     //   215: astore 8
/*    */     //   217: aload 4
/*    */     //   219: ifnull +18 -> 237
/*    */     //   222: aload 4
/*    */     //   224: invokeinterface 183 1 0
/*    */     //   229: aconst_null
/*    */     //   230: astore 4
/*    */     //   232: goto +5 -> 237
/*    */     //   235: astore 9
/*    */     //   237: aload 5
/*    */     //   239: ifnull +18 -> 257
/*    */     //   242: aload 5
/*    */     //   244: invokeinterface 186 1 0
/*    */     //   249: aconst_null
/*    */     //   250: astore 5
/*    */     //   252: goto +5 -> 257
/*    */     //   255: astore 9
/*    */     //   257: aload_3
/*    */     //   258: ifnull +16 -> 274
/*    */     //   261: aload_3
/*    */     //   262: invokeinterface 187 1 0
/*    */     //   267: aconst_null
/*    */     //   268: astore_3
/*    */     //   269: goto +5 -> 274
/*    */     //   272: astore 9
/*    */     //   274: aload 8
/*    */     //   276: athrow
/*    */     //   277: aload 4
/*    */     //   279: ifnull +18 -> 297
/*    */     //   282: aload 4
/*    */     //   284: invokeinterface 183 1 0
/*    */     //   289: aconst_null
/*    */     //   290: astore 4
/*    */     //   292: goto +5 -> 297
/*    */     //   295: astore 9
/*    */     //   297: aload 5
/*    */     //   299: ifnull +18 -> 317
/*    */     //   302: aload 5
/*    */     //   304: invokeinterface 186 1 0
/*    */     //   309: aconst_null
/*    */     //   310: astore 5
/*    */     //   312: goto +5 -> 317
/*    */     //   315: astore 9
/*    */     //   317: aload_3
/*    */     //   318: ifnull +16 -> 334
/*    */     //   321: aload_3
/*    */     //   322: invokeinterface 187 1 0
/*    */     //   327: aconst_null
/*    */     //   328: astore_3
/*    */     //   329: goto +5 -> 334
/*    */     //   332: astore 9
/*    */     //   334: iload 6
/*    */     //   336: ireturn
/*    */     // Line number table:
/*    */     //   Java source line #104	-> byte code offset #0
/*    */     //   Java source line #105	-> byte code offset #2
/*    */     //   Java source line #106	-> byte code offset #5
/*    */     //   Java source line #107	-> byte code offset #8
/*    */     //   Java source line #109	-> byte code offset #11
/*    */     //   Java source line #111	-> byte code offset #21
/*    */     //   Java source line #112	-> byte code offset #30
/*    */     //   Java source line #113	-> byte code offset #38
/*    */     //   Java source line #114	-> byte code offset #53
/*    */     //   Java source line #117	-> byte code offset #61
/*    */     //   Java source line #118	-> byte code offset #74
/*    */     //   Java source line #119	-> byte code offset #83
/*    */     //   Java source line #120	-> byte code offset #92
/*    */     //   Java source line #123	-> byte code offset #101
/*    */     //   Java source line #124	-> byte code offset #111
/*    */     //   Java source line #128	-> byte code offset #117
/*    */     //   Java source line #129	-> byte code offset #119
/*    */     //   Java source line #130	-> byte code offset #130
/*    */     //   Java source line #131	-> byte code offset #166
/*    */     //   Java source line #132	-> byte code offset #168
/*    */     //   Java source line #133	-> byte code offset #179
/*    */     //   Java source line #135	-> byte code offset #215
/*    */     //   Java source line #136	-> byte code offset #217
/*    */     //   Java source line #137	-> byte code offset #237
/*    */     //   Java source line #138	-> byte code offset #257
/*    */     //   Java source line #139	-> byte code offset #274
/*    */     //   Java source line #136	-> byte code offset #277
/*    */     //   Java source line #137	-> byte code offset #297
/*    */     //   Java source line #138	-> byte code offset #317
/*    */     //   Java source line #140	-> byte code offset #334
/*    */     // Local variable table:
/*    */     //   start	length	slot	name	signature
/*    */     //   0	337	0	this	AsignacionPorErrorAplicaDAO
/*    */     //   0	337	1	Cuenta	String
/*    */     //   0	337	2	Telefono	String
/*    */     //   1	328	3	conn	java.sql.Connection
/*    */     //   3	288	4	statement	java.sql.PreparedStatement
/*    */     //   6	305	5	resultSet	java.sql.ResultSet
/*    */     //   9	326	6	bandera	boolean
/*    */     //   28	35	7	query	StringBuffer
/*    */     //   117	44	7	e	java.sql.SQLException
/*    */     //   166	44	7	e	Exception
/*    */     //   215	60	8	localObject	Object
/*    */     //   235	1	9	localException1	Exception
/*    */     //   255	1	9	localException2	Exception
/*    */     //   272	1	9	localException3	Exception
/*    */     //   295	1	9	localException4	Exception
/*    */     //   315	1	9	localException5	Exception
/*    */     //   332	1	9	localException6	Exception
/*    */     // Exception table:
/*    */     //   from	to	target	type
/*    */     //   11	114	117	java/sql/SQLException
/*    */     //   11	114	166	java/lang/Exception
/*    */     //   11	215	215	finally
/*    */     //   222	232	235	java/lang/Exception
/*    */     //   242	252	255	java/lang/Exception
/*    */     //   261	269	272	java/lang/Exception
/*    */     //   282	292	295	java/lang/Exception
/*    */     //   302	312	315	java/lang/Exception
/*    */     //   321	329	332	java/lang/Exception
/*    */   }
/*    */ }


/* Location:              /opt/trabajo/claro/Guatemala/IS/CO/ClaroClub.ear!/ClaroClubEJB.jar!/com/claro/dao/AsignacionPorErrorAplicaDAO.class
 * Java compiler version: 6 (50.0)
 * JD-Core Version:       0.7.1
 */