/*    */package com.claro.dao;

/*    */
/*    *//*    */
import org.apache.log4j.Logger;

import com.claro.util.ServiceLocator;

/*    */
/*    */
/*    */
/*    */
/*    */
/*    */
/*    */
/*    */
/*    */
/*    */
/*    */
/*    */
/*    */public class AvisosDAO
/*    */{
	/* 19 */protected final Logger logger = Logger
			.getLogger("loggerCirculoAzul");
	/* 20 */protected final Logger error = Logger
			.getLogger("loggerCirculoAzulError");
	/*    */private String schema_database;

	/*    */
	/*    */public AvisosDAO() {
		/*    */try {
			/* 25 */this.schema_database = ServiceLocator.getInstance()
					.getVariable(ServiceLocator.schema_database);
			/*    */} catch (Exception e) {
			/* 27 */this.error.error("AvisosDAO", e);
			/*    */}
		/*    */}

	/*    */
	/*    *//* Error */
	/*    */public java.util.ArrayList<com.claro.transfer.AvisosTO> historicoAvisos(
			String sFechaIni, String sFechaFin, String tipoAviso, String estatus)
	/*    */throws com.claro.exception.CAException
	/*    */{
		return null;
		/*    */// Byte code:
		/*    */// 0: aconst_null
		/*    */// 1: astore 5
		/*    */// 3: aconst_null
		/*    */// 4: astore 6
		/*    */// 6: aconst_null
		/*    */// 7: astore 7
		/*    */// 9: aconst_null
		/*    */// 10: astore 8
		/*    */// 12: aconst_null
		/*    */// 13: astore 9
		/*    */// 15: new 63 java/lang/StringBuffer
		/*    */// 18: dup
		/*    */// 19: invokespecial 65 java/lang/StringBuffer:<init> ()V
		/*    */// 22: astore 10
		/*    */// 24: new 66 java/util/ArrayList
		/*    */// 27: dup
		/*    */// 28: invokespecial 68 java/util/ArrayList:<init> ()V
		/*    */// 31: astore 11
		/*    */// 33: aload 10
		/*    */// 35: ldc 69
		/*    */// 37: invokevirtual 71 java/lang/StringBuffer:append
				// (Ljava/lang/String;)Ljava/lang/StringBuffer;
		/*    */// 40: pop
		/*    */// 41: aload 10
		/*    */// 43: ldc 75
		/*    */// 45: invokevirtual 71 java/lang/StringBuffer:append
				// (Ljava/lang/String;)Ljava/lang/StringBuffer;
		/*    */// 48: pop
		/*    */// 49: aload 10
		/*    */// 51: ldc 77
		/*    */// 53: invokevirtual 71 java/lang/StringBuffer:append
				// (Ljava/lang/String;)Ljava/lang/StringBuffer;
		/*    */// 56: aload_0
		/*    */// 57: getfield 41 com/claro/dao/AvisosDAO:schema_database
				// Ljava/lang/String;
		/*    */// 60: invokevirtual 71 java/lang/StringBuffer:append
				// (Ljava/lang/String;)Ljava/lang/StringBuffer;
		/*    */// 63: ldc 79
		/*    */// 65: invokevirtual 71 java/lang/StringBuffer:append
				// (Ljava/lang/String;)Ljava/lang/StringBuffer;
		/*    */// 68: pop
		/*    */// 69: aload 10
		/*    */// 71: ldc 81
		/*    */// 73: invokevirtual 71 java/lang/StringBuffer:append
				// (Ljava/lang/String;)Ljava/lang/StringBuffer;
		/*    */// 76: pop
		/*    */// 77: aload_1
		/*    */// 78: ifnull +15 -> 93
		/*    */// 81: aload_2
		/*    */// 82: ifnull +11 -> 93
		/*    */// 85: aload 10
		/*    */// 87: ldc 83
		/*    */// 89: invokevirtual 71 java/lang/StringBuffer:append
				// (Ljava/lang/String;)Ljava/lang/StringBuffer;
		/*    */// 92: pop
		/*    */// 93: aload_3
		/*    */// 94: ifnull +11 -> 105
		/*    */// 97: aload 10
		/*    */// 99: ldc 85
		/*    */// 101: invokevirtual 71 java/lang/StringBuffer:append
				// (Ljava/lang/String;)Ljava/lang/StringBuffer;
		/*    */// 104: pop
		/*    */// 105: aload 10
		/*    */// 107: ldc 87
		/*    */// 109: invokevirtual 71 java/lang/StringBuffer:append
				// (Ljava/lang/String;)Ljava/lang/StringBuffer;
		/*    */// 112: pop
		/*    */// 113: invokestatic 29 com/claro/util/ServiceLocator:getInstance
				// ()Lcom/claro/util/ServiceLocator;
		/*    */// 116: getstatic 89 com/claro/util/ServiceLocator:jdbcCirculoAzul
				// Ljava/lang/String;
		/*    */// 119: invokevirtual 92
				// com/claro/util/ServiceLocator:getConnection
				// (Ljava/lang/String;)Ljava/sql/Connection;
		/*    */// 122: astore 7
		/*    */// 124: aload 7
		/*    */// 126: aload 10
		/*    */// 128: invokevirtual 96 java/lang/StringBuffer:toString
				// ()Ljava/lang/String;
		/*    */// 131: invokeinterface 100 2 0
		/*    */// 136: astore 5
		/*    */// 138: aload 4
		/*    */// 140: ifnull +16 -> 156
		/*    */// 143: aload 5
		/*    */// 145: iconst_1
		/*    */// 146: aload 4
		/*    */// 148: invokeinterface 106 3 0
		/*    */// 153: goto +13 -> 166
		/*    */// 156: aload 5
		/*    */// 158: iconst_1
		/*    */// 159: ldc 112
		/*    */// 161: invokeinterface 106 3 0
		/*    */// 166: aload_1
		/*    */// 167: ifnull +45 -> 212
		/*    */// 170: aload_2
		/*    */// 171: ifnull +41 -> 212
		/*    */// 174: new 114 java/lang/StringBuilder
		/*    */// 177: dup
		/*    */// 178: aload_2
		/*    */// 179: invokestatic 116 java/lang/String:valueOf
				// (Ljava/lang/Object;)Ljava/lang/String;
		/*    */// 182: invokespecial 122 java/lang/StringBuilder:<init>
				// (Ljava/lang/String;)V
		/*    */// 185: ldc 125
		/*    */// 187: invokevirtual 127 java/lang/StringBuilder:append
				// (Ljava/lang/String;)Ljava/lang/StringBuilder;
		/*    */// 190: invokevirtual 130 java/lang/StringBuilder:toString
				// ()Ljava/lang/String;
		/*    */// 193: astore_2
		/*    */// 194: getstatic 131
				// com/claro/util/Constantes:DATEFORMATMM_dd_YYYY
				// Ljava/text/SimpleDateFormat;
		/*    */// 197: aload_1
		/*    */// 198: invokevirtual 137 java/text/SimpleDateFormat:parse
				// (Ljava/lang/String;)Ljava/util/Date;
		/*    */// 201: astore 8
		/*    */// 203: getstatic 143
				// com/claro/util/Constantes:DATEFORMATMM_dd_YYYY_HHmmss
				// Ljava/text/SimpleDateFormat;
		/*    */// 206: aload_2
		/*    */// 207: invokevirtual 137 java/text/SimpleDateFormat:parse
				// (Ljava/lang/String;)Ljava/util/Date;
		/*    */// 210: astore 9
		/*    */// 212: aload 8
		/*    */// 214: ifnull +48 -> 262
		/*    */// 217: aload 9
		/*    */// 219: ifnull +43 -> 262
		/*    */// 222: aload 5
		/*    */// 224: iconst_2
		/*    */// 225: new 146 java/sql/Timestamp
		/*    */// 228: dup
		/*    */// 229: aload 8
		/*    */// 231: invokevirtual 148 java/util/Date:getTime ()J
		/*    */// 234: invokespecial 154 java/sql/Timestamp:<init> (J)V
		/*    */// 237: invokeinterface 157 3 0
		/*    */// 242: aload 5
		/*    */// 244: iconst_3
		/*    */// 245: new 146 java/sql/Timestamp
		/*    */// 248: dup
		/*    */// 249: aload 9
		/*    */// 251: invokevirtual 148 java/util/Date:getTime ()J
		/*    */// 254: invokespecial 154 java/sql/Timestamp:<init> (J)V
		/*    */// 257: invokeinterface 157 3 0
		/*    */// 262: aload_3
		/*    */// 263: ifnull +12 -> 275
		/*    */// 266: aload 5
		/*    */// 268: iconst_4
		/*    */// 269: aload_3
		/*    */// 270: invokeinterface 106 3 0
		/*    */// 275: aload 5
		/*    */// 277: invokeinterface 161 1 0
		/*    */// 282: astore 6
		/*    */// 284: goto +200 -> 484
		/*    */// 287: new 165 com/claro/transfer/AvisosTO
		/*    */// 290: dup
		/*    */// 291: invokespecial 167 com/claro/transfer/AvisosTO:<init> ()V
		/*    */// 294: astore 12
		/*    */// 296: aload 12
		/*    */// 298: aload 6
		/*    */// 300: ldc -88
		/*    */// 302: invokeinterface 170 2 0
		/*    */// 307: invokevirtual 176 com/claro/transfer/AvisosTO:setIdAviso
				// (I)V
		/*    */// 310: aload 12
		/*    */// 312: aload 6
		/*    */// 314: ldc -76
		/*    */// 316: invokeinterface 182 2 0
		/*    */// 321: invokevirtual 185 com/claro/transfer/AvisosTO:setIdUsuario
				// (Ljava/lang/String;)V
		/*    */// 324: aload 12
		/*    */// 326: aload 6
		/*    */// 328: ldc -68
		/*    */// 330: invokeinterface 182 2 0
		/*    */// 335: invokevirtual 190
				// com/claro/transfer/AvisosTO:setDescripcion
				// (Ljava/lang/String;)V
		/*    */// 338: aload 12
		/*    */// 340: aload 6
		/*    */// 342: ldc -63
		/*    */// 344: invokeinterface 195 2 0
		/*    */// 349: invokevirtual 199 com/claro/transfer/AvisosTO:setFechaAlta
				// (Ljava/sql/Timestamp;)V
		/*    */// 352: aload 12
		/*    */// 354: aload 6
		/*    */// 356: ldc -53
		/*    */// 358: invokeinterface 195 2 0
		/*    */// 363: invokevirtual 205
				// com/claro/transfer/AvisosTO:setFechaActivacion
				// (Ljava/sql/Timestamp;)V
		/*    */// 366: aload 12
		/*    */// 368: aload 6
		/*    */// 370: ldc -48
		/*    */// 372: invokeinterface 195 2 0
		/*    */// 377: invokevirtual 210
				// com/claro/transfer/AvisosTO:setFechaExpiracion
				// (Ljava/sql/Timestamp;)V
		/*    */// 380: aload 6
		/*    */// 382: ldc -43
		/*    */// 384: invokeinterface 182 2 0
		/*    */// 389: ldc -41
		/*    */// 391: invokevirtual 217 java/lang/String:equals
				// (Ljava/lang/Object;)Z
		/*    */// 394: ifeq +13 -> 407
		/*    */// 397: aload 12
		/*    */// 399: ldc -35
		/*    */// 401: invokevirtual 223 com/claro/transfer/AvisosTO:setTipoAviso
				// (Ljava/lang/String;)V
		/*    */// 404: goto +10 -> 414
		/*    */// 407: aload 12
		/*    */// 409: ldc -30
		/*    */// 411: invokevirtual 223 com/claro/transfer/AvisosTO:setTipoAviso
				// (Ljava/lang/String;)V
		/*    */// 414: aload 6
		/*    */// 416: ldc -28
		/*    */// 418: invokeinterface 182 2 0
		/*    */// 423: ldc 112
		/*    */// 425: invokevirtual 217 java/lang/String:equals
				// (Ljava/lang/Object;)Z
		/*    */// 428: ifeq +13 -> 441
		/*    */// 431: aload 12
		/*    */// 433: ldc -26
		/*    */// 435: invokevirtual 232 com/claro/transfer/AvisosTO:setEstatus
				// (Ljava/lang/String;)V
		/*    */// 438: goto +10 -> 448
		/*    */// 441: aload 12
		/*    */// 443: ldc -21
		/*    */// 445: invokevirtual 232 com/claro/transfer/AvisosTO:setEstatus
				// (Ljava/lang/String;)V
		/*    */// 448: aload 12
		/*    */// 450: aload 6
		/*    */// 452: ldc -19
		/*    */// 454: invokeinterface 195 2 0
		/*    */// 459: invokevirtual 239
				// com/claro/transfer/AvisosTO:setFechaModificacion
				// (Ljava/sql/Timestamp;)V
		/*    */// 462: aload 12
		/*    */// 464: aload 6
		/*    */// 466: ldc -14
		/*    */// 468: invokeinterface 182 2 0
		/*    */// 473: invokevirtual 244
				// com/claro/transfer/AvisosTO:setIdUsuarioMod
				// (Ljava/lang/String;)V
		/*    */// 476: aload 11
		/*    */// 478: aload 12
		/*    */// 480: invokevirtual 247 java/util/ArrayList:add
				// (Ljava/lang/Object;)Z
		/*    */// 483: pop
		/*    */// 484: aload 6
		/*    */// 486: invokeinterface 250 1 0
		/*    */// 491: ifne -204 -> 287
		/*    */// 494: goto +115 -> 609
		/*    */// 497: astore 12
		/*    */// 499: new 59 com/claro/exception/CAException
		/*    */// 502: dup
		/*    */// 503: iconst_m1
		/*    */// 504: ldc -2
		/*    */// 506: aload 12
		/*    */// 508: invokespecial 256 com/claro/exception/CAException:<init>
				// (ILjava/lang/String;Ljava/lang/Exception;)V
		/*    */// 511: athrow
		/*    */// 512: astore 12
		/*    */// 514: new 59 com/claro/exception/CAException
		/*    */// 517: dup
		/*    */// 518: iconst_m1
		/*    */// 519: ldc_w 259
		/*    */// 522: aload 12
		/*    */// 524: invokespecial 256 com/claro/exception/CAException:<init>
				// (ILjava/lang/String;Ljava/lang/Exception;)V
		/*    */// 527: athrow
		/*    */// 528: astore 12
		/*    */// 530: new 59 com/claro/exception/CAException
		/*    */// 533: dup
		/*    */// 534: iconst_m1
		/*    */// 535: ldc_w 261
		/*    */// 538: aload 12
		/*    */// 540: invokespecial 256 com/claro/exception/CAException:<init>
				// (ILjava/lang/String;Ljava/lang/Exception;)V
		/*    */// 543: athrow
		/*    */// 544: astore 13
		/*    */// 546: aload 6
		/*    */// 548: ifnull +18 -> 566
		/*    */// 551: aload 6
		/*    */// 553: invokeinterface 263 1 0
		/*    */// 558: aconst_null
		/*    */// 559: astore 6
		/*    */// 561: goto +5 -> 566
		/*    */// 564: astore 14
		/*    */// 566: aload 5
		/*    */// 568: ifnull +18 -> 586
		/*    */// 571: aload 5
		/*    */// 573: invokeinterface 266 1 0
		/*    */// 578: aconst_null
		/*    */// 579: astore 5
		/*    */// 581: goto +5 -> 586
		/*    */// 584: astore 14
		/*    */// 586: aload 7
		/*    */// 588: ifnull +18 -> 606
		/*    */// 591: aload 7
		/*    */// 593: invokeinterface 267 1 0
		/*    */// 598: aconst_null
		/*    */// 599: astore 7
		/*    */// 601: goto +5 -> 606
		/*    */// 604: astore 14
		/*    */// 606: aload 13
		/*    */// 608: athrow
		/*    */// 609: aload 6
		/*    */// 611: ifnull +18 -> 629
		/*    */// 614: aload 6
		/*    */// 616: invokeinterface 263 1 0
		/*    */// 621: aconst_null
		/*    */// 622: astore 6
		/*    */// 624: goto +5 -> 629
		/*    */// 627: astore 14
		/*    */// 629: aload 5
		/*    */// 631: ifnull +18 -> 649
		/*    */// 634: aload 5
		/*    */// 636: invokeinterface 266 1 0
		/*    */// 641: aconst_null
		/*    */// 642: astore 5
		/*    */// 644: goto +5 -> 649
		/*    */// 647: astore 14
		/*    */// 649: aload 7
		/*    */// 651: ifnull +18 -> 669
		/*    */// 654: aload 7
		/*    */// 656: invokeinterface 267 1 0
		/*    */// 661: aconst_null
		/*    */// 662: astore 7
		/*    */// 664: goto +5 -> 669
		/*    */// 667: astore 14
		/*    */// 669: aload 11
		/*    */// 671: areturn
		/*    */// Line number table:
		/*    */// Java source line #36 -> byte code offset #0
		/*    */// Java source line #37 -> byte code offset #3
		/*    */// Java source line #38 -> byte code offset #6
		/*    */// Java source line #39 -> byte code offset #9
		/*    */// Java source line #40 -> byte code offset #12
		/*    */// Java source line #42 -> byte code offset #15
		/*    */// Java source line #43 -> byte code offset #24
		/*    */// Java source line #45 -> byte code offset #33
		/*    */// Java source line #46 -> byte code offset #41
		/*    */// Java source line #47 -> byte code offset #49
		/*    */// Java source line #48 -> byte code offset #69
		/*    */// Java source line #50 -> byte code offset #77
		/*    */// Java source line #51 -> byte code offset #85
		/*    */// Java source line #53 -> byte code offset #93
		/*    */// Java source line #56 -> byte code offset #105
		/*    */// Java source line #59 -> byte code offset #113
		/*    */// Java source line #60 -> byte code offset #124
		/*    */// Java source line #62 -> byte code offset #138
		/*    */// Java source line #63 -> byte code offset #143
		/*    */// Java source line #65 -> byte code offset #156
		/*    */// Java source line #68 -> byte code offset #166
		/*    */// Java source line #69 -> byte code offset #174
		/*    */// Java source line #70 -> byte code offset #194
		/*    */// Java source line #71 -> byte code offset #203
		/*    */// Java source line #73 -> byte code offset #212
		/*    */// Java source line #74 -> byte code offset #222
		/*    */// Java source line #75 -> byte code offset #242
		/*    */// Java source line #79 -> byte code offset #262
		/*    */// Java source line #82 -> byte code offset #275
		/*    */// Java source line #83 -> byte code offset #284
		/*    */// Java source line #84 -> byte code offset #287
		/*    */// Java source line #85 -> byte code offset #296
		/*    */// Java source line #86 -> byte code offset #310
		/*    */// Java source line #87 -> byte code offset #324
		/*    */// Java source line #88 -> byte code offset #338
		/*    */// Java source line #89 -> byte code offset #352
		/*    */// Java source line #90 -> byte code offset #366
		/*    */// Java source line #92 -> byte code offset #380
		/*    */// Java source line #93 -> byte code offset #397
		/*    */// Java source line #95 -> byte code offset #407
		/*    */// Java source line #98 -> byte code offset #414
		/*    */// Java source line #99 -> byte code offset #431
		/*    */// Java source line #101 -> byte code offset #441
		/*    */// Java source line #103 -> byte code offset #448
		/*    */// Java source line #104 -> byte code offset #462
		/*    */// Java source line #105 -> byte code offset #476
		/*    */// Java source line #83 -> byte code offset #484
		/*    */// Java source line #107 -> byte code offset #497
		/*    */// Java source line #108 -> byte code offset #499
		/*    */// Java source line #109 -> byte code offset #512
		/*    */// Java source line #110 -> byte code offset #514
		/*    */// Java source line #111 -> byte code offset #528
		/*    */// Java source line #112 -> byte code offset #530
		/*    */// Java source line #113 -> byte code offset #544
		/*    */// Java source line #114 -> byte code offset #546
		/*    */// Java source line #115 -> byte code offset #566
		/*    */// Java source line #116 -> byte code offset #586
		/*    */// Java source line #117 -> byte code offset #606
		/*    */// Java source line #114 -> byte code offset #609
		/*    */// Java source line #115 -> byte code offset #629
		/*    */// Java source line #116 -> byte code offset #649
		/*    */// Java source line #118 -> byte code offset #669
		/*    */// Local variable table:
		/*    */// start length slot name signature
		/*    */// 0 672 0 this AvisosDAO
		/*    */// 0 672 1 sFechaIni String
		/*    */// 0 672 2 sFechaFin String
		/*    */// 0 672 3 tipoAviso String
		/*    */// 0 672 4 estatus String
		/*    */// 1 642 5 statement java.sql.PreparedStatement
		/*    */// 4 619 6 resultSet java.sql.ResultSet
		/*    */// 7 656 7 connection java.sql.Connection
		/*    */// 10 220 8 dFechaIni java.util.Date
		/*    */// 13 237 9 dFechaFin java.util.Date
		/*    */// 22 105 10 query StringBuffer
		/*    */// 31 639 11 historicoAvisosTO
				// java.util.ArrayList<com.claro.transfer.AvisosTO>
		/*    */// 294 185 12 avisosTO com.claro.transfer.AvisosTO
		/*    */// 497 10 12 e java.sql.SQLException
		/*    */// 512 11 12 e NumberFormatException
		/*    */// 528 11 12 e Exception
		/*    */// 544 63 13 localObject Object
		/*    */// 564 1 14 localException1 Exception
		/*    */// 584 1 14 localException2 Exception
		/*    */// 604 1 14 localException3 Exception
		/*    */// 627 1 14 localException4 Exception
		/*    */// 647 1 14 localException5 Exception
		/*    */// 667 1 14 localException6 Exception
		/*    */// Exception table:
		/*    */// from to target type
		/*    */// 113 494 497 java/sql/SQLException
		/*    */// 113 494 512 java/lang/NumberFormatException
		/*    */// 113 494 528 java/lang/Exception
		/*    */// 113 544 544 finally
		/*    */// 551 561 564 java/lang/Exception
		/*    */// 571 581 584 java/lang/Exception
		/*    */// 591 601 604 java/lang/Exception
		/*    */// 614 624 627 java/lang/Exception
		/*    */// 634 644 647 java/lang/Exception
		/*    */// 654 664 667 java/lang/Exception
		/*    */}

	/*    */
	/*    *//* Error */
	/*    */public com.claro.transfer.MensajeTO insertarAvisos(
			String sDescripcion, String sFechaFin, String sTipoAviso,
			String sUsuario, String sFechaInicio)
	/*    */throws com.claro.exception.CAException
	/*    */{
		return null;
		/*    */// Byte code:
		/*    */// 0: aconst_null
		/*    */// 1: astore 6
		/*    */// 3: aconst_null
		/*    */// 4: astore 7
		/*    */// 6: new 299 com/claro/transfer/MensajeTO
		/*    */// 9: dup
		/*    */// 10: invokespecial 301 com/claro/transfer/MensajeTO:<init> ()V
		/*    */// 13: astore 8
		/*    */// 15: new 146 java/sql/Timestamp
		/*    */// 18: dup
		/*    */// 19: invokestatic 302 java/lang/System:currentTimeMillis ()J
		/*    */// 22: invokespecial 154 java/sql/Timestamp:<init> (J)V
		/*    */// 25: astore 9
		/*    */// 27: aconst_null
		/*    */// 28: astore 10
		/*    */// 30: aconst_null
		/*    */// 31: astore 11
		/*    */// 33: iconst_0
		/*    */// 34: istore 12
		/*    */// 36: aload_0
		/*    */// 37: invokevirtual 307 com/claro/dao/AvisosDAO:maxIdAvisos ()I
		/*    */// 40: istore 12
		/*    */// 42: new 114 java/lang/StringBuilder
		/*    */// 45: dup
		/*    */// 46: ldc_w 311
		/*    */// 49: invokespecial 122 java/lang/StringBuilder:<init>
				// (Ljava/lang/String;)V
		/*    */// 52: aload_0
		/*    */// 53: getfield 41 com/claro/dao/AvisosDAO:schema_database
				// Ljava/lang/String;
		/*    */// 56: invokevirtual 127 java/lang/StringBuilder:append
				// (Ljava/lang/String;)Ljava/lang/StringBuilder;
		/*    */// 59: ldc_w 313
		/*    */// 62: invokevirtual 127 java/lang/StringBuilder:append
				// (Ljava/lang/String;)Ljava/lang/StringBuilder;
		/*    */// 65: ldc_w 315
		/*    */// 68: invokevirtual 127 java/lang/StringBuilder:append
				// (Ljava/lang/String;)Ljava/lang/StringBuilder;
		/*    */// 71: ldc_w 317
		/*    */// 74: invokevirtual 127 java/lang/StringBuilder:append
				// (Ljava/lang/String;)Ljava/lang/StringBuilder;
		/*    */// 77: invokevirtual 130 java/lang/StringBuilder:toString
				// ()Ljava/lang/String;
		/*    */// 80: astore 13
		/*    */// 82: invokestatic 29 com/claro/util/ServiceLocator:getInstance
				// ()Lcom/claro/util/ServiceLocator;
		/*    */// 85: getstatic 89 com/claro/util/ServiceLocator:jdbcCirculoAzul
				// Ljava/lang/String;
		/*    */// 88: invokevirtual 92 com/claro/util/ServiceLocator:getConnection
				// (Ljava/lang/String;)Ljava/sql/Connection;
		/*    */// 91: astore 7
		/*    */// 93: aload 7
		/*    */// 95: aload 13
		/*    */// 97: invokevirtual 319 java/lang/String:toString
				// ()Ljava/lang/String;
		/*    */// 100: invokeinterface 100 2 0
		/*    */// 105: astore 6
		/*    */// 107: getstatic 131
				// com/claro/util/Constantes:DATEFORMATMM_dd_YYYY
				// Ljava/text/SimpleDateFormat;
		/*    */// 110: aload 5
		/*    */// 112: invokevirtual 137 java/text/SimpleDateFormat:parse
				// (Ljava/lang/String;)Ljava/util/Date;
		/*    */// 115: astore 10
		/*    */// 117: getstatic 131
				// com/claro/util/Constantes:DATEFORMATMM_dd_YYYY
				// Ljava/text/SimpleDateFormat;
		/*    */// 120: aload_2
		/*    */// 121: invokevirtual 137 java/text/SimpleDateFormat:parse
				// (Ljava/lang/String;)Ljava/util/Date;
		/*    */// 124: astore 11
		/*    */// 126: aload 6
		/*    */// 128: iconst_1
		/*    */// 129: iload 12
		/*    */// 131: invokeinterface 320 3 0
		/*    */// 136: aload 6
		/*    */// 138: iconst_2
		/*    */// 139: aload_1
		/*    */// 140: invokeinterface 106 3 0
		/*    */// 145: aload 6
		/*    */// 147: iconst_3
		/*    */// 148: aload 9
		/*    */// 150: invokeinterface 157 3 0
		/*    */// 155: aload 6
		/*    */// 157: iconst_4
		/*    */// 158: new 146 java/sql/Timestamp
		/*    */// 161: dup
		/*    */// 162: aload 11
		/*    */// 164: invokevirtual 148 java/util/Date:getTime ()J
		/*    */// 167: invokespecial 154 java/sql/Timestamp:<init> (J)V
		/*    */// 170: invokeinterface 157 3 0
		/*    */// 175: aload 6
		/*    */// 177: iconst_5
		/*    */// 178: aload_3
		/*    */// 179: invokeinterface 106 3 0
		/*    */// 184: aload 6
		/*    */// 186: bipush 6
		/*    */// 188: aload 4
		/*    */// 190: invokeinterface 106 3 0
		/*    */// 195: aload 6
		/*    */// 197: bipush 7
		/*    */// 199: new 146 java/sql/Timestamp
		/*    */// 202: dup
		/*    */// 203: aload 10
		/*    */// 205: invokevirtual 148 java/util/Date:getTime ()J
		/*    */// 208: invokespecial 154 java/sql/Timestamp:<init> (J)V
		/*    */// 211: invokeinterface 157 3 0
		/*    */// 216: aload 6
		/*    */// 218: invokeinterface 324 1 0
		/*    */// 223: ifle +15 -> 238
		/*    */// 226: aload 8
		/*    */// 228: iconst_0
		/*    */// 229: ldc_w 327
		/*    */// 232: invokevirtual 329
				// com/claro/transfer/MensajeTO:agregaMensaje
				// (ILjava/lang/String;)V
		/*    */// 235: goto +164 -> 399
		/*    */// 238: aload 8
		/*    */// 240: iconst_m1
		/*    */// 241: ldc_w 332
		/*    */// 244: invokevirtual 329
				// com/claro/transfer/MensajeTO:agregaMensaje
				// (ILjava/lang/String;)V
		/*    */// 247: goto +152 -> 399
		/*    */// 250: astore 14
		/*    */// 252: aload_0
		/*    */// 253: getfield 27 com/claro/dao/AvisosDAO:error
				// Lorg/apache/log4j/Logger;
		/*    */// 256: ldc_w 334
		/*    */// 259: aload 14
		/*    */// 261: invokevirtual 336 org/apache/log4j/Logger:info
				// (Ljava/lang/Object;Ljava/lang/Throwable;)V
		/*    */// 264: new 59 com/claro/exception/CAException
		/*    */// 267: dup
		/*    */// 268: iconst_m1
		/*    */// 269: new 114 java/lang/StringBuilder
		/*    */// 272: dup
		/*    */// 273: ldc_w 339
		/*    */// 276: invokespecial 122 java/lang/StringBuilder:<init>
				// (Ljava/lang/String;)V
		/*    */// 279: aload 14
		/*    */// 281: invokevirtual 341 java/sql/SQLException:toString
				// ()Ljava/lang/String;
		/*    */// 284: invokevirtual 127 java/lang/StringBuilder:append
				// (Ljava/lang/String;)Ljava/lang/StringBuilder;
		/*    */// 287: ldc_w 342
		/*    */// 290: invokevirtual 127 java/lang/StringBuilder:append
				// (Ljava/lang/String;)Ljava/lang/StringBuilder;
		/*    */// 293: invokevirtual 130 java/lang/StringBuilder:toString
				// ()Ljava/lang/String;
		/*    */// 296: aload 14
		/*    */// 298: invokespecial 256 com/claro/exception/CAException:<init>
				// (ILjava/lang/String;Ljava/lang/Exception;)V
		/*    */// 301: athrow
		/*    */// 302: astore 14
		/*    */// 304: aload_0
		/*    */// 305: getfield 27 com/claro/dao/AvisosDAO:error
				// Lorg/apache/log4j/Logger;
		/*    */// 308: ldc_w 344
		/*    */// 311: aload 14
		/*    */// 313: invokevirtual 336 org/apache/log4j/Logger:info
				// (Ljava/lang/Object;Ljava/lang/Throwable;)V
		/*    */// 316: new 59 com/claro/exception/CAException
		/*    */// 319: dup
		/*    */// 320: iconst_m1
		/*    */// 321: new 114 java/lang/StringBuilder
		/*    */// 324: dup
		/*    */// 325: ldc_w 346
		/*    */// 328: invokespecial 122 java/lang/StringBuilder:<init>
				// (Ljava/lang/String;)V
		/*    */// 331: aload 14
		/*    */// 333: invokevirtual 348 java/lang/Exception:toString
				// ()Ljava/lang/String;
		/*    */// 336: invokevirtual 127 java/lang/StringBuilder:append
				// (Ljava/lang/String;)Ljava/lang/StringBuilder;
		/*    */// 339: ldc_w 342
		/*    */// 342: invokevirtual 127 java/lang/StringBuilder:append
				// (Ljava/lang/String;)Ljava/lang/StringBuilder;
		/*    */// 345: invokevirtual 130 java/lang/StringBuilder:toString
				// ()Ljava/lang/String;
		/*    */// 348: aload 14
		/*    */// 350: invokespecial 256 com/claro/exception/CAException:<init>
				// (ILjava/lang/String;Ljava/lang/Exception;)V
		/*    */// 353: athrow
		/*    */// 354: astore 15
		/*    */// 356: aload 6
		/*    */// 358: ifnull +18 -> 376
		/*    */// 361: aload 6
		/*    */// 363: invokeinterface 266 1 0
		/*    */// 368: aconst_null
		/*    */// 369: astore 6
		/*    */// 371: goto +5 -> 376
		/*    */// 374: astore 16
		/*    */// 376: aload 7
		/*    */// 378: ifnull +18 -> 396
		/*    */// 381: aload 7
		/*    */// 383: invokeinterface 267 1 0
		/*    */// 388: aconst_null
		/*    */// 389: astore 7
		/*    */// 391: goto +5 -> 396
		/*    */// 394: astore 16
		/*    */// 396: aload 15
		/*    */// 398: athrow
		/*    */// 399: aload 6
		/*    */// 401: ifnull +18 -> 419
		/*    */// 404: aload 6
		/*    */// 406: invokeinterface 266 1 0
		/*    */// 411: aconst_null
		/*    */// 412: astore 6
		/*    */// 414: goto +5 -> 419
		/*    */// 417: astore 16
		/*    */// 419: aload 7
		/*    */// 421: ifnull +18 -> 439
		/*    */// 424: aload 7
		/*    */// 426: invokeinterface 267 1 0
		/*    */// 431: aconst_null
		/*    */// 432: astore 7
		/*    */// 434: goto +5 -> 439
		/*    */// 437: astore 16
		/*    */// 439: aload 8
		/*    */// 441: areturn
		/*    */// Line number table:
		/*    */// Java source line #126 -> byte code offset #0
		/*    */// Java source line #127 -> byte code offset #3
		/*    */// Java source line #128 -> byte code offset #6
		/*    */// Java source line #129 -> byte code offset #15
		/*    */// Java source line #130 -> byte code offset #27
		/*    */// Java source line #131 -> byte code offset #30
		/*    */// Java source line #133 -> byte code offset #33
		/*    */// Java source line #135 -> byte code offset #36
		/*    */// Java source line #137 -> byte code offset #42
		/*    */// Java source line #138 -> byte code offset #65
		/*    */// Java source line #139 -> byte code offset #71
		/*    */// Java source line #137 -> byte code offset #77
		/*    */// Java source line #142 -> byte code offset #82
		/*    */// Java source line #143 -> byte code offset #93
		/*    */// Java source line #145 -> byte code offset #107
		/*    */// Java source line #146 -> byte code offset #117
		/*    */// Java source line #148 -> byte code offset #126
		/*    */// Java source line #149 -> byte code offset #136
		/*    */// Java source line #150 -> byte code offset #145
		/*    */// Java source line #151 -> byte code offset #155
		/*    */// Java source line #152 -> byte code offset #175
		/*    */// Java source line #153 -> byte code offset #184
		/*    */// Java source line #154 -> byte code offset #195
		/*    */// Java source line #156 -> byte code offset #216
		/*    */// Java source line #157 -> byte code offset #226
		/*    */// Java source line #158 -> byte code offset #238
		/*    */// Java source line #161 -> byte code offset #250
		/*    */// Java source line #162 -> byte code offset #252
		/*    */// Java source line #163 -> byte code offset #264
		/*    */// Java source line #164 -> byte code offset #302
		/*    */// Java source line #165 -> byte code offset #304
		/*    */// Java source line #166 -> byte code offset #316
		/*    */// Java source line #167 -> byte code offset #354
		/*    */// Java source line #168 -> byte code offset #356
		/*    */// Java source line #169 -> byte code offset #376
		/*    */// Java source line #170 -> byte code offset #396
		/*    */// Java source line #168 -> byte code offset #399
		/*    */// Java source line #169 -> byte code offset #419
		/*    */// Java source line #171 -> byte code offset #439
		/*    */// Local variable table:
		/*    */// start length slot name signature
		/*    */// 0 442 0 this AvisosDAO
		/*    */// 0 442 1 sDescripcion String
		/*    */// 0 442 2 sFechaFin String
		/*    */// 0 442 3 sTipoAviso String
		/*    */// 0 442 4 sUsuario String
		/*    */// 0 442 5 sFechaInicio String
		/*    */// 1 412 6 statement java.sql.PreparedStatement
		/*    */// 4 429 7 connection java.sql.Connection
		/*    */// 13 427 8 mensajeTO com.claro.transfer.MensajeTO
		/*    */// 25 124 9 fechaAlta java.sql.Timestamp
		/*    */// 28 176 10 dFechaIni java.util.Date
		/*    */// 31 132 11 dFechaFin java.util.Date
		/*    */// 34 96 12 indice int
		/*    */// 80 16 13 queryInsert String
		/*    */// 250 47 14 e java.sql.SQLException
		/*    */// 302 47 14 e Exception
		/*    */// 354 43 15 localObject Object
		/*    */// 374 1 16 localException1 Exception
		/*    */// 394 1 16 localException2 Exception
		/*    */// 417 1 16 localException3 Exception
		/*    */// 437 1 16 localException4 Exception
		/*    */// Exception table:
		/*    */// from to target type
		/*    */// 82 247 250 java/sql/SQLException
		/*    */// 82 247 302 java/lang/Exception
		/*    */// 82 354 354 finally
		/*    */// 361 371 374 java/lang/Exception
		/*    */// 381 391 394 java/lang/Exception
		/*    */// 404 414 417 java/lang/Exception
		/*    */// 424 434 437 java/lang/Exception
		/*    */}

	/*    */
	/*    *//* Error */
	/*    */public com.claro.transfer.MensajeTO eliminarAvisos(String sUsuarioMod,
			int idAviso)
	/*    */throws com.claro.exception.CAException
	/*    */{
		return null;
		/*    */// Byte code:
		/*    */// 0: aconst_null
		/*    */// 1: astore_3
		/*    */// 2: aconst_null
		/*    */// 3: astore 4
		/*    */// 5: new 299 com/claro/transfer/MensajeTO
		/*    */// 8: dup
		/*    */// 9: invokespecial 301 com/claro/transfer/MensajeTO:<init> ()V
		/*    */// 12: astore 5
		/*    */// 14: new 146 java/sql/Timestamp
		/*    */// 17: dup
		/*    */// 18: invokestatic 302 java/lang/System:currentTimeMillis ()J
		/*    */// 21: invokespecial 154 java/sql/Timestamp:<init> (J)V
		/*    */// 24: astore 6
		/*    */// 26: new 114 java/lang/StringBuilder
		/*    */// 29: dup
		/*    */// 30: ldc_w 362
		/*    */// 33: invokespecial 122 java/lang/StringBuilder:<init>
				// (Ljava/lang/String;)V
		/*    */// 36: aload_0
		/*    */// 37: getfield 41 com/claro/dao/AvisosDAO:schema_database
				// Ljava/lang/String;
		/*    */// 40: invokevirtual 127 java/lang/StringBuilder:append
				// (Ljava/lang/String;)Ljava/lang/StringBuilder;
		/*    */// 43: ldc_w 364
		/*    */// 46: invokevirtual 127 java/lang/StringBuilder:append
				// (Ljava/lang/String;)Ljava/lang/StringBuilder;
		/*    */// 49: ldc_w 366
		/*    */// 52: invokevirtual 127 java/lang/StringBuilder:append
				// (Ljava/lang/String;)Ljava/lang/StringBuilder;
		/*    */// 55: invokevirtual 130 java/lang/StringBuilder:toString
				// ()Ljava/lang/String;
		/*    */// 58: astore 7
		/*    */// 60: invokestatic 29 com/claro/util/ServiceLocator:getInstance
				// ()Lcom/claro/util/ServiceLocator;
		/*    */// 63: getstatic 89 com/claro/util/ServiceLocator:jdbcCirculoAzul
				// Ljava/lang/String;
		/*    */// 66: invokevirtual 92 com/claro/util/ServiceLocator:getConnection
				// (Ljava/lang/String;)Ljava/sql/Connection;
		/*    */// 69: astore 4
		/*    */// 71: aload 4
		/*    */// 73: aload 7
		/*    */// 75: invokeinterface 100 2 0
		/*    */// 80: astore_3
		/*    */// 81: aload_3
		/*    */// 82: iconst_1
		/*    */// 83: aload_1
		/*    */// 84: invokeinterface 106 3 0
		/*    */// 89: aload_3
		/*    */// 90: iconst_2
		/*    */// 91: aload 6
		/*    */// 93: invokeinterface 157 3 0
		/*    */// 98: aload_3
		/*    */// 99: iconst_3
		/*    */// 100: iload_2
		/*    */// 101: invokeinterface 320 3 0
		/*    */// 106: aload_3
		/*    */// 107: invokeinterface 324 1 0
		/*    */// 112: ifle +15 -> 127
		/*    */// 115: aload 5
		/*    */// 117: iconst_0
		/*    */// 118: ldc_w 368
		/*    */// 121: invokevirtual 329
				// com/claro/transfer/MensajeTO:agregaMensaje
				// (ILjava/lang/String;)V
		/*    */// 124: goto +161 -> 285
		/*    */// 127: aload 5
		/*    */// 129: iconst_1
		/*    */// 130: ldc_w 370
		/*    */// 133: invokevirtual 329
				// com/claro/transfer/MensajeTO:agregaMensaje
				// (ILjava/lang/String;)V
		/*    */// 136: goto +149 -> 285
		/*    */// 139: astore 8
		/*    */// 141: aload 4
		/*    */// 143: ifnull +15 -> 158
		/*    */// 146: aload 4
		/*    */// 148: invokeinterface 372 1 0
		/*    */// 153: goto +5 -> 158
		/*    */// 156: astore 9
		/*    */// 158: aload_0
		/*    */// 159: getfield 27 com/claro/dao/AvisosDAO:error
				// Lorg/apache/log4j/Logger;
		/*    */// 162: ldc_w 375
		/*    */// 165: aload 8
		/*    */// 167: invokevirtual 336 org/apache/log4j/Logger:info
				// (Ljava/lang/Object;Ljava/lang/Throwable;)V
		/*    */// 170: new 59 com/claro/exception/CAException
		/*    */// 173: dup
		/*    */// 174: iconst_m1
		/*    */// 175: new 114 java/lang/StringBuilder
		/*    */// 178: dup
		/*    */// 179: ldc_w 377
		/*    */// 182: invokespecial 122 java/lang/StringBuilder:<init>
				// (Ljava/lang/String;)V
		/*    */// 185: aload 8
		/*    */// 187: invokevirtual 341 java/sql/SQLException:toString
				// ()Ljava/lang/String;
		/*    */// 190: invokevirtual 127 java/lang/StringBuilder:append
				// (Ljava/lang/String;)Ljava/lang/StringBuilder;
		/*    */// 193: ldc_w 379
		/*    */// 196: invokevirtual 127 java/lang/StringBuilder:append
				// (Ljava/lang/String;)Ljava/lang/StringBuilder;
		/*    */// 199: invokevirtual 130 java/lang/StringBuilder:toString
				// ()Ljava/lang/String;
		/*    */// 202: aload 8
		/*    */// 204: invokespecial 256 com/claro/exception/CAException:<init>
				// (ILjava/lang/String;Ljava/lang/Exception;)V
		/*    */// 207: athrow
		/*    */// 208: astore 8
		/*    */// 210: aload_0
		/*    */// 211: getfield 27 com/claro/dao/AvisosDAO:error
				// Lorg/apache/log4j/Logger;
		/*    */// 214: ldc_w 381
		/*    */// 217: aload 8
		/*    */// 219: invokevirtual 336 org/apache/log4j/Logger:info
				// (Ljava/lang/Object;Ljava/lang/Throwable;)V
		/*    */// 222: new 59 com/claro/exception/CAException
		/*    */// 225: dup
		/*    */// 226: iconst_m1
		/*    */// 227: new 114 java/lang/StringBuilder
		/*    */// 230: dup
		/*    */// 231: ldc_w 383
		/*    */// 234: invokespecial 122 java/lang/StringBuilder:<init>
				// (Ljava/lang/String;)V
		/*    */// 237: aload 8
		/*    */// 239: invokevirtual 348 java/lang/Exception:toString
				// ()Ljava/lang/String;
		/*    */// 242: invokevirtual 127 java/lang/StringBuilder:append
				// (Ljava/lang/String;)Ljava/lang/StringBuilder;
		/*    */// 245: ldc_w 379
		/*    */// 248: invokevirtual 127 java/lang/StringBuilder:append
				// (Ljava/lang/String;)Ljava/lang/StringBuilder;
		/*    */// 251: invokevirtual 130 java/lang/StringBuilder:toString
				// ()Ljava/lang/String;
		/*    */// 254: aload 8
		/*    */// 256: invokespecial 256 com/claro/exception/CAException:<init>
				// (ILjava/lang/String;Ljava/lang/Exception;)V
		/*    */// 259: athrow
		/*    */// 260: astore 10
		/*    */// 262: aload 4
		/*    */// 264: ifnonnull +18 -> 282
		/*    */// 267: aload 4
		/*    */// 269: invokeinterface 267 1 0
		/*    */// 274: aconst_null
		/*    */// 275: astore 4
		/*    */// 277: goto +5 -> 282
		/*    */// 280: astore 11
		/*    */// 282: aload 10
		/*    */// 284: athrow
		/*    */// 285: aload 4
		/*    */// 287: ifnonnull +18 -> 305
		/*    */// 290: aload 4
		/*    */// 292: invokeinterface 267 1 0
		/*    */// 297: aconst_null
		/*    */// 298: astore 4
		/*    */// 300: goto +5 -> 305
		/*    */// 303: astore 11
		/*    */// 305: aload 5
		/*    */// 307: areturn
		/*    */// Line number table:
		/*    */// Java source line #176 -> byte code offset #0
		/*    */// Java source line #177 -> byte code offset #2
		/*    */// Java source line #178 -> byte code offset #5
		/*    */// Java source line #179 -> byte code offset #14
		/*    */// Java source line #181 -> byte code offset #26
		/*    */// Java source line #182 -> byte code offset #49
		/*    */// Java source line #181 -> byte code offset #55
		/*    */// Java source line #185 -> byte code offset #60
		/*    */// Java source line #186 -> byte code offset #71
		/*    */// Java source line #188 -> byte code offset #81
		/*    */// Java source line #189 -> byte code offset #89
		/*    */// Java source line #190 -> byte code offset #98
		/*    */// Java source line #192 -> byte code offset #106
		/*    */// Java source line #193 -> byte code offset #127
		/*    */// Java source line #194 -> byte code offset #139
		/*    */// Java source line #195 -> byte code offset #141
		/*    */// Java source line #196 -> byte code offset #158
		/*    */// Java source line #197 -> byte code offset #170
		/*    */// Java source line #198 -> byte code offset #208
		/*    */// Java source line #199 -> byte code offset #210
		/*    */// Java source line #200 -> byte code offset #222
		/*    */// Java source line #201 -> byte code offset #260
		/*    */// Java source line #202 -> byte code offset #262
		/*    */// Java source line #203 -> byte code offset #282
		/*    */// Java source line #202 -> byte code offset #285
		/*    */// Java source line #204 -> byte code offset #305
		/*    */// Local variable table:
		/*    */// start length slot name signature
		/*    */// 0 308 0 this AvisosDAO
		/*    */// 0 308 1 sUsuarioMod String
		/*    */// 0 308 2 idAviso int
		/*    */// 1 106 3 statement java.sql.PreparedStatement
		/*    */// 3 296 4 connection java.sql.Connection
		/*    */// 12 294 5 mensajeTO com.claro.transfer.MensajeTO
		/*    */// 24 68 6 fechaMod java.sql.Timestamp
		/*    */// 58 16 7 query String
		/*    */// 139 64 8 e java.sql.SQLException
		/*    */// 208 47 8 e Exception
		/*    */// 156 1 9 localException1 Exception
		/*    */// 260 23 10 localObject Object
		/*    */// 280 1 11 localException2 Exception
		/*    */// 303 1 11 localException3 Exception
		/*    */// Exception table:
		/*    */// from to target type
		/*    */// 60 136 139 java/sql/SQLException
		/*    */// 146 153 156 java/lang/Exception
		/*    */// 60 136 208 java/lang/Exception
		/*    */// 60 260 260 finally
		/*    */// 267 277 280 java/lang/Exception
		/*    */// 290 300 303 java/lang/Exception
		/*    */}

	/*    */
	/*    *//* Error */
	/*    */public java.util.ArrayList<com.claro.transfer.AvisosTO> marquesinaAvisos(
			long fecha)
	/*    */throws com.claro.exception.CAException
	/*    */{
		return null;
		/*    */// Byte code:
		/*    */// 0: aconst_null
		/*    */// 1: astore_3
		/*    */// 2: aconst_null
		/*    */// 3: astore 4
		/*    */// 5: aconst_null
		/*    */// 6: astore 5
		/*    */// 8: new 63 java/lang/StringBuffer
		/*    */// 11: dup
		/*    */// 12: invokespecial 65 java/lang/StringBuffer:<init> ()V
		/*    */// 15: astore 6
		/*    */// 17: new 66 java/util/ArrayList
		/*    */// 20: dup
		/*    */// 21: invokespecial 68 java/util/ArrayList:<init> ()V
		/*    */// 24: astore 7
		/*    */// 26: aload 6
		/*    */// 28: ldc_w 391
		/*    */// 31: invokevirtual 71 java/lang/StringBuffer:append
				// (Ljava/lang/String;)Ljava/lang/StringBuffer;
		/*    */// 34: pop
		/*    */// 35: aload 6
		/*    */// 37: ldc 77
		/*    */// 39: invokevirtual 71 java/lang/StringBuffer:append
				// (Ljava/lang/String;)Ljava/lang/StringBuffer;
		/*    */// 42: aload_0
		/*    */// 43: getfield 41 com/claro/dao/AvisosDAO:schema_database
				// Ljava/lang/String;
		/*    */// 46: invokevirtual 71 java/lang/StringBuffer:append
				// (Ljava/lang/String;)Ljava/lang/StringBuffer;
		/*    */// 49: ldc 79
		/*    */// 51: invokevirtual 71 java/lang/StringBuffer:append
				// (Ljava/lang/String;)Ljava/lang/StringBuffer;
		/*    */// 54: pop
		/*    */// 55: aload 6
		/*    */// 57: ldc_w 393
		/*    */// 60: invokevirtual 71 java/lang/StringBuffer:append
				// (Ljava/lang/String;)Ljava/lang/StringBuffer;
		/*    */// 63: pop
		/*    */// 64: aload 6
		/*    */// 66: ldc_w 395
		/*    */// 69: invokevirtual 71 java/lang/StringBuffer:append
				// (Ljava/lang/String;)Ljava/lang/StringBuffer;
		/*    */// 72: pop
		/*    */// 73: invokestatic 29 com/claro/util/ServiceLocator:getInstance
				// ()Lcom/claro/util/ServiceLocator;
		/*    */// 76: getstatic 89 com/claro/util/ServiceLocator:jdbcCirculoAzul
				// Ljava/lang/String;
		/*    */// 79: invokevirtual 92 com/claro/util/ServiceLocator:getConnection
				// (Ljava/lang/String;)Ljava/sql/Connection;
		/*    */// 82: astore 5
		/*    */// 84: aload 5
		/*    */// 86: aload 6
		/*    */// 88: invokevirtual 96 java/lang/StringBuffer:toString
				// ()Ljava/lang/String;
		/*    */// 91: invokeinterface 100 2 0
		/*    */// 96: astore_3
		/*    */// 97: aload_3
		/*    */// 98: iconst_1
		/*    */// 99: ldc 112
		/*    */// 101: invokeinterface 106 3 0
		/*    */// 106: aload_3
		/*    */// 107: iconst_2
		/*    */// 108: new 146 java/sql/Timestamp
		/*    */// 111: dup
		/*    */// 112: lload_1
		/*    */// 113: invokespecial 154 java/sql/Timestamp:<init> (J)V
		/*    */// 116: invokeinterface 157 3 0
		/*    */// 121: aload_3
		/*    */// 122: invokeinterface 161 1 0
		/*    */// 127: astore 4
		/*    */// 129: goto +48 -> 177
		/*    */// 132: new 165 com/claro/transfer/AvisosTO
		/*    */// 135: dup
		/*    */// 136: invokespecial 167 com/claro/transfer/AvisosTO:<init> ()V
		/*    */// 139: astore 8
		/*    */// 141: aload 8
		/*    */// 143: aload 4
		/*    */// 145: ldc -68
		/*    */// 147: invokeinterface 182 2 0
		/*    */// 152: invokevirtual 190
				// com/claro/transfer/AvisosTO:setDescripcion
				// (Ljava/lang/String;)V
		/*    */// 155: aload 8
		/*    */// 157: aload 4
		/*    */// 159: ldc -43
		/*    */// 161: invokeinterface 182 2 0
		/*    */// 166: invokevirtual 223 com/claro/transfer/AvisosTO:setTipoAviso
				// (Ljava/lang/String;)V
		/*    */// 169: aload 7
		/*    */// 171: aload 8
		/*    */// 173: invokevirtual 247 java/util/ArrayList:add
				// (Ljava/lang/Object;)Z
		/*    */// 176: pop
		/*    */// 177: aload 4
		/*    */// 179: invokeinterface 250 1 0
		/*    */// 184: ifne -52 -> 132
		/*    */// 187: goto +113 -> 300
		/*    */// 190: astore 8
		/*    */// 192: new 59 com/claro/exception/CAException
		/*    */// 195: dup
		/*    */// 196: iconst_m1
		/*    */// 197: ldc_w 397
		/*    */// 200: aload 8
		/*    */// 202: invokespecial 256 com/claro/exception/CAException:<init>
				// (ILjava/lang/String;Ljava/lang/Exception;)V
		/*    */// 205: athrow
		/*    */// 206: astore 8
		/*    */// 208: new 59 com/claro/exception/CAException
		/*    */// 211: dup
		/*    */// 212: iconst_m1
		/*    */// 213: ldc_w 399
		/*    */// 216: aload 8
		/*    */// 218: invokespecial 256 com/claro/exception/CAException:<init>
				// (ILjava/lang/String;Ljava/lang/Exception;)V
		/*    */// 221: athrow
		/*    */// 222: astore 8
		/*    */// 224: new 59 com/claro/exception/CAException
		/*    */// 227: dup
		/*    */// 228: iconst_m1
		/*    */// 229: ldc_w 401
		/*    */// 232: aload 8
		/*    */// 234: invokespecial 256 com/claro/exception/CAException:<init>
				// (ILjava/lang/String;Ljava/lang/Exception;)V
		/*    */// 237: athrow
		/*    */// 238: astore 9
		/*    */// 240: aload 4
		/*    */// 242: ifnull +18 -> 260
		/*    */// 245: aload 4
		/*    */// 247: invokeinterface 263 1 0
		/*    */// 252: aconst_null
		/*    */// 253: astore 4
		/*    */// 255: goto +5 -> 260
		/*    */// 258: astore 10
		/*    */// 260: aload_3
		/*    */// 261: ifnull +16 -> 277
		/*    */// 264: aload_3
		/*    */// 265: invokeinterface 266 1 0
		/*    */// 270: aconst_null
		/*    */// 271: astore_3
		/*    */// 272: goto +5 -> 277
		/*    */// 275: astore 10
		/*    */// 277: aload 5
		/*    */// 279: ifnull +18 -> 297
		/*    */// 282: aload 5
		/*    */// 284: invokeinterface 267 1 0
		/*    */// 289: aconst_null
		/*    */// 290: astore 5
		/*    */// 292: goto +5 -> 297
		/*    */// 295: astore 10
		/*    */// 297: aload 9
		/*    */// 299: athrow
		/*    */// 300: aload 4
		/*    */// 302: ifnull +18 -> 320
		/*    */// 305: aload 4
		/*    */// 307: invokeinterface 263 1 0
		/*    */// 312: aconst_null
		/*    */// 313: astore 4
		/*    */// 315: goto +5 -> 320
		/*    */// 318: astore 10
		/*    */// 320: aload_3
		/*    */// 321: ifnull +16 -> 337
		/*    */// 324: aload_3
		/*    */// 325: invokeinterface 266 1 0
		/*    */// 330: aconst_null
		/*    */// 331: astore_3
		/*    */// 332: goto +5 -> 337
		/*    */// 335: astore 10
		/*    */// 337: aload 5
		/*    */// 339: ifnull +18 -> 357
		/*    */// 342: aload 5
		/*    */// 344: invokeinterface 267 1 0
		/*    */// 349: aconst_null
		/*    */// 350: astore 5
		/*    */// 352: goto +5 -> 357
		/*    */// 355: astore 10
		/*    */// 357: aload 7
		/*    */// 359: areturn
		/*    */// Line number table:
		/*    */// Java source line #209 -> byte code offset #0
		/*    */// Java source line #210 -> byte code offset #2
		/*    */// Java source line #211 -> byte code offset #5
		/*    */// Java source line #213 -> byte code offset #8
		/*    */// Java source line #214 -> byte code offset #17
		/*    */// Java source line #216 -> byte code offset #26
		/*    */// Java source line #217 -> byte code offset #35
		/*    */// Java source line #218 -> byte code offset #55
		/*    */// Java source line #219 -> byte code offset #64
		/*    */// Java source line #222 -> byte code offset #73
		/*    */// Java source line #223 -> byte code offset #84
		/*    */// Java source line #225 -> byte code offset #97
		/*    */// Java source line #227 -> byte code offset #106
		/*    */// Java source line #230 -> byte code offset #121
		/*    */// Java source line #231 -> byte code offset #129
		/*    */// Java source line #232 -> byte code offset #132
		/*    */// Java source line #233 -> byte code offset #141
		/*    */// Java source line #234 -> byte code offset #155
		/*    */// Java source line #235 -> byte code offset #169
		/*    */// Java source line #231 -> byte code offset #177
		/*    */// Java source line #237 -> byte code offset #190
		/*    */// Java source line #238 -> byte code offset #192
		/*    */// Java source line #239 -> byte code offset #206
		/*    */// Java source line #240 -> byte code offset #208
		/*    */// Java source line #241 -> byte code offset #222
		/*    */// Java source line #242 -> byte code offset #224
		/*    */// Java source line #243 -> byte code offset #238
		/*    */// Java source line #244 -> byte code offset #240
		/*    */// Java source line #245 -> byte code offset #260
		/*    */// Java source line #246 -> byte code offset #277
		/*    */// Java source line #247 -> byte code offset #297
		/*    */// Java source line #244 -> byte code offset #300
		/*    */// Java source line #245 -> byte code offset #320
		/*    */// Java source line #246 -> byte code offset #337
		/*    */// Java source line #248 -> byte code offset #357
		/*    */// Local variable table:
		/*    */// start length slot name signature
		/*    */// 0 360 0 this AvisosDAO
		/*    */// 0 360 1 fecha long
		/*    */// 1 331 3 statement java.sql.PreparedStatement
		/*    */// 3 311 4 resultSet java.sql.ResultSet
		/*    */// 6 345 5 connection java.sql.Connection
		/*    */// 15 72 6 query StringBuffer
		/*    */// 24 334 7 marquesina
				// java.util.ArrayList<com.claro.transfer.AvisosTO>
		/*    */// 139 33 8 avisosTO com.claro.transfer.AvisosTO
		/*    */// 190 11 8 e java.sql.SQLException
		/*    */// 206 11 8 e NumberFormatException
		/*    */// 222 11 8 e Exception
		/*    */// 238 60 9 localObject Object
		/*    */// 258 1 10 localException1 Exception
		/*    */// 275 1 10 localException2 Exception
		/*    */// 295 1 10 localException3 Exception
		/*    */// 318 1 10 localException4 Exception
		/*    */// 335 1 10 localException5 Exception
		/*    */// 355 1 10 localException6 Exception
		/*    */// Exception table:
		/*    */// from to target type
		/*    */// 73 187 190 java/sql/SQLException
		/*    */// 73 187 206 java/lang/NumberFormatException
		/*    */// 73 187 222 java/lang/Exception
		/*    */// 73 238 238 finally
		/*    */// 245 255 258 java/lang/Exception
		/*    */// 264 272 275 java/lang/Exception
		/*    */// 282 292 295 java/lang/Exception
		/*    */// 305 315 318 java/lang/Exception
		/*    */// 324 332 335 java/lang/Exception
		/*    */// 342 352 355 java/lang/Exception
		/*    */}

	/*    */
	/*    *//* Error */
	/*    */public int maxIdAvisos()
	/*    */throws com.claro.exception.CAException
	/*    */{
		return 0;
		/*    */// Byte code:
		/*    */// 0: aconst_null
		/*    */// 1: astore_1
		/*    */// 2: aconst_null
		/*    */// 3: astore_2
		/*    */// 4: aconst_null
		/*    */// 5: astore_3
		/*    */// 6: new 114 java/lang/StringBuilder
		/*    */// 9: dup
		/*    */// 10: ldc_w 406
		/*    */// 13: invokespecial 122 java/lang/StringBuilder:<init>
				// (Ljava/lang/String;)V
		/*    */// 16: aload_0
		/*    */// 17: getfield 41 com/claro/dao/AvisosDAO:schema_database
				// Ljava/lang/String;
		/*    */// 20: invokevirtual 127 java/lang/StringBuilder:append
				// (Ljava/lang/String;)Ljava/lang/StringBuilder;
		/*    */// 23: ldc_w 408
		/*    */// 26: invokevirtual 127 java/lang/StringBuilder:append
				// (Ljava/lang/String;)Ljava/lang/StringBuilder;
		/*    */// 29: invokevirtual 130 java/lang/StringBuilder:toString
				// ()Ljava/lang/String;
		/*    */// 32: astore 5
		/*    */// 34: invokestatic 29 com/claro/util/ServiceLocator:getInstance
				// ()Lcom/claro/util/ServiceLocator;
		/*    */// 37: getstatic 89 com/claro/util/ServiceLocator:jdbcCirculoAzul
				// Ljava/lang/String;
		/*    */// 40: invokevirtual 92 com/claro/util/ServiceLocator:getConnection
				// (Ljava/lang/String;)Ljava/sql/Connection;
		/*    */// 43: astore_2
		/*    */// 44: aload_2
		/*    */// 45: aload 5
		/*    */// 47: invokevirtual 319 java/lang/String:toString
				// ()Ljava/lang/String;
		/*    */// 50: invokeinterface 100 2 0
		/*    */// 55: astore_1
		/*    */// 56: aload_1
		/*    */// 57: invokeinterface 161 1 0
		/*    */// 62: astore_3
		/*    */// 63: aload_3
		/*    */// 64: invokeinterface 250 1 0
		/*    */// 69: ifeq +17 -> 86
		/*    */// 72: aload_3
		/*    */// 73: iconst_1
		/*    */// 74: invokeinterface 410 2 0
		/*    */// 79: iconst_1
		/*    */// 80: iadd
		/*    */// 81: istore 4
		/*    */// 83: goto +113 -> 196
		/*    */// 86: iconst_0
		/*    */// 87: istore 4
		/*    */// 89: goto +107 -> 196
		/*    */// 92: astore 6
		/*    */// 94: new 59 com/claro/exception/CAException
		/*    */// 97: dup
		/*    */// 98: iconst_m1
		/*    */// 99: ldc_w 413
		/*    */// 102: aload 6
		/*    */// 104: invokespecial 256 com/claro/exception/CAException:<init>
				// (ILjava/lang/String;Ljava/lang/Exception;)V
		/*    */// 107: athrow
		/*    */// 108: astore 6
		/*    */// 110: new 59 com/claro/exception/CAException
		/*    */// 113: dup
		/*    */// 114: iconst_m1
		/*    */// 115: ldc_w 415
		/*    */// 118: aload 6
		/*    */// 120: invokespecial 256 com/claro/exception/CAException:<init>
				// (ILjava/lang/String;Ljava/lang/Exception;)V
		/*    */// 123: athrow
		/*    */// 124: astore 6
		/*    */// 126: new 59 com/claro/exception/CAException
		/*    */// 129: dup
		/*    */// 130: iconst_m1
		/*    */// 131: ldc_w 417
		/*    */// 134: aload 6
		/*    */// 136: invokespecial 256 com/claro/exception/CAException:<init>
				// (ILjava/lang/String;Ljava/lang/Exception;)V
		/*    */// 139: athrow
		/*    */// 140: astore 7
		/*    */// 142: aload_3
		/*    */// 143: ifnull +16 -> 159
		/*    */// 146: aload_3
		/*    */// 147: invokeinterface 263 1 0
		/*    */// 152: aconst_null
		/*    */// 153: astore_3
		/*    */// 154: goto +5 -> 159
		/*    */// 157: astore 8
		/*    */// 159: aload_1
		/*    */// 160: ifnull +16 -> 176
		/*    */// 163: aload_1
		/*    */// 164: invokeinterface 266 1 0
		/*    */// 169: aconst_null
		/*    */// 170: astore_1
		/*    */// 171: goto +5 -> 176
		/*    */// 174: astore 8
		/*    */// 176: aload_2
		/*    */// 177: ifnull +16 -> 193
		/*    */// 180: aload_2
		/*    */// 181: invokeinterface 267 1 0
		/*    */// 186: aconst_null
		/*    */// 187: astore_2
		/*    */// 188: goto +5 -> 193
		/*    */// 191: astore 8
		/*    */// 193: aload 7
		/*    */// 195: athrow
		/*    */// 196: aload_3
		/*    */// 197: ifnull +16 -> 213
		/*    */// 200: aload_3
		/*    */// 201: invokeinterface 263 1 0
		/*    */// 206: aconst_null
		/*    */// 207: astore_3
		/*    */// 208: goto +5 -> 213
		/*    */// 211: astore 8
		/*    */// 213: aload_1
		/*    */// 214: ifnull +16 -> 230
		/*    */// 217: aload_1
		/*    */// 218: invokeinterface 266 1 0
		/*    */// 223: aconst_null
		/*    */// 224: astore_1
		/*    */// 225: goto +5 -> 230
		/*    */// 228: astore 8
		/*    */// 230: aload_2
		/*    */// 231: ifnull +16 -> 247
		/*    */// 234: aload_2
		/*    */// 235: invokeinterface 267 1 0
		/*    */// 240: aconst_null
		/*    */// 241: astore_2
		/*    */// 242: goto +5 -> 247
		/*    */// 245: astore 8
		/*    */// 247: iload 4
		/*    */// 249: ireturn
		/*    */// Line number table:
		/*    */// Java source line #252 -> byte code offset #0
		/*    */// Java source line #253 -> byte code offset #2
		/*    */// Java source line #254 -> byte code offset #4
		/*    */// Java source line #256 -> byte code offset #6
		/*    */// Java source line #259 -> byte code offset #34
		/*    */// Java source line #260 -> byte code offset #44
		/*    */// Java source line #263 -> byte code offset #56
		/*    */// Java source line #264 -> byte code offset #63
		/*    */// Java source line #265 -> byte code offset #72
		/*    */// Java source line #267 -> byte code offset #86
		/*    */// Java source line #270 -> byte code offset #92
		/*    */// Java source line #271 -> byte code offset #94
		/*    */// Java source line #272 -> byte code offset #108
		/*    */// Java source line #273 -> byte code offset #110
		/*    */// Java source line #274 -> byte code offset #124
		/*    */// Java source line #275 -> byte code offset #126
		/*    */// Java source line #276 -> byte code offset #140
		/*    */// Java source line #277 -> byte code offset #142
		/*    */// Java source line #278 -> byte code offset #159
		/*    */// Java source line #279 -> byte code offset #176
		/*    */// Java source line #280 -> byte code offset #193
		/*    */// Java source line #277 -> byte code offset #196
		/*    */// Java source line #278 -> byte code offset #213
		/*    */// Java source line #279 -> byte code offset #230
		/*    */// Java source line #281 -> byte code offset #247
		/*    */// Local variable table:
		/*    */// start length slot name signature
		/*    */// 0 250 0 this AvisosDAO
		/*    */// 1 224 1 statement java.sql.PreparedStatement
		/*    */// 3 239 2 connection java.sql.Connection
		/*    */// 5 203 3 resultSet java.sql.ResultSet
		/*    */// 81 3 4 idnum int
		/*    */// 87 3 4 idnum int
		/*    */// 196 52 4 idnum int
		/*    */// 32 14 5 query String
		/*    */// 92 11 6 e java.sql.SQLException
		/*    */// 108 11 6 e NumberFormatException
		/*    */// 124 11 6 e Exception
		/*    */// 140 54 7 localObject Object
		/*    */// 157 1 8 localException1 Exception
		/*    */// 174 1 8 localException2 Exception
		/*    */// 191 1 8 localException3 Exception
		/*    */// 211 1 8 localException4 Exception
		/*    */// 228 1 8 localException5 Exception
		/*    */// 245 1 8 localException6 Exception
		/*    */// Exception table:
		/*    */// from to target type
		/*    */// 34 89 92 java/sql/SQLException
		/*    */// 34 89 108 java/lang/NumberFormatException
		/*    */// 34 89 124 java/lang/Exception
		/*    */// 34 140 140 finally
		/*    */// 146 154 157 java/lang/Exception
		/*    */// 163 171 174 java/lang/Exception
		/*    */// 180 188 191 java/lang/Exception
		/*    */// 200 208 211 java/lang/Exception
		/*    */// 217 225 228 java/lang/Exception
		/*    */// 234 242 245 java/lang/Exception
		/*    */}
	/*    */
}

/*
 * Location:
 * /opt/trabajo/claro/Guatemala/IS/CO/ClaroClub.ear!/ClaroClubEJB.jar!/
 * com/claro/dao/AvisosDAO.class Java compiler version: 6 (50.0) JD-Core
 * Version: 0.7.1
 */