/*     */ package com.claro.dao;
/*     */ 
/*     */ import com.claro.exception.CAException;
/*     */ import com.claro.transfer.MobileTO;
/*     */ import com.claro.transfer.ParametrosTO;
/*     */ import com.claro.transfer.PlanTO;
/*     */ import com.claro.transfer.TelefonoTO;
/*     */ import com.claro.util.ServiceLocator;
/*     */ import java.math.BigDecimal;
/*     */ import java.math.BigInteger;
/*     */ import java.sql.Connection;
/*     */ import java.sql.ResultSet;
/*     */ import java.sql.SQLException;
/*     */ import java.sql.Statement;
/*     */ import org.apache.log4j.Logger;
/*     */ 
/*     */ 
/*     */ 
/*     */ 
/*     */ 
/*     */ 
/*     */ 
/*     */ 
/*     */ 
/*     */ 
/*     */ 
/*     */ 
/*     */ 
/*     */ 
/*     */ public class ConsultasGapDAO
/*     */ {
/*  32 */   protected final Logger logger = Logger.getLogger("loggerCirculoAzul");
/*  33 */   protected final Logger error = Logger.getLogger("loggerCirculoAzulError");
/*  34 */   private String schemaGap = null;
/*     */   
/*     */ 
/*     */ 
/*     */   public ConsultasGapDAO()
/*     */   {
/*     */     try
/*     */     {
/*  42 */       this.schemaGap = ServiceLocator.getInstance().getVariable(ServiceLocator.schemaGap_database);
/*     */     } catch (Exception e) {
/*  44 */       this.error.error("ConsultasGapDAO" + e.toString());
/*     */       
/*  46 */       e.printStackTrace();
/*     */     }
/*     */   }
/*     */   
/*     */ 
/*     */ 
/*     */ 
/*     */ 
/*     */ 
/*     */   public void consultaAnacrGap(MobileTO mobileTO, TelefonoTO telefonoTO, PlanTO planTO, ParametrosTO parametrosTO)
/*     */     throws CAException
/*     */   {
/*  58 */     StringBuffer stringBuffer = new StringBuffer();
/*  59 */     Connection connection = null;
/*  60 */     StringBuffer sRegion = new StringBuffer();
/*  61 */     Statement statement = null;
/*  62 */     ResultSet resultSet = null;
/*  63 */     String dwtag = "";
/*     */     
/*     */     try
/*     */     {
/*  67 */       telefonoTO.setSAnacr("0.9");
/*  68 */       String nCalificacion = "";
/*     */       
/*  70 */       if ((planTO.getBanMixto() != null) && (!planTO.getBanMixto().equals(""))) {
/*  71 */         if ("S".equals(planTO.getBanMixto().trim())) {
/*  72 */           dwtag = "DWTAG_VALORACION_MIXTO";
/*     */         } else
/*  74 */           dwtag = "DWTAG_VALORACION_POSPAGO";
/*     */       } else {
/*  76 */         return;
/*     */       }
/*  78 */       sRegion.append("R0").append(String.valueOf(parametrosTO.getRegion()));
/*  79 */       stringBuffer.append(" SELECT NCALIFICACION FROM ").append(this.schemaGap).append(dwtag);
/*  80 */       stringBuffer.append(" WHERE NLINEAID= ").append(new BigInteger(mobileTO.getTelefono().trim()));
/*  81 */       stringBuffer.append(" AND SREGIONID= '").append(sRegion.toString()).append("'");
/*     */       
/*  83 */       connection = ServiceLocator.getInstance().getConnection(ServiceLocator.jdbcGap);
/*  84 */       statement = connection.createStatement();
/*     */       
/*  86 */       statement.setQueryTimeout(15);
/*  87 */       resultSet = statement.executeQuery(stringBuffer.toString());
/*  88 */       if (resultSet.next()) {
/*  89 */         nCalificacion = resultSet.getBigDecimal("NCALIFICACION").toString();
/*     */       }
/*     */       
/*  92 */       if (!"".equals(nCalificacion)) {
/*  93 */         if ("0".equals(nCalificacion)) {
/*  94 */           telefonoTO.setSAnacr(new BigDecimal(nCalificacion).setScale(1).toString());
/*     */         } else {
/*  96 */           telefonoTO.setSAnacr(nCalificacion);
/*     */         }
/*     */       }
/*     */     }
/*     */     catch (SQLException exception) {
/* 101 */       throw new CAException(-1, "ConsultasGapDAO.consultaAnacrGap:[" + exception.toString() + "]");
/*     */     } catch (Exception e) {
/* 103 */       throw new CAException(-1, "ConsultasGapDAO.consultaAnacrGap:[" + e.toString() + "]");
/*     */     } finally {
/*     */       try {
/* 106 */         if (connection != null) { connection.close();connection = null; }
/* 107 */         if (statement != null) { statement.close();statement = null; }
/* 108 */         if (resultSet != null) { resultSet.close();resultSet = null;
/*     */         }
/*     */       }
/*     */       catch (SQLException localSQLException2) {}
/*     */     }
/*     */     try
/*     */     {
/* 106 */       if (connection != null) { connection.close();connection = null; }
/* 107 */       if (statement != null) { statement.close();statement = null; }
/* 108 */       if (resultSet != null) { resultSet.close();resultSet = null;
/*     */       }
/*     */     }
/*     */     catch (SQLException localSQLException3) {}
/*     */   }
/*     */   
/*     */   /* Error */
/*     */   public com.claro.transfer.gap.PromocionCaTO consultaPromocionCA(com.claro.transfer.gap.InfoPromocionGapTO infoPromocionGapTO)
/*     */     throws CAException
/*     */   {
/*     */     // Byte code:
/*     */     //   0: new 80	java/lang/StringBuffer
/*     */     //   3: dup
/*     */     //   4: invokespecial 82	java/lang/StringBuffer:<init>	()V
/*     */     //   7: astore_2
/*     */     //   8: aconst_null
/*     */     //   9: astore_3
/*     */     //   10: aconst_null
/*     */     //   11: astore 4
/*     */     //   13: aconst_null
/*     */     //   14: astore 5
/*     */     //   16: aconst_null
/*     */     //   17: astore 6
/*     */     //   19: aload_2
/*     */     //   20: ldc -24
/*     */     //   22: invokevirtual 125	java/lang/StringBuffer:append	(Ljava/lang/String;)Ljava/lang/StringBuffer;
/*     */     //   25: pop
/*     */     //   26: aload_2
/*     */     //   27: ldc -22
/*     */     //   29: invokevirtual 125	java/lang/StringBuffer:append	(Ljava/lang/String;)Ljava/lang/StringBuffer;
/*     */     //   32: pop
/*     */     //   33: aload_2
/*     */     //   34: ldc -20
/*     */     //   36: invokevirtual 125	java/lang/StringBuffer:append	(Ljava/lang/String;)Ljava/lang/StringBuffer;
/*     */     //   39: pop
/*     */     //   40: aload_2
/*     */     //   41: ldc -18
/*     */     //   43: invokevirtual 125	java/lang/StringBuffer:append	(Ljava/lang/String;)Ljava/lang/StringBuffer;
/*     */     //   46: pop
/*     */     //   47: aload_2
/*     */     //   48: ldc -16
/*     */     //   50: invokevirtual 125	java/lang/StringBuffer:append	(Ljava/lang/String;)Ljava/lang/StringBuffer;
/*     */     //   53: aload_0
/*     */     //   54: getfield 29	com/claro/dao/ConsultasGapDAO:schemaGap	Ljava/lang/String;
/*     */     //   57: invokevirtual 125	java/lang/StringBuffer:append	(Ljava/lang/String;)Ljava/lang/StringBuffer;
/*     */     //   60: ldc -14
/*     */     //   62: invokevirtual 125	java/lang/StringBuffer:append	(Ljava/lang/String;)Ljava/lang/StringBuffer;
/*     */     //   65: pop
/*     */     //   66: aload_2
/*     */     //   67: ldc -12
/*     */     //   69: invokevirtual 125	java/lang/StringBuffer:append	(Ljava/lang/String;)Ljava/lang/StringBuffer;
/*     */     //   72: pop
/*     */     //   73: invokestatic 31	com/claro/util/ServiceLocator:getInstance	()Lcom/claro/util/ServiceLocator;
/*     */     //   76: getstatic 158	com/claro/util/ServiceLocator:jdbcGap	Ljava/lang/String;
/*     */     //   79: invokevirtual 161	com/claro/util/ServiceLocator:getConnection	(Ljava/lang/String;)Ljava/sql/Connection;
/*     */     //   82: astore_3
/*     */     //   83: aload_3
/*     */     //   84: aload_2
/*     */     //   85: invokevirtual 155	java/lang/StringBuffer:toString	()Ljava/lang/String;
/*     */     //   88: invokeinterface 246 2 0
/*     */     //   93: astore 4
/*     */     //   95: aload 4
/*     */     //   97: iconst_1
/*     */     //   98: aload_1
/*     */     //   99: invokevirtual 250	com/claro/transfer/gap/InfoPromocionGapTO:getIdPromocion	()Ljava/lang/String;
/*     */     //   102: invokevirtual 105	java/lang/String:trim	()Ljava/lang/String;
/*     */     //   105: invokestatic 255	java/lang/Integer:parseInt	(Ljava/lang/String;)I
/*     */     //   108: invokeinterface 261 3 0
/*     */     //   113: aload 4
/*     */     //   115: iconst_2
/*     */     //   116: aload_1
/*     */     //   117: invokevirtual 267	com/claro/transfer/gap/InfoPromocionGapTO:getVersionPromocion	()Ljava/lang/String;
/*     */     //   120: invokestatic 255	java/lang/Integer:parseInt	(Ljava/lang/String;)I
/*     */     //   123: invokeinterface 261 3 0
/*     */     //   128: aload 4
/*     */     //   130: bipush 15
/*     */     //   132: invokeinterface 270 2 0
/*     */     //   137: aload 4
/*     */     //   139: invokeinterface 271 1 0
/*     */     //   144: astore 5
/*     */     //   146: aload 5
/*     */     //   148: invokeinterface 177 1 0
/*     */     //   153: ifeq +423 -> 576
/*     */     //   156: new 274	com/claro/transfer/gap/PromocionCaTO
/*     */     //   159: dup
/*     */     //   160: invokespecial 276	com/claro/transfer/gap/PromocionCaTO:<init>	()V
/*     */     //   163: astore 6
/*     */     //   165: aload 6
/*     */     //   167: aload 5
/*     */     //   169: ldc_w 277
/*     */     //   172: invokeinterface 279 2 0
/*     */     //   177: invokevirtual 282	com/claro/transfer/gap/PromocionCaTO:setIdPromocionCA	(I)V
/*     */     //   180: aload 6
/*     */     //   182: aload_1
/*     */     //   183: invokevirtual 250	com/claro/transfer/gap/InfoPromocionGapTO:getIdPromocion	()Ljava/lang/String;
/*     */     //   186: invokevirtual 105	java/lang/String:trim	()Ljava/lang/String;
/*     */     //   189: invokestatic 255	java/lang/Integer:parseInt	(Ljava/lang/String;)I
/*     */     //   192: invokevirtual 285	com/claro/transfer/gap/PromocionCaTO:setIdPromocion	(I)V
/*     */     //   195: aload 6
/*     */     //   197: aload 5
/*     */     //   199: ldc_w 288
/*     */     //   202: invokeinterface 279 2 0
/*     */     //   207: invokevirtual 290	com/claro/transfer/gap/PromocionCaTO:setVersionPromocion	(I)V
/*     */     //   210: aload 6
/*     */     //   212: aload 5
/*     */     //   214: ldc_w 293
/*     */     //   217: invokeinterface 295 2 0
/*     */     //   222: ifnull +16 -> 238
/*     */     //   225: aload 5
/*     */     //   227: ldc_w 293
/*     */     //   230: invokeinterface 295 2 0
/*     */     //   235: goto +5 -> 240
/*     */     //   238: ldc 83
/*     */     //   240: invokevirtual 298	com/claro/transfer/gap/PromocionCaTO:setModelo	(Ljava/lang/String;)V
/*     */     //   243: aload 6
/*     */     //   245: aload 5
/*     */     //   247: ldc_w 301
/*     */     //   250: invokeinterface 295 2 0
/*     */     //   255: ifnull +16 -> 271
/*     */     //   258: aload 5
/*     */     //   260: ldc_w 301
/*     */     //   263: invokeinterface 295 2 0
/*     */     //   268: goto +5 -> 273
/*     */     //   271: ldc 83
/*     */     //   273: invokevirtual 303	com/claro/transfer/gap/PromocionCaTO:setMarca	(Ljava/lang/String;)V
/*     */     //   276: aload 6
/*     */     //   278: aload 5
/*     */     //   280: ldc_w 306
/*     */     //   283: invokeinterface 279 2 0
/*     */     //   288: invokevirtual 308	com/claro/transfer/gap/PromocionCaTO:setIdGrupoPlanNuevo	(I)V
/*     */     //   291: aload 6
/*     */     //   293: aload 5
/*     */     //   295: ldc_w 311
/*     */     //   298: invokeinterface 279 2 0
/*     */     //   303: invokevirtual 313	com/claro/transfer/gap/PromocionCaTO:setIdGrupoPlanAnterior	(I)V
/*     */     //   306: aload 6
/*     */     //   308: aload 5
/*     */     //   310: ldc_w 316
/*     */     //   313: invokeinterface 279 2 0
/*     */     //   318: invokevirtual 318	com/claro/transfer/gap/PromocionCaTO:setPlazoFzoNuevo	(I)V
/*     */     //   321: aload 6
/*     */     //   323: aload 5
/*     */     //   325: ldc_w 321
/*     */     //   328: invokeinterface 279 2 0
/*     */     //   333: invokevirtual 323	com/claro/transfer/gap/PromocionCaTO:setPlazoFzoAnterior	(I)V
/*     */     //   336: aload 6
/*     */     //   338: aload 5
/*     */     //   340: ldc_w 326
/*     */     //   343: invokeinterface 295 2 0
/*     */     //   348: ifnull +16 -> 364
/*     */     //   351: aload 5
/*     */     //   353: ldc_w 326
/*     */     //   356: invokeinterface 295 2 0
/*     */     //   361: goto +5 -> 366
/*     */     //   364: ldc 83
/*     */     //   366: invokevirtual 328	com/claro/transfer/gap/PromocionCaTO:setBonoDescuento	(Ljava/lang/String;)V
/*     */     //   369: aload 6
/*     */     //   371: aload 5
/*     */     //   373: ldc_w 331
/*     */     //   376: invokeinterface 295 2 0
/*     */     //   381: ifnull +16 -> 397
/*     */     //   384: aload 5
/*     */     //   386: ldc_w 331
/*     */     //   389: invokeinterface 295 2 0
/*     */     //   394: goto +5 -> 399
/*     */     //   397: ldc 83
/*     */     //   399: invokevirtual 333	com/claro/transfer/gap/PromocionCaTO:setProductoM2K	(Ljava/lang/String;)V
/*     */     //   402: aload 6
/*     */     //   404: aload 5
/*     */     //   406: ldc_w 336
/*     */     //   409: invokeinterface 183 2 0
/*     */     //   414: invokevirtual 338	com/claro/transfer/gap/PromocionCaTO:setCantidadDescuento	(Ljava/math/BigDecimal;)V
/*     */     //   417: aload 6
/*     */     //   419: aload 5
/*     */     //   421: ldc_w 342
/*     */     //   424: invokeinterface 279 2 0
/*     */     //   429: invokevirtual 344	com/claro/transfer/gap/PromocionCaTO:setModoSuscripcionNuevo	(I)V
/*     */     //   432: aload 6
/*     */     //   434: aload 5
/*     */     //   436: ldc_w 347
/*     */     //   439: invokeinterface 279 2 0
/*     */     //   444: invokevirtual 349	com/claro/transfer/gap/PromocionCaTO:setModoSuscripcionAnterior	(I)V
/*     */     //   447: goto +129 -> 576
/*     */     //   450: astore 7
/*     */     //   452: new 78	com/claro/exception/CAException
/*     */     //   455: dup
/*     */     //   456: iconst_m1
/*     */     //   457: new 44	java/lang/StringBuilder
/*     */     //   460: dup
/*     */     //   461: ldc_w 352
/*     */     //   464: invokespecial 48	java/lang/StringBuilder:<init>	(Ljava/lang/String;)V
/*     */     //   467: aload 7
/*     */     //   469: invokevirtual 199	java/sql/SQLException:toString	()Ljava/lang/String;
/*     */     //   472: invokevirtual 57	java/lang/StringBuilder:append	(Ljava/lang/String;)Ljava/lang/StringBuilder;
/*     */     //   475: ldc -54
/*     */     //   477: invokevirtual 57	java/lang/StringBuilder:append	(Ljava/lang/String;)Ljava/lang/StringBuilder;
/*     */     //   480: invokevirtual 61	java/lang/StringBuilder:toString	()Ljava/lang/String;
/*     */     //   483: invokespecial 204	com/claro/exception/CAException:<init>	(ILjava/lang/String;)V
/*     */     //   486: athrow
/*     */     //   487: astore 7
/*     */     //   489: new 78	com/claro/exception/CAException
/*     */     //   492: dup
/*     */     //   493: iconst_m1
/*     */     //   494: new 44	java/lang/StringBuilder
/*     */     //   497: dup
/*     */     //   498: ldc_w 352
/*     */     //   501: invokespecial 48	java/lang/StringBuilder:<init>	(Ljava/lang/String;)V
/*     */     //   504: aload 7
/*     */     //   506: invokevirtual 51	java/lang/Exception:toString	()Ljava/lang/String;
/*     */     //   509: invokevirtual 57	java/lang/StringBuilder:append	(Ljava/lang/String;)Ljava/lang/StringBuilder;
/*     */     //   512: ldc -54
/*     */     //   514: invokevirtual 57	java/lang/StringBuilder:append	(Ljava/lang/String;)Ljava/lang/StringBuilder;
/*     */     //   517: invokevirtual 61	java/lang/StringBuilder:toString	()Ljava/lang/String;
/*     */     //   520: invokespecial 204	com/claro/exception/CAException:<init>	(ILjava/lang/String;)V
/*     */     //   523: athrow
/*     */     //   524: astore 8
/*     */     //   526: aload_3
/*     */     //   527: ifnull +11 -> 538
/*     */     //   530: aload_3
/*     */     //   531: invokeinterface 112 1 0
/*     */     //   536: aconst_null
/*     */     //   537: astore_3
/*     */     //   538: aload 4
/*     */     //   540: ifnull +13 -> 553
/*     */     //   543: aload 4
/*     */     //   545: invokeinterface 354 1 0
/*     */     //   550: aconst_null
/*     */     //   551: astore 4
/*     */     //   553: aload 5
/*     */     //   555: ifnull +18 -> 573
/*     */     //   558: aload 5
/*     */     //   560: invokeinterface 120 1 0
/*     */     //   565: aconst_null
/*     */     //   566: astore 5
/*     */     //   568: goto +5 -> 573
/*     */     //   571: astore 9
/*     */     //   573: aload 8
/*     */     //   575: athrow
/*     */     //   576: aload_3
/*     */     //   577: ifnull +11 -> 588
/*     */     //   580: aload_3
/*     */     //   581: invokeinterface 112 1 0
/*     */     //   586: aconst_null
/*     */     //   587: astore_3
/*     */     //   588: aload 4
/*     */     //   590: ifnull +13 -> 603
/*     */     //   593: aload 4
/*     */     //   595: invokeinterface 354 1 0
/*     */     //   600: aconst_null
/*     */     //   601: astore 4
/*     */     //   603: aload 5
/*     */     //   605: ifnull +18 -> 623
/*     */     //   608: aload 5
/*     */     //   610: invokeinterface 120 1 0
/*     */     //   615: aconst_null
/*     */     //   616: astore 5
/*     */     //   618: goto +5 -> 623
/*     */     //   621: astore 9
/*     */     //   623: aload 6
/*     */     //   625: areturn
/*     */     // Line number table:
/*     */     //   Java source line #118	-> byte code offset #0
/*     */     //   Java source line #119	-> byte code offset #8
/*     */     //   Java source line #120	-> byte code offset #10
/*     */     //   Java source line #121	-> byte code offset #13
/*     */     //   Java source line #122	-> byte code offset #16
/*     */     //   Java source line #124	-> byte code offset #19
/*     */     //   Java source line #125	-> byte code offset #26
/*     */     //   Java source line #126	-> byte code offset #33
/*     */     //   Java source line #127	-> byte code offset #40
/*     */     //   Java source line #128	-> byte code offset #47
/*     */     //   Java source line #129	-> byte code offset #66
/*     */     //   Java source line #132	-> byte code offset #73
/*     */     //   Java source line #133	-> byte code offset #83
/*     */     //   Java source line #134	-> byte code offset #95
/*     */     //   Java source line #135	-> byte code offset #113
/*     */     //   Java source line #136	-> byte code offset #128
/*     */     //   Java source line #137	-> byte code offset #137
/*     */     //   Java source line #138	-> byte code offset #146
/*     */     //   Java source line #139	-> byte code offset #156
/*     */     //   Java source line #140	-> byte code offset #165
/*     */     //   Java source line #141	-> byte code offset #180
/*     */     //   Java source line #142	-> byte code offset #195
/*     */     //   Java source line #143	-> byte code offset #210
/*     */     //   Java source line #144	-> byte code offset #243
/*     */     //   Java source line #145	-> byte code offset #276
/*     */     //   Java source line #146	-> byte code offset #291
/*     */     //   Java source line #147	-> byte code offset #306
/*     */     //   Java source line #148	-> byte code offset #321
/*     */     //   Java source line #149	-> byte code offset #336
/*     */     //   Java source line #150	-> byte code offset #369
/*     */     //   Java source line #154	-> byte code offset #402
/*     */     //   Java source line #155	-> byte code offset #417
/*     */     //   Java source line #156	-> byte code offset #432
/*     */     //   Java source line #159	-> byte code offset #450
/*     */     //   Java source line #160	-> byte code offset #452
/*     */     //   Java source line #161	-> byte code offset #487
/*     */     //   Java source line #162	-> byte code offset #489
/*     */     //   Java source line #163	-> byte code offset #524
/*     */     //   Java source line #165	-> byte code offset #526
/*     */     //   Java source line #166	-> byte code offset #538
/*     */     //   Java source line #167	-> byte code offset #553
/*     */     //   Java source line #168	-> byte code offset #571
/*     */     //   Java source line #169	-> byte code offset #573
/*     */     //   Java source line #165	-> byte code offset #576
/*     */     //   Java source line #166	-> byte code offset #588
/*     */     //   Java source line #167	-> byte code offset #603
/*     */     //   Java source line #168	-> byte code offset #621
/*     */     //   Java source line #170	-> byte code offset #623
/*     */     // Local variable table:
/*     */     //   start	length	slot	name	signature
/*     */     //   0	626	0	this	ConsultasGapDAO
/*     */     //   0	626	1	infoPromocionGapTO	com.claro.transfer.gap.InfoPromocionGapTO
/*     */     //   7	78	2	stringBuffer	StringBuffer
/*     */     //   9	579	3	connection	Connection
/*     */     //   11	591	4	preparedStatement	java.sql.PreparedStatement
/*     */     //   14	603	5	resultSet	ResultSet
/*     */     //   17	607	6	gapCaTO	com.claro.transfer.gap.PromocionCaTO
/*     */     //   450	18	7	e	SQLException
/*     */     //   487	18	7	e	Exception
/*     */     //   524	50	8	localObject	Object
/*     */     //   571	1	9	localSQLException1	SQLException
/*     */     //   621	1	9	localSQLException2	SQLException
/*     */     // Exception table:
/*     */     //   from	to	target	type
/*     */     //   73	447	450	java/sql/SQLException
/*     */     //   73	447	487	java/lang/Exception
/*     */     //   73	524	524	finally
/*     */     //   526	568	571	java/sql/SQLException
/*     */     //   576	618	621	java/sql/SQLException
/*     */   }
/*     */   
/*     */   /* Error */
/*     */   public java.util.List<String> getPlanesByIdGrupoPlan(int idGrupoPlan, int idModoSubscripcion, int idRegion)
/*     */     throws CAException
/*     */   {
/*     */     // Byte code:
/*     */     //   0: aconst_null
/*     */     //   1: astore 4
/*     */     //   3: new 80	java/lang/StringBuffer
/*     */     //   6: dup
/*     */     //   7: invokespecial 82	java/lang/StringBuffer:<init>	()V
/*     */     //   10: astore 5
/*     */     //   12: aconst_null
/*     */     //   13: astore 6
/*     */     //   15: aconst_null
/*     */     //   16: astore 7
/*     */     //   18: aconst_null
/*     */     //   19: astore 8
/*     */     //   21: aload 5
/*     */     //   23: ldc_w 365
/*     */     //   26: invokevirtual 125	java/lang/StringBuffer:append	(Ljava/lang/String;)Ljava/lang/StringBuffer;
/*     */     //   29: pop
/*     */     //   30: aload 5
/*     */     //   32: ldc -16
/*     */     //   34: invokevirtual 125	java/lang/StringBuffer:append	(Ljava/lang/String;)Ljava/lang/StringBuffer;
/*     */     //   37: aload_0
/*     */     //   38: getfield 29	com/claro/dao/ConsultasGapDAO:schemaGap	Ljava/lang/String;
/*     */     //   41: invokevirtual 125	java/lang/StringBuffer:append	(Ljava/lang/String;)Ljava/lang/StringBuffer;
/*     */     //   44: ldc_w 367
/*     */     //   47: invokevirtual 125	java/lang/StringBuffer:append	(Ljava/lang/String;)Ljava/lang/StringBuffer;
/*     */     //   50: aload_0
/*     */     //   51: getfield 29	com/claro/dao/ConsultasGapDAO:schemaGap	Ljava/lang/String;
/*     */     //   54: invokevirtual 125	java/lang/StringBuffer:append	(Ljava/lang/String;)Ljava/lang/StringBuffer;
/*     */     //   57: ldc_w 369
/*     */     //   60: invokevirtual 125	java/lang/StringBuffer:append	(Ljava/lang/String;)Ljava/lang/StringBuffer;
/*     */     //   63: pop
/*     */     //   64: aload 5
/*     */     //   66: ldc_w 371
/*     */     //   69: invokevirtual 125	java/lang/StringBuffer:append	(Ljava/lang/String;)Ljava/lang/StringBuffer;
/*     */     //   72: pop
/*     */     //   73: aload 5
/*     */     //   75: ldc_w 373
/*     */     //   78: invokevirtual 125	java/lang/StringBuffer:append	(Ljava/lang/String;)Ljava/lang/StringBuffer;
/*     */     //   81: pop
/*     */     //   82: aload 5
/*     */     //   84: ldc_w 375
/*     */     //   87: invokevirtual 125	java/lang/StringBuffer:append	(Ljava/lang/String;)Ljava/lang/StringBuffer;
/*     */     //   90: pop
/*     */     //   91: aload 5
/*     */     //   93: ldc_w 377
/*     */     //   96: invokevirtual 125	java/lang/StringBuffer:append	(Ljava/lang/String;)Ljava/lang/StringBuffer;
/*     */     //   99: pop
/*     */     //   100: invokestatic 31	com/claro/util/ServiceLocator:getInstance	()Lcom/claro/util/ServiceLocator;
/*     */     //   103: getstatic 158	com/claro/util/ServiceLocator:jdbcGap	Ljava/lang/String;
/*     */     //   106: invokevirtual 161	com/claro/util/ServiceLocator:getConnection	(Ljava/lang/String;)Ljava/sql/Connection;
/*     */     //   109: astore 6
/*     */     //   111: aload 6
/*     */     //   113: aload 5
/*     */     //   115: invokevirtual 155	java/lang/StringBuffer:toString	()Ljava/lang/String;
/*     */     //   118: invokeinterface 246 2 0
/*     */     //   123: astore 7
/*     */     //   125: aload 7
/*     */     //   127: iconst_1
/*     */     //   128: iload_1
/*     */     //   129: invokeinterface 261 3 0
/*     */     //   134: aload 7
/*     */     //   136: iconst_2
/*     */     //   137: iload_2
/*     */     //   138: invokeinterface 261 3 0
/*     */     //   143: aload 7
/*     */     //   145: iconst_3
/*     */     //   146: iload_3
/*     */     //   147: invokeinterface 261 3 0
/*     */     //   152: aload 7
/*     */     //   154: bipush 15
/*     */     //   156: invokeinterface 270 2 0
/*     */     //   161: aload 7
/*     */     //   163: invokeinterface 271 1 0
/*     */     //   168: astore 8
/*     */     //   170: new 379	java/util/ArrayList
/*     */     //   173: dup
/*     */     //   174: invokespecial 381	java/util/ArrayList:<init>	()V
/*     */     //   177: astore 4
/*     */     //   179: goto +24 -> 203
/*     */     //   182: aload 4
/*     */     //   184: aload 8
/*     */     //   186: ldc_w 382
/*     */     //   189: invokeinterface 295 2 0
/*     */     //   194: invokevirtual 105	java/lang/String:trim	()Ljava/lang/String;
/*     */     //   197: invokeinterface 384 2 0
/*     */     //   202: pop
/*     */     //   203: aload 8
/*     */     //   205: invokeinterface 177 1 0
/*     */     //   210: ifne -28 -> 182
/*     */     //   213: goto +132 -> 345
/*     */     //   216: astore 9
/*     */     //   218: new 78	com/claro/exception/CAException
/*     */     //   221: dup
/*     */     //   222: iconst_m1
/*     */     //   223: new 44	java/lang/StringBuilder
/*     */     //   226: dup
/*     */     //   227: ldc_w 389
/*     */     //   230: invokespecial 48	java/lang/StringBuilder:<init>	(Ljava/lang/String;)V
/*     */     //   233: aload 9
/*     */     //   235: invokevirtual 199	java/sql/SQLException:toString	()Ljava/lang/String;
/*     */     //   238: invokevirtual 57	java/lang/StringBuilder:append	(Ljava/lang/String;)Ljava/lang/StringBuilder;
/*     */     //   241: ldc -54
/*     */     //   243: invokevirtual 57	java/lang/StringBuilder:append	(Ljava/lang/String;)Ljava/lang/StringBuilder;
/*     */     //   246: invokevirtual 61	java/lang/StringBuilder:toString	()Ljava/lang/String;
/*     */     //   249: invokespecial 204	com/claro/exception/CAException:<init>	(ILjava/lang/String;)V
/*     */     //   252: athrow
/*     */     //   253: astore 9
/*     */     //   255: new 78	com/claro/exception/CAException
/*     */     //   258: dup
/*     */     //   259: iconst_m1
/*     */     //   260: new 44	java/lang/StringBuilder
/*     */     //   263: dup
/*     */     //   264: ldc_w 389
/*     */     //   267: invokespecial 48	java/lang/StringBuilder:<init>	(Ljava/lang/String;)V
/*     */     //   270: aload 9
/*     */     //   272: invokevirtual 51	java/lang/Exception:toString	()Ljava/lang/String;
/*     */     //   275: invokevirtual 57	java/lang/StringBuilder:append	(Ljava/lang/String;)Ljava/lang/StringBuilder;
/*     */     //   278: ldc -54
/*     */     //   280: invokevirtual 57	java/lang/StringBuilder:append	(Ljava/lang/String;)Ljava/lang/StringBuilder;
/*     */     //   283: invokevirtual 61	java/lang/StringBuilder:toString	()Ljava/lang/String;
/*     */     //   286: invokespecial 204	com/claro/exception/CAException:<init>	(ILjava/lang/String;)V
/*     */     //   289: athrow
/*     */     //   290: astore 10
/*     */     //   292: aload 6
/*     */     //   294: ifnull +13 -> 307
/*     */     //   297: aload 6
/*     */     //   299: invokeinterface 112 1 0
/*     */     //   304: aconst_null
/*     */     //   305: astore 6
/*     */     //   307: aload 7
/*     */     //   309: ifnull +13 -> 322
/*     */     //   312: aload 7
/*     */     //   314: invokeinterface 354 1 0
/*     */     //   319: aconst_null
/*     */     //   320: astore 7
/*     */     //   322: aload 8
/*     */     //   324: ifnull +18 -> 342
/*     */     //   327: aload 8
/*     */     //   329: invokeinterface 120 1 0
/*     */     //   334: aconst_null
/*     */     //   335: astore 8
/*     */     //   337: goto +5 -> 342
/*     */     //   340: astore 11
/*     */     //   342: aload 10
/*     */     //   344: athrow
/*     */     //   345: aload 6
/*     */     //   347: ifnull +13 -> 360
/*     */     //   350: aload 6
/*     */     //   352: invokeinterface 112 1 0
/*     */     //   357: aconst_null
/*     */     //   358: astore 6
/*     */     //   360: aload 7
/*     */     //   362: ifnull +13 -> 375
/*     */     //   365: aload 7
/*     */     //   367: invokeinterface 354 1 0
/*     */     //   372: aconst_null
/*     */     //   373: astore 7
/*     */     //   375: aload 8
/*     */     //   377: ifnull +18 -> 395
/*     */     //   380: aload 8
/*     */     //   382: invokeinterface 120 1 0
/*     */     //   387: aconst_null
/*     */     //   388: astore 8
/*     */     //   390: goto +5 -> 395
/*     */     //   393: astore 11
/*     */     //   395: aload 4
/*     */     //   397: areturn
/*     */     // Line number table:
/*     */     //   Java source line #180	-> byte code offset #0
/*     */     //   Java source line #181	-> byte code offset #3
/*     */     //   Java source line #182	-> byte code offset #12
/*     */     //   Java source line #183	-> byte code offset #15
/*     */     //   Java source line #184	-> byte code offset #18
/*     */     //   Java source line #186	-> byte code offset #21
/*     */     //   Java source line #187	-> byte code offset #30
/*     */     //   Java source line #188	-> byte code offset #64
/*     */     //   Java source line #189	-> byte code offset #73
/*     */     //   Java source line #190	-> byte code offset #82
/*     */     //   Java source line #191	-> byte code offset #91
/*     */     //   Java source line #194	-> byte code offset #100
/*     */     //   Java source line #195	-> byte code offset #111
/*     */     //   Java source line #196	-> byte code offset #125
/*     */     //   Java source line #197	-> byte code offset #134
/*     */     //   Java source line #198	-> byte code offset #143
/*     */     //   Java source line #199	-> byte code offset #152
/*     */     //   Java source line #200	-> byte code offset #161
/*     */     //   Java source line #201	-> byte code offset #170
/*     */     //   Java source line #202	-> byte code offset #179
/*     */     //   Java source line #203	-> byte code offset #182
/*     */     //   Java source line #202	-> byte code offset #203
/*     */     //   Java source line #205	-> byte code offset #216
/*     */     //   Java source line #206	-> byte code offset #218
/*     */     //   Java source line #207	-> byte code offset #253
/*     */     //   Java source line #208	-> byte code offset #255
/*     */     //   Java source line #209	-> byte code offset #290
/*     */     //   Java source line #211	-> byte code offset #292
/*     */     //   Java source line #212	-> byte code offset #307
/*     */     //   Java source line #213	-> byte code offset #322
/*     */     //   Java source line #214	-> byte code offset #340
/*     */     //   Java source line #215	-> byte code offset #342
/*     */     //   Java source line #211	-> byte code offset #345
/*     */     //   Java source line #212	-> byte code offset #360
/*     */     //   Java source line #213	-> byte code offset #375
/*     */     //   Java source line #214	-> byte code offset #393
/*     */     //   Java source line #216	-> byte code offset #395
/*     */     // Local variable table:
/*     */     //   start	length	slot	name	signature
/*     */     //   0	398	0	this	ConsultasGapDAO
/*     */     //   0	398	1	idGrupoPlan	int
/*     */     //   0	398	2	idModoSubscripcion	int
/*     */     //   0	398	3	idRegion	int
/*     */     //   1	395	4	planesList	java.util.List<String>
/*     */     //   10	104	5	stringBuffer	StringBuffer
/*     */     //   13	346	6	connection	Connection
/*     */     //   16	358	7	preparedStatement	java.sql.PreparedStatement
/*     */     //   19	370	8	resultSet	ResultSet
/*     */     //   216	18	9	e	SQLException
/*     */     //   253	18	9	e	Exception
/*     */     //   290	53	10	localObject	Object
/*     */     //   340	1	11	localSQLException1	SQLException
/*     */     //   393	1	11	localSQLException2	SQLException
/*     */     // Exception table:
/*     */     //   from	to	target	type
/*     */     //   100	213	216	java/sql/SQLException
/*     */     //   100	213	253	java/lang/Exception
/*     */     //   100	290	290	finally
/*     */     //   292	337	340	java/sql/SQLException
/*     */     //   345	390	393	java/sql/SQLException
/*     */   }
/*     */   
/*     */   /* Error */
/*     */   public int validaPromocionOfrecida(int idPromocionGap, String telefono, int versionPromoGap)
/*     */     throws Exception
/*     */   {
/*     */     // Byte code:
/*     */     //   0: iconst_0
/*     */     //   1: istore 4
/*     */     //   3: new 80	java/lang/StringBuffer
/*     */     //   6: dup
/*     */     //   7: invokespecial 82	java/lang/StringBuffer:<init>	()V
/*     */     //   10: astore 5
/*     */     //   12: aconst_null
/*     */     //   13: astore 6
/*     */     //   15: aconst_null
/*     */     //   16: astore 7
/*     */     //   18: aconst_null
/*     */     //   19: astore 8
/*     */     //   21: aload 5
/*     */     //   23: ldc_w 401
/*     */     //   26: invokevirtual 125	java/lang/StringBuffer:append	(Ljava/lang/String;)Ljava/lang/StringBuffer;
/*     */     //   29: aload_0
/*     */     //   30: getfield 29	com/claro/dao/ConsultasGapDAO:schemaGap	Ljava/lang/String;
/*     */     //   33: invokevirtual 125	java/lang/StringBuffer:append	(Ljava/lang/String;)Ljava/lang/StringBuffer;
/*     */     //   36: ldc_w 403
/*     */     //   39: invokevirtual 125	java/lang/StringBuffer:append	(Ljava/lang/String;)Ljava/lang/StringBuffer;
/*     */     //   42: pop
/*     */     //   43: aload 5
/*     */     //   45: ldc_w 405
/*     */     //   48: invokevirtual 125	java/lang/StringBuffer:append	(Ljava/lang/String;)Ljava/lang/StringBuffer;
/*     */     //   51: pop
/*     */     //   52: invokestatic 31	com/claro/util/ServiceLocator:getInstance	()Lcom/claro/util/ServiceLocator;
/*     */     //   55: getstatic 158	com/claro/util/ServiceLocator:jdbcGap	Ljava/lang/String;
/*     */     //   58: invokevirtual 161	com/claro/util/ServiceLocator:getConnection	(Ljava/lang/String;)Ljava/sql/Connection;
/*     */     //   61: astore 6
/*     */     //   63: aload 6
/*     */     //   65: aload 5
/*     */     //   67: invokevirtual 155	java/lang/StringBuffer:toString	()Ljava/lang/String;
/*     */     //   70: invokeinterface 246 2 0
/*     */     //   75: astore 7
/*     */     //   77: aload 7
/*     */     //   79: iconst_1
/*     */     //   80: iload_1
/*     */     //   81: invokeinterface 261 3 0
/*     */     //   86: aload 7
/*     */     //   88: iconst_2
/*     */     //   89: new 407	java/lang/Long
/*     */     //   92: dup
/*     */     //   93: aload_2
/*     */     //   94: invokevirtual 105	java/lang/String:trim	()Ljava/lang/String;
/*     */     //   97: invokespecial 409	java/lang/Long:<init>	(Ljava/lang/String;)V
/*     */     //   100: invokevirtual 410	java/lang/Long:longValue	()J
/*     */     //   103: invokeinterface 414 4 0
/*     */     //   108: aload 7
/*     */     //   110: iconst_3
/*     */     //   111: iload_3
/*     */     //   112: invokeinterface 261 3 0
/*     */     //   117: aload 7
/*     */     //   119: bipush 15
/*     */     //   121: invokeinterface 270 2 0
/*     */     //   126: aload 7
/*     */     //   128: invokeinterface 271 1 0
/*     */     //   133: astore 8
/*     */     //   135: aload 8
/*     */     //   137: invokeinterface 177 1 0
/*     */     //   142: ifeq +147 -> 289
/*     */     //   145: aload 8
/*     */     //   147: ldc_w 418
/*     */     //   150: invokeinterface 279 2 0
/*     */     //   155: istore 4
/*     */     //   157: goto +132 -> 289
/*     */     //   160: astore 9
/*     */     //   162: new 78	com/claro/exception/CAException
/*     */     //   165: dup
/*     */     //   166: iconst_m1
/*     */     //   167: new 44	java/lang/StringBuilder
/*     */     //   170: dup
/*     */     //   171: ldc_w 420
/*     */     //   174: invokespecial 48	java/lang/StringBuilder:<init>	(Ljava/lang/String;)V
/*     */     //   177: aload 9
/*     */     //   179: invokevirtual 199	java/sql/SQLException:toString	()Ljava/lang/String;
/*     */     //   182: invokevirtual 57	java/lang/StringBuilder:append	(Ljava/lang/String;)Ljava/lang/StringBuilder;
/*     */     //   185: ldc -54
/*     */     //   187: invokevirtual 57	java/lang/StringBuilder:append	(Ljava/lang/String;)Ljava/lang/StringBuilder;
/*     */     //   190: invokevirtual 61	java/lang/StringBuilder:toString	()Ljava/lang/String;
/*     */     //   193: invokespecial 204	com/claro/exception/CAException:<init>	(ILjava/lang/String;)V
/*     */     //   196: athrow
/*     */     //   197: astore 9
/*     */     //   199: new 78	com/claro/exception/CAException
/*     */     //   202: dup
/*     */     //   203: iconst_m1
/*     */     //   204: new 44	java/lang/StringBuilder
/*     */     //   207: dup
/*     */     //   208: ldc_w 420
/*     */     //   211: invokespecial 48	java/lang/StringBuilder:<init>	(Ljava/lang/String;)V
/*     */     //   214: aload 9
/*     */     //   216: invokevirtual 51	java/lang/Exception:toString	()Ljava/lang/String;
/*     */     //   219: invokevirtual 57	java/lang/StringBuilder:append	(Ljava/lang/String;)Ljava/lang/StringBuilder;
/*     */     //   222: ldc -54
/*     */     //   224: invokevirtual 57	java/lang/StringBuilder:append	(Ljava/lang/String;)Ljava/lang/StringBuilder;
/*     */     //   227: invokevirtual 61	java/lang/StringBuilder:toString	()Ljava/lang/String;
/*     */     //   230: invokespecial 204	com/claro/exception/CAException:<init>	(ILjava/lang/String;)V
/*     */     //   233: athrow
/*     */     //   234: astore 10
/*     */     //   236: aload 6
/*     */     //   238: ifnull +13 -> 251
/*     */     //   241: aload 6
/*     */     //   243: invokeinterface 112 1 0
/*     */     //   248: aconst_null
/*     */     //   249: astore 6
/*     */     //   251: aload 7
/*     */     //   253: ifnull +13 -> 266
/*     */     //   256: aload 7
/*     */     //   258: invokeinterface 354 1 0
/*     */     //   263: aconst_null
/*     */     //   264: astore 7
/*     */     //   266: aload 8
/*     */     //   268: ifnull +18 -> 286
/*     */     //   271: aload 8
/*     */     //   273: invokeinterface 120 1 0
/*     */     //   278: aconst_null
/*     */     //   279: astore 8
/*     */     //   281: goto +5 -> 286
/*     */     //   284: astore 11
/*     */     //   286: aload 10
/*     */     //   288: athrow
/*     */     //   289: aload 6
/*     */     //   291: ifnull +13 -> 304
/*     */     //   294: aload 6
/*     */     //   296: invokeinterface 112 1 0
/*     */     //   301: aconst_null
/*     */     //   302: astore 6
/*     */     //   304: aload 7
/*     */     //   306: ifnull +13 -> 319
/*     */     //   309: aload 7
/*     */     //   311: invokeinterface 354 1 0
/*     */     //   316: aconst_null
/*     */     //   317: astore 7
/*     */     //   319: aload 8
/*     */     //   321: ifnull +18 -> 339
/*     */     //   324: aload 8
/*     */     //   326: invokeinterface 120 1 0
/*     */     //   331: aconst_null
/*     */     //   332: astore 8
/*     */     //   334: goto +5 -> 339
/*     */     //   337: astore 11
/*     */     //   339: iload 4
/*     */     //   341: ireturn
/*     */     // Line number table:
/*     */     //   Java source line #227	-> byte code offset #0
/*     */     //   Java source line #228	-> byte code offset #3
/*     */     //   Java source line #229	-> byte code offset #12
/*     */     //   Java source line #230	-> byte code offset #15
/*     */     //   Java source line #231	-> byte code offset #18
/*     */     //   Java source line #232	-> byte code offset #21
/*     */     //   Java source line #233	-> byte code offset #43
/*     */     //   Java source line #235	-> byte code offset #52
/*     */     //   Java source line #236	-> byte code offset #63
/*     */     //   Java source line #237	-> byte code offset #77
/*     */     //   Java source line #238	-> byte code offset #86
/*     */     //   Java source line #239	-> byte code offset #108
/*     */     //   Java source line #240	-> byte code offset #117
/*     */     //   Java source line #241	-> byte code offset #126
/*     */     //   Java source line #242	-> byte code offset #135
/*     */     //   Java source line #243	-> byte code offset #145
/*     */     //   Java source line #245	-> byte code offset #160
/*     */     //   Java source line #246	-> byte code offset #162
/*     */     //   Java source line #247	-> byte code offset #197
/*     */     //   Java source line #248	-> byte code offset #199
/*     */     //   Java source line #249	-> byte code offset #234
/*     */     //   Java source line #251	-> byte code offset #236
/*     */     //   Java source line #252	-> byte code offset #251
/*     */     //   Java source line #253	-> byte code offset #266
/*     */     //   Java source line #254	-> byte code offset #284
/*     */     //   Java source line #255	-> byte code offset #286
/*     */     //   Java source line #251	-> byte code offset #289
/*     */     //   Java source line #252	-> byte code offset #304
/*     */     //   Java source line #253	-> byte code offset #319
/*     */     //   Java source line #254	-> byte code offset #337
/*     */     //   Java source line #256	-> byte code offset #339
/*     */     // Local variable table:
/*     */     //   start	length	slot	name	signature
/*     */     //   0	342	0	this	ConsultasGapDAO
/*     */     //   0	342	1	idPromocionGap	int
/*     */     //   0	342	2	telefono	String
/*     */     //   0	342	3	versionPromoGap	int
/*     */     //   1	339	4	status	int
/*     */     //   10	56	5	stringBuffer	StringBuffer
/*     */     //   13	290	6	connection	Connection
/*     */     //   16	302	7	preparedStatement	java.sql.PreparedStatement
/*     */     //   19	314	8	resultSet	ResultSet
/*     */     //   160	18	9	e	SQLException
/*     */     //   197	18	9	e	Exception
/*     */     //   234	53	10	localObject	Object
/*     */     //   284	1	11	localSQLException1	SQLException
/*     */     //   337	1	11	localSQLException2	SQLException
/*     */     // Exception table:
/*     */     //   from	to	target	type
/*     */     //   52	157	160	java/sql/SQLException
/*     */     //   52	157	197	java/lang/Exception
/*     */     //   52	234	234	finally
/*     */     //   236	281	284	java/sql/SQLException
/*     */     //   289	334	337	java/sql/SQLException
/*     */   }
/*     */   
/*     */   /* Error */
/*     */   public com.claro.transfer.MensajeTO insertaPromocionOfrecida(int idPromocionGap, int versionPromoGap, String telefono, long fechaTransaccion, String msg)
/*     */     throws Exception
/*     */   {
/*     */     // Byte code:
/*     */     //   0: new 80	java/lang/StringBuffer
/*     */     //   3: dup
/*     */     //   4: invokespecial 82	java/lang/StringBuffer:<init>	()V
/*     */     //   7: astore 7
/*     */     //   9: aconst_null
/*     */     //   10: astore 8
/*     */     //   12: aconst_null
/*     */     //   13: astore 9
/*     */     //   15: aconst_null
/*     */     //   16: astore 10
/*     */     //   18: new 428	com/claro/transfer/MensajeTO
/*     */     //   21: dup
/*     */     //   22: invokespecial 430	com/claro/transfer/MensajeTO:<init>	()V
/*     */     //   25: astore 11
/*     */     //   27: aload 7
/*     */     //   29: ldc_w 431
/*     */     //   32: invokevirtual 125	java/lang/StringBuffer:append	(Ljava/lang/String;)Ljava/lang/StringBuffer;
/*     */     //   35: aload_0
/*     */     //   36: getfield 29	com/claro/dao/ConsultasGapDAO:schemaGap	Ljava/lang/String;
/*     */     //   39: invokevirtual 125	java/lang/StringBuffer:append	(Ljava/lang/String;)Ljava/lang/StringBuffer;
/*     */     //   42: ldc_w 403
/*     */     //   45: invokevirtual 125	java/lang/StringBuffer:append	(Ljava/lang/String;)Ljava/lang/StringBuffer;
/*     */     //   48: pop
/*     */     //   49: aload 7
/*     */     //   51: ldc_w 433
/*     */     //   54: invokevirtual 125	java/lang/StringBuffer:append	(Ljava/lang/String;)Ljava/lang/StringBuffer;
/*     */     //   57: pop
/*     */     //   58: aload 7
/*     */     //   60: ldc_w 435
/*     */     //   63: invokevirtual 125	java/lang/StringBuffer:append	(Ljava/lang/String;)Ljava/lang/StringBuffer;
/*     */     //   66: pop
/*     */     //   67: invokestatic 31	com/claro/util/ServiceLocator:getInstance	()Lcom/claro/util/ServiceLocator;
/*     */     //   70: getstatic 158	com/claro/util/ServiceLocator:jdbcGap	Ljava/lang/String;
/*     */     //   73: invokevirtual 161	com/claro/util/ServiceLocator:getConnection	(Ljava/lang/String;)Ljava/sql/Connection;
/*     */     //   76: astore 8
/*     */     //   78: aload 8
/*     */     //   80: iconst_0
/*     */     //   81: invokeinterface 437 2 0
/*     */     //   86: aload 8
/*     */     //   88: aload 7
/*     */     //   90: invokevirtual 155	java/lang/StringBuffer:toString	()Ljava/lang/String;
/*     */     //   93: invokeinterface 246 2 0
/*     */     //   98: astore 9
/*     */     //   100: aload 9
/*     */     //   102: iconst_1
/*     */     //   103: iload_1
/*     */     //   104: invokeinterface 261 3 0
/*     */     //   109: aload 9
/*     */     //   111: iconst_2
/*     */     //   112: iload_2
/*     */     //   113: invokeinterface 261 3 0
/*     */     //   118: aload 9
/*     */     //   120: iconst_3
/*     */     //   121: new 407	java/lang/Long
/*     */     //   124: dup
/*     */     //   125: aload_3
/*     */     //   126: invokevirtual 105	java/lang/String:trim	()Ljava/lang/String;
/*     */     //   129: invokespecial 409	java/lang/Long:<init>	(Ljava/lang/String;)V
/*     */     //   132: invokevirtual 410	java/lang/Long:longValue	()J
/*     */     //   135: invokeinterface 414 4 0
/*     */     //   140: aload 9
/*     */     //   142: iconst_4
/*     */     //   143: iconst_1
/*     */     //   144: invokeinterface 261 3 0
/*     */     //   149: aload 9
/*     */     //   151: iconst_5
/*     */     //   152: new 441	java/sql/Date
/*     */     //   155: dup
/*     */     //   156: lload 4
/*     */     //   158: invokespecial 443	java/sql/Date:<init>	(J)V
/*     */     //   161: invokevirtual 446	java/sql/Date:toString	()Ljava/lang/String;
/*     */     //   164: ldc_w 447
/*     */     //   167: ldc 83
/*     */     //   169: invokevirtual 449	java/lang/String:replaceAll	(Ljava/lang/String;Ljava/lang/String;)Ljava/lang/String;
/*     */     //   172: invokestatic 255	java/lang/Integer:parseInt	(Ljava/lang/String;)I
/*     */     //   175: invokeinterface 261 3 0
/*     */     //   180: aload 9
/*     */     //   182: bipush 6
/*     */     //   184: iconst_5
/*     */     //   185: invokeinterface 261 3 0
/*     */     //   190: aload 9
/*     */     //   192: bipush 7
/*     */     //   194: aload 6
/*     */     //   196: invokeinterface 453 3 0
/*     */     //   201: aload 9
/*     */     //   203: bipush 15
/*     */     //   205: invokeinterface 270 2 0
/*     */     //   210: aload 9
/*     */     //   212: invokeinterface 456 1 0
/*     */     //   217: ifle +22 -> 239
/*     */     //   220: aload 8
/*     */     //   222: invokeinterface 459 1 0
/*     */     //   227: aload 11
/*     */     //   229: iconst_0
/*     */     //   230: ldc_w 462
/*     */     //   233: invokevirtual 464	com/claro/transfer/MensajeTO:agregaMensaje	(ILjava/lang/String;)V
/*     */     //   236: goto +165 -> 401
/*     */     //   239: aload 8
/*     */     //   241: invokeinterface 467 1 0
/*     */     //   246: aload 11
/*     */     //   248: iconst_1
/*     */     //   249: ldc_w 470
/*     */     //   252: invokevirtual 464	com/claro/transfer/MensajeTO:agregaMensaje	(ILjava/lang/String;)V
/*     */     //   255: goto +146 -> 401
/*     */     //   258: astore 12
/*     */     //   260: aload 8
/*     */     //   262: invokeinterface 467 1 0
/*     */     //   267: new 78	com/claro/exception/CAException
/*     */     //   270: dup
/*     */     //   271: iconst_m1
/*     */     //   272: new 44	java/lang/StringBuilder
/*     */     //   275: dup
/*     */     //   276: ldc_w 472
/*     */     //   279: invokespecial 48	java/lang/StringBuilder:<init>	(Ljava/lang/String;)V
/*     */     //   282: aload 12
/*     */     //   284: invokevirtual 199	java/sql/SQLException:toString	()Ljava/lang/String;
/*     */     //   287: invokevirtual 57	java/lang/StringBuilder:append	(Ljava/lang/String;)Ljava/lang/StringBuilder;
/*     */     //   290: ldc -54
/*     */     //   292: invokevirtual 57	java/lang/StringBuilder:append	(Ljava/lang/String;)Ljava/lang/StringBuilder;
/*     */     //   295: invokevirtual 61	java/lang/StringBuilder:toString	()Ljava/lang/String;
/*     */     //   298: invokespecial 204	com/claro/exception/CAException:<init>	(ILjava/lang/String;)V
/*     */     //   301: athrow
/*     */     //   302: astore 12
/*     */     //   304: aload 8
/*     */     //   306: invokeinterface 467 1 0
/*     */     //   311: new 78	com/claro/exception/CAException
/*     */     //   314: dup
/*     */     //   315: iconst_m1
/*     */     //   316: new 44	java/lang/StringBuilder
/*     */     //   319: dup
/*     */     //   320: ldc_w 472
/*     */     //   323: invokespecial 48	java/lang/StringBuilder:<init>	(Ljava/lang/String;)V
/*     */     //   326: aload 12
/*     */     //   328: invokevirtual 51	java/lang/Exception:toString	()Ljava/lang/String;
/*     */     //   331: invokevirtual 57	java/lang/StringBuilder:append	(Ljava/lang/String;)Ljava/lang/StringBuilder;
/*     */     //   334: ldc -54
/*     */     //   336: invokevirtual 57	java/lang/StringBuilder:append	(Ljava/lang/String;)Ljava/lang/StringBuilder;
/*     */     //   339: invokevirtual 61	java/lang/StringBuilder:toString	()Ljava/lang/String;
/*     */     //   342: invokespecial 204	com/claro/exception/CAException:<init>	(ILjava/lang/String;)V
/*     */     //   345: athrow
/*     */     //   346: astore 13
/*     */     //   348: aload 8
/*     */     //   350: ifnull +13 -> 363
/*     */     //   353: aload 8
/*     */     //   355: invokeinterface 112 1 0
/*     */     //   360: aconst_null
/*     */     //   361: astore 8
/*     */     //   363: aload 9
/*     */     //   365: ifnull +13 -> 378
/*     */     //   368: aload 9
/*     */     //   370: invokeinterface 354 1 0
/*     */     //   375: aconst_null
/*     */     //   376: astore 9
/*     */     //   378: aload 10
/*     */     //   380: ifnull +18 -> 398
/*     */     //   383: aload 10
/*     */     //   385: invokeinterface 120 1 0
/*     */     //   390: aconst_null
/*     */     //   391: astore 10
/*     */     //   393: goto +5 -> 398
/*     */     //   396: astore 14
/*     */     //   398: aload 13
/*     */     //   400: athrow
/*     */     //   401: aload 8
/*     */     //   403: ifnull +13 -> 416
/*     */     //   406: aload 8
/*     */     //   408: invokeinterface 112 1 0
/*     */     //   413: aconst_null
/*     */     //   414: astore 8
/*     */     //   416: aload 9
/*     */     //   418: ifnull +13 -> 431
/*     */     //   421: aload 9
/*     */     //   423: invokeinterface 354 1 0
/*     */     //   428: aconst_null
/*     */     //   429: astore 9
/*     */     //   431: aload 10
/*     */     //   433: ifnull +18 -> 451
/*     */     //   436: aload 10
/*     */     //   438: invokeinterface 120 1 0
/*     */     //   443: aconst_null
/*     */     //   444: astore 10
/*     */     //   446: goto +5 -> 451
/*     */     //   449: astore 14
/*     */     //   451: aload 11
/*     */     //   453: areturn
/*     */     // Line number table:
/*     */     //   Java source line #267	-> byte code offset #0
/*     */     //   Java source line #268	-> byte code offset #9
/*     */     //   Java source line #269	-> byte code offset #12
/*     */     //   Java source line #270	-> byte code offset #15
/*     */     //   Java source line #271	-> byte code offset #18
/*     */     //   Java source line #272	-> byte code offset #27
/*     */     //   Java source line #273	-> byte code offset #49
/*     */     //   Java source line #274	-> byte code offset #58
/*     */     //   Java source line #276	-> byte code offset #67
/*     */     //   Java source line #277	-> byte code offset #78
/*     */     //   Java source line #278	-> byte code offset #86
/*     */     //   Java source line #280	-> byte code offset #100
/*     */     //   Java source line #281	-> byte code offset #109
/*     */     //   Java source line #282	-> byte code offset #118
/*     */     //   Java source line #283	-> byte code offset #140
/*     */     //   Java source line #284	-> byte code offset #149
/*     */     //   Java source line #285	-> byte code offset #180
/*     */     //   Java source line #286	-> byte code offset #190
/*     */     //   Java source line #287	-> byte code offset #201
/*     */     //   Java source line #288	-> byte code offset #210
/*     */     //   Java source line #289	-> byte code offset #220
/*     */     //   Java source line #290	-> byte code offset #227
/*     */     //   Java source line #292	-> byte code offset #239
/*     */     //   Java source line #293	-> byte code offset #246
/*     */     //   Java source line #295	-> byte code offset #258
/*     */     //   Java source line #296	-> byte code offset #260
/*     */     //   Java source line #297	-> byte code offset #267
/*     */     //   Java source line #298	-> byte code offset #302
/*     */     //   Java source line #299	-> byte code offset #304
/*     */     //   Java source line #300	-> byte code offset #311
/*     */     //   Java source line #301	-> byte code offset #346
/*     */     //   Java source line #303	-> byte code offset #348
/*     */     //   Java source line #304	-> byte code offset #363
/*     */     //   Java source line #305	-> byte code offset #378
/*     */     //   Java source line #306	-> byte code offset #396
/*     */     //   Java source line #307	-> byte code offset #398
/*     */     //   Java source line #303	-> byte code offset #401
/*     */     //   Java source line #304	-> byte code offset #416
/*     */     //   Java source line #305	-> byte code offset #431
/*     */     //   Java source line #306	-> byte code offset #449
/*     */     //   Java source line #308	-> byte code offset #451
/*     */     // Local variable table:
/*     */     //   start	length	slot	name	signature
/*     */     //   0	454	0	this	ConsultasGapDAO
/*     */     //   0	454	1	idPromocionGap	int
/*     */     //   0	454	2	versionPromoGap	int
/*     */     //   0	454	3	telefono	String
/*     */     //   0	454	4	fechaTransaccion	long
/*     */     //   0	454	6	msg	String
/*     */     //   7	82	7	stringBuffer	StringBuffer
/*     */     //   10	405	8	connection	Connection
/*     */     //   13	417	9	preparedStatement	java.sql.PreparedStatement
/*     */     //   16	429	10	resultSet	ResultSet
/*     */     //   25	427	11	mensajeTO	com.claro.transfer.MensajeTO
/*     */     //   258	25	12	e	SQLException
/*     */     //   302	25	12	e	Exception
/*     */     //   346	53	13	localObject	Object
/*     */     //   396	1	14	localSQLException1	SQLException
/*     */     //   449	1	14	localSQLException2	SQLException
/*     */     // Exception table:
/*     */     //   from	to	target	type
/*     */     //   67	255	258	java/sql/SQLException
/*     */     //   67	255	302	java/lang/Exception
/*     */     //   67	346	346	finally
/*     */     //   348	393	396	java/sql/SQLException
/*     */     //   401	446	449	java/sql/SQLException
/*     */   }
/*     */   
/*     */   /* Error */
/*     */   public com.claro.transfer.MensajeTO actualizaPromocionOfrecida(int idPromocionGap, int versionPromoGap, String telefono, long fechaTransaccion, String msg)
/*     */     throws Exception
/*     */   {
/*     */     // Byte code:
/*     */     //   0: new 80	java/lang/StringBuffer
/*     */     //   3: dup
/*     */     //   4: invokespecial 82	java/lang/StringBuffer:<init>	()V
/*     */     //   7: astore 7
/*     */     //   9: aconst_null
/*     */     //   10: astore 8
/*     */     //   12: aconst_null
/*     */     //   13: astore 9
/*     */     //   15: aconst_null
/*     */     //   16: astore 10
/*     */     //   18: new 428	com/claro/transfer/MensajeTO
/*     */     //   21: dup
/*     */     //   22: invokespecial 430	com/claro/transfer/MensajeTO:<init>	()V
/*     */     //   25: astore 11
/*     */     //   27: aload 7
/*     */     //   29: ldc_w 480
/*     */     //   32: invokevirtual 125	java/lang/StringBuffer:append	(Ljava/lang/String;)Ljava/lang/StringBuffer;
/*     */     //   35: aload_0
/*     */     //   36: getfield 29	com/claro/dao/ConsultasGapDAO:schemaGap	Ljava/lang/String;
/*     */     //   39: invokevirtual 125	java/lang/StringBuffer:append	(Ljava/lang/String;)Ljava/lang/StringBuffer;
/*     */     //   42: ldc_w 403
/*     */     //   45: invokevirtual 125	java/lang/StringBuffer:append	(Ljava/lang/String;)Ljava/lang/StringBuffer;
/*     */     //   48: pop
/*     */     //   49: aload 7
/*     */     //   51: ldc_w 482
/*     */     //   54: invokevirtual 125	java/lang/StringBuffer:append	(Ljava/lang/String;)Ljava/lang/StringBuffer;
/*     */     //   57: pop
/*     */     //   58: aload 7
/*     */     //   60: ldc_w 484
/*     */     //   63: invokevirtual 125	java/lang/StringBuffer:append	(Ljava/lang/String;)Ljava/lang/StringBuffer;
/*     */     //   66: pop
/*     */     //   67: invokestatic 31	com/claro/util/ServiceLocator:getInstance	()Lcom/claro/util/ServiceLocator;
/*     */     //   70: getstatic 158	com/claro/util/ServiceLocator:jdbcGap	Ljava/lang/String;
/*     */     //   73: invokevirtual 161	com/claro/util/ServiceLocator:getConnection	(Ljava/lang/String;)Ljava/sql/Connection;
/*     */     //   76: astore 8
/*     */     //   78: aload 8
/*     */     //   80: aload 7
/*     */     //   82: invokevirtual 155	java/lang/StringBuffer:toString	()Ljava/lang/String;
/*     */     //   85: invokeinterface 246 2 0
/*     */     //   90: astore 9
/*     */     //   92: aload 9
/*     */     //   94: iconst_1
/*     */     //   95: iconst_1
/*     */     //   96: invokeinterface 261 3 0
/*     */     //   101: aload 9
/*     */     //   103: iconst_2
/*     */     //   104: new 441	java/sql/Date
/*     */     //   107: dup
/*     */     //   108: lload 4
/*     */     //   110: invokespecial 443	java/sql/Date:<init>	(J)V
/*     */     //   113: invokevirtual 446	java/sql/Date:toString	()Ljava/lang/String;
/*     */     //   116: ldc_w 447
/*     */     //   119: ldc 83
/*     */     //   121: invokevirtual 449	java/lang/String:replaceAll	(Ljava/lang/String;Ljava/lang/String;)Ljava/lang/String;
/*     */     //   124: invokestatic 255	java/lang/Integer:parseInt	(Ljava/lang/String;)I
/*     */     //   127: invokeinterface 261 3 0
/*     */     //   132: aload 9
/*     */     //   134: iconst_3
/*     */     //   135: aload 6
/*     */     //   137: invokeinterface 453 3 0
/*     */     //   142: aload 9
/*     */     //   144: iconst_4
/*     */     //   145: iload_1
/*     */     //   146: invokeinterface 261 3 0
/*     */     //   151: aload 9
/*     */     //   153: iconst_5
/*     */     //   154: new 407	java/lang/Long
/*     */     //   157: dup
/*     */     //   158: aload_3
/*     */     //   159: invokevirtual 105	java/lang/String:trim	()Ljava/lang/String;
/*     */     //   162: invokespecial 409	java/lang/Long:<init>	(Ljava/lang/String;)V
/*     */     //   165: invokevirtual 410	java/lang/Long:longValue	()J
/*     */     //   168: invokeinterface 414 4 0
/*     */     //   173: aload 9
/*     */     //   175: bipush 6
/*     */     //   177: iload_2
/*     */     //   178: invokeinterface 261 3 0
/*     */     //   183: aload 9
/*     */     //   185: bipush 15
/*     */     //   187: invokeinterface 270 2 0
/*     */     //   192: aload 9
/*     */     //   194: invokeinterface 456 1 0
/*     */     //   199: ifle +22 -> 221
/*     */     //   202: aload 8
/*     */     //   204: invokeinterface 459 1 0
/*     */     //   209: aload 11
/*     */     //   211: iconst_0
/*     */     //   212: ldc_w 462
/*     */     //   215: invokevirtual 464	com/claro/transfer/MensajeTO:agregaMensaje	(ILjava/lang/String;)V
/*     */     //   218: goto +158 -> 376
/*     */     //   221: aload 11
/*     */     //   223: iconst_1
/*     */     //   224: ldc_w 470
/*     */     //   227: invokevirtual 464	com/claro/transfer/MensajeTO:agregaMensaje	(ILjava/lang/String;)V
/*     */     //   230: goto +146 -> 376
/*     */     //   233: astore 12
/*     */     //   235: aload 8
/*     */     //   237: invokeinterface 467 1 0
/*     */     //   242: new 78	com/claro/exception/CAException
/*     */     //   245: dup
/*     */     //   246: iconst_m1
/*     */     //   247: new 44	java/lang/StringBuilder
/*     */     //   250: dup
/*     */     //   251: ldc_w 486
/*     */     //   254: invokespecial 48	java/lang/StringBuilder:<init>	(Ljava/lang/String;)V
/*     */     //   257: aload 12
/*     */     //   259: invokevirtual 199	java/sql/SQLException:toString	()Ljava/lang/String;
/*     */     //   262: invokevirtual 57	java/lang/StringBuilder:append	(Ljava/lang/String;)Ljava/lang/StringBuilder;
/*     */     //   265: ldc -54
/*     */     //   267: invokevirtual 57	java/lang/StringBuilder:append	(Ljava/lang/String;)Ljava/lang/StringBuilder;
/*     */     //   270: invokevirtual 61	java/lang/StringBuilder:toString	()Ljava/lang/String;
/*     */     //   273: invokespecial 204	com/claro/exception/CAException:<init>	(ILjava/lang/String;)V
/*     */     //   276: athrow
/*     */     //   277: astore 12
/*     */     //   279: aload 8
/*     */     //   281: invokeinterface 467 1 0
/*     */     //   286: new 78	com/claro/exception/CAException
/*     */     //   289: dup
/*     */     //   290: iconst_m1
/*     */     //   291: new 44	java/lang/StringBuilder
/*     */     //   294: dup
/*     */     //   295: ldc_w 486
/*     */     //   298: invokespecial 48	java/lang/StringBuilder:<init>	(Ljava/lang/String;)V
/*     */     //   301: aload 12
/*     */     //   303: invokevirtual 51	java/lang/Exception:toString	()Ljava/lang/String;
/*     */     //   306: invokevirtual 57	java/lang/StringBuilder:append	(Ljava/lang/String;)Ljava/lang/StringBuilder;
/*     */     //   309: ldc -54
/*     */     //   311: invokevirtual 57	java/lang/StringBuilder:append	(Ljava/lang/String;)Ljava/lang/StringBuilder;
/*     */     //   314: invokevirtual 61	java/lang/StringBuilder:toString	()Ljava/lang/String;
/*     */     //   317: invokespecial 204	com/claro/exception/CAException:<init>	(ILjava/lang/String;)V
/*     */     //   320: athrow
/*     */     //   321: astore 13
/*     */     //   323: aload 8
/*     */     //   325: ifnull +13 -> 338
/*     */     //   328: aload 8
/*     */     //   330: invokeinterface 112 1 0
/*     */     //   335: aconst_null
/*     */     //   336: astore 8
/*     */     //   338: aload 9
/*     */     //   340: ifnull +13 -> 353
/*     */     //   343: aload 9
/*     */     //   345: invokeinterface 354 1 0
/*     */     //   350: aconst_null
/*     */     //   351: astore 9
/*     */     //   353: aload 10
/*     */     //   355: ifnull +18 -> 373
/*     */     //   358: aload 10
/*     */     //   360: invokeinterface 120 1 0
/*     */     //   365: aconst_null
/*     */     //   366: astore 10
/*     */     //   368: goto +5 -> 373
/*     */     //   371: astore 14
/*     */     //   373: aload 13
/*     */     //   375: athrow
/*     */     //   376: aload 8
/*     */     //   378: ifnull +13 -> 391
/*     */     //   381: aload 8
/*     */     //   383: invokeinterface 112 1 0
/*     */     //   388: aconst_null
/*     */     //   389: astore 8
/*     */     //   391: aload 9
/*     */     //   393: ifnull +13 -> 406
/*     */     //   396: aload 9
/*     */     //   398: invokeinterface 354 1 0
/*     */     //   403: aconst_null
/*     */     //   404: astore 9
/*     */     //   406: aload 10
/*     */     //   408: ifnull +18 -> 426
/*     */     //   411: aload 10
/*     */     //   413: invokeinterface 120 1 0
/*     */     //   418: aconst_null
/*     */     //   419: astore 10
/*     */     //   421: goto +5 -> 426
/*     */     //   424: astore 14
/*     */     //   426: aload 11
/*     */     //   428: areturn
/*     */     // Line number table:
/*     */     //   Java source line #319	-> byte code offset #0
/*     */     //   Java source line #320	-> byte code offset #9
/*     */     //   Java source line #321	-> byte code offset #12
/*     */     //   Java source line #322	-> byte code offset #15
/*     */     //   Java source line #323	-> byte code offset #18
/*     */     //   Java source line #324	-> byte code offset #27
/*     */     //   Java source line #325	-> byte code offset #49
/*     */     //   Java source line #326	-> byte code offset #58
/*     */     //   Java source line #328	-> byte code offset #67
/*     */     //   Java source line #329	-> byte code offset #78
/*     */     //   Java source line #330	-> byte code offset #92
/*     */     //   Java source line #331	-> byte code offset #101
/*     */     //   Java source line #332	-> byte code offset #132
/*     */     //   Java source line #333	-> byte code offset #142
/*     */     //   Java source line #334	-> byte code offset #151
/*     */     //   Java source line #335	-> byte code offset #173
/*     */     //   Java source line #336	-> byte code offset #183
/*     */     //   Java source line #337	-> byte code offset #192
/*     */     //   Java source line #338	-> byte code offset #202
/*     */     //   Java source line #339	-> byte code offset #209
/*     */     //   Java source line #341	-> byte code offset #221
/*     */     //   Java source line #343	-> byte code offset #233
/*     */     //   Java source line #344	-> byte code offset #235
/*     */     //   Java source line #345	-> byte code offset #242
/*     */     //   Java source line #346	-> byte code offset #277
/*     */     //   Java source line #347	-> byte code offset #279
/*     */     //   Java source line #348	-> byte code offset #286
/*     */     //   Java source line #349	-> byte code offset #321
/*     */     //   Java source line #351	-> byte code offset #323
/*     */     //   Java source line #352	-> byte code offset #338
/*     */     //   Java source line #353	-> byte code offset #353
/*     */     //   Java source line #354	-> byte code offset #371
/*     */     //   Java source line #355	-> byte code offset #373
/*     */     //   Java source line #351	-> byte code offset #376
/*     */     //   Java source line #352	-> byte code offset #391
/*     */     //   Java source line #353	-> byte code offset #406
/*     */     //   Java source line #354	-> byte code offset #424
/*     */     //   Java source line #356	-> byte code offset #426
/*     */     // Local variable table:
/*     */     //   start	length	slot	name	signature
/*     */     //   0	429	0	this	ConsultasGapDAO
/*     */     //   0	429	1	idPromocionGap	int
/*     */     //   0	429	2	versionPromoGap	int
/*     */     //   0	429	3	telefono	String
/*     */     //   0	429	4	fechaTransaccion	long
/*     */     //   0	429	6	msg	String
/*     */     //   7	74	7	stringBuffer	StringBuffer
/*     */     //   10	380	8	connection	Connection
/*     */     //   13	392	9	preparedStatement	java.sql.PreparedStatement
/*     */     //   16	404	10	resultSet	ResultSet
/*     */     //   25	402	11	mensajeTO	com.claro.transfer.MensajeTO
/*     */     //   233	25	12	e	SQLException
/*     */     //   277	25	12	e	Exception
/*     */     //   321	53	13	localObject	Object
/*     */     //   371	1	14	localSQLException1	SQLException
/*     */     //   424	1	14	localSQLException2	SQLException
/*     */     // Exception table:
/*     */     //   from	to	target	type
/*     */     //   67	230	233	java/sql/SQLException
/*     */     //   67	230	277	java/lang/Exception
/*     */     //   67	321	321	finally
/*     */     //   323	368	371	java/sql/SQLException
/*     */     //   376	421	424	java/sql/SQLException
/*     */   }
/*     */ }


/* Location:              /opt/trabajo/claro/Guatemala/IS/CO/ClaroClub.ear!/ClaroClubEJB.jar!/com/claro/dao/ConsultasGapDAO.class
 * Java compiler version: 6 (50.0)
 * JD-Core Version:       0.7.1
 */