/*     */ package com.claro.dao;
/*     */ 
/*     */ import com.claro.exception.CAException;
/*     */ import com.claro.transfer.MobileTO;
/*     */ import com.claro.transfer.ParametrosTO;
/*     */ import com.claro.util.Constantes;
/*     */ import com.claro.util.ServiceLocator;
/*     */ import java.sql.Connection;
/*     */ import java.sql.SQLException;
/*     */ import java.text.SimpleDateFormat;
/*     */ import java.util.Date;
/*     */ import org.apache.log4j.Logger;
/*     */ 
/*     */ 
/*     */ 
/*     */ 
/*     */ 
/*     */ 
/*     */ 
/*     */ 
/*     */ 
/*     */ 
/*     */ 
/*     */ 
/*     */ 
/*     */ 
/*     */ 
/*     */ 
/*     */ public class ConsultaM2KDAO
/*     */ {
/*  31 */   protected final Logger logger = Logger.getLogger("loggerCirculoAzul");
/*  32 */   protected final Logger error = Logger.getLogger("loggerCirculoAzulError");
/*     */   
/*     */   /* Error */
/*     */   private MobileTO consultaMobile(ParametrosTO parametrosTO, Connection connection)
/*     */     throws CAException
/*     */   {
/*     */     // Byte code:
/*     */     //   0: new 36	java/lang/StringBuffer
/*     */     //   3: dup
/*     */     //   4: invokespecial 38	java/lang/StringBuffer:<init>	()V
/*     */     //   7: astore_3
/*     */     //   8: aload_1
/*     */     //   9: invokevirtual 39	com/claro/transfer/ParametrosTO:getRegion	()I
/*     */     //   12: bipush 9
/*     */     //   14: if_icmpne +10 -> 24
/*     */     //   17: ldc 45
/*     */     //   19: astore 4
/*     */     //   21: goto +29 -> 50
/*     */     //   24: new 47	java/lang/StringBuilder
/*     */     //   27: dup
/*     */     //   28: ldc 49
/*     */     //   30: invokespecial 51	java/lang/StringBuilder:<init>	(Ljava/lang/String;)V
/*     */     //   33: aload_1
/*     */     //   34: invokevirtual 39	com/claro/transfer/ParametrosTO:getRegion	()I
/*     */     //   37: invokevirtual 54	java/lang/StringBuilder:append	(I)Ljava/lang/StringBuilder;
/*     */     //   40: ldc 58
/*     */     //   42: invokevirtual 60	java/lang/StringBuilder:append	(Ljava/lang/String;)Ljava/lang/StringBuilder;
/*     */     //   45: invokevirtual 63	java/lang/StringBuilder:toString	()Ljava/lang/String;
/*     */     //   48: astore 4
/*     */     //   50: aload_3
/*     */     //   51: ldc 67
/*     */     //   53: invokevirtual 69	java/lang/StringBuffer:append	(Ljava/lang/String;)Ljava/lang/StringBuffer;
/*     */     //   56: pop
/*     */     //   57: aload_3
/*     */     //   58: ldc 72
/*     */     //   60: invokevirtual 69	java/lang/StringBuffer:append	(Ljava/lang/String;)Ljava/lang/StringBuffer;
/*     */     //   63: pop
/*     */     //   64: aload_3
/*     */     //   65: ldc 74
/*     */     //   67: invokevirtual 69	java/lang/StringBuffer:append	(Ljava/lang/String;)Ljava/lang/StringBuffer;
/*     */     //   70: pop
/*     */     //   71: aload_3
/*     */     //   72: ldc 76
/*     */     //   74: invokevirtual 69	java/lang/StringBuffer:append	(Ljava/lang/String;)Ljava/lang/StringBuffer;
/*     */     //   77: pop
/*     */     //   78: aload_3
/*     */     //   79: ldc 78
/*     */     //   81: invokevirtual 69	java/lang/StringBuffer:append	(Ljava/lang/String;)Ljava/lang/StringBuffer;
/*     */     //   84: pop
/*     */     //   85: aload_3
/*     */     //   86: ldc 76
/*     */     //   88: invokevirtual 69	java/lang/StringBuffer:append	(Ljava/lang/String;)Ljava/lang/StringBuffer;
/*     */     //   91: pop
/*     */     //   92: aload_3
/*     */     //   93: ldc 80
/*     */     //   95: invokevirtual 69	java/lang/StringBuffer:append	(Ljava/lang/String;)Ljava/lang/StringBuffer;
/*     */     //   98: pop
/*     */     //   99: aload_3
/*     */     //   100: ldc 82
/*     */     //   102: invokevirtual 69	java/lang/StringBuffer:append	(Ljava/lang/String;)Ljava/lang/StringBuffer;
/*     */     //   105: aload 4
/*     */     //   107: invokevirtual 69	java/lang/StringBuffer:append	(Ljava/lang/String;)Ljava/lang/StringBuffer;
/*     */     //   110: ldc 84
/*     */     //   112: invokevirtual 69	java/lang/StringBuffer:append	(Ljava/lang/String;)Ljava/lang/StringBuffer;
/*     */     //   115: pop
/*     */     //   116: aload_1
/*     */     //   117: invokevirtual 86	com/claro/transfer/ParametrosTO:getTelefono	()Ljava/lang/String;
/*     */     //   120: ifnull +20 -> 140
/*     */     //   123: aload_3
/*     */     //   124: ldc 89
/*     */     //   126: invokevirtual 69	java/lang/StringBuffer:append	(Ljava/lang/String;)Ljava/lang/StringBuffer;
/*     */     //   129: aload_1
/*     */     //   130: invokevirtual 86	com/claro/transfer/ParametrosTO:getTelefono	()Ljava/lang/String;
/*     */     //   133: invokevirtual 69	java/lang/StringBuffer:append	(Ljava/lang/String;)Ljava/lang/StringBuffer;
/*     */     //   136: pop
/*     */     //   137: goto +17 -> 154
/*     */     //   140: aload_3
/*     */     //   141: ldc 91
/*     */     //   143: invokevirtual 69	java/lang/StringBuffer:append	(Ljava/lang/String;)Ljava/lang/StringBuffer;
/*     */     //   146: aload_1
/*     */     //   147: invokevirtual 93	com/claro/transfer/ParametrosTO:getCuenta	()Ljava/lang/String;
/*     */     //   150: invokevirtual 69	java/lang/StringBuffer:append	(Ljava/lang/String;)Ljava/lang/StringBuffer;
/*     */     //   153: pop
/*     */     //   154: aload_3
/*     */     //   155: ldc 96
/*     */     //   157: invokevirtual 69	java/lang/StringBuffer:append	(Ljava/lang/String;)Ljava/lang/StringBuffer;
/*     */     //   160: pop
/*     */     //   161: aload_3
/*     */     //   162: aload 4
/*     */     //   164: invokevirtual 69	java/lang/StringBuffer:append	(Ljava/lang/String;)Ljava/lang/StringBuffer;
/*     */     //   167: ldc 98
/*     */     //   169: invokevirtual 69	java/lang/StringBuffer:append	(Ljava/lang/String;)Ljava/lang/StringBuffer;
/*     */     //   172: pop
/*     */     //   173: aload_1
/*     */     //   174: invokevirtual 86	com/claro/transfer/ParametrosTO:getTelefono	()Ljava/lang/String;
/*     */     //   177: ifnull +32 -> 209
/*     */     //   180: aload_3
/*     */     //   181: ldc 100
/*     */     //   183: invokevirtual 69	java/lang/StringBuffer:append	(Ljava/lang/String;)Ljava/lang/StringBuffer;
/*     */     //   186: aload_1
/*     */     //   187: invokevirtual 86	com/claro/transfer/ParametrosTO:getTelefono	()Ljava/lang/String;
/*     */     //   190: invokevirtual 69	java/lang/StringBuffer:append	(Ljava/lang/String;)Ljava/lang/StringBuffer;
/*     */     //   193: ldc 102
/*     */     //   195: invokevirtual 69	java/lang/StringBuffer:append	(Ljava/lang/String;)Ljava/lang/StringBuffer;
/*     */     //   198: pop
/*     */     //   199: aload_3
/*     */     //   200: ldc 104
/*     */     //   202: invokevirtual 69	java/lang/StringBuffer:append	(Ljava/lang/String;)Ljava/lang/StringBuffer;
/*     */     //   205: pop
/*     */     //   206: goto +29 -> 235
/*     */     //   209: aload_3
/*     */     //   210: ldc 106
/*     */     //   212: invokevirtual 69	java/lang/StringBuffer:append	(Ljava/lang/String;)Ljava/lang/StringBuffer;
/*     */     //   215: aload_1
/*     */     //   216: invokevirtual 93	com/claro/transfer/ParametrosTO:getCuenta	()Ljava/lang/String;
/*     */     //   219: invokevirtual 69	java/lang/StringBuffer:append	(Ljava/lang/String;)Ljava/lang/StringBuffer;
/*     */     //   222: ldc 102
/*     */     //   224: invokevirtual 69	java/lang/StringBuffer:append	(Ljava/lang/String;)Ljava/lang/StringBuffer;
/*     */     //   227: pop
/*     */     //   228: aload_3
/*     */     //   229: ldc 108
/*     */     //   231: invokevirtual 69	java/lang/StringBuffer:append	(Ljava/lang/String;)Ljava/lang/StringBuffer;
/*     */     //   234: pop
/*     */     //   235: aconst_null
/*     */     //   236: astore 5
/*     */     //   238: aconst_null
/*     */     //   239: astore 6
/*     */     //   241: new 110	com/claro/transfer/MobileTO
/*     */     //   244: dup
/*     */     //   245: invokespecial 112	com/claro/transfer/MobileTO:<init>	()V
/*     */     //   248: astore 7
/*     */     //   250: invokestatic 113	java/lang/System:currentTimeMillis	()J
/*     */     //   253: lstore 8
/*     */     //   255: aload_0
/*     */     //   256: getfield 21	com/claro/dao/ConsultaM2KDAO:logger	Lorg/apache/log4j/Logger;
/*     */     //   259: new 47	java/lang/StringBuilder
/*     */     //   262: dup
/*     */     //   263: ldc 119
/*     */     //   265: invokespecial 51	java/lang/StringBuilder:<init>	(Ljava/lang/String;)V
/*     */     //   268: getstatic 121	com/claro/util/Constantes:DATEFORMTALog	Ljava/text/SimpleDateFormat;
/*     */     //   271: new 127	java/util/Date
/*     */     //   274: dup
/*     */     //   275: invokespecial 129	java/util/Date:<init>	()V
/*     */     //   278: invokevirtual 130	java/text/SimpleDateFormat:format	(Ljava/util/Date;)Ljava/lang/String;
/*     */     //   281: invokevirtual 60	java/lang/StringBuilder:append	(Ljava/lang/String;)Ljava/lang/StringBuilder;
/*     */     //   284: ldc -120
/*     */     //   286: invokevirtual 60	java/lang/StringBuilder:append	(Ljava/lang/String;)Ljava/lang/StringBuilder;
/*     */     //   289: lload 8
/*     */     //   291: invokevirtual 138	java/lang/StringBuilder:append	(J)Ljava/lang/StringBuilder;
/*     */     //   294: invokevirtual 63	java/lang/StringBuilder:toString	()Ljava/lang/String;
/*     */     //   297: invokevirtual 141	org/apache/log4j/Logger:info	(Ljava/lang/Object;)V
/*     */     //   300: aload_2
/*     */     //   301: invokeinterface 145 1 0
/*     */     //   306: astore 5
/*     */     //   308: aload 5
/*     */     //   310: aload_3
/*     */     //   311: invokevirtual 151	java/lang/StringBuffer:toString	()Ljava/lang/String;
/*     */     //   314: invokeinterface 152 2 0
/*     */     //   319: astore 6
/*     */     //   321: aload 6
/*     */     //   323: invokeinterface 158 1 0
/*     */     //   328: ifeq +180 -> 508
/*     */     //   331: new 110	com/claro/transfer/MobileTO
/*     */     //   334: dup
/*     */     //   335: invokespecial 112	com/claro/transfer/MobileTO:<init>	()V
/*     */     //   338: astore 7
/*     */     //   340: aload 7
/*     */     //   342: aload 6
/*     */     //   344: ldc -92
/*     */     //   346: invokeinterface 166 2 0
/*     */     //   351: invokevirtual 170	com/claro/transfer/MobileTO:setCuenta	(Ljava/lang/String;)V
/*     */     //   354: aload 7
/*     */     //   356: aload 6
/*     */     //   358: ldc -83
/*     */     //   360: invokeinterface 166 2 0
/*     */     //   365: invokevirtual 175	com/claro/transfer/MobileTO:setStatus	(Ljava/lang/String;)V
/*     */     //   368: aload 7
/*     */     //   370: aload 6
/*     */     //   372: ldc -78
/*     */     //   374: invokeinterface 166 2 0
/*     */     //   379: invokevirtual 180	com/claro/transfer/MobileTO:setTelefono	(Ljava/lang/String;)V
/*     */     //   382: aload 7
/*     */     //   384: aload 6
/*     */     //   386: ldc -73
/*     */     //   388: invokeinterface 166 2 0
/*     */     //   393: invokevirtual 185	com/claro/transfer/MobileTO:setIdTecnologia	(Ljava/lang/String;)V
/*     */     //   396: aload 7
/*     */     //   398: aload 6
/*     */     //   400: ldc -68
/*     */     //   402: invokeinterface 166 2 0
/*     */     //   407: invokevirtual 190	com/claro/transfer/MobileTO:setMotivo	(Ljava/lang/String;)V
/*     */     //   410: aload 7
/*     */     //   412: aload 6
/*     */     //   414: ldc -63
/*     */     //   416: invokeinterface 166 2 0
/*     */     //   421: invokevirtual 195	com/claro/transfer/MobileTO:setSecuencia	(Ljava/lang/String;)V
/*     */     //   424: aload 7
/*     */     //   426: aload 6
/*     */     //   428: ldc -58
/*     */     //   430: invokeinterface 166 2 0
/*     */     //   435: invokevirtual 200	com/claro/transfer/MobileTO:setFecEfectiva	(Ljava/lang/String;)V
/*     */     //   438: aload 7
/*     */     //   440: aload 6
/*     */     //   442: bipush 7
/*     */     //   444: invokeinterface 203 2 0
/*     */     //   449: invokestatic 206	com/claro/util/Utils:formatFecha	(Ljava/lang/String;)Ljava/lang/String;
/*     */     //   452: invokevirtual 211	com/claro/transfer/MobileTO:setFechaSuspension	(Ljava/lang/String;)V
/*     */     //   455: aload 7
/*     */     //   457: aload 6
/*     */     //   459: ldc -42
/*     */     //   461: invokeinterface 166 2 0
/*     */     //   466: invokevirtual 216	com/claro/transfer/MobileTO:setEsn	(Ljava/lang/String;)V
/*     */     //   469: aload 7
/*     */     //   471: aload 6
/*     */     //   473: ldc -37
/*     */     //   475: invokeinterface 166 2 0
/*     */     //   480: invokevirtual 221	com/claro/transfer/MobileTO:setImei	(Ljava/lang/String;)V
/*     */     //   483: aload 7
/*     */     //   485: aload 6
/*     */     //   487: ldc -32
/*     */     //   489: invokeinterface 166 2 0
/*     */     //   494: invokevirtual 226	com/claro/transfer/MobileTO:setIccid	(Ljava/lang/String;)V
/*     */     //   497: aload 7
/*     */     //   499: iconst_0
/*     */     //   500: ldc -27
/*     */     //   502: invokevirtual 231	com/claro/transfer/MobileTO:agregaMensaje	(ILjava/lang/String;)V
/*     */     //   505: goto +11 -> 516
/*     */     //   508: aload 7
/*     */     //   510: iconst_m1
/*     */     //   511: ldc -21
/*     */     //   513: invokevirtual 231	com/claro/transfer/MobileTO:agregaMensaje	(ILjava/lang/String;)V
/*     */     //   516: aload 7
/*     */     //   518: invokevirtual 237	com/claro/transfer/MobileTO:getCuenta	()Ljava/lang/String;
/*     */     //   521: ifnonnull +11 -> 532
/*     */     //   524: aload 7
/*     */     //   526: iconst_m1
/*     */     //   527: ldc -18
/*     */     //   529: invokevirtual 231	com/claro/transfer/MobileTO:agregaMensaje	(ILjava/lang/String;)V
/*     */     //   532: aload_0
/*     */     //   533: getfield 21	com/claro/dao/ConsultaM2KDAO:logger	Lorg/apache/log4j/Logger;
/*     */     //   536: new 47	java/lang/StringBuilder
/*     */     //   539: dup
/*     */     //   540: ldc -16
/*     */     //   542: invokespecial 51	java/lang/StringBuilder:<init>	(Ljava/lang/String;)V
/*     */     //   545: getstatic 121	com/claro/util/Constantes:DATEFORMTALog	Ljava/text/SimpleDateFormat;
/*     */     //   548: new 127	java/util/Date
/*     */     //   551: dup
/*     */     //   552: invokespecial 129	java/util/Date:<init>	()V
/*     */     //   555: invokevirtual 130	java/text/SimpleDateFormat:format	(Ljava/util/Date;)Ljava/lang/String;
/*     */     //   558: invokevirtual 60	java/lang/StringBuilder:append	(Ljava/lang/String;)Ljava/lang/StringBuilder;
/*     */     //   561: ldc -120
/*     */     //   563: invokevirtual 60	java/lang/StringBuilder:append	(Ljava/lang/String;)Ljava/lang/StringBuilder;
/*     */     //   566: invokestatic 113	java/lang/System:currentTimeMillis	()J
/*     */     //   569: lload 8
/*     */     //   571: lsub
/*     */     //   572: invokevirtual 138	java/lang/StringBuilder:append	(J)Ljava/lang/StringBuilder;
/*     */     //   575: invokevirtual 63	java/lang/StringBuilder:toString	()Ljava/lang/String;
/*     */     //   578: invokevirtual 141	org/apache/log4j/Logger:info	(Ljava/lang/Object;)V
/*     */     //   581: goto +150 -> 731
/*     */     //   584: astore 8
/*     */     //   586: aload_0
/*     */     //   587: getfield 25	com/claro/dao/ConsultaM2KDAO:error	Lorg/apache/log4j/Logger;
/*     */     //   590: ldc -14
/*     */     //   592: aload 8
/*     */     //   594: invokevirtual 244	org/apache/log4j/Logger:info	(Ljava/lang/Object;Ljava/lang/Throwable;)V
/*     */     //   597: new 34	com/claro/exception/CAException
/*     */     //   600: dup
/*     */     //   601: bipush -2
/*     */     //   603: new 47	java/lang/StringBuilder
/*     */     //   606: dup
/*     */     //   607: ldc -9
/*     */     //   609: invokespecial 51	java/lang/StringBuilder:<init>	(Ljava/lang/String;)V
/*     */     //   612: aload 8
/*     */     //   614: invokevirtual 249	java/sql/SQLException:toString	()Ljava/lang/String;
/*     */     //   617: invokevirtual 60	java/lang/StringBuilder:append	(Ljava/lang/String;)Ljava/lang/StringBuilder;
/*     */     //   620: ldc -4
/*     */     //   622: invokevirtual 60	java/lang/StringBuilder:append	(Ljava/lang/String;)Ljava/lang/StringBuilder;
/*     */     //   625: invokevirtual 63	java/lang/StringBuilder:toString	()Ljava/lang/String;
/*     */     //   628: aload 8
/*     */     //   630: invokespecial 254	com/claro/exception/CAException:<init>	(ILjava/lang/String;Ljava/lang/Exception;)V
/*     */     //   633: athrow
/*     */     //   634: astore 8
/*     */     //   636: aload_0
/*     */     //   637: getfield 25	com/claro/dao/ConsultaM2KDAO:error	Lorg/apache/log4j/Logger;
/*     */     //   640: ldc_w 257
/*     */     //   643: aload 8
/*     */     //   645: invokevirtual 244	org/apache/log4j/Logger:info	(Ljava/lang/Object;Ljava/lang/Throwable;)V
/*     */     //   648: new 34	com/claro/exception/CAException
/*     */     //   651: dup
/*     */     //   652: bipush -3
/*     */     //   654: new 47	java/lang/StringBuilder
/*     */     //   657: dup
/*     */     //   658: ldc_w 259
/*     */     //   661: invokespecial 51	java/lang/StringBuilder:<init>	(Ljava/lang/String;)V
/*     */     //   664: aload 8
/*     */     //   666: invokevirtual 261	java/lang/Exception:toString	()Ljava/lang/String;
/*     */     //   669: invokevirtual 60	java/lang/StringBuilder:append	(Ljava/lang/String;)Ljava/lang/StringBuilder;
/*     */     //   672: ldc -4
/*     */     //   674: invokevirtual 60	java/lang/StringBuilder:append	(Ljava/lang/String;)Ljava/lang/StringBuilder;
/*     */     //   677: invokevirtual 63	java/lang/StringBuilder:toString	()Ljava/lang/String;
/*     */     //   680: aload 8
/*     */     //   682: invokespecial 254	com/claro/exception/CAException:<init>	(ILjava/lang/String;Ljava/lang/Exception;)V
/*     */     //   685: athrow
/*     */     //   686: astore 10
/*     */     //   688: aload 6
/*     */     //   690: ifnull +18 -> 708
/*     */     //   693: aload 6
/*     */     //   695: invokeinterface 264 1 0
/*     */     //   700: aconst_null
/*     */     //   701: astore 6
/*     */     //   703: goto +5 -> 708
/*     */     //   706: astore 11
/*     */     //   708: aload 5
/*     */     //   710: ifnull +18 -> 728
/*     */     //   713: aload 5
/*     */     //   715: invokeinterface 267 1 0
/*     */     //   720: aconst_null
/*     */     //   721: astore 5
/*     */     //   723: goto +5 -> 728
/*     */     //   726: astore 11
/*     */     //   728: aload 10
/*     */     //   730: athrow
/*     */     //   731: aload 6
/*     */     //   733: ifnull +18 -> 751
/*     */     //   736: aload 6
/*     */     //   738: invokeinterface 264 1 0
/*     */     //   743: aconst_null
/*     */     //   744: astore 6
/*     */     //   746: goto +5 -> 751
/*     */     //   749: astore 11
/*     */     //   751: aload 5
/*     */     //   753: ifnull +18 -> 771
/*     */     //   756: aload 5
/*     */     //   758: invokeinterface 267 1 0
/*     */     //   763: aconst_null
/*     */     //   764: astore 5
/*     */     //   766: goto +5 -> 771
/*     */     //   769: astore 11
/*     */     //   771: aload 7
/*     */     //   773: areturn
/*     */     // Line number table:
/*     */     //   Java source line #35	-> byte code offset #0
/*     */     //   Java source line #40	-> byte code offset #8
/*     */     //   Java source line #41	-> byte code offset #17
/*     */     //   Java source line #43	-> byte code offset #24
/*     */     //   Java source line #46	-> byte code offset #50
/*     */     //   Java source line #47	-> byte code offset #57
/*     */     //   Java source line #48	-> byte code offset #64
/*     */     //   Java source line #49	-> byte code offset #71
/*     */     //   Java source line #50	-> byte code offset #78
/*     */     //   Java source line #51	-> byte code offset #85
/*     */     //   Java source line #52	-> byte code offset #92
/*     */     //   Java source line #53	-> byte code offset #99
/*     */     //   Java source line #55	-> byte code offset #116
/*     */     //   Java source line #56	-> byte code offset #123
/*     */     //   Java source line #58	-> byte code offset #140
/*     */     //   Java source line #60	-> byte code offset #154
/*     */     //   Java source line #61	-> byte code offset #161
/*     */     //   Java source line #63	-> byte code offset #173
/*     */     //   Java source line #64	-> byte code offset #180
/*     */     //   Java source line #65	-> byte code offset #199
/*     */     //   Java source line #68	-> byte code offset #209
/*     */     //   Java source line #69	-> byte code offset #228
/*     */     //   Java source line #72	-> byte code offset #235
/*     */     //   Java source line #73	-> byte code offset #238
/*     */     //   Java source line #75	-> byte code offset #241
/*     */     //   Java source line #77	-> byte code offset #250
/*     */     //   Java source line #78	-> byte code offset #255
/*     */     //   Java source line #79	-> byte code offset #300
/*     */     //   Java source line #80	-> byte code offset #308
/*     */     //   Java source line #81	-> byte code offset #321
/*     */     //   Java source line #82	-> byte code offset #331
/*     */     //   Java source line #83	-> byte code offset #340
/*     */     //   Java source line #84	-> byte code offset #354
/*     */     //   Java source line #85	-> byte code offset #368
/*     */     //   Java source line #86	-> byte code offset #382
/*     */     //   Java source line #87	-> byte code offset #396
/*     */     //   Java source line #88	-> byte code offset #410
/*     */     //   Java source line #89	-> byte code offset #424
/*     */     //   Java source line #90	-> byte code offset #438
/*     */     //   Java source line #91	-> byte code offset #455
/*     */     //   Java source line #92	-> byte code offset #469
/*     */     //   Java source line #93	-> byte code offset #483
/*     */     //   Java source line #94	-> byte code offset #497
/*     */     //   Java source line #96	-> byte code offset #508
/*     */     //   Java source line #98	-> byte code offset #516
/*     */     //   Java source line #99	-> byte code offset #524
/*     */     //   Java source line #101	-> byte code offset #532
/*     */     //   Java source line #102	-> byte code offset #584
/*     */     //   Java source line #103	-> byte code offset #586
/*     */     //   Java source line #104	-> byte code offset #597
/*     */     //   Java source line #105	-> byte code offset #634
/*     */     //   Java source line #106	-> byte code offset #636
/*     */     //   Java source line #107	-> byte code offset #648
/*     */     //   Java source line #109	-> byte code offset #686
/*     */     //   Java source line #110	-> byte code offset #688
/*     */     //   Java source line #111	-> byte code offset #708
/*     */     //   Java source line #112	-> byte code offset #728
/*     */     //   Java source line #110	-> byte code offset #731
/*     */     //   Java source line #111	-> byte code offset #751
/*     */     //   Java source line #113	-> byte code offset #771
/*     */     // Local variable table:
/*     */     //   start	length	slot	name	signature
/*     */     //   0	774	0	this	ConsultaM2KDAO
/*     */     //   0	774	1	parametrosTO	ParametrosTO
/*     */     //   0	774	2	connection	Connection
/*     */     //   7	304	3	query	StringBuffer
/*     */     //   19	3	4	mertelM2K	String
/*     */     //   48	115	4	mertelM2K	String
/*     */     //   236	529	5	statement	java.sql.Statement
/*     */     //   239	506	6	resultSet	java.sql.ResultSet
/*     */     //   248	524	7	mobileTO	MobileTO
/*     */     //   253	317	8	inicioConsulta	long
/*     */     //   584	45	8	e	SQLException
/*     */     //   634	47	8	e	Exception
/*     */     //   686	43	10	localObject	Object
/*     */     //   706	1	11	localException1	Exception
/*     */     //   726	1	11	localException2	Exception
/*     */     //   749	1	11	localException3	Exception
/*     */     //   769	1	11	localException4	Exception
/*     */     // Exception table:
/*     */     //   from	to	target	type
/*     */     //   250	581	584	java/sql/SQLException
/*     */     //   250	581	634	java/lang/Exception
/*     */     //   250	686	686	finally
/*     */     //   693	703	706	java/lang/Exception
/*     */     //   713	723	726	java/lang/Exception
/*     */     //   736	746	749	java/lang/Exception
/*     */     //   756	766	769	java/lang/Exception
/*     */   }
/*     */   
/*     */   public MobileTO consultaDatosM2K(ParametrosTO parametrosTO)
/*     */     throws CAException
/*     */   {
/* 120 */     Connection connection = null;
/* 121 */     MobileTO mobileTO = null;
/*     */     try {
/* 123 */       long inicioProceso = System.currentTimeMillis();
/* 124 */       this.logger.info("consultaDatosM2K|Inicio Proceso|" + Constantes.DATEFORMTALog.format(new Date()) + "|" + inicioProceso);
/* 125 */       this.logger.info("consultaDatosM2K|Antes de Conexion|" + Constantes.DATEFORMTALog.format(new Date()) + "|" + inicioProceso);
/*     */       
/* 127 */       if ((parametrosTO.getRegion() == 4) || (parametrosTO.getRegion() == 5) || (parametrosTO.getRegion() == 9)) {
/* 128 */         connection = ServiceLocator.getInstance().getConnection(ServiceLocator.jdbcMobile459);
/*     */       } else
/* 130 */         connection = ServiceLocator.getInstance().getConnection(ServiceLocator.jdbcMobile);
/* 131 */       this.logger.info("consultaDatosM2K|Despues de Conexion|" + Constantes.DATEFORMTALog.format(new Date()) + "|" + (System.currentTimeMillis() - inicioProceso));
/*     */       
/* 133 */       mobileTO = consultaMobile(parametrosTO, connection);
/*     */       
/* 135 */       if (mobileTO.getIdMensaje() == -1) {
/* 136 */         return mobileTO;
/*     */       }
/* 138 */       obtieneDatosM2K(parametrosTO.getRegion(), mobileTO, connection);
/* 139 */       this.logger.info("consultaDatosM2K|FinProceso|" + Constantes.DATEFORMTALog.format(new Date()) + "|" + (System.currentTimeMillis() - inicioProceso));
/*     */     } catch (SQLException e) {
/* 141 */       this.error.info("SQLException.consultaEmpleado:", e);
/* 142 */       throw new CAException(-1, "SQLException.consultaDatosM2K[" + e.toString() + "]", e);
/*     */     } catch (Exception e) {
/* 144 */       this.error.info("Exception.consultaDatosM2K:", e);
/* 145 */       throw new CAException(-1, "ConsultaM2KDAO.consultaDatosM2K[" + e.toString() + "]", e);
/*     */     } finally {
/* 147 */       if (connection != null) try { connection.close();connection = null; } catch (Exception localException2) {} } if (connection != null) try { connection.close();connection = null;
/*     */       } catch (Exception localException3) {}
/* 149 */     return mobileTO;
/*     */   }
/*     */   
/*     */   /* Error */
/*     */   private void obtieneDatosM2K(int region, MobileTO mobileTO, Connection connection)
/*     */     throws CAException
/*     */   {
/*     */     // Byte code:
/*     */     //   0: iload_1
/*     */     //   1: iconst_4
/*     */     //   2: if_icmpne +11 -> 13
/*     */     //   5: ldc_w 337
/*     */     //   8: astore 4
/*     */     //   10: goto +41 -> 51
/*     */     //   13: iload_1
/*     */     //   14: bipush 9
/*     */     //   16: if_icmpne +11 -> 27
/*     */     //   19: ldc_w 339
/*     */     //   22: astore 4
/*     */     //   24: goto +27 -> 51
/*     */     //   27: new 47	java/lang/StringBuilder
/*     */     //   30: dup
/*     */     //   31: ldc 49
/*     */     //   33: invokespecial 51	java/lang/StringBuilder:<init>	(Ljava/lang/String;)V
/*     */     //   36: iload_1
/*     */     //   37: invokevirtual 54	java/lang/StringBuilder:append	(I)Ljava/lang/StringBuilder;
/*     */     //   40: ldc_w 341
/*     */     //   43: invokevirtual 60	java/lang/StringBuilder:append	(Ljava/lang/String;)Ljava/lang/StringBuilder;
/*     */     //   46: invokevirtual 63	java/lang/StringBuilder:toString	()Ljava/lang/String;
/*     */     //   49: astore 4
/*     */     //   51: new 36	java/lang/StringBuffer
/*     */     //   54: dup
/*     */     //   55: invokespecial 38	java/lang/StringBuffer:<init>	()V
/*     */     //   58: astore 5
/*     */     //   60: aload 5
/*     */     //   62: ldc_w 343
/*     */     //   65: invokevirtual 69	java/lang/StringBuffer:append	(Ljava/lang/String;)Ljava/lang/StringBuffer;
/*     */     //   68: pop
/*     */     //   69: aload 5
/*     */     //   71: ldc_w 345
/*     */     //   74: invokevirtual 69	java/lang/StringBuffer:append	(Ljava/lang/String;)Ljava/lang/StringBuffer;
/*     */     //   77: pop
/*     */     //   78: aload 5
/*     */     //   80: ldc_w 347
/*     */     //   83: invokevirtual 69	java/lang/StringBuffer:append	(Ljava/lang/String;)Ljava/lang/StringBuffer;
/*     */     //   86: pop
/*     */     //   87: aload 5
/*     */     //   89: ldc_w 349
/*     */     //   92: invokevirtual 69	java/lang/StringBuffer:append	(Ljava/lang/String;)Ljava/lang/StringBuffer;
/*     */     //   95: pop
/*     */     //   96: aload 5
/*     */     //   98: ldc_w 351
/*     */     //   101: invokevirtual 69	java/lang/StringBuffer:append	(Ljava/lang/String;)Ljava/lang/StringBuffer;
/*     */     //   104: pop
/*     */     //   105: aload 5
/*     */     //   107: ldc_w 347
/*     */     //   110: invokevirtual 69	java/lang/StringBuffer:append	(Ljava/lang/String;)Ljava/lang/StringBuffer;
/*     */     //   113: pop
/*     */     //   114: aload 5
/*     */     //   116: ldc_w 349
/*     */     //   119: invokevirtual 69	java/lang/StringBuffer:append	(Ljava/lang/String;)Ljava/lang/StringBuffer;
/*     */     //   122: pop
/*     */     //   123: aload 5
/*     */     //   125: ldc_w 353
/*     */     //   128: invokevirtual 69	java/lang/StringBuffer:append	(Ljava/lang/String;)Ljava/lang/StringBuffer;
/*     */     //   131: pop
/*     */     //   132: aload 5
/*     */     //   134: ldc_w 355
/*     */     //   137: invokevirtual 69	java/lang/StringBuffer:append	(Ljava/lang/String;)Ljava/lang/StringBuffer;
/*     */     //   140: pop
/*     */     //   141: aload 5
/*     */     //   143: ldc_w 357
/*     */     //   146: invokevirtual 69	java/lang/StringBuffer:append	(Ljava/lang/String;)Ljava/lang/StringBuffer;
/*     */     //   149: pop
/*     */     //   150: aload 5
/*     */     //   152: ldc_w 359
/*     */     //   155: invokevirtual 69	java/lang/StringBuffer:append	(Ljava/lang/String;)Ljava/lang/StringBuffer;
/*     */     //   158: pop
/*     */     //   159: aload 5
/*     */     //   161: ldc_w 361
/*     */     //   164: invokevirtual 69	java/lang/StringBuffer:append	(Ljava/lang/String;)Ljava/lang/StringBuffer;
/*     */     //   167: pop
/*     */     //   168: aload 5
/*     */     //   170: ldc_w 363
/*     */     //   173: invokevirtual 69	java/lang/StringBuffer:append	(Ljava/lang/String;)Ljava/lang/StringBuffer;
/*     */     //   176: pop
/*     */     //   177: aload 5
/*     */     //   179: ldc_w 365
/*     */     //   182: invokevirtual 69	java/lang/StringBuffer:append	(Ljava/lang/String;)Ljava/lang/StringBuffer;
/*     */     //   185: pop
/*     */     //   186: aload 5
/*     */     //   188: ldc_w 361
/*     */     //   191: invokevirtual 69	java/lang/StringBuffer:append	(Ljava/lang/String;)Ljava/lang/StringBuffer;
/*     */     //   194: pop
/*     */     //   195: aload 5
/*     */     //   197: ldc_w 363
/*     */     //   200: invokevirtual 69	java/lang/StringBuffer:append	(Ljava/lang/String;)Ljava/lang/StringBuffer;
/*     */     //   203: pop
/*     */     //   204: aload 5
/*     */     //   206: ldc_w 367
/*     */     //   209: invokevirtual 69	java/lang/StringBuffer:append	(Ljava/lang/String;)Ljava/lang/StringBuffer;
/*     */     //   212: pop
/*     */     //   213: aload 5
/*     */     //   215: ldc_w 369
/*     */     //   218: invokevirtual 69	java/lang/StringBuffer:append	(Ljava/lang/String;)Ljava/lang/StringBuffer;
/*     */     //   221: pop
/*     */     //   222: aload 5
/*     */     //   224: ldc_w 371
/*     */     //   227: invokevirtual 69	java/lang/StringBuffer:append	(Ljava/lang/String;)Ljava/lang/StringBuffer;
/*     */     //   230: pop
/*     */     //   231: aload 5
/*     */     //   233: ldc_w 373
/*     */     //   236: invokevirtual 69	java/lang/StringBuffer:append	(Ljava/lang/String;)Ljava/lang/StringBuffer;
/*     */     //   239: pop
/*     */     //   240: aload 5
/*     */     //   242: ldc_w 375
/*     */     //   245: invokevirtual 69	java/lang/StringBuffer:append	(Ljava/lang/String;)Ljava/lang/StringBuffer;
/*     */     //   248: pop
/*     */     //   249: aload 5
/*     */     //   251: ldc_w 371
/*     */     //   254: invokevirtual 69	java/lang/StringBuffer:append	(Ljava/lang/String;)Ljava/lang/StringBuffer;
/*     */     //   257: pop
/*     */     //   258: aload 5
/*     */     //   260: ldc_w 373
/*     */     //   263: invokevirtual 69	java/lang/StringBuffer:append	(Ljava/lang/String;)Ljava/lang/StringBuffer;
/*     */     //   266: pop
/*     */     //   267: aload 5
/*     */     //   269: ldc_w 377
/*     */     //   272: invokevirtual 69	java/lang/StringBuffer:append	(Ljava/lang/String;)Ljava/lang/StringBuffer;
/*     */     //   275: pop
/*     */     //   276: aload 5
/*     */     //   278: ldc_w 379
/*     */     //   281: invokevirtual 69	java/lang/StringBuffer:append	(Ljava/lang/String;)Ljava/lang/StringBuffer;
/*     */     //   284: pop
/*     */     //   285: aload 5
/*     */     //   287: ldc_w 381
/*     */     //   290: invokevirtual 69	java/lang/StringBuffer:append	(Ljava/lang/String;)Ljava/lang/StringBuffer;
/*     */     //   293: aload 4
/*     */     //   295: invokevirtual 69	java/lang/StringBuffer:append	(Ljava/lang/String;)Ljava/lang/StringBuffer;
/*     */     //   298: ldc_w 383
/*     */     //   301: invokevirtual 69	java/lang/StringBuffer:append	(Ljava/lang/String;)Ljava/lang/StringBuffer;
/*     */     //   304: pop
/*     */     //   305: aload 5
/*     */     //   307: aload 4
/*     */     //   309: invokevirtual 69	java/lang/StringBuffer:append	(Ljava/lang/String;)Ljava/lang/StringBuffer;
/*     */     //   312: ldc_w 385
/*     */     //   315: invokevirtual 69	java/lang/StringBuffer:append	(Ljava/lang/String;)Ljava/lang/StringBuffer;
/*     */     //   318: pop
/*     */     //   319: aload 5
/*     */     //   321: ldc_w 387
/*     */     //   324: invokevirtual 69	java/lang/StringBuffer:append	(Ljava/lang/String;)Ljava/lang/StringBuffer;
/*     */     //   327: aload 4
/*     */     //   329: invokevirtual 69	java/lang/StringBuffer:append	(Ljava/lang/String;)Ljava/lang/StringBuffer;
/*     */     //   332: ldc_w 389
/*     */     //   335: invokevirtual 69	java/lang/StringBuffer:append	(Ljava/lang/String;)Ljava/lang/StringBuffer;
/*     */     //   338: pop
/*     */     //   339: aload 5
/*     */     //   341: ldc_w 391
/*     */     //   344: invokevirtual 69	java/lang/StringBuffer:append	(Ljava/lang/String;)Ljava/lang/StringBuffer;
/*     */     //   347: aload 4
/*     */     //   349: invokevirtual 69	java/lang/StringBuffer:append	(Ljava/lang/String;)Ljava/lang/StringBuffer;
/*     */     //   352: ldc_w 393
/*     */     //   355: invokevirtual 69	java/lang/StringBuffer:append	(Ljava/lang/String;)Ljava/lang/StringBuffer;
/*     */     //   358: pop
/*     */     //   359: aload 5
/*     */     //   361: ldc_w 395
/*     */     //   364: invokevirtual 69	java/lang/StringBuffer:append	(Ljava/lang/String;)Ljava/lang/StringBuffer;
/*     */     //   367: pop
/*     */     //   368: aload 5
/*     */     //   370: ldc_w 397
/*     */     //   373: invokevirtual 69	java/lang/StringBuffer:append	(Ljava/lang/String;)Ljava/lang/StringBuffer;
/*     */     //   376: iload_1
/*     */     //   377: invokevirtual 399	java/lang/StringBuffer:append	(I)Ljava/lang/StringBuffer;
/*     */     //   380: ldc_w 402
/*     */     //   383: invokevirtual 69	java/lang/StringBuffer:append	(Ljava/lang/String;)Ljava/lang/StringBuffer;
/*     */     //   386: pop
/*     */     //   387: aload 5
/*     */     //   389: ldc_w 404
/*     */     //   392: invokevirtual 69	java/lang/StringBuffer:append	(Ljava/lang/String;)Ljava/lang/StringBuffer;
/*     */     //   395: aload_2
/*     */     //   396: invokevirtual 237	com/claro/transfer/MobileTO:getCuenta	()Ljava/lang/String;
/*     */     //   399: invokevirtual 69	java/lang/StringBuffer:append	(Ljava/lang/String;)Ljava/lang/StringBuffer;
/*     */     //   402: pop
/*     */     //   403: aload 5
/*     */     //   405: ldc_w 406
/*     */     //   408: invokevirtual 69	java/lang/StringBuffer:append	(Ljava/lang/String;)Ljava/lang/StringBuffer;
/*     */     //   411: pop
/*     */     //   412: aload 5
/*     */     //   414: ldc_w 408
/*     */     //   417: invokevirtual 69	java/lang/StringBuffer:append	(Ljava/lang/String;)Ljava/lang/StringBuffer;
/*     */     //   420: aload_2
/*     */     //   421: invokevirtual 410	com/claro/transfer/MobileTO:getSecuencia	()Ljava/lang/String;
/*     */     //   424: invokevirtual 69	java/lang/StringBuffer:append	(Ljava/lang/String;)Ljava/lang/StringBuffer;
/*     */     //   427: pop
/*     */     //   428: aload 5
/*     */     //   430: ldc_w 413
/*     */     //   433: invokevirtual 69	java/lang/StringBuffer:append	(Ljava/lang/String;)Ljava/lang/StringBuffer;
/*     */     //   436: pop
/*     */     //   437: aload 5
/*     */     //   439: ldc_w 415
/*     */     //   442: invokevirtual 69	java/lang/StringBuffer:append	(Ljava/lang/String;)Ljava/lang/StringBuffer;
/*     */     //   445: pop
/*     */     //   446: aload 5
/*     */     //   448: ldc_w 417
/*     */     //   451: invokevirtual 69	java/lang/StringBuffer:append	(Ljava/lang/String;)Ljava/lang/StringBuffer;
/*     */     //   454: aload 4
/*     */     //   456: invokevirtual 69	java/lang/StringBuffer:append	(Ljava/lang/String;)Ljava/lang/StringBuffer;
/*     */     //   459: ldc_w 419
/*     */     //   462: invokevirtual 69	java/lang/StringBuffer:append	(Ljava/lang/String;)Ljava/lang/StringBuffer;
/*     */     //   465: pop
/*     */     //   466: aload 5
/*     */     //   468: ldc_w 421
/*     */     //   471: invokevirtual 69	java/lang/StringBuffer:append	(Ljava/lang/String;)Ljava/lang/StringBuffer;
/*     */     //   474: iload_1
/*     */     //   475: invokevirtual 399	java/lang/StringBuffer:append	(I)Ljava/lang/StringBuffer;
/*     */     //   478: ldc_w 402
/*     */     //   481: invokevirtual 69	java/lang/StringBuffer:append	(Ljava/lang/String;)Ljava/lang/StringBuffer;
/*     */     //   484: pop
/*     */     //   485: aload 5
/*     */     //   487: ldc_w 423
/*     */     //   490: invokevirtual 69	java/lang/StringBuffer:append	(Ljava/lang/String;)Ljava/lang/StringBuffer;
/*     */     //   493: aload_2
/*     */     //   494: invokevirtual 237	com/claro/transfer/MobileTO:getCuenta	()Ljava/lang/String;
/*     */     //   497: invokevirtual 69	java/lang/StringBuffer:append	(Ljava/lang/String;)Ljava/lang/StringBuffer;
/*     */     //   500: pop
/*     */     //   501: aload 5
/*     */     //   503: ldc_w 425
/*     */     //   506: invokevirtual 69	java/lang/StringBuffer:append	(Ljava/lang/String;)Ljava/lang/StringBuffer;
/*     */     //   509: aload_2
/*     */     //   510: invokevirtual 410	com/claro/transfer/MobileTO:getSecuencia	()Ljava/lang/String;
/*     */     //   513: invokevirtual 69	java/lang/StringBuffer:append	(Ljava/lang/String;)Ljava/lang/StringBuffer;
/*     */     //   516: ldc_w 427
/*     */     //   519: invokevirtual 69	java/lang/StringBuffer:append	(Ljava/lang/String;)Ljava/lang/StringBuffer;
/*     */     //   522: pop
/*     */     //   523: aconst_null
/*     */     //   524: astore 6
/*     */     //   526: aconst_null
/*     */     //   527: astore 7
/*     */     //   529: invokestatic 113	java/lang/System:currentTimeMillis	()J
/*     */     //   532: lstore 8
/*     */     //   534: aload_0
/*     */     //   535: getfield 21	com/claro/dao/ConsultaM2KDAO:logger	Lorg/apache/log4j/Logger;
/*     */     //   538: new 47	java/lang/StringBuilder
/*     */     //   541: dup
/*     */     //   542: ldc_w 429
/*     */     //   545: invokespecial 51	java/lang/StringBuilder:<init>	(Ljava/lang/String;)V
/*     */     //   548: getstatic 121	com/claro/util/Constantes:DATEFORMTALog	Ljava/text/SimpleDateFormat;
/*     */     //   551: new 127	java/util/Date
/*     */     //   554: dup
/*     */     //   555: invokespecial 129	java/util/Date:<init>	()V
/*     */     //   558: invokevirtual 130	java/text/SimpleDateFormat:format	(Ljava/util/Date;)Ljava/lang/String;
/*     */     //   561: invokevirtual 60	java/lang/StringBuilder:append	(Ljava/lang/String;)Ljava/lang/StringBuilder;
/*     */     //   564: ldc -120
/*     */     //   566: invokevirtual 60	java/lang/StringBuilder:append	(Ljava/lang/String;)Ljava/lang/StringBuilder;
/*     */     //   569: lload 8
/*     */     //   571: invokevirtual 138	java/lang/StringBuilder:append	(J)Ljava/lang/StringBuilder;
/*     */     //   574: invokevirtual 63	java/lang/StringBuilder:toString	()Ljava/lang/String;
/*     */     //   577: invokevirtual 141	org/apache/log4j/Logger:info	(Ljava/lang/Object;)V
/*     */     //   580: aload_3
/*     */     //   581: invokeinterface 145 1 0
/*     */     //   586: astore 6
/*     */     //   588: aload 6
/*     */     //   590: aload 5
/*     */     //   592: invokevirtual 151	java/lang/StringBuffer:toString	()Ljava/lang/String;
/*     */     //   595: invokeinterface 152 2 0
/*     */     //   600: astore 7
/*     */     //   602: aload 7
/*     */     //   604: invokeinterface 158 1 0
/*     */     //   609: ifeq +410 -> 1019
/*     */     //   612: aload 7
/*     */     //   614: ldc_w 431
/*     */     //   617: invokeinterface 166 2 0
/*     */     //   622: astore 10
/*     */     //   624: aload_2
/*     */     //   625: aload 7
/*     */     //   627: ldc_w 433
/*     */     //   630: invokeinterface 166 2 0
/*     */     //   635: invokevirtual 435	com/claro/transfer/MobileTO:setCiclo	(Ljava/lang/String;)V
/*     */     //   638: aload_2
/*     */     //   639: aload 7
/*     */     //   641: ldc_w 438
/*     */     //   644: invokeinterface 166 2 0
/*     */     //   649: invokevirtual 440	com/claro/transfer/MobileTO:setPlanM2K	(Ljava/lang/String;)V
/*     */     //   652: aload_2
/*     */     //   653: aload 7
/*     */     //   655: ldc_w 443
/*     */     //   658: invokeinterface 166 2 0
/*     */     //   663: invokevirtual 445	com/claro/transfer/MobileTO:setEstCobranza	(Ljava/lang/String;)V
/*     */     //   666: aload_2
/*     */     //   667: aload 7
/*     */     //   669: ldc_w 448
/*     */     //   672: invokeinterface 166 2 0
/*     */     //   677: invokevirtual 450	com/claro/transfer/MobileTO:setLastName	(Ljava/lang/String;)V
/*     */     //   680: aload_2
/*     */     //   681: aload 7
/*     */     //   683: ldc_w 453
/*     */     //   686: invokeinterface 166 2 0
/*     */     //   691: invokevirtual 455	com/claro/transfer/MobileTO:setFirstName	(Ljava/lang/String;)V
/*     */     //   694: aload_2
/*     */     //   695: aload 7
/*     */     //   697: ldc_w 458
/*     */     //   700: invokeinterface 166 2 0
/*     */     //   705: invokevirtual 460	com/claro/transfer/MobileTO:setTelContacto1	(Ljava/lang/String;)V
/*     */     //   708: aload_2
/*     */     //   709: aload 7
/*     */     //   711: ldc_w 463
/*     */     //   714: invokeinterface 166 2 0
/*     */     //   719: invokevirtual 465	com/claro/transfer/MobileTO:setTelContacto2	(Ljava/lang/String;)V
/*     */     //   722: aload_2
/*     */     //   723: aload 7
/*     */     //   725: ldc_w 468
/*     */     //   728: invokeinterface 166 2 0
/*     */     //   733: invokevirtual 470	com/claro/transfer/MobileTO:setExtContacto1	(Ljava/lang/String;)V
/*     */     //   736: aload_2
/*     */     //   737: aload 7
/*     */     //   739: ldc_w 473
/*     */     //   742: invokeinterface 166 2 0
/*     */     //   747: invokevirtual 475	com/claro/transfer/MobileTO:setExtContacto2	(Ljava/lang/String;)V
/*     */     //   750: aload_2
/*     */     //   751: aload 7
/*     */     //   753: ldc_w 478
/*     */     //   756: invokeinterface 166 2 0
/*     */     //   761: invokevirtual 480	com/claro/transfer/MobileTO:setCuentaCorreo	(Ljava/lang/String;)V
/*     */     //   764: aload_2
/*     */     //   765: aload 7
/*     */     //   767: bipush 10
/*     */     //   769: invokeinterface 203 2 0
/*     */     //   774: invokestatic 206	com/claro/util/Utils:formatFecha	(Ljava/lang/String;)Ljava/lang/String;
/*     */     //   777: invokevirtual 200	com/claro/transfer/MobileTO:setFecEfectiva	(Ljava/lang/String;)V
/*     */     //   780: aload 7
/*     */     //   782: iconst_4
/*     */     //   783: invokeinterface 203 2 0
/*     */     //   788: astore 11
/*     */     //   790: aload 11
/*     */     //   792: ifnull +14 -> 806
/*     */     //   795: aload 11
/*     */     //   797: ldc_w 483
/*     */     //   800: invokevirtual 485	java/lang/String:equals	(Ljava/lang/Object;)Z
/*     */     //   803: ifeq +14 -> 817
/*     */     //   806: aload_2
/*     */     //   807: aload_2
/*     */     //   808: invokevirtual 489	com/claro/transfer/MobileTO:getFecEfectiva	()Ljava/lang/String;
/*     */     //   811: invokevirtual 492	com/claro/transfer/MobileTO:setFecAltaUser	(Ljava/lang/String;)V
/*     */     //   814: goto +12 -> 826
/*     */     //   817: aload_2
/*     */     //   818: aload 11
/*     */     //   820: invokestatic 206	com/claro/util/Utils:formatFecha	(Ljava/lang/String;)Ljava/lang/String;
/*     */     //   823: invokevirtual 492	com/claro/transfer/MobileTO:setFecAltaUser	(Ljava/lang/String;)V
/*     */     //   826: aload 7
/*     */     //   828: bipush 9
/*     */     //   830: invokeinterface 203 2 0
/*     */     //   835: astore 12
/*     */     //   837: aload 12
/*     */     //   839: ifnull +14 -> 853
/*     */     //   842: aload 12
/*     */     //   844: ldc_w 495
/*     */     //   847: invokevirtual 485	java/lang/String:equals	(Ljava/lang/Object;)Z
/*     */     //   850: ifeq +14 -> 864
/*     */     //   853: aload_2
/*     */     //   854: aload_2
/*     */     //   855: invokevirtual 497	com/claro/transfer/MobileTO:getFecAltaUser	()Ljava/lang/String;
/*     */     //   858: invokevirtual 500	com/claro/transfer/MobileTO:setFecAddM2K	(Ljava/lang/String;)V
/*     */     //   861: goto +12 -> 873
/*     */     //   864: aload_2
/*     */     //   865: aload 12
/*     */     //   867: invokestatic 206	com/claro/util/Utils:formatFecha	(Ljava/lang/String;)Ljava/lang/String;
/*     */     //   870: invokevirtual 500	com/claro/transfer/MobileTO:setFecAddM2K	(Ljava/lang/String;)V
/*     */     //   873: aload_2
/*     */     //   874: aload 7
/*     */     //   876: ldc_w 503
/*     */     //   879: invokeinterface 166 2 0
/*     */     //   884: invokevirtual 505	com/claro/transfer/MobileTO:setClaseCredit	(Ljava/lang/String;)V
/*     */     //   887: aload 10
/*     */     //   889: invokevirtual 508	java/lang/String:trim	()Ljava/lang/String;
/*     */     //   892: ldc_w 511
/*     */     //   895: invokevirtual 485	java/lang/String:equals	(Ljava/lang/Object;)Z
/*     */     //   898: ifeq +29 -> 927
/*     */     //   901: iload_1
/*     */     //   902: bipush 9
/*     */     //   904: if_icmpne +13 -> 917
/*     */     //   907: aload_2
/*     */     //   908: ldc_w 513
/*     */     //   911: invokevirtual 515	com/claro/transfer/MobileTO:setAddM2K	(Ljava/lang/String;)V
/*     */     //   914: goto +19 -> 933
/*     */     //   917: aload_2
/*     */     //   918: ldc_w 518
/*     */     //   921: invokevirtual 515	com/claro/transfer/MobileTO:setAddM2K	(Ljava/lang/String;)V
/*     */     //   924: goto +9 -> 933
/*     */     //   927: aload_2
/*     */     //   928: aload 10
/*     */     //   930: invokevirtual 515	com/claro/transfer/MobileTO:setAddM2K	(Ljava/lang/String;)V
/*     */     //   933: aload_2
/*     */     //   934: aload 7
/*     */     //   936: bipush 11
/*     */     //   938: invokeinterface 203 2 0
/*     */     //   943: invokevirtual 520	com/claro/transfer/MobileTO:setCuentaPadre	(Ljava/lang/String;)V
/*     */     //   946: aload_2
/*     */     //   947: aload 7
/*     */     //   949: ldc_w 523
/*     */     //   952: invokeinterface 166 2 0
/*     */     //   957: invokevirtual 525	com/claro/transfer/MobileTO:setMarca	(Ljava/lang/String;)V
/*     */     //   960: aload_2
/*     */     //   961: aload 7
/*     */     //   963: ldc_w 528
/*     */     //   966: invokeinterface 166 2 0
/*     */     //   971: invokevirtual 530	com/claro/transfer/MobileTO:setModelo	(Ljava/lang/String;)V
/*     */     //   974: aload_2
/*     */     //   975: aload 7
/*     */     //   977: ldc_w 533
/*     */     //   980: invokeinterface 166 2 0
/*     */     //   985: ifnull +19 -> 1004
/*     */     //   988: aload 7
/*     */     //   990: ldc_w 533
/*     */     //   993: invokeinterface 166 2 0
/*     */     //   998: invokevirtual 508	java/lang/String:trim	()Ljava/lang/String;
/*     */     //   1001: goto +4 -> 1005
/*     */     //   1004: aconst_null
/*     */     //   1005: invokevirtual 535	com/claro/transfer/MobileTO:setRfc	(Ljava/lang/String;)V
/*     */     //   1008: aload_2
/*     */     //   1009: iconst_0
/*     */     //   1010: ldc_w 538
/*     */     //   1013: invokevirtual 231	com/claro/transfer/MobileTO:agregaMensaje	(ILjava/lang/String;)V
/*     */     //   1016: goto +11 -> 1027
/*     */     //   1019: aload_2
/*     */     //   1020: iconst_m1
/*     */     //   1021: ldc_w 540
/*     */     //   1024: invokevirtual 231	com/claro/transfer/MobileTO:agregaMensaje	(ILjava/lang/String;)V
/*     */     //   1027: aload_0
/*     */     //   1028: getfield 21	com/claro/dao/ConsultaM2KDAO:logger	Lorg/apache/log4j/Logger;
/*     */     //   1031: new 47	java/lang/StringBuilder
/*     */     //   1034: dup
/*     */     //   1035: ldc_w 542
/*     */     //   1038: invokespecial 51	java/lang/StringBuilder:<init>	(Ljava/lang/String;)V
/*     */     //   1041: getstatic 121	com/claro/util/Constantes:DATEFORMTALog	Ljava/text/SimpleDateFormat;
/*     */     //   1044: new 127	java/util/Date
/*     */     //   1047: dup
/*     */     //   1048: invokespecial 129	java/util/Date:<init>	()V
/*     */     //   1051: invokevirtual 130	java/text/SimpleDateFormat:format	(Ljava/util/Date;)Ljava/lang/String;
/*     */     //   1054: invokevirtual 60	java/lang/StringBuilder:append	(Ljava/lang/String;)Ljava/lang/StringBuilder;
/*     */     //   1057: ldc -120
/*     */     //   1059: invokevirtual 60	java/lang/StringBuilder:append	(Ljava/lang/String;)Ljava/lang/StringBuilder;
/*     */     //   1062: invokestatic 113	java/lang/System:currentTimeMillis	()J
/*     */     //   1065: lload 8
/*     */     //   1067: lsub
/*     */     //   1068: invokevirtual 138	java/lang/StringBuilder:append	(J)Ljava/lang/StringBuilder;
/*     */     //   1071: invokevirtual 63	java/lang/StringBuilder:toString	()Ljava/lang/String;
/*     */     //   1074: invokevirtual 141	org/apache/log4j/Logger:info	(Ljava/lang/Object;)V
/*     */     //   1077: goto +150 -> 1227
/*     */     //   1080: astore 8
/*     */     //   1082: aload_0
/*     */     //   1083: getfield 25	com/claro/dao/ConsultaM2KDAO:error	Lorg/apache/log4j/Logger;
/*     */     //   1086: ldc_w 544
/*     */     //   1089: aload 8
/*     */     //   1091: invokevirtual 244	org/apache/log4j/Logger:info	(Ljava/lang/Object;Ljava/lang/Throwable;)V
/*     */     //   1094: new 34	com/claro/exception/CAException
/*     */     //   1097: dup
/*     */     //   1098: iconst_m1
/*     */     //   1099: new 47	java/lang/StringBuilder
/*     */     //   1102: dup
/*     */     //   1103: ldc_w 546
/*     */     //   1106: invokespecial 51	java/lang/StringBuilder:<init>	(Ljava/lang/String;)V
/*     */     //   1109: aload 8
/*     */     //   1111: invokevirtual 249	java/sql/SQLException:toString	()Ljava/lang/String;
/*     */     //   1114: invokevirtual 60	java/lang/StringBuilder:append	(Ljava/lang/String;)Ljava/lang/StringBuilder;
/*     */     //   1117: ldc -4
/*     */     //   1119: invokevirtual 60	java/lang/StringBuilder:append	(Ljava/lang/String;)Ljava/lang/StringBuilder;
/*     */     //   1122: invokevirtual 63	java/lang/StringBuilder:toString	()Ljava/lang/String;
/*     */     //   1125: aload 8
/*     */     //   1127: invokespecial 254	com/claro/exception/CAException:<init>	(ILjava/lang/String;Ljava/lang/Exception;)V
/*     */     //   1130: athrow
/*     */     //   1131: astore 8
/*     */     //   1133: aload_0
/*     */     //   1134: getfield 25	com/claro/dao/ConsultaM2KDAO:error	Lorg/apache/log4j/Logger;
/*     */     //   1137: ldc_w 548
/*     */     //   1140: aload 8
/*     */     //   1142: invokevirtual 244	org/apache/log4j/Logger:info	(Ljava/lang/Object;Ljava/lang/Throwable;)V
/*     */     //   1145: new 34	com/claro/exception/CAException
/*     */     //   1148: dup
/*     */     //   1149: iconst_m1
/*     */     //   1150: new 47	java/lang/StringBuilder
/*     */     //   1153: dup
/*     */     //   1154: ldc_w 550
/*     */     //   1157: invokespecial 51	java/lang/StringBuilder:<init>	(Ljava/lang/String;)V
/*     */     //   1160: aload 8
/*     */     //   1162: invokevirtual 261	java/lang/Exception:toString	()Ljava/lang/String;
/*     */     //   1165: invokevirtual 60	java/lang/StringBuilder:append	(Ljava/lang/String;)Ljava/lang/StringBuilder;
/*     */     //   1168: ldc -4
/*     */     //   1170: invokevirtual 60	java/lang/StringBuilder:append	(Ljava/lang/String;)Ljava/lang/StringBuilder;
/*     */     //   1173: invokevirtual 63	java/lang/StringBuilder:toString	()Ljava/lang/String;
/*     */     //   1176: aload 8
/*     */     //   1178: invokespecial 254	com/claro/exception/CAException:<init>	(ILjava/lang/String;Ljava/lang/Exception;)V
/*     */     //   1181: athrow
/*     */     //   1182: astore 13
/*     */     //   1184: aload 7
/*     */     //   1186: ifnull +18 -> 1204
/*     */     //   1189: aload 7
/*     */     //   1191: invokeinterface 264 1 0
/*     */     //   1196: aconst_null
/*     */     //   1197: astore 7
/*     */     //   1199: goto +5 -> 1204
/*     */     //   1202: astore 14
/*     */     //   1204: aload 6
/*     */     //   1206: ifnull +18 -> 1224
/*     */     //   1209: aload 6
/*     */     //   1211: invokeinterface 267 1 0
/*     */     //   1216: aconst_null
/*     */     //   1217: astore 6
/*     */     //   1219: goto +5 -> 1224
/*     */     //   1222: astore 14
/*     */     //   1224: aload 13
/*     */     //   1226: athrow
/*     */     //   1227: aload 7
/*     */     //   1229: ifnull +18 -> 1247
/*     */     //   1232: aload 7
/*     */     //   1234: invokeinterface 264 1 0
/*     */     //   1239: aconst_null
/*     */     //   1240: astore 7
/*     */     //   1242: goto +5 -> 1247
/*     */     //   1245: astore 14
/*     */     //   1247: aload 6
/*     */     //   1249: ifnull +18 -> 1267
/*     */     //   1252: aload 6
/*     */     //   1254: invokeinterface 267 1 0
/*     */     //   1259: aconst_null
/*     */     //   1260: astore 6
/*     */     //   1262: goto +5 -> 1267
/*     */     //   1265: astore 14
/*     */     //   1267: return
/*     */     // Line number table:
/*     */     //   Java source line #155	-> byte code offset #0
/*     */     //   Java source line #156	-> byte code offset #5
/*     */     //   Java source line #157	-> byte code offset #13
/*     */     //   Java source line #158	-> byte code offset #19
/*     */     //   Java source line #160	-> byte code offset #27
/*     */     //   Java source line #162	-> byte code offset #51
/*     */     //   Java source line #165	-> byte code offset #60
/*     */     //   Java source line #166	-> byte code offset #69
/*     */     //   Java source line #167	-> byte code offset #78
/*     */     //   Java source line #168	-> byte code offset #87
/*     */     //   Java source line #169	-> byte code offset #96
/*     */     //   Java source line #170	-> byte code offset #105
/*     */     //   Java source line #171	-> byte code offset #114
/*     */     //   Java source line #172	-> byte code offset #123
/*     */     //   Java source line #173	-> byte code offset #132
/*     */     //   Java source line #174	-> byte code offset #141
/*     */     //   Java source line #175	-> byte code offset #150
/*     */     //   Java source line #176	-> byte code offset #159
/*     */     //   Java source line #177	-> byte code offset #168
/*     */     //   Java source line #178	-> byte code offset #177
/*     */     //   Java source line #179	-> byte code offset #186
/*     */     //   Java source line #180	-> byte code offset #195
/*     */     //   Java source line #181	-> byte code offset #204
/*     */     //   Java source line #182	-> byte code offset #213
/*     */     //   Java source line #183	-> byte code offset #222
/*     */     //   Java source line #184	-> byte code offset #231
/*     */     //   Java source line #185	-> byte code offset #240
/*     */     //   Java source line #186	-> byte code offset #249
/*     */     //   Java source line #187	-> byte code offset #258
/*     */     //   Java source line #188	-> byte code offset #267
/*     */     //   Java source line #189	-> byte code offset #276
/*     */     //   Java source line #190	-> byte code offset #285
/*     */     //   Java source line #191	-> byte code offset #305
/*     */     //   Java source line #192	-> byte code offset #319
/*     */     //   Java source line #193	-> byte code offset #339
/*     */     //   Java source line #194	-> byte code offset #359
/*     */     //   Java source line #195	-> byte code offset #368
/*     */     //   Java source line #196	-> byte code offset #387
/*     */     //   Java source line #197	-> byte code offset #403
/*     */     //   Java source line #198	-> byte code offset #412
/*     */     //   Java source line #199	-> byte code offset #428
/*     */     //   Java source line #200	-> byte code offset #437
/*     */     //   Java source line #201	-> byte code offset #446
/*     */     //   Java source line #202	-> byte code offset #466
/*     */     //   Java source line #203	-> byte code offset #485
/*     */     //   Java source line #204	-> byte code offset #501
/*     */     //   Java source line #205	-> byte code offset #523
/*     */     //   Java source line #206	-> byte code offset #526
/*     */     //   Java source line #209	-> byte code offset #529
/*     */     //   Java source line #210	-> byte code offset #534
/*     */     //   Java source line #211	-> byte code offset #580
/*     */     //   Java source line #212	-> byte code offset #588
/*     */     //   Java source line #213	-> byte code offset #602
/*     */     //   Java source line #214	-> byte code offset #612
/*     */     //   Java source line #215	-> byte code offset #624
/*     */     //   Java source line #216	-> byte code offset #638
/*     */     //   Java source line #218	-> byte code offset #652
/*     */     //   Java source line #219	-> byte code offset #666
/*     */     //   Java source line #220	-> byte code offset #680
/*     */     //   Java source line #221	-> byte code offset #694
/*     */     //   Java source line #222	-> byte code offset #708
/*     */     //   Java source line #223	-> byte code offset #722
/*     */     //   Java source line #224	-> byte code offset #736
/*     */     //   Java source line #225	-> byte code offset #750
/*     */     //   Java source line #227	-> byte code offset #764
/*     */     //   Java source line #229	-> byte code offset #780
/*     */     //   Java source line #231	-> byte code offset #790
/*     */     //   Java source line #232	-> byte code offset #806
/*     */     //   Java source line #234	-> byte code offset #817
/*     */     //   Java source line #236	-> byte code offset #826
/*     */     //   Java source line #237	-> byte code offset #837
/*     */     //   Java source line #238	-> byte code offset #853
/*     */     //   Java source line #240	-> byte code offset #864
/*     */     //   Java source line #242	-> byte code offset #873
/*     */     //   Java source line #245	-> byte code offset #887
/*     */     //   Java source line #246	-> byte code offset #901
/*     */     //   Java source line #247	-> byte code offset #907
/*     */     //   Java source line #249	-> byte code offset #917
/*     */     //   Java source line #250	-> byte code offset #927
/*     */     //   Java source line #252	-> byte code offset #933
/*     */     //   Java source line #253	-> byte code offset #946
/*     */     //   Java source line #254	-> byte code offset #960
/*     */     //   Java source line #256	-> byte code offset #974
/*     */     //   Java source line #257	-> byte code offset #1008
/*     */     //   Java source line #259	-> byte code offset #1019
/*     */     //   Java source line #261	-> byte code offset #1027
/*     */     //   Java source line #262	-> byte code offset #1080
/*     */     //   Java source line #263	-> byte code offset #1082
/*     */     //   Java source line #264	-> byte code offset #1094
/*     */     //   Java source line #265	-> byte code offset #1131
/*     */     //   Java source line #266	-> byte code offset #1133
/*     */     //   Java source line #267	-> byte code offset #1145
/*     */     //   Java source line #268	-> byte code offset #1182
/*     */     //   Java source line #269	-> byte code offset #1184
/*     */     //   Java source line #270	-> byte code offset #1204
/*     */     //   Java source line #271	-> byte code offset #1224
/*     */     //   Java source line #269	-> byte code offset #1227
/*     */     //   Java source line #270	-> byte code offset #1247
/*     */     //   Java source line #272	-> byte code offset #1267
/*     */     // Local variable table:
/*     */     //   start	length	slot	name	signature
/*     */     //   0	1268	0	this	ConsultaM2KDAO
/*     */     //   0	1268	1	region	int
/*     */     //   0	1268	2	mobileTO	MobileTO
/*     */     //   0	1268	3	connection	Connection
/*     */     //   8	3	4	mercadoM2K	String
/*     */     //   22	3	4	mercadoM2K	String
/*     */     //   49	406	4	mercadoM2K	String
/*     */     //   58	533	5	query1	StringBuffer
/*     */     //   524	737	6	statement	java.sql.Statement
/*     */     //   527	714	7	resultSet	java.sql.ResultSet
/*     */     //   532	534	8	inicioConsulta	long
/*     */     //   1080	46	8	e	SQLException
/*     */     //   1131	46	8	e	Exception
/*     */     //   622	307	10	lAddM2K	String
/*     */     //   788	31	11	sFecAltaUser	String
/*     */     //   835	31	12	sFecAddM2K	String
/*     */     //   1182	43	13	localObject	Object
/*     */     //   1202	1	14	localException1	Exception
/*     */     //   1222	1	14	localException2	Exception
/*     */     //   1245	1	14	localException3	Exception
/*     */     //   1265	1	14	localException4	Exception
/*     */     // Exception table:
/*     */     //   from	to	target	type
/*     */     //   529	1077	1080	java/sql/SQLException
/*     */     //   529	1077	1131	java/lang/Exception
/*     */     //   529	1182	1182	finally
/*     */     //   1189	1199	1202	java/lang/Exception
/*     */     //   1209	1219	1222	java/lang/Exception
/*     */     //   1232	1242	1245	java/lang/Exception
/*     */     //   1252	1262	1265	java/lang/Exception
/*     */   }
/*     */   
/*     */   /* Error */
/*     */   public void obtenPromedioFacturaciones(MobileTO mobileTO, int region, String cuenta)
/*     */     throws CAException
/*     */   {
/*     */     // Byte code:
/*     */     //   0: iload_2
/*     */     //   1: iconst_4
/*     */     //   2: if_icmpne +11 -> 13
/*     */     //   5: ldc_w 337
/*     */     //   8: astore 4
/*     */     //   10: goto +41 -> 51
/*     */     //   13: iload_2
/*     */     //   14: bipush 9
/*     */     //   16: if_icmpne +11 -> 27
/*     */     //   19: ldc_w 339
/*     */     //   22: astore 4
/*     */     //   24: goto +27 -> 51
/*     */     //   27: new 47	java/lang/StringBuilder
/*     */     //   30: dup
/*     */     //   31: ldc 49
/*     */     //   33: invokespecial 51	java/lang/StringBuilder:<init>	(Ljava/lang/String;)V
/*     */     //   36: iload_2
/*     */     //   37: invokevirtual 54	java/lang/StringBuilder:append	(I)Ljava/lang/StringBuilder;
/*     */     //   40: ldc_w 341
/*     */     //   43: invokevirtual 60	java/lang/StringBuilder:append	(Ljava/lang/String;)Ljava/lang/StringBuilder;
/*     */     //   46: invokevirtual 63	java/lang/StringBuilder:toString	()Ljava/lang/String;
/*     */     //   49: astore 4
/*     */     //   51: iload_2
/*     */     //   52: bipush 9
/*     */     //   54: if_icmpne +10 -> 64
/*     */     //   57: ldc 45
/*     */     //   59: astore 5
/*     */     //   61: goto +26 -> 87
/*     */     //   64: new 47	java/lang/StringBuilder
/*     */     //   67: dup
/*     */     //   68: ldc 49
/*     */     //   70: invokespecial 51	java/lang/StringBuilder:<init>	(Ljava/lang/String;)V
/*     */     //   73: iload_2
/*     */     //   74: invokevirtual 54	java/lang/StringBuilder:append	(I)Ljava/lang/StringBuilder;
/*     */     //   77: ldc 58
/*     */     //   79: invokevirtual 60	java/lang/StringBuilder:append	(Ljava/lang/String;)Ljava/lang/StringBuilder;
/*     */     //   82: invokevirtual 63	java/lang/StringBuilder:toString	()Ljava/lang/String;
/*     */     //   85: astore 5
/*     */     //   87: new 36	java/lang/StringBuffer
/*     */     //   90: dup
/*     */     //   91: invokespecial 38	java/lang/StringBuffer:<init>	()V
/*     */     //   94: astore 6
/*     */     //   96: aload 6
/*     */     //   98: ldc_w 561
/*     */     //   101: invokevirtual 69	java/lang/StringBuffer:append	(Ljava/lang/String;)Ljava/lang/StringBuffer;
/*     */     //   104: aload 4
/*     */     //   106: invokevirtual 69	java/lang/StringBuffer:append	(Ljava/lang/String;)Ljava/lang/StringBuffer;
/*     */     //   109: ldc_w 563
/*     */     //   112: invokevirtual 69	java/lang/StringBuffer:append	(Ljava/lang/String;)Ljava/lang/StringBuffer;
/*     */     //   115: pop
/*     */     //   116: aload 6
/*     */     //   118: ldc_w 565
/*     */     //   121: invokevirtual 69	java/lang/StringBuffer:append	(Ljava/lang/String;)Ljava/lang/StringBuffer;
/*     */     //   124: aload_3
/*     */     //   125: invokevirtual 69	java/lang/StringBuffer:append	(Ljava/lang/String;)Ljava/lang/StringBuffer;
/*     */     //   128: ldc_w 567
/*     */     //   131: invokevirtual 69	java/lang/StringBuffer:append	(Ljava/lang/String;)Ljava/lang/StringBuffer;
/*     */     //   134: iload_2
/*     */     //   135: invokevirtual 399	java/lang/StringBuffer:append	(I)Ljava/lang/StringBuffer;
/*     */     //   138: ldc_w 402
/*     */     //   141: invokevirtual 69	java/lang/StringBuffer:append	(Ljava/lang/String;)Ljava/lang/StringBuffer;
/*     */     //   144: pop
/*     */     //   145: aload 6
/*     */     //   147: ldc_w 569
/*     */     //   150: invokevirtual 69	java/lang/StringBuffer:append	(Ljava/lang/String;)Ljava/lang/StringBuffer;
/*     */     //   153: pop
/*     */     //   154: aload 6
/*     */     //   156: ldc_w 571
/*     */     //   159: invokevirtual 69	java/lang/StringBuffer:append	(Ljava/lang/String;)Ljava/lang/StringBuffer;
/*     */     //   162: aload_1
/*     */     //   163: invokevirtual 410	com/claro/transfer/MobileTO:getSecuencia	()Ljava/lang/String;
/*     */     //   166: invokevirtual 69	java/lang/StringBuffer:append	(Ljava/lang/String;)Ljava/lang/StringBuffer;
/*     */     //   169: pop
/*     */     //   170: aload 6
/*     */     //   172: ldc_w 573
/*     */     //   175: invokevirtual 69	java/lang/StringBuffer:append	(Ljava/lang/String;)Ljava/lang/StringBuffer;
/*     */     //   178: pop
/*     */     //   179: aload 6
/*     */     //   181: ldc_w 575
/*     */     //   184: invokevirtual 69	java/lang/StringBuffer:append	(Ljava/lang/String;)Ljava/lang/StringBuffer;
/*     */     //   187: pop
/*     */     //   188: new 36	java/lang/StringBuffer
/*     */     //   191: dup
/*     */     //   192: invokespecial 38	java/lang/StringBuffer:<init>	()V
/*     */     //   195: astore 7
/*     */     //   197: aload 7
/*     */     //   199: ldc_w 577
/*     */     //   202: invokevirtual 69	java/lang/StringBuffer:append	(Ljava/lang/String;)Ljava/lang/StringBuffer;
/*     */     //   205: pop
/*     */     //   206: aload 7
/*     */     //   208: ldc_w 579
/*     */     //   211: invokevirtual 69	java/lang/StringBuffer:append	(Ljava/lang/String;)Ljava/lang/StringBuffer;
/*     */     //   214: pop
/*     */     //   215: aload 7
/*     */     //   217: ldc_w 581
/*     */     //   220: invokevirtual 69	java/lang/StringBuffer:append	(Ljava/lang/String;)Ljava/lang/StringBuffer;
/*     */     //   223: pop
/*     */     //   224: aload 7
/*     */     //   226: ldc_w 381
/*     */     //   229: invokevirtual 69	java/lang/StringBuffer:append	(Ljava/lang/String;)Ljava/lang/StringBuffer;
/*     */     //   232: aload 4
/*     */     //   234: invokevirtual 69	java/lang/StringBuffer:append	(Ljava/lang/String;)Ljava/lang/StringBuffer;
/*     */     //   237: ldc_w 583
/*     */     //   240: invokevirtual 69	java/lang/StringBuffer:append	(Ljava/lang/String;)Ljava/lang/StringBuffer;
/*     */     //   243: pop
/*     */     //   244: aload 7
/*     */     //   246: ldc_w 585
/*     */     //   249: invokevirtual 69	java/lang/StringBuffer:append	(Ljava/lang/String;)Ljava/lang/StringBuffer;
/*     */     //   252: pop
/*     */     //   253: aload 7
/*     */     //   255: ldc_w 587
/*     */     //   258: invokevirtual 69	java/lang/StringBuffer:append	(Ljava/lang/String;)Ljava/lang/StringBuffer;
/*     */     //   261: pop
/*     */     //   262: aload 7
/*     */     //   264: ldc_w 589
/*     */     //   267: invokevirtual 69	java/lang/StringBuffer:append	(Ljava/lang/String;)Ljava/lang/StringBuffer;
/*     */     //   270: pop
/*     */     //   271: aload 7
/*     */     //   273: ldc_w 591
/*     */     //   276: invokevirtual 69	java/lang/StringBuffer:append	(Ljava/lang/String;)Ljava/lang/StringBuffer;
/*     */     //   279: pop
/*     */     //   280: aload 7
/*     */     //   282: ldc_w 593
/*     */     //   285: invokevirtual 69	java/lang/StringBuffer:append	(Ljava/lang/String;)Ljava/lang/StringBuffer;
/*     */     //   288: pop
/*     */     //   289: new 36	java/lang/StringBuffer
/*     */     //   292: dup
/*     */     //   293: invokespecial 38	java/lang/StringBuffer:<init>	()V
/*     */     //   296: astore 8
/*     */     //   298: aload 8
/*     */     //   300: ldc_w 595
/*     */     //   303: invokevirtual 69	java/lang/StringBuffer:append	(Ljava/lang/String;)Ljava/lang/StringBuffer;
/*     */     //   306: pop
/*     */     //   307: aload 8
/*     */     //   309: ldc_w 381
/*     */     //   312: invokevirtual 69	java/lang/StringBuffer:append	(Ljava/lang/String;)Ljava/lang/StringBuffer;
/*     */     //   315: aload 5
/*     */     //   317: invokevirtual 69	java/lang/StringBuffer:append	(Ljava/lang/String;)Ljava/lang/StringBuffer;
/*     */     //   320: ldc_w 597
/*     */     //   323: invokevirtual 69	java/lang/StringBuffer:append	(Ljava/lang/String;)Ljava/lang/StringBuffer;
/*     */     //   326: pop
/*     */     //   327: aload 8
/*     */     //   329: ldc_w 599
/*     */     //   332: invokevirtual 69	java/lang/StringBuffer:append	(Ljava/lang/String;)Ljava/lang/StringBuffer;
/*     */     //   335: pop
/*     */     //   336: aload 8
/*     */     //   338: ldc_w 601
/*     */     //   341: invokevirtual 69	java/lang/StringBuffer:append	(Ljava/lang/String;)Ljava/lang/StringBuffer;
/*     */     //   344: pop
/*     */     //   345: aload 8
/*     */     //   347: ldc_w 603
/*     */     //   350: invokevirtual 69	java/lang/StringBuffer:append	(Ljava/lang/String;)Ljava/lang/StringBuffer;
/*     */     //   353: pop
/*     */     //   354: aconst_null
/*     */     //   355: astore 9
/*     */     //   357: aconst_null
/*     */     //   358: astore 10
/*     */     //   360: aconst_null
/*     */     //   361: astore 11
/*     */     //   363: aconst_null
/*     */     //   364: astore 12
/*     */     //   366: aconst_null
/*     */     //   367: astore 13
/*     */     //   369: aconst_null
/*     */     //   370: astore 14
/*     */     //   372: aconst_null
/*     */     //   373: astore 15
/*     */     //   375: iconst_1
/*     */     //   376: istore 16
/*     */     //   378: iconst_0
/*     */     //   379: istore 17
/*     */     //   381: iload_2
/*     */     //   382: iconst_4
/*     */     //   383: if_icmpeq +14 -> 397
/*     */     //   386: iload_2
/*     */     //   387: iconst_5
/*     */     //   388: if_icmpeq +9 -> 397
/*     */     //   391: iload_2
/*     */     //   392: bipush 9
/*     */     //   394: if_icmpne +17 -> 411
/*     */     //   397: invokestatic 298	com/claro/util/ServiceLocator:getInstance	()Lcom/claro/util/ServiceLocator;
/*     */     //   400: getstatic 304	com/claro/util/ServiceLocator:jdbcMobile459	Ljava/lang/String;
/*     */     //   403: invokevirtual 307	com/claro/util/ServiceLocator:getConnection	(Ljava/lang/String;)Ljava/sql/Connection;
/*     */     //   406: astore 15
/*     */     //   408: goto +14 -> 422
/*     */     //   411: invokestatic 298	com/claro/util/ServiceLocator:getInstance	()Lcom/claro/util/ServiceLocator;
/*     */     //   414: getstatic 311	com/claro/util/ServiceLocator:jdbcMobile	Ljava/lang/String;
/*     */     //   417: invokevirtual 307	com/claro/util/ServiceLocator:getConnection	(Ljava/lang/String;)Ljava/sql/Connection;
/*     */     //   420: astore 15
/*     */     //   422: aload 15
/*     */     //   424: aload 6
/*     */     //   426: invokevirtual 151	java/lang/StringBuffer:toString	()Ljava/lang/String;
/*     */     //   429: invokeinterface 605 2 0
/*     */     //   434: astore 9
/*     */     //   436: aload 15
/*     */     //   438: aload 7
/*     */     //   440: invokevirtual 151	java/lang/StringBuffer:toString	()Ljava/lang/String;
/*     */     //   443: invokeinterface 605 2 0
/*     */     //   448: astore 10
/*     */     //   450: aload 15
/*     */     //   452: aload 8
/*     */     //   454: invokevirtual 151	java/lang/StringBuffer:toString	()Ljava/lang/String;
/*     */     //   457: invokeinterface 605 2 0
/*     */     //   462: astore 11
/*     */     //   464: aload 9
/*     */     //   466: invokeinterface 609 1 0
/*     */     //   471: astore 12
/*     */     //   473: new 614	java/util/ArrayList
/*     */     //   476: dup
/*     */     //   477: invokespecial 616	java/util/ArrayList:<init>	()V
/*     */     //   480: astore 18
/*     */     //   482: iconst_0
/*     */     //   483: istore 19
/*     */     //   485: goto +181 -> 666
/*     */     //   488: iinc 19 1
/*     */     //   491: aload 12
/*     */     //   493: iconst_1
/*     */     //   494: invokeinterface 203 2 0
/*     */     //   499: astore 20
/*     */     //   501: aload 12
/*     */     //   503: iconst_2
/*     */     //   504: invokeinterface 617 2 0
/*     */     //   509: astore 21
/*     */     //   511: aload 12
/*     */     //   513: iconst_3
/*     */     //   514: invokeinterface 617 2 0
/*     */     //   519: astore 22
/*     */     //   521: aload 10
/*     */     //   523: invokeinterface 621 1 0
/*     */     //   528: aload 10
/*     */     //   530: iconst_1
/*     */     //   531: aload 20
/*     */     //   533: invokeinterface 624 3 0
/*     */     //   538: aload 10
/*     */     //   540: iconst_2
/*     */     //   541: aload 21
/*     */     //   543: invokeinterface 627 3 0
/*     */     //   548: aload 10
/*     */     //   550: iconst_3
/*     */     //   551: aload 22
/*     */     //   553: invokeinterface 627 3 0
/*     */     //   558: aload 10
/*     */     //   560: iconst_4
/*     */     //   561: aload_1
/*     */     //   562: invokevirtual 410	com/claro/transfer/MobileTO:getSecuencia	()Ljava/lang/String;
/*     */     //   565: ifnull +13 -> 578
/*     */     //   568: aload_1
/*     */     //   569: invokevirtual 410	com/claro/transfer/MobileTO:getSecuencia	()Ljava/lang/String;
/*     */     //   572: invokestatic 631	java/lang/Integer:parseInt	(Ljava/lang/String;)I
/*     */     //   575: goto +4 -> 579
/*     */     //   578: iconst_1
/*     */     //   579: invokeinterface 637 3 0
/*     */     //   584: aload 10
/*     */     //   586: invokeinterface 609 1 0
/*     */     //   591: astore 13
/*     */     //   593: aload 13
/*     */     //   595: invokeinterface 158 1 0
/*     */     //   600: ifeq +40 -> 640
/*     */     //   603: new 641	com/claro/transfer/FacturaTO
/*     */     //   606: dup
/*     */     //   607: invokespecial 643	com/claro/transfer/FacturaTO:<init>	()V
/*     */     //   610: astore 23
/*     */     //   612: aload 23
/*     */     //   614: aload 13
/*     */     //   616: iconst_1
/*     */     //   617: invokeinterface 644 2 0
/*     */     //   622: invokevirtual 648	com/claro/transfer/FacturaTO:setMonto	(D)V
/*     */     //   625: aload 23
/*     */     //   627: aload 22
/*     */     //   629: invokevirtual 652	com/claro/transfer/FacturaTO:setFechaFactura	(Ljava/math/BigDecimal;)V
/*     */     //   632: aload 18
/*     */     //   634: aload 23
/*     */     //   636: invokevirtual 656	java/util/ArrayList:add	(Ljava/lang/Object;)Z
/*     */     //   639: pop
/*     */     //   640: aload 13
/*     */     //   642: ifnull +18 -> 660
/*     */     //   645: aload 13
/*     */     //   647: invokeinterface 264 1 0
/*     */     //   652: aconst_null
/*     */     //   653: astore 13
/*     */     //   655: goto +5 -> 660
/*     */     //   658: astore 23
/*     */     //   660: iinc 16 1
/*     */     //   663: iinc 17 1
/*     */     //   666: aload 12
/*     */     //   668: invokeinterface 158 1 0
/*     */     //   673: ifne -185 -> 488
/*     */     //   676: iload 17
/*     */     //   678: ifne +35 -> 713
/*     */     //   681: aload_1
/*     */     //   682: iconst_m1
/*     */     //   683: new 47	java/lang/StringBuilder
/*     */     //   686: dup
/*     */     //   687: ldc_w 659
/*     */     //   690: invokespecial 51	java/lang/StringBuilder:<init>	(Ljava/lang/String;)V
/*     */     //   693: iload_2
/*     */     //   694: invokevirtual 54	java/lang/StringBuilder:append	(I)Ljava/lang/StringBuilder;
/*     */     //   697: ldc_w 661
/*     */     //   700: invokevirtual 60	java/lang/StringBuilder:append	(Ljava/lang/String;)Ljava/lang/StringBuilder;
/*     */     //   703: aload_3
/*     */     //   704: invokevirtual 60	java/lang/StringBuilder:append	(Ljava/lang/String;)Ljava/lang/StringBuilder;
/*     */     //   707: invokevirtual 63	java/lang/StringBuilder:toString	()Ljava/lang/String;
/*     */     //   710: invokevirtual 231	com/claro/transfer/MobileTO:agregaMensaje	(ILjava/lang/String;)V
/*     */     //   713: aload_1
/*     */     //   714: aload 18
/*     */     //   716: invokevirtual 663	com/claro/transfer/MobileTO:setFacturas	(Ljava/util/ArrayList;)V
/*     */     //   719: aload_1
/*     */     //   720: aload_1
/*     */     //   721: invokevirtual 667	com/claro/transfer/MobileTO:getPromedio	()D
/*     */     //   724: invokestatic 671	java/lang/Double:toString	(D)Ljava/lang/String;
/*     */     //   727: invokevirtual 676	com/claro/transfer/MobileTO:setSPromFacturaAV	(Ljava/lang/String;)V
/*     */     //   730: aload 11
/*     */     //   732: invokeinterface 621 1 0
/*     */     //   737: aload 11
/*     */     //   739: iconst_1
/*     */     //   740: aload_3
/*     */     //   741: invokeinterface 624 3 0
/*     */     //   746: aload 11
/*     */     //   748: invokeinterface 609 1 0
/*     */     //   753: astore 14
/*     */     //   755: aload 14
/*     */     //   757: invokeinterface 158 1 0
/*     */     //   762: ifeq +15 -> 777
/*     */     //   765: aload_1
/*     */     //   766: aload 14
/*     */     //   768: iconst_1
/*     */     //   769: invokeinterface 679 2 0
/*     */     //   774: invokevirtual 683	com/claro/transfer/MobileTO:setNoBajas	(I)V
/*     */     //   777: aload 14
/*     */     //   779: ifnull +204 -> 983
/*     */     //   782: aload 14
/*     */     //   784: invokeinterface 264 1 0
/*     */     //   789: aconst_null
/*     */     //   790: astore 14
/*     */     //   792: goto +191 -> 983
/*     */     //   795: astore 20
/*     */     //   797: goto +186 -> 983
/*     */     //   800: astore 18
/*     */     //   802: new 34	com/claro/exception/CAException
/*     */     //   805: dup
/*     */     //   806: iconst_m1
/*     */     //   807: new 47	java/lang/StringBuilder
/*     */     //   810: dup
/*     */     //   811: ldc_w 687
/*     */     //   814: invokespecial 51	java/lang/StringBuilder:<init>	(Ljava/lang/String;)V
/*     */     //   817: aload 18
/*     */     //   819: invokevirtual 249	java/sql/SQLException:toString	()Ljava/lang/String;
/*     */     //   822: invokevirtual 60	java/lang/StringBuilder:append	(Ljava/lang/String;)Ljava/lang/StringBuilder;
/*     */     //   825: ldc -4
/*     */     //   827: invokevirtual 60	java/lang/StringBuilder:append	(Ljava/lang/String;)Ljava/lang/StringBuilder;
/*     */     //   830: invokevirtual 63	java/lang/StringBuilder:toString	()Ljava/lang/String;
/*     */     //   833: aload 18
/*     */     //   835: invokespecial 254	com/claro/exception/CAException:<init>	(ILjava/lang/String;Ljava/lang/Exception;)V
/*     */     //   838: athrow
/*     */     //   839: astore 18
/*     */     //   841: new 34	com/claro/exception/CAException
/*     */     //   844: dup
/*     */     //   845: iconst_m1
/*     */     //   846: new 47	java/lang/StringBuilder
/*     */     //   849: dup
/*     */     //   850: ldc_w 689
/*     */     //   853: invokespecial 51	java/lang/StringBuilder:<init>	(Ljava/lang/String;)V
/*     */     //   856: aload 18
/*     */     //   858: invokevirtual 261	java/lang/Exception:toString	()Ljava/lang/String;
/*     */     //   861: invokevirtual 60	java/lang/StringBuilder:append	(Ljava/lang/String;)Ljava/lang/StringBuilder;
/*     */     //   864: ldc -4
/*     */     //   866: invokevirtual 60	java/lang/StringBuilder:append	(Ljava/lang/String;)Ljava/lang/StringBuilder;
/*     */     //   869: invokevirtual 63	java/lang/StringBuilder:toString	()Ljava/lang/String;
/*     */     //   872: aload 18
/*     */     //   874: invokespecial 254	com/claro/exception/CAException:<init>	(ILjava/lang/String;Ljava/lang/Exception;)V
/*     */     //   877: athrow
/*     */     //   878: astore 24
/*     */     //   880: aload 13
/*     */     //   882: ifnull +18 -> 900
/*     */     //   885: aload 13
/*     */     //   887: invokeinterface 264 1 0
/*     */     //   892: aconst_null
/*     */     //   893: astore 13
/*     */     //   895: goto +5 -> 900
/*     */     //   898: astore 25
/*     */     //   900: aload 12
/*     */     //   902: ifnull +18 -> 920
/*     */     //   905: aload 12
/*     */     //   907: invokeinterface 264 1 0
/*     */     //   912: aconst_null
/*     */     //   913: astore 12
/*     */     //   915: goto +5 -> 920
/*     */     //   918: astore 25
/*     */     //   920: aload 10
/*     */     //   922: ifnull +18 -> 940
/*     */     //   925: aload 10
/*     */     //   927: invokeinterface 691 1 0
/*     */     //   932: aconst_null
/*     */     //   933: astore 10
/*     */     //   935: goto +5 -> 940
/*     */     //   938: astore 25
/*     */     //   940: aload 9
/*     */     //   942: ifnull +18 -> 960
/*     */     //   945: aload 9
/*     */     //   947: invokeinterface 691 1 0
/*     */     //   952: aconst_null
/*     */     //   953: astore 9
/*     */     //   955: goto +5 -> 960
/*     */     //   958: astore 25
/*     */     //   960: aload 15
/*     */     //   962: ifnull +18 -> 980
/*     */     //   965: aload 15
/*     */     //   967: invokeinterface 321 1 0
/*     */     //   972: aconst_null
/*     */     //   973: astore 15
/*     */     //   975: goto +5 -> 980
/*     */     //   978: astore 25
/*     */     //   980: aload 24
/*     */     //   982: athrow
/*     */     //   983: aload 13
/*     */     //   985: ifnull +18 -> 1003
/*     */     //   988: aload 13
/*     */     //   990: invokeinterface 264 1 0
/*     */     //   995: aconst_null
/*     */     //   996: astore 13
/*     */     //   998: goto +5 -> 1003
/*     */     //   1001: astore 25
/*     */     //   1003: aload 12
/*     */     //   1005: ifnull +18 -> 1023
/*     */     //   1008: aload 12
/*     */     //   1010: invokeinterface 264 1 0
/*     */     //   1015: aconst_null
/*     */     //   1016: astore 12
/*     */     //   1018: goto +5 -> 1023
/*     */     //   1021: astore 25
/*     */     //   1023: aload 10
/*     */     //   1025: ifnull +18 -> 1043
/*     */     //   1028: aload 10
/*     */     //   1030: invokeinterface 691 1 0
/*     */     //   1035: aconst_null
/*     */     //   1036: astore 10
/*     */     //   1038: goto +5 -> 1043
/*     */     //   1041: astore 25
/*     */     //   1043: aload 9
/*     */     //   1045: ifnull +18 -> 1063
/*     */     //   1048: aload 9
/*     */     //   1050: invokeinterface 691 1 0
/*     */     //   1055: aconst_null
/*     */     //   1056: astore 9
/*     */     //   1058: goto +5 -> 1063
/*     */     //   1061: astore 25
/*     */     //   1063: aload 15
/*     */     //   1065: ifnull +18 -> 1083
/*     */     //   1068: aload 15
/*     */     //   1070: invokeinterface 321 1 0
/*     */     //   1075: aconst_null
/*     */     //   1076: astore 15
/*     */     //   1078: goto +5 -> 1083
/*     */     //   1081: astore 25
/*     */     //   1083: return
/*     */     // Line number table:
/*     */     //   Java source line #285	-> byte code offset #0
/*     */     //   Java source line #286	-> byte code offset #13
/*     */     //   Java source line #287	-> byte code offset #27
/*     */     //   Java source line #289	-> byte code offset #51
/*     */     //   Java source line #290	-> byte code offset #64
/*     */     //   Java source line #292	-> byte code offset #87
/*     */     //   Java source line #294	-> byte code offset #96
/*     */     //   Java source line #295	-> byte code offset #116
/*     */     //   Java source line #296	-> byte code offset #145
/*     */     //   Java source line #297	-> byte code offset #154
/*     */     //   Java source line #298	-> byte code offset #170
/*     */     //   Java source line #299	-> byte code offset #179
/*     */     //   Java source line #302	-> byte code offset #188
/*     */     //   Java source line #303	-> byte code offset #197
/*     */     //   Java source line #304	-> byte code offset #206
/*     */     //   Java source line #305	-> byte code offset #215
/*     */     //   Java source line #306	-> byte code offset #224
/*     */     //   Java source line #307	-> byte code offset #244
/*     */     //   Java source line #308	-> byte code offset #253
/*     */     //   Java source line #309	-> byte code offset #262
/*     */     //   Java source line #310	-> byte code offset #271
/*     */     //   Java source line #311	-> byte code offset #280
/*     */     //   Java source line #313	-> byte code offset #289
/*     */     //   Java source line #315	-> byte code offset #298
/*     */     //   Java source line #316	-> byte code offset #307
/*     */     //   Java source line #317	-> byte code offset #327
/*     */     //   Java source line #318	-> byte code offset #336
/*     */     //   Java source line #319	-> byte code offset #345
/*     */     //   Java source line #321	-> byte code offset #354
/*     */     //   Java source line #322	-> byte code offset #363
/*     */     //   Java source line #323	-> byte code offset #366
/*     */     //   Java source line #324	-> byte code offset #369
/*     */     //   Java source line #326	-> byte code offset #372
/*     */     //   Java source line #327	-> byte code offset #375
/*     */     //   Java source line #330	-> byte code offset #381
/*     */     //   Java source line #331	-> byte code offset #397
/*     */     //   Java source line #333	-> byte code offset #411
/*     */     //   Java source line #335	-> byte code offset #422
/*     */     //   Java source line #336	-> byte code offset #436
/*     */     //   Java source line #337	-> byte code offset #450
/*     */     //   Java source line #339	-> byte code offset #464
/*     */     //   Java source line #341	-> byte code offset #473
/*     */     //   Java source line #342	-> byte code offset #482
/*     */     //   Java source line #343	-> byte code offset #485
/*     */     //   Java source line #344	-> byte code offset #488
/*     */     //   Java source line #345	-> byte code offset #491
/*     */     //   Java source line #346	-> byte code offset #501
/*     */     //   Java source line #347	-> byte code offset #511
/*     */     //   Java source line #349	-> byte code offset #521
/*     */     //   Java source line #350	-> byte code offset #528
/*     */     //   Java source line #351	-> byte code offset #538
/*     */     //   Java source line #352	-> byte code offset #548
/*     */     //   Java source line #353	-> byte code offset #558
/*     */     //   Java source line #354	-> byte code offset #584
/*     */     //   Java source line #356	-> byte code offset #593
/*     */     //   Java source line #357	-> byte code offset #603
/*     */     //   Java source line #358	-> byte code offset #612
/*     */     //   Java source line #359	-> byte code offset #625
/*     */     //   Java source line #360	-> byte code offset #632
/*     */     //   Java source line #362	-> byte code offset #640
/*     */     //   Java source line #364	-> byte code offset #660
/*     */     //   Java source line #365	-> byte code offset #663
/*     */     //   Java source line #343	-> byte code offset #666
/*     */     //   Java source line #367	-> byte code offset #676
/*     */     //   Java source line #368	-> byte code offset #681
/*     */     //   Java source line #370	-> byte code offset #713
/*     */     //   Java source line #371	-> byte code offset #719
/*     */     //   Java source line #372	-> byte code offset #730
/*     */     //   Java source line #373	-> byte code offset #737
/*     */     //   Java source line #374	-> byte code offset #746
/*     */     //   Java source line #376	-> byte code offset #755
/*     */     //   Java source line #377	-> byte code offset #765
/*     */     //   Java source line #379	-> byte code offset #777
/*     */     //   Java source line #381	-> byte code offset #800
/*     */     //   Java source line #382	-> byte code offset #802
/*     */     //   Java source line #383	-> byte code offset #839
/*     */     //   Java source line #384	-> byte code offset #841
/*     */     //   Java source line #385	-> byte code offset #878
/*     */     //   Java source line #386	-> byte code offset #880
/*     */     //   Java source line #387	-> byte code offset #900
/*     */     //   Java source line #388	-> byte code offset #920
/*     */     //   Java source line #389	-> byte code offset #940
/*     */     //   Java source line #390	-> byte code offset #960
/*     */     //   Java source line #391	-> byte code offset #980
/*     */     //   Java source line #386	-> byte code offset #983
/*     */     //   Java source line #387	-> byte code offset #1003
/*     */     //   Java source line #388	-> byte code offset #1023
/*     */     //   Java source line #389	-> byte code offset #1043
/*     */     //   Java source line #390	-> byte code offset #1063
/*     */     //   Java source line #392	-> byte code offset #1083
/*     */     // Local variable table:
/*     */     //   start	length	slot	name	signature
/*     */     //   0	1084	0	this	ConsultaM2KDAO
/*     */     //   0	1084	1	mobileTO	MobileTO
/*     */     //   0	1084	2	region	int
/*     */     //   0	1084	3	cuenta	String
/*     */     //   8	3	4	mercadoM2K	String
/*     */     //   22	3	4	mercadoM2K	String
/*     */     //   49	184	4	mercadoM2K	String
/*     */     //   59	3	5	mertelM2K	String
/*     */     //   85	231	5	mertelM2K	String
/*     */     //   94	331	6	query1	StringBuffer
/*     */     //   195	244	7	query2	StringBuffer
/*     */     //   296	157	8	query3	StringBuffer
/*     */     //   355	702	9	statementSelectFecFac	java.sql.PreparedStatement
/*     */     //   358	679	10	statementFactura	java.sql.PreparedStatement
/*     */     //   361	386	11	statementBajaClimo	java.sql.PreparedStatement
/*     */     //   364	653	12	resultSetFecFac	java.sql.ResultSet
/*     */     //   367	630	13	resultSetFactura	java.sql.ResultSet
/*     */     //   370	421	14	resultSetBajaClimo	java.sql.ResultSet
/*     */     //   373	704	15	connection	Connection
/*     */     //   376	285	16	iNoFactura	int
/*     */     //   379	298	17	iCount	int
/*     */     //   480	235	18	facturas	java.util.ArrayList<com.claro.transfer.FacturaTO>
/*     */     //   800	34	18	e	SQLException
/*     */     //   839	34	18	e	Exception
/*     */     //   483	6	19	i	int
/*     */     //   499	33	20	sRegion	String
/*     */     //   795	1	20	localException2	Exception
/*     */     //   509	33	21	cuentaBig	java.math.BigDecimal
/*     */     //   519	109	22	fechaFac	java.math.BigDecimal
/*     */     //   610	25	23	facturaTO	com.claro.transfer.FacturaTO
/*     */     //   658	1	23	localException1	Exception
/*     */     //   878	103	24	localObject	Object
/*     */     //   898	1	25	localException3	Exception
/*     */     //   918	1	25	localException4	Exception
/*     */     //   938	1	25	localException5	Exception
/*     */     //   958	1	25	localException6	Exception
/*     */     //   978	1	25	localException7	Exception
/*     */     //   1001	1	25	localException8	Exception
/*     */     //   1021	1	25	localException9	Exception
/*     */     //   1041	1	25	localException10	Exception
/*     */     //   1061	1	25	localException11	Exception
/*     */     //   1081	1	25	localException12	Exception
/*     */     // Exception table:
/*     */     //   from	to	target	type
/*     */     //   645	655	658	java/lang/Exception
/*     */     //   782	792	795	java/lang/Exception
/*     */     //   381	797	800	java/sql/SQLException
/*     */     //   381	797	839	java/lang/Exception
/*     */     //   381	878	878	finally
/*     */     //   885	895	898	java/lang/Exception
/*     */     //   905	915	918	java/lang/Exception
/*     */     //   925	935	938	java/lang/Exception
/*     */     //   945	955	958	java/lang/Exception
/*     */     //   965	975	978	java/lang/Exception
/*     */     //   988	998	1001	java/lang/Exception
/*     */     //   1008	1018	1021	java/lang/Exception
/*     */     //   1028	1038	1041	java/lang/Exception
/*     */     //   1048	1058	1061	java/lang/Exception
/*     */     //   1068	1078	1081	java/lang/Exception
/*     */   }
/*     */   
/*     */   /* Error */
/*     */   public MobileTO consultaPorCuenta(String lCta, int nReg)
/*     */     throws CAException
/*     */   {
/*     */     // Byte code:
/*     */     //   0: aconst_null
/*     */     //   1: astore_3
/*     */     //   2: aconst_null
/*     */     //   3: astore 4
/*     */     //   5: aconst_null
/*     */     //   6: astore 5
/*     */     //   8: aconst_null
/*     */     //   9: astore 6
/*     */     //   11: aconst_null
/*     */     //   12: astore 7
/*     */     //   14: iload_2
/*     */     //   15: iconst_4
/*     */     //   16: if_icmpne +11 -> 27
/*     */     //   19: ldc_w 337
/*     */     //   22: astore 8
/*     */     //   24: goto +41 -> 65
/*     */     //   27: iload_2
/*     */     //   28: bipush 9
/*     */     //   30: if_icmpne +11 -> 41
/*     */     //   33: ldc_w 339
/*     */     //   36: astore 8
/*     */     //   38: goto +27 -> 65
/*     */     //   41: new 47	java/lang/StringBuilder
/*     */     //   44: dup
/*     */     //   45: ldc 49
/*     */     //   47: invokespecial 51	java/lang/StringBuilder:<init>	(Ljava/lang/String;)V
/*     */     //   50: iload_2
/*     */     //   51: invokevirtual 54	java/lang/StringBuilder:append	(I)Ljava/lang/StringBuilder;
/*     */     //   54: ldc_w 341
/*     */     //   57: invokevirtual 60	java/lang/StringBuilder:append	(Ljava/lang/String;)Ljava/lang/StringBuilder;
/*     */     //   60: invokevirtual 63	java/lang/StringBuilder:toString	()Ljava/lang/String;
/*     */     //   63: astore 8
/*     */     //   65: iload_2
/*     */     //   66: bipush 9
/*     */     //   68: if_icmpne +10 -> 78
/*     */     //   71: ldc 45
/*     */     //   73: astore 9
/*     */     //   75: goto +26 -> 101
/*     */     //   78: new 47	java/lang/StringBuilder
/*     */     //   81: dup
/*     */     //   82: ldc 49
/*     */     //   84: invokespecial 51	java/lang/StringBuilder:<init>	(Ljava/lang/String;)V
/*     */     //   87: iload_2
/*     */     //   88: invokevirtual 54	java/lang/StringBuilder:append	(I)Ljava/lang/StringBuilder;
/*     */     //   91: ldc 58
/*     */     //   93: invokevirtual 60	java/lang/StringBuilder:append	(Ljava/lang/String;)Ljava/lang/StringBuilder;
/*     */     //   96: invokevirtual 63	java/lang/StringBuilder:toString	()Ljava/lang/String;
/*     */     //   99: astore 9
/*     */     //   101: new 47	java/lang/StringBuilder
/*     */     //   104: dup
/*     */     //   105: ldc_w 719
/*     */     //   108: invokespecial 51	java/lang/StringBuilder:<init>	(Ljava/lang/String;)V
/*     */     //   111: aload 8
/*     */     //   113: invokevirtual 60	java/lang/StringBuilder:append	(Ljava/lang/String;)Ljava/lang/StringBuilder;
/*     */     //   116: ldc_w 721
/*     */     //   119: invokevirtual 60	java/lang/StringBuilder:append	(Ljava/lang/String;)Ljava/lang/StringBuilder;
/*     */     //   122: ldc_w 723
/*     */     //   125: invokevirtual 60	java/lang/StringBuilder:append	(Ljava/lang/String;)Ljava/lang/StringBuilder;
/*     */     //   128: aload 8
/*     */     //   130: invokevirtual 60	java/lang/StringBuilder:append	(Ljava/lang/String;)Ljava/lang/StringBuilder;
/*     */     //   133: ldc_w 725
/*     */     //   136: invokevirtual 60	java/lang/StringBuilder:append	(Ljava/lang/String;)Ljava/lang/StringBuilder;
/*     */     //   139: ldc_w 727
/*     */     //   142: invokevirtual 60	java/lang/StringBuilder:append	(Ljava/lang/String;)Ljava/lang/StringBuilder;
/*     */     //   145: iload_2
/*     */     //   146: invokevirtual 54	java/lang/StringBuilder:append	(I)Ljava/lang/StringBuilder;
/*     */     //   149: ldc_w 729
/*     */     //   152: invokevirtual 60	java/lang/StringBuilder:append	(Ljava/lang/String;)Ljava/lang/StringBuilder;
/*     */     //   155: aload_1
/*     */     //   156: invokevirtual 60	java/lang/StringBuilder:append	(Ljava/lang/String;)Ljava/lang/StringBuilder;
/*     */     //   159: ldc_w 731
/*     */     //   162: invokevirtual 60	java/lang/StringBuilder:append	(Ljava/lang/String;)Ljava/lang/StringBuilder;
/*     */     //   165: ldc_w 733
/*     */     //   168: invokevirtual 60	java/lang/StringBuilder:append	(Ljava/lang/String;)Ljava/lang/StringBuilder;
/*     */     //   171: aload 8
/*     */     //   173: invokevirtual 60	java/lang/StringBuilder:append	(Ljava/lang/String;)Ljava/lang/StringBuilder;
/*     */     //   176: ldc_w 419
/*     */     //   179: invokevirtual 60	java/lang/StringBuilder:append	(Ljava/lang/String;)Ljava/lang/StringBuilder;
/*     */     //   182: ldc_w 735
/*     */     //   185: invokevirtual 60	java/lang/StringBuilder:append	(Ljava/lang/String;)Ljava/lang/StringBuilder;
/*     */     //   188: iload_2
/*     */     //   189: invokevirtual 54	java/lang/StringBuilder:append	(I)Ljava/lang/StringBuilder;
/*     */     //   192: ldc_w 402
/*     */     //   195: invokevirtual 60	java/lang/StringBuilder:append	(Ljava/lang/String;)Ljava/lang/StringBuilder;
/*     */     //   198: ldc_w 737
/*     */     //   201: invokevirtual 60	java/lang/StringBuilder:append	(Ljava/lang/String;)Ljava/lang/StringBuilder;
/*     */     //   204: aload_1
/*     */     //   205: invokevirtual 60	java/lang/StringBuilder:append	(Ljava/lang/String;)Ljava/lang/StringBuilder;
/*     */     //   208: ldc_w 427
/*     */     //   211: invokevirtual 60	java/lang/StringBuilder:append	(Ljava/lang/String;)Ljava/lang/StringBuilder;
/*     */     //   214: invokevirtual 63	java/lang/StringBuilder:toString	()Ljava/lang/String;
/*     */     //   217: astore 7
/*     */     //   219: iload_2
/*     */     //   220: iconst_4
/*     */     //   221: if_icmpeq +14 -> 235
/*     */     //   224: iload_2
/*     */     //   225: iconst_5
/*     */     //   226: if_icmpeq +9 -> 235
/*     */     //   229: iload_2
/*     */     //   230: bipush 9
/*     */     //   232: if_icmpne +16 -> 248
/*     */     //   235: invokestatic 298	com/claro/util/ServiceLocator:getInstance	()Lcom/claro/util/ServiceLocator;
/*     */     //   238: getstatic 304	com/claro/util/ServiceLocator:jdbcMobile459	Ljava/lang/String;
/*     */     //   241: invokevirtual 307	com/claro/util/ServiceLocator:getConnection	(Ljava/lang/String;)Ljava/sql/Connection;
/*     */     //   244: astore_3
/*     */     //   245: goto +13 -> 258
/*     */     //   248: invokestatic 298	com/claro/util/ServiceLocator:getInstance	()Lcom/claro/util/ServiceLocator;
/*     */     //   251: getstatic 311	com/claro/util/ServiceLocator:jdbcMobile	Ljava/lang/String;
/*     */     //   254: invokevirtual 307	com/claro/util/ServiceLocator:getConnection	(Ljava/lang/String;)Ljava/sql/Connection;
/*     */     //   257: astore_3
/*     */     //   258: aload_3
/*     */     //   259: invokeinterface 145 1 0
/*     */     //   264: astore 5
/*     */     //   266: aload 5
/*     */     //   268: aload 7
/*     */     //   270: invokeinterface 152 2 0
/*     */     //   275: astore 6
/*     */     //   277: new 110	com/claro/transfer/MobileTO
/*     */     //   280: dup
/*     */     //   281: invokespecial 112	com/claro/transfer/MobileTO:<init>	()V
/*     */     //   284: astore 4
/*     */     //   286: aload 6
/*     */     //   288: invokeinterface 158 1 0
/*     */     //   293: ifeq +52 -> 345
/*     */     //   296: aload 4
/*     */     //   298: aload 6
/*     */     //   300: ldc_w 739
/*     */     //   303: invokeinterface 166 2 0
/*     */     //   308: invokevirtual 175	com/claro/transfer/MobileTO:setStatus	(Ljava/lang/String;)V
/*     */     //   311: aload 4
/*     */     //   313: aload 6
/*     */     //   315: ldc_w 443
/*     */     //   318: invokeinterface 166 2 0
/*     */     //   323: invokevirtual 445	com/claro/transfer/MobileTO:setEstCobranza	(Ljava/lang/String;)V
/*     */     //   326: aload 4
/*     */     //   328: aload 6
/*     */     //   330: iconst_1
/*     */     //   331: invokeinterface 203 2 0
/*     */     //   336: invokestatic 206	com/claro/util/Utils:formatFecha	(Ljava/lang/String;)Ljava/lang/String;
/*     */     //   339: invokevirtual 492	com/claro/transfer/MobileTO:setFecAltaUser	(Ljava/lang/String;)V
/*     */     //   342: goto +150 -> 492
/*     */     //   345: aload 4
/*     */     //   347: ldc_w 741
/*     */     //   350: invokevirtual 743	com/claro/transfer/MobileTO:setMensaje	(Ljava/lang/String;)V
/*     */     //   353: goto +139 -> 492
/*     */     //   356: astore 10
/*     */     //   358: new 34	com/claro/exception/CAException
/*     */     //   361: dup
/*     */     //   362: iconst_0
/*     */     //   363: new 47	java/lang/StringBuilder
/*     */     //   366: dup
/*     */     //   367: ldc_w 746
/*     */     //   370: invokespecial 51	java/lang/StringBuilder:<init>	(Ljava/lang/String;)V
/*     */     //   373: aload_1
/*     */     //   374: invokevirtual 60	java/lang/StringBuilder:append	(Ljava/lang/String;)Ljava/lang/StringBuilder;
/*     */     //   377: ldc_w 748
/*     */     //   380: invokevirtual 60	java/lang/StringBuilder:append	(Ljava/lang/String;)Ljava/lang/StringBuilder;
/*     */     //   383: aload 10
/*     */     //   385: invokevirtual 750	java/sql/SQLException:getMessage	()Ljava/lang/String;
/*     */     //   388: invokevirtual 60	java/lang/StringBuilder:append	(Ljava/lang/String;)Ljava/lang/StringBuilder;
/*     */     //   391: invokevirtual 63	java/lang/StringBuilder:toString	()Ljava/lang/String;
/*     */     //   394: invokespecial 753	com/claro/exception/CAException:<init>	(ILjava/lang/String;)V
/*     */     //   397: athrow
/*     */     //   398: astore 10
/*     */     //   400: new 34	com/claro/exception/CAException
/*     */     //   403: dup
/*     */     //   404: iconst_0
/*     */     //   405: new 47	java/lang/StringBuilder
/*     */     //   408: dup
/*     */     //   409: ldc_w 755
/*     */     //   412: invokespecial 51	java/lang/StringBuilder:<init>	(Ljava/lang/String;)V
/*     */     //   415: aload_1
/*     */     //   416: invokevirtual 60	java/lang/StringBuilder:append	(Ljava/lang/String;)Ljava/lang/StringBuilder;
/*     */     //   419: ldc_w 748
/*     */     //   422: invokevirtual 60	java/lang/StringBuilder:append	(Ljava/lang/String;)Ljava/lang/StringBuilder;
/*     */     //   425: aload 10
/*     */     //   427: invokevirtual 757	java/lang/Exception:getMessage	()Ljava/lang/String;
/*     */     //   430: invokevirtual 60	java/lang/StringBuilder:append	(Ljava/lang/String;)Ljava/lang/StringBuilder;
/*     */     //   433: invokevirtual 63	java/lang/StringBuilder:toString	()Ljava/lang/String;
/*     */     //   436: invokespecial 753	com/claro/exception/CAException:<init>	(ILjava/lang/String;)V
/*     */     //   439: athrow
/*     */     //   440: astore 11
/*     */     //   442: aload 6
/*     */     //   444: ifnull +13 -> 457
/*     */     //   447: aload 6
/*     */     //   449: invokeinterface 264 1 0
/*     */     //   454: aconst_null
/*     */     //   455: astore 6
/*     */     //   457: aload 5
/*     */     //   459: ifnull +13 -> 472
/*     */     //   462: aload 5
/*     */     //   464: invokeinterface 267 1 0
/*     */     //   469: aconst_null
/*     */     //   470: astore 5
/*     */     //   472: aload_3
/*     */     //   473: ifnull +16 -> 489
/*     */     //   476: aload_3
/*     */     //   477: invokeinterface 321 1 0
/*     */     //   482: aconst_null
/*     */     //   483: astore_3
/*     */     //   484: goto +5 -> 489
/*     */     //   487: astore 12
/*     */     //   489: aload 11
/*     */     //   491: athrow
/*     */     //   492: aload 6
/*     */     //   494: ifnull +13 -> 507
/*     */     //   497: aload 6
/*     */     //   499: invokeinterface 264 1 0
/*     */     //   504: aconst_null
/*     */     //   505: astore 6
/*     */     //   507: aload 5
/*     */     //   509: ifnull +13 -> 522
/*     */     //   512: aload 5
/*     */     //   514: invokeinterface 267 1 0
/*     */     //   519: aconst_null
/*     */     //   520: astore 5
/*     */     //   522: aload_3
/*     */     //   523: ifnull +16 -> 539
/*     */     //   526: aload_3
/*     */     //   527: invokeinterface 321 1 0
/*     */     //   532: aconst_null
/*     */     //   533: astore_3
/*     */     //   534: goto +5 -> 539
/*     */     //   537: astore 12
/*     */     //   539: aload 4
/*     */     //   541: areturn
/*     */     // Line number table:
/*     */     //   Java source line #404	-> byte code offset #0
/*     */     //   Java source line #405	-> byte code offset #2
/*     */     //   Java source line #406	-> byte code offset #5
/*     */     //   Java source line #407	-> byte code offset #8
/*     */     //   Java source line #408	-> byte code offset #11
/*     */     //   Java source line #415	-> byte code offset #14
/*     */     //   Java source line #416	-> byte code offset #27
/*     */     //   Java source line #417	-> byte code offset #41
/*     */     //   Java source line #419	-> byte code offset #65
/*     */     //   Java source line #420	-> byte code offset #78
/*     */     //   Java source line #422	-> byte code offset #101
/*     */     //   Java source line #429	-> byte code offset #111
/*     */     //   Java source line #430	-> byte code offset #122
/*     */     //   Java source line #431	-> byte code offset #139
/*     */     //   Java source line #432	-> byte code offset #159
/*     */     //   Java source line #433	-> byte code offset #165
/*     */     //   Java source line #434	-> byte code offset #182
/*     */     //   Java source line #435	-> byte code offset #198
/*     */     //   Java source line #422	-> byte code offset #214
/*     */     //   Java source line #438	-> byte code offset #219
/*     */     //   Java source line #439	-> byte code offset #235
/*     */     //   Java source line #441	-> byte code offset #248
/*     */     //   Java source line #443	-> byte code offset #258
/*     */     //   Java source line #445	-> byte code offset #266
/*     */     //   Java source line #446	-> byte code offset #277
/*     */     //   Java source line #448	-> byte code offset #286
/*     */     //   Java source line #452	-> byte code offset #296
/*     */     //   Java source line #453	-> byte code offset #311
/*     */     //   Java source line #454	-> byte code offset #326
/*     */     //   Java source line #456	-> byte code offset #345
/*     */     //   Java source line #458	-> byte code offset #356
/*     */     //   Java source line #459	-> byte code offset #358
/*     */     //   Java source line #460	-> byte code offset #398
/*     */     //   Java source line #461	-> byte code offset #400
/*     */     //   Java source line #462	-> byte code offset #440
/*     */     //   Java source line #464	-> byte code offset #442
/*     */     //   Java source line #465	-> byte code offset #457
/*     */     //   Java source line #466	-> byte code offset #472
/*     */     //   Java source line #468	-> byte code offset #487
/*     */     //   Java source line #469	-> byte code offset #489
/*     */     //   Java source line #464	-> byte code offset #492
/*     */     //   Java source line #465	-> byte code offset #507
/*     */     //   Java source line #466	-> byte code offset #522
/*     */     //   Java source line #468	-> byte code offset #537
/*     */     //   Java source line #470	-> byte code offset #539
/*     */     // Local variable table:
/*     */     //   start	length	slot	name	signature
/*     */     //   0	542	0	this	ConsultaM2KDAO
/*     */     //   0	542	1	lCta	String
/*     */     //   0	542	2	nReg	int
/*     */     //   1	533	3	connection	Connection
/*     */     //   3	537	4	mobileTO	MobileTO
/*     */     //   6	515	5	stmt	java.sql.Statement
/*     */     //   9	497	6	rset	java.sql.ResultSet
/*     */     //   12	257	7	sQuery	String
/*     */     //   22	3	8	mercadoM2K	String
/*     */     //   36	3	8	mercadoM2K	String
/*     */     //   63	109	8	mercadoM2K	String
/*     */     //   73	3	9	mertelM2K	String
/*     */     //   99	3	9	mertelM2K	String
/*     */     //   356	28	10	e	SQLException
/*     */     //   398	28	10	e	Exception
/*     */     //   440	50	11	localObject	Object
/*     */     //   487	1	12	localException1	Exception
/*     */     //   537	1	12	localException2	Exception
/*     */     // Exception table:
/*     */     //   from	to	target	type
/*     */     //   219	353	356	java/sql/SQLException
/*     */     //   219	353	398	java/lang/Exception
/*     */     //   219	440	440	finally
/*     */     //   442	484	487	java/lang/Exception
/*     */     //   492	534	537	java/lang/Exception
/*     */   }
/*     */   
/*     */   /* Error */
/*     */   public void obtenFacturaciones(MobileTO mobileTO, int region, String cuenta, int numFacturas)
/*     */     throws CAException
/*     */   {
/*     */     // Byte code:
/*     */     //   0: iload_2
/*     */     //   1: iconst_4
/*     */     //   2: if_icmpne +11 -> 13
/*     */     //   5: ldc_w 337
/*     */     //   8: astore 5
/*     */     //   10: goto +41 -> 51
/*     */     //   13: iload_2
/*     */     //   14: bipush 9
/*     */     //   16: if_icmpne +11 -> 27
/*     */     //   19: ldc_w 339
/*     */     //   22: astore 5
/*     */     //   24: goto +27 -> 51
/*     */     //   27: new 47	java/lang/StringBuilder
/*     */     //   30: dup
/*     */     //   31: ldc 49
/*     */     //   33: invokespecial 51	java/lang/StringBuilder:<init>	(Ljava/lang/String;)V
/*     */     //   36: iload_2
/*     */     //   37: invokevirtual 54	java/lang/StringBuilder:append	(I)Ljava/lang/StringBuilder;
/*     */     //   40: ldc_w 341
/*     */     //   43: invokevirtual 60	java/lang/StringBuilder:append	(Ljava/lang/String;)Ljava/lang/StringBuilder;
/*     */     //   46: invokevirtual 63	java/lang/StringBuilder:toString	()Ljava/lang/String;
/*     */     //   49: astore 5
/*     */     //   51: iload_2
/*     */     //   52: bipush 9
/*     */     //   54: if_icmpne +10 -> 64
/*     */     //   57: ldc 45
/*     */     //   59: astore 6
/*     */     //   61: goto +26 -> 87
/*     */     //   64: new 47	java/lang/StringBuilder
/*     */     //   67: dup
/*     */     //   68: ldc 49
/*     */     //   70: invokespecial 51	java/lang/StringBuilder:<init>	(Ljava/lang/String;)V
/*     */     //   73: iload_2
/*     */     //   74: invokevirtual 54	java/lang/StringBuilder:append	(I)Ljava/lang/StringBuilder;
/*     */     //   77: ldc 58
/*     */     //   79: invokevirtual 60	java/lang/StringBuilder:append	(Ljava/lang/String;)Ljava/lang/StringBuilder;
/*     */     //   82: invokevirtual 63	java/lang/StringBuilder:toString	()Ljava/lang/String;
/*     */     //   85: astore 6
/*     */     //   87: new 36	java/lang/StringBuffer
/*     */     //   90: dup
/*     */     //   91: invokespecial 38	java/lang/StringBuffer:<init>	()V
/*     */     //   94: astore 7
/*     */     //   96: aload 7
/*     */     //   98: ldc_w 561
/*     */     //   101: invokevirtual 69	java/lang/StringBuffer:append	(Ljava/lang/String;)Ljava/lang/StringBuffer;
/*     */     //   104: aload 5
/*     */     //   106: invokevirtual 69	java/lang/StringBuffer:append	(Ljava/lang/String;)Ljava/lang/StringBuffer;
/*     */     //   109: ldc_w 563
/*     */     //   112: invokevirtual 69	java/lang/StringBuffer:append	(Ljava/lang/String;)Ljava/lang/StringBuffer;
/*     */     //   115: pop
/*     */     //   116: aload 7
/*     */     //   118: ldc_w 565
/*     */     //   121: invokevirtual 69	java/lang/StringBuffer:append	(Ljava/lang/String;)Ljava/lang/StringBuffer;
/*     */     //   124: aload_3
/*     */     //   125: invokevirtual 69	java/lang/StringBuffer:append	(Ljava/lang/String;)Ljava/lang/StringBuffer;
/*     */     //   128: ldc_w 567
/*     */     //   131: invokevirtual 69	java/lang/StringBuffer:append	(Ljava/lang/String;)Ljava/lang/StringBuffer;
/*     */     //   134: iload_2
/*     */     //   135: invokevirtual 399	java/lang/StringBuffer:append	(I)Ljava/lang/StringBuffer;
/*     */     //   138: ldc_w 402
/*     */     //   141: invokevirtual 69	java/lang/StringBuffer:append	(Ljava/lang/String;)Ljava/lang/StringBuffer;
/*     */     //   144: pop
/*     */     //   145: aload 7
/*     */     //   147: ldc_w 569
/*     */     //   150: invokevirtual 69	java/lang/StringBuffer:append	(Ljava/lang/String;)Ljava/lang/StringBuffer;
/*     */     //   153: pop
/*     */     //   154: aload 7
/*     */     //   156: ldc_w 571
/*     */     //   159: invokevirtual 69	java/lang/StringBuffer:append	(Ljava/lang/String;)Ljava/lang/StringBuffer;
/*     */     //   162: aload_1
/*     */     //   163: invokevirtual 410	com/claro/transfer/MobileTO:getSecuencia	()Ljava/lang/String;
/*     */     //   166: invokevirtual 69	java/lang/StringBuffer:append	(Ljava/lang/String;)Ljava/lang/StringBuffer;
/*     */     //   169: pop
/*     */     //   170: aload 7
/*     */     //   172: ldc_w 573
/*     */     //   175: invokevirtual 69	java/lang/StringBuffer:append	(Ljava/lang/String;)Ljava/lang/StringBuffer;
/*     */     //   178: pop
/*     */     //   179: new 47	java/lang/StringBuilder
/*     */     //   182: dup
/*     */     //   183: ldc_w 765
/*     */     //   186: invokespecial 51	java/lang/StringBuilder:<init>	(Ljava/lang/String;)V
/*     */     //   189: iload 4
/*     */     //   191: invokevirtual 54	java/lang/StringBuilder:append	(I)Ljava/lang/StringBuilder;
/*     */     //   194: ldc_w 767
/*     */     //   197: invokevirtual 60	java/lang/StringBuilder:append	(Ljava/lang/String;)Ljava/lang/StringBuilder;
/*     */     //   200: invokevirtual 63	java/lang/StringBuilder:toString	()Ljava/lang/String;
/*     */     //   203: astore 8
/*     */     //   205: aload 7
/*     */     //   207: aload 8
/*     */     //   209: invokevirtual 69	java/lang/StringBuffer:append	(Ljava/lang/String;)Ljava/lang/StringBuffer;
/*     */     //   212: pop
/*     */     //   213: new 36	java/lang/StringBuffer
/*     */     //   216: dup
/*     */     //   217: invokespecial 38	java/lang/StringBuffer:<init>	()V
/*     */     //   220: astore 9
/*     */     //   222: aload 9
/*     */     //   224: ldc_w 577
/*     */     //   227: invokevirtual 69	java/lang/StringBuffer:append	(Ljava/lang/String;)Ljava/lang/StringBuffer;
/*     */     //   230: pop
/*     */     //   231: aload 9
/*     */     //   233: ldc_w 579
/*     */     //   236: invokevirtual 69	java/lang/StringBuffer:append	(Ljava/lang/String;)Ljava/lang/StringBuffer;
/*     */     //   239: pop
/*     */     //   240: aload 9
/*     */     //   242: ldc_w 581
/*     */     //   245: invokevirtual 69	java/lang/StringBuffer:append	(Ljava/lang/String;)Ljava/lang/StringBuffer;
/*     */     //   248: pop
/*     */     //   249: aload 9
/*     */     //   251: ldc_w 381
/*     */     //   254: invokevirtual 69	java/lang/StringBuffer:append	(Ljava/lang/String;)Ljava/lang/StringBuffer;
/*     */     //   257: aload 5
/*     */     //   259: invokevirtual 69	java/lang/StringBuffer:append	(Ljava/lang/String;)Ljava/lang/StringBuffer;
/*     */     //   262: ldc_w 583
/*     */     //   265: invokevirtual 69	java/lang/StringBuffer:append	(Ljava/lang/String;)Ljava/lang/StringBuffer;
/*     */     //   268: pop
/*     */     //   269: aload 9
/*     */     //   271: ldc_w 585
/*     */     //   274: invokevirtual 69	java/lang/StringBuffer:append	(Ljava/lang/String;)Ljava/lang/StringBuffer;
/*     */     //   277: pop
/*     */     //   278: aload 9
/*     */     //   280: ldc_w 587
/*     */     //   283: invokevirtual 69	java/lang/StringBuffer:append	(Ljava/lang/String;)Ljava/lang/StringBuffer;
/*     */     //   286: pop
/*     */     //   287: aload 9
/*     */     //   289: ldc_w 589
/*     */     //   292: invokevirtual 69	java/lang/StringBuffer:append	(Ljava/lang/String;)Ljava/lang/StringBuffer;
/*     */     //   295: pop
/*     */     //   296: aload 9
/*     */     //   298: ldc_w 591
/*     */     //   301: invokevirtual 69	java/lang/StringBuffer:append	(Ljava/lang/String;)Ljava/lang/StringBuffer;
/*     */     //   304: pop
/*     */     //   305: aload 9
/*     */     //   307: ldc_w 593
/*     */     //   310: invokevirtual 69	java/lang/StringBuffer:append	(Ljava/lang/String;)Ljava/lang/StringBuffer;
/*     */     //   313: pop
/*     */     //   314: new 36	java/lang/StringBuffer
/*     */     //   317: dup
/*     */     //   318: invokespecial 38	java/lang/StringBuffer:<init>	()V
/*     */     //   321: astore 10
/*     */     //   323: aload 10
/*     */     //   325: ldc_w 595
/*     */     //   328: invokevirtual 69	java/lang/StringBuffer:append	(Ljava/lang/String;)Ljava/lang/StringBuffer;
/*     */     //   331: pop
/*     */     //   332: aload 10
/*     */     //   334: ldc_w 381
/*     */     //   337: invokevirtual 69	java/lang/StringBuffer:append	(Ljava/lang/String;)Ljava/lang/StringBuffer;
/*     */     //   340: aload 6
/*     */     //   342: invokevirtual 69	java/lang/StringBuffer:append	(Ljava/lang/String;)Ljava/lang/StringBuffer;
/*     */     //   345: ldc_w 597
/*     */     //   348: invokevirtual 69	java/lang/StringBuffer:append	(Ljava/lang/String;)Ljava/lang/StringBuffer;
/*     */     //   351: pop
/*     */     //   352: aload 10
/*     */     //   354: ldc_w 599
/*     */     //   357: invokevirtual 69	java/lang/StringBuffer:append	(Ljava/lang/String;)Ljava/lang/StringBuffer;
/*     */     //   360: pop
/*     */     //   361: aload 10
/*     */     //   363: ldc_w 601
/*     */     //   366: invokevirtual 69	java/lang/StringBuffer:append	(Ljava/lang/String;)Ljava/lang/StringBuffer;
/*     */     //   369: pop
/*     */     //   370: aload 10
/*     */     //   372: ldc_w 603
/*     */     //   375: invokevirtual 69	java/lang/StringBuffer:append	(Ljava/lang/String;)Ljava/lang/StringBuffer;
/*     */     //   378: pop
/*     */     //   379: aconst_null
/*     */     //   380: astore 11
/*     */     //   382: aconst_null
/*     */     //   383: astore 12
/*     */     //   385: aconst_null
/*     */     //   386: astore 13
/*     */     //   388: aconst_null
/*     */     //   389: astore 14
/*     */     //   391: aconst_null
/*     */     //   392: astore 15
/*     */     //   394: aconst_null
/*     */     //   395: astore 16
/*     */     //   397: aconst_null
/*     */     //   398: astore 17
/*     */     //   400: iconst_1
/*     */     //   401: istore 18
/*     */     //   403: iconst_0
/*     */     //   404: istore 19
/*     */     //   406: iload_2
/*     */     //   407: iconst_4
/*     */     //   408: if_icmpeq +14 -> 422
/*     */     //   411: iload_2
/*     */     //   412: iconst_5
/*     */     //   413: if_icmpeq +9 -> 422
/*     */     //   416: iload_2
/*     */     //   417: bipush 9
/*     */     //   419: if_icmpne +17 -> 436
/*     */     //   422: invokestatic 298	com/claro/util/ServiceLocator:getInstance	()Lcom/claro/util/ServiceLocator;
/*     */     //   425: getstatic 304	com/claro/util/ServiceLocator:jdbcMobile459	Ljava/lang/String;
/*     */     //   428: invokevirtual 307	com/claro/util/ServiceLocator:getConnection	(Ljava/lang/String;)Ljava/sql/Connection;
/*     */     //   431: astore 17
/*     */     //   433: goto +14 -> 447
/*     */     //   436: invokestatic 298	com/claro/util/ServiceLocator:getInstance	()Lcom/claro/util/ServiceLocator;
/*     */     //   439: getstatic 311	com/claro/util/ServiceLocator:jdbcMobile	Ljava/lang/String;
/*     */     //   442: invokevirtual 307	com/claro/util/ServiceLocator:getConnection	(Ljava/lang/String;)Ljava/sql/Connection;
/*     */     //   445: astore 17
/*     */     //   447: aload 17
/*     */     //   449: aload 7
/*     */     //   451: invokevirtual 151	java/lang/StringBuffer:toString	()Ljava/lang/String;
/*     */     //   454: invokeinterface 605 2 0
/*     */     //   459: astore 11
/*     */     //   461: aload 17
/*     */     //   463: aload 9
/*     */     //   465: invokevirtual 151	java/lang/StringBuffer:toString	()Ljava/lang/String;
/*     */     //   468: invokeinterface 605 2 0
/*     */     //   473: astore 12
/*     */     //   475: aload 17
/*     */     //   477: aload 10
/*     */     //   479: invokevirtual 151	java/lang/StringBuffer:toString	()Ljava/lang/String;
/*     */     //   482: invokeinterface 605 2 0
/*     */     //   487: astore 13
/*     */     //   489: aload 11
/*     */     //   491: invokeinterface 609 1 0
/*     */     //   496: astore 14
/*     */     //   498: new 614	java/util/ArrayList
/*     */     //   501: dup
/*     */     //   502: invokespecial 616	java/util/ArrayList:<init>	()V
/*     */     //   505: astore 20
/*     */     //   507: iconst_0
/*     */     //   508: istore 21
/*     */     //   510: goto +181 -> 691
/*     */     //   513: iinc 21 1
/*     */     //   516: aload 14
/*     */     //   518: iconst_1
/*     */     //   519: invokeinterface 203 2 0
/*     */     //   524: astore 22
/*     */     //   526: aload 14
/*     */     //   528: iconst_2
/*     */     //   529: invokeinterface 617 2 0
/*     */     //   534: astore 23
/*     */     //   536: aload 14
/*     */     //   538: iconst_3
/*     */     //   539: invokeinterface 617 2 0
/*     */     //   544: astore 24
/*     */     //   546: aload 12
/*     */     //   548: invokeinterface 621 1 0
/*     */     //   553: aload 12
/*     */     //   555: iconst_1
/*     */     //   556: aload 22
/*     */     //   558: invokeinterface 624 3 0
/*     */     //   563: aload 12
/*     */     //   565: iconst_2
/*     */     //   566: aload 23
/*     */     //   568: invokeinterface 627 3 0
/*     */     //   573: aload 12
/*     */     //   575: iconst_3
/*     */     //   576: aload 24
/*     */     //   578: invokeinterface 627 3 0
/*     */     //   583: aload 12
/*     */     //   585: iconst_4
/*     */     //   586: aload_1
/*     */     //   587: invokevirtual 410	com/claro/transfer/MobileTO:getSecuencia	()Ljava/lang/String;
/*     */     //   590: ifnull +13 -> 603
/*     */     //   593: aload_1
/*     */     //   594: invokevirtual 410	com/claro/transfer/MobileTO:getSecuencia	()Ljava/lang/String;
/*     */     //   597: invokestatic 631	java/lang/Integer:parseInt	(Ljava/lang/String;)I
/*     */     //   600: goto +4 -> 604
/*     */     //   603: iconst_1
/*     */     //   604: invokeinterface 637 3 0
/*     */     //   609: aload 12
/*     */     //   611: invokeinterface 609 1 0
/*     */     //   616: astore 15
/*     */     //   618: aload 15
/*     */     //   620: invokeinterface 158 1 0
/*     */     //   625: ifeq +40 -> 665
/*     */     //   628: new 641	com/claro/transfer/FacturaTO
/*     */     //   631: dup
/*     */     //   632: invokespecial 643	com/claro/transfer/FacturaTO:<init>	()V
/*     */     //   635: astore 25
/*     */     //   637: aload 25
/*     */     //   639: aload 15
/*     */     //   641: iconst_1
/*     */     //   642: invokeinterface 644 2 0
/*     */     //   647: invokevirtual 648	com/claro/transfer/FacturaTO:setMonto	(D)V
/*     */     //   650: aload 25
/*     */     //   652: aload 24
/*     */     //   654: invokevirtual 652	com/claro/transfer/FacturaTO:setFechaFactura	(Ljava/math/BigDecimal;)V
/*     */     //   657: aload 20
/*     */     //   659: aload 25
/*     */     //   661: invokevirtual 656	java/util/ArrayList:add	(Ljava/lang/Object;)Z
/*     */     //   664: pop
/*     */     //   665: aload 15
/*     */     //   667: ifnull +18 -> 685
/*     */     //   670: aload 15
/*     */     //   672: invokeinterface 264 1 0
/*     */     //   677: aconst_null
/*     */     //   678: astore 15
/*     */     //   680: goto +5 -> 685
/*     */     //   683: astore 25
/*     */     //   685: iinc 18 1
/*     */     //   688: iinc 19 1
/*     */     //   691: aload 14
/*     */     //   693: invokeinterface 158 1 0
/*     */     //   698: ifne -185 -> 513
/*     */     //   701: iload 19
/*     */     //   703: ifne +35 -> 738
/*     */     //   706: aload_1
/*     */     //   707: iconst_m1
/*     */     //   708: new 47	java/lang/StringBuilder
/*     */     //   711: dup
/*     */     //   712: ldc_w 659
/*     */     //   715: invokespecial 51	java/lang/StringBuilder:<init>	(Ljava/lang/String;)V
/*     */     //   718: iload_2
/*     */     //   719: invokevirtual 54	java/lang/StringBuilder:append	(I)Ljava/lang/StringBuilder;
/*     */     //   722: ldc_w 661
/*     */     //   725: invokevirtual 60	java/lang/StringBuilder:append	(Ljava/lang/String;)Ljava/lang/StringBuilder;
/*     */     //   728: aload_3
/*     */     //   729: invokevirtual 60	java/lang/StringBuilder:append	(Ljava/lang/String;)Ljava/lang/StringBuilder;
/*     */     //   732: invokevirtual 63	java/lang/StringBuilder:toString	()Ljava/lang/String;
/*     */     //   735: invokevirtual 231	com/claro/transfer/MobileTO:agregaMensaje	(ILjava/lang/String;)V
/*     */     //   738: aload_1
/*     */     //   739: aload 20
/*     */     //   741: invokevirtual 663	com/claro/transfer/MobileTO:setFacturas	(Ljava/util/ArrayList;)V
/*     */     //   744: aload_1
/*     */     //   745: aload_1
/*     */     //   746: invokevirtual 667	com/claro/transfer/MobileTO:getPromedio	()D
/*     */     //   749: invokestatic 671	java/lang/Double:toString	(D)Ljava/lang/String;
/*     */     //   752: invokevirtual 676	com/claro/transfer/MobileTO:setSPromFacturaAV	(Ljava/lang/String;)V
/*     */     //   755: aload 13
/*     */     //   757: invokeinterface 621 1 0
/*     */     //   762: aload 13
/*     */     //   764: iconst_1
/*     */     //   765: aload_3
/*     */     //   766: invokeinterface 624 3 0
/*     */     //   771: aload 13
/*     */     //   773: invokeinterface 609 1 0
/*     */     //   778: astore 16
/*     */     //   780: aload 16
/*     */     //   782: invokeinterface 158 1 0
/*     */     //   787: ifeq +15 -> 802
/*     */     //   790: aload_1
/*     */     //   791: aload 16
/*     */     //   793: iconst_1
/*     */     //   794: invokeinterface 679 2 0
/*     */     //   799: invokevirtual 683	com/claro/transfer/MobileTO:setNoBajas	(I)V
/*     */     //   802: aload 16
/*     */     //   804: ifnull +204 -> 1008
/*     */     //   807: aload 16
/*     */     //   809: invokeinterface 264 1 0
/*     */     //   814: aconst_null
/*     */     //   815: astore 16
/*     */     //   817: goto +191 -> 1008
/*     */     //   820: astore 22
/*     */     //   822: goto +186 -> 1008
/*     */     //   825: astore 20
/*     */     //   827: new 34	com/claro/exception/CAException
/*     */     //   830: dup
/*     */     //   831: iconst_m1
/*     */     //   832: new 47	java/lang/StringBuilder
/*     */     //   835: dup
/*     */     //   836: ldc_w 687
/*     */     //   839: invokespecial 51	java/lang/StringBuilder:<init>	(Ljava/lang/String;)V
/*     */     //   842: aload 20
/*     */     //   844: invokevirtual 249	java/sql/SQLException:toString	()Ljava/lang/String;
/*     */     //   847: invokevirtual 60	java/lang/StringBuilder:append	(Ljava/lang/String;)Ljava/lang/StringBuilder;
/*     */     //   850: ldc -4
/*     */     //   852: invokevirtual 60	java/lang/StringBuilder:append	(Ljava/lang/String;)Ljava/lang/StringBuilder;
/*     */     //   855: invokevirtual 63	java/lang/StringBuilder:toString	()Ljava/lang/String;
/*     */     //   858: aload 20
/*     */     //   860: invokespecial 254	com/claro/exception/CAException:<init>	(ILjava/lang/String;Ljava/lang/Exception;)V
/*     */     //   863: athrow
/*     */     //   864: astore 20
/*     */     //   866: new 34	com/claro/exception/CAException
/*     */     //   869: dup
/*     */     //   870: iconst_m1
/*     */     //   871: new 47	java/lang/StringBuilder
/*     */     //   874: dup
/*     */     //   875: ldc_w 689
/*     */     //   878: invokespecial 51	java/lang/StringBuilder:<init>	(Ljava/lang/String;)V
/*     */     //   881: aload 20
/*     */     //   883: invokevirtual 261	java/lang/Exception:toString	()Ljava/lang/String;
/*     */     //   886: invokevirtual 60	java/lang/StringBuilder:append	(Ljava/lang/String;)Ljava/lang/StringBuilder;
/*     */     //   889: ldc -4
/*     */     //   891: invokevirtual 60	java/lang/StringBuilder:append	(Ljava/lang/String;)Ljava/lang/StringBuilder;
/*     */     //   894: invokevirtual 63	java/lang/StringBuilder:toString	()Ljava/lang/String;
/*     */     //   897: aload 20
/*     */     //   899: invokespecial 254	com/claro/exception/CAException:<init>	(ILjava/lang/String;Ljava/lang/Exception;)V
/*     */     //   902: athrow
/*     */     //   903: astore 26
/*     */     //   905: aload 15
/*     */     //   907: ifnull +18 -> 925
/*     */     //   910: aload 15
/*     */     //   912: invokeinterface 264 1 0
/*     */     //   917: aconst_null
/*     */     //   918: astore 15
/*     */     //   920: goto +5 -> 925
/*     */     //   923: astore 27
/*     */     //   925: aload 14
/*     */     //   927: ifnull +18 -> 945
/*     */     //   930: aload 14
/*     */     //   932: invokeinterface 264 1 0
/*     */     //   937: aconst_null
/*     */     //   938: astore 14
/*     */     //   940: goto +5 -> 945
/*     */     //   943: astore 27
/*     */     //   945: aload 12
/*     */     //   947: ifnull +18 -> 965
/*     */     //   950: aload 12
/*     */     //   952: invokeinterface 691 1 0
/*     */     //   957: aconst_null
/*     */     //   958: astore 12
/*     */     //   960: goto +5 -> 965
/*     */     //   963: astore 27
/*     */     //   965: aload 11
/*     */     //   967: ifnull +18 -> 985
/*     */     //   970: aload 11
/*     */     //   972: invokeinterface 691 1 0
/*     */     //   977: aconst_null
/*     */     //   978: astore 11
/*     */     //   980: goto +5 -> 985
/*     */     //   983: astore 27
/*     */     //   985: aload 17
/*     */     //   987: ifnull +18 -> 1005
/*     */     //   990: aload 17
/*     */     //   992: invokeinterface 321 1 0
/*     */     //   997: aconst_null
/*     */     //   998: astore 17
/*     */     //   1000: goto +5 -> 1005
/*     */     //   1003: astore 27
/*     */     //   1005: aload 26
/*     */     //   1007: athrow
/*     */     //   1008: aload 15
/*     */     //   1010: ifnull +18 -> 1028
/*     */     //   1013: aload 15
/*     */     //   1015: invokeinterface 264 1 0
/*     */     //   1020: aconst_null
/*     */     //   1021: astore 15
/*     */     //   1023: goto +5 -> 1028
/*     */     //   1026: astore 27
/*     */     //   1028: aload 14
/*     */     //   1030: ifnull +18 -> 1048
/*     */     //   1033: aload 14
/*     */     //   1035: invokeinterface 264 1 0
/*     */     //   1040: aconst_null
/*     */     //   1041: astore 14
/*     */     //   1043: goto +5 -> 1048
/*     */     //   1046: astore 27
/*     */     //   1048: aload 12
/*     */     //   1050: ifnull +18 -> 1068
/*     */     //   1053: aload 12
/*     */     //   1055: invokeinterface 691 1 0
/*     */     //   1060: aconst_null
/*     */     //   1061: astore 12
/*     */     //   1063: goto +5 -> 1068
/*     */     //   1066: astore 27
/*     */     //   1068: aload 11
/*     */     //   1070: ifnull +18 -> 1088
/*     */     //   1073: aload 11
/*     */     //   1075: invokeinterface 691 1 0
/*     */     //   1080: aconst_null
/*     */     //   1081: astore 11
/*     */     //   1083: goto +5 -> 1088
/*     */     //   1086: astore 27
/*     */     //   1088: aload 17
/*     */     //   1090: ifnull +18 -> 1108
/*     */     //   1093: aload 17
/*     */     //   1095: invokeinterface 321 1 0
/*     */     //   1100: aconst_null
/*     */     //   1101: astore 17
/*     */     //   1103: goto +5 -> 1108
/*     */     //   1106: astore 27
/*     */     //   1108: return
/*     */     // Line number table:
/*     */     //   Java source line #486	-> byte code offset #0
/*     */     //   Java source line #487	-> byte code offset #13
/*     */     //   Java source line #488	-> byte code offset #27
/*     */     //   Java source line #490	-> byte code offset #51
/*     */     //   Java source line #491	-> byte code offset #64
/*     */     //   Java source line #501	-> byte code offset #87
/*     */     //   Java source line #502	-> byte code offset #96
/*     */     //   Java source line #503	-> byte code offset #116
/*     */     //   Java source line #504	-> byte code offset #145
/*     */     //   Java source line #505	-> byte code offset #154
/*     */     //   Java source line #506	-> byte code offset #170
/*     */     //   Java source line #507	-> byte code offset #179
/*     */     //   Java source line #508	-> byte code offset #205
/*     */     //   Java source line #513	-> byte code offset #213
/*     */     //   Java source line #514	-> byte code offset #222
/*     */     //   Java source line #515	-> byte code offset #231
/*     */     //   Java source line #516	-> byte code offset #240
/*     */     //   Java source line #517	-> byte code offset #249
/*     */     //   Java source line #518	-> byte code offset #269
/*     */     //   Java source line #519	-> byte code offset #278
/*     */     //   Java source line #520	-> byte code offset #287
/*     */     //   Java source line #521	-> byte code offset #296
/*     */     //   Java source line #523	-> byte code offset #305
/*     */     //   Java source line #527	-> byte code offset #314
/*     */     //   Java source line #529	-> byte code offset #323
/*     */     //   Java source line #530	-> byte code offset #332
/*     */     //   Java source line #531	-> byte code offset #352
/*     */     //   Java source line #532	-> byte code offset #361
/*     */     //   Java source line #533	-> byte code offset #370
/*     */     //   Java source line #537	-> byte code offset #379
/*     */     //   Java source line #539	-> byte code offset #388
/*     */     //   Java source line #540	-> byte code offset #391
/*     */     //   Java source line #541	-> byte code offset #394
/*     */     //   Java source line #543	-> byte code offset #397
/*     */     //   Java source line #544	-> byte code offset #400
/*     */     //   Java source line #548	-> byte code offset #406
/*     */     //   Java source line #549	-> byte code offset #422
/*     */     //   Java source line #551	-> byte code offset #436
/*     */     //   Java source line #553	-> byte code offset #447
/*     */     //   Java source line #554	-> byte code offset #461
/*     */     //   Java source line #555	-> byte code offset #475
/*     */     //   Java source line #557	-> byte code offset #489
/*     */     //   Java source line #559	-> byte code offset #498
/*     */     //   Java source line #560	-> byte code offset #507
/*     */     //   Java source line #561	-> byte code offset #510
/*     */     //   Java source line #562	-> byte code offset #513
/*     */     //   Java source line #563	-> byte code offset #516
/*     */     //   Java source line #564	-> byte code offset #526
/*     */     //   Java source line #565	-> byte code offset #536
/*     */     //   Java source line #567	-> byte code offset #546
/*     */     //   Java source line #568	-> byte code offset #553
/*     */     //   Java source line #569	-> byte code offset #563
/*     */     //   Java source line #570	-> byte code offset #573
/*     */     //   Java source line #571	-> byte code offset #583
/*     */     //   Java source line #572	-> byte code offset #609
/*     */     //   Java source line #574	-> byte code offset #618
/*     */     //   Java source line #575	-> byte code offset #628
/*     */     //   Java source line #576	-> byte code offset #637
/*     */     //   Java source line #577	-> byte code offset #650
/*     */     //   Java source line #578	-> byte code offset #657
/*     */     //   Java source line #580	-> byte code offset #665
/*     */     //   Java source line #582	-> byte code offset #685
/*     */     //   Java source line #583	-> byte code offset #688
/*     */     //   Java source line #561	-> byte code offset #691
/*     */     //   Java source line #585	-> byte code offset #701
/*     */     //   Java source line #586	-> byte code offset #706
/*     */     //   Java source line #588	-> byte code offset #738
/*     */     //   Java source line #589	-> byte code offset #744
/*     */     //   Java source line #590	-> byte code offset #755
/*     */     //   Java source line #591	-> byte code offset #762
/*     */     //   Java source line #592	-> byte code offset #771
/*     */     //   Java source line #594	-> byte code offset #780
/*     */     //   Java source line #595	-> byte code offset #790
/*     */     //   Java source line #597	-> byte code offset #802
/*     */     //   Java source line #599	-> byte code offset #825
/*     */     //   Java source line #600	-> byte code offset #827
/*     */     //   Java source line #601	-> byte code offset #864
/*     */     //   Java source line #602	-> byte code offset #866
/*     */     //   Java source line #603	-> byte code offset #903
/*     */     //   Java source line #604	-> byte code offset #905
/*     */     //   Java source line #605	-> byte code offset #925
/*     */     //   Java source line #606	-> byte code offset #945
/*     */     //   Java source line #607	-> byte code offset #965
/*     */     //   Java source line #608	-> byte code offset #985
/*     */     //   Java source line #609	-> byte code offset #1005
/*     */     //   Java source line #604	-> byte code offset #1008
/*     */     //   Java source line #605	-> byte code offset #1028
/*     */     //   Java source line #606	-> byte code offset #1048
/*     */     //   Java source line #607	-> byte code offset #1068
/*     */     //   Java source line #608	-> byte code offset #1088
/*     */     //   Java source line #610	-> byte code offset #1108
/*     */     // Local variable table:
/*     */     //   start	length	slot	name	signature
/*     */     //   0	1109	0	this	ConsultaM2KDAO
/*     */     //   0	1109	1	mobileTO	MobileTO
/*     */     //   0	1109	2	region	int
/*     */     //   0	1109	3	cuenta	String
/*     */     //   0	1109	4	numFacturas	int
/*     */     //   8	3	5	mercadoM2K	String
/*     */     //   22	3	5	mercadoM2K	String
/*     */     //   49	209	5	mercadoM2K	String
/*     */     //   59	3	6	mertelM2K	String
/*     */     //   85	256	6	mertelM2K	String
/*     */     //   94	356	7	query1	StringBuffer
/*     */     //   203	5	8	rowsOnly	String
/*     */     //   220	244	9	query2	StringBuffer
/*     */     //   321	157	10	query3	StringBuffer
/*     */     //   380	702	11	statementSelectFecFac	java.sql.PreparedStatement
/*     */     //   383	679	12	statementFactura	java.sql.PreparedStatement
/*     */     //   386	386	13	statementBajaClimo	java.sql.PreparedStatement
/*     */     //   389	653	14	resultSetFecFac	java.sql.ResultSet
/*     */     //   392	630	15	resultSetFactura	java.sql.ResultSet
/*     */     //   395	421	16	resultSetBajaClimo	java.sql.ResultSet
/*     */     //   398	704	17	connection	Connection
/*     */     //   401	285	18	iNoFactura	int
/*     */     //   404	298	19	iCount	int
/*     */     //   505	235	20	facturas	java.util.ArrayList<com.claro.transfer.FacturaTO>
/*     */     //   825	34	20	e	SQLException
/*     */     //   864	34	20	e	Exception
/*     */     //   508	6	21	i	int
/*     */     //   524	33	22	sRegion	String
/*     */     //   820	1	22	localException2	Exception
/*     */     //   534	33	23	cuentaBig	java.math.BigDecimal
/*     */     //   544	109	24	fechaFac	java.math.BigDecimal
/*     */     //   635	25	25	facturaTO	com.claro.transfer.FacturaTO
/*     */     //   683	1	25	localException1	Exception
/*     */     //   903	103	26	localObject	Object
/*     */     //   923	1	27	localException3	Exception
/*     */     //   943	1	27	localException4	Exception
/*     */     //   963	1	27	localException5	Exception
/*     */     //   983	1	27	localException6	Exception
/*     */     //   1003	1	27	localException7	Exception
/*     */     //   1026	1	27	localException8	Exception
/*     */     //   1046	1	27	localException9	Exception
/*     */     //   1066	1	27	localException10	Exception
/*     */     //   1086	1	27	localException11	Exception
/*     */     //   1106	1	27	localException12	Exception
/*     */     // Exception table:
/*     */     //   from	to	target	type
/*     */     //   670	680	683	java/lang/Exception
/*     */     //   807	817	820	java/lang/Exception
/*     */     //   406	822	825	java/sql/SQLException
/*     */     //   406	822	864	java/lang/Exception
/*     */     //   406	903	903	finally
/*     */     //   910	920	923	java/lang/Exception
/*     */     //   930	940	943	java/lang/Exception
/*     */     //   950	960	963	java/lang/Exception
/*     */     //   970	980	983	java/lang/Exception
/*     */     //   990	1000	1003	java/lang/Exception
/*     */     //   1013	1023	1026	java/lang/Exception
/*     */     //   1033	1043	1046	java/lang/Exception
/*     */     //   1053	1063	1066	java/lang/Exception
/*     */     //   1073	1083	1086	java/lang/Exception
/*     */     //   1093	1103	1106	java/lang/Exception
/*     */   }
/*     */   
/*     */   /* Error */
/*     */   public com.claro.transfer.MensajeTO consultaTipoPlan(String idPlan, int nReg)
/*     */     throws CAException
/*     */   {
/*     */     // Byte code:
/*     */     //   0: aconst_null
/*     */     //   1: astore_3
/*     */     //   2: aconst_null
/*     */     //   3: astore 4
/*     */     //   5: aconst_null
/*     */     //   6: astore 5
/*     */     //   8: aconst_null
/*     */     //   9: astore 6
/*     */     //   11: aconst_null
/*     */     //   12: astore 9
/*     */     //   14: iload_2
/*     */     //   15: iconst_4
/*     */     //   16: if_icmpne +11 -> 27
/*     */     //   19: ldc_w 337
/*     */     //   22: astore 7
/*     */     //   24: goto +41 -> 65
/*     */     //   27: iload_2
/*     */     //   28: bipush 9
/*     */     //   30: if_icmpne +11 -> 41
/*     */     //   33: ldc_w 339
/*     */     //   36: astore 7
/*     */     //   38: goto +27 -> 65
/*     */     //   41: new 47	java/lang/StringBuilder
/*     */     //   44: dup
/*     */     //   45: ldc 49
/*     */     //   47: invokespecial 51	java/lang/StringBuilder:<init>	(Ljava/lang/String;)V
/*     */     //   50: iload_2
/*     */     //   51: invokevirtual 54	java/lang/StringBuilder:append	(I)Ljava/lang/StringBuilder;
/*     */     //   54: ldc_w 341
/*     */     //   57: invokevirtual 60	java/lang/StringBuilder:append	(Ljava/lang/String;)Ljava/lang/StringBuilder;
/*     */     //   60: invokevirtual 63	java/lang/StringBuilder:toString	()Ljava/lang/String;
/*     */     //   63: astore 7
/*     */     //   65: iload_2
/*     */     //   66: bipush 9
/*     */     //   68: if_icmpne +10 -> 78
/*     */     //   71: ldc 45
/*     */     //   73: astore 8
/*     */     //   75: goto +26 -> 101
/*     */     //   78: new 47	java/lang/StringBuilder
/*     */     //   81: dup
/*     */     //   82: ldc 49
/*     */     //   84: invokespecial 51	java/lang/StringBuilder:<init>	(Ljava/lang/String;)V
/*     */     //   87: iload_2
/*     */     //   88: invokevirtual 54	java/lang/StringBuilder:append	(I)Ljava/lang/StringBuilder;
/*     */     //   91: ldc 58
/*     */     //   93: invokevirtual 60	java/lang/StringBuilder:append	(Ljava/lang/String;)Ljava/lang/StringBuilder;
/*     */     //   96: invokevirtual 63	java/lang/StringBuilder:toString	()Ljava/lang/String;
/*     */     //   99: astore 8
/*     */     //   101: new 47	java/lang/StringBuilder
/*     */     //   104: dup
/*     */     //   105: ldc_w 773
/*     */     //   108: invokespecial 51	java/lang/StringBuilder:<init>	(Ljava/lang/String;)V
/*     */     //   111: aload 7
/*     */     //   113: invokevirtual 60	java/lang/StringBuilder:append	(Ljava/lang/String;)Ljava/lang/StringBuilder;
/*     */     //   116: ldc_w 775
/*     */     //   119: invokevirtual 60	java/lang/StringBuilder:append	(Ljava/lang/String;)Ljava/lang/StringBuilder;
/*     */     //   122: ldc_w 735
/*     */     //   125: invokevirtual 60	java/lang/StringBuilder:append	(Ljava/lang/String;)Ljava/lang/StringBuilder;
/*     */     //   128: iload_2
/*     */     //   129: invokevirtual 54	java/lang/StringBuilder:append	(I)Ljava/lang/StringBuilder;
/*     */     //   132: ldc_w 777
/*     */     //   135: invokevirtual 60	java/lang/StringBuilder:append	(Ljava/lang/String;)Ljava/lang/StringBuilder;
/*     */     //   138: aload_1
/*     */     //   139: invokevirtual 60	java/lang/StringBuilder:append	(Ljava/lang/String;)Ljava/lang/StringBuilder;
/*     */     //   142: ldc_w 779
/*     */     //   145: invokevirtual 60	java/lang/StringBuilder:append	(Ljava/lang/String;)Ljava/lang/StringBuilder;
/*     */     //   148: invokevirtual 63	java/lang/StringBuilder:toString	()Ljava/lang/String;
/*     */     //   151: astore 6
/*     */     //   153: iload_2
/*     */     //   154: iconst_4
/*     */     //   155: if_icmpeq +14 -> 169
/*     */     //   158: iload_2
/*     */     //   159: iconst_5
/*     */     //   160: if_icmpeq +9 -> 169
/*     */     //   163: iload_2
/*     */     //   164: bipush 9
/*     */     //   166: if_icmpne +16 -> 182
/*     */     //   169: invokestatic 298	com/claro/util/ServiceLocator:getInstance	()Lcom/claro/util/ServiceLocator;
/*     */     //   172: getstatic 304	com/claro/util/ServiceLocator:jdbcMobile459	Ljava/lang/String;
/*     */     //   175: invokevirtual 307	com/claro/util/ServiceLocator:getConnection	(Ljava/lang/String;)Ljava/sql/Connection;
/*     */     //   178: astore_3
/*     */     //   179: goto +13 -> 192
/*     */     //   182: invokestatic 298	com/claro/util/ServiceLocator:getInstance	()Lcom/claro/util/ServiceLocator;
/*     */     //   185: getstatic 311	com/claro/util/ServiceLocator:jdbcMobile	Ljava/lang/String;
/*     */     //   188: invokevirtual 307	com/claro/util/ServiceLocator:getConnection	(Ljava/lang/String;)Ljava/sql/Connection;
/*     */     //   191: astore_3
/*     */     //   192: aload_3
/*     */     //   193: invokeinterface 145 1 0
/*     */     //   198: astore 4
/*     */     //   200: aload 4
/*     */     //   202: aload 6
/*     */     //   204: invokeinterface 152 2 0
/*     */     //   209: astore 5
/*     */     //   211: new 781	com/claro/transfer/MensajeTO
/*     */     //   214: dup
/*     */     //   215: invokespecial 783	com/claro/transfer/MensajeTO:<init>	()V
/*     */     //   218: astore 9
/*     */     //   220: aload 5
/*     */     //   222: invokeinterface 158 1 0
/*     */     //   227: ifeq +141 -> 368
/*     */     //   230: aload 9
/*     */     //   232: iconst_2
/*     */     //   233: ldc_w 784
/*     */     //   236: invokevirtual 786	com/claro/transfer/MensajeTO:agregaMensaje	(ILjava/lang/String;)V
/*     */     //   239: goto +129 -> 368
/*     */     //   242: astore 10
/*     */     //   244: new 34	com/claro/exception/CAException
/*     */     //   247: dup
/*     */     //   248: iconst_0
/*     */     //   249: new 47	java/lang/StringBuilder
/*     */     //   252: dup
/*     */     //   253: ldc_w 787
/*     */     //   256: invokespecial 51	java/lang/StringBuilder:<init>	(Ljava/lang/String;)V
/*     */     //   259: aload 10
/*     */     //   261: invokevirtual 750	java/sql/SQLException:getMessage	()Ljava/lang/String;
/*     */     //   264: invokevirtual 60	java/lang/StringBuilder:append	(Ljava/lang/String;)Ljava/lang/StringBuilder;
/*     */     //   267: invokevirtual 63	java/lang/StringBuilder:toString	()Ljava/lang/String;
/*     */     //   270: invokespecial 753	com/claro/exception/CAException:<init>	(ILjava/lang/String;)V
/*     */     //   273: athrow
/*     */     //   274: astore 10
/*     */     //   276: new 34	com/claro/exception/CAException
/*     */     //   279: dup
/*     */     //   280: iconst_0
/*     */     //   281: new 47	java/lang/StringBuilder
/*     */     //   284: dup
/*     */     //   285: ldc_w 755
/*     */     //   288: invokespecial 51	java/lang/StringBuilder:<init>	(Ljava/lang/String;)V
/*     */     //   291: aload_1
/*     */     //   292: invokevirtual 60	java/lang/StringBuilder:append	(Ljava/lang/String;)Ljava/lang/StringBuilder;
/*     */     //   295: ldc_w 748
/*     */     //   298: invokevirtual 60	java/lang/StringBuilder:append	(Ljava/lang/String;)Ljava/lang/StringBuilder;
/*     */     //   301: aload 10
/*     */     //   303: invokevirtual 757	java/lang/Exception:getMessage	()Ljava/lang/String;
/*     */     //   306: invokevirtual 60	java/lang/StringBuilder:append	(Ljava/lang/String;)Ljava/lang/StringBuilder;
/*     */     //   309: invokevirtual 63	java/lang/StringBuilder:toString	()Ljava/lang/String;
/*     */     //   312: invokespecial 753	com/claro/exception/CAException:<init>	(ILjava/lang/String;)V
/*     */     //   315: athrow
/*     */     //   316: astore 11
/*     */     //   318: aload 5
/*     */     //   320: ifnull +13 -> 333
/*     */     //   323: aload 5
/*     */     //   325: invokeinterface 264 1 0
/*     */     //   330: aconst_null
/*     */     //   331: astore 5
/*     */     //   333: aload 4
/*     */     //   335: ifnull +13 -> 348
/*     */     //   338: aload 4
/*     */     //   340: invokeinterface 267 1 0
/*     */     //   345: aconst_null
/*     */     //   346: astore 4
/*     */     //   348: aload_3
/*     */     //   349: ifnull +16 -> 365
/*     */     //   352: aload_3
/*     */     //   353: invokeinterface 321 1 0
/*     */     //   358: aconst_null
/*     */     //   359: astore_3
/*     */     //   360: goto +5 -> 365
/*     */     //   363: astore 12
/*     */     //   365: aload 11
/*     */     //   367: athrow
/*     */     //   368: aload 5
/*     */     //   370: ifnull +13 -> 383
/*     */     //   373: aload 5
/*     */     //   375: invokeinterface 264 1 0
/*     */     //   380: aconst_null
/*     */     //   381: astore 5
/*     */     //   383: aload 4
/*     */     //   385: ifnull +13 -> 398
/*     */     //   388: aload 4
/*     */     //   390: invokeinterface 267 1 0
/*     */     //   395: aconst_null
/*     */     //   396: astore 4
/*     */     //   398: aload_3
/*     */     //   399: ifnull +16 -> 415
/*     */     //   402: aload_3
/*     */     //   403: invokeinterface 321 1 0
/*     */     //   408: aconst_null
/*     */     //   409: astore_3
/*     */     //   410: goto +5 -> 415
/*     */     //   413: astore 12
/*     */     //   415: aload 9
/*     */     //   417: areturn
/*     */     // Line number table:
/*     */     //   Java source line #628	-> byte code offset #0
/*     */     //   Java source line #629	-> byte code offset #2
/*     */     //   Java source line #630	-> byte code offset #5
/*     */     //   Java source line #631	-> byte code offset #8
/*     */     //   Java source line #638	-> byte code offset #11
/*     */     //   Java source line #641	-> byte code offset #14
/*     */     //   Java source line #642	-> byte code offset #27
/*     */     //   Java source line #643	-> byte code offset #41
/*     */     //   Java source line #645	-> byte code offset #65
/*     */     //   Java source line #646	-> byte code offset #78
/*     */     //   Java source line #648	-> byte code offset #101
/*     */     //   Java source line #649	-> byte code offset #111
/*     */     //   Java source line #650	-> byte code offset #122
/*     */     //   Java source line #651	-> byte code offset #142
/*     */     //   Java source line #648	-> byte code offset #148
/*     */     //   Java source line #654	-> byte code offset #153
/*     */     //   Java source line #655	-> byte code offset #169
/*     */     //   Java source line #657	-> byte code offset #182
/*     */     //   Java source line #659	-> byte code offset #192
/*     */     //   Java source line #661	-> byte code offset #200
/*     */     //   Java source line #663	-> byte code offset #211
/*     */     //   Java source line #665	-> byte code offset #220
/*     */     //   Java source line #666	-> byte code offset #230
/*     */     //   Java source line #669	-> byte code offset #242
/*     */     //   Java source line #670	-> byte code offset #244
/*     */     //   Java source line #671	-> byte code offset #274
/*     */     //   Java source line #672	-> byte code offset #276
/*     */     //   Java source line #673	-> byte code offset #316
/*     */     //   Java source line #675	-> byte code offset #318
/*     */     //   Java source line #676	-> byte code offset #333
/*     */     //   Java source line #677	-> byte code offset #348
/*     */     //   Java source line #679	-> byte code offset #363
/*     */     //   Java source line #680	-> byte code offset #365
/*     */     //   Java source line #675	-> byte code offset #368
/*     */     //   Java source line #676	-> byte code offset #383
/*     */     //   Java source line #677	-> byte code offset #398
/*     */     //   Java source line #679	-> byte code offset #413
/*     */     //   Java source line #681	-> byte code offset #415
/*     */     // Local variable table:
/*     */     //   start	length	slot	name	signature
/*     */     //   0	418	0	this	ConsultaM2KDAO
/*     */     //   0	418	1	idPlan	String
/*     */     //   0	418	2	nReg	int
/*     */     //   1	409	3	connection	Connection
/*     */     //   3	394	4	stmt	java.sql.Statement
/*     */     //   6	376	5	rset	java.sql.ResultSet
/*     */     //   9	194	6	sQuery	String
/*     */     //   22	3	7	mercadoM2K	String
/*     */     //   36	3	7	mercadoM2K	String
/*     */     //   63	49	7	mercadoM2K	String
/*     */     //   73	3	8	mertelM2K	String
/*     */     //   99	3	8	mertelM2K	String
/*     */     //   12	404	9	mensajeTO	com.claro.transfer.MensajeTO
/*     */     //   242	18	10	e	SQLException
/*     */     //   274	28	10	e	Exception
/*     */     //   316	50	11	localObject	Object
/*     */     //   363	1	12	localException1	Exception
/*     */     //   413	1	12	localException2	Exception
/*     */     // Exception table:
/*     */     //   from	to	target	type
/*     */     //   153	239	242	java/sql/SQLException
/*     */     //   153	239	274	java/lang/Exception
/*     */     //   153	316	316	finally
/*     */     //   318	360	363	java/lang/Exception
/*     */     //   368	410	413	java/lang/Exception
/*     */   }
/*     */   
/*     */   /* Error */
/*     */   public java.util.ArrayList<com.claro.transfer.membresia.MembresiaTO> consultaDatosM2KMembresias(ParametrosTO parametrosTO, com.claro.transfer.service.FileDataTO fileDataTO)
/*     */     throws CAException
/*     */   {
/*     */     // Byte code:
/*     */     //   0: aconst_null
/*     */     //   1: astore_3
/*     */     //   2: aconst_null
/*     */     //   3: astore 4
/*     */     //   5: aconst_null
/*     */     //   6: astore 5
/*     */     //   8: invokestatic 113	java/lang/System:currentTimeMillis	()J
/*     */     //   11: lstore 6
/*     */     //   13: aload_0
/*     */     //   14: getfield 21	com/claro/dao/ConsultaM2KDAO:logger	Lorg/apache/log4j/Logger;
/*     */     //   17: new 47	java/lang/StringBuilder
/*     */     //   20: dup
/*     */     //   21: ldc_w 796
/*     */     //   24: invokespecial 51	java/lang/StringBuilder:<init>	(Ljava/lang/String;)V
/*     */     //   27: getstatic 121	com/claro/util/Constantes:DATEFORMTALog	Ljava/text/SimpleDateFormat;
/*     */     //   30: new 127	java/util/Date
/*     */     //   33: dup
/*     */     //   34: invokespecial 129	java/util/Date:<init>	()V
/*     */     //   37: invokevirtual 130	java/text/SimpleDateFormat:format	(Ljava/util/Date;)Ljava/lang/String;
/*     */     //   40: invokevirtual 60	java/lang/StringBuilder:append	(Ljava/lang/String;)Ljava/lang/StringBuilder;
/*     */     //   43: ldc -120
/*     */     //   45: invokevirtual 60	java/lang/StringBuilder:append	(Ljava/lang/String;)Ljava/lang/StringBuilder;
/*     */     //   48: lload 6
/*     */     //   50: invokevirtual 138	java/lang/StringBuilder:append	(J)Ljava/lang/StringBuilder;
/*     */     //   53: invokevirtual 63	java/lang/StringBuilder:toString	()Ljava/lang/String;
/*     */     //   56: invokevirtual 141	org/apache/log4j/Logger:info	(Ljava/lang/Object;)V
/*     */     //   59: aload_0
/*     */     //   60: getfield 21	com/claro/dao/ConsultaM2KDAO:logger	Lorg/apache/log4j/Logger;
/*     */     //   63: new 47	java/lang/StringBuilder
/*     */     //   66: dup
/*     */     //   67: ldc_w 798
/*     */     //   70: invokespecial 51	java/lang/StringBuilder:<init>	(Ljava/lang/String;)V
/*     */     //   73: getstatic 121	com/claro/util/Constantes:DATEFORMTALog	Ljava/text/SimpleDateFormat;
/*     */     //   76: new 127	java/util/Date
/*     */     //   79: dup
/*     */     //   80: invokespecial 129	java/util/Date:<init>	()V
/*     */     //   83: invokevirtual 130	java/text/SimpleDateFormat:format	(Ljava/util/Date;)Ljava/lang/String;
/*     */     //   86: invokevirtual 60	java/lang/StringBuilder:append	(Ljava/lang/String;)Ljava/lang/StringBuilder;
/*     */     //   89: ldc -120
/*     */     //   91: invokevirtual 60	java/lang/StringBuilder:append	(Ljava/lang/String;)Ljava/lang/StringBuilder;
/*     */     //   94: lload 6
/*     */     //   96: invokevirtual 138	java/lang/StringBuilder:append	(J)Ljava/lang/StringBuilder;
/*     */     //   99: invokevirtual 63	java/lang/StringBuilder:toString	()Ljava/lang/String;
/*     */     //   102: invokevirtual 141	org/apache/log4j/Logger:info	(Ljava/lang/Object;)V
/*     */     //   105: aload_1
/*     */     //   106: invokevirtual 39	com/claro/transfer/ParametrosTO:getRegion	()I
/*     */     //   109: iconst_4
/*     */     //   110: if_icmpeq +20 -> 130
/*     */     //   113: aload_1
/*     */     //   114: invokevirtual 39	com/claro/transfer/ParametrosTO:getRegion	()I
/*     */     //   117: iconst_5
/*     */     //   118: if_icmpeq +12 -> 130
/*     */     //   121: aload_1
/*     */     //   122: invokevirtual 39	com/claro/transfer/ParametrosTO:getRegion	()I
/*     */     //   125: bipush 9
/*     */     //   127: if_icmpne +16 -> 143
/*     */     //   130: invokestatic 298	com/claro/util/ServiceLocator:getInstance	()Lcom/claro/util/ServiceLocator;
/*     */     //   133: getstatic 304	com/claro/util/ServiceLocator:jdbcMobile459	Ljava/lang/String;
/*     */     //   136: invokevirtual 307	com/claro/util/ServiceLocator:getConnection	(Ljava/lang/String;)Ljava/sql/Connection;
/*     */     //   139: astore_3
/*     */     //   140: goto +13 -> 153
/*     */     //   143: invokestatic 298	com/claro/util/ServiceLocator:getInstance	()Lcom/claro/util/ServiceLocator;
/*     */     //   146: getstatic 311	com/claro/util/ServiceLocator:jdbcMobile	Ljava/lang/String;
/*     */     //   149: invokevirtual 307	com/claro/util/ServiceLocator:getConnection	(Ljava/lang/String;)Ljava/sql/Connection;
/*     */     //   152: astore_3
/*     */     //   153: aload_0
/*     */     //   154: getfield 21	com/claro/dao/ConsultaM2KDAO:logger	Lorg/apache/log4j/Logger;
/*     */     //   157: new 47	java/lang/StringBuilder
/*     */     //   160: dup
/*     */     //   161: ldc_w 314
/*     */     //   164: invokespecial 51	java/lang/StringBuilder:<init>	(Ljava/lang/String;)V
/*     */     //   167: getstatic 121	com/claro/util/Constantes:DATEFORMTALog	Ljava/text/SimpleDateFormat;
/*     */     //   170: new 127	java/util/Date
/*     */     //   173: dup
/*     */     //   174: invokespecial 129	java/util/Date:<init>	()V
/*     */     //   177: invokevirtual 130	java/text/SimpleDateFormat:format	(Ljava/util/Date;)Ljava/lang/String;
/*     */     //   180: invokevirtual 60	java/lang/StringBuilder:append	(Ljava/lang/String;)Ljava/lang/StringBuilder;
/*     */     //   183: ldc -120
/*     */     //   185: invokevirtual 60	java/lang/StringBuilder:append	(Ljava/lang/String;)Ljava/lang/StringBuilder;
/*     */     //   188: invokestatic 113	java/lang/System:currentTimeMillis	()J
/*     */     //   191: lload 6
/*     */     //   193: lsub
/*     */     //   194: invokevirtual 138	java/lang/StringBuilder:append	(J)Ljava/lang/StringBuilder;
/*     */     //   197: invokevirtual 63	java/lang/StringBuilder:toString	()Ljava/lang/String;
/*     */     //   200: invokevirtual 141	org/apache/log4j/Logger:info	(Ljava/lang/Object;)V
/*     */     //   203: new 614	java/util/ArrayList
/*     */     //   206: dup
/*     */     //   207: invokespecial 616	java/util/ArrayList:<init>	()V
/*     */     //   210: astore 5
/*     */     //   212: aconst_null
/*     */     //   213: astore 8
/*     */     //   215: aconst_null
/*     */     //   216: astore 9
/*     */     //   218: new 800	java/io/InputStreamReader
/*     */     //   221: dup
/*     */     //   222: aload_2
/*     */     //   223: invokevirtual 802	com/claro/transfer/service/FileDataTO:getData	()Ljava/io/InputStream;
/*     */     //   226: invokespecial 808	java/io/InputStreamReader:<init>	(Ljava/io/InputStream;)V
/*     */     //   229: astore 8
/*     */     //   231: new 811	java/io/BufferedReader
/*     */     //   234: dup
/*     */     //   235: aload 8
/*     */     //   237: invokespecial 813	java/io/BufferedReader:<init>	(Ljava/io/Reader;)V
/*     */     //   240: astore 9
/*     */     //   242: ldc_w 511
/*     */     //   245: astore 10
/*     */     //   247: goto +146 -> 393
/*     */     //   250: aload 10
/*     */     //   252: ldc_w 511
/*     */     //   255: invokevirtual 485	java/lang/String:equals	(Ljava/lang/Object;)Z
/*     */     //   258: ifne +135 -> 393
/*     */     //   261: new 816	com/claro/transfer/membresia/MembresiaTO
/*     */     //   264: dup
/*     */     //   265: invokespecial 818	com/claro/transfer/membresia/MembresiaTO:<init>	()V
/*     */     //   268: astore 11
/*     */     //   270: aload_1
/*     */     //   271: aload 10
/*     */     //   273: ldc_w 819
/*     */     //   276: ldc_w 511
/*     */     //   279: invokevirtual 821	java/lang/String:replace	(Ljava/lang/CharSequence;Ljava/lang/CharSequence;)Ljava/lang/String;
/*     */     //   282: invokevirtual 508	java/lang/String:trim	()Ljava/lang/String;
/*     */     //   285: invokevirtual 825	com/claro/transfer/ParametrosTO:setTelefono	(Ljava/lang/String;)V
/*     */     //   288: aload_0
/*     */     //   289: aload_1
/*     */     //   290: aload_3
/*     */     //   291: invokespecial 316	com/claro/dao/ConsultaM2KDAO:consultaMobile	(Lcom/claro/transfer/ParametrosTO;Ljava/sql/Connection;)Lcom/claro/transfer/MobileTO;
/*     */     //   294: astore 4
/*     */     //   296: aload 4
/*     */     //   298: invokevirtual 318	com/claro/transfer/MobileTO:getIdMensaje	()I
/*     */     //   301: ifne +14 -> 315
/*     */     //   304: aload_0
/*     */     //   305: aload_1
/*     */     //   306: invokevirtual 39	com/claro/transfer/ParametrosTO:getRegion	()I
/*     */     //   309: aload 4
/*     */     //   311: aload_3
/*     */     //   312: invokespecial 826	com/claro/dao/ConsultaM2KDAO:obtieneDatosCtesMembresiaM2K	(ILcom/claro/transfer/MobileTO;Ljava/sql/Connection;)V
/*     */     //   315: aload 4
/*     */     //   317: invokevirtual 318	com/claro/transfer/MobileTO:getIdMensaje	()I
/*     */     //   320: ifne +73 -> 393
/*     */     //   323: aload 11
/*     */     //   325: aload_1
/*     */     //   326: invokevirtual 86	com/claro/transfer/ParametrosTO:getTelefono	()Ljava/lang/String;
/*     */     //   329: invokevirtual 829	com/claro/transfer/membresia/MembresiaTO:setTelefono	(Ljava/lang/String;)V
/*     */     //   332: aload 11
/*     */     //   334: aload 4
/*     */     //   336: invokevirtual 237	com/claro/transfer/MobileTO:getCuenta	()Ljava/lang/String;
/*     */     //   339: invokevirtual 830	com/claro/transfer/membresia/MembresiaTO:setCuenta	(Ljava/lang/String;)V
/*     */     //   342: aload 11
/*     */     //   344: aload 4
/*     */     //   346: invokevirtual 410	com/claro/transfer/MobileTO:getSecuencia	()Ljava/lang/String;
/*     */     //   349: invokestatic 631	java/lang/Integer:parseInt	(Ljava/lang/String;)I
/*     */     //   352: invokevirtual 831	com/claro/transfer/membresia/MembresiaTO:setSecuencia	(I)V
/*     */     //   355: aload 11
/*     */     //   357: aload 4
/*     */     //   359: invokevirtual 833	com/claro/transfer/MobileTO:getNombre	()Ljava/lang/String;
/*     */     //   362: invokevirtual 836	com/claro/transfer/membresia/MembresiaTO:setNombre	(Ljava/lang/String;)V
/*     */     //   365: aload 11
/*     */     //   367: aload 4
/*     */     //   369: invokevirtual 839	com/claro/transfer/MobileTO:getFirstName	()Ljava/lang/String;
/*     */     //   372: invokevirtual 842	com/claro/transfer/membresia/MembresiaTO:setApPaterno	(Ljava/lang/String;)V
/*     */     //   375: aload 11
/*     */     //   377: aload 4
/*     */     //   379: invokevirtual 845	com/claro/transfer/MobileTO:getLastName	()Ljava/lang/String;
/*     */     //   382: invokevirtual 848	com/claro/transfer/membresia/MembresiaTO:setApMaterno	(Ljava/lang/String;)V
/*     */     //   385: aload 5
/*     */     //   387: aload 11
/*     */     //   389: invokevirtual 656	java/util/ArrayList:add	(Ljava/lang/Object;)Z
/*     */     //   392: pop
/*     */     //   393: aload 9
/*     */     //   395: invokevirtual 851	java/io/BufferedReader:readLine	()Ljava/lang/String;
/*     */     //   398: dup
/*     */     //   399: astore 10
/*     */     //   401: ifnonnull -151 -> 250
/*     */     //   404: aload_0
/*     */     //   405: getfield 21	com/claro/dao/ConsultaM2KDAO:logger	Lorg/apache/log4j/Logger;
/*     */     //   408: new 47	java/lang/StringBuilder
/*     */     //   411: dup
/*     */     //   412: ldc_w 854
/*     */     //   415: invokespecial 51	java/lang/StringBuilder:<init>	(Ljava/lang/String;)V
/*     */     //   418: getstatic 121	com/claro/util/Constantes:DATEFORMTALog	Ljava/text/SimpleDateFormat;
/*     */     //   421: new 127	java/util/Date
/*     */     //   424: dup
/*     */     //   425: invokespecial 129	java/util/Date:<init>	()V
/*     */     //   428: invokevirtual 130	java/text/SimpleDateFormat:format	(Ljava/util/Date;)Ljava/lang/String;
/*     */     //   431: invokevirtual 60	java/lang/StringBuilder:append	(Ljava/lang/String;)Ljava/lang/StringBuilder;
/*     */     //   434: ldc -120
/*     */     //   436: invokevirtual 60	java/lang/StringBuilder:append	(Ljava/lang/String;)Ljava/lang/StringBuilder;
/*     */     //   439: invokestatic 113	java/lang/System:currentTimeMillis	()J
/*     */     //   442: lload 6
/*     */     //   444: lsub
/*     */     //   445: invokevirtual 138	java/lang/StringBuilder:append	(J)Ljava/lang/StringBuilder;
/*     */     //   448: invokevirtual 63	java/lang/StringBuilder:toString	()Ljava/lang/String;
/*     */     //   451: invokevirtual 141	org/apache/log4j/Logger:info	(Ljava/lang/Object;)V
/*     */     //   454: goto +127 -> 581
/*     */     //   457: astore 6
/*     */     //   459: aload_0
/*     */     //   460: getfield 25	com/claro/dao/ConsultaM2KDAO:error	Lorg/apache/log4j/Logger;
/*     */     //   463: ldc_w 856
/*     */     //   466: aload 6
/*     */     //   468: invokevirtual 244	org/apache/log4j/Logger:info	(Ljava/lang/Object;Ljava/lang/Throwable;)V
/*     */     //   471: new 34	com/claro/exception/CAException
/*     */     //   474: dup
/*     */     //   475: iconst_m1
/*     */     //   476: new 47	java/lang/StringBuilder
/*     */     //   479: dup
/*     */     //   480: ldc_w 858
/*     */     //   483: invokespecial 51	java/lang/StringBuilder:<init>	(Ljava/lang/String;)V
/*     */     //   486: aload 6
/*     */     //   488: invokevirtual 249	java/sql/SQLException:toString	()Ljava/lang/String;
/*     */     //   491: invokevirtual 60	java/lang/StringBuilder:append	(Ljava/lang/String;)Ljava/lang/StringBuilder;
/*     */     //   494: ldc -4
/*     */     //   496: invokevirtual 60	java/lang/StringBuilder:append	(Ljava/lang/String;)Ljava/lang/StringBuilder;
/*     */     //   499: invokevirtual 63	java/lang/StringBuilder:toString	()Ljava/lang/String;
/*     */     //   502: aload 6
/*     */     //   504: invokespecial 254	com/claro/exception/CAException:<init>	(ILjava/lang/String;Ljava/lang/Exception;)V
/*     */     //   507: athrow
/*     */     //   508: astore 6
/*     */     //   510: aload_0
/*     */     //   511: getfield 25	com/claro/dao/ConsultaM2KDAO:error	Lorg/apache/log4j/Logger;
/*     */     //   514: ldc_w 860
/*     */     //   517: aload 6
/*     */     //   519: invokevirtual 244	org/apache/log4j/Logger:info	(Ljava/lang/Object;Ljava/lang/Throwable;)V
/*     */     //   522: new 34	com/claro/exception/CAException
/*     */     //   525: dup
/*     */     //   526: iconst_m1
/*     */     //   527: new 47	java/lang/StringBuilder
/*     */     //   530: dup
/*     */     //   531: ldc_w 862
/*     */     //   534: invokespecial 51	java/lang/StringBuilder:<init>	(Ljava/lang/String;)V
/*     */     //   537: aload 6
/*     */     //   539: invokevirtual 261	java/lang/Exception:toString	()Ljava/lang/String;
/*     */     //   542: invokevirtual 60	java/lang/StringBuilder:append	(Ljava/lang/String;)Ljava/lang/StringBuilder;
/*     */     //   545: ldc -4
/*     */     //   547: invokevirtual 60	java/lang/StringBuilder:append	(Ljava/lang/String;)Ljava/lang/StringBuilder;
/*     */     //   550: invokevirtual 63	java/lang/StringBuilder:toString	()Ljava/lang/String;
/*     */     //   553: aload 6
/*     */     //   555: invokespecial 254	com/claro/exception/CAException:<init>	(ILjava/lang/String;Ljava/lang/Exception;)V
/*     */     //   558: athrow
/*     */     //   559: astore 12
/*     */     //   561: aload_3
/*     */     //   562: ifnull +16 -> 578
/*     */     //   565: aload_3
/*     */     //   566: invokeinterface 321 1 0
/*     */     //   571: aconst_null
/*     */     //   572: astore_3
/*     */     //   573: goto +5 -> 578
/*     */     //   576: astore 13
/*     */     //   578: aload 12
/*     */     //   580: athrow
/*     */     //   581: aload_3
/*     */     //   582: ifnull +16 -> 598
/*     */     //   585: aload_3
/*     */     //   586: invokeinterface 321 1 0
/*     */     //   591: aconst_null
/*     */     //   592: astore_3
/*     */     //   593: goto +5 -> 598
/*     */     //   596: astore 13
/*     */     //   598: aload 5
/*     */     //   600: areturn
/*     */     // Line number table:
/*     */     //   Java source line #689	-> byte code offset #0
/*     */     //   Java source line #690	-> byte code offset #2
/*     */     //   Java source line #692	-> byte code offset #5
/*     */     //   Java source line #694	-> byte code offset #8
/*     */     //   Java source line #695	-> byte code offset #13
/*     */     //   Java source line #696	-> byte code offset #59
/*     */     //   Java source line #698	-> byte code offset #105
/*     */     //   Java source line #699	-> byte code offset #130
/*     */     //   Java source line #701	-> byte code offset #143
/*     */     //   Java source line #702	-> byte code offset #153
/*     */     //   Java source line #704	-> byte code offset #203
/*     */     //   Java source line #706	-> byte code offset #212
/*     */     //   Java source line #707	-> byte code offset #215
/*     */     //   Java source line #709	-> byte code offset #218
/*     */     //   Java source line #710	-> byte code offset #231
/*     */     //   Java source line #711	-> byte code offset #242
/*     */     //   Java source line #712	-> byte code offset #247
/*     */     //   Java source line #713	-> byte code offset #250
/*     */     //   Java source line #714	-> byte code offset #261
/*     */     //   Java source line #715	-> byte code offset #270
/*     */     //   Java source line #716	-> byte code offset #288
/*     */     //   Java source line #718	-> byte code offset #296
/*     */     //   Java source line #719	-> byte code offset #304
/*     */     //   Java source line #720	-> byte code offset #315
/*     */     //   Java source line #721	-> byte code offset #323
/*     */     //   Java source line #722	-> byte code offset #332
/*     */     //   Java source line #723	-> byte code offset #342
/*     */     //   Java source line #724	-> byte code offset #355
/*     */     //   Java source line #725	-> byte code offset #365
/*     */     //   Java source line #726	-> byte code offset #375
/*     */     //   Java source line #727	-> byte code offset #385
/*     */     //   Java source line #712	-> byte code offset #393
/*     */     //   Java source line #731	-> byte code offset #404
/*     */     //   Java source line #733	-> byte code offset #457
/*     */     //   Java source line #734	-> byte code offset #459
/*     */     //   Java source line #735	-> byte code offset #471
/*     */     //   Java source line #736	-> byte code offset #508
/*     */     //   Java source line #737	-> byte code offset #510
/*     */     //   Java source line #738	-> byte code offset #522
/*     */     //   Java source line #739	-> byte code offset #559
/*     */     //   Java source line #740	-> byte code offset #561
/*     */     //   Java source line #741	-> byte code offset #578
/*     */     //   Java source line #740	-> byte code offset #581
/*     */     //   Java source line #742	-> byte code offset #598
/*     */     // Local variable table:
/*     */     //   start	length	slot	name	signature
/*     */     //   0	601	0	this	ConsultaM2KDAO
/*     */     //   0	601	1	parametrosTO	ParametrosTO
/*     */     //   0	601	2	fileDataTO	com.claro.transfer.service.FileDataTO
/*     */     //   1	592	3	connection	Connection
/*     */     //   3	375	4	mobileTO	MobileTO
/*     */     //   6	593	5	arrayMembresia	java.util.ArrayList<com.claro.transfer.membresia.MembresiaTO>
/*     */     //   11	432	6	inicioProceso	long
/*     */     //   457	46	6	e	SQLException
/*     */     //   508	46	6	e	Exception
/*     */     //   213	23	8	inputStreamReader	java.io.InputStreamReader
/*     */     //   216	178	9	reader	java.io.BufferedReader
/*     */     //   245	155	10	telefono	String
/*     */     //   268	120	11	membresiaTO	com.claro.transfer.membresia.MembresiaTO
/*     */     //   559	20	12	localObject	Object
/*     */     //   576	1	13	localException1	Exception
/*     */     //   596	1	13	localException2	Exception
/*     */     // Exception table:
/*     */     //   from	to	target	type
/*     */     //   8	454	457	java/sql/SQLException
/*     */     //   8	454	508	java/lang/Exception
/*     */     //   8	559	559	finally
/*     */     //   565	573	576	java/lang/Exception
/*     */     //   585	593	596	java/lang/Exception
/*     */   }
/*     */   
/*     */   /* Error */
/*     */   private void obtieneDatosCtesMembresiaM2K(int region, MobileTO mobileTO, Connection connection)
/*     */     throws CAException
/*     */   {
/*     */     // Byte code:
/*     */     //   0: iload_1
/*     */     //   1: iconst_4
/*     */     //   2: if_icmpne +11 -> 13
/*     */     //   5: ldc_w 337
/*     */     //   8: astore 4
/*     */     //   10: goto +41 -> 51
/*     */     //   13: iload_1
/*     */     //   14: bipush 9
/*     */     //   16: if_icmpne +11 -> 27
/*     */     //   19: ldc_w 339
/*     */     //   22: astore 4
/*     */     //   24: goto +27 -> 51
/*     */     //   27: new 47	java/lang/StringBuilder
/*     */     //   30: dup
/*     */     //   31: ldc 49
/*     */     //   33: invokespecial 51	java/lang/StringBuilder:<init>	(Ljava/lang/String;)V
/*     */     //   36: iload_1
/*     */     //   37: invokevirtual 54	java/lang/StringBuilder:append	(I)Ljava/lang/StringBuilder;
/*     */     //   40: ldc_w 341
/*     */     //   43: invokevirtual 60	java/lang/StringBuilder:append	(Ljava/lang/String;)Ljava/lang/StringBuilder;
/*     */     //   46: invokevirtual 63	java/lang/StringBuilder:toString	()Ljava/lang/String;
/*     */     //   49: astore 4
/*     */     //   51: new 36	java/lang/StringBuffer
/*     */     //   54: dup
/*     */     //   55: invokespecial 38	java/lang/StringBuffer:<init>	()V
/*     */     //   58: astore 5
/*     */     //   60: aload 5
/*     */     //   62: ldc_w 875
/*     */     //   65: invokevirtual 69	java/lang/StringBuffer:append	(Ljava/lang/String;)Ljava/lang/StringBuffer;
/*     */     //   68: pop
/*     */     //   69: aload 5
/*     */     //   71: ldc_w 381
/*     */     //   74: invokevirtual 69	java/lang/StringBuffer:append	(Ljava/lang/String;)Ljava/lang/StringBuffer;
/*     */     //   77: aload 4
/*     */     //   79: invokevirtual 69	java/lang/StringBuffer:append	(Ljava/lang/String;)Ljava/lang/StringBuffer;
/*     */     //   82: ldc_w 877
/*     */     //   85: invokevirtual 69	java/lang/StringBuffer:append	(Ljava/lang/String;)Ljava/lang/StringBuffer;
/*     */     //   88: pop
/*     */     //   89: aload 5
/*     */     //   91: aload 4
/*     */     //   93: invokevirtual 69	java/lang/StringBuffer:append	(Ljava/lang/String;)Ljava/lang/StringBuffer;
/*     */     //   96: ldc_w 879
/*     */     //   99: invokevirtual 69	java/lang/StringBuffer:append	(Ljava/lang/String;)Ljava/lang/StringBuffer;
/*     */     //   102: pop
/*     */     //   103: aload 5
/*     */     //   105: ldc_w 881
/*     */     //   108: invokevirtual 69	java/lang/StringBuffer:append	(Ljava/lang/String;)Ljava/lang/StringBuffer;
/*     */     //   111: iload_1
/*     */     //   112: invokevirtual 399	java/lang/StringBuffer:append	(I)Ljava/lang/StringBuffer;
/*     */     //   115: ldc_w 402
/*     */     //   118: invokevirtual 69	java/lang/StringBuffer:append	(Ljava/lang/String;)Ljava/lang/StringBuffer;
/*     */     //   121: pop
/*     */     //   122: aload 5
/*     */     //   124: ldc_w 883
/*     */     //   127: invokevirtual 69	java/lang/StringBuffer:append	(Ljava/lang/String;)Ljava/lang/StringBuffer;
/*     */     //   130: aload_2
/*     */     //   131: invokevirtual 237	com/claro/transfer/MobileTO:getCuenta	()Ljava/lang/String;
/*     */     //   134: invokevirtual 69	java/lang/StringBuffer:append	(Ljava/lang/String;)Ljava/lang/StringBuffer;
/*     */     //   137: pop
/*     */     //   138: aload 5
/*     */     //   140: ldc_w 885
/*     */     //   143: invokevirtual 69	java/lang/StringBuffer:append	(Ljava/lang/String;)Ljava/lang/StringBuffer;
/*     */     //   146: pop
/*     */     //   147: aload 5
/*     */     //   149: ldc_w 887
/*     */     //   152: invokevirtual 69	java/lang/StringBuffer:append	(Ljava/lang/String;)Ljava/lang/StringBuffer;
/*     */     //   155: pop
/*     */     //   156: aload 5
/*     */     //   158: ldc_w 889
/*     */     //   161: invokevirtual 69	java/lang/StringBuffer:append	(Ljava/lang/String;)Ljava/lang/StringBuffer;
/*     */     //   164: pop
/*     */     //   165: aload 5
/*     */     //   167: ldc_w 891
/*     */     //   170: invokevirtual 69	java/lang/StringBuffer:append	(Ljava/lang/String;)Ljava/lang/StringBuffer;
/*     */     //   173: pop
/*     */     //   174: aload 5
/*     */     //   176: ldc_w 893
/*     */     //   179: invokevirtual 69	java/lang/StringBuffer:append	(Ljava/lang/String;)Ljava/lang/StringBuffer;
/*     */     //   182: pop
/*     */     //   183: aload 5
/*     */     //   185: ldc_w 895
/*     */     //   188: invokevirtual 69	java/lang/StringBuffer:append	(Ljava/lang/String;)Ljava/lang/StringBuffer;
/*     */     //   191: pop
/*     */     //   192: aconst_null
/*     */     //   193: astore 6
/*     */     //   195: aconst_null
/*     */     //   196: astore 7
/*     */     //   198: invokestatic 113	java/lang/System:currentTimeMillis	()J
/*     */     //   201: lstore 8
/*     */     //   203: aload_0
/*     */     //   204: getfield 21	com/claro/dao/ConsultaM2KDAO:logger	Lorg/apache/log4j/Logger;
/*     */     //   207: new 47	java/lang/StringBuilder
/*     */     //   210: dup
/*     */     //   211: ldc_w 897
/*     */     //   214: invokespecial 51	java/lang/StringBuilder:<init>	(Ljava/lang/String;)V
/*     */     //   217: getstatic 121	com/claro/util/Constantes:DATEFORMTALog	Ljava/text/SimpleDateFormat;
/*     */     //   220: new 127	java/util/Date
/*     */     //   223: dup
/*     */     //   224: invokespecial 129	java/util/Date:<init>	()V
/*     */     //   227: invokevirtual 130	java/text/SimpleDateFormat:format	(Ljava/util/Date;)Ljava/lang/String;
/*     */     //   230: invokevirtual 60	java/lang/StringBuilder:append	(Ljava/lang/String;)Ljava/lang/StringBuilder;
/*     */     //   233: ldc -120
/*     */     //   235: invokevirtual 60	java/lang/StringBuilder:append	(Ljava/lang/String;)Ljava/lang/StringBuilder;
/*     */     //   238: lload 8
/*     */     //   240: invokevirtual 138	java/lang/StringBuilder:append	(J)Ljava/lang/StringBuilder;
/*     */     //   243: invokevirtual 63	java/lang/StringBuilder:toString	()Ljava/lang/String;
/*     */     //   246: invokevirtual 141	org/apache/log4j/Logger:info	(Ljava/lang/Object;)V
/*     */     //   249: aload_3
/*     */     //   250: invokeinterface 145 1 0
/*     */     //   255: astore 6
/*     */     //   257: aload 6
/*     */     //   259: aload 5
/*     */     //   261: invokevirtual 151	java/lang/StringBuffer:toString	()Ljava/lang/String;
/*     */     //   264: invokeinterface 152 2 0
/*     */     //   269: astore 7
/*     */     //   271: aload 7
/*     */     //   273: invokeinterface 158 1 0
/*     */     //   278: ifeq +42 -> 320
/*     */     //   281: aload_2
/*     */     //   282: aload 7
/*     */     //   284: ldc_w 448
/*     */     //   287: invokeinterface 166 2 0
/*     */     //   292: invokevirtual 450	com/claro/transfer/MobileTO:setLastName	(Ljava/lang/String;)V
/*     */     //   295: aload_2
/*     */     //   296: aload 7
/*     */     //   298: ldc_w 453
/*     */     //   301: invokeinterface 166 2 0
/*     */     //   306: invokevirtual 455	com/claro/transfer/MobileTO:setFirstName	(Ljava/lang/String;)V
/*     */     //   309: aload_2
/*     */     //   310: iconst_0
/*     */     //   311: ldc_w 538
/*     */     //   314: invokevirtual 231	com/claro/transfer/MobileTO:agregaMensaje	(ILjava/lang/String;)V
/*     */     //   317: goto +11 -> 328
/*     */     //   320: aload_2
/*     */     //   321: iconst_m1
/*     */     //   322: ldc_w 899
/*     */     //   325: invokevirtual 231	com/claro/transfer/MobileTO:agregaMensaje	(ILjava/lang/String;)V
/*     */     //   328: aload_0
/*     */     //   329: getfield 21	com/claro/dao/ConsultaM2KDAO:logger	Lorg/apache/log4j/Logger;
/*     */     //   332: new 47	java/lang/StringBuilder
/*     */     //   335: dup
/*     */     //   336: ldc_w 901
/*     */     //   339: invokespecial 51	java/lang/StringBuilder:<init>	(Ljava/lang/String;)V
/*     */     //   342: getstatic 121	com/claro/util/Constantes:DATEFORMTALog	Ljava/text/SimpleDateFormat;
/*     */     //   345: new 127	java/util/Date
/*     */     //   348: dup
/*     */     //   349: invokespecial 129	java/util/Date:<init>	()V
/*     */     //   352: invokevirtual 130	java/text/SimpleDateFormat:format	(Ljava/util/Date;)Ljava/lang/String;
/*     */     //   355: invokevirtual 60	java/lang/StringBuilder:append	(Ljava/lang/String;)Ljava/lang/StringBuilder;
/*     */     //   358: ldc -120
/*     */     //   360: invokevirtual 60	java/lang/StringBuilder:append	(Ljava/lang/String;)Ljava/lang/StringBuilder;
/*     */     //   363: invokestatic 113	java/lang/System:currentTimeMillis	()J
/*     */     //   366: lload 8
/*     */     //   368: lsub
/*     */     //   369: invokevirtual 138	java/lang/StringBuilder:append	(J)Ljava/lang/StringBuilder;
/*     */     //   372: invokevirtual 63	java/lang/StringBuilder:toString	()Ljava/lang/String;
/*     */     //   375: invokevirtual 141	org/apache/log4j/Logger:info	(Ljava/lang/Object;)V
/*     */     //   378: goto +150 -> 528
/*     */     //   381: astore 8
/*     */     //   383: aload_0
/*     */     //   384: getfield 25	com/claro/dao/ConsultaM2KDAO:error	Lorg/apache/log4j/Logger;
/*     */     //   387: ldc_w 903
/*     */     //   390: aload 8
/*     */     //   392: invokevirtual 244	org/apache/log4j/Logger:info	(Ljava/lang/Object;Ljava/lang/Throwable;)V
/*     */     //   395: new 34	com/claro/exception/CAException
/*     */     //   398: dup
/*     */     //   399: iconst_m1
/*     */     //   400: new 47	java/lang/StringBuilder
/*     */     //   403: dup
/*     */     //   404: ldc_w 905
/*     */     //   407: invokespecial 51	java/lang/StringBuilder:<init>	(Ljava/lang/String;)V
/*     */     //   410: aload 8
/*     */     //   412: invokevirtual 249	java/sql/SQLException:toString	()Ljava/lang/String;
/*     */     //   415: invokevirtual 60	java/lang/StringBuilder:append	(Ljava/lang/String;)Ljava/lang/StringBuilder;
/*     */     //   418: ldc -4
/*     */     //   420: invokevirtual 60	java/lang/StringBuilder:append	(Ljava/lang/String;)Ljava/lang/StringBuilder;
/*     */     //   423: invokevirtual 63	java/lang/StringBuilder:toString	()Ljava/lang/String;
/*     */     //   426: aload 8
/*     */     //   428: invokespecial 254	com/claro/exception/CAException:<init>	(ILjava/lang/String;Ljava/lang/Exception;)V
/*     */     //   431: athrow
/*     */     //   432: astore 8
/*     */     //   434: aload_0
/*     */     //   435: getfield 25	com/claro/dao/ConsultaM2KDAO:error	Lorg/apache/log4j/Logger;
/*     */     //   438: ldc_w 907
/*     */     //   441: aload 8
/*     */     //   443: invokevirtual 244	org/apache/log4j/Logger:info	(Ljava/lang/Object;Ljava/lang/Throwable;)V
/*     */     //   446: new 34	com/claro/exception/CAException
/*     */     //   449: dup
/*     */     //   450: iconst_m1
/*     */     //   451: new 47	java/lang/StringBuilder
/*     */     //   454: dup
/*     */     //   455: ldc_w 909
/*     */     //   458: invokespecial 51	java/lang/StringBuilder:<init>	(Ljava/lang/String;)V
/*     */     //   461: aload 8
/*     */     //   463: invokevirtual 261	java/lang/Exception:toString	()Ljava/lang/String;
/*     */     //   466: invokevirtual 60	java/lang/StringBuilder:append	(Ljava/lang/String;)Ljava/lang/StringBuilder;
/*     */     //   469: ldc -4
/*     */     //   471: invokevirtual 60	java/lang/StringBuilder:append	(Ljava/lang/String;)Ljava/lang/StringBuilder;
/*     */     //   474: invokevirtual 63	java/lang/StringBuilder:toString	()Ljava/lang/String;
/*     */     //   477: aload 8
/*     */     //   479: invokespecial 254	com/claro/exception/CAException:<init>	(ILjava/lang/String;Ljava/lang/Exception;)V
/*     */     //   482: athrow
/*     */     //   483: astore 10
/*     */     //   485: aload 7
/*     */     //   487: ifnull +18 -> 505
/*     */     //   490: aload 7
/*     */     //   492: invokeinterface 264 1 0
/*     */     //   497: aconst_null
/*     */     //   498: astore 7
/*     */     //   500: goto +5 -> 505
/*     */     //   503: astore 11
/*     */     //   505: aload 6
/*     */     //   507: ifnull +18 -> 525
/*     */     //   510: aload 6
/*     */     //   512: invokeinterface 267 1 0
/*     */     //   517: aconst_null
/*     */     //   518: astore 6
/*     */     //   520: goto +5 -> 525
/*     */     //   523: astore 11
/*     */     //   525: aload 10
/*     */     //   527: athrow
/*     */     //   528: aload 7
/*     */     //   530: ifnull +18 -> 548
/*     */     //   533: aload 7
/*     */     //   535: invokeinterface 264 1 0
/*     */     //   540: aconst_null
/*     */     //   541: astore 7
/*     */     //   543: goto +5 -> 548
/*     */     //   546: astore 11
/*     */     //   548: aload 6
/*     */     //   550: ifnull +18 -> 568
/*     */     //   553: aload 6
/*     */     //   555: invokeinterface 267 1 0
/*     */     //   560: aconst_null
/*     */     //   561: astore 6
/*     */     //   563: goto +5 -> 568
/*     */     //   566: astore 11
/*     */     //   568: return
/*     */     // Line number table:
/*     */     //   Java source line #748	-> byte code offset #0
/*     */     //   Java source line #749	-> byte code offset #5
/*     */     //   Java source line #750	-> byte code offset #13
/*     */     //   Java source line #751	-> byte code offset #19
/*     */     //   Java source line #753	-> byte code offset #27
/*     */     //   Java source line #755	-> byte code offset #51
/*     */     //   Java source line #757	-> byte code offset #60
/*     */     //   Java source line #758	-> byte code offset #69
/*     */     //   Java source line #759	-> byte code offset #89
/*     */     //   Java source line #760	-> byte code offset #103
/*     */     //   Java source line #761	-> byte code offset #122
/*     */     //   Java source line #762	-> byte code offset #138
/*     */     //   Java source line #763	-> byte code offset #147
/*     */     //   Java source line #764	-> byte code offset #156
/*     */     //   Java source line #765	-> byte code offset #165
/*     */     //   Java source line #766	-> byte code offset #174
/*     */     //   Java source line #767	-> byte code offset #183
/*     */     //   Java source line #769	-> byte code offset #192
/*     */     //   Java source line #770	-> byte code offset #195
/*     */     //   Java source line #773	-> byte code offset #198
/*     */     //   Java source line #774	-> byte code offset #203
/*     */     //   Java source line #775	-> byte code offset #249
/*     */     //   Java source line #776	-> byte code offset #257
/*     */     //   Java source line #777	-> byte code offset #271
/*     */     //   Java source line #779	-> byte code offset #281
/*     */     //   Java source line #780	-> byte code offset #295
/*     */     //   Java source line #781	-> byte code offset #309
/*     */     //   Java source line #783	-> byte code offset #320
/*     */     //   Java source line #785	-> byte code offset #328
/*     */     //   Java source line #786	-> byte code offset #381
/*     */     //   Java source line #787	-> byte code offset #383
/*     */     //   Java source line #788	-> byte code offset #395
/*     */     //   Java source line #789	-> byte code offset #432
/*     */     //   Java source line #790	-> byte code offset #434
/*     */     //   Java source line #791	-> byte code offset #446
/*     */     //   Java source line #792	-> byte code offset #483
/*     */     //   Java source line #793	-> byte code offset #485
/*     */     //   Java source line #794	-> byte code offset #505
/*     */     //   Java source line #795	-> byte code offset #525
/*     */     //   Java source line #793	-> byte code offset #528
/*     */     //   Java source line #794	-> byte code offset #548
/*     */     //   Java source line #796	-> byte code offset #568
/*     */     // Local variable table:
/*     */     //   start	length	slot	name	signature
/*     */     //   0	569	0	this	ConsultaM2KDAO
/*     */     //   0	569	1	region	int
/*     */     //   0	569	2	mobileTO	MobileTO
/*     */     //   0	569	3	connection	Connection
/*     */     //   8	3	4	mercadoM2K	String
/*     */     //   22	3	4	mercadoM2K	String
/*     */     //   49	43	4	mercadoM2K	String
/*     */     //   58	202	5	query1	StringBuffer
/*     */     //   193	369	6	statement	java.sql.Statement
/*     */     //   196	346	7	resultSet	java.sql.ResultSet
/*     */     //   201	166	8	inicioConsulta	long
/*     */     //   381	46	8	e	SQLException
/*     */     //   432	46	8	e	Exception
/*     */     //   483	43	10	localObject	Object
/*     */     //   503	1	11	localException1	Exception
/*     */     //   523	1	11	localException2	Exception
/*     */     //   546	1	11	localException3	Exception
/*     */     //   566	1	11	localException4	Exception
/*     */     // Exception table:
/*     */     //   from	to	target	type
/*     */     //   198	378	381	java/sql/SQLException
/*     */     //   198	378	432	java/lang/Exception
/*     */     //   198	483	483	finally
/*     */     //   490	500	503	java/lang/Exception
/*     */     //   510	520	523	java/lang/Exception
/*     */     //   533	543	546	java/lang/Exception
/*     */     //   553	563	566	java/lang/Exception
/*     */   }
/*     */ }


/* Location:              /opt/trabajo/claro/Guatemala/IS/CO/ClaroClub.ear!/ClaroClubEJB.jar!/com/claro/dao/ConsultaM2KDAO.class
 * Java compiler version: 6 (50.0)
 * JD-Core Version:       0.7.1
 */