/*    */ package com.claro.dao;
/*    */ 
/*    */ import com.claro.util.ServiceLocator;
/*    */ import org.apache.log4j.Logger;
/*    */ 
/*    */ 
/*    */ 
/*    */ 
/*    */ 
/*    */ 
/*    */ public class ConsultaCuentasCorreoDAO
/*    */ {
/* 13 */   protected final Logger error = Logger.getLogger("loggerCirculoAzulError");
/* 14 */   protected final Logger logger = Logger.getLogger("loggerCirculoAzul");
/*    */   private String schema_database;
/*    */   
/*    */   public ConsultaCuentasCorreoDAO() {
/*    */     try {
/* 19 */       this.schema_database = ServiceLocator.getInstance().getVariable(ServiceLocator.schema_database);
/*    */     }
/*    */     catch (Exception e) {
/* 22 */       this.error.error("ConsultaCuentasCorreoDAO", e);
/*    */     }
/*    */   }
/*    */   
/*    */   /* Error */
/*    */   public java.util.Map<String, String> obtieneCuentasCorreo(int idReporte)
/*    */   {
/*    */     // Byte code:
/*    */     //   0: aconst_null
/*    */     //   1: astore_2
/*    */     //   2: aconst_null
/*    */     //   3: astore_3
/*    */     //   4: aconst_null
/*    */     //   5: astore 4
/*    */     //   7: aconst_null
/*    */     //   8: astore 5
/*    */     //   10: invokestatic 29	com/claro/util/ServiceLocator:getInstance	()Lcom/claro/util/ServiceLocator;
/*    */     //   13: getstatic 60	com/claro/util/ServiceLocator:jdbcCirculoAzul	Ljava/lang/String;
/*    */     //   16: invokevirtual 63	com/claro/util/ServiceLocator:getConnection	(Ljava/lang/String;)Ljava/sql/Connection;
/*    */     //   19: astore_2
/*    */     //   20: new 67	java/lang/StringBuffer
/*    */     //   23: dup
/*    */     //   24: invokespecial 69	java/lang/StringBuffer:<init>	()V
/*    */     //   27: astore 6
/*    */     //   29: aload 6
/*    */     //   31: ldc 70
/*    */     //   33: invokevirtual 72	java/lang/StringBuffer:append	(Ljava/lang/String;)Ljava/lang/StringBuffer;
/*    */     //   36: pop
/*    */     //   37: aload 6
/*    */     //   39: aload_0
/*    */     //   40: getfield 41	com/claro/dao/ConsultaCuentasCorreoDAO:schema_database	Ljava/lang/String;
/*    */     //   43: invokevirtual 72	java/lang/StringBuffer:append	(Ljava/lang/String;)Ljava/lang/StringBuffer;
/*    */     //   46: ldc 76
/*    */     //   48: invokevirtual 72	java/lang/StringBuffer:append	(Ljava/lang/String;)Ljava/lang/StringBuffer;
/*    */     //   51: pop
/*    */     //   52: aload 6
/*    */     //   54: ldc 78
/*    */     //   56: invokevirtual 72	java/lang/StringBuffer:append	(Ljava/lang/String;)Ljava/lang/StringBuffer;
/*    */     //   59: pop
/*    */     //   60: aload_2
/*    */     //   61: aload 6
/*    */     //   63: invokevirtual 80	java/lang/StringBuffer:toString	()Ljava/lang/String;
/*    */     //   66: invokeinterface 84 2 0
/*    */     //   71: astore_3
/*    */     //   72: aload_3
/*    */     //   73: iconst_1
/*    */     //   74: iload_1
/*    */     //   75: invokeinterface 90 3 0
/*    */     //   80: aload_3
/*    */     //   81: invokeinterface 96 1 0
/*    */     //   86: astore 4
/*    */     //   88: goto +69 -> 157
/*    */     //   91: new 100	java/util/HashMap
/*    */     //   94: dup
/*    */     //   95: invokespecial 102	java/util/HashMap:<init>	()V
/*    */     //   98: astore 5
/*    */     //   100: aload 5
/*    */     //   102: ldc 103
/*    */     //   104: aload 4
/*    */     //   106: ldc 105
/*    */     //   108: invokeinterface 107 2 0
/*    */     //   113: invokeinterface 112 3 0
/*    */     //   118: pop
/*    */     //   119: aload 5
/*    */     //   121: ldc 118
/*    */     //   123: aload 4
/*    */     //   125: ldc 120
/*    */     //   127: invokeinterface 107 2 0
/*    */     //   132: invokeinterface 112 3 0
/*    */     //   137: pop
/*    */     //   138: aload 5
/*    */     //   140: ldc 122
/*    */     //   142: aload 4
/*    */     //   144: ldc 124
/*    */     //   146: invokeinterface 107 2 0
/*    */     //   151: invokeinterface 112 3 0
/*    */     //   156: pop
/*    */     //   157: aload 4
/*    */     //   159: invokeinterface 126 1 0
/*    */     //   164: ifne -73 -> 91
/*    */     //   167: goto +107 -> 274
/*    */     //   170: astore 6
/*    */     //   172: aload 4
/*    */     //   174: ifnull +15 -> 189
/*    */     //   177: aload 4
/*    */     //   179: invokeinterface 130 1 0
/*    */     //   184: goto +5 -> 189
/*    */     //   187: astore 8
/*    */     //   189: aload_3
/*    */     //   190: ifnull +14 -> 204
/*    */     //   193: aload_3
/*    */     //   194: invokeinterface 133 1 0
/*    */     //   199: goto +5 -> 204
/*    */     //   202: astore 8
/*    */     //   204: aload_2
/*    */     //   205: ifnull +116 -> 321
/*    */     //   208: aload_2
/*    */     //   209: invokeinterface 134 1 0
/*    */     //   214: goto +107 -> 321
/*    */     //   217: astore 8
/*    */     //   219: goto +102 -> 321
/*    */     //   222: astore 7
/*    */     //   224: aload 4
/*    */     //   226: ifnull +15 -> 241
/*    */     //   229: aload 4
/*    */     //   231: invokeinterface 130 1 0
/*    */     //   236: goto +5 -> 241
/*    */     //   239: astore 8
/*    */     //   241: aload_3
/*    */     //   242: ifnull +14 -> 256
/*    */     //   245: aload_3
/*    */     //   246: invokeinterface 133 1 0
/*    */     //   251: goto +5 -> 256
/*    */     //   254: astore 8
/*    */     //   256: aload_2
/*    */     //   257: ifnull +14 -> 271
/*    */     //   260: aload_2
/*    */     //   261: invokeinterface 134 1 0
/*    */     //   266: goto +5 -> 271
/*    */     //   269: astore 8
/*    */     //   271: aload 7
/*    */     //   273: athrow
/*    */     //   274: aload 4
/*    */     //   276: ifnull +15 -> 291
/*    */     //   279: aload 4
/*    */     //   281: invokeinterface 130 1 0
/*    */     //   286: goto +5 -> 291
/*    */     //   289: astore 8
/*    */     //   291: aload_3
/*    */     //   292: ifnull +14 -> 306
/*    */     //   295: aload_3
/*    */     //   296: invokeinterface 133 1 0
/*    */     //   301: goto +5 -> 306
/*    */     //   304: astore 8
/*    */     //   306: aload_2
/*    */     //   307: ifnull +14 -> 321
/*    */     //   310: aload_2
/*    */     //   311: invokeinterface 134 1 0
/*    */     //   316: goto +5 -> 321
/*    */     //   319: astore 8
/*    */     //   321: aload 5
/*    */     //   323: areturn
/*    */     // Line number table:
/*    */     //   Java source line #27	-> byte code offset #0
/*    */     //   Java source line #28	-> byte code offset #2
/*    */     //   Java source line #29	-> byte code offset #4
/*    */     //   Java source line #30	-> byte code offset #7
/*    */     //   Java source line #33	-> byte code offset #10
/*    */     //   Java source line #35	-> byte code offset #20
/*    */     //   Java source line #36	-> byte code offset #29
/*    */     //   Java source line #37	-> byte code offset #37
/*    */     //   Java source line #38	-> byte code offset #52
/*    */     //   Java source line #40	-> byte code offset #60
/*    */     //   Java source line #41	-> byte code offset #72
/*    */     //   Java source line #43	-> byte code offset #80
/*    */     //   Java source line #45	-> byte code offset #88
/*    */     //   Java source line #46	-> byte code offset #91
/*    */     //   Java source line #47	-> byte code offset #100
/*    */     //   Java source line #48	-> byte code offset #119
/*    */     //   Java source line #49	-> byte code offset #138
/*    */     //   Java source line #45	-> byte code offset #157
/*    */     //   Java source line #53	-> byte code offset #170
/*    */     //   Java source line #56	-> byte code offset #172
/*    */     //   Java source line #57	-> byte code offset #189
/*    */     //   Java source line #58	-> byte code offset #204
/*    */     //   Java source line #55	-> byte code offset #222
/*    */     //   Java source line #56	-> byte code offset #224
/*    */     //   Java source line #57	-> byte code offset #241
/*    */     //   Java source line #58	-> byte code offset #256
/*    */     //   Java source line #59	-> byte code offset #271
/*    */     //   Java source line #56	-> byte code offset #274
/*    */     //   Java source line #57	-> byte code offset #291
/*    */     //   Java source line #58	-> byte code offset #306
/*    */     //   Java source line #60	-> byte code offset #321
/*    */     // Local variable table:
/*    */     //   start	length	slot	name	signature
/*    */     //   0	324	0	this	ConsultaCuentasCorreoDAO
/*    */     //   0	324	1	idReporte	int
/*    */     //   1	310	2	conn	java.sql.Connection
/*    */     //   3	293	3	statement	java.sql.PreparedStatement
/*    */     //   5	275	4	resultSet	java.sql.ResultSet
/*    */     //   8	314	5	parametrosCorreo	java.util.Map<String, String>
/*    */     //   27	35	6	query	StringBuffer
/*    */     //   170	1	6	localException	Exception
/*    */     //   222	50	7	localObject	Object
/*    */     //   187	1	8	localException1	Exception
/*    */     //   202	1	8	localException2	Exception
/*    */     //   217	1	8	localException3	Exception
/*    */     //   239	1	8	localException4	Exception
/*    */     //   254	1	8	localException5	Exception
/*    */     //   269	1	8	localException6	Exception
/*    */     //   289	1	8	localException7	Exception
/*    */     //   304	1	8	localException8	Exception
/*    */     //   319	1	8	localException9	Exception
/*    */     // Exception table:
/*    */     //   from	to	target	type
/*    */     //   10	167	170	java/lang/Exception
/*    */     //   172	184	187	java/lang/Exception
/*    */     //   189	199	202	java/lang/Exception
/*    */     //   204	214	217	java/lang/Exception
/*    */     //   10	172	222	finally
/*    */     //   224	236	239	java/lang/Exception
/*    */     //   241	251	254	java/lang/Exception
/*    */     //   256	266	269	java/lang/Exception
/*    */     //   274	286	289	java/lang/Exception
/*    */     //   291	301	304	java/lang/Exception
/*    */     //   306	316	319	java/lang/Exception
/*    */   }
/*    */   
/*    */   /* Error */
/*    */   public java.util.Map<String, String> obtieneCuentasCorreoCargaCatalogos(int idRegion)
/*    */   {
/*    */     // Byte code:
/*    */     //   0: aconst_null
/*    */     //   1: astore_2
/*    */     //   2: aconst_null
/*    */     //   3: astore_3
/*    */     //   4: aconst_null
/*    */     //   5: astore 4
/*    */     //   7: aconst_null
/*    */     //   8: astore 5
/*    */     //   10: invokestatic 29	com/claro/util/ServiceLocator:getInstance	()Lcom/claro/util/ServiceLocator;
/*    */     //   13: getstatic 60	com/claro/util/ServiceLocator:jdbcCirculoAzul	Ljava/lang/String;
/*    */     //   16: invokevirtual 63	com/claro/util/ServiceLocator:getConnection	(Ljava/lang/String;)Ljava/sql/Connection;
/*    */     //   19: astore_2
/*    */     //   20: new 67	java/lang/StringBuffer
/*    */     //   23: dup
/*    */     //   24: invokespecial 69	java/lang/StringBuffer:<init>	()V
/*    */     //   27: astore 6
/*    */     //   29: aload 6
/*    */     //   31: ldc 70
/*    */     //   33: invokevirtual 72	java/lang/StringBuffer:append	(Ljava/lang/String;)Ljava/lang/StringBuffer;
/*    */     //   36: pop
/*    */     //   37: aload 6
/*    */     //   39: aload_0
/*    */     //   40: getfield 41	com/claro/dao/ConsultaCuentasCorreoDAO:schema_database	Ljava/lang/String;
/*    */     //   43: invokevirtual 72	java/lang/StringBuffer:append	(Ljava/lang/String;)Ljava/lang/StringBuffer;
/*    */     //   46: ldc 76
/*    */     //   48: invokevirtual 72	java/lang/StringBuffer:append	(Ljava/lang/String;)Ljava/lang/StringBuffer;
/*    */     //   51: pop
/*    */     //   52: aload 6
/*    */     //   54: ldc 78
/*    */     //   56: invokevirtual 72	java/lang/StringBuffer:append	(Ljava/lang/String;)Ljava/lang/StringBuffer;
/*    */     //   59: pop
/*    */     //   60: aload_2
/*    */     //   61: aload 6
/*    */     //   63: invokevirtual 80	java/lang/StringBuffer:toString	()Ljava/lang/String;
/*    */     //   66: invokeinterface 84 2 0
/*    */     //   71: astore_3
/*    */     //   72: iload_1
/*    */     //   73: bipush 9
/*    */     //   75: if_icmpne +16 -> 91
/*    */     //   78: aload_3
/*    */     //   79: iconst_1
/*    */     //   80: sipush 2001
/*    */     //   83: invokeinterface 90 3 0
/*    */     //   88: goto +13 -> 101
/*    */     //   91: aload_3
/*    */     //   92: iconst_1
/*    */     //   93: sipush 2000
/*    */     //   96: invokeinterface 90 3 0
/*    */     //   101: aload_3
/*    */     //   102: invokeinterface 96 1 0
/*    */     //   107: astore 4
/*    */     //   109: goto +69 -> 178
/*    */     //   112: new 100	java/util/HashMap
/*    */     //   115: dup
/*    */     //   116: invokespecial 102	java/util/HashMap:<init>	()V
/*    */     //   119: astore 5
/*    */     //   121: aload 5
/*    */     //   123: ldc 103
/*    */     //   125: aload 4
/*    */     //   127: ldc 105
/*    */     //   129: invokeinterface 107 2 0
/*    */     //   134: invokeinterface 112 3 0
/*    */     //   139: pop
/*    */     //   140: aload 5
/*    */     //   142: ldc 118
/*    */     //   144: aload 4
/*    */     //   146: ldc 120
/*    */     //   148: invokeinterface 107 2 0
/*    */     //   153: invokeinterface 112 3 0
/*    */     //   158: pop
/*    */     //   159: aload 5
/*    */     //   161: ldc 122
/*    */     //   163: aload 4
/*    */     //   165: ldc 124
/*    */     //   167: invokeinterface 107 2 0
/*    */     //   172: invokeinterface 112 3 0
/*    */     //   177: pop
/*    */     //   178: aload 4
/*    */     //   180: invokeinterface 126 1 0
/*    */     //   185: ifne -73 -> 112
/*    */     //   188: goto +107 -> 295
/*    */     //   191: astore 6
/*    */     //   193: aload 4
/*    */     //   195: ifnull +15 -> 210
/*    */     //   198: aload 4
/*    */     //   200: invokeinterface 130 1 0
/*    */     //   205: goto +5 -> 210
/*    */     //   208: astore 8
/*    */     //   210: aload_3
/*    */     //   211: ifnull +14 -> 225
/*    */     //   214: aload_3
/*    */     //   215: invokeinterface 133 1 0
/*    */     //   220: goto +5 -> 225
/*    */     //   223: astore 8
/*    */     //   225: aload_2
/*    */     //   226: ifnull +116 -> 342
/*    */     //   229: aload_2
/*    */     //   230: invokeinterface 134 1 0
/*    */     //   235: goto +107 -> 342
/*    */     //   238: astore 8
/*    */     //   240: goto +102 -> 342
/*    */     //   243: astore 7
/*    */     //   245: aload 4
/*    */     //   247: ifnull +15 -> 262
/*    */     //   250: aload 4
/*    */     //   252: invokeinterface 130 1 0
/*    */     //   257: goto +5 -> 262
/*    */     //   260: astore 8
/*    */     //   262: aload_3
/*    */     //   263: ifnull +14 -> 277
/*    */     //   266: aload_3
/*    */     //   267: invokeinterface 133 1 0
/*    */     //   272: goto +5 -> 277
/*    */     //   275: astore 8
/*    */     //   277: aload_2
/*    */     //   278: ifnull +14 -> 292
/*    */     //   281: aload_2
/*    */     //   282: invokeinterface 134 1 0
/*    */     //   287: goto +5 -> 292
/*    */     //   290: astore 8
/*    */     //   292: aload 7
/*    */     //   294: athrow
/*    */     //   295: aload 4
/*    */     //   297: ifnull +15 -> 312
/*    */     //   300: aload 4
/*    */     //   302: invokeinterface 130 1 0
/*    */     //   307: goto +5 -> 312
/*    */     //   310: astore 8
/*    */     //   312: aload_3
/*    */     //   313: ifnull +14 -> 327
/*    */     //   316: aload_3
/*    */     //   317: invokeinterface 133 1 0
/*    */     //   322: goto +5 -> 327
/*    */     //   325: astore 8
/*    */     //   327: aload_2
/*    */     //   328: ifnull +14 -> 342
/*    */     //   331: aload_2
/*    */     //   332: invokeinterface 134 1 0
/*    */     //   337: goto +5 -> 342
/*    */     //   340: astore 8
/*    */     //   342: aload 5
/*    */     //   344: areturn
/*    */     // Line number table:
/*    */     //   Java source line #65	-> byte code offset #0
/*    */     //   Java source line #66	-> byte code offset #2
/*    */     //   Java source line #67	-> byte code offset #4
/*    */     //   Java source line #68	-> byte code offset #7
/*    */     //   Java source line #71	-> byte code offset #10
/*    */     //   Java source line #73	-> byte code offset #20
/*    */     //   Java source line #74	-> byte code offset #29
/*    */     //   Java source line #75	-> byte code offset #37
/*    */     //   Java source line #76	-> byte code offset #52
/*    */     //   Java source line #78	-> byte code offset #60
/*    */     //   Java source line #80	-> byte code offset #72
/*    */     //   Java source line #81	-> byte code offset #78
/*    */     //   Java source line #83	-> byte code offset #91
/*    */     //   Java source line #85	-> byte code offset #101
/*    */     //   Java source line #87	-> byte code offset #109
/*    */     //   Java source line #88	-> byte code offset #112
/*    */     //   Java source line #89	-> byte code offset #121
/*    */     //   Java source line #90	-> byte code offset #140
/*    */     //   Java source line #91	-> byte code offset #159
/*    */     //   Java source line #87	-> byte code offset #178
/*    */     //   Java source line #95	-> byte code offset #191
/*    */     //   Java source line #98	-> byte code offset #193
/*    */     //   Java source line #99	-> byte code offset #210
/*    */     //   Java source line #100	-> byte code offset #225
/*    */     //   Java source line #97	-> byte code offset #243
/*    */     //   Java source line #98	-> byte code offset #245
/*    */     //   Java source line #99	-> byte code offset #262
/*    */     //   Java source line #100	-> byte code offset #277
/*    */     //   Java source line #101	-> byte code offset #292
/*    */     //   Java source line #98	-> byte code offset #295
/*    */     //   Java source line #99	-> byte code offset #312
/*    */     //   Java source line #100	-> byte code offset #327
/*    */     //   Java source line #102	-> byte code offset #342
/*    */     // Local variable table:
/*    */     //   start	length	slot	name	signature
/*    */     //   0	345	0	this	ConsultaCuentasCorreoDAO
/*    */     //   0	345	1	idRegion	int
/*    */     //   1	331	2	conn	java.sql.Connection
/*    */     //   3	314	3	statement	java.sql.PreparedStatement
/*    */     //   5	296	4	resultSet	java.sql.ResultSet
/*    */     //   8	335	5	parametrosCorreo	java.util.Map<String, String>
/*    */     //   27	35	6	query	StringBuffer
/*    */     //   191	1	6	localException	Exception
/*    */     //   243	50	7	localObject	Object
/*    */     //   208	1	8	localException1	Exception
/*    */     //   223	1	8	localException2	Exception
/*    */     //   238	1	8	localException3	Exception
/*    */     //   260	1	8	localException4	Exception
/*    */     //   275	1	8	localException5	Exception
/*    */     //   290	1	8	localException6	Exception
/*    */     //   310	1	8	localException7	Exception
/*    */     //   325	1	8	localException8	Exception
/*    */     //   340	1	8	localException9	Exception
/*    */     // Exception table:
/*    */     //   from	to	target	type
/*    */     //   10	188	191	java/lang/Exception
/*    */     //   193	205	208	java/lang/Exception
/*    */     //   210	220	223	java/lang/Exception
/*    */     //   225	235	238	java/lang/Exception
/*    */     //   10	193	243	finally
/*    */     //   245	257	260	java/lang/Exception
/*    */     //   262	272	275	java/lang/Exception
/*    */     //   277	287	290	java/lang/Exception
/*    */     //   295	307	310	java/lang/Exception
/*    */     //   312	322	325	java/lang/Exception
/*    */     //   327	337	340	java/lang/Exception
/*    */   }
/*    */ }


/* Location:              /opt/trabajo/claro/Guatemala/IS/CO/ClaroClub.ear!/ClaroClubEJB.jar!/com/claro/dao/ConsultaCuentasCorreoDAO.class
 * Java compiler version: 6 (50.0)
 * JD-Core Version:       0.7.1
 */