/*     */ package com.claro.dao;
/*     */ 
/*     */ import com.claro.exception.CAException;
/*     */ import com.claro.transfer.ImpresionTO;
/*     */ import com.claro.util.Impresion;
/*     */ import com.claro.util.ServiceLocator;
/*     */ import com.claro.util.Utils;
/*     */ import java.sql.Connection;
/*     */ import java.sql.PreparedStatement;
/*     */ import java.sql.ResultSet;
/*     */ import java.sql.SQLException;
/*     */ import java.sql.Timestamp;
/*     */ import org.apache.log4j.Logger;
/*     */ 
/*     */ 
/*     */ 
/*     */ 
/*     */ 
/*     */ 
/*     */ 
/*     */ 
/*     */ 
/*     */ public class ImpresionDAO
/*     */ {
/*  25 */   protected final Logger logger = Logger.getLogger("loggerCirculoAzul");
/*  26 */   protected final Logger error = Logger.getLogger("loggerCirculoAzulError");
/*     */   
/*     */   private String schema_database;
/*     */   
/*     */   public ImpresionDAO()
/*     */   {
/*     */     try
/*     */     {
/*  34 */       this.schema_database = ServiceLocator.getInstance().getVariable(ServiceLocator.schema_database);
/*     */     } catch (Exception e) {
/*  36 */       this.error.error("ImpresionDAO", e);
/*     */     }
/*     */   }
/*     */   
/*     */ 
/*     */ 
/*     */ 
/*     */ 
/*     */   public ImpresionTO datosConstanciaImpresion(String sTelefono, String cuenta, String fechaFolio, String folio, String fechaOperacion, String tipoReden)
/*     */     throws CAException
/*     */   {
/*  47 */     PreparedStatement statement = null;
/*  48 */     ResultSet resultSet = null;
/*  49 */     Connection connection = null;
/*     */     
/*  51 */     StringBuffer query = new StringBuffer();
/*     */     
/*     */ 
/*     */ 
/*     */ 
/*  56 */     query.append(" SELECT C.IDPUNTOVTA,D.PLANANT,D.ADDANT,D.FECPLAZOANT, ");
/*  57 */     query.append(" C.FECHAOPER,D.PUNTOSDISPO,C.VALORPTOS, ");
/*  58 */     query.append(" D.PTSDISPORES,D.PLANNVO,D.ADDNVO,D.FECPLAZOSUG, ");
/*  59 */     query.append(" D.FECHAFOLIO,D.TIPOREDEN,D.FORMARED,C.IDPRODUCTO, ");
/*  60 */     query.append(" C.DESCRIPCION,C.MARCA,C.MODELO,C.PRECIO,C.DESCUENTO, ");
/*  61 */     query.append(" C.PRECIOIVA,C.COMENTARIO,D.ESNIMEIR,D.ESNIMEIP,D.ICCID, ");
/*  62 */     query.append(" C.PTOSMIN , C.BONOPRORR , D.PUNTOSACUM, D.PTSACUMRES,C.FOLIO, ");
/*  63 */     query.append(" C.BONOROEXT , C.BONOALTOVALOR , C.BONOGAP,C.BONOINBURSA,C.BONOMARCA ");
/*  64 */     query.append("  FROM  ").append(this.schema_database).append("PTO_TBLLINEAS A,  ")
/*  65 */       .append(this.schema_database).append("PTO_TBLTOTALES B, ")
/*  66 */       .append(this.schema_database).append("PTO_TBLREDENCION C, ")
/*  67 */       .append(this.schema_database).append("PTO_TBLCONSTANCIA D ");
/*  68 */     query.append(" WHERE ");
/*     */     
/*  70 */     if ((sTelefono != null) && (sTelefono.trim().length() > 0)) {
/*  71 */       query.append(" C.LINEA = ? ");
/*     */     }
/*  73 */     else if ((cuenta != null) && (cuenta.trim().length() > 0)) {
/*  74 */       query.append(" C.CUENTA = ? ");
/*     */     } else {
/*  76 */       query.append("  C.FOLIO = ? ");
/*     */     }
/*     */     
/*     */ 
/*     */ 
/*  81 */     if (folio != null) query.append(" AND C.FOLIO = ? ");
/*  82 */     if (fechaFolio != null) query.append(" AND C.FECHAFOLIO = ? ");
/*  83 */     if (fechaOperacion != null) query.append(" AND C.FECHAOPER=? ");
/*  84 */     if (tipoReden != null) query.append(" AND C.TIPOREDEN=? ");
/*  85 */     query.append(" AND A.CUENTA = B.CUENTA AND A.SECUENCIA = B.SECUENCIA ");
/*  86 */     query.append(" AND A.CUENTA = C.CUENTA AND A.SECUENCIA = C.SECUENCIA ");
/*  87 */     query.append(" AND C.CUENTA = D.CUENTA AND C.SECUENCIA = D.SECUENCIA ");
/*  88 */     query.append(" AND C.FECHAFOLIO = D.FECHAFOLIO ");
/*  89 */     query.append(" AND C.FECHAOPER = D.FECHAOPER ");
/*  90 */     query.append(" AND C.TIPOREDEN = D.TIPOREDEN ");
/*  91 */     query.append(" AND C.ESTATUS = 'A' AND D.ESTATUS = 'A' ");
/*  92 */     query.append(" GROUP BY C.IDPUNTOVTA,D.PLANANT,D.ADDANT,D.FECPLAZOANT, ");
/*  93 */     query.append(" C.FECHAOPER, D.PUNTOSDISPO,C.VALORPTOS,D.PTSDISPORES,D.PLANNVO,ADDNVO, ");
/*  94 */     query.append(" D.FECPLAZOSUG,D.FECHAFOLIO,D.TIPOREDEN,D.FORMARED,C.IDPRODUCTO, ");
/*  95 */     query.append(" C.DESCRIPCION,C.MARCA,C.MODELO,C.PRECIO,C.DESCUENTO, ");
/*  96 */     query.append(" C.PRECIOIVA,C.COMENTARIO,D.ESNIMEIR,D.ESNIMEIP,D.ICCID, ");
/*  97 */     query.append(" C.PTOSMIN , C.BONOPRORR , D.PUNTOSACUM, D.PTSACUMRES,C.FOLIO, ");
/*  98 */     query.append(" C.BONOROEXT , C.BONOALTOVALOR , C.BONOGAP,C.BONOINBURSA,C.BONOMARCA ");
/*  99 */     query.append(" ORDER BY D.FECPLAZOANT ");
/* 100 */     ImpresionTO impresionTO = new ImpresionTO();
/*     */     try
/*     */     {
/* 103 */       connection = ServiceLocator.getInstance().getConnection(ServiceLocator.jdbcCirculoAzul);
/* 104 */       statement = connection.prepareStatement(query.toString());
/*     */       
/* 106 */       int contador = 1;
/*     */       
/* 108 */       if ((sTelefono != null) && (sTelefono.trim().length() > 0)) {
/* 109 */         statement.setString(contador++, sTelefono);
/*     */       }
/* 111 */       else if ((cuenta != null) && (cuenta.trim().length() > 0)) {
/* 112 */         statement.setString(contador++, cuenta);
/*     */       } else {
/* 114 */         statement.setString(contador++, folio);
/*     */       }
/*     */       
/*     */ 
/* 118 */       if (folio != null) statement.setString(contador++, folio);
/* 119 */       if (fechaFolio != null) statement.setTimestamp(contador++, new Timestamp(new Long(fechaFolio).longValue()));
/* 120 */       if (fechaOperacion != null) statement.setTimestamp(contador++, new Timestamp(new Long(fechaOperacion).longValue()));
/* 121 */       if (tipoReden != null) { statement.setString(contador++, tipoReden);
/*     */       }
/* 123 */       resultSet = statement.executeQuery();
/*     */       
/* 125 */       if (resultSet.next()) {
/* 126 */         impresionTO.setIdPuntoVenta(resultSet.getString("IDPUNTOVTA"));
/* 127 */         impresionTO.setPlanAnt(resultSet.getString("PLANANT"));
/* 128 */         impresionTO.setAddAnt(resultSet.getInt("ADDANT"));
/* 129 */         impresionTO.setFechaPlazoAnt(resultSet.getDate("FECPLAZOANT"));
/* 130 */         impresionTO.setFechaOperacion(resultSet.getDate("FECHAOPER"));
/* 131 */         impresionTO.setPtosDisp(resultSet.getInt("PUNTOSDISPO"));
/* 132 */         impresionTO.setValorPuntos(resultSet.getInt("VALORPTOS"));
/* 133 */         impresionTO.setPtsDispRestantes(resultSet.getInt("PTSDISPORES"));
/* 134 */         impresionTO.setPlanNuevo(resultSet.getString("PLANNVO"));
/* 135 */         impresionTO.setAddNuevo(resultSet.getInt("ADDNVO"));
/* 136 */         impresionTO.setFechaPlazoSeg(resultSet.getDate("FECPLAZOSUG"));
/* 137 */         impresionTO.setFechaFolio(resultSet.getTimestamp("FECHAFOLIO"));
/*     */         
/* 139 */         impresionTO.setTipoReden(resultSet.getString("TIPOREDEN"));
/* 140 */         String formaReden = resultSet.getString("FORMARED");
/*     */         
/* 142 */         impresionTO.setIdProducto(resultSet.getString("IDPRODUCTO"));
/* 143 */         impresionTO.setDescripcion(resultSet.getString("DESCRIPCION"));
/* 144 */         impresionTO.setMarca(resultSet.getString("MARCA"));
/* 145 */         impresionTO.setModelo(resultSet.getString("MODELO"));
/* 146 */         impresionTO.setPrecio(resultSet.getBigDecimal("PRECIO"));
/* 147 */         impresionTO.setDescuento(resultSet.getBigDecimal("DESCUENTO"));
/* 148 */         impresionTO.setPrecioIva(resultSet.getBigDecimal("PRECIOIVA"));
/*     */         
/* 150 */         impresionTO.setComentario(resultSet.getString("COMENTARIO"));
/* 151 */         impresionTO.setEsnImeiR(resultSet.getString("ESNIMEIR"));
/* 152 */         impresionTO.setEsnImeiP(resultSet.getString("ESNIMEIP"));
/* 153 */         impresionTO.setIccid(resultSet.getString("ICCID"));
/* 154 */         impresionTO.setPtsMinimos(resultSet.getInt("PTOSMIN"));
/* 155 */         impresionTO.setBonoProrr(resultSet.getInt("BONOPRORR"));
/* 156 */         impresionTO.setPtsAcum(resultSet.getInt("PUNTOSACUM"));
/* 157 */         impresionTO.setPtsAcumRes(resultSet.getInt("PTSACUMRES"));
/* 158 */         impresionTO.setFolio(resultSet.getString("FOLIO"));
/*     */         
/* 160 */         impresionTO.setFormaReden(Impresion.getFormaRed(formaReden));
/* 161 */         impresionTO.setTipoRedenDB(Impresion.getTipoRed(impresionTO.getTipoReden()));
/*     */         
/* 163 */         impresionTO.setPrecioIvaFormato(Utils.setFormatoDecimalPrecio(resultSet.getString("PRECIOIVA")));
/* 164 */         impresionTO.setPrecioFormato(Utils.setFormatoDecimalPrecio(resultSet.getString("PRECIO")));
/* 165 */         impresionTO.setDescuentoFormato(Utils.setFormatoDecimalPrecio(resultSet.getString("DESCUENTO")));
/* 166 */         impresionTO.setBonosRoext(resultSet.getInt("BONOROEXT"));
/* 167 */         impresionTO.setBonosAltoValor(resultSet.getInt("BONOALTOVALOR"));
/* 168 */         impresionTO.setBonosGap(resultSet.getInt("BONOGAP"));
/* 169 */         impresionTO.setInbursaFormato(Utils.setFormatoDecimalPrecio(resultSet.getString("BONOINBURSA")));
/* 170 */         impresionTO.setMarcaFormato(Utils.setFormatoDecimalPrecio(resultSet.getString("BONOMARCA")));
/*     */         
/*     */ 
/* 173 */         impresionTO.setPtsAcumResCF(Utils.setFormatoPtos(impresionTO.getPtsAcumRes()));
/* 174 */         impresionTO.setPtosDispCF(Utils.setFormatoPtos(impresionTO.getPtosDisp()));
/* 175 */         impresionTO.setPtsDispRestantesCF(Utils.setFormatoPtos(impresionTO.getPtsDispRestantes()));
/* 176 */         impresionTO.setValorPuntosCF(Utils.setFormatoPtos(impresionTO.getValorPuntos()));
/* 177 */         impresionTO.setPtsMinimosCF(Utils.setFormatoPtos(impresionTO.getPtsMinimos()));
/* 178 */         impresionTO.setPtsAcumCF(Utils.setFormatoPtos(impresionTO.getPtsAcum()));
/* 179 */         impresionTO.setPtsTransferidosCF(Utils.setFormatoPtos(impresionTO.getPtsTransferidos()));
/* 180 */         impresionTO.setPtsMillasCF(Utils.setFormatoPtos(impresionTO.getPtsMillas()));
/* 181 */         impresionTO.setPtsCanjeadoCF(Utils.setFormatoPtos(impresionTO.getPtsCanjeado()));
/* 182 */         impresionTO.agregaMensaje(0, "Proceso Exitoso");
/* 183 */         return impresionTO;
/*     */       }
/* 185 */       throw new CAException(1, "No existe ninguna redencion.");
/*     */     }
/*     */     catch (SQLException e) {
/* 188 */       throw new CAException(-1, "SQLException.datosConstanciaImpresion [" + e.toString() + "]", e);
/*     */     } catch (Exception e) {
/* 190 */       throw new CAException(-1, "ImpresionDAO.datosConstanciaImpresion[" + e.toString() + "]", e);
/*     */     } finally {
/* 192 */       if (resultSet != null) try { resultSet.close();resultSet = null; } catch (Exception localException4) {}
/* 193 */       if (statement != null) try { statement.close();statement = null; } catch (Exception localException5) {}
/* 194 */       if (connection != null) { try { connection.close();connection = null;
/*     */         }
/*     */         catch (Exception localException6) {}
/*     */       }
/*     */     }
/*     */   }
/*     */   
/*     */ 
/*     */   public ImpresionTO datosConstanciaBonoInbursa(String sTelefono, String cuenta)
/*     */     throws CAException
/*     */   {
/* 205 */     PreparedStatement statement = null;
/* 206 */     ResultSet resultSet = null;
/* 207 */     Connection connection = null;
/*     */     
/* 209 */     StringBuffer query = new StringBuffer();
/*     */     
/*     */ 
/*     */ 
/* 213 */     query.append(" SELECT  FOLIO,LINEA,CUENTA,DESCUENTOINBURSA,DESCUENTOMARCA,FECHAIMPRESION,FECHAEXPIRACION,CAC,FOLIOREDENCION ");
/* 214 */     query.append("  FROM  ").append(this.schema_database).append("PTO_TBLBONOINBURSA ");
/* 215 */     query.append(" WHERE FECHAEXPIRACION IS NOT NULL AND LINEA = ? AND CUENTA = ? ");
/*     */     try
/*     */     {
/* 218 */       connection = ServiceLocator.getInstance().getConnection(ServiceLocator.jdbcCirculoAzul);
/* 219 */       statement = connection.prepareStatement(query.toString());
/*     */       
/* 221 */       statement.setString(1, sTelefono);
/* 222 */       statement.setString(2, cuenta);
/*     */       
/*     */ 
/* 225 */       resultSet = statement.executeQuery();
/*     */       
/* 227 */       if (resultSet.next()) {
/* 228 */         ImpresionTO impresionTO = new ImpresionTO();
/* 229 */         impresionTO.setFolio(resultSet.getString("FOLIO"));
/* 230 */         impresionTO.setTelefono(resultSet.getString("LINEA"));
/* 231 */         impresionTO.setCuenta(resultSet.getString("CUENTA"));
/* 232 */         impresionTO.setInbursaFormato(Utils.setFormatoDecimal(resultSet.getString("DESCUENTOINBURSA")));
/* 233 */         impresionTO.setMarcaFormato(Utils.setFormatoDecimal(resultSet.getString("DESCUENTOMARCA")));
/* 234 */         impresionTO.setFechaOperacion(resultSet.getDate("FECHAIMPRESION"));
/* 235 */         impresionTO.setFechaPlazoSeg(resultSet.getDate("FECHAEXPIRACION"));
/* 236 */         impresionTO.setIdPuntoVenta(resultSet.getString("CAC"));
/* 237 */         impresionTO.setFolioRedencion(resultSet.getString("FOLIOREDENCION"));
/* 238 */         impresionTO.agregaMensaje(0, "Proceso Exitoso");
/* 239 */         return impresionTO;
/*     */       }
/* 241 */       throw new CAException(1, "No existe ninguna redencion.");
/*     */     }
/*     */     catch (SQLException e) {
/* 244 */       throw new CAException(-1, "SQLException.datosConstanciaImpresion [" + e.toString() + "]", e);
/*     */     } catch (Exception e) {
/* 246 */       throw new CAException(-1, "ImpresionDAO.datosConstanciaImpresion[" + e.toString() + "]", e);
/*     */     } finally {
/* 248 */       if (resultSet != null) try { resultSet.close();resultSet = null; } catch (Exception localException4) {}
/* 249 */       if (statement != null) try { statement.close();statement = null; } catch (Exception localException5) {}
/* 250 */       if (connection != null) try { connection.close();connection = null;
/*     */         }
/*     */         catch (Exception localException6) {}
/*     */     }
/*     */   }
/*     */   
/*     */   /* Error */
/*     */   public java.util.ArrayList<ImpresionTO> detalleRedenImp(String sTelefono, String cuenta, String sFecha)
/*     */     throws CAException
/*     */   {
/*     */     // Byte code:
/*     */     //   0: aconst_null
/*     */     //   1: astore 4
/*     */     //   3: aconst_null
/*     */     //   4: astore 5
/*     */     //   6: aconst_null
/*     */     //   7: astore 6
/*     */     //   9: new 61	java/lang/StringBuffer
/*     */     //   12: dup
/*     */     //   13: invokespecial 63	java/lang/StringBuffer:<init>	()V
/*     */     //   16: astore 7
/*     */     //   18: aconst_null
/*     */     //   19: astore 8
/*     */     //   21: new 575	java/util/ArrayList
/*     */     //   24: dup
/*     */     //   25: invokespecial 577	java/util/ArrayList:<init>	()V
/*     */     //   28: astore 9
/*     */     //   30: aload 7
/*     */     //   32: ldc_w 578
/*     */     //   35: invokevirtual 66	java/lang/StringBuffer:append	(Ljava/lang/String;)Ljava/lang/StringBuffer;
/*     */     //   38: pop
/*     */     //   39: aload 7
/*     */     //   41: ldc_w 580
/*     */     //   44: invokevirtual 66	java/lang/StringBuffer:append	(Ljava/lang/String;)Ljava/lang/StringBuffer;
/*     */     //   47: aload_0
/*     */     //   48: getfield 41	com/claro/dao/ImpresionDAO:schema_database	Ljava/lang/String;
/*     */     //   51: invokevirtual 66	java/lang/StringBuffer:append	(Ljava/lang/String;)Ljava/lang/StringBuffer;
/*     */     //   54: ldc_w 582
/*     */     //   57: invokevirtual 66	java/lang/StringBuffer:append	(Ljava/lang/String;)Ljava/lang/StringBuffer;
/*     */     //   60: pop
/*     */     //   61: aload 7
/*     */     //   63: aload_0
/*     */     //   64: getfield 41	com/claro/dao/ImpresionDAO:schema_database	Ljava/lang/String;
/*     */     //   67: invokevirtual 66	java/lang/StringBuffer:append	(Ljava/lang/String;)Ljava/lang/StringBuffer;
/*     */     //   70: ldc_w 584
/*     */     //   73: invokevirtual 66	java/lang/StringBuffer:append	(Ljava/lang/String;)Ljava/lang/StringBuffer;
/*     */     //   76: pop
/*     */     //   77: aload 7
/*     */     //   79: ldc 94
/*     */     //   81: invokevirtual 66	java/lang/StringBuffer:append	(Ljava/lang/String;)Ljava/lang/StringBuffer;
/*     */     //   84: pop
/*     */     //   85: aload_1
/*     */     //   86: ifnull +22 -> 108
/*     */     //   89: aload_1
/*     */     //   90: invokevirtual 102	java/lang/String:length	()I
/*     */     //   93: ifle +15 -> 108
/*     */     //   96: aload 7
/*     */     //   98: ldc_w 586
/*     */     //   101: invokevirtual 66	java/lang/StringBuffer:append	(Ljava/lang/String;)Ljava/lang/StringBuffer;
/*     */     //   104: pop
/*     */     //   105: goto +12 -> 117
/*     */     //   108: aload 7
/*     */     //   110: ldc_w 588
/*     */     //   113: invokevirtual 66	java/lang/StringBuffer:append	(Ljava/lang/String;)Ljava/lang/StringBuffer;
/*     */     //   116: pop
/*     */     //   117: aload 7
/*     */     //   119: ldc_w 590
/*     */     //   122: invokevirtual 66	java/lang/StringBuffer:append	(Ljava/lang/String;)Ljava/lang/StringBuffer;
/*     */     //   125: pop
/*     */     //   126: aload 7
/*     */     //   128: ldc_w 592
/*     */     //   131: invokevirtual 66	java/lang/StringBuffer:append	(Ljava/lang/String;)Ljava/lang/StringBuffer;
/*     */     //   134: pop
/*     */     //   135: aload 7
/*     */     //   137: ldc_w 594
/*     */     //   140: invokevirtual 66	java/lang/StringBuffer:append	(Ljava/lang/String;)Ljava/lang/StringBuffer;
/*     */     //   143: pop
/*     */     //   144: aload 7
/*     */     //   146: ldc_w 596
/*     */     //   149: invokevirtual 66	java/lang/StringBuffer:append	(Ljava/lang/String;)Ljava/lang/StringBuffer;
/*     */     //   152: pop
/*     */     //   153: invokestatic 29	com/claro/util/ServiceLocator:getInstance	()Lcom/claro/util/ServiceLocator;
/*     */     //   156: getstatic 145	com/claro/util/ServiceLocator:jdbcCirculoAzul	Ljava/lang/String;
/*     */     //   159: invokevirtual 148	com/claro/util/ServiceLocator:getConnection	(Ljava/lang/String;)Ljava/sql/Connection;
/*     */     //   162: astore 6
/*     */     //   164: aload 6
/*     */     //   166: aload 7
/*     */     //   168: invokevirtual 152	java/lang/StringBuffer:toString	()Ljava/lang/String;
/*     */     //   171: invokeinterface 155 2 0
/*     */     //   176: astore 4
/*     */     //   178: aload_1
/*     */     //   179: ifnull +22 -> 201
/*     */     //   182: aload_1
/*     */     //   183: invokevirtual 102	java/lang/String:length	()I
/*     */     //   186: ifle +15 -> 201
/*     */     //   189: aload 4
/*     */     //   191: iconst_1
/*     */     //   192: aload_1
/*     */     //   193: invokeinterface 161 3 0
/*     */     //   198: goto +12 -> 210
/*     */     //   201: aload 4
/*     */     //   203: iconst_1
/*     */     //   204: aload_2
/*     */     //   205: invokeinterface 161 3 0
/*     */     //   210: aload_3
/*     */     //   211: ifnull +12 -> 223
/*     */     //   214: getstatic 598	com/claro/util/Constantes:DATEFORMATdd_MM_YYYY_2	Ljava/text/SimpleDateFormat;
/*     */     //   217: aload_3
/*     */     //   218: invokevirtual 604	java/text/SimpleDateFormat:parse	(Ljava/lang/String;)Ljava/util/Date;
/*     */     //   221: astore 8
/*     */     //   223: aload 8
/*     */     //   225: ifnull +23 -> 248
/*     */     //   228: aload 4
/*     */     //   230: iconst_2
/*     */     //   231: new 610	java/sql/Date
/*     */     //   234: dup
/*     */     //   235: aload 8
/*     */     //   237: invokevirtual 612	java/util/Date:getTime	()J
/*     */     //   240: invokespecial 617	java/sql/Date:<init>	(J)V
/*     */     //   243: invokeinterface 618 3 0
/*     */     //   248: aload 4
/*     */     //   250: invokeinterface 185 1 0
/*     */     //   255: astore 5
/*     */     //   257: goto +228 -> 485
/*     */     //   260: new 142	com/claro/transfer/ImpresionTO
/*     */     //   263: dup
/*     */     //   264: invokespecial 144	com/claro/transfer/ImpresionTO:<init>	()V
/*     */     //   267: astore 10
/*     */     //   269: aload 10
/*     */     //   271: aload 5
/*     */     //   273: ldc_w 263
/*     */     //   276: invokeinterface 265 2 0
/*     */     //   281: invokevirtual 269	com/claro/transfer/ImpresionTO:setFechaFolio	(Ljava/sql/Timestamp;)V
/*     */     //   284: aload 10
/*     */     //   286: aload 5
/*     */     //   288: ldc_w 273
/*     */     //   291: invokeinterface 197 2 0
/*     */     //   296: invokevirtual 275	com/claro/transfer/ImpresionTO:setTipoReden	(Ljava/lang/String;)V
/*     */     //   299: aload 10
/*     */     //   301: aload 5
/*     */     //   303: ldc_w 290
/*     */     //   306: invokeinterface 197 2 0
/*     */     //   311: invokevirtual 292	com/claro/transfer/ImpresionTO:setMarca	(Ljava/lang/String;)V
/*     */     //   314: aload 10
/*     */     //   316: aload 5
/*     */     //   318: ldc_w 295
/*     */     //   321: invokeinterface 197 2 0
/*     */     //   326: invokevirtual 297	com/claro/transfer/ImpresionTO:setModelo	(Ljava/lang/String;)V
/*     */     //   329: aload 10
/*     */     //   331: aload 5
/*     */     //   333: ldc -18
/*     */     //   335: invokeinterface 210 2 0
/*     */     //   340: invokevirtual 240	com/claro/transfer/ImpresionTO:setValorPuntos	(I)V
/*     */     //   343: aload 10
/*     */     //   345: aload 5
/*     */     //   347: ldc_w 315
/*     */     //   350: invokeinterface 302 2 0
/*     */     //   355: invokevirtual 317	com/claro/transfer/ImpresionTO:setPrecioIva	(Ljava/math/BigDecimal;)V
/*     */     //   358: aload 10
/*     */     //   360: aload 5
/*     */     //   362: ldc_w 622
/*     */     //   365: invokeinterface 197 2 0
/*     */     //   370: invokevirtual 624	com/claro/transfer/ImpresionTO:setIdUsuario	(Ljava/lang/String;)V
/*     */     //   373: aload 10
/*     */     //   375: aload 5
/*     */     //   377: ldc_w 280
/*     */     //   380: invokeinterface 197 2 0
/*     */     //   385: invokevirtual 282	com/claro/transfer/ImpresionTO:setIdProducto	(Ljava/lang/String;)V
/*     */     //   388: aload 10
/*     */     //   390: aload 5
/*     */     //   392: ldc_w 548
/*     */     //   395: invokeinterface 197 2 0
/*     */     //   400: invokevirtual 550	com/claro/transfer/ImpresionTO:setCuenta	(Ljava/lang/String;)V
/*     */     //   403: aload 10
/*     */     //   405: aload 5
/*     */     //   407: ldc_w 627
/*     */     //   410: invokeinterface 210 2 0
/*     */     //   415: invokevirtual 629	com/claro/transfer/ImpresionTO:setIdRegion	(I)V
/*     */     //   418: aload 10
/*     */     //   420: aload 5
/*     */     //   422: ldc_w 360
/*     */     //   425: invokeinterface 197 2 0
/*     */     //   430: invokevirtual 362	com/claro/transfer/ImpresionTO:setFolio	(Ljava/lang/String;)V
/*     */     //   433: aload 10
/*     */     //   435: aload 5
/*     */     //   437: ldc_w 315
/*     */     //   440: invokeinterface 197 2 0
/*     */     //   445: invokestatic 555	com/claro/util/Utils:setFormatoDecimal	(Ljava/lang/String;)Ljava/lang/String;
/*     */     //   448: invokevirtual 387	com/claro/transfer/ImpresionTO:setPrecioIvaFormato	(Ljava/lang/String;)V
/*     */     //   451: aload 10
/*     */     //   453: aload 10
/*     */     //   455: invokevirtual 632	com/claro/transfer/ImpresionTO:getPrecioIvaFormato	()Ljava/lang/String;
/*     */     //   458: invokestatic 382	com/claro/util/Utils:setFormatoDecimalPrecio	(Ljava/lang/String;)Ljava/lang/String;
/*     */     //   461: invokevirtual 387	com/claro/transfer/ImpresionTO:setPrecioIvaFormato	(Ljava/lang/String;)V
/*     */     //   464: aload 10
/*     */     //   466: aload 10
/*     */     //   468: invokevirtual 443	com/claro/transfer/ImpresionTO:getValorPuntos	()I
/*     */     //   471: invokestatic 424	com/claro/util/Utils:setFormatoPtos	(I)Ljava/lang/String;
/*     */     //   474: invokevirtual 446	com/claro/transfer/ImpresionTO:setValorPuntosCF	(Ljava/lang/String;)V
/*     */     //   477: aload 9
/*     */     //   479: aload 10
/*     */     //   481: invokevirtual 635	java/util/ArrayList:add	(Ljava/lang/Object;)Z
/*     */     //   484: pop
/*     */     //   485: aload 5
/*     */     //   487: invokeinterface 189 1 0
/*     */     //   492: ifne -232 -> 260
/*     */     //   495: goto +148 -> 643
/*     */     //   498: astore 10
/*     */     //   500: new 59	com/claro/exception/CAException
/*     */     //   503: dup
/*     */     //   504: iconst_m1
/*     */     //   505: new 493	java/lang/StringBuilder
/*     */     //   508: dup
/*     */     //   509: ldc_w 639
/*     */     //   512: invokespecial 497	java/lang/StringBuilder:<init>	(Ljava/lang/String;)V
/*     */     //   515: aload 10
/*     */     //   517: invokevirtual 498	java/sql/SQLException:toString	()Ljava/lang/String;
/*     */     //   520: invokevirtual 501	java/lang/StringBuilder:append	(Ljava/lang/String;)Ljava/lang/StringBuilder;
/*     */     //   523: ldc_w 504
/*     */     //   526: invokevirtual 501	java/lang/StringBuilder:append	(Ljava/lang/String;)Ljava/lang/StringBuilder;
/*     */     //   529: invokevirtual 506	java/lang/StringBuilder:toString	()Ljava/lang/String;
/*     */     //   532: aload 10
/*     */     //   534: invokespecial 507	com/claro/exception/CAException:<init>	(ILjava/lang/String;Ljava/lang/Exception;)V
/*     */     //   537: athrow
/*     */     //   538: astore 10
/*     */     //   540: new 59	com/claro/exception/CAException
/*     */     //   543: dup
/*     */     //   544: iconst_m1
/*     */     //   545: new 493	java/lang/StringBuilder
/*     */     //   548: dup
/*     */     //   549: ldc_w 641
/*     */     //   552: invokespecial 497	java/lang/StringBuilder:<init>	(Ljava/lang/String;)V
/*     */     //   555: aload 10
/*     */     //   557: invokevirtual 512	java/lang/Exception:toString	()Ljava/lang/String;
/*     */     //   560: invokevirtual 501	java/lang/StringBuilder:append	(Ljava/lang/String;)Ljava/lang/StringBuilder;
/*     */     //   563: ldc_w 504
/*     */     //   566: invokevirtual 501	java/lang/StringBuilder:append	(Ljava/lang/String;)Ljava/lang/StringBuilder;
/*     */     //   569: invokevirtual 506	java/lang/StringBuilder:toString	()Ljava/lang/String;
/*     */     //   572: aload 10
/*     */     //   574: invokespecial 507	com/claro/exception/CAException:<init>	(ILjava/lang/String;Ljava/lang/Exception;)V
/*     */     //   577: athrow
/*     */     //   578: astore 11
/*     */     //   580: aload 5
/*     */     //   582: ifnull +18 -> 600
/*     */     //   585: aload 5
/*     */     //   587: invokeinterface 484 1 0
/*     */     //   592: aconst_null
/*     */     //   593: astore 5
/*     */     //   595: goto +5 -> 600
/*     */     //   598: astore 12
/*     */     //   600: aload 4
/*     */     //   602: ifnull +18 -> 620
/*     */     //   605: aload 4
/*     */     //   607: invokeinterface 487 1 0
/*     */     //   612: aconst_null
/*     */     //   613: astore 4
/*     */     //   615: goto +5 -> 620
/*     */     //   618: astore 12
/*     */     //   620: aload 6
/*     */     //   622: ifnull +18 -> 640
/*     */     //   625: aload 6
/*     */     //   627: invokeinterface 488 1 0
/*     */     //   632: aconst_null
/*     */     //   633: astore 6
/*     */     //   635: goto +5 -> 640
/*     */     //   638: astore 12
/*     */     //   640: aload 11
/*     */     //   642: athrow
/*     */     //   643: aload 5
/*     */     //   645: ifnull +18 -> 663
/*     */     //   648: aload 5
/*     */     //   650: invokeinterface 484 1 0
/*     */     //   655: aconst_null
/*     */     //   656: astore 5
/*     */     //   658: goto +5 -> 663
/*     */     //   661: astore 12
/*     */     //   663: aload 4
/*     */     //   665: ifnull +18 -> 683
/*     */     //   668: aload 4
/*     */     //   670: invokeinterface 487 1 0
/*     */     //   675: aconst_null
/*     */     //   676: astore 4
/*     */     //   678: goto +5 -> 683
/*     */     //   681: astore 12
/*     */     //   683: aload 6
/*     */     //   685: ifnull +18 -> 703
/*     */     //   688: aload 6
/*     */     //   690: invokeinterface 488 1 0
/*     */     //   695: aconst_null
/*     */     //   696: astore 6
/*     */     //   698: goto +5 -> 703
/*     */     //   701: astore 12
/*     */     //   703: aload 9
/*     */     //   705: areturn
/*     */     // Line number table:
/*     */     //   Java source line #263	-> byte code offset #0
/*     */     //   Java source line #264	-> byte code offset #3
/*     */     //   Java source line #265	-> byte code offset #6
/*     */     //   Java source line #266	-> byte code offset #9
/*     */     //   Java source line #267	-> byte code offset #18
/*     */     //   Java source line #269	-> byte code offset #21
/*     */     //   Java source line #271	-> byte code offset #30
/*     */     //   Java source line #272	-> byte code offset #39
/*     */     //   Java source line #273	-> byte code offset #61
/*     */     //   Java source line #274	-> byte code offset #77
/*     */     //   Java source line #276	-> byte code offset #85
/*     */     //   Java source line #277	-> byte code offset #96
/*     */     //   Java source line #279	-> byte code offset #108
/*     */     //   Java source line #282	-> byte code offset #117
/*     */     //   Java source line #283	-> byte code offset #126
/*     */     //   Java source line #284	-> byte code offset #135
/*     */     //   Java source line #285	-> byte code offset #144
/*     */     //   Java source line #288	-> byte code offset #153
/*     */     //   Java source line #289	-> byte code offset #164
/*     */     //   Java source line #291	-> byte code offset #178
/*     */     //   Java source line #292	-> byte code offset #189
/*     */     //   Java source line #294	-> byte code offset #201
/*     */     //   Java source line #297	-> byte code offset #210
/*     */     //   Java source line #298	-> byte code offset #214
/*     */     //   Java source line #299	-> byte code offset #223
/*     */     //   Java source line #300	-> byte code offset #228
/*     */     //   Java source line #303	-> byte code offset #248
/*     */     //   Java source line #305	-> byte code offset #257
/*     */     //   Java source line #306	-> byte code offset #260
/*     */     //   Java source line #308	-> byte code offset #269
/*     */     //   Java source line #309	-> byte code offset #284
/*     */     //   Java source line #310	-> byte code offset #299
/*     */     //   Java source line #311	-> byte code offset #314
/*     */     //   Java source line #312	-> byte code offset #329
/*     */     //   Java source line #313	-> byte code offset #343
/*     */     //   Java source line #314	-> byte code offset #358
/*     */     //   Java source line #315	-> byte code offset #373
/*     */     //   Java source line #316	-> byte code offset #388
/*     */     //   Java source line #317	-> byte code offset #403
/*     */     //   Java source line #318	-> byte code offset #418
/*     */     //   Java source line #319	-> byte code offset #433
/*     */     //   Java source line #320	-> byte code offset #451
/*     */     //   Java source line #321	-> byte code offset #464
/*     */     //   Java source line #322	-> byte code offset #477
/*     */     //   Java source line #305	-> byte code offset #485
/*     */     //   Java source line #324	-> byte code offset #498
/*     */     //   Java source line #325	-> byte code offset #500
/*     */     //   Java source line #326	-> byte code offset #538
/*     */     //   Java source line #327	-> byte code offset #540
/*     */     //   Java source line #328	-> byte code offset #578
/*     */     //   Java source line #329	-> byte code offset #580
/*     */     //   Java source line #330	-> byte code offset #600
/*     */     //   Java source line #331	-> byte code offset #620
/*     */     //   Java source line #332	-> byte code offset #640
/*     */     //   Java source line #329	-> byte code offset #643
/*     */     //   Java source line #330	-> byte code offset #663
/*     */     //   Java source line #331	-> byte code offset #683
/*     */     //   Java source line #333	-> byte code offset #703
/*     */     // Local variable table:
/*     */     //   start	length	slot	name	signature
/*     */     //   0	706	0	this	ImpresionDAO
/*     */     //   0	706	1	sTelefono	String
/*     */     //   0	706	2	cuenta	String
/*     */     //   0	706	3	sFecha	String
/*     */     //   1	676	4	statement	PreparedStatement
/*     */     //   4	653	5	resultSet	ResultSet
/*     */     //   7	690	6	connection	Connection
/*     */     //   16	151	7	query	StringBuffer
/*     */     //   19	217	8	dFecha	java.util.Date
/*     */     //   28	676	9	impresionDetalleRed	java.util.ArrayList<ImpresionTO>
/*     */     //   267	213	10	impresionTO	ImpresionTO
/*     */     //   498	35	10	e	SQLException
/*     */     //   538	35	10	e	Exception
/*     */     //   578	63	11	localObject	Object
/*     */     //   598	1	12	localException1	Exception
/*     */     //   618	1	12	localException2	Exception
/*     */     //   638	1	12	localException3	Exception
/*     */     //   661	1	12	localException4	Exception
/*     */     //   681	1	12	localException5	Exception
/*     */     //   701	1	12	localException6	Exception
/*     */     // Exception table:
/*     */     //   from	to	target	type
/*     */     //   153	495	498	java/sql/SQLException
/*     */     //   153	495	538	java/lang/Exception
/*     */     //   153	578	578	finally
/*     */     //   585	595	598	java/lang/Exception
/*     */     //   605	615	618	java/lang/Exception
/*     */     //   625	635	638	java/lang/Exception
/*     */     //   648	658	661	java/lang/Exception
/*     */     //   668	678	681	java/lang/Exception
/*     */     //   688	698	701	java/lang/Exception
/*     */   }
/*     */   
/*     */   /* Error */
/*     */   public java.util.ArrayList<ImpresionTO> detalleBonosInbursa(String sTelefono, String cuenta)
/*     */     throws CAException
/*     */   {
/*     */     // Byte code:
/*     */     //   0: aconst_null
/*     */     //   1: astore_3
/*     */     //   2: aconst_null
/*     */     //   3: astore 4
/*     */     //   5: aconst_null
/*     */     //   6: astore 5
/*     */     //   8: new 61	java/lang/StringBuffer
/*     */     //   11: dup
/*     */     //   12: invokespecial 63	java/lang/StringBuffer:<init>	()V
/*     */     //   15: astore 6
/*     */     //   17: new 575	java/util/ArrayList
/*     */     //   20: dup
/*     */     //   21: invokespecial 577	java/util/ArrayList:<init>	()V
/*     */     //   24: astore 7
/*     */     //   26: aload 6
/*     */     //   28: ldc_w 537
/*     */     //   31: invokevirtual 66	java/lang/StringBuffer:append	(Ljava/lang/String;)Ljava/lang/StringBuffer;
/*     */     //   34: pop
/*     */     //   35: aload 6
/*     */     //   37: ldc_w 580
/*     */     //   40: invokevirtual 66	java/lang/StringBuffer:append	(Ljava/lang/String;)Ljava/lang/StringBuffer;
/*     */     //   43: aload_0
/*     */     //   44: getfield 41	com/claro/dao/ImpresionDAO:schema_database	Ljava/lang/String;
/*     */     //   47: invokevirtual 66	java/lang/StringBuffer:append	(Ljava/lang/String;)Ljava/lang/StringBuffer;
/*     */     //   50: ldc_w 539
/*     */     //   53: invokevirtual 66	java/lang/StringBuffer:append	(Ljava/lang/String;)Ljava/lang/StringBuffer;
/*     */     //   56: pop
/*     */     //   57: aload 6
/*     */     //   59: ldc 94
/*     */     //   61: invokevirtual 66	java/lang/StringBuffer:append	(Ljava/lang/String;)Ljava/lang/StringBuffer;
/*     */     //   64: pop
/*     */     //   65: aload_1
/*     */     //   66: ifnull +22 -> 88
/*     */     //   69: aload_1
/*     */     //   70: invokevirtual 102	java/lang/String:length	()I
/*     */     //   73: ifle +15 -> 88
/*     */     //   76: aload 6
/*     */     //   78: ldc_w 653
/*     */     //   81: invokevirtual 66	java/lang/StringBuffer:append	(Ljava/lang/String;)Ljava/lang/StringBuffer;
/*     */     //   84: pop
/*     */     //   85: goto +12 -> 97
/*     */     //   88: aload 6
/*     */     //   90: ldc_w 655
/*     */     //   93: invokevirtual 66	java/lang/StringBuffer:append	(Ljava/lang/String;)Ljava/lang/StringBuffer;
/*     */     //   96: pop
/*     */     //   97: aload 6
/*     */     //   99: ldc_w 657
/*     */     //   102: invokevirtual 66	java/lang/StringBuffer:append	(Ljava/lang/String;)Ljava/lang/StringBuffer;
/*     */     //   105: pop
/*     */     //   106: invokestatic 29	com/claro/util/ServiceLocator:getInstance	()Lcom/claro/util/ServiceLocator;
/*     */     //   109: getstatic 145	com/claro/util/ServiceLocator:jdbcCirculoAzul	Ljava/lang/String;
/*     */     //   112: invokevirtual 148	com/claro/util/ServiceLocator:getConnection	(Ljava/lang/String;)Ljava/sql/Connection;
/*     */     //   115: astore 5
/*     */     //   117: aload 5
/*     */     //   119: aload 6
/*     */     //   121: invokevirtual 152	java/lang/StringBuffer:toString	()Ljava/lang/String;
/*     */     //   124: invokeinterface 155 2 0
/*     */     //   129: astore_3
/*     */     //   130: aload_1
/*     */     //   131: ifnull +21 -> 152
/*     */     //   134: aload_1
/*     */     //   135: invokevirtual 102	java/lang/String:length	()I
/*     */     //   138: ifle +14 -> 152
/*     */     //   141: aload_3
/*     */     //   142: iconst_1
/*     */     //   143: aload_1
/*     */     //   144: invokeinterface 161 3 0
/*     */     //   149: goto +11 -> 160
/*     */     //   152: aload_3
/*     */     //   153: iconst_1
/*     */     //   154: aload_2
/*     */     //   155: invokeinterface 161 3 0
/*     */     //   160: aload_3
/*     */     //   161: invokeinterface 185 1 0
/*     */     //   166: astore 4
/*     */     //   168: goto +161 -> 329
/*     */     //   171: new 142	com/claro/transfer/ImpresionTO
/*     */     //   174: dup
/*     */     //   175: invokespecial 144	com/claro/transfer/ImpresionTO:<init>	()V
/*     */     //   178: astore 8
/*     */     //   180: aload 8
/*     */     //   182: aload 4
/*     */     //   184: ldc_w 360
/*     */     //   187: invokeinterface 197 2 0
/*     */     //   192: invokevirtual 362	com/claro/transfer/ImpresionTO:setFolio	(Ljava/lang/String;)V
/*     */     //   195: aload 8
/*     */     //   197: aload 4
/*     */     //   199: ldc_w 543
/*     */     //   202: invokeinterface 197 2 0
/*     */     //   207: invokevirtual 545	com/claro/transfer/ImpresionTO:setTelefono	(Ljava/lang/String;)V
/*     */     //   210: aload 8
/*     */     //   212: aload 4
/*     */     //   214: ldc_w 548
/*     */     //   217: invokeinterface 197 2 0
/*     */     //   222: invokevirtual 550	com/claro/transfer/ImpresionTO:setCuenta	(Ljava/lang/String;)V
/*     */     //   225: aload 8
/*     */     //   227: aload 4
/*     */     //   229: ldc_w 553
/*     */     //   232: invokeinterface 197 2 0
/*     */     //   237: invokestatic 555	com/claro/util/Utils:setFormatoDecimal	(Ljava/lang/String;)Ljava/lang/String;
/*     */     //   240: invokevirtual 413	com/claro/transfer/ImpresionTO:setInbursaFormato	(Ljava/lang/String;)V
/*     */     //   243: aload 8
/*     */     //   245: aload 4
/*     */     //   247: ldc_w 558
/*     */     //   250: invokeinterface 197 2 0
/*     */     //   255: invokestatic 555	com/claro/util/Utils:setFormatoDecimal	(Ljava/lang/String;)Ljava/lang/String;
/*     */     //   258: invokevirtual 418	com/claro/transfer/ImpresionTO:setMarcaFormato	(Ljava/lang/String;)V
/*     */     //   261: aload 8
/*     */     //   263: aload 4
/*     */     //   265: ldc_w 560
/*     */     //   268: invokeinterface 220 2 0
/*     */     //   273: invokevirtual 230	com/claro/transfer/ImpresionTO:setFechaOperacion	(Ljava/util/Date;)V
/*     */     //   276: aload 8
/*     */     //   278: aload 4
/*     */     //   280: ldc_w 562
/*     */     //   283: invokeinterface 220 2 0
/*     */     //   288: invokevirtual 260	com/claro/transfer/ImpresionTO:setFechaPlazoSeg	(Ljava/util/Date;)V
/*     */     //   291: aload 8
/*     */     //   293: aload 4
/*     */     //   295: ldc_w 564
/*     */     //   298: invokeinterface 197 2 0
/*     */     //   303: invokevirtual 200	com/claro/transfer/ImpresionTO:setIdPuntoVenta	(Ljava/lang/String;)V
/*     */     //   306: aload 8
/*     */     //   308: aload 4
/*     */     //   310: ldc_w 566
/*     */     //   313: invokeinterface 197 2 0
/*     */     //   318: invokevirtual 568	com/claro/transfer/ImpresionTO:setFolioRedencion	(Ljava/lang/String;)V
/*     */     //   321: aload 7
/*     */     //   323: aload 8
/*     */     //   325: invokevirtual 635	java/util/ArrayList:add	(Ljava/lang/Object;)Z
/*     */     //   328: pop
/*     */     //   329: aload 4
/*     */     //   331: invokeinterface 189 1 0
/*     */     //   336: ifne -165 -> 171
/*     */     //   339: goto +145 -> 484
/*     */     //   342: astore 8
/*     */     //   344: new 59	com/claro/exception/CAException
/*     */     //   347: dup
/*     */     //   348: iconst_m1
/*     */     //   349: new 493	java/lang/StringBuilder
/*     */     //   352: dup
/*     */     //   353: ldc_w 639
/*     */     //   356: invokespecial 497	java/lang/StringBuilder:<init>	(Ljava/lang/String;)V
/*     */     //   359: aload 8
/*     */     //   361: invokevirtual 498	java/sql/SQLException:toString	()Ljava/lang/String;
/*     */     //   364: invokevirtual 501	java/lang/StringBuilder:append	(Ljava/lang/String;)Ljava/lang/StringBuilder;
/*     */     //   367: ldc_w 504
/*     */     //   370: invokevirtual 501	java/lang/StringBuilder:append	(Ljava/lang/String;)Ljava/lang/StringBuilder;
/*     */     //   373: invokevirtual 506	java/lang/StringBuilder:toString	()Ljava/lang/String;
/*     */     //   376: aload 8
/*     */     //   378: invokespecial 507	com/claro/exception/CAException:<init>	(ILjava/lang/String;Ljava/lang/Exception;)V
/*     */     //   381: athrow
/*     */     //   382: astore 8
/*     */     //   384: new 59	com/claro/exception/CAException
/*     */     //   387: dup
/*     */     //   388: iconst_m1
/*     */     //   389: new 493	java/lang/StringBuilder
/*     */     //   392: dup
/*     */     //   393: ldc_w 641
/*     */     //   396: invokespecial 497	java/lang/StringBuilder:<init>	(Ljava/lang/String;)V
/*     */     //   399: aload 8
/*     */     //   401: invokevirtual 512	java/lang/Exception:toString	()Ljava/lang/String;
/*     */     //   404: invokevirtual 501	java/lang/StringBuilder:append	(Ljava/lang/String;)Ljava/lang/StringBuilder;
/*     */     //   407: ldc_w 504
/*     */     //   410: invokevirtual 501	java/lang/StringBuilder:append	(Ljava/lang/String;)Ljava/lang/StringBuilder;
/*     */     //   413: invokevirtual 506	java/lang/StringBuilder:toString	()Ljava/lang/String;
/*     */     //   416: aload 8
/*     */     //   418: invokespecial 507	com/claro/exception/CAException:<init>	(ILjava/lang/String;Ljava/lang/Exception;)V
/*     */     //   421: athrow
/*     */     //   422: astore 9
/*     */     //   424: aload 4
/*     */     //   426: ifnull +18 -> 444
/*     */     //   429: aload 4
/*     */     //   431: invokeinterface 484 1 0
/*     */     //   436: aconst_null
/*     */     //   437: astore 4
/*     */     //   439: goto +5 -> 444
/*     */     //   442: astore 10
/*     */     //   444: aload_3
/*     */     //   445: ifnull +16 -> 461
/*     */     //   448: aload_3
/*     */     //   449: invokeinterface 487 1 0
/*     */     //   454: aconst_null
/*     */     //   455: astore_3
/*     */     //   456: goto +5 -> 461
/*     */     //   459: astore 10
/*     */     //   461: aload 5
/*     */     //   463: ifnull +18 -> 481
/*     */     //   466: aload 5
/*     */     //   468: invokeinterface 488 1 0
/*     */     //   473: aconst_null
/*     */     //   474: astore 5
/*     */     //   476: goto +5 -> 481
/*     */     //   479: astore 10
/*     */     //   481: aload 9
/*     */     //   483: athrow
/*     */     //   484: aload 4
/*     */     //   486: ifnull +18 -> 504
/*     */     //   489: aload 4
/*     */     //   491: invokeinterface 484 1 0
/*     */     //   496: aconst_null
/*     */     //   497: astore 4
/*     */     //   499: goto +5 -> 504
/*     */     //   502: astore 10
/*     */     //   504: aload_3
/*     */     //   505: ifnull +16 -> 521
/*     */     //   508: aload_3
/*     */     //   509: invokeinterface 487 1 0
/*     */     //   514: aconst_null
/*     */     //   515: astore_3
/*     */     //   516: goto +5 -> 521
/*     */     //   519: astore 10
/*     */     //   521: aload 5
/*     */     //   523: ifnull +18 -> 541
/*     */     //   526: aload 5
/*     */     //   528: invokeinterface 488 1 0
/*     */     //   533: aconst_null
/*     */     //   534: astore 5
/*     */     //   536: goto +5 -> 541
/*     */     //   539: astore 10
/*     */     //   541: aload 7
/*     */     //   543: areturn
/*     */     // Line number table:
/*     */     //   Java source line #338	-> byte code offset #0
/*     */     //   Java source line #339	-> byte code offset #2
/*     */     //   Java source line #340	-> byte code offset #5
/*     */     //   Java source line #341	-> byte code offset #8
/*     */     //   Java source line #343	-> byte code offset #17
/*     */     //   Java source line #345	-> byte code offset #26
/*     */     //   Java source line #346	-> byte code offset #35
/*     */     //   Java source line #347	-> byte code offset #57
/*     */     //   Java source line #349	-> byte code offset #65
/*     */     //   Java source line #350	-> byte code offset #76
/*     */     //   Java source line #352	-> byte code offset #88
/*     */     //   Java source line #354	-> byte code offset #97
/*     */     //   Java source line #357	-> byte code offset #106
/*     */     //   Java source line #358	-> byte code offset #117
/*     */     //   Java source line #360	-> byte code offset #130
/*     */     //   Java source line #361	-> byte code offset #141
/*     */     //   Java source line #363	-> byte code offset #152
/*     */     //   Java source line #367	-> byte code offset #160
/*     */     //   Java source line #369	-> byte code offset #168
/*     */     //   Java source line #370	-> byte code offset #171
/*     */     //   Java source line #371	-> byte code offset #180
/*     */     //   Java source line #372	-> byte code offset #195
/*     */     //   Java source line #373	-> byte code offset #210
/*     */     //   Java source line #374	-> byte code offset #225
/*     */     //   Java source line #375	-> byte code offset #243
/*     */     //   Java source line #376	-> byte code offset #261
/*     */     //   Java source line #377	-> byte code offset #276
/*     */     //   Java source line #378	-> byte code offset #291
/*     */     //   Java source line #379	-> byte code offset #306
/*     */     //   Java source line #380	-> byte code offset #321
/*     */     //   Java source line #369	-> byte code offset #329
/*     */     //   Java source line #382	-> byte code offset #342
/*     */     //   Java source line #383	-> byte code offset #344
/*     */     //   Java source line #384	-> byte code offset #382
/*     */     //   Java source line #385	-> byte code offset #384
/*     */     //   Java source line #386	-> byte code offset #422
/*     */     //   Java source line #387	-> byte code offset #424
/*     */     //   Java source line #388	-> byte code offset #444
/*     */     //   Java source line #389	-> byte code offset #461
/*     */     //   Java source line #390	-> byte code offset #481
/*     */     //   Java source line #387	-> byte code offset #484
/*     */     //   Java source line #388	-> byte code offset #504
/*     */     //   Java source line #389	-> byte code offset #521
/*     */     //   Java source line #391	-> byte code offset #541
/*     */     // Local variable table:
/*     */     //   start	length	slot	name	signature
/*     */     //   0	544	0	this	ImpresionDAO
/*     */     //   0	544	1	sTelefono	String
/*     */     //   0	544	2	cuenta	String
/*     */     //   1	515	3	statement	PreparedStatement
/*     */     //   3	495	4	resultSet	ResultSet
/*     */     //   6	529	5	connection	Connection
/*     */     //   15	105	6	query	StringBuffer
/*     */     //   24	518	7	impresionDetalleBonoInbursa	java.util.ArrayList<ImpresionTO>
/*     */     //   178	146	8	impresionTO	ImpresionTO
/*     */     //   342	35	8	e	SQLException
/*     */     //   382	35	8	e	Exception
/*     */     //   422	60	9	localObject	Object
/*     */     //   442	1	10	localException1	Exception
/*     */     //   459	1	10	localException2	Exception
/*     */     //   479	1	10	localException3	Exception
/*     */     //   502	1	10	localException4	Exception
/*     */     //   519	1	10	localException5	Exception
/*     */     //   539	1	10	localException6	Exception
/*     */     // Exception table:
/*     */     //   from	to	target	type
/*     */     //   106	339	342	java/sql/SQLException
/*     */     //   106	339	382	java/lang/Exception
/*     */     //   106	422	422	finally
/*     */     //   429	439	442	java/lang/Exception
/*     */     //   448	456	459	java/lang/Exception
/*     */     //   466	476	479	java/lang/Exception
/*     */     //   489	499	502	java/lang/Exception
/*     */     //   508	516	519	java/lang/Exception
/*     */     //   526	536	539	java/lang/Exception
/*     */   }
/*     */   
/*     */   /* Error */
/*     */   public ImpresionTO obtieneConstanciaAlianzas(String sFecha, String sCuenta, int iSecuencia, int tipoAlianza, String sFechaFolio, String sLinea)
/*     */     throws CAException
/*     */   {
/*     */     // Byte code:
/*     */     //   0: aconst_null
/*     */     //   1: astore 7
/*     */     //   3: aconst_null
/*     */     //   4: astore 8
/*     */     //   6: aconst_null
/*     */     //   7: astore 9
/*     */     //   9: new 61	java/lang/StringBuffer
/*     */     //   12: dup
/*     */     //   13: invokespecial 63	java/lang/StringBuffer:<init>	()V
/*     */     //   16: astore 10
/*     */     //   18: aconst_null
/*     */     //   19: astore 11
/*     */     //   21: new 142	com/claro/transfer/ImpresionTO
/*     */     //   24: dup
/*     */     //   25: invokespecial 144	com/claro/transfer/ImpresionTO:<init>	()V
/*     */     //   28: astore 12
/*     */     //   30: aload 10
/*     */     //   32: ldc_w 662
/*     */     //   35: invokevirtual 66	java/lang/StringBuffer:append	(Ljava/lang/String;)Ljava/lang/StringBuffer;
/*     */     //   38: pop
/*     */     //   39: aload 10
/*     */     //   41: ldc_w 664
/*     */     //   44: invokevirtual 66	java/lang/StringBuffer:append	(Ljava/lang/String;)Ljava/lang/StringBuffer;
/*     */     //   47: pop
/*     */     //   48: aload 10
/*     */     //   50: ldc_w 666
/*     */     //   53: invokevirtual 66	java/lang/StringBuffer:append	(Ljava/lang/String;)Ljava/lang/StringBuffer;
/*     */     //   56: pop
/*     */     //   57: aload 10
/*     */     //   59: ldc_w 580
/*     */     //   62: invokevirtual 66	java/lang/StringBuffer:append	(Ljava/lang/String;)Ljava/lang/StringBuffer;
/*     */     //   65: aload_0
/*     */     //   66: getfield 41	com/claro/dao/ImpresionDAO:schema_database	Ljava/lang/String;
/*     */     //   69: invokevirtual 66	java/lang/StringBuffer:append	(Ljava/lang/String;)Ljava/lang/StringBuffer;
/*     */     //   72: ldc_w 668
/*     */     //   75: invokevirtual 66	java/lang/StringBuffer:append	(Ljava/lang/String;)Ljava/lang/StringBuffer;
/*     */     //   78: aload_0
/*     */     //   79: getfield 41	com/claro/dao/ImpresionDAO:schema_database	Ljava/lang/String;
/*     */     //   82: invokevirtual 66	java/lang/StringBuffer:append	(Ljava/lang/String;)Ljava/lang/StringBuffer;
/*     */     //   85: ldc_w 670
/*     */     //   88: invokevirtual 66	java/lang/StringBuffer:append	(Ljava/lang/String;)Ljava/lang/StringBuffer;
/*     */     //   91: pop
/*     */     //   92: aload 10
/*     */     //   94: ldc 94
/*     */     //   96: invokevirtual 66	java/lang/StringBuffer:append	(Ljava/lang/String;)Ljava/lang/StringBuffer;
/*     */     //   99: pop
/*     */     //   100: aload 6
/*     */     //   102: ifnonnull +15 -> 117
/*     */     //   105: aload 10
/*     */     //   107: ldc_w 672
/*     */     //   110: invokevirtual 66	java/lang/StringBuffer:append	(Ljava/lang/String;)Ljava/lang/StringBuffer;
/*     */     //   113: pop
/*     */     //   114: goto +12 -> 126
/*     */     //   117: aload 10
/*     */     //   119: ldc_w 674
/*     */     //   122: invokevirtual 66	java/lang/StringBuffer:append	(Ljava/lang/String;)Ljava/lang/StringBuffer;
/*     */     //   125: pop
/*     */     //   126: aload 10
/*     */     //   128: ldc_w 676
/*     */     //   131: invokevirtual 66	java/lang/StringBuffer:append	(Ljava/lang/String;)Ljava/lang/StringBuffer;
/*     */     //   134: pop
/*     */     //   135: aload 10
/*     */     //   137: ldc_w 678
/*     */     //   140: invokevirtual 66	java/lang/StringBuffer:append	(Ljava/lang/String;)Ljava/lang/StringBuffer;
/*     */     //   143: pop
/*     */     //   144: aload 10
/*     */     //   146: ldc_w 680
/*     */     //   149: invokevirtual 66	java/lang/StringBuffer:append	(Ljava/lang/String;)Ljava/lang/StringBuffer;
/*     */     //   152: pop
/*     */     //   153: aload_1
/*     */     //   154: ifnull +12 -> 166
/*     */     //   157: aload 10
/*     */     //   159: ldc_w 682
/*     */     //   162: invokevirtual 66	java/lang/StringBuffer:append	(Ljava/lang/String;)Ljava/lang/StringBuffer;
/*     */     //   165: pop
/*     */     //   166: aload 10
/*     */     //   168: ldc_w 684
/*     */     //   171: invokevirtual 66	java/lang/StringBuffer:append	(Ljava/lang/String;)Ljava/lang/StringBuffer;
/*     */     //   174: pop
/*     */     //   175: aload 10
/*     */     //   177: ldc_w 686
/*     */     //   180: invokevirtual 66	java/lang/StringBuffer:append	(Ljava/lang/String;)Ljava/lang/StringBuffer;
/*     */     //   183: pop
/*     */     //   184: invokestatic 29	com/claro/util/ServiceLocator:getInstance	()Lcom/claro/util/ServiceLocator;
/*     */     //   187: getstatic 145	com/claro/util/ServiceLocator:jdbcCirculoAzul	Ljava/lang/String;
/*     */     //   190: invokevirtual 148	com/claro/util/ServiceLocator:getConnection	(Ljava/lang/String;)Ljava/sql/Connection;
/*     */     //   193: astore 9
/*     */     //   195: aload 9
/*     */     //   197: aload 10
/*     */     //   199: invokevirtual 152	java/lang/StringBuffer:toString	()Ljava/lang/String;
/*     */     //   202: invokeinterface 155 2 0
/*     */     //   207: astore 7
/*     */     //   209: aload 6
/*     */     //   211: ifnonnull +15 -> 226
/*     */     //   214: aload 7
/*     */     //   216: iconst_1
/*     */     //   217: aload_2
/*     */     //   218: invokeinterface 161 3 0
/*     */     //   223: goto +13 -> 236
/*     */     //   226: aload 7
/*     */     //   228: iconst_1
/*     */     //   229: aload 6
/*     */     //   231: invokeinterface 161 3 0
/*     */     //   236: aload 7
/*     */     //   238: iconst_2
/*     */     //   239: iload_3
/*     */     //   240: invokeinterface 688 3 0
/*     */     //   245: aload 7
/*     */     //   247: iconst_3
/*     */     //   248: iload 4
/*     */     //   250: invokeinterface 688 3 0
/*     */     //   255: aload_1
/*     */     //   256: ifnull +32 -> 288
/*     */     //   259: getstatic 598	com/claro/util/Constantes:DATEFORMATdd_MM_YYYY_2	Ljava/text/SimpleDateFormat;
/*     */     //   262: aload_1
/*     */     //   263: invokevirtual 604	java/text/SimpleDateFormat:parse	(Ljava/lang/String;)Ljava/util/Date;
/*     */     //   266: astore 11
/*     */     //   268: aload 7
/*     */     //   270: iconst_4
/*     */     //   271: new 610	java/sql/Date
/*     */     //   274: dup
/*     */     //   275: aload 11
/*     */     //   277: invokevirtual 612	java/util/Date:getTime	()J
/*     */     //   280: invokespecial 617	java/sql/Date:<init>	(J)V
/*     */     //   283: invokeinterface 618 3 0
/*     */     //   288: aload 7
/*     */     //   290: invokeinterface 185 1 0
/*     */     //   295: astore 8
/*     */     //   297: iconst_0
/*     */     //   298: istore 13
/*     */     //   300: new 575	java/util/ArrayList
/*     */     //   303: dup
/*     */     //   304: invokespecial 577	java/util/ArrayList:<init>	()V
/*     */     //   307: astore 14
/*     */     //   309: goto +283 -> 592
/*     */     //   312: iload 13
/*     */     //   314: ifne +78 -> 392
/*     */     //   317: aload 12
/*     */     //   319: aload 8
/*     */     //   321: ldc_w 548
/*     */     //   324: invokeinterface 197 2 0
/*     */     //   329: invokevirtual 550	com/claro/transfer/ImpresionTO:setCuenta	(Ljava/lang/String;)V
/*     */     //   332: aload 12
/*     */     //   334: aload 8
/*     */     //   336: ldc -28
/*     */     //   338: invokeinterface 220 2 0
/*     */     //   343: invokevirtual 230	com/claro/transfer/ImpresionTO:setFechaOperacion	(Ljava/util/Date;)V
/*     */     //   346: aload 12
/*     */     //   348: aload 8
/*     */     //   350: ldc -13
/*     */     //   352: invokeinterface 210 2 0
/*     */     //   357: invokevirtual 245	com/claro/transfer/ImpresionTO:setPtsDispRestantes	(I)V
/*     */     //   360: aload 12
/*     */     //   362: aload 8
/*     */     //   364: ldc_w 692
/*     */     //   367: invokeinterface 210 2 0
/*     */     //   372: invokevirtual 694	com/claro/transfer/ImpresionTO:setPtsTransferidos	(I)V
/*     */     //   375: aload 12
/*     */     //   377: aload 8
/*     */     //   379: ldc -61
/*     */     //   381: invokeinterface 197 2 0
/*     */     //   386: invokevirtual 200	com/claro/transfer/ImpresionTO:setIdPuntoVenta	(Ljava/lang/String;)V
/*     */     //   389: iinc 13 1
/*     */     //   392: aload 8
/*     */     //   394: ldc_w 692
/*     */     //   397: invokeinterface 210 2 0
/*     */     //   402: istore 15
/*     */     //   404: aload 8
/*     */     //   406: ldc_w 697
/*     */     //   409: invokeinterface 210 2 0
/*     */     //   414: istore 16
/*     */     //   416: aload 12
/*     */     //   418: aload 12
/*     */     //   420: invokevirtual 473	com/claro/transfer/ImpresionTO:getPtsCanjeado	()I
/*     */     //   423: iload 15
/*     */     //   425: iadd
/*     */     //   426: invokevirtual 699	com/claro/transfer/ImpresionTO:setPtsCanjeado	(I)V
/*     */     //   429: aload 12
/*     */     //   431: aload 12
/*     */     //   433: invokevirtual 467	com/claro/transfer/ImpresionTO:getPtsMillas	()I
/*     */     //   436: iload 16
/*     */     //   438: iadd
/*     */     //   439: invokevirtual 702	com/claro/transfer/ImpresionTO:setPtsMillas	(I)V
/*     */     //   442: new 705	com/claro/transfer/AlianzasTO
/*     */     //   445: dup
/*     */     //   446: invokespecial 707	com/claro/transfer/AlianzasTO:<init>	()V
/*     */     //   449: astore 17
/*     */     //   451: aload 17
/*     */     //   453: aload 8
/*     */     //   455: ldc_w 548
/*     */     //   458: invokeinterface 197 2 0
/*     */     //   463: invokevirtual 708	com/claro/transfer/AlianzasTO:setCuenta	(Ljava/lang/String;)V
/*     */     //   466: aload 17
/*     */     //   468: aload 8
/*     */     //   470: ldc -28
/*     */     //   472: invokeinterface 220 2 0
/*     */     //   477: invokevirtual 709	com/claro/transfer/AlianzasTO:setFechaOperacion	(Ljava/sql/Date;)V
/*     */     //   480: aload 17
/*     */     //   482: aload 8
/*     */     //   484: ldc_w 712
/*     */     //   487: invokeinterface 197 2 0
/*     */     //   492: invokevirtual 714	com/claro/transfer/AlianzasTO:setCuentaAlianza	(Ljava/lang/String;)V
/*     */     //   495: aload 17
/*     */     //   497: iload 15
/*     */     //   499: invokevirtual 717	com/claro/transfer/AlianzasTO:setPtsTransferidos	(I)V
/*     */     //   502: aload 17
/*     */     //   504: iload 16
/*     */     //   506: invokevirtual 718	com/claro/transfer/AlianzasTO:setMillas	(I)V
/*     */     //   509: aload 17
/*     */     //   511: aload 8
/*     */     //   513: ldc_w 721
/*     */     //   516: invokeinterface 197 2 0
/*     */     //   521: invokevirtual 723	com/claro/transfer/AlianzasTO:setComentario	(Ljava/lang/String;)V
/*     */     //   524: aload 17
/*     */     //   526: aload 8
/*     */     //   528: ldc_w 360
/*     */     //   531: invokeinterface 197 2 0
/*     */     //   536: invokevirtual 724	com/claro/transfer/AlianzasTO:setFolio	(Ljava/lang/String;)V
/*     */     //   539: aload 17
/*     */     //   541: aload 8
/*     */     //   543: ldc_w 725
/*     */     //   546: invokeinterface 210 2 0
/*     */     //   551: invokevirtual 727	com/claro/transfer/AlianzasTO:setValorCuponOrig	(I)V
/*     */     //   554: aload 17
/*     */     //   556: aload 8
/*     */     //   558: ldc_w 263
/*     */     //   561: invokeinterface 265 2 0
/*     */     //   566: invokevirtual 730	com/claro/transfer/AlianzasTO:setFechaFolio	(Ljava/sql/Timestamp;)V
/*     */     //   569: aload 17
/*     */     //   571: aload 8
/*     */     //   573: ldc_w 731
/*     */     //   576: invokeinterface 197 2 0
/*     */     //   581: invokevirtual 733	com/claro/transfer/AlianzasTO:setArchivoSalida	(Ljava/lang/String;)V
/*     */     //   584: aload 14
/*     */     //   586: aload 17
/*     */     //   588: invokevirtual 635	java/util/ArrayList:add	(Ljava/lang/Object;)Z
/*     */     //   591: pop
/*     */     //   592: aload 8
/*     */     //   594: invokeinterface 189 1 0
/*     */     //   599: ifne -287 -> 312
/*     */     //   602: aload 12
/*     */     //   604: aload 12
/*     */     //   606: invokevirtual 473	com/claro/transfer/ImpresionTO:getPtsCanjeado	()I
/*     */     //   609: invokestatic 424	com/claro/util/Utils:setFormatoPtos	(I)Ljava/lang/String;
/*     */     //   612: invokevirtual 476	com/claro/transfer/ImpresionTO:setPtsCanjeadoCF	(Ljava/lang/String;)V
/*     */     //   615: aload 12
/*     */     //   617: aload 12
/*     */     //   619: invokevirtual 467	com/claro/transfer/ImpresionTO:getPtsMillas	()I
/*     */     //   622: invokestatic 424	com/claro/util/Utils:setFormatoPtos	(I)Ljava/lang/String;
/*     */     //   625: invokevirtual 470	com/claro/transfer/ImpresionTO:setPtsMillasCF	(Ljava/lang/String;)V
/*     */     //   628: aload 12
/*     */     //   630: aload 12
/*     */     //   632: invokevirtual 431	com/claro/transfer/ImpresionTO:getPtosDisp	()I
/*     */     //   635: invokestatic 424	com/claro/util/Utils:setFormatoPtos	(I)Ljava/lang/String;
/*     */     //   638: invokevirtual 434	com/claro/transfer/ImpresionTO:setPtosDispCF	(Ljava/lang/String;)V
/*     */     //   641: aload 12
/*     */     //   643: aload 14
/*     */     //   645: invokevirtual 736	com/claro/transfer/ImpresionTO:setAlianzas	(Ljava/util/ArrayList;)V
/*     */     //   648: goto +148 -> 796
/*     */     //   651: astore 13
/*     */     //   653: new 59	com/claro/exception/CAException
/*     */     //   656: dup
/*     */     //   657: iconst_m1
/*     */     //   658: new 493	java/lang/StringBuilder
/*     */     //   661: dup
/*     */     //   662: ldc_w 740
/*     */     //   665: invokespecial 497	java/lang/StringBuilder:<init>	(Ljava/lang/String;)V
/*     */     //   668: aload 13
/*     */     //   670: invokevirtual 498	java/sql/SQLException:toString	()Ljava/lang/String;
/*     */     //   673: invokevirtual 501	java/lang/StringBuilder:append	(Ljava/lang/String;)Ljava/lang/StringBuilder;
/*     */     //   676: ldc_w 504
/*     */     //   679: invokevirtual 501	java/lang/StringBuilder:append	(Ljava/lang/String;)Ljava/lang/StringBuilder;
/*     */     //   682: invokevirtual 506	java/lang/StringBuilder:toString	()Ljava/lang/String;
/*     */     //   685: aload 13
/*     */     //   687: invokespecial 507	com/claro/exception/CAException:<init>	(ILjava/lang/String;Ljava/lang/Exception;)V
/*     */     //   690: athrow
/*     */     //   691: astore 13
/*     */     //   693: new 59	com/claro/exception/CAException
/*     */     //   696: dup
/*     */     //   697: iconst_m1
/*     */     //   698: new 493	java/lang/StringBuilder
/*     */     //   701: dup
/*     */     //   702: ldc_w 742
/*     */     //   705: invokespecial 497	java/lang/StringBuilder:<init>	(Ljava/lang/String;)V
/*     */     //   708: aload 13
/*     */     //   710: invokevirtual 512	java/lang/Exception:toString	()Ljava/lang/String;
/*     */     //   713: invokevirtual 501	java/lang/StringBuilder:append	(Ljava/lang/String;)Ljava/lang/StringBuilder;
/*     */     //   716: ldc_w 504
/*     */     //   719: invokevirtual 501	java/lang/StringBuilder:append	(Ljava/lang/String;)Ljava/lang/StringBuilder;
/*     */     //   722: invokevirtual 506	java/lang/StringBuilder:toString	()Ljava/lang/String;
/*     */     //   725: aload 13
/*     */     //   727: invokespecial 507	com/claro/exception/CAException:<init>	(ILjava/lang/String;Ljava/lang/Exception;)V
/*     */     //   730: athrow
/*     */     //   731: astore 18
/*     */     //   733: aload 8
/*     */     //   735: ifnull +18 -> 753
/*     */     //   738: aload 8
/*     */     //   740: invokeinterface 484 1 0
/*     */     //   745: aconst_null
/*     */     //   746: astore 8
/*     */     //   748: goto +5 -> 753
/*     */     //   751: astore 19
/*     */     //   753: aload 7
/*     */     //   755: ifnull +18 -> 773
/*     */     //   758: aload 7
/*     */     //   760: invokeinterface 487 1 0
/*     */     //   765: aconst_null
/*     */     //   766: astore 7
/*     */     //   768: goto +5 -> 773
/*     */     //   771: astore 19
/*     */     //   773: aload 9
/*     */     //   775: ifnull +18 -> 793
/*     */     //   778: aload 9
/*     */     //   780: invokeinterface 488 1 0
/*     */     //   785: aconst_null
/*     */     //   786: astore 9
/*     */     //   788: goto +5 -> 793
/*     */     //   791: astore 19
/*     */     //   793: aload 18
/*     */     //   795: athrow
/*     */     //   796: aload 8
/*     */     //   798: ifnull +18 -> 816
/*     */     //   801: aload 8
/*     */     //   803: invokeinterface 484 1 0
/*     */     //   808: aconst_null
/*     */     //   809: astore 8
/*     */     //   811: goto +5 -> 816
/*     */     //   814: astore 19
/*     */     //   816: aload 7
/*     */     //   818: ifnull +18 -> 836
/*     */     //   821: aload 7
/*     */     //   823: invokeinterface 487 1 0
/*     */     //   828: aconst_null
/*     */     //   829: astore 7
/*     */     //   831: goto +5 -> 836
/*     */     //   834: astore 19
/*     */     //   836: aload 9
/*     */     //   838: ifnull +18 -> 856
/*     */     //   841: aload 9
/*     */     //   843: invokeinterface 488 1 0
/*     */     //   848: aconst_null
/*     */     //   849: astore 9
/*     */     //   851: goto +5 -> 856
/*     */     //   854: astore 19
/*     */     //   856: aload 12
/*     */     //   858: areturn
/*     */     // Line number table:
/*     */     //   Java source line #396	-> byte code offset #0
/*     */     //   Java source line #397	-> byte code offset #3
/*     */     //   Java source line #398	-> byte code offset #6
/*     */     //   Java source line #399	-> byte code offset #9
/*     */     //   Java source line #400	-> byte code offset #18
/*     */     //   Java source line #402	-> byte code offset #21
/*     */     //   Java source line #404	-> byte code offset #30
/*     */     //   Java source line #405	-> byte code offset #39
/*     */     //   Java source line #406	-> byte code offset #48
/*     */     //   Java source line #407	-> byte code offset #57
/*     */     //   Java source line #408	-> byte code offset #92
/*     */     //   Java source line #409	-> byte code offset #100
/*     */     //   Java source line #410	-> byte code offset #105
/*     */     //   Java source line #412	-> byte code offset #117
/*     */     //   Java source line #414	-> byte code offset #126
/*     */     //   Java source line #415	-> byte code offset #135
/*     */     //   Java source line #416	-> byte code offset #144
/*     */     //   Java source line #417	-> byte code offset #153
/*     */     //   Java source line #418	-> byte code offset #157
/*     */     //   Java source line #420	-> byte code offset #166
/*     */     //   Java source line #421	-> byte code offset #175
/*     */     //   Java source line #424	-> byte code offset #184
/*     */     //   Java source line #425	-> byte code offset #195
/*     */     //   Java source line #427	-> byte code offset #209
/*     */     //   Java source line #428	-> byte code offset #214
/*     */     //   Java source line #430	-> byte code offset #226
/*     */     //   Java source line #432	-> byte code offset #236
/*     */     //   Java source line #433	-> byte code offset #245
/*     */     //   Java source line #435	-> byte code offset #255
/*     */     //   Java source line #436	-> byte code offset #259
/*     */     //   Java source line #437	-> byte code offset #268
/*     */     //   Java source line #441	-> byte code offset #288
/*     */     //   Java source line #442	-> byte code offset #297
/*     */     //   Java source line #443	-> byte code offset #300
/*     */     //   Java source line #444	-> byte code offset #309
/*     */     //   Java source line #446	-> byte code offset #312
/*     */     //   Java source line #447	-> byte code offset #317
/*     */     //   Java source line #448	-> byte code offset #332
/*     */     //   Java source line #449	-> byte code offset #346
/*     */     //   Java source line #450	-> byte code offset #360
/*     */     //   Java source line #451	-> byte code offset #375
/*     */     //   Java source line #452	-> byte code offset #389
/*     */     //   Java source line #454	-> byte code offset #392
/*     */     //   Java source line #455	-> byte code offset #404
/*     */     //   Java source line #457	-> byte code offset #416
/*     */     //   Java source line #458	-> byte code offset #429
/*     */     //   Java source line #460	-> byte code offset #442
/*     */     //   Java source line #461	-> byte code offset #451
/*     */     //   Java source line #462	-> byte code offset #466
/*     */     //   Java source line #463	-> byte code offset #480
/*     */     //   Java source line #464	-> byte code offset #495
/*     */     //   Java source line #465	-> byte code offset #502
/*     */     //   Java source line #466	-> byte code offset #509
/*     */     //   Java source line #467	-> byte code offset #524
/*     */     //   Java source line #468	-> byte code offset #539
/*     */     //   Java source line #469	-> byte code offset #554
/*     */     //   Java source line #470	-> byte code offset #569
/*     */     //   Java source line #473	-> byte code offset #584
/*     */     //   Java source line #444	-> byte code offset #592
/*     */     //   Java source line #475	-> byte code offset #602
/*     */     //   Java source line #476	-> byte code offset #615
/*     */     //   Java source line #477	-> byte code offset #628
/*     */     //   Java source line #478	-> byte code offset #641
/*     */     //   Java source line #479	-> byte code offset #651
/*     */     //   Java source line #480	-> byte code offset #653
/*     */     //   Java source line #481	-> byte code offset #691
/*     */     //   Java source line #482	-> byte code offset #693
/*     */     //   Java source line #483	-> byte code offset #731
/*     */     //   Java source line #484	-> byte code offset #733
/*     */     //   Java source line #485	-> byte code offset #753
/*     */     //   Java source line #486	-> byte code offset #773
/*     */     //   Java source line #487	-> byte code offset #793
/*     */     //   Java source line #484	-> byte code offset #796
/*     */     //   Java source line #485	-> byte code offset #816
/*     */     //   Java source line #486	-> byte code offset #836
/*     */     //   Java source line #488	-> byte code offset #856
/*     */     // Local variable table:
/*     */     //   start	length	slot	name	signature
/*     */     //   0	859	0	this	ImpresionDAO
/*     */     //   0	859	1	sFecha	String
/*     */     //   0	859	2	sCuenta	String
/*     */     //   0	859	3	iSecuencia	int
/*     */     //   0	859	4	tipoAlianza	int
/*     */     //   0	859	5	sFechaFolio	String
/*     */     //   0	859	6	sLinea	String
/*     */     //   1	829	7	statement	PreparedStatement
/*     */     //   4	806	8	resultSet	ResultSet
/*     */     //   7	843	9	connection	Connection
/*     */     //   16	182	10	query	StringBuffer
/*     */     //   19	257	11	dFecha	java.util.Date
/*     */     //   28	829	12	impresionTO	ImpresionTO
/*     */     //   298	92	13	contador	int
/*     */     //   651	35	13	e	SQLException
/*     */     //   691	35	13	e	Exception
/*     */     //   307	337	14	alianzasTO	java.util.ArrayList<com.claro.transfer.AlianzasTO>
/*     */     //   402	96	15	ptsTranferidos	int
/*     */     //   414	91	16	ptsMillas	int
/*     */     //   449	138	17	alianzaTO	com.claro.transfer.AlianzasTO
/*     */     //   731	63	18	localObject	Object
/*     */     //   751	1	19	localException1	Exception
/*     */     //   771	1	19	localException2	Exception
/*     */     //   791	1	19	localException3	Exception
/*     */     //   814	1	19	localException4	Exception
/*     */     //   834	1	19	localException5	Exception
/*     */     //   854	1	19	localException6	Exception
/*     */     // Exception table:
/*     */     //   from	to	target	type
/*     */     //   184	648	651	java/sql/SQLException
/*     */     //   184	648	691	java/lang/Exception
/*     */     //   184	731	731	finally
/*     */     //   738	748	751	java/lang/Exception
/*     */     //   758	768	771	java/lang/Exception
/*     */     //   778	788	791	java/lang/Exception
/*     */     //   801	811	814	java/lang/Exception
/*     */     //   821	831	834	java/lang/Exception
/*     */     //   841	851	854	java/lang/Exception
/*     */   }
/*     */   
/*     */   /* Error */
/*     */   public java.util.ArrayList<ImpresionTO> detalleImpresionAlianzas(String sFecha, String sCuenta, int iSecuencia, int tipoAlianza, String sFolio)
/*     */     throws CAException
/*     */   {
/*     */     // Byte code:
/*     */     //   0: aconst_null
/*     */     //   1: astore 6
/*     */     //   3: aconst_null
/*     */     //   4: astore 7
/*     */     //   6: aconst_null
/*     */     //   7: astore 8
/*     */     //   9: new 61	java/lang/StringBuffer
/*     */     //   12: dup
/*     */     //   13: invokespecial 63	java/lang/StringBuffer:<init>	()V
/*     */     //   16: astore 9
/*     */     //   18: new 575	java/util/ArrayList
/*     */     //   21: dup
/*     */     //   22: invokespecial 577	java/util/ArrayList:<init>	()V
/*     */     //   25: astore 10
/*     */     //   27: aload 9
/*     */     //   29: ldc_w 758
/*     */     //   32: invokevirtual 66	java/lang/StringBuffer:append	(Ljava/lang/String;)Ljava/lang/StringBuffer;
/*     */     //   35: pop
/*     */     //   36: aload 9
/*     */     //   38: ldc_w 760
/*     */     //   41: invokevirtual 66	java/lang/StringBuffer:append	(Ljava/lang/String;)Ljava/lang/StringBuffer;
/*     */     //   44: pop
/*     */     //   45: aload 9
/*     */     //   47: ldc 84
/*     */     //   49: invokevirtual 66	java/lang/StringBuffer:append	(Ljava/lang/String;)Ljava/lang/StringBuffer;
/*     */     //   52: aload_0
/*     */     //   53: getfield 41	com/claro/dao/ImpresionDAO:schema_database	Ljava/lang/String;
/*     */     //   56: invokevirtual 66	java/lang/StringBuffer:append	(Ljava/lang/String;)Ljava/lang/StringBuffer;
/*     */     //   59: ldc_w 762
/*     */     //   62: invokevirtual 66	java/lang/StringBuffer:append	(Ljava/lang/String;)Ljava/lang/StringBuffer;
/*     */     //   65: aload_0
/*     */     //   66: getfield 41	com/claro/dao/ImpresionDAO:schema_database	Ljava/lang/String;
/*     */     //   69: invokevirtual 66	java/lang/StringBuffer:append	(Ljava/lang/String;)Ljava/lang/StringBuffer;
/*     */     //   72: ldc_w 764
/*     */     //   75: invokevirtual 66	java/lang/StringBuffer:append	(Ljava/lang/String;)Ljava/lang/StringBuffer;
/*     */     //   78: aload_0
/*     */     //   79: getfield 41	com/claro/dao/ImpresionDAO:schema_database	Ljava/lang/String;
/*     */     //   82: invokevirtual 66	java/lang/StringBuffer:append	(Ljava/lang/String;)Ljava/lang/StringBuffer;
/*     */     //   85: ldc_w 766
/*     */     //   88: invokevirtual 66	java/lang/StringBuffer:append	(Ljava/lang/String;)Ljava/lang/StringBuffer;
/*     */     //   91: pop
/*     */     //   92: aload 9
/*     */     //   94: ldc_w 768
/*     */     //   97: invokevirtual 66	java/lang/StringBuffer:append	(Ljava/lang/String;)Ljava/lang/StringBuffer;
/*     */     //   100: pop
/*     */     //   101: aload 9
/*     */     //   103: ldc_w 770
/*     */     //   106: invokevirtual 66	java/lang/StringBuffer:append	(Ljava/lang/String;)Ljava/lang/StringBuffer;
/*     */     //   109: pop
/*     */     //   110: aload 9
/*     */     //   112: ldc_w 772
/*     */     //   115: invokevirtual 66	java/lang/StringBuffer:append	(Ljava/lang/String;)Ljava/lang/StringBuffer;
/*     */     //   118: pop
/*     */     //   119: aload 9
/*     */     //   121: ldc_w 774
/*     */     //   124: invokevirtual 66	java/lang/StringBuffer:append	(Ljava/lang/String;)Ljava/lang/StringBuffer;
/*     */     //   127: pop
/*     */     //   128: iload 4
/*     */     //   130: iconst_2
/*     */     //   131: if_icmpne +12 -> 143
/*     */     //   134: aload 9
/*     */     //   136: ldc_w 776
/*     */     //   139: invokevirtual 66	java/lang/StringBuffer:append	(Ljava/lang/String;)Ljava/lang/StringBuffer;
/*     */     //   142: pop
/*     */     //   143: aload 9
/*     */     //   145: ldc_w 778
/*     */     //   148: invokevirtual 66	java/lang/StringBuffer:append	(Ljava/lang/String;)Ljava/lang/StringBuffer;
/*     */     //   151: pop
/*     */     //   152: invokestatic 29	com/claro/util/ServiceLocator:getInstance	()Lcom/claro/util/ServiceLocator;
/*     */     //   155: getstatic 145	com/claro/util/ServiceLocator:jdbcCirculoAzul	Ljava/lang/String;
/*     */     //   158: invokevirtual 148	com/claro/util/ServiceLocator:getConnection	(Ljava/lang/String;)Ljava/sql/Connection;
/*     */     //   161: astore 8
/*     */     //   163: aload 8
/*     */     //   165: aload 9
/*     */     //   167: invokevirtual 152	java/lang/StringBuffer:toString	()Ljava/lang/String;
/*     */     //   170: invokeinterface 155 2 0
/*     */     //   175: astore 6
/*     */     //   177: aload 6
/*     */     //   179: iconst_1
/*     */     //   180: aload_2
/*     */     //   181: invokeinterface 161 3 0
/*     */     //   186: aload 6
/*     */     //   188: iconst_2
/*     */     //   189: iload_3
/*     */     //   190: invokeinterface 688 3 0
/*     */     //   195: aload 6
/*     */     //   197: iconst_3
/*     */     //   198: iload 4
/*     */     //   200: invokeinterface 688 3 0
/*     */     //   205: iload 4
/*     */     //   207: iconst_2
/*     */     //   208: if_icmpne +13 -> 221
/*     */     //   211: aload 6
/*     */     //   213: iconst_4
/*     */     //   214: aload 5
/*     */     //   216: invokeinterface 161 3 0
/*     */     //   221: aload 6
/*     */     //   223: invokeinterface 185 1 0
/*     */     //   228: astore 7
/*     */     //   230: goto +181 -> 411
/*     */     //   233: new 142	com/claro/transfer/ImpresionTO
/*     */     //   236: dup
/*     */     //   237: invokespecial 144	com/claro/transfer/ImpresionTO:<init>	()V
/*     */     //   240: astore 11
/*     */     //   242: new 142	com/claro/transfer/ImpresionTO
/*     */     //   245: dup
/*     */     //   246: invokespecial 144	com/claro/transfer/ImpresionTO:<init>	()V
/*     */     //   249: astore 12
/*     */     //   251: aload_0
/*     */     //   252: aload 7
/*     */     //   254: ldc_w 543
/*     */     //   257: invokeinterface 197 2 0
/*     */     //   262: aload 5
/*     */     //   264: invokevirtual 780	com/claro/dao/ImpresionDAO:datosImpresion	(Ljava/lang/String;Ljava/lang/String;)Lcom/claro/transfer/ImpresionTO;
/*     */     //   267: astore 12
/*     */     //   269: aload 11
/*     */     //   271: aload 7
/*     */     //   273: ldc_w 548
/*     */     //   276: invokeinterface 197 2 0
/*     */     //   281: invokevirtual 550	com/claro/transfer/ImpresionTO:setCuenta	(Ljava/lang/String;)V
/*     */     //   284: aload 11
/*     */     //   286: aload 7
/*     */     //   288: ldc -28
/*     */     //   290: invokeinterface 220 2 0
/*     */     //   295: invokevirtual 230	com/claro/transfer/ImpresionTO:setFechaOperacion	(Ljava/util/Date;)V
/*     */     //   298: aload 11
/*     */     //   300: aload 7
/*     */     //   302: ldc_w 692
/*     */     //   305: invokeinterface 210 2 0
/*     */     //   310: invokevirtual 694	com/claro/transfer/ImpresionTO:setPtsTransferidos	(I)V
/*     */     //   313: aload 11
/*     */     //   315: aload 7
/*     */     //   317: ldc_w 725
/*     */     //   320: invokeinterface 210 2 0
/*     */     //   325: invokevirtual 783	com/claro/transfer/ImpresionTO:setValorCuponOrig	(I)V
/*     */     //   328: aload 11
/*     */     //   330: aload 7
/*     */     //   332: ldc_w 721
/*     */     //   335: invokeinterface 197 2 0
/*     */     //   340: invokevirtual 322	com/claro/transfer/ImpresionTO:setComentario	(Ljava/lang/String;)V
/*     */     //   343: aload 11
/*     */     //   345: aload 7
/*     */     //   347: ldc_w 280
/*     */     //   350: invokeinterface 197 2 0
/*     */     //   355: invokevirtual 282	com/claro/transfer/ImpresionTO:setIdProducto	(Ljava/lang/String;)V
/*     */     //   358: aload 11
/*     */     //   360: aload 7
/*     */     //   362: ldc_w 285
/*     */     //   365: invokeinterface 197 2 0
/*     */     //   370: invokevirtual 287	com/claro/transfer/ImpresionTO:setDescripcion	(Ljava/lang/String;)V
/*     */     //   373: aload 11
/*     */     //   375: aload 7
/*     */     //   377: ldc_w 697
/*     */     //   380: invokeinterface 210 2 0
/*     */     //   385: invokevirtual 702	com/claro/transfer/ImpresionTO:setPtsMillas	(I)V
/*     */     //   388: aload 11
/*     */     //   390: aload 7
/*     */     //   392: ldc_w 784
/*     */     //   395: invokeinterface 197 2 0
/*     */     //   400: invokevirtual 786	com/claro/transfer/ImpresionTO:setIdReferencia	(Ljava/lang/String;)V
/*     */     //   403: aload 10
/*     */     //   405: aload 11
/*     */     //   407: invokevirtual 635	java/util/ArrayList:add	(Ljava/lang/Object;)Z
/*     */     //   410: pop
/*     */     //   411: aload 7
/*     */     //   413: invokeinterface 189 1 0
/*     */     //   418: ifne -185 -> 233
/*     */     //   421: goto +148 -> 569
/*     */     //   424: astore 11
/*     */     //   426: new 59	com/claro/exception/CAException
/*     */     //   429: dup
/*     */     //   430: iconst_m1
/*     */     //   431: new 493	java/lang/StringBuilder
/*     */     //   434: dup
/*     */     //   435: ldc_w 789
/*     */     //   438: invokespecial 497	java/lang/StringBuilder:<init>	(Ljava/lang/String;)V
/*     */     //   441: aload 11
/*     */     //   443: invokevirtual 498	java/sql/SQLException:toString	()Ljava/lang/String;
/*     */     //   446: invokevirtual 501	java/lang/StringBuilder:append	(Ljava/lang/String;)Ljava/lang/StringBuilder;
/*     */     //   449: ldc_w 504
/*     */     //   452: invokevirtual 501	java/lang/StringBuilder:append	(Ljava/lang/String;)Ljava/lang/StringBuilder;
/*     */     //   455: invokevirtual 506	java/lang/StringBuilder:toString	()Ljava/lang/String;
/*     */     //   458: aload 11
/*     */     //   460: invokespecial 507	com/claro/exception/CAException:<init>	(ILjava/lang/String;Ljava/lang/Exception;)V
/*     */     //   463: athrow
/*     */     //   464: astore 11
/*     */     //   466: new 59	com/claro/exception/CAException
/*     */     //   469: dup
/*     */     //   470: iconst_m1
/*     */     //   471: new 493	java/lang/StringBuilder
/*     */     //   474: dup
/*     */     //   475: ldc_w 791
/*     */     //   478: invokespecial 497	java/lang/StringBuilder:<init>	(Ljava/lang/String;)V
/*     */     //   481: aload 11
/*     */     //   483: invokevirtual 512	java/lang/Exception:toString	()Ljava/lang/String;
/*     */     //   486: invokevirtual 501	java/lang/StringBuilder:append	(Ljava/lang/String;)Ljava/lang/StringBuilder;
/*     */     //   489: ldc_w 504
/*     */     //   492: invokevirtual 501	java/lang/StringBuilder:append	(Ljava/lang/String;)Ljava/lang/StringBuilder;
/*     */     //   495: invokevirtual 506	java/lang/StringBuilder:toString	()Ljava/lang/String;
/*     */     //   498: aload 11
/*     */     //   500: invokespecial 507	com/claro/exception/CAException:<init>	(ILjava/lang/String;Ljava/lang/Exception;)V
/*     */     //   503: athrow
/*     */     //   504: astore 13
/*     */     //   506: aload 7
/*     */     //   508: ifnull +18 -> 526
/*     */     //   511: aload 7
/*     */     //   513: invokeinterface 484 1 0
/*     */     //   518: aconst_null
/*     */     //   519: astore 7
/*     */     //   521: goto +5 -> 526
/*     */     //   524: astore 14
/*     */     //   526: aload 6
/*     */     //   528: ifnull +18 -> 546
/*     */     //   531: aload 6
/*     */     //   533: invokeinterface 487 1 0
/*     */     //   538: aconst_null
/*     */     //   539: astore 6
/*     */     //   541: goto +5 -> 546
/*     */     //   544: astore 14
/*     */     //   546: aload 8
/*     */     //   548: ifnull +18 -> 566
/*     */     //   551: aload 8
/*     */     //   553: invokeinterface 488 1 0
/*     */     //   558: aconst_null
/*     */     //   559: astore 8
/*     */     //   561: goto +5 -> 566
/*     */     //   564: astore 14
/*     */     //   566: aload 13
/*     */     //   568: athrow
/*     */     //   569: aload 7
/*     */     //   571: ifnull +18 -> 589
/*     */     //   574: aload 7
/*     */     //   576: invokeinterface 484 1 0
/*     */     //   581: aconst_null
/*     */     //   582: astore 7
/*     */     //   584: goto +5 -> 589
/*     */     //   587: astore 14
/*     */     //   589: aload 6
/*     */     //   591: ifnull +18 -> 609
/*     */     //   594: aload 6
/*     */     //   596: invokeinterface 487 1 0
/*     */     //   601: aconst_null
/*     */     //   602: astore 6
/*     */     //   604: goto +5 -> 609
/*     */     //   607: astore 14
/*     */     //   609: aload 8
/*     */     //   611: ifnull +18 -> 629
/*     */     //   614: aload 8
/*     */     //   616: invokeinterface 488 1 0
/*     */     //   621: aconst_null
/*     */     //   622: astore 8
/*     */     //   624: goto +5 -> 629
/*     */     //   627: astore 14
/*     */     //   629: aload 10
/*     */     //   631: areturn
/*     */     // Line number table:
/*     */     //   Java source line #502	-> byte code offset #0
/*     */     //   Java source line #503	-> byte code offset #3
/*     */     //   Java source line #504	-> byte code offset #6
/*     */     //   Java source line #505	-> byte code offset #9
/*     */     //   Java source line #507	-> byte code offset #18
/*     */     //   Java source line #509	-> byte code offset #27
/*     */     //   Java source line #510	-> byte code offset #36
/*     */     //   Java source line #511	-> byte code offset #45
/*     */     //   Java source line #512	-> byte code offset #65
/*     */     //   Java source line #513	-> byte code offset #78
/*     */     //   Java source line #514	-> byte code offset #92
/*     */     //   Java source line #515	-> byte code offset #101
/*     */     //   Java source line #516	-> byte code offset #110
/*     */     //   Java source line #517	-> byte code offset #119
/*     */     //   Java source line #519	-> byte code offset #128
/*     */     //   Java source line #520	-> byte code offset #134
/*     */     //   Java source line #522	-> byte code offset #143
/*     */     //   Java source line #525	-> byte code offset #152
/*     */     //   Java source line #526	-> byte code offset #163
/*     */     //   Java source line #528	-> byte code offset #177
/*     */     //   Java source line #529	-> byte code offset #186
/*     */     //   Java source line #530	-> byte code offset #195
/*     */     //   Java source line #531	-> byte code offset #205
/*     */     //   Java source line #532	-> byte code offset #211
/*     */     //   Java source line #536	-> byte code offset #221
/*     */     //   Java source line #538	-> byte code offset #230
/*     */     //   Java source line #539	-> byte code offset #233
/*     */     //   Java source line #540	-> byte code offset #242
/*     */     //   Java source line #541	-> byte code offset #251
/*     */     //   Java source line #543	-> byte code offset #269
/*     */     //   Java source line #544	-> byte code offset #284
/*     */     //   Java source line #545	-> byte code offset #298
/*     */     //   Java source line #546	-> byte code offset #313
/*     */     //   Java source line #547	-> byte code offset #328
/*     */     //   Java source line #548	-> byte code offset #343
/*     */     //   Java source line #549	-> byte code offset #358
/*     */     //   Java source line #550	-> byte code offset #373
/*     */     //   Java source line #551	-> byte code offset #388
/*     */     //   Java source line #552	-> byte code offset #403
/*     */     //   Java source line #538	-> byte code offset #411
/*     */     //   Java source line #554	-> byte code offset #424
/*     */     //   Java source line #555	-> byte code offset #426
/*     */     //   Java source line #556	-> byte code offset #464
/*     */     //   Java source line #557	-> byte code offset #466
/*     */     //   Java source line #558	-> byte code offset #504
/*     */     //   Java source line #559	-> byte code offset #506
/*     */     //   Java source line #560	-> byte code offset #526
/*     */     //   Java source line #561	-> byte code offset #546
/*     */     //   Java source line #562	-> byte code offset #566
/*     */     //   Java source line #559	-> byte code offset #569
/*     */     //   Java source line #560	-> byte code offset #589
/*     */     //   Java source line #561	-> byte code offset #609
/*     */     //   Java source line #563	-> byte code offset #629
/*     */     // Local variable table:
/*     */     //   start	length	slot	name	signature
/*     */     //   0	632	0	this	ImpresionDAO
/*     */     //   0	632	1	sFecha	String
/*     */     //   0	632	2	sCuenta	String
/*     */     //   0	632	3	iSecuencia	int
/*     */     //   0	632	4	tipoAlianza	int
/*     */     //   0	632	5	sFolio	String
/*     */     //   1	602	6	statement	PreparedStatement
/*     */     //   4	579	7	resultSet	ResultSet
/*     */     //   7	616	8	connection	Connection
/*     */     //   16	150	9	query	StringBuffer
/*     */     //   25	605	10	impresionDetAlianza	java.util.ArrayList<ImpresionTO>
/*     */     //   240	166	11	impresionTO	ImpresionTO
/*     */     //   424	35	11	e	SQLException
/*     */     //   464	35	11	e	Exception
/*     */     //   249	19	12	tmp	ImpresionTO
/*     */     //   504	63	13	localObject	Object
/*     */     //   524	1	14	localException1	Exception
/*     */     //   544	1	14	localException2	Exception
/*     */     //   564	1	14	localException3	Exception
/*     */     //   587	1	14	localException4	Exception
/*     */     //   607	1	14	localException5	Exception
/*     */     //   627	1	14	localException6	Exception
/*     */     // Exception table:
/*     */     //   from	to	target	type
/*     */     //   152	421	424	java/sql/SQLException
/*     */     //   152	421	464	java/lang/Exception
/*     */     //   152	504	504	finally
/*     */     //   511	521	524	java/lang/Exception
/*     */     //   531	541	544	java/lang/Exception
/*     */     //   551	561	564	java/lang/Exception
/*     */     //   574	584	587	java/lang/Exception
/*     */     //   594	604	607	java/lang/Exception
/*     */     //   614	624	627	java/lang/Exception
/*     */   }
/*     */   
/*     */   public ImpresionTO datosImpresion(String sTelefono, String fechaFolio)
/*     */     throws CAException
/*     */   {
/* 575 */     PreparedStatement statement = null;
/* 576 */     ResultSet resultSet = null;
/* 577 */     Connection connection = null;
/*     */     
/* 579 */     StringBuffer query = new StringBuffer();
/*     */     
/*     */ 
/*     */ 
/*     */ 
/* 584 */     query.append(" SELECT C.IDPUNTOVTA, MAX(C.FECHAOPER) FECHAOPER,  ");
/* 585 */     query.append(" C.PUNTOSACUM, C.PUNTOSDISPO, C.PTRANSF, C.PTSACUMRES,  ");
/* 586 */     query.append(" C.PTSDISPORES,C.FECHAFOLIO, C.OPCION, C.CUENTA, C.SECUENCIA   ");
/* 587 */     query.append("  FROM  ").append(this.schema_database).append("PTO_TBLLINEAS A,  ")
/* 588 */       .append(this.schema_database).append("PTO_TBLTOTALES B, ")
/* 589 */       .append(this.schema_database).append("PTO_TBLALIANZAS  C ");
/* 590 */     query.append(" WHERE A.LINEA = ? ");
/* 591 */     query.append(" AND A.CUENTA = B.CUENTA AND A.SECUENCIA = B.SECUENCIA  ");
/* 592 */     query.append(" AND A.CUENTA = C.CUENTA AND A.SECUENCIA = C.SECUENCIA  ");
/* 593 */     query.append(" AND C.ESTATUS = 'A'\tAND C.FECHAFOLIO = ?  ");
/* 594 */     query.append(" GROUP BY C.IDPUNTOVTA, C.PUNTOSACUM, C.PUNTOSDISPO,  ");
/* 595 */     query.append(" C.PTRANSF, C.PTSACUMRES, C.PTSDISPORES, C.FECHAFOLIO,  ");
/* 596 */     query.append(" C.OPCION, C.CUENTA, C.SECUENCIA  ");
/* 597 */     query.append(" ORDER BY C.FECHAFOLIO ");
/* 598 */     ImpresionTO impresionTO = new ImpresionTO();
/*     */     try
/*     */     {
/* 601 */       connection = ServiceLocator.getInstance().getConnection(ServiceLocator.jdbcCirculoAzul);
/* 602 */       statement = connection.prepareStatement(query.toString());
/*     */       
/*     */ 
/*     */ 
/*     */ 
/*     */ 
/*     */ 
/*     */ 
/*     */ 
/* 611 */       statement.setString(1, sTelefono);
/*     */       
/*     */ 
/*     */ 
/*     */ 
/*     */ 
/*     */ 
/* 618 */       statement.setTimestamp(2, new Timestamp(new Long(fechaFolio).longValue()));
/*     */       
/*     */ 
/*     */ 
/*     */ 
/* 623 */       resultSet = statement.executeQuery();
/*     */       
/* 625 */       if (resultSet.next()) {
/* 626 */         impresionTO.setIdPuntoVenta(resultSet.getString("IDPUNTOVTA"));
/* 627 */         impresionTO.setFechaOperacion(resultSet.getDate("FECHAOPER"));
/* 628 */         impresionTO.setPtsAcum(resultSet.getInt("PUNTOSACUM"));
/* 629 */         impresionTO.setPtosDisp(resultSet.getInt("PUNTOSDISPO"));
/* 630 */         impresionTO.setPtsTransferidos(resultSet.getInt("PTRANSF"));
/* 631 */         impresionTO.setPtsAcumRes(resultSet.getInt("PTSACUMRES"));
/* 632 */         impresionTO.setPtsDispRestantes(resultSet.getInt("PTSDISPORES"));
/* 633 */         impresionTO.setFechaFolio(resultSet.getTimestamp("FECHAFOLIO"));
/* 634 */         impresionTO.setOpcion(resultSet.getInt("OPCION"));
/* 635 */         impresionTO.setCuenta(resultSet.getString("CUENTA"));
/* 636 */         impresionTO.setSecuencia(resultSet.getInt("SECUENCIA"));
/* 637 */         return impresionTO;
/*     */       }
/* 639 */       impresionTO.agregaMensaje(1, "No existe ninguna redencion para el telefono y la fecha indicados.");
/*     */     }
/*     */     catch (SQLException e) {
/* 642 */       throw new CAException(-1, "SQLException.datosImpresion [" + e.toString() + "]", e);
/*     */     } catch (Exception e) {
/* 644 */       throw new CAException(-1, "ImpresionDAO.datosImpresion[" + e.toString() + "]", e);
/*     */     } finally {
/* 646 */       if (resultSet != null) try { resultSet.close();resultSet = null; } catch (Exception localException4) {}
/* 647 */       if (statement != null) try { statement.close();statement = null; } catch (Exception localException5) {}
/* 648 */       if (connection != null) try { connection.close();connection = null;
/*     */         }
/*     */         catch (Exception localException6) {}
/*     */     }
/* 646 */     if (resultSet != null) try { resultSet.close();resultSet = null; } catch (Exception localException7) {}
/* 647 */     if (statement != null) try { statement.close();statement = null; } catch (Exception localException8) {}
/* 648 */     if (connection != null) try { connection.close();connection = null;
/*     */       } catch (Exception localException9) {}
/* 650 */     return impresionTO;
/*     */   }
/*     */   
/*     */   /* Error */
/*     */   public java.util.ArrayList<ImpresionTO> detalleEquipo(String sFecha, String sTipoRed, String sFechaFolio, String sCuenta, String sTelefono)
/*     */     throws CAException
/*     */   {
/*     */     // Byte code:
/*     */     //   0: aconst_null
/*     */     //   1: astore 6
/*     */     //   3: aconst_null
/*     */     //   4: astore 7
/*     */     //   6: aconst_null
/*     */     //   7: astore 8
/*     */     //   9: new 61	java/lang/StringBuffer
/*     */     //   12: dup
/*     */     //   13: invokespecial 63	java/lang/StringBuffer:<init>	()V
/*     */     //   16: astore 9
/*     */     //   18: aconst_null
/*     */     //   19: astore 10
/*     */     //   21: aconst_null
/*     */     //   22: astore 11
/*     */     //   24: new 575	java/util/ArrayList
/*     */     //   27: dup
/*     */     //   28: invokespecial 577	java/util/ArrayList:<init>	()V
/*     */     //   31: astore 12
/*     */     //   33: aload 9
/*     */     //   35: ldc_w 839
/*     */     //   38: invokevirtual 66	java/lang/StringBuffer:append	(Ljava/lang/String;)Ljava/lang/StringBuffer;
/*     */     //   41: pop
/*     */     //   42: aload 9
/*     */     //   44: ldc_w 841
/*     */     //   47: invokevirtual 66	java/lang/StringBuffer:append	(Ljava/lang/String;)Ljava/lang/StringBuffer;
/*     */     //   50: pop
/*     */     //   51: aload 9
/*     */     //   53: ldc_w 580
/*     */     //   56: invokevirtual 66	java/lang/StringBuffer:append	(Ljava/lang/String;)Ljava/lang/StringBuffer;
/*     */     //   59: aload_0
/*     */     //   60: getfield 41	com/claro/dao/ImpresionDAO:schema_database	Ljava/lang/String;
/*     */     //   63: invokevirtual 66	java/lang/StringBuffer:append	(Ljava/lang/String;)Ljava/lang/StringBuffer;
/*     */     //   66: ldc_w 843
/*     */     //   69: invokevirtual 66	java/lang/StringBuffer:append	(Ljava/lang/String;)Ljava/lang/StringBuffer;
/*     */     //   72: pop
/*     */     //   73: aload 9
/*     */     //   75: ldc_w 845
/*     */     //   78: invokevirtual 66	java/lang/StringBuffer:append	(Ljava/lang/String;)Ljava/lang/StringBuffer;
/*     */     //   81: pop
/*     */     //   82: aload 9
/*     */     //   84: ldc_w 847
/*     */     //   87: invokevirtual 66	java/lang/StringBuffer:append	(Ljava/lang/String;)Ljava/lang/StringBuffer;
/*     */     //   90: pop
/*     */     //   91: aload 9
/*     */     //   93: ldc_w 592
/*     */     //   96: invokevirtual 66	java/lang/StringBuffer:append	(Ljava/lang/String;)Ljava/lang/StringBuffer;
/*     */     //   99: pop
/*     */     //   100: aload 9
/*     */     //   102: ldc_w 849
/*     */     //   105: invokevirtual 66	java/lang/StringBuffer:append	(Ljava/lang/String;)Ljava/lang/StringBuffer;
/*     */     //   108: pop
/*     */     //   109: aload 9
/*     */     //   111: ldc_w 851
/*     */     //   114: invokevirtual 66	java/lang/StringBuffer:append	(Ljava/lang/String;)Ljava/lang/StringBuffer;
/*     */     //   117: pop
/*     */     //   118: aload_3
/*     */     //   119: ifnull +12 -> 131
/*     */     //   122: aload 9
/*     */     //   124: ldc_w 853
/*     */     //   127: invokevirtual 66	java/lang/StringBuffer:append	(Ljava/lang/String;)Ljava/lang/StringBuffer;
/*     */     //   130: pop
/*     */     //   131: invokestatic 29	com/claro/util/ServiceLocator:getInstance	()Lcom/claro/util/ServiceLocator;
/*     */     //   134: getstatic 145	com/claro/util/ServiceLocator:jdbcCirculoAzul	Ljava/lang/String;
/*     */     //   137: invokevirtual 148	com/claro/util/ServiceLocator:getConnection	(Ljava/lang/String;)Ljava/sql/Connection;
/*     */     //   140: astore 8
/*     */     //   142: aload 8
/*     */     //   144: aload 9
/*     */     //   146: invokevirtual 152	java/lang/StringBuffer:toString	()Ljava/lang/String;
/*     */     //   149: invokeinterface 155 2 0
/*     */     //   154: astore 6
/*     */     //   156: aload 6
/*     */     //   158: iconst_1
/*     */     //   159: aload 4
/*     */     //   161: invokeinterface 161 3 0
/*     */     //   166: aload 6
/*     */     //   168: iconst_2
/*     */     //   169: aload 5
/*     */     //   171: invokeinterface 161 3 0
/*     */     //   176: aload_1
/*     */     //   177: ifnull +12 -> 189
/*     */     //   180: getstatic 855	com/claro/util/Constantes:DATEFORMATyyyy_MM_dd	Ljava/text/SimpleDateFormat;
/*     */     //   183: aload_1
/*     */     //   184: invokevirtual 604	java/text/SimpleDateFormat:parse	(Ljava/lang/String;)Ljava/util/Date;
/*     */     //   187: astore 10
/*     */     //   189: aload 10
/*     */     //   191: ifnull +23 -> 214
/*     */     //   194: aload 6
/*     */     //   196: iconst_3
/*     */     //   197: new 610	java/sql/Date
/*     */     //   200: dup
/*     */     //   201: aload 10
/*     */     //   203: invokevirtual 612	java/util/Date:getTime	()J
/*     */     //   206: invokespecial 617	java/sql/Date:<init>	(J)V
/*     */     //   209: invokeinterface 618 3 0
/*     */     //   214: aload 6
/*     */     //   216: iconst_4
/*     */     //   217: aload_2
/*     */     //   218: invokeinterface 161 3 0
/*     */     //   223: aload_3
/*     */     //   224: ifnull +12 -> 236
/*     */     //   227: getstatic 858	com/claro/util/Constantes:DATEFORMTAyyyy_MM_ddHHmmss	Ljava/text/SimpleDateFormat;
/*     */     //   230: aload_3
/*     */     //   231: invokevirtual 604	java/text/SimpleDateFormat:parse	(Ljava/lang/String;)Ljava/util/Date;
/*     */     //   234: astore 11
/*     */     //   236: aload 11
/*     */     //   238: ifnull +23 -> 261
/*     */     //   241: aload 6
/*     */     //   243: iconst_5
/*     */     //   244: new 610	java/sql/Date
/*     */     //   247: dup
/*     */     //   248: aload 11
/*     */     //   250: invokevirtual 612	java/util/Date:getTime	()J
/*     */     //   253: invokespecial 617	java/sql/Date:<init>	(J)V
/*     */     //   256: invokeinterface 618 3 0
/*     */     //   261: aload 6
/*     */     //   263: invokeinterface 185 1 0
/*     */     //   268: astore 7
/*     */     //   270: goto +208 -> 478
/*     */     //   273: new 142	com/claro/transfer/ImpresionTO
/*     */     //   276: dup
/*     */     //   277: invokespecial 144	com/claro/transfer/ImpresionTO:<init>	()V
/*     */     //   280: astore 13
/*     */     //   282: aload 13
/*     */     //   284: aload 7
/*     */     //   286: ldc_w 285
/*     */     //   289: invokeinterface 197 2 0
/*     */     //   294: invokevirtual 287	com/claro/transfer/ImpresionTO:setDescripcion	(Ljava/lang/String;)V
/*     */     //   297: aload 13
/*     */     //   299: aload 7
/*     */     //   301: ldc_w 290
/*     */     //   304: invokeinterface 197 2 0
/*     */     //   309: invokevirtual 297	com/claro/transfer/ImpresionTO:setModelo	(Ljava/lang/String;)V
/*     */     //   312: aload 13
/*     */     //   314: aload 7
/*     */     //   316: ldc_w 295
/*     */     //   319: invokeinterface 197 2 0
/*     */     //   324: invokevirtual 292	com/claro/transfer/ImpresionTO:setMarca	(Ljava/lang/String;)V
/*     */     //   327: aload 13
/*     */     //   329: aload 7
/*     */     //   331: ldc -18
/*     */     //   333: invokeinterface 210 2 0
/*     */     //   338: invokevirtual 240	com/claro/transfer/ImpresionTO:setValorPuntos	(I)V
/*     */     //   341: aload 13
/*     */     //   343: aload 7
/*     */     //   345: ldc_w 315
/*     */     //   348: invokeinterface 197 2 0
/*     */     //   353: invokestatic 555	com/claro/util/Utils:setFormatoDecimal	(Ljava/lang/String;)Ljava/lang/String;
/*     */     //   356: invokevirtual 387	com/claro/transfer/ImpresionTO:setPrecioIvaFormato	(Ljava/lang/String;)V
/*     */     //   359: aload 13
/*     */     //   361: aload 7
/*     */     //   363: ldc_w 320
/*     */     //   366: invokeinterface 197 2 0
/*     */     //   371: invokevirtual 322	com/claro/transfer/ImpresionTO:setComentario	(Ljava/lang/String;)V
/*     */     //   374: aload 13
/*     */     //   376: aload 7
/*     */     //   378: ldc_w 273
/*     */     //   381: invokeinterface 197 2 0
/*     */     //   386: invokevirtual 275	com/claro/transfer/ImpresionTO:setTipoReden	(Ljava/lang/String;)V
/*     */     //   389: aload 13
/*     */     //   391: aload 7
/*     */     //   393: ldc_w 263
/*     */     //   396: invokeinterface 265 2 0
/*     */     //   401: invokevirtual 269	com/claro/transfer/ImpresionTO:setFechaFolio	(Ljava/sql/Timestamp;)V
/*     */     //   404: aload 13
/*     */     //   406: aload 7
/*     */     //   408: ldc_w 280
/*     */     //   411: invokeinterface 197 2 0
/*     */     //   416: invokevirtual 282	com/claro/transfer/ImpresionTO:setIdProducto	(Ljava/lang/String;)V
/*     */     //   419: aload 13
/*     */     //   421: aload 7
/*     */     //   423: ldc_w 622
/*     */     //   426: invokeinterface 197 2 0
/*     */     //   431: invokevirtual 624	com/claro/transfer/ImpresionTO:setIdUsuario	(Ljava/lang/String;)V
/*     */     //   434: aload 13
/*     */     //   436: aload 7
/*     */     //   438: ldc_w 310
/*     */     //   441: invokeinterface 197 2 0
/*     */     //   446: invokestatic 555	com/claro/util/Utils:setFormatoDecimal	(Ljava/lang/String;)Ljava/lang/String;
/*     */     //   449: invokevirtual 393	com/claro/transfer/ImpresionTO:setDescuentoFormato	(Ljava/lang/String;)V
/*     */     //   452: aload 13
/*     */     //   454: aload 7
/*     */     //   456: ldc_w 300
/*     */     //   459: invokeinterface 197 2 0
/*     */     //   464: invokestatic 555	com/claro/util/Utils:setFormatoDecimal	(Ljava/lang/String;)Ljava/lang/String;
/*     */     //   467: invokevirtual 390	com/claro/transfer/ImpresionTO:setPrecioFormato	(Ljava/lang/String;)V
/*     */     //   470: aload 12
/*     */     //   472: aload 13
/*     */     //   474: invokevirtual 635	java/util/ArrayList:add	(Ljava/lang/Object;)Z
/*     */     //   477: pop
/*     */     //   478: aload 7
/*     */     //   480: invokeinterface 189 1 0
/*     */     //   485: ifne -212 -> 273
/*     */     //   488: goto +148 -> 636
/*     */     //   491: astore 13
/*     */     //   493: new 59	com/claro/exception/CAException
/*     */     //   496: dup
/*     */     //   497: iconst_m1
/*     */     //   498: new 493	java/lang/StringBuilder
/*     */     //   501: dup
/*     */     //   502: ldc_w 861
/*     */     //   505: invokespecial 497	java/lang/StringBuilder:<init>	(Ljava/lang/String;)V
/*     */     //   508: aload 13
/*     */     //   510: invokevirtual 498	java/sql/SQLException:toString	()Ljava/lang/String;
/*     */     //   513: invokevirtual 501	java/lang/StringBuilder:append	(Ljava/lang/String;)Ljava/lang/StringBuilder;
/*     */     //   516: ldc_w 504
/*     */     //   519: invokevirtual 501	java/lang/StringBuilder:append	(Ljava/lang/String;)Ljava/lang/StringBuilder;
/*     */     //   522: invokevirtual 506	java/lang/StringBuilder:toString	()Ljava/lang/String;
/*     */     //   525: aload 13
/*     */     //   527: invokespecial 507	com/claro/exception/CAException:<init>	(ILjava/lang/String;Ljava/lang/Exception;)V
/*     */     //   530: athrow
/*     */     //   531: astore 13
/*     */     //   533: new 59	com/claro/exception/CAException
/*     */     //   536: dup
/*     */     //   537: iconst_m1
/*     */     //   538: new 493	java/lang/StringBuilder
/*     */     //   541: dup
/*     */     //   542: ldc_w 863
/*     */     //   545: invokespecial 497	java/lang/StringBuilder:<init>	(Ljava/lang/String;)V
/*     */     //   548: aload 13
/*     */     //   550: invokevirtual 512	java/lang/Exception:toString	()Ljava/lang/String;
/*     */     //   553: invokevirtual 501	java/lang/StringBuilder:append	(Ljava/lang/String;)Ljava/lang/StringBuilder;
/*     */     //   556: ldc_w 504
/*     */     //   559: invokevirtual 501	java/lang/StringBuilder:append	(Ljava/lang/String;)Ljava/lang/StringBuilder;
/*     */     //   562: invokevirtual 506	java/lang/StringBuilder:toString	()Ljava/lang/String;
/*     */     //   565: aload 13
/*     */     //   567: invokespecial 507	com/claro/exception/CAException:<init>	(ILjava/lang/String;Ljava/lang/Exception;)V
/*     */     //   570: athrow
/*     */     //   571: astore 14
/*     */     //   573: aload 7
/*     */     //   575: ifnull +18 -> 593
/*     */     //   578: aload 7
/*     */     //   580: invokeinterface 484 1 0
/*     */     //   585: aconst_null
/*     */     //   586: astore 7
/*     */     //   588: goto +5 -> 593
/*     */     //   591: astore 15
/*     */     //   593: aload 6
/*     */     //   595: ifnull +18 -> 613
/*     */     //   598: aload 6
/*     */     //   600: invokeinterface 487 1 0
/*     */     //   605: aconst_null
/*     */     //   606: astore 6
/*     */     //   608: goto +5 -> 613
/*     */     //   611: astore 15
/*     */     //   613: aload 8
/*     */     //   615: ifnull +18 -> 633
/*     */     //   618: aload 8
/*     */     //   620: invokeinterface 488 1 0
/*     */     //   625: aconst_null
/*     */     //   626: astore 8
/*     */     //   628: goto +5 -> 633
/*     */     //   631: astore 15
/*     */     //   633: aload 14
/*     */     //   635: athrow
/*     */     //   636: aload 7
/*     */     //   638: ifnull +18 -> 656
/*     */     //   641: aload 7
/*     */     //   643: invokeinterface 484 1 0
/*     */     //   648: aconst_null
/*     */     //   649: astore 7
/*     */     //   651: goto +5 -> 656
/*     */     //   654: astore 15
/*     */     //   656: aload 6
/*     */     //   658: ifnull +18 -> 676
/*     */     //   661: aload 6
/*     */     //   663: invokeinterface 487 1 0
/*     */     //   668: aconst_null
/*     */     //   669: astore 6
/*     */     //   671: goto +5 -> 676
/*     */     //   674: astore 15
/*     */     //   676: aload 8
/*     */     //   678: ifnull +18 -> 696
/*     */     //   681: aload 8
/*     */     //   683: invokeinterface 488 1 0
/*     */     //   688: aconst_null
/*     */     //   689: astore 8
/*     */     //   691: goto +5 -> 696
/*     */     //   694: astore 15
/*     */     //   696: aload 12
/*     */     //   698: areturn
/*     */     // Line number table:
/*     */     //   Java source line #665	-> byte code offset #0
/*     */     //   Java source line #666	-> byte code offset #3
/*     */     //   Java source line #667	-> byte code offset #6
/*     */     //   Java source line #668	-> byte code offset #9
/*     */     //   Java source line #669	-> byte code offset #18
/*     */     //   Java source line #670	-> byte code offset #21
/*     */     //   Java source line #672	-> byte code offset #24
/*     */     //   Java source line #674	-> byte code offset #33
/*     */     //   Java source line #675	-> byte code offset #42
/*     */     //   Java source line #676	-> byte code offset #51
/*     */     //   Java source line #677	-> byte code offset #73
/*     */     //   Java source line #678	-> byte code offset #82
/*     */     //   Java source line #679	-> byte code offset #91
/*     */     //   Java source line #680	-> byte code offset #100
/*     */     //   Java source line #681	-> byte code offset #109
/*     */     //   Java source line #683	-> byte code offset #118
/*     */     //   Java source line #684	-> byte code offset #122
/*     */     //   Java source line #687	-> byte code offset #131
/*     */     //   Java source line #688	-> byte code offset #142
/*     */     //   Java source line #690	-> byte code offset #156
/*     */     //   Java source line #691	-> byte code offset #166
/*     */     //   Java source line #692	-> byte code offset #176
/*     */     //   Java source line #693	-> byte code offset #180
/*     */     //   Java source line #694	-> byte code offset #189
/*     */     //   Java source line #695	-> byte code offset #194
/*     */     //   Java source line #697	-> byte code offset #214
/*     */     //   Java source line #699	-> byte code offset #223
/*     */     //   Java source line #700	-> byte code offset #227
/*     */     //   Java source line #701	-> byte code offset #236
/*     */     //   Java source line #702	-> byte code offset #241
/*     */     //   Java source line #705	-> byte code offset #261
/*     */     //   Java source line #707	-> byte code offset #270
/*     */     //   Java source line #708	-> byte code offset #273
/*     */     //   Java source line #709	-> byte code offset #282
/*     */     //   Java source line #710	-> byte code offset #297
/*     */     //   Java source line #711	-> byte code offset #312
/*     */     //   Java source line #712	-> byte code offset #327
/*     */     //   Java source line #713	-> byte code offset #341
/*     */     //   Java source line #714	-> byte code offset #359
/*     */     //   Java source line #715	-> byte code offset #374
/*     */     //   Java source line #716	-> byte code offset #389
/*     */     //   Java source line #717	-> byte code offset #404
/*     */     //   Java source line #718	-> byte code offset #419
/*     */     //   Java source line #719	-> byte code offset #434
/*     */     //   Java source line #720	-> byte code offset #452
/*     */     //   Java source line #721	-> byte code offset #470
/*     */     //   Java source line #707	-> byte code offset #478
/*     */     //   Java source line #723	-> byte code offset #491
/*     */     //   Java source line #724	-> byte code offset #493
/*     */     //   Java source line #725	-> byte code offset #531
/*     */     //   Java source line #726	-> byte code offset #533
/*     */     //   Java source line #727	-> byte code offset #571
/*     */     //   Java source line #728	-> byte code offset #573
/*     */     //   Java source line #729	-> byte code offset #593
/*     */     //   Java source line #730	-> byte code offset #613
/*     */     //   Java source line #731	-> byte code offset #633
/*     */     //   Java source line #728	-> byte code offset #636
/*     */     //   Java source line #729	-> byte code offset #656
/*     */     //   Java source line #730	-> byte code offset #676
/*     */     //   Java source line #732	-> byte code offset #696
/*     */     // Local variable table:
/*     */     //   start	length	slot	name	signature
/*     */     //   0	699	0	this	ImpresionDAO
/*     */     //   0	699	1	sFecha	String
/*     */     //   0	699	2	sTipoRed	String
/*     */     //   0	699	3	sFechaFolio	String
/*     */     //   0	699	4	sCuenta	String
/*     */     //   0	699	5	sTelefono	String
/*     */     //   1	669	6	statement	PreparedStatement
/*     */     //   4	646	7	resultSet	ResultSet
/*     */     //   7	683	8	connection	Connection
/*     */     //   16	129	9	query	StringBuffer
/*     */     //   19	183	10	dFecha	java.util.Date
/*     */     //   22	227	11	dFechaFolio	java.util.Date
/*     */     //   31	666	12	impresionDetalleEquipo	java.util.ArrayList<ImpresionTO>
/*     */     //   280	193	13	impresionTO	ImpresionTO
/*     */     //   491	35	13	e	SQLException
/*     */     //   531	35	13	e	Exception
/*     */     //   571	63	14	localObject	Object
/*     */     //   591	1	15	localException1	Exception
/*     */     //   611	1	15	localException2	Exception
/*     */     //   631	1	15	localException3	Exception
/*     */     //   654	1	15	localException4	Exception
/*     */     //   674	1	15	localException5	Exception
/*     */     //   694	1	15	localException6	Exception
/*     */     // Exception table:
/*     */     //   from	to	target	type
/*     */     //   131	488	491	java/sql/SQLException
/*     */     //   131	488	531	java/lang/Exception
/*     */     //   131	571	571	finally
/*     */     //   578	588	591	java/lang/Exception
/*     */     //   598	608	611	java/lang/Exception
/*     */     //   618	628	631	java/lang/Exception
/*     */     //   641	651	654	java/lang/Exception
/*     */     //   661	671	674	java/lang/Exception
/*     */     //   681	691	694	java/lang/Exception
/*     */   }
/*     */   
/*     */   /* Error */
/*     */   public ImpresionTO consultaCertificados(String lFecha, String cuenta, String sec)
/*     */     throws CAException
/*     */   {
/*     */     // Byte code:
/*     */     //   0: aconst_null
/*     */     //   1: astore 4
/*     */     //   3: aconst_null
/*     */     //   4: astore 5
/*     */     //   6: aconst_null
/*     */     //   7: astore 6
/*     */     //   9: new 61	java/lang/StringBuffer
/*     */     //   12: dup
/*     */     //   13: invokespecial 63	java/lang/StringBuffer:<init>	()V
/*     */     //   16: astore 7
/*     */     //   18: new 575	java/util/ArrayList
/*     */     //   21: dup
/*     */     //   22: invokespecial 577	java/util/ArrayList:<init>	()V
/*     */     //   25: astore 8
/*     */     //   27: new 142	com/claro/transfer/ImpresionTO
/*     */     //   30: dup
/*     */     //   31: invokespecial 144	com/claro/transfer/ImpresionTO:<init>	()V
/*     */     //   34: astore 9
/*     */     //   36: aload 7
/*     */     //   38: ldc_w 870
/*     */     //   41: invokevirtual 66	java/lang/StringBuffer:append	(Ljava/lang/String;)Ljava/lang/StringBuffer;
/*     */     //   44: pop
/*     */     //   45: aload 7
/*     */     //   47: ldc_w 872
/*     */     //   50: invokevirtual 66	java/lang/StringBuffer:append	(Ljava/lang/String;)Ljava/lang/StringBuffer;
/*     */     //   53: aload_0
/*     */     //   54: getfield 41	com/claro/dao/ImpresionDAO:schema_database	Ljava/lang/String;
/*     */     //   57: invokevirtual 66	java/lang/StringBuffer:append	(Ljava/lang/String;)Ljava/lang/StringBuffer;
/*     */     //   60: ldc_w 874
/*     */     //   63: invokevirtual 66	java/lang/StringBuffer:append	(Ljava/lang/String;)Ljava/lang/StringBuffer;
/*     */     //   66: pop
/*     */     //   67: aload 7
/*     */     //   69: ldc_w 876
/*     */     //   72: invokevirtual 66	java/lang/StringBuffer:append	(Ljava/lang/String;)Ljava/lang/StringBuffer;
/*     */     //   75: pop
/*     */     //   76: aload 7
/*     */     //   78: ldc_w 878
/*     */     //   81: invokevirtual 66	java/lang/StringBuffer:append	(Ljava/lang/String;)Ljava/lang/StringBuffer;
/*     */     //   84: pop
/*     */     //   85: aload 7
/*     */     //   87: ldc_w 880
/*     */     //   90: invokevirtual 66	java/lang/StringBuffer:append	(Ljava/lang/String;)Ljava/lang/StringBuffer;
/*     */     //   93: pop
/*     */     //   94: aload_1
/*     */     //   95: ifnull +22 -> 117
/*     */     //   98: ldc_w 882
/*     */     //   101: aload_1
/*     */     //   102: invokevirtual 884	java/lang/String:equals	(Ljava/lang/Object;)Z
/*     */     //   105: ifne +12 -> 117
/*     */     //   108: aload 7
/*     */     //   110: ldc_w 887
/*     */     //   113: invokevirtual 66	java/lang/StringBuffer:append	(Ljava/lang/String;)Ljava/lang/StringBuffer;
/*     */     //   116: pop
/*     */     //   117: aload 7
/*     */     //   119: ldc_w 889
/*     */     //   122: invokevirtual 66	java/lang/StringBuffer:append	(Ljava/lang/String;)Ljava/lang/StringBuffer;
/*     */     //   125: pop
/*     */     //   126: invokestatic 29	com/claro/util/ServiceLocator:getInstance	()Lcom/claro/util/ServiceLocator;
/*     */     //   129: getstatic 145	com/claro/util/ServiceLocator:jdbcCirculoAzul	Ljava/lang/String;
/*     */     //   132: invokevirtual 148	com/claro/util/ServiceLocator:getConnection	(Ljava/lang/String;)Ljava/sql/Connection;
/*     */     //   135: astore 6
/*     */     //   137: aload 6
/*     */     //   139: aload 7
/*     */     //   141: invokevirtual 152	java/lang/StringBuffer:toString	()Ljava/lang/String;
/*     */     //   144: invokeinterface 155 2 0
/*     */     //   149: astore 4
/*     */     //   151: aload 4
/*     */     //   153: iconst_1
/*     */     //   154: aload_2
/*     */     //   155: invokeinterface 161 3 0
/*     */     //   160: aload 4
/*     */     //   162: iconst_2
/*     */     //   163: aload_3
/*     */     //   164: invokeinterface 161 3 0
/*     */     //   169: aload_1
/*     */     //   170: ifnull +139 -> 309
/*     */     //   173: ldc_w 882
/*     */     //   176: aload_1
/*     */     //   177: invokevirtual 884	java/lang/String:equals	(Ljava/lang/Object;)Z
/*     */     //   180: ifne +129 -> 309
/*     */     //   183: invokestatic 891	java/util/Calendar:getInstance	()Ljava/util/Calendar;
/*     */     //   186: astore 10
/*     */     //   188: aload_1
/*     */     //   189: iconst_0
/*     */     //   190: aload_1
/*     */     //   191: ldc_w 896
/*     */     //   194: invokevirtual 898	java/lang/String:indexOf	(Ljava/lang/String;)I
/*     */     //   197: invokevirtual 901	java/lang/String:substring	(II)Ljava/lang/String;
/*     */     //   200: invokestatic 905	java/lang/Integer:parseInt	(Ljava/lang/String;)I
/*     */     //   203: istore 11
/*     */     //   205: aload_1
/*     */     //   206: aload_1
/*     */     //   207: ldc_w 896
/*     */     //   210: invokevirtual 898	java/lang/String:indexOf	(Ljava/lang/String;)I
/*     */     //   213: iconst_1
/*     */     //   214: iadd
/*     */     //   215: aload_1
/*     */     //   216: ldc_w 896
/*     */     //   219: invokevirtual 910	java/lang/String:lastIndexOf	(Ljava/lang/String;)I
/*     */     //   222: invokevirtual 901	java/lang/String:substring	(II)Ljava/lang/String;
/*     */     //   225: invokestatic 905	java/lang/Integer:parseInt	(Ljava/lang/String;)I
/*     */     //   228: iconst_1
/*     */     //   229: isub
/*     */     //   230: istore 12
/*     */     //   232: aload_1
/*     */     //   233: aload_1
/*     */     //   234: ldc_w 896
/*     */     //   237: invokevirtual 910	java/lang/String:lastIndexOf	(Ljava/lang/String;)I
/*     */     //   240: iconst_1
/*     */     //   241: iadd
/*     */     //   242: aload_1
/*     */     //   243: invokevirtual 102	java/lang/String:length	()I
/*     */     //   246: invokevirtual 901	java/lang/String:substring	(II)Ljava/lang/String;
/*     */     //   249: invokestatic 905	java/lang/Integer:parseInt	(Ljava/lang/String;)I
/*     */     //   252: istore 13
/*     */     //   254: aload 10
/*     */     //   256: iconst_5
/*     */     //   257: iload 11
/*     */     //   259: invokevirtual 913	java/util/Calendar:set	(II)V
/*     */     //   262: aload 10
/*     */     //   264: iconst_2
/*     */     //   265: iload 12
/*     */     //   267: invokevirtual 913	java/util/Calendar:set	(II)V
/*     */     //   270: aload 10
/*     */     //   272: iconst_1
/*     */     //   273: iload 13
/*     */     //   275: invokevirtual 913	java/util/Calendar:set	(II)V
/*     */     //   278: getstatic 916	java/lang/System:out	Ljava/io/PrintStream;
/*     */     //   281: aload 10
/*     */     //   283: invokevirtual 922	java/util/Calendar:getTime	()Ljava/util/Date;
/*     */     //   286: invokevirtual 925	java/io/PrintStream:println	(Ljava/lang/Object;)V
/*     */     //   289: aload 4
/*     */     //   291: iconst_3
/*     */     //   292: new 610	java/sql/Date
/*     */     //   295: dup
/*     */     //   296: aload 10
/*     */     //   298: invokevirtual 931	java/util/Calendar:getTimeInMillis	()J
/*     */     //   301: invokespecial 617	java/sql/Date:<init>	(J)V
/*     */     //   304: invokeinterface 618 3 0
/*     */     //   309: aload 4
/*     */     //   311: invokeinterface 185 1 0
/*     */     //   316: astore 5
/*     */     //   318: goto +95 -> 413
/*     */     //   321: new 705	com/claro/transfer/AlianzasTO
/*     */     //   324: dup
/*     */     //   325: invokespecial 707	com/claro/transfer/AlianzasTO:<init>	()V
/*     */     //   328: astore 10
/*     */     //   330: aload 10
/*     */     //   332: aload 5
/*     */     //   334: ldc_w 934
/*     */     //   337: invokeinterface 197 2 0
/*     */     //   342: invokevirtual 724	com/claro/transfer/AlianzasTO:setFolio	(Ljava/lang/String;)V
/*     */     //   345: aload 10
/*     */     //   347: aload 5
/*     */     //   349: ldc_w 936
/*     */     //   352: invokeinterface 220 2 0
/*     */     //   357: invokevirtual 709	com/claro/transfer/AlianzasTO:setFechaOperacion	(Ljava/sql/Date;)V
/*     */     //   360: aload 10
/*     */     //   362: aload 5
/*     */     //   364: ldc_w 938
/*     */     //   367: invokeinterface 210 2 0
/*     */     //   372: invokevirtual 717	com/claro/transfer/AlianzasTO:setPtsTransferidos	(I)V
/*     */     //   375: aload 10
/*     */     //   377: aload 5
/*     */     //   379: ldc_w 940
/*     */     //   382: invokeinterface 210 2 0
/*     */     //   387: invokevirtual 727	com/claro/transfer/AlianzasTO:setValorCuponOrig	(I)V
/*     */     //   390: aload 10
/*     */     //   392: aload 5
/*     */     //   394: ldc_w 942
/*     */     //   397: invokeinterface 197 2 0
/*     */     //   402: invokevirtual 723	com/claro/transfer/AlianzasTO:setComentario	(Ljava/lang/String;)V
/*     */     //   405: aload 8
/*     */     //   407: aload 10
/*     */     //   409: invokevirtual 635	java/util/ArrayList:add	(Ljava/lang/Object;)Z
/*     */     //   412: pop
/*     */     //   413: aload 5
/*     */     //   415: invokeinterface 189 1 0
/*     */     //   420: ifne -99 -> 321
/*     */     //   423: aload 9
/*     */     //   425: aload 8
/*     */     //   427: invokevirtual 736	com/claro/transfer/ImpresionTO:setAlianzas	(Ljava/util/ArrayList;)V
/*     */     //   430: goto +148 -> 578
/*     */     //   433: astore 10
/*     */     //   435: new 59	com/claro/exception/CAException
/*     */     //   438: dup
/*     */     //   439: iconst_m1
/*     */     //   440: new 493	java/lang/StringBuilder
/*     */     //   443: dup
/*     */     //   444: ldc_w 944
/*     */     //   447: invokespecial 497	java/lang/StringBuilder:<init>	(Ljava/lang/String;)V
/*     */     //   450: aload 10
/*     */     //   452: invokevirtual 498	java/sql/SQLException:toString	()Ljava/lang/String;
/*     */     //   455: invokevirtual 501	java/lang/StringBuilder:append	(Ljava/lang/String;)Ljava/lang/StringBuilder;
/*     */     //   458: ldc_w 504
/*     */     //   461: invokevirtual 501	java/lang/StringBuilder:append	(Ljava/lang/String;)Ljava/lang/StringBuilder;
/*     */     //   464: invokevirtual 506	java/lang/StringBuilder:toString	()Ljava/lang/String;
/*     */     //   467: aload 10
/*     */     //   469: invokespecial 507	com/claro/exception/CAException:<init>	(ILjava/lang/String;Ljava/lang/Exception;)V
/*     */     //   472: athrow
/*     */     //   473: astore 10
/*     */     //   475: new 59	com/claro/exception/CAException
/*     */     //   478: dup
/*     */     //   479: iconst_m1
/*     */     //   480: new 493	java/lang/StringBuilder
/*     */     //   483: dup
/*     */     //   484: ldc_w 946
/*     */     //   487: invokespecial 497	java/lang/StringBuilder:<init>	(Ljava/lang/String;)V
/*     */     //   490: aload 10
/*     */     //   492: invokevirtual 512	java/lang/Exception:toString	()Ljava/lang/String;
/*     */     //   495: invokevirtual 501	java/lang/StringBuilder:append	(Ljava/lang/String;)Ljava/lang/StringBuilder;
/*     */     //   498: ldc_w 504
/*     */     //   501: invokevirtual 501	java/lang/StringBuilder:append	(Ljava/lang/String;)Ljava/lang/StringBuilder;
/*     */     //   504: invokevirtual 506	java/lang/StringBuilder:toString	()Ljava/lang/String;
/*     */     //   507: aload 10
/*     */     //   509: invokespecial 507	com/claro/exception/CAException:<init>	(ILjava/lang/String;Ljava/lang/Exception;)V
/*     */     //   512: athrow
/*     */     //   513: astore 14
/*     */     //   515: aload 5
/*     */     //   517: ifnull +18 -> 535
/*     */     //   520: aload 5
/*     */     //   522: invokeinterface 484 1 0
/*     */     //   527: aconst_null
/*     */     //   528: astore 5
/*     */     //   530: goto +5 -> 535
/*     */     //   533: astore 15
/*     */     //   535: aload 4
/*     */     //   537: ifnull +18 -> 555
/*     */     //   540: aload 4
/*     */     //   542: invokeinterface 487 1 0
/*     */     //   547: aconst_null
/*     */     //   548: astore 4
/*     */     //   550: goto +5 -> 555
/*     */     //   553: astore 15
/*     */     //   555: aload 6
/*     */     //   557: ifnull +18 -> 575
/*     */     //   560: aload 6
/*     */     //   562: invokeinterface 488 1 0
/*     */     //   567: aconst_null
/*     */     //   568: astore 6
/*     */     //   570: goto +5 -> 575
/*     */     //   573: astore 15
/*     */     //   575: aload 14
/*     */     //   577: athrow
/*     */     //   578: aload 5
/*     */     //   580: ifnull +18 -> 598
/*     */     //   583: aload 5
/*     */     //   585: invokeinterface 484 1 0
/*     */     //   590: aconst_null
/*     */     //   591: astore 5
/*     */     //   593: goto +5 -> 598
/*     */     //   596: astore 15
/*     */     //   598: aload 4
/*     */     //   600: ifnull +18 -> 618
/*     */     //   603: aload 4
/*     */     //   605: invokeinterface 487 1 0
/*     */     //   610: aconst_null
/*     */     //   611: astore 4
/*     */     //   613: goto +5 -> 618
/*     */     //   616: astore 15
/*     */     //   618: aload 6
/*     */     //   620: ifnull +18 -> 638
/*     */     //   623: aload 6
/*     */     //   625: invokeinterface 488 1 0
/*     */     //   630: aconst_null
/*     */     //   631: astore 6
/*     */     //   633: goto +5 -> 638
/*     */     //   636: astore 15
/*     */     //   638: aload 9
/*     */     //   640: areturn
/*     */     // Line number table:
/*     */     //   Java source line #739	-> byte code offset #0
/*     */     //   Java source line #740	-> byte code offset #3
/*     */     //   Java source line #741	-> byte code offset #6
/*     */     //   Java source line #742	-> byte code offset #9
/*     */     //   Java source line #744	-> byte code offset #18
/*     */     //   Java source line #745	-> byte code offset #27
/*     */     //   Java source line #747	-> byte code offset #36
/*     */     //   Java source line #748	-> byte code offset #45
/*     */     //   Java source line #749	-> byte code offset #67
/*     */     //   Java source line #750	-> byte code offset #76
/*     */     //   Java source line #751	-> byte code offset #85
/*     */     //   Java source line #752	-> byte code offset #94
/*     */     //   Java source line #753	-> byte code offset #117
/*     */     //   Java source line #756	-> byte code offset #126
/*     */     //   Java source line #757	-> byte code offset #137
/*     */     //   Java source line #759	-> byte code offset #151
/*     */     //   Java source line #760	-> byte code offset #160
/*     */     //   Java source line #762	-> byte code offset #169
/*     */     //   Java source line #764	-> byte code offset #183
/*     */     //   Java source line #766	-> byte code offset #188
/*     */     //   Java source line #767	-> byte code offset #205
/*     */     //   Java source line #768	-> byte code offset #232
/*     */     //   Java source line #770	-> byte code offset #254
/*     */     //   Java source line #771	-> byte code offset #262
/*     */     //   Java source line #772	-> byte code offset #270
/*     */     //   Java source line #774	-> byte code offset #278
/*     */     //   Java source line #776	-> byte code offset #289
/*     */     //   Java source line #779	-> byte code offset #309
/*     */     //   Java source line #781	-> byte code offset #318
/*     */     //   Java source line #782	-> byte code offset #321
/*     */     //   Java source line #783	-> byte code offset #330
/*     */     //   Java source line #784	-> byte code offset #345
/*     */     //   Java source line #785	-> byte code offset #360
/*     */     //   Java source line #786	-> byte code offset #375
/*     */     //   Java source line #787	-> byte code offset #390
/*     */     //   Java source line #788	-> byte code offset #405
/*     */     //   Java source line #781	-> byte code offset #413
/*     */     //   Java source line #790	-> byte code offset #423
/*     */     //   Java source line #791	-> byte code offset #433
/*     */     //   Java source line #792	-> byte code offset #435
/*     */     //   Java source line #793	-> byte code offset #473
/*     */     //   Java source line #794	-> byte code offset #475
/*     */     //   Java source line #795	-> byte code offset #513
/*     */     //   Java source line #796	-> byte code offset #515
/*     */     //   Java source line #797	-> byte code offset #535
/*     */     //   Java source line #798	-> byte code offset #555
/*     */     //   Java source line #799	-> byte code offset #575
/*     */     //   Java source line #796	-> byte code offset #578
/*     */     //   Java source line #797	-> byte code offset #598
/*     */     //   Java source line #798	-> byte code offset #618
/*     */     //   Java source line #800	-> byte code offset #638
/*     */     // Local variable table:
/*     */     //   start	length	slot	name	signature
/*     */     //   0	641	0	this	ImpresionDAO
/*     */     //   0	641	1	lFecha	String
/*     */     //   0	641	2	cuenta	String
/*     */     //   0	641	3	sec	String
/*     */     //   1	611	4	statement	PreparedStatement
/*     */     //   4	588	5	resultSet	ResultSet
/*     */     //   7	625	6	connection	Connection
/*     */     //   16	124	7	query	StringBuffer
/*     */     //   25	401	8	alianzasArray	java.util.ArrayList<com.claro.transfer.AlianzasTO>
/*     */     //   34	605	9	impresionTO	ImpresionTO
/*     */     //   186	111	10	fechaOperacion	java.util.Calendar
/*     */     //   328	80	10	alianza	com.claro.transfer.AlianzasTO
/*     */     //   433	35	10	e	SQLException
/*     */     //   473	35	10	e	Exception
/*     */     //   203	55	11	dia	int
/*     */     //   230	36	12	mes	int
/*     */     //   252	22	13	anio	int
/*     */     //   513	63	14	localObject	Object
/*     */     //   533	1	15	localException1	Exception
/*     */     //   553	1	15	localException2	Exception
/*     */     //   573	1	15	localException3	Exception
/*     */     //   596	1	15	localException4	Exception
/*     */     //   616	1	15	localException5	Exception
/*     */     //   636	1	15	localException6	Exception
/*     */     // Exception table:
/*     */     //   from	to	target	type
/*     */     //   126	430	433	java/sql/SQLException
/*     */     //   126	430	473	java/lang/Exception
/*     */     //   126	513	513	finally
/*     */     //   520	530	533	java/lang/Exception
/*     */     //   540	550	553	java/lang/Exception
/*     */     //   560	570	573	java/lang/Exception
/*     */     //   583	593	596	java/lang/Exception
/*     */     //   603	613	616	java/lang/Exception
/*     */     //   623	633	636	java/lang/Exception
/*     */   }
/*     */   
/*     */   /* Error */
/*     */   public ImpresionTO obtieneCertificado(String folio, String cuenta, String sec)
/*     */     throws CAException
/*     */   {
/*     */     // Byte code:
/*     */     //   0: aconst_null
/*     */     //   1: astore 4
/*     */     //   3: aconst_null
/*     */     //   4: astore 5
/*     */     //   6: aconst_null
/*     */     //   7: astore 6
/*     */     //   9: new 61	java/lang/StringBuffer
/*     */     //   12: dup
/*     */     //   13: invokespecial 63	java/lang/StringBuffer:<init>	()V
/*     */     //   16: astore 7
/*     */     //   18: new 575	java/util/ArrayList
/*     */     //   21: dup
/*     */     //   22: invokespecial 577	java/util/ArrayList:<init>	()V
/*     */     //   25: astore 8
/*     */     //   27: new 142	com/claro/transfer/ImpresionTO
/*     */     //   30: dup
/*     */     //   31: invokespecial 144	com/claro/transfer/ImpresionTO:<init>	()V
/*     */     //   34: astore 9
/*     */     //   36: aload 7
/*     */     //   38: ldc_w 957
/*     */     //   41: invokevirtual 66	java/lang/StringBuffer:append	(Ljava/lang/String;)Ljava/lang/StringBuffer;
/*     */     //   44: pop
/*     */     //   45: aload 7
/*     */     //   47: ldc_w 959
/*     */     //   50: invokevirtual 66	java/lang/StringBuffer:append	(Ljava/lang/String;)Ljava/lang/StringBuffer;
/*     */     //   53: pop
/*     */     //   54: aload 7
/*     */     //   56: ldc_w 872
/*     */     //   59: invokevirtual 66	java/lang/StringBuffer:append	(Ljava/lang/String;)Ljava/lang/StringBuffer;
/*     */     //   62: aload_0
/*     */     //   63: getfield 41	com/claro/dao/ImpresionDAO:schema_database	Ljava/lang/String;
/*     */     //   66: invokevirtual 66	java/lang/StringBuffer:append	(Ljava/lang/String;)Ljava/lang/StringBuffer;
/*     */     //   69: ldc_w 961
/*     */     //   72: invokevirtual 66	java/lang/StringBuffer:append	(Ljava/lang/String;)Ljava/lang/StringBuffer;
/*     */     //   75: pop
/*     */     //   76: aload 7
/*     */     //   78: aload_0
/*     */     //   79: getfield 41	com/claro/dao/ImpresionDAO:schema_database	Ljava/lang/String;
/*     */     //   82: invokevirtual 66	java/lang/StringBuffer:append	(Ljava/lang/String;)Ljava/lang/StringBuffer;
/*     */     //   85: ldc_w 963
/*     */     //   88: invokevirtual 66	java/lang/StringBuffer:append	(Ljava/lang/String;)Ljava/lang/StringBuffer;
/*     */     //   91: pop
/*     */     //   92: aload 7
/*     */     //   94: ldc_w 965
/*     */     //   97: invokevirtual 66	java/lang/StringBuffer:append	(Ljava/lang/String;)Ljava/lang/StringBuffer;
/*     */     //   100: pop
/*     */     //   101: aload 7
/*     */     //   103: ldc_w 967
/*     */     //   106: invokevirtual 66	java/lang/StringBuffer:append	(Ljava/lang/String;)Ljava/lang/StringBuffer;
/*     */     //   109: pop
/*     */     //   110: aload 7
/*     */     //   112: ldc_w 969
/*     */     //   115: invokevirtual 66	java/lang/StringBuffer:append	(Ljava/lang/String;)Ljava/lang/StringBuffer;
/*     */     //   118: pop
/*     */     //   119: aload 7
/*     */     //   121: ldc_w 971
/*     */     //   124: invokevirtual 66	java/lang/StringBuffer:append	(Ljava/lang/String;)Ljava/lang/StringBuffer;
/*     */     //   127: pop
/*     */     //   128: invokestatic 29	com/claro/util/ServiceLocator:getInstance	()Lcom/claro/util/ServiceLocator;
/*     */     //   131: getstatic 145	com/claro/util/ServiceLocator:jdbcCirculoAzul	Ljava/lang/String;
/*     */     //   134: invokevirtual 148	com/claro/util/ServiceLocator:getConnection	(Ljava/lang/String;)Ljava/sql/Connection;
/*     */     //   137: astore 6
/*     */     //   139: aload 6
/*     */     //   141: aload 7
/*     */     //   143: invokevirtual 152	java/lang/StringBuffer:toString	()Ljava/lang/String;
/*     */     //   146: invokeinterface 155 2 0
/*     */     //   151: astore 4
/*     */     //   153: aload 4
/*     */     //   155: iconst_1
/*     */     //   156: aload_2
/*     */     //   157: invokeinterface 161 3 0
/*     */     //   162: aload 4
/*     */     //   164: iconst_2
/*     */     //   165: aload_3
/*     */     //   166: invokeinterface 161 3 0
/*     */     //   171: aload 4
/*     */     //   173: iconst_3
/*     */     //   174: aload_1
/*     */     //   175: invokeinterface 161 3 0
/*     */     //   180: aload 4
/*     */     //   182: invokeinterface 185 1 0
/*     */     //   187: astore 5
/*     */     //   189: goto +140 -> 329
/*     */     //   192: new 705	com/claro/transfer/AlianzasTO
/*     */     //   195: dup
/*     */     //   196: invokespecial 707	com/claro/transfer/AlianzasTO:<init>	()V
/*     */     //   199: astore 10
/*     */     //   201: aload 10
/*     */     //   203: aload 5
/*     */     //   205: ldc_w 934
/*     */     //   208: invokeinterface 197 2 0
/*     */     //   213: invokevirtual 724	com/claro/transfer/AlianzasTO:setFolio	(Ljava/lang/String;)V
/*     */     //   216: aload 10
/*     */     //   218: aload 5
/*     */     //   220: ldc_w 936
/*     */     //   223: invokeinterface 220 2 0
/*     */     //   228: invokevirtual 709	com/claro/transfer/AlianzasTO:setFechaOperacion	(Ljava/sql/Date;)V
/*     */     //   231: aload 10
/*     */     //   233: aload 5
/*     */     //   235: ldc_w 938
/*     */     //   238: invokeinterface 210 2 0
/*     */     //   243: invokevirtual 717	com/claro/transfer/AlianzasTO:setPtsTransferidos	(I)V
/*     */     //   246: aload 10
/*     */     //   248: aload 5
/*     */     //   250: ldc_w 940
/*     */     //   253: invokeinterface 210 2 0
/*     */     //   258: invokevirtual 727	com/claro/transfer/AlianzasTO:setValorCuponOrig	(I)V
/*     */     //   261: aload 10
/*     */     //   263: aload 5
/*     */     //   265: ldc_w 973
/*     */     //   268: invokeinterface 220 2 0
/*     */     //   273: invokevirtual 975	com/claro/transfer/AlianzasTO:setVigenciaMax	(Ljava/sql/Date;)V
/*     */     //   276: aload 10
/*     */     //   278: aload 5
/*     */     //   280: ldc_w 978
/*     */     //   283: invokeinterface 197 2 0
/*     */     //   288: invokevirtual 980	com/claro/transfer/AlianzasTO:setNombre	(Ljava/lang/String;)V
/*     */     //   291: aload 10
/*     */     //   293: aload 5
/*     */     //   295: ldc_w 983
/*     */     //   298: invokeinterface 197 2 0
/*     */     //   303: invokevirtual 985	com/claro/transfer/AlianzasTO:setAMaterno	(Ljava/lang/String;)V
/*     */     //   306: aload 10
/*     */     //   308: aload 5
/*     */     //   310: ldc_w 988
/*     */     //   313: invokeinterface 197 2 0
/*     */     //   318: invokevirtual 990	com/claro/transfer/AlianzasTO:setAPaterno	(Ljava/lang/String;)V
/*     */     //   321: aload 8
/*     */     //   323: aload 10
/*     */     //   325: invokevirtual 635	java/util/ArrayList:add	(Ljava/lang/Object;)Z
/*     */     //   328: pop
/*     */     //   329: aload 5
/*     */     //   331: invokeinterface 189 1 0
/*     */     //   336: ifne -144 -> 192
/*     */     //   339: aload 9
/*     */     //   341: aload 8
/*     */     //   343: invokevirtual 736	com/claro/transfer/ImpresionTO:setAlianzas	(Ljava/util/ArrayList;)V
/*     */     //   346: goto +148 -> 494
/*     */     //   349: astore 10
/*     */     //   351: new 59	com/claro/exception/CAException
/*     */     //   354: dup
/*     */     //   355: iconst_m1
/*     */     //   356: new 493	java/lang/StringBuilder
/*     */     //   359: dup
/*     */     //   360: ldc_w 993
/*     */     //   363: invokespecial 497	java/lang/StringBuilder:<init>	(Ljava/lang/String;)V
/*     */     //   366: aload 10
/*     */     //   368: invokevirtual 498	java/sql/SQLException:toString	()Ljava/lang/String;
/*     */     //   371: invokevirtual 501	java/lang/StringBuilder:append	(Ljava/lang/String;)Ljava/lang/StringBuilder;
/*     */     //   374: ldc_w 504
/*     */     //   377: invokevirtual 501	java/lang/StringBuilder:append	(Ljava/lang/String;)Ljava/lang/StringBuilder;
/*     */     //   380: invokevirtual 506	java/lang/StringBuilder:toString	()Ljava/lang/String;
/*     */     //   383: aload 10
/*     */     //   385: invokespecial 507	com/claro/exception/CAException:<init>	(ILjava/lang/String;Ljava/lang/Exception;)V
/*     */     //   388: athrow
/*     */     //   389: astore 10
/*     */     //   391: new 59	com/claro/exception/CAException
/*     */     //   394: dup
/*     */     //   395: iconst_m1
/*     */     //   396: new 493	java/lang/StringBuilder
/*     */     //   399: dup
/*     */     //   400: ldc_w 995
/*     */     //   403: invokespecial 497	java/lang/StringBuilder:<init>	(Ljava/lang/String;)V
/*     */     //   406: aload 10
/*     */     //   408: invokevirtual 512	java/lang/Exception:toString	()Ljava/lang/String;
/*     */     //   411: invokevirtual 501	java/lang/StringBuilder:append	(Ljava/lang/String;)Ljava/lang/StringBuilder;
/*     */     //   414: ldc_w 504
/*     */     //   417: invokevirtual 501	java/lang/StringBuilder:append	(Ljava/lang/String;)Ljava/lang/StringBuilder;
/*     */     //   420: invokevirtual 506	java/lang/StringBuilder:toString	()Ljava/lang/String;
/*     */     //   423: aload 10
/*     */     //   425: invokespecial 507	com/claro/exception/CAException:<init>	(ILjava/lang/String;Ljava/lang/Exception;)V
/*     */     //   428: athrow
/*     */     //   429: astore 11
/*     */     //   431: aload 5
/*     */     //   433: ifnull +18 -> 451
/*     */     //   436: aload 5
/*     */     //   438: invokeinterface 484 1 0
/*     */     //   443: aconst_null
/*     */     //   444: astore 5
/*     */     //   446: goto +5 -> 451
/*     */     //   449: astore 12
/*     */     //   451: aload 4
/*     */     //   453: ifnull +18 -> 471
/*     */     //   456: aload 4
/*     */     //   458: invokeinterface 487 1 0
/*     */     //   463: aconst_null
/*     */     //   464: astore 4
/*     */     //   466: goto +5 -> 471
/*     */     //   469: astore 12
/*     */     //   471: aload 6
/*     */     //   473: ifnull +18 -> 491
/*     */     //   476: aload 6
/*     */     //   478: invokeinterface 488 1 0
/*     */     //   483: aconst_null
/*     */     //   484: astore 6
/*     */     //   486: goto +5 -> 491
/*     */     //   489: astore 12
/*     */     //   491: aload 11
/*     */     //   493: athrow
/*     */     //   494: aload 5
/*     */     //   496: ifnull +18 -> 514
/*     */     //   499: aload 5
/*     */     //   501: invokeinterface 484 1 0
/*     */     //   506: aconst_null
/*     */     //   507: astore 5
/*     */     //   509: goto +5 -> 514
/*     */     //   512: astore 12
/*     */     //   514: aload 4
/*     */     //   516: ifnull +18 -> 534
/*     */     //   519: aload 4
/*     */     //   521: invokeinterface 487 1 0
/*     */     //   526: aconst_null
/*     */     //   527: astore 4
/*     */     //   529: goto +5 -> 534
/*     */     //   532: astore 12
/*     */     //   534: aload 6
/*     */     //   536: ifnull +18 -> 554
/*     */     //   539: aload 6
/*     */     //   541: invokeinterface 488 1 0
/*     */     //   546: aconst_null
/*     */     //   547: astore 6
/*     */     //   549: goto +5 -> 554
/*     */     //   552: astore 12
/*     */     //   554: aload 9
/*     */     //   556: areturn
/*     */     // Line number table:
/*     */     //   Java source line #807	-> byte code offset #0
/*     */     //   Java source line #808	-> byte code offset #3
/*     */     //   Java source line #809	-> byte code offset #6
/*     */     //   Java source line #810	-> byte code offset #9
/*     */     //   Java source line #814	-> byte code offset #18
/*     */     //   Java source line #815	-> byte code offset #27
/*     */     //   Java source line #822	-> byte code offset #36
/*     */     //   Java source line #823	-> byte code offset #45
/*     */     //   Java source line #824	-> byte code offset #54
/*     */     //   Java source line #825	-> byte code offset #76
/*     */     //   Java source line #826	-> byte code offset #92
/*     */     //   Java source line #827	-> byte code offset #101
/*     */     //   Java source line #828	-> byte code offset #110
/*     */     //   Java source line #829	-> byte code offset #119
/*     */     //   Java source line #832	-> byte code offset #128
/*     */     //   Java source line #833	-> byte code offset #139
/*     */     //   Java source line #835	-> byte code offset #153
/*     */     //   Java source line #836	-> byte code offset #162
/*     */     //   Java source line #837	-> byte code offset #171
/*     */     //   Java source line #839	-> byte code offset #180
/*     */     //   Java source line #841	-> byte code offset #189
/*     */     //   Java source line #842	-> byte code offset #192
/*     */     //   Java source line #843	-> byte code offset #201
/*     */     //   Java source line #844	-> byte code offset #216
/*     */     //   Java source line #845	-> byte code offset #231
/*     */     //   Java source line #846	-> byte code offset #246
/*     */     //   Java source line #847	-> byte code offset #261
/*     */     //   Java source line #848	-> byte code offset #276
/*     */     //   Java source line #849	-> byte code offset #291
/*     */     //   Java source line #850	-> byte code offset #306
/*     */     //   Java source line #851	-> byte code offset #321
/*     */     //   Java source line #841	-> byte code offset #329
/*     */     //   Java source line #853	-> byte code offset #339
/*     */     //   Java source line #854	-> byte code offset #349
/*     */     //   Java source line #855	-> byte code offset #351
/*     */     //   Java source line #856	-> byte code offset #389
/*     */     //   Java source line #857	-> byte code offset #391
/*     */     //   Java source line #858	-> byte code offset #429
/*     */     //   Java source line #859	-> byte code offset #431
/*     */     //   Java source line #860	-> byte code offset #451
/*     */     //   Java source line #861	-> byte code offset #471
/*     */     //   Java source line #862	-> byte code offset #491
/*     */     //   Java source line #859	-> byte code offset #494
/*     */     //   Java source line #860	-> byte code offset #514
/*     */     //   Java source line #861	-> byte code offset #534
/*     */     //   Java source line #863	-> byte code offset #554
/*     */     // Local variable table:
/*     */     //   start	length	slot	name	signature
/*     */     //   0	557	0	this	ImpresionDAO
/*     */     //   0	557	1	folio	String
/*     */     //   0	557	2	cuenta	String
/*     */     //   0	557	3	sec	String
/*     */     //   1	527	4	statement	PreparedStatement
/*     */     //   4	504	5	resultSet	ResultSet
/*     */     //   7	541	6	connection	Connection
/*     */     //   16	126	7	query	StringBuffer
/*     */     //   25	317	8	alianzasArray	java.util.ArrayList<com.claro.transfer.AlianzasTO>
/*     */     //   34	521	9	impresionTO	ImpresionTO
/*     */     //   199	125	10	alianza	com.claro.transfer.AlianzasTO
/*     */     //   349	35	10	e	SQLException
/*     */     //   389	35	10	e	Exception
/*     */     //   429	63	11	localObject	Object
/*     */     //   449	1	12	localException1	Exception
/*     */     //   469	1	12	localException2	Exception
/*     */     //   489	1	12	localException3	Exception
/*     */     //   512	1	12	localException4	Exception
/*     */     //   532	1	12	localException5	Exception
/*     */     //   552	1	12	localException6	Exception
/*     */     // Exception table:
/*     */     //   from	to	target	type
/*     */     //   128	346	349	java/sql/SQLException
/*     */     //   128	346	389	java/lang/Exception
/*     */     //   128	429	429	finally
/*     */     //   436	446	449	java/lang/Exception
/*     */     //   456	466	469	java/lang/Exception
/*     */     //   476	486	489	java/lang/Exception
/*     */     //   499	509	512	java/lang/Exception
/*     */     //   519	529	532	java/lang/Exception
/*     */     //   539	549	552	java/lang/Exception
/*     */   }
/*     */ }


/* Location:              /opt/trabajo/claro/Guatemala/IS/CO/ClaroClub.ear!/ClaroClubEJB.jar!/com/claro/dao/ImpresionDAO.class
 * Java compiler version: 6 (50.0)
 * JD-Core Version:       0.7.1
 */