/*    */ package com.claro.dao;
/*    */ 
/*    */ import com.claro.util.ServiceLocator;
/*    */ import org.apache.log4j.Logger;
/*    */ 
/*    */ 
/*    */ 
/*    */ 
/*    */ 
/*    */ 
/*    */ 
/*    */ 
/*    */ 
/*    */ 
/*    */ public class LineasRestringidasDAO
/*    */ {
/* 17 */   protected final Logger logger = Logger.getLogger("loggerCirculoAzul");
/* 18 */   protected final Logger error = Logger.getLogger("loggerCirculoAzulError");
/*    */   private String schema_database;
/*    */   
/*    */   public LineasRestringidasDAO() {
/*    */     try {
/* 23 */       this.schema_database = ServiceLocator.getInstance().getVariable(ServiceLocator.schema_database);
/*    */     } catch (Exception e) {
/* 25 */       this.error.error("LineasRestringidasDAO", e);
/*    */     }
/*    */   }
/*    */   
/*    */   /* Error */
/*    */   public boolean isLineaBloqueada(String cuenta, String telefono)
/*    */     throws com.claro.exception.CAException
/*    */   {
/*    */     // Byte code:
/*    */     //   0: iconst_0
/*    */     //   1: istore_3
/*    */     //   2: aconst_null
/*    */     //   3: astore 4
/*    */     //   5: aconst_null
/*    */     //   6: astore 5
/*    */     //   8: aconst_null
/*    */     //   9: astore 6
/*    */     //   11: new 61	java/lang/StringBuilder
/*    */     //   14: dup
/*    */     //   15: invokespecial 63	java/lang/StringBuilder:<init>	()V
/*    */     //   18: astore 7
/*    */     //   20: invokestatic 29	com/claro/util/ServiceLocator:getInstance	()Lcom/claro/util/ServiceLocator;
/*    */     //   23: getstatic 64	com/claro/util/ServiceLocator:jdbcCirculoAzul	Ljava/lang/String;
/*    */     //   26: invokevirtual 67	com/claro/util/ServiceLocator:getConnection	(Ljava/lang/String;)Ljava/sql/Connection;
/*    */     //   29: astore 4
/*    */     //   31: aload_2
/*    */     //   32: ifnull +31 -> 63
/*    */     //   35: aload_2
/*    */     //   36: invokevirtual 71	java/lang/String:trim	()Ljava/lang/String;
/*    */     //   39: ldc 77
/*    */     //   41: invokevirtual 79	java/lang/String:equals	(Ljava/lang/Object;)Z
/*    */     //   44: ifne +19 -> 63
/*    */     //   47: aload_1
/*    */     //   48: ifnull +15 -> 63
/*    */     //   51: aload_1
/*    */     //   52: invokevirtual 71	java/lang/String:trim	()Ljava/lang/String;
/*    */     //   55: ldc 77
/*    */     //   57: invokevirtual 79	java/lang/String:equals	(Ljava/lang/Object;)Z
/*    */     //   60: ifeq +180 -> 240
/*    */     //   63: aload_2
/*    */     //   64: ifnull +15 -> 79
/*    */     //   67: aload_2
/*    */     //   68: invokevirtual 71	java/lang/String:trim	()Ljava/lang/String;
/*    */     //   71: ldc 77
/*    */     //   73: invokevirtual 79	java/lang/String:equals	(Ljava/lang/Object;)Z
/*    */     //   76: ifeq +49 -> 125
/*    */     //   79: aload 7
/*    */     //   81: ldc 83
/*    */     //   83: invokevirtual 85	java/lang/StringBuilder:append	(Ljava/lang/String;)Ljava/lang/StringBuilder;
/*    */     //   86: aload_0
/*    */     //   87: getfield 41	com/claro/dao/LineasRestringidasDAO:schema_database	Ljava/lang/String;
/*    */     //   90: invokevirtual 85	java/lang/StringBuilder:append	(Ljava/lang/String;)Ljava/lang/StringBuilder;
/*    */     //   93: ldc 89
/*    */     //   95: invokevirtual 85	java/lang/StringBuilder:append	(Ljava/lang/String;)Ljava/lang/StringBuilder;
/*    */     //   98: pop
/*    */     //   99: aload 4
/*    */     //   101: aload 7
/*    */     //   103: invokevirtual 91	java/lang/StringBuilder:toString	()Ljava/lang/String;
/*    */     //   106: invokeinterface 94 2 0
/*    */     //   111: astore 5
/*    */     //   113: aload 5
/*    */     //   115: iconst_1
/*    */     //   116: aload_1
/*    */     //   117: invokeinterface 100 3 0
/*    */     //   122: goto +46 -> 168
/*    */     //   125: aload 7
/*    */     //   127: ldc 83
/*    */     //   129: invokevirtual 85	java/lang/StringBuilder:append	(Ljava/lang/String;)Ljava/lang/StringBuilder;
/*    */     //   132: aload_0
/*    */     //   133: getfield 41	com/claro/dao/LineasRestringidasDAO:schema_database	Ljava/lang/String;
/*    */     //   136: invokevirtual 85	java/lang/StringBuilder:append	(Ljava/lang/String;)Ljava/lang/StringBuilder;
/*    */     //   139: ldc 106
/*    */     //   141: invokevirtual 85	java/lang/StringBuilder:append	(Ljava/lang/String;)Ljava/lang/StringBuilder;
/*    */     //   144: pop
/*    */     //   145: aload 4
/*    */     //   147: aload 7
/*    */     //   149: invokevirtual 91	java/lang/StringBuilder:toString	()Ljava/lang/String;
/*    */     //   152: invokeinterface 94 2 0
/*    */     //   157: astore 5
/*    */     //   159: aload 5
/*    */     //   161: iconst_1
/*    */     //   162: aload_2
/*    */     //   163: invokeinterface 100 3 0
/*    */     //   168: aload 5
/*    */     //   170: invokeinterface 108 1 0
/*    */     //   175: astore 6
/*    */     //   177: goto +23 -> 200
/*    */     //   180: aload 6
/*    */     //   182: ldc 112
/*    */     //   184: invokeinterface 114 2 0
/*    */     //   189: astore_1
/*    */     //   190: aload 6
/*    */     //   192: ldc 119
/*    */     //   194: invokeinterface 114 2 0
/*    */     //   199: astore_2
/*    */     //   200: aload 6
/*    */     //   202: invokeinterface 121 1 0
/*    */     //   207: ifne -27 -> 180
/*    */     //   210: aload 5
/*    */     //   212: ifnull +13 -> 225
/*    */     //   215: aload 5
/*    */     //   217: invokeinterface 125 1 0
/*    */     //   222: aconst_null
/*    */     //   223: astore 5
/*    */     //   225: aload 6
/*    */     //   227: ifnull +13 -> 240
/*    */     //   230: aload 6
/*    */     //   232: invokeinterface 128 1 0
/*    */     //   237: aconst_null
/*    */     //   238: astore 6
/*    */     //   240: new 61	java/lang/StringBuilder
/*    */     //   243: dup
/*    */     //   244: invokespecial 63	java/lang/StringBuilder:<init>	()V
/*    */     //   247: astore 7
/*    */     //   249: aload 7
/*    */     //   251: ldc -127
/*    */     //   253: invokevirtual 85	java/lang/StringBuilder:append	(Ljava/lang/String;)Ljava/lang/StringBuilder;
/*    */     //   256: aload_0
/*    */     //   257: getfield 41	com/claro/dao/LineasRestringidasDAO:schema_database	Ljava/lang/String;
/*    */     //   260: invokevirtual 85	java/lang/StringBuilder:append	(Ljava/lang/String;)Ljava/lang/StringBuilder;
/*    */     //   263: ldc -125
/*    */     //   265: invokevirtual 85	java/lang/StringBuilder:append	(Ljava/lang/String;)Ljava/lang/StringBuilder;
/*    */     //   268: pop
/*    */     //   269: aload 4
/*    */     //   271: aload 7
/*    */     //   273: invokevirtual 91	java/lang/StringBuilder:toString	()Ljava/lang/String;
/*    */     //   276: invokeinterface 94 2 0
/*    */     //   281: astore 5
/*    */     //   283: aload 5
/*    */     //   285: iconst_1
/*    */     //   286: aload_1
/*    */     //   287: invokeinterface 100 3 0
/*    */     //   292: aload 5
/*    */     //   294: iconst_2
/*    */     //   295: aload_2
/*    */     //   296: invokeinterface 100 3 0
/*    */     //   301: aload 5
/*    */     //   303: invokeinterface 108 1 0
/*    */     //   308: astore 6
/*    */     //   310: goto +22 -> 332
/*    */     //   313: aload 6
/*    */     //   315: ldc -123
/*    */     //   317: invokeinterface 135 2 0
/*    */     //   322: istore 8
/*    */     //   324: iload 8
/*    */     //   326: iconst_1
/*    */     //   327: if_icmpne +5 -> 332
/*    */     //   330: iconst_1
/*    */     //   331: istore_3
/*    */     //   332: aload 6
/*    */     //   334: invokeinterface 121 1 0
/*    */     //   339: ifne -26 -> 313
/*    */     //   342: goto +106 -> 448
/*    */     //   345: astore 8
/*    */     //   347: new 59	com/claro/exception/CAException
/*    */     //   350: dup
/*    */     //   351: iconst_m1
/*    */     //   352: new 61	java/lang/StringBuilder
/*    */     //   355: dup
/*    */     //   356: ldc -117
/*    */     //   358: invokespecial 141	java/lang/StringBuilder:<init>	(Ljava/lang/String;)V
/*    */     //   361: aload 8
/*    */     //   363: invokevirtual 144	java/lang/Exception:toString	()Ljava/lang/String;
/*    */     //   366: invokevirtual 85	java/lang/StringBuilder:append	(Ljava/lang/String;)Ljava/lang/StringBuilder;
/*    */     //   369: ldc -111
/*    */     //   371: invokevirtual 85	java/lang/StringBuilder:append	(Ljava/lang/String;)Ljava/lang/StringBuilder;
/*    */     //   374: invokevirtual 91	java/lang/StringBuilder:toString	()Ljava/lang/String;
/*    */     //   377: aload 8
/*    */     //   379: invokespecial 147	com/claro/exception/CAException:<init>	(ILjava/lang/String;Ljava/lang/Exception;)V
/*    */     //   382: athrow
/*    */     //   383: astore 9
/*    */     //   385: aload 5
/*    */     //   387: ifnull +18 -> 405
/*    */     //   390: aload 5
/*    */     //   392: invokeinterface 125 1 0
/*    */     //   397: aconst_null
/*    */     //   398: astore 5
/*    */     //   400: goto +5 -> 405
/*    */     //   403: astore 10
/*    */     //   405: aload 6
/*    */     //   407: ifnull +18 -> 425
/*    */     //   410: aload 6
/*    */     //   412: invokeinterface 128 1 0
/*    */     //   417: aconst_null
/*    */     //   418: astore 5
/*    */     //   420: goto +5 -> 425
/*    */     //   423: astore 10
/*    */     //   425: aload 4
/*    */     //   427: ifnull +18 -> 445
/*    */     //   430: aload 4
/*    */     //   432: invokeinterface 150 1 0
/*    */     //   437: aconst_null
/*    */     //   438: astore 5
/*    */     //   440: goto +5 -> 445
/*    */     //   443: astore 10
/*    */     //   445: aload 9
/*    */     //   447: athrow
/*    */     //   448: aload 5
/*    */     //   450: ifnull +18 -> 468
/*    */     //   453: aload 5
/*    */     //   455: invokeinterface 125 1 0
/*    */     //   460: aconst_null
/*    */     //   461: astore 5
/*    */     //   463: goto +5 -> 468
/*    */     //   466: astore 10
/*    */     //   468: aload 6
/*    */     //   470: ifnull +18 -> 488
/*    */     //   473: aload 6
/*    */     //   475: invokeinterface 128 1 0
/*    */     //   480: aconst_null
/*    */     //   481: astore 5
/*    */     //   483: goto +5 -> 488
/*    */     //   486: astore 10
/*    */     //   488: aload 4
/*    */     //   490: ifnull +18 -> 508
/*    */     //   493: aload 4
/*    */     //   495: invokeinterface 150 1 0
/*    */     //   500: aconst_null
/*    */     //   501: astore 5
/*    */     //   503: goto +5 -> 508
/*    */     //   506: astore 10
/*    */     //   508: iload_3
/*    */     //   509: ireturn
/*    */     // Line number table:
/*    */     //   Java source line #32	-> byte code offset #0
/*    */     //   Java source line #33	-> byte code offset #2
/*    */     //   Java source line #35	-> byte code offset #5
/*    */     //   Java source line #36	-> byte code offset #8
/*    */     //   Java source line #38	-> byte code offset #11
/*    */     //   Java source line #42	-> byte code offset #20
/*    */     //   Java source line #44	-> byte code offset #31
/*    */     //   Java source line #45	-> byte code offset #63
/*    */     //   Java source line #46	-> byte code offset #79
/*    */     //   Java source line #47	-> byte code offset #99
/*    */     //   Java source line #48	-> byte code offset #113
/*    */     //   Java source line #51	-> byte code offset #125
/*    */     //   Java source line #52	-> byte code offset #145
/*    */     //   Java source line #53	-> byte code offset #159
/*    */     //   Java source line #55	-> byte code offset #168
/*    */     //   Java source line #57	-> byte code offset #177
/*    */     //   Java source line #58	-> byte code offset #180
/*    */     //   Java source line #59	-> byte code offset #190
/*    */     //   Java source line #57	-> byte code offset #200
/*    */     //   Java source line #61	-> byte code offset #210
/*    */     //   Java source line #62	-> byte code offset #215
/*    */     //   Java source line #63	-> byte code offset #222
/*    */     //   Java source line #65	-> byte code offset #225
/*    */     //   Java source line #66	-> byte code offset #230
/*    */     //   Java source line #67	-> byte code offset #237
/*    */     //   Java source line #71	-> byte code offset #240
/*    */     //   Java source line #73	-> byte code offset #249
/*    */     //   Java source line #75	-> byte code offset #269
/*    */     //   Java source line #76	-> byte code offset #283
/*    */     //   Java source line #77	-> byte code offset #292
/*    */     //   Java source line #79	-> byte code offset #301
/*    */     //   Java source line #80	-> byte code offset #310
/*    */     //   Java source line #81	-> byte code offset #313
/*    */     //   Java source line #82	-> byte code offset #324
/*    */     //   Java source line #83	-> byte code offset #330
/*    */     //   Java source line #80	-> byte code offset #332
/*    */     //   Java source line #87	-> byte code offset #345
/*    */     //   Java source line #88	-> byte code offset #347
/*    */     //   Java source line #89	-> byte code offset #383
/*    */     //   Java source line #90	-> byte code offset #385
/*    */     //   Java source line #91	-> byte code offset #405
/*    */     //   Java source line #92	-> byte code offset #425
/*    */     //   Java source line #93	-> byte code offset #445
/*    */     //   Java source line #90	-> byte code offset #448
/*    */     //   Java source line #91	-> byte code offset #468
/*    */     //   Java source line #92	-> byte code offset #488
/*    */     //   Java source line #95	-> byte code offset #508
/*    */     // Local variable table:
/*    */     //   start	length	slot	name	signature
/*    */     //   0	510	0	this	LineasRestringidasDAO
/*    */     //   0	510	1	cuenta	String
/*    */     //   0	510	2	telefono	String
/*    */     //   1	508	3	isLineaBloqueada	boolean
/*    */     //   3	491	4	conn	java.sql.Connection
/*    */     //   6	496	5	stmt	java.sql.PreparedStatement
/*    */     //   9	465	6	resultSet	java.sql.ResultSet
/*    */     //   18	254	7	query	StringBuilder
/*    */     //   322	3	8	lineaBloqueada	int
/*    */     //   345	33	8	e	Exception
/*    */     //   383	63	9	localObject	Object
/*    */     //   403	1	10	localException1	Exception
/*    */     //   423	1	10	localException2	Exception
/*    */     //   443	1	10	localException3	Exception
/*    */     //   466	1	10	localException4	Exception
/*    */     //   486	1	10	localException5	Exception
/*    */     //   506	1	10	localException6	Exception
/*    */     // Exception table:
/*    */     //   from	to	target	type
/*    */     //   20	342	345	java/lang/Exception
/*    */     //   20	383	383	finally
/*    */     //   390	400	403	java/lang/Exception
/*    */     //   410	420	423	java/lang/Exception
/*    */     //   430	440	443	java/lang/Exception
/*    */     //   453	463	466	java/lang/Exception
/*    */     //   473	483	486	java/lang/Exception
/*    */     //   493	503	506	java/lang/Exception
/*    */   }
/*    */   
/*    */   /* Error */
/*    */   public void cargaLineasRestringidas(java.util.List<com.claro.transfer.TelefonoTO> lineas)
/*    */     throws com.claro.exception.CAException
/*    */   {
/*    */     // Byte code:
/*    */     //   0: aconst_null
/*    */     //   1: astore_2
/*    */     //   2: aconst_null
/*    */     //   3: astore_3
/*    */     //   4: aconst_null
/*    */     //   5: astore 4
/*    */     //   7: invokestatic 29	com/claro/util/ServiceLocator:getInstance	()Lcom/claro/util/ServiceLocator;
/*    */     //   10: getstatic 64	com/claro/util/ServiceLocator:jdbcCirculoAzul	Ljava/lang/String;
/*    */     //   13: invokevirtual 67	com/claro/util/ServiceLocator:getConnection	(Ljava/lang/String;)Ljava/sql/Connection;
/*    */     //   16: astore_2
/*    */     //   17: new 61	java/lang/StringBuilder
/*    */     //   20: dup
/*    */     //   21: invokespecial 63	java/lang/StringBuilder:<init>	()V
/*    */     //   24: astore 5
/*    */     //   26: aload 5
/*    */     //   28: ldc 83
/*    */     //   30: invokevirtual 85	java/lang/StringBuilder:append	(Ljava/lang/String;)Ljava/lang/StringBuilder;
/*    */     //   33: aload_0
/*    */     //   34: getfield 41	com/claro/dao/LineasRestringidasDAO:schema_database	Ljava/lang/String;
/*    */     //   37: invokevirtual 85	java/lang/StringBuilder:append	(Ljava/lang/String;)Ljava/lang/StringBuilder;
/*    */     //   40: ldc -86
/*    */     //   42: invokevirtual 85	java/lang/StringBuilder:append	(Ljava/lang/String;)Ljava/lang/StringBuilder;
/*    */     //   45: pop
/*    */     //   46: aload 5
/*    */     //   48: ldc -84
/*    */     //   50: invokevirtual 85	java/lang/StringBuilder:append	(Ljava/lang/String;)Ljava/lang/StringBuilder;
/*    */     //   53: pop
/*    */     //   54: new 61	java/lang/StringBuilder
/*    */     //   57: dup
/*    */     //   58: invokespecial 63	java/lang/StringBuilder:<init>	()V
/*    */     //   61: astore 6
/*    */     //   63: aload 6
/*    */     //   65: ldc -82
/*    */     //   67: invokevirtual 85	java/lang/StringBuilder:append	(Ljava/lang/String;)Ljava/lang/StringBuilder;
/*    */     //   70: aload_0
/*    */     //   71: getfield 41	com/claro/dao/LineasRestringidasDAO:schema_database	Ljava/lang/String;
/*    */     //   74: invokevirtual 85	java/lang/StringBuilder:append	(Ljava/lang/String;)Ljava/lang/StringBuilder;
/*    */     //   77: ldc -86
/*    */     //   79: invokevirtual 85	java/lang/StringBuilder:append	(Ljava/lang/String;)Ljava/lang/StringBuilder;
/*    */     //   82: pop
/*    */     //   83: aload 6
/*    */     //   85: ldc -80
/*    */     //   87: invokevirtual 85	java/lang/StringBuilder:append	(Ljava/lang/String;)Ljava/lang/StringBuilder;
/*    */     //   90: pop
/*    */     //   91: aload 6
/*    */     //   93: ldc -78
/*    */     //   95: invokevirtual 85	java/lang/StringBuilder:append	(Ljava/lang/String;)Ljava/lang/StringBuilder;
/*    */     //   98: pop
/*    */     //   99: new 61	java/lang/StringBuilder
/*    */     //   102: dup
/*    */     //   103: invokespecial 63	java/lang/StringBuilder:<init>	()V
/*    */     //   106: astore 7
/*    */     //   108: aload 7
/*    */     //   110: ldc -76
/*    */     //   112: invokevirtual 85	java/lang/StringBuilder:append	(Ljava/lang/String;)Ljava/lang/StringBuilder;
/*    */     //   115: aload_0
/*    */     //   116: getfield 41	com/claro/dao/LineasRestringidasDAO:schema_database	Ljava/lang/String;
/*    */     //   119: invokevirtual 85	java/lang/StringBuilder:append	(Ljava/lang/String;)Ljava/lang/StringBuilder;
/*    */     //   122: ldc -86
/*    */     //   124: invokevirtual 85	java/lang/StringBuilder:append	(Ljava/lang/String;)Ljava/lang/StringBuilder;
/*    */     //   127: pop
/*    */     //   128: aload 7
/*    */     //   130: ldc -74
/*    */     //   132: invokevirtual 85	java/lang/StringBuilder:append	(Ljava/lang/String;)Ljava/lang/StringBuilder;
/*    */     //   135: pop
/*    */     //   136: new 61	java/lang/StringBuilder
/*    */     //   139: dup
/*    */     //   140: invokespecial 63	java/lang/StringBuilder:<init>	()V
/*    */     //   143: astore 8
/*    */     //   145: aload 8
/*    */     //   147: ldc -76
/*    */     //   149: invokevirtual 85	java/lang/StringBuilder:append	(Ljava/lang/String;)Ljava/lang/StringBuilder;
/*    */     //   152: aload_0
/*    */     //   153: getfield 41	com/claro/dao/LineasRestringidasDAO:schema_database	Ljava/lang/String;
/*    */     //   156: invokevirtual 85	java/lang/StringBuilder:append	(Ljava/lang/String;)Ljava/lang/StringBuilder;
/*    */     //   159: ldc -72
/*    */     //   161: invokevirtual 85	java/lang/StringBuilder:append	(Ljava/lang/String;)Ljava/lang/StringBuilder;
/*    */     //   164: pop
/*    */     //   165: aload 8
/*    */     //   167: ldc -70
/*    */     //   169: invokevirtual 85	java/lang/StringBuilder:append	(Ljava/lang/String;)Ljava/lang/StringBuilder;
/*    */     //   172: pop
/*    */     //   173: new 61	java/lang/StringBuilder
/*    */     //   176: dup
/*    */     //   177: invokespecial 63	java/lang/StringBuilder:<init>	()V
/*    */     //   180: astore 9
/*    */     //   182: aload 9
/*    */     //   184: ldc -68
/*    */     //   186: invokevirtual 85	java/lang/StringBuilder:append	(Ljava/lang/String;)Ljava/lang/StringBuilder;
/*    */     //   189: aload_0
/*    */     //   190: getfield 41	com/claro/dao/LineasRestringidasDAO:schema_database	Ljava/lang/String;
/*    */     //   193: invokevirtual 85	java/lang/StringBuilder:append	(Ljava/lang/String;)Ljava/lang/StringBuilder;
/*    */     //   196: ldc -66
/*    */     //   198: invokevirtual 85	java/lang/StringBuilder:append	(Ljava/lang/String;)Ljava/lang/StringBuilder;
/*    */     //   201: pop
/*    */     //   202: aload_1
/*    */     //   203: invokeinterface 192 1 0
/*    */     //   208: astore 10
/*    */     //   210: goto +371 -> 581
/*    */     //   213: aload 10
/*    */     //   215: invokeinterface 198 1 0
/*    */     //   220: checkcast 203	com/claro/transfer/TelefonoTO
/*    */     //   223: astore 11
/*    */     //   225: aload_2
/*    */     //   226: aload 5
/*    */     //   228: invokevirtual 91	java/lang/StringBuilder:toString	()Ljava/lang/String;
/*    */     //   231: invokeinterface 94 2 0
/*    */     //   236: astore 4
/*    */     //   238: aload 4
/*    */     //   240: iconst_1
/*    */     //   241: aload 11
/*    */     //   243: invokevirtual 205	com/claro/transfer/TelefonoTO:getCuenta	()Ljava/lang/String;
/*    */     //   246: invokeinterface 100 3 0
/*    */     //   251: aload 4
/*    */     //   253: iconst_2
/*    */     //   254: aload 11
/*    */     //   256: invokevirtual 208	com/claro/transfer/TelefonoTO:getTelefono	()Ljava/lang/String;
/*    */     //   259: invokeinterface 100 3 0
/*    */     //   264: aload 4
/*    */     //   266: invokeinterface 108 1 0
/*    */     //   271: astore_3
/*    */     //   272: iconst_0
/*    */     //   273: istore 12
/*    */     //   275: goto +6 -> 281
/*    */     //   278: iconst_1
/*    */     //   279: istore 12
/*    */     //   281: aload_3
/*    */     //   282: invokeinterface 121 1 0
/*    */     //   287: ifne -9 -> 278
/*    */     //   290: aload_3
/*    */     //   291: ifnull +11 -> 302
/*    */     //   294: aload_3
/*    */     //   295: invokeinterface 128 1 0
/*    */     //   300: aconst_null
/*    */     //   301: astore_3
/*    */     //   302: aload 4
/*    */     //   304: ifnull +13 -> 317
/*    */     //   307: aload 4
/*    */     //   309: invokeinterface 125 1 0
/*    */     //   314: aconst_null
/*    */     //   315: astore 4
/*    */     //   317: iload 12
/*    */     //   319: ifeq +53 -> 372
/*    */     //   322: aload_2
/*    */     //   323: aload 6
/*    */     //   325: invokevirtual 91	java/lang/StringBuilder:toString	()Ljava/lang/String;
/*    */     //   328: invokeinterface 94 2 0
/*    */     //   333: astore 4
/*    */     //   335: aload 4
/*    */     //   337: iconst_1
/*    */     //   338: aload 11
/*    */     //   340: invokevirtual 205	com/claro/transfer/TelefonoTO:getCuenta	()Ljava/lang/String;
/*    */     //   343: invokeinterface 100 3 0
/*    */     //   348: aload 4
/*    */     //   350: iconst_2
/*    */     //   351: aload 11
/*    */     //   353: invokevirtual 208	com/claro/transfer/TelefonoTO:getTelefono	()Ljava/lang/String;
/*    */     //   356: invokeinterface 100 3 0
/*    */     //   361: aload 4
/*    */     //   363: invokeinterface 211 1 0
/*    */     //   368: pop
/*    */     //   369: goto +212 -> 581
/*    */     //   372: iconst_0
/*    */     //   373: istore 13
/*    */     //   375: aload_2
/*    */     //   376: aload 9
/*    */     //   378: invokevirtual 91	java/lang/StringBuilder:toString	()Ljava/lang/String;
/*    */     //   381: invokeinterface 94 2 0
/*    */     //   386: astore 4
/*    */     //   388: aload 4
/*    */     //   390: iconst_1
/*    */     //   391: aload 11
/*    */     //   393: invokevirtual 205	com/claro/transfer/TelefonoTO:getCuenta	()Ljava/lang/String;
/*    */     //   396: invokeinterface 100 3 0
/*    */     //   401: aload 4
/*    */     //   403: invokeinterface 108 1 0
/*    */     //   408: astore_3
/*    */     //   409: aload_3
/*    */     //   410: invokeinterface 121 1 0
/*    */     //   415: ifeq +6 -> 421
/*    */     //   418: iconst_1
/*    */     //   419: istore 13
/*    */     //   421: aload_3
/*    */     //   422: ifnull +11 -> 433
/*    */     //   425: aload_3
/*    */     //   426: invokeinterface 128 1 0
/*    */     //   431: aconst_null
/*    */     //   432: astore_3
/*    */     //   433: aload 4
/*    */     //   435: ifnull +13 -> 448
/*    */     //   438: aload 4
/*    */     //   440: invokeinterface 125 1 0
/*    */     //   445: aconst_null
/*    */     //   446: astore 4
/*    */     //   448: iload 12
/*    */     //   450: ifne +71 -> 521
/*    */     //   453: aload_2
/*    */     //   454: aload 7
/*    */     //   456: invokevirtual 91	java/lang/StringBuilder:toString	()Ljava/lang/String;
/*    */     //   459: invokeinterface 94 2 0
/*    */     //   464: astore 4
/*    */     //   466: aload 4
/*    */     //   468: iconst_1
/*    */     //   469: aload 11
/*    */     //   471: invokevirtual 205	com/claro/transfer/TelefonoTO:getCuenta	()Ljava/lang/String;
/*    */     //   474: invokevirtual 71	java/lang/String:trim	()Ljava/lang/String;
/*    */     //   477: invokeinterface 100 3 0
/*    */     //   482: aload 4
/*    */     //   484: iconst_2
/*    */     //   485: aload 11
/*    */     //   487: invokevirtual 208	com/claro/transfer/TelefonoTO:getTelefono	()Ljava/lang/String;
/*    */     //   490: invokevirtual 71	java/lang/String:trim	()Ljava/lang/String;
/*    */     //   493: invokeinterface 100 3 0
/*    */     //   498: aload 4
/*    */     //   500: invokeinterface 211 1 0
/*    */     //   505: pop
/*    */     //   506: aload 4
/*    */     //   508: ifnull +13 -> 521
/*    */     //   511: aload 4
/*    */     //   513: invokeinterface 125 1 0
/*    */     //   518: aconst_null
/*    */     //   519: astore 4
/*    */     //   521: iload 13
/*    */     //   523: ifne +58 -> 581
/*    */     //   526: aload_2
/*    */     //   527: aload 8
/*    */     //   529: invokevirtual 91	java/lang/StringBuilder:toString	()Ljava/lang/String;
/*    */     //   532: invokevirtual 71	java/lang/String:trim	()Ljava/lang/String;
/*    */     //   535: invokeinterface 94 2 0
/*    */     //   540: astore 4
/*    */     //   542: aload 4
/*    */     //   544: iconst_1
/*    */     //   545: aload 11
/*    */     //   547: invokevirtual 205	com/claro/transfer/TelefonoTO:getCuenta	()Ljava/lang/String;
/*    */     //   550: invokevirtual 71	java/lang/String:trim	()Ljava/lang/String;
/*    */     //   553: invokeinterface 100 3 0
/*    */     //   558: aload 4
/*    */     //   560: invokeinterface 211 1 0
/*    */     //   565: pop
/*    */     //   566: aload 4
/*    */     //   568: ifnull +13 -> 581
/*    */     //   571: aload 4
/*    */     //   573: invokeinterface 125 1 0
/*    */     //   578: aconst_null
/*    */     //   579: astore 4
/*    */     //   581: aload 10
/*    */     //   583: invokeinterface 215 1 0
/*    */     //   588: ifne -375 -> 213
/*    */     //   591: goto +102 -> 693
/*    */     //   594: astore 5
/*    */     //   596: new 59	com/claro/exception/CAException
/*    */     //   599: dup
/*    */     //   600: iconst_m1
/*    */     //   601: new 61	java/lang/StringBuilder
/*    */     //   604: dup
/*    */     //   605: ldc -38
/*    */     //   607: invokespecial 141	java/lang/StringBuilder:<init>	(Ljava/lang/String;)V
/*    */     //   610: aload 5
/*    */     //   612: invokevirtual 144	java/lang/Exception:toString	()Ljava/lang/String;
/*    */     //   615: invokevirtual 85	java/lang/StringBuilder:append	(Ljava/lang/String;)Ljava/lang/StringBuilder;
/*    */     //   618: ldc -111
/*    */     //   620: invokevirtual 85	java/lang/StringBuilder:append	(Ljava/lang/String;)Ljava/lang/StringBuilder;
/*    */     //   623: invokevirtual 91	java/lang/StringBuilder:toString	()Ljava/lang/String;
/*    */     //   626: aload 5
/*    */     //   628: invokespecial 147	com/claro/exception/CAException:<init>	(ILjava/lang/String;Ljava/lang/Exception;)V
/*    */     //   631: athrow
/*    */     //   632: astore 14
/*    */     //   634: aload 4
/*    */     //   636: ifnull +18 -> 654
/*    */     //   639: aload 4
/*    */     //   641: invokeinterface 125 1 0
/*    */     //   646: aconst_null
/*    */     //   647: astore 4
/*    */     //   649: goto +5 -> 654
/*    */     //   652: astore 15
/*    */     //   654: aload_3
/*    */     //   655: ifnull +17 -> 672
/*    */     //   658: aload_3
/*    */     //   659: invokeinterface 128 1 0
/*    */     //   664: aconst_null
/*    */     //   665: astore 4
/*    */     //   667: goto +5 -> 672
/*    */     //   670: astore 15
/*    */     //   672: aload_2
/*    */     //   673: ifnull +17 -> 690
/*    */     //   676: aload_2
/*    */     //   677: invokeinterface 150 1 0
/*    */     //   682: aconst_null
/*    */     //   683: astore 4
/*    */     //   685: goto +5 -> 690
/*    */     //   688: astore 15
/*    */     //   690: aload 14
/*    */     //   692: athrow
/*    */     //   693: aload 4
/*    */     //   695: ifnull +18 -> 713
/*    */     //   698: aload 4
/*    */     //   700: invokeinterface 125 1 0
/*    */     //   705: aconst_null
/*    */     //   706: astore 4
/*    */     //   708: goto +5 -> 713
/*    */     //   711: astore 15
/*    */     //   713: aload_3
/*    */     //   714: ifnull +17 -> 731
/*    */     //   717: aload_3
/*    */     //   718: invokeinterface 128 1 0
/*    */     //   723: aconst_null
/*    */     //   724: astore 4
/*    */     //   726: goto +5 -> 731
/*    */     //   729: astore 15
/*    */     //   731: aload_2
/*    */     //   732: ifnull +17 -> 749
/*    */     //   735: aload_2
/*    */     //   736: invokeinterface 150 1 0
/*    */     //   741: aconst_null
/*    */     //   742: astore 4
/*    */     //   744: goto +5 -> 749
/*    */     //   747: astore 15
/*    */     //   749: return
/*    */     // Line number table:
/*    */     //   Java source line #100	-> byte code offset #0
/*    */     //   Java source line #101	-> byte code offset #2
/*    */     //   Java source line #102	-> byte code offset #4
/*    */     //   Java source line #105	-> byte code offset #7
/*    */     //   Java source line #107	-> byte code offset #17
/*    */     //   Java source line #108	-> byte code offset #26
/*    */     //   Java source line #109	-> byte code offset #46
/*    */     //   Java source line #111	-> byte code offset #54
/*    */     //   Java source line #112	-> byte code offset #63
/*    */     //   Java source line #113	-> byte code offset #83
/*    */     //   Java source line #114	-> byte code offset #91
/*    */     //   Java source line #116	-> byte code offset #99
/*    */     //   Java source line #117	-> byte code offset #108
/*    */     //   Java source line #118	-> byte code offset #128
/*    */     //   Java source line #120	-> byte code offset #136
/*    */     //   Java source line #121	-> byte code offset #145
/*    */     //   Java source line #122	-> byte code offset #165
/*    */     //   Java source line #124	-> byte code offset #173
/*    */     //   Java source line #125	-> byte code offset #182
/*    */     //   Java source line #127	-> byte code offset #202
/*    */     //   Java source line #129	-> byte code offset #210
/*    */     //   Java source line #130	-> byte code offset #213
/*    */     //   Java source line #133	-> byte code offset #225
/*    */     //   Java source line #134	-> byte code offset #238
/*    */     //   Java source line #135	-> byte code offset #251
/*    */     //   Java source line #137	-> byte code offset #264
/*    */     //   Java source line #138	-> byte code offset #272
/*    */     //   Java source line #139	-> byte code offset #275
/*    */     //   Java source line #140	-> byte code offset #278
/*    */     //   Java source line #139	-> byte code offset #281
/*    */     //   Java source line #142	-> byte code offset #290
/*    */     //   Java source line #143	-> byte code offset #294
/*    */     //   Java source line #144	-> byte code offset #300
/*    */     //   Java source line #146	-> byte code offset #302
/*    */     //   Java source line #147	-> byte code offset #307
/*    */     //   Java source line #148	-> byte code offset #314
/*    */     //   Java source line #152	-> byte code offset #317
/*    */     //   Java source line #153	-> byte code offset #322
/*    */     //   Java source line #154	-> byte code offset #335
/*    */     //   Java source line #155	-> byte code offset #348
/*    */     //   Java source line #156	-> byte code offset #361
/*    */     //   Java source line #160	-> byte code offset #372
/*    */     //   Java source line #162	-> byte code offset #375
/*    */     //   Java source line #163	-> byte code offset #388
/*    */     //   Java source line #164	-> byte code offset #401
/*    */     //   Java source line #166	-> byte code offset #409
/*    */     //   Java source line #167	-> byte code offset #418
/*    */     //   Java source line #171	-> byte code offset #421
/*    */     //   Java source line #172	-> byte code offset #425
/*    */     //   Java source line #173	-> byte code offset #431
/*    */     //   Java source line #175	-> byte code offset #433
/*    */     //   Java source line #176	-> byte code offset #438
/*    */     //   Java source line #177	-> byte code offset #445
/*    */     //   Java source line #180	-> byte code offset #448
/*    */     //   Java source line #182	-> byte code offset #453
/*    */     //   Java source line #183	-> byte code offset #466
/*    */     //   Java source line #184	-> byte code offset #482
/*    */     //   Java source line #185	-> byte code offset #498
/*    */     //   Java source line #187	-> byte code offset #506
/*    */     //   Java source line #188	-> byte code offset #511
/*    */     //   Java source line #189	-> byte code offset #518
/*    */     //   Java source line #192	-> byte code offset #521
/*    */     //   Java source line #194	-> byte code offset #526
/*    */     //   Java source line #195	-> byte code offset #542
/*    */     //   Java source line #196	-> byte code offset #558
/*    */     //   Java source line #198	-> byte code offset #566
/*    */     //   Java source line #199	-> byte code offset #571
/*    */     //   Java source line #200	-> byte code offset #578
/*    */     //   Java source line #129	-> byte code offset #581
/*    */     //   Java source line #206	-> byte code offset #594
/*    */     //   Java source line #207	-> byte code offset #596
/*    */     //   Java source line #208	-> byte code offset #632
/*    */     //   Java source line #209	-> byte code offset #634
/*    */     //   Java source line #210	-> byte code offset #654
/*    */     //   Java source line #211	-> byte code offset #672
/*    */     //   Java source line #212	-> byte code offset #690
/*    */     //   Java source line #209	-> byte code offset #693
/*    */     //   Java source line #210	-> byte code offset #713
/*    */     //   Java source line #211	-> byte code offset #731
/*    */     //   Java source line #214	-> byte code offset #749
/*    */     // Local variable table:
/*    */     //   start	length	slot	name	signature
/*    */     //   0	750	0	this	LineasRestringidasDAO
/*    */     //   0	750	1	lineas	java.util.List<com.claro.transfer.TelefonoTO>
/*    */     //   1	735	2	conn	java.sql.Connection
/*    */     //   3	715	3	resultSet	java.sql.ResultSet
/*    */     //   5	738	4	stmt	java.sql.PreparedStatement
/*    */     //   24	203	5	queryBusqueda	StringBuilder
/*    */     //   594	33	5	e	Exception
/*    */     //   61	263	6	update	StringBuilder
/*    */     //   106	349	7	insertaLinea	StringBuilder
/*    */     //   143	385	8	insertaTotales	StringBuilder
/*    */     //   180	197	9	buscaTotales	StringBuilder
/*    */     //   208	374	10	iteraLineas	java.util.Iterator<com.claro.transfer.TelefonoTO>
/*    */     //   223	323	11	telefonoTO	com.claro.transfer.TelefonoTO
/*    */     //   273	176	12	existeLinea	boolean
/*    */     //   373	149	13	existeTotales	boolean
/*    */     //   632	59	14	localObject	Object
/*    */     //   652	1	15	localException1	Exception
/*    */     //   670	1	15	localException2	Exception
/*    */     //   688	1	15	localException3	Exception
/*    */     //   711	1	15	localException4	Exception
/*    */     //   729	1	15	localException5	Exception
/*    */     //   747	1	15	localException6	Exception
/*    */     // Exception table:
/*    */     //   from	to	target	type
/*    */     //   7	591	594	java/lang/Exception
/*    */     //   7	632	632	finally
/*    */     //   639	649	652	java/lang/Exception
/*    */     //   658	667	670	java/lang/Exception
/*    */     //   676	685	688	java/lang/Exception
/*    */     //   698	708	711	java/lang/Exception
/*    */     //   717	726	729	java/lang/Exception
/*    */     //   735	744	747	java/lang/Exception
/*    */   }
/*    */   
/*    */   /* Error */
/*    */   public java.util.List<com.claro.transfer.TelefonoTO> generaReporteLineasRestringidas()
/*    */     throws com.claro.exception.CAException
/*    */   {
/*    */     // Byte code:
/*    */     //   0: aconst_null
/*    */     //   1: astore_1
/*    */     //   2: aconst_null
/*    */     //   3: astore_2
/*    */     //   4: aconst_null
/*    */     //   5: astore_3
/*    */     //   6: new 239	java/util/ArrayList
/*    */     //   9: dup
/*    */     //   10: invokespecial 241	java/util/ArrayList:<init>	()V
/*    */     //   13: astore 4
/*    */     //   15: new 61	java/lang/StringBuilder
/*    */     //   18: dup
/*    */     //   19: invokespecial 63	java/lang/StringBuilder:<init>	()V
/*    */     //   22: astore 5
/*    */     //   24: invokestatic 29	com/claro/util/ServiceLocator:getInstance	()Lcom/claro/util/ServiceLocator;
/*    */     //   27: getstatic 64	com/claro/util/ServiceLocator:jdbcCirculoAzul	Ljava/lang/String;
/*    */     //   30: invokevirtual 67	com/claro/util/ServiceLocator:getConnection	(Ljava/lang/String;)Ljava/sql/Connection;
/*    */     //   33: astore_1
/*    */     //   34: aload 5
/*    */     //   36: ldc -14
/*    */     //   38: invokevirtual 85	java/lang/StringBuilder:append	(Ljava/lang/String;)Ljava/lang/StringBuilder;
/*    */     //   41: aload_0
/*    */     //   42: getfield 41	com/claro/dao/LineasRestringidasDAO:schema_database	Ljava/lang/String;
/*    */     //   45: invokevirtual 85	java/lang/StringBuilder:append	(Ljava/lang/String;)Ljava/lang/StringBuilder;
/*    */     //   48: ldc -12
/*    */     //   50: invokevirtual 85	java/lang/StringBuilder:append	(Ljava/lang/String;)Ljava/lang/StringBuilder;
/*    */     //   53: pop
/*    */     //   54: aload_1
/*    */     //   55: aload 5
/*    */     //   57: invokevirtual 91	java/lang/StringBuilder:toString	()Ljava/lang/String;
/*    */     //   60: invokeinterface 94 2 0
/*    */     //   65: astore_2
/*    */     //   66: aload_2
/*    */     //   67: invokeinterface 108 1 0
/*    */     //   72: astore_3
/*    */     //   73: goto +75 -> 148
/*    */     //   76: new 203	com/claro/transfer/TelefonoTO
/*    */     //   79: dup
/*    */     //   80: invokespecial 246	com/claro/transfer/TelefonoTO:<init>	()V
/*    */     //   83: astore 6
/*    */     //   85: aload 6
/*    */     //   87: aload_3
/*    */     //   88: ldc 112
/*    */     //   90: invokeinterface 114 2 0
/*    */     //   95: invokevirtual 247	com/claro/transfer/TelefonoTO:setCuenta	(Ljava/lang/String;)V
/*    */     //   98: aload 6
/*    */     //   100: aload_3
/*    */     //   101: ldc 119
/*    */     //   103: invokeinterface 114 2 0
/*    */     //   108: invokevirtual 250	com/claro/transfer/TelefonoTO:setTelefono	(Ljava/lang/String;)V
/*    */     //   111: aload 6
/*    */     //   113: aload_3
/*    */     //   114: ldc -3
/*    */     //   116: invokeinterface 135 2 0
/*    */     //   121: invokevirtual 255	com/claro/transfer/TelefonoTO:setRegion	(I)V
/*    */     //   124: aload 6
/*    */     //   126: aload_3
/*    */     //   127: ldc_w 259
/*    */     //   130: invokeinterface 114 2 0
/*    */     //   135: invokevirtual 261	com/claro/transfer/TelefonoTO:setPlan	(Ljava/lang/String;)V
/*    */     //   138: aload 4
/*    */     //   140: aload 6
/*    */     //   142: invokeinterface 264 2 0
/*    */     //   147: pop
/*    */     //   148: aload_3
/*    */     //   149: invokeinterface 121 1 0
/*    */     //   154: ifne -78 -> 76
/*    */     //   157: goto +98 -> 255
/*    */     //   160: astore 6
/*    */     //   162: new 59	com/claro/exception/CAException
/*    */     //   165: dup
/*    */     //   166: iconst_m1
/*    */     //   167: new 61	java/lang/StringBuilder
/*    */     //   170: dup
/*    */     //   171: ldc_w 267
/*    */     //   174: invokespecial 141	java/lang/StringBuilder:<init>	(Ljava/lang/String;)V
/*    */     //   177: aload 6
/*    */     //   179: invokevirtual 144	java/lang/Exception:toString	()Ljava/lang/String;
/*    */     //   182: invokevirtual 85	java/lang/StringBuilder:append	(Ljava/lang/String;)Ljava/lang/StringBuilder;
/*    */     //   185: ldc -111
/*    */     //   187: invokevirtual 85	java/lang/StringBuilder:append	(Ljava/lang/String;)Ljava/lang/StringBuilder;
/*    */     //   190: invokevirtual 91	java/lang/StringBuilder:toString	()Ljava/lang/String;
/*    */     //   193: aload 6
/*    */     //   195: invokespecial 147	com/claro/exception/CAException:<init>	(ILjava/lang/String;Ljava/lang/Exception;)V
/*    */     //   198: athrow
/*    */     //   199: astore 7
/*    */     //   201: aload_2
/*    */     //   202: ifnull +16 -> 218
/*    */     //   205: aload_2
/*    */     //   206: invokeinterface 125 1 0
/*    */     //   211: aconst_null
/*    */     //   212: astore_2
/*    */     //   213: goto +5 -> 218
/*    */     //   216: astore 8
/*    */     //   218: aload_3
/*    */     //   219: ifnull +16 -> 235
/*    */     //   222: aload_3
/*    */     //   223: invokeinterface 128 1 0
/*    */     //   228: aconst_null
/*    */     //   229: astore_2
/*    */     //   230: goto +5 -> 235
/*    */     //   233: astore 8
/*    */     //   235: aload_1
/*    */     //   236: ifnull +16 -> 252
/*    */     //   239: aload_1
/*    */     //   240: invokeinterface 150 1 0
/*    */     //   245: aconst_null
/*    */     //   246: astore_2
/*    */     //   247: goto +5 -> 252
/*    */     //   250: astore 8
/*    */     //   252: aload 7
/*    */     //   254: athrow
/*    */     //   255: aload_2
/*    */     //   256: ifnull +16 -> 272
/*    */     //   259: aload_2
/*    */     //   260: invokeinterface 125 1 0
/*    */     //   265: aconst_null
/*    */     //   266: astore_2
/*    */     //   267: goto +5 -> 272
/*    */     //   270: astore 8
/*    */     //   272: aload_3
/*    */     //   273: ifnull +16 -> 289
/*    */     //   276: aload_3
/*    */     //   277: invokeinterface 128 1 0
/*    */     //   282: aconst_null
/*    */     //   283: astore_2
/*    */     //   284: goto +5 -> 289
/*    */     //   287: astore 8
/*    */     //   289: aload_1
/*    */     //   290: ifnull +16 -> 306
/*    */     //   293: aload_1
/*    */     //   294: invokeinterface 150 1 0
/*    */     //   299: aconst_null
/*    */     //   300: astore_2
/*    */     //   301: goto +5 -> 306
/*    */     //   304: astore 8
/*    */     //   306: aload 4
/*    */     //   308: areturn
/*    */     // Line number table:
/*    */     //   Java source line #218	-> byte code offset #0
/*    */     //   Java source line #220	-> byte code offset #2
/*    */     //   Java source line #221	-> byte code offset #4
/*    */     //   Java source line #222	-> byte code offset #6
/*    */     //   Java source line #223	-> byte code offset #15
/*    */     //   Java source line #227	-> byte code offset #24
/*    */     //   Java source line #229	-> byte code offset #34
/*    */     //   Java source line #230	-> byte code offset #54
/*    */     //   Java source line #232	-> byte code offset #66
/*    */     //   Java source line #234	-> byte code offset #73
/*    */     //   Java source line #235	-> byte code offset #76
/*    */     //   Java source line #236	-> byte code offset #85
/*    */     //   Java source line #237	-> byte code offset #98
/*    */     //   Java source line #238	-> byte code offset #111
/*    */     //   Java source line #239	-> byte code offset #124
/*    */     //   Java source line #240	-> byte code offset #138
/*    */     //   Java source line #234	-> byte code offset #148
/*    */     //   Java source line #242	-> byte code offset #160
/*    */     //   Java source line #243	-> byte code offset #162
/*    */     //   Java source line #244	-> byte code offset #199
/*    */     //   Java source line #245	-> byte code offset #201
/*    */     //   Java source line #246	-> byte code offset #218
/*    */     //   Java source line #247	-> byte code offset #235
/*    */     //   Java source line #248	-> byte code offset #252
/*    */     //   Java source line #245	-> byte code offset #255
/*    */     //   Java source line #246	-> byte code offset #272
/*    */     //   Java source line #247	-> byte code offset #289
/*    */     //   Java source line #250	-> byte code offset #306
/*    */     // Local variable table:
/*    */     //   start	length	slot	name	signature
/*    */     //   0	309	0	this	LineasRestringidasDAO
/*    */     //   1	293	1	conn	java.sql.Connection
/*    */     //   3	298	2	stmt	java.sql.PreparedStatement
/*    */     //   5	272	3	resultSet	java.sql.ResultSet
/*    */     //   13	294	4	lineas	java.util.List<com.claro.transfer.TelefonoTO>
/*    */     //   22	34	5	query	StringBuilder
/*    */     //   83	58	6	telefonoTO	com.claro.transfer.TelefonoTO
/*    */     //   160	34	6	e	Exception
/*    */     //   199	54	7	localObject	Object
/*    */     //   216	1	8	localException1	Exception
/*    */     //   233	1	8	localException2	Exception
/*    */     //   250	1	8	localException3	Exception
/*    */     //   270	1	8	localException4	Exception
/*    */     //   287	1	8	localException5	Exception
/*    */     //   304	1	8	localException6	Exception
/*    */     // Exception table:
/*    */     //   from	to	target	type
/*    */     //   24	157	160	java/lang/Exception
/*    */     //   24	199	199	finally
/*    */     //   205	213	216	java/lang/Exception
/*    */     //   222	230	233	java/lang/Exception
/*    */     //   239	247	250	java/lang/Exception
/*    */     //   259	267	270	java/lang/Exception
/*    */     //   276	284	287	java/lang/Exception
/*    */     //   293	301	304	java/lang/Exception
/*    */   }
/*    */ }


/* Location:              /opt/trabajo/claro/Guatemala/IS/CO/ClaroClub.ear!/ClaroClubEJB.jar!/com/claro/dao/LineasRestringidasDAO.class
 * Java compiler version: 6 (50.0)
 * JD-Core Version:       0.7.1
 */