/*    */ package com.claro.dao;
/*    */ 
/*    */ import com.claro.util.ServiceLocator;
/*    */ import org.apache.log4j.Logger;
/*    */ 
/*    */ 
/*    */ 
/*    */ 
/*    */ 
/*    */ 
/*    */ 
/*    */ 
/*    */ 
/*    */ 
/*    */ 
/*    */ 
/*    */ 
/*    */ 
/*    */ 
/*    */ 
/*    */ 
/*    */ public class MembresiaDAO
/*    */ {
/* 24 */   protected final Logger logger = Logger.getLogger("loggerCirculoAzul");
/* 25 */   protected final Logger error = Logger.getLogger("loggerCirculoAzulError");
/*    */   private String schema_database;
/*    */   
/*    */   public MembresiaDAO()
/*    */   {
/*    */     try {
/* 31 */       this.schema_database = ServiceLocator.getInstance().getVariable(ServiceLocator.schema_database);
/*    */     } catch (Exception e) {
/* 33 */       this.error.error("PuntosDAO", e);
/*    */     }
/*    */   }
/*    */   
/*    */   /* Error */
/*    */   private com.claro.transfer.MensajeTO insertaReposiciones(java.sql.Connection connection, long fechaTransaccion, com.claro.transfer.membresia.MembresiaTO membresiaTO)
/*    */     throws com.claro.exception.CAException
/*    */   {
/*    */     // Byte code:
/*    */     //   0: aconst_null
/*    */     //   1: astore 5
/*    */     //   3: aconst_null
/*    */     //   4: astore 6
/*    */     //   6: new 61	com/claro/transfer/MensajeTO
/*    */     //   9: dup
/*    */     //   10: invokespecial 63	com/claro/transfer/MensajeTO:<init>	()V
/*    */     //   13: astore 7
/*    */     //   15: aload_1
/*    */     //   16: ifnonnull +17 -> 33
/*    */     //   19: invokestatic 29	com/claro/util/ServiceLocator:getInstance	()Lcom/claro/util/ServiceLocator;
/*    */     //   22: getstatic 64	com/claro/util/ServiceLocator:jdbcCirculoAzul	Ljava/lang/String;
/*    */     //   25: invokevirtual 67	com/claro/util/ServiceLocator:getConnection	(Ljava/lang/String;)Ljava/sql/Connection;
/*    */     //   28: astore 5
/*    */     //   30: goto +6 -> 36
/*    */     //   33: aload_1
/*    */     //   34: astore 5
/*    */     //   36: new 71	java/lang/StringBuilder
/*    */     //   39: dup
/*    */     //   40: ldc 73
/*    */     //   42: invokespecial 75	java/lang/StringBuilder:<init>	(Ljava/lang/String;)V
/*    */     //   45: aload_0
/*    */     //   46: getfield 41	com/claro/dao/MembresiaDAO:schema_database	Ljava/lang/String;
/*    */     //   49: invokevirtual 78	java/lang/StringBuilder:append	(Ljava/lang/String;)Ljava/lang/StringBuilder;
/*    */     //   52: ldc 82
/*    */     //   54: invokevirtual 78	java/lang/StringBuilder:append	(Ljava/lang/String;)Ljava/lang/StringBuilder;
/*    */     //   57: ldc 84
/*    */     //   59: invokevirtual 78	java/lang/StringBuilder:append	(Ljava/lang/String;)Ljava/lang/StringBuilder;
/*    */     //   62: ldc 86
/*    */     //   64: invokevirtual 78	java/lang/StringBuilder:append	(Ljava/lang/String;)Ljava/lang/StringBuilder;
/*    */     //   67: ldc 88
/*    */     //   69: invokevirtual 78	java/lang/StringBuilder:append	(Ljava/lang/String;)Ljava/lang/StringBuilder;
/*    */     //   72: ldc 88
/*    */     //   74: invokevirtual 78	java/lang/StringBuilder:append	(Ljava/lang/String;)Ljava/lang/StringBuilder;
/*    */     //   77: ldc 90
/*    */     //   79: invokevirtual 78	java/lang/StringBuilder:append	(Ljava/lang/String;)Ljava/lang/StringBuilder;
/*    */     //   82: invokevirtual 92	java/lang/StringBuilder:toString	()Ljava/lang/String;
/*    */     //   85: astore 8
/*    */     //   87: aload 5
/*    */     //   89: aload 8
/*    */     //   91: invokeinterface 96 2 0
/*    */     //   96: astore 6
/*    */     //   98: aload 6
/*    */     //   100: iconst_1
/*    */     //   101: aload 4
/*    */     //   103: invokevirtual 102	com/claro/transfer/membresia/MembresiaTO:getCuenta	()Ljava/lang/String;
/*    */     //   106: invokeinterface 107 3 0
/*    */     //   111: aload 6
/*    */     //   113: iconst_2
/*    */     //   114: aload 4
/*    */     //   116: invokevirtual 113	com/claro/transfer/membresia/MembresiaTO:getSecuencia	()I
/*    */     //   119: invokeinterface 117 3 0
/*    */     //   124: aload 6
/*    */     //   126: iconst_3
/*    */     //   127: aload 4
/*    */     //   129: invokevirtual 121	com/claro/transfer/membresia/MembresiaTO:getNombreM2K	()Ljava/lang/String;
/*    */     //   132: invokeinterface 107 3 0
/*    */     //   137: aload 6
/*    */     //   139: iconst_4
/*    */     //   140: aload 4
/*    */     //   142: invokevirtual 124	com/claro/transfer/membresia/MembresiaTO:getFechaAltaM2K	()Ljava/lang/String;
/*    */     //   145: invokeinterface 107 3 0
/*    */     //   150: aload 6
/*    */     //   152: iconst_5
/*    */     //   153: aload 4
/*    */     //   155: invokevirtual 127	com/claro/transfer/membresia/MembresiaTO:getRegion	()I
/*    */     //   158: invokeinterface 117 3 0
/*    */     //   163: aload 6
/*    */     //   165: bipush 6
/*    */     //   167: aload 4
/*    */     //   169: invokevirtual 130	com/claro/transfer/membresia/MembresiaTO:getTelefono	()Ljava/lang/String;
/*    */     //   172: invokeinterface 107 3 0
/*    */     //   177: aload 6
/*    */     //   179: bipush 7
/*    */     //   181: aload 4
/*    */     //   183: invokevirtual 133	com/claro/transfer/membresia/MembresiaTO:getSegmento	()Ljava/lang/String;
/*    */     //   186: invokeinterface 107 3 0
/*    */     //   191: aload 6
/*    */     //   193: bipush 8
/*    */     //   195: aload 4
/*    */     //   197: invokevirtual 136	com/claro/transfer/membresia/MembresiaTO:getPlan	()Ljava/lang/String;
/*    */     //   200: invokeinterface 107 3 0
/*    */     //   205: aload 6
/*    */     //   207: bipush 9
/*    */     //   209: aload 4
/*    */     //   211: invokevirtual 139	com/claro/transfer/membresia/MembresiaTO:getDescPlan	()Ljava/lang/String;
/*    */     //   214: invokeinterface 107 3 0
/*    */     //   219: aload 6
/*    */     //   221: bipush 10
/*    */     //   223: aload 4
/*    */     //   225: invokevirtual 142	com/claro/transfer/membresia/MembresiaTO:getNombre	()Ljava/lang/String;
/*    */     //   228: invokeinterface 107 3 0
/*    */     //   233: aload 6
/*    */     //   235: bipush 11
/*    */     //   237: aload 4
/*    */     //   239: invokevirtual 145	com/claro/transfer/membresia/MembresiaTO:getApPaterno	()Ljava/lang/String;
/*    */     //   242: invokeinterface 107 3 0
/*    */     //   247: aload 6
/*    */     //   249: bipush 12
/*    */     //   251: aload 4
/*    */     //   253: invokevirtual 148	com/claro/transfer/membresia/MembresiaTO:getApMaterno	()Ljava/lang/String;
/*    */     //   256: invokeinterface 107 3 0
/*    */     //   261: aload 6
/*    */     //   263: bipush 13
/*    */     //   265: aload 4
/*    */     //   267: invokevirtual 151	com/claro/transfer/membresia/MembresiaTO:getTipoCalle	()Ljava/lang/String;
/*    */     //   270: invokeinterface 107 3 0
/*    */     //   275: aload 6
/*    */     //   277: bipush 14
/*    */     //   279: aload 4
/*    */     //   281: invokevirtual 154	com/claro/transfer/membresia/MembresiaTO:getCalle	()Ljava/lang/String;
/*    */     //   284: invokeinterface 107 3 0
/*    */     //   289: aload 6
/*    */     //   291: bipush 15
/*    */     //   293: aload 4
/*    */     //   295: invokevirtual 157	com/claro/transfer/membresia/MembresiaTO:getNumExterior	()Ljava/lang/String;
/*    */     //   298: invokeinterface 107 3 0
/*    */     //   303: aload 6
/*    */     //   305: bipush 16
/*    */     //   307: aload 4
/*    */     //   309: invokevirtual 160	com/claro/transfer/membresia/MembresiaTO:getNumInterior	()Ljava/lang/String;
/*    */     //   312: invokeinterface 107 3 0
/*    */     //   317: aload 6
/*    */     //   319: bipush 17
/*    */     //   321: aload 4
/*    */     //   323: invokevirtual 163	com/claro/transfer/membresia/MembresiaTO:getColonia	()Ljava/lang/String;
/*    */     //   326: invokeinterface 107 3 0
/*    */     //   331: aload 6
/*    */     //   333: bipush 18
/*    */     //   335: aload 4
/*    */     //   337: invokevirtual 166	com/claro/transfer/membresia/MembresiaTO:getCiudad	()Ljava/lang/String;
/*    */     //   340: invokeinterface 107 3 0
/*    */     //   345: aload 6
/*    */     //   347: bipush 19
/*    */     //   349: aload 4
/*    */     //   351: invokevirtual 169	com/claro/transfer/membresia/MembresiaTO:getEstado	()Ljava/lang/String;
/*    */     //   354: invokeinterface 107 3 0
/*    */     //   359: aload 6
/*    */     //   361: bipush 20
/*    */     //   363: aload 4
/*    */     //   365: invokevirtual 172	com/claro/transfer/membresia/MembresiaTO:getCodigoPostal	()Ljava/lang/String;
/*    */     //   368: invokeinterface 107 3 0
/*    */     //   373: aload 6
/*    */     //   375: bipush 21
/*    */     //   377: aload 4
/*    */     //   379: invokevirtual 175	com/claro/transfer/membresia/MembresiaTO:getUsuario	()Ljava/lang/String;
/*    */     //   382: invokeinterface 107 3 0
/*    */     //   387: aload 6
/*    */     //   389: bipush 22
/*    */     //   391: new 178	java/sql/Date
/*    */     //   394: dup
/*    */     //   395: lload_2
/*    */     //   396: invokespecial 180	java/sql/Date:<init>	(J)V
/*    */     //   399: invokeinterface 183 3 0
/*    */     //   404: aload 6
/*    */     //   406: bipush 23
/*    */     //   408: aload 4
/*    */     //   410: invokevirtual 187	com/claro/transfer/membresia/MembresiaTO:getEstatus	()Ljava/lang/String;
/*    */     //   413: invokeinterface 107 3 0
/*    */     //   418: aload 6
/*    */     //   420: bipush 24
/*    */     //   422: aload 4
/*    */     //   424: invokevirtual 190	com/claro/transfer/membresia/MembresiaTO:getMotivo	()Ljava/lang/String;
/*    */     //   427: invokeinterface 107 3 0
/*    */     //   432: aload 6
/*    */     //   434: bipush 25
/*    */     //   436: aload 4
/*    */     //   438: invokevirtual 193	com/claro/transfer/membresia/MembresiaTO:getCosto	()I
/*    */     //   441: invokeinterface 117 3 0
/*    */     //   446: aload 6
/*    */     //   448: invokeinterface 196 1 0
/*    */     //   453: ifle +14 -> 467
/*    */     //   456: aload 7
/*    */     //   458: iconst_0
/*    */     //   459: ldc -57
/*    */     //   461: invokevirtual 201	com/claro/transfer/MensajeTO:agregaMensaje	(ILjava/lang/String;)V
/*    */     //   464: goto +161 -> 625
/*    */     //   467: aload 7
/*    */     //   469: iconst_1
/*    */     //   470: ldc -52
/*    */     //   472: invokevirtual 201	com/claro/transfer/MensajeTO:agregaMensaje	(ILjava/lang/String;)V
/*    */     //   475: goto +150 -> 625
/*    */     //   478: astore 8
/*    */     //   480: aload_0
/*    */     //   481: getfield 27	com/claro/dao/MembresiaDAO:error	Lorg/apache/log4j/Logger;
/*    */     //   484: ldc -50
/*    */     //   486: aload 8
/*    */     //   488: invokevirtual 208	org/apache/log4j/Logger:info	(Ljava/lang/Object;Ljava/lang/Throwable;)V
/*    */     //   491: new 59	com/claro/exception/CAException
/*    */     //   494: dup
/*    */     //   495: iconst_m1
/*    */     //   496: new 71	java/lang/StringBuilder
/*    */     //   499: dup
/*    */     //   500: ldc -45
/*    */     //   502: invokespecial 75	java/lang/StringBuilder:<init>	(Ljava/lang/String;)V
/*    */     //   505: aload 8
/*    */     //   507: invokevirtual 213	java/sql/SQLException:toString	()Ljava/lang/String;
/*    */     //   510: invokevirtual 78	java/lang/StringBuilder:append	(Ljava/lang/String;)Ljava/lang/StringBuilder;
/*    */     //   513: ldc -40
/*    */     //   515: invokevirtual 78	java/lang/StringBuilder:append	(Ljava/lang/String;)Ljava/lang/StringBuilder;
/*    */     //   518: invokevirtual 92	java/lang/StringBuilder:toString	()Ljava/lang/String;
/*    */     //   521: aload 8
/*    */     //   523: invokespecial 218	com/claro/exception/CAException:<init>	(ILjava/lang/String;Ljava/lang/Exception;)V
/*    */     //   526: athrow
/*    */     //   527: astore 8
/*    */     //   529: aload_0
/*    */     //   530: getfield 27	com/claro/dao/MembresiaDAO:error	Lorg/apache/log4j/Logger;
/*    */     //   533: ldc -35
/*    */     //   535: aload 8
/*    */     //   537: invokevirtual 208	org/apache/log4j/Logger:info	(Ljava/lang/Object;Ljava/lang/Throwable;)V
/*    */     //   540: new 59	com/claro/exception/CAException
/*    */     //   543: dup
/*    */     //   544: iconst_m1
/*    */     //   545: new 71	java/lang/StringBuilder
/*    */     //   548: dup
/*    */     //   549: ldc -33
/*    */     //   551: invokespecial 75	java/lang/StringBuilder:<init>	(Ljava/lang/String;)V
/*    */     //   554: aload 8
/*    */     //   556: invokevirtual 225	java/lang/Exception:toString	()Ljava/lang/String;
/*    */     //   559: invokevirtual 78	java/lang/StringBuilder:append	(Ljava/lang/String;)Ljava/lang/StringBuilder;
/*    */     //   562: ldc -40
/*    */     //   564: invokevirtual 78	java/lang/StringBuilder:append	(Ljava/lang/String;)Ljava/lang/StringBuilder;
/*    */     //   567: invokevirtual 92	java/lang/StringBuilder:toString	()Ljava/lang/String;
/*    */     //   570: aload 8
/*    */     //   572: invokespecial 218	com/claro/exception/CAException:<init>	(ILjava/lang/String;Ljava/lang/Exception;)V
/*    */     //   575: athrow
/*    */     //   576: astore 9
/*    */     //   578: aload 6
/*    */     //   580: ifnull +18 -> 598
/*    */     //   583: aload 6
/*    */     //   585: invokeinterface 226 1 0
/*    */     //   590: aconst_null
/*    */     //   591: astore 6
/*    */     //   593: goto +5 -> 598
/*    */     //   596: astore 10
/*    */     //   598: aload_1
/*    */     //   599: ifnonnull +23 -> 622
/*    */     //   602: aload 5
/*    */     //   604: ifnull +18 -> 622
/*    */     //   607: aload 5
/*    */     //   609: invokeinterface 229 1 0
/*    */     //   614: aconst_null
/*    */     //   615: astore 5
/*    */     //   617: goto +5 -> 622
/*    */     //   620: astore 10
/*    */     //   622: aload 9
/*    */     //   624: athrow
/*    */     //   625: aload 6
/*    */     //   627: ifnull +18 -> 645
/*    */     //   630: aload 6
/*    */     //   632: invokeinterface 226 1 0
/*    */     //   637: aconst_null
/*    */     //   638: astore 6
/*    */     //   640: goto +5 -> 645
/*    */     //   643: astore 10
/*    */     //   645: aload_1
/*    */     //   646: ifnonnull +23 -> 669
/*    */     //   649: aload 5
/*    */     //   651: ifnull +18 -> 669
/*    */     //   654: aload 5
/*    */     //   656: invokeinterface 229 1 0
/*    */     //   661: aconst_null
/*    */     //   662: astore 5
/*    */     //   664: goto +5 -> 669
/*    */     //   667: astore 10
/*    */     //   669: aload 7
/*    */     //   671: areturn
/*    */     // Line number table:
/*    */     //   Java source line #39	-> byte code offset #0
/*    */     //   Java source line #40	-> byte code offset #3
/*    */     //   Java source line #41	-> byte code offset #6
/*    */     //   Java source line #44	-> byte code offset #15
/*    */     //   Java source line #45	-> byte code offset #33
/*    */     //   Java source line #47	-> byte code offset #36
/*    */     //   Java source line #48	-> byte code offset #57
/*    */     //   Java source line #49	-> byte code offset #62
/*    */     //   Java source line #50	-> byte code offset #67
/*    */     //   Java source line #51	-> byte code offset #72
/*    */     //   Java source line #52	-> byte code offset #77
/*    */     //   Java source line #47	-> byte code offset #82
/*    */     //   Java source line #54	-> byte code offset #87
/*    */     //   Java source line #55	-> byte code offset #98
/*    */     //   Java source line #56	-> byte code offset #111
/*    */     //   Java source line #57	-> byte code offset #124
/*    */     //   Java source line #58	-> byte code offset #137
/*    */     //   Java source line #59	-> byte code offset #150
/*    */     //   Java source line #60	-> byte code offset #163
/*    */     //   Java source line #61	-> byte code offset #177
/*    */     //   Java source line #62	-> byte code offset #191
/*    */     //   Java source line #63	-> byte code offset #205
/*    */     //   Java source line #64	-> byte code offset #219
/*    */     //   Java source line #65	-> byte code offset #233
/*    */     //   Java source line #66	-> byte code offset #247
/*    */     //   Java source line #67	-> byte code offset #261
/*    */     //   Java source line #68	-> byte code offset #275
/*    */     //   Java source line #69	-> byte code offset #289
/*    */     //   Java source line #70	-> byte code offset #303
/*    */     //   Java source line #71	-> byte code offset #317
/*    */     //   Java source line #72	-> byte code offset #331
/*    */     //   Java source line #73	-> byte code offset #345
/*    */     //   Java source line #74	-> byte code offset #359
/*    */     //   Java source line #75	-> byte code offset #373
/*    */     //   Java source line #76	-> byte code offset #387
/*    */     //   Java source line #77	-> byte code offset #404
/*    */     //   Java source line #78	-> byte code offset #418
/*    */     //   Java source line #79	-> byte code offset #432
/*    */     //   Java source line #81	-> byte code offset #446
/*    */     //   Java source line #82	-> byte code offset #467
/*    */     //   Java source line #84	-> byte code offset #478
/*    */     //   Java source line #85	-> byte code offset #480
/*    */     //   Java source line #86	-> byte code offset #491
/*    */     //   Java source line #87	-> byte code offset #527
/*    */     //   Java source line #88	-> byte code offset #529
/*    */     //   Java source line #89	-> byte code offset #540
/*    */     //   Java source line #90	-> byte code offset #576
/*    */     //   Java source line #91	-> byte code offset #578
/*    */     //   Java source line #92	-> byte code offset #598
/*    */     //   Java source line #93	-> byte code offset #622
/*    */     //   Java source line #91	-> byte code offset #625
/*    */     //   Java source line #92	-> byte code offset #645
/*    */     //   Java source line #94	-> byte code offset #669
/*    */     // Local variable table:
/*    */     //   start	length	slot	name	signature
/*    */     //   0	672	0	this	MembresiaDAO
/*    */     //   0	672	1	connection	java.sql.Connection
/*    */     //   0	672	2	fechaTransaccion	long
/*    */     //   0	672	4	membresiaTO	com.claro.transfer.membresia.MembresiaTO
/*    */     //   1	662	5	lConn	java.sql.Connection
/*    */     //   4	635	6	statement	java.sql.PreparedStatement
/*    */     //   13	657	7	mensajeTO	com.claro.transfer.MensajeTO
/*    */     //   85	5	8	insert	String
/*    */     //   478	44	8	e	java.sql.SQLException
/*    */     //   527	44	8	e	Exception
/*    */     //   576	47	9	localObject	Object
/*    */     //   596	1	10	localException1	Exception
/*    */     //   620	1	10	localException2	Exception
/*    */     //   643	1	10	localException3	Exception
/*    */     //   667	1	10	localException4	Exception
/*    */     // Exception table:
/*    */     //   from	to	target	type
/*    */     //   15	475	478	java/sql/SQLException
/*    */     //   15	475	527	java/lang/Exception
/*    */     //   15	576	576	finally
/*    */     //   583	593	596	java/lang/Exception
/*    */     //   607	617	620	java/lang/Exception
/*    */     //   630	640	643	java/lang/Exception
/*    */     //   654	664	667	java/lang/Exception
/*    */   }
/*    */   
/*    */   /* Error */
/*    */   public com.claro.transfer.MensajeTO agregarMembresia(com.claro.transfer.membresia.MembresiaTO membresiaTO)
/*    */     throws com.claro.exception.CAException
/*    */   {
/*    */     // Byte code:
/*    */     //   0: aconst_null
/*    */     //   1: astore_2
/*    */     //   2: new 61	com/claro/transfer/MensajeTO
/*    */     //   5: dup
/*    */     //   6: invokespecial 63	com/claro/transfer/MensajeTO:<init>	()V
/*    */     //   9: astore_3
/*    */     //   10: new 249	com/claro/dao/PuntosDAO
/*    */     //   13: dup
/*    */     //   14: invokespecial 251	com/claro/dao/PuntosDAO:<init>	()V
/*    */     //   17: astore 4
/*    */     //   19: invokestatic 29	com/claro/util/ServiceLocator:getInstance	()Lcom/claro/util/ServiceLocator;
/*    */     //   22: getstatic 64	com/claro/util/ServiceLocator:jdbcCirculoAzul	Ljava/lang/String;
/*    */     //   25: invokevirtual 67	com/claro/util/ServiceLocator:getConnection	(Ljava/lang/String;)Ljava/sql/Connection;
/*    */     //   28: astore_2
/*    */     //   29: aload_2
/*    */     //   30: iconst_0
/*    */     //   31: invokeinterface 252 2 0
/*    */     //   36: invokestatic 256	java/lang/System:currentTimeMillis	()J
/*    */     //   39: lstore 5
/*    */     //   41: aload_1
/*    */     //   42: ldc_w 262
/*    */     //   45: invokevirtual 264	com/claro/transfer/membresia/MembresiaTO:setEstatus	(Ljava/lang/String;)V
/*    */     //   48: aload_0
/*    */     //   49: aload_2
/*    */     //   50: lload 5
/*    */     //   52: aload_1
/*    */     //   53: invokespecial 267	com/claro/dao/MembresiaDAO:insertaReposiciones	(Ljava/sql/Connection;JLcom/claro/transfer/membresia/MembresiaTO;)Lcom/claro/transfer/MensajeTO;
/*    */     //   56: astore_3
/*    */     //   57: aload_3
/*    */     //   58: invokevirtual 269	com/claro/transfer/MensajeTO:getIdMensaje	()I
/*    */     //   61: ifne +63 -> 124
/*    */     //   64: aload 4
/*    */     //   66: aload_2
/*    */     //   67: aload_1
/*    */     //   68: invokevirtual 127	com/claro/transfer/membresia/MembresiaTO:getRegion	()I
/*    */     //   71: aload_1
/*    */     //   72: invokevirtual 102	com/claro/transfer/membresia/MembresiaTO:getCuenta	()Ljava/lang/String;
/*    */     //   75: aload_1
/*    */     //   76: invokevirtual 175	com/claro/transfer/membresia/MembresiaTO:getUsuario	()Ljava/lang/String;
/*    */     //   79: lload 5
/*    */     //   81: new 71	java/lang/StringBuilder
/*    */     //   84: dup
/*    */     //   85: ldc_w 272
/*    */     //   88: invokespecial 75	java/lang/StringBuilder:<init>	(Ljava/lang/String;)V
/*    */     //   91: aload_1
/*    */     //   92: invokevirtual 175	com/claro/transfer/membresia/MembresiaTO:getUsuario	()Ljava/lang/String;
/*    */     //   95: invokevirtual 78	java/lang/StringBuilder:append	(Ljava/lang/String;)Ljava/lang/StringBuilder;
/*    */     //   98: ldc_w 274
/*    */     //   101: invokevirtual 78	java/lang/StringBuilder:append	(Ljava/lang/String;)Ljava/lang/StringBuilder;
/*    */     //   104: aload_1
/*    */     //   105: invokevirtual 190	com/claro/transfer/membresia/MembresiaTO:getMotivo	()Ljava/lang/String;
/*    */     //   108: invokevirtual 78	java/lang/StringBuilder:append	(Ljava/lang/String;)Ljava/lang/StringBuilder;
/*    */     //   111: ldc_w 276
/*    */     //   114: invokevirtual 78	java/lang/StringBuilder:append	(Ljava/lang/String;)Ljava/lang/StringBuilder;
/*    */     //   117: invokevirtual 92	java/lang/StringBuilder:toString	()Ljava/lang/String;
/*    */     //   120: invokevirtual 278	com/claro/dao/PuntosDAO:insertaComentarioTMP	(Ljava/sql/Connection;ILjava/lang/String;Ljava/lang/String;JLjava/lang/String;)Lcom/claro/transfer/MensajeTO;
/*    */     //   123: astore_3
/*    */     //   124: aload_3
/*    */     //   125: invokevirtual 269	com/claro/transfer/MensajeTO:getIdMensaje	()I
/*    */     //   128: ifne +95 -> 223
/*    */     //   131: new 71	java/lang/StringBuilder
/*    */     //   134: dup
/*    */     //   135: ldc_w 282
/*    */     //   138: invokespecial 75	java/lang/StringBuilder:<init>	(Ljava/lang/String;)V
/*    */     //   141: aload_1
/*    */     //   142: invokevirtual 175	com/claro/transfer/membresia/MembresiaTO:getUsuario	()Ljava/lang/String;
/*    */     //   145: invokevirtual 78	java/lang/StringBuilder:append	(Ljava/lang/String;)Ljava/lang/StringBuilder;
/*    */     //   148: ldc_w 284
/*    */     //   151: invokevirtual 78	java/lang/StringBuilder:append	(Ljava/lang/String;)Ljava/lang/StringBuilder;
/*    */     //   154: aload_1
/*    */     //   155: invokevirtual 190	com/claro/transfer/membresia/MembresiaTO:getMotivo	()Ljava/lang/String;
/*    */     //   158: invokevirtual 78	java/lang/StringBuilder:append	(Ljava/lang/String;)Ljava/lang/StringBuilder;
/*    */     //   161: ldc_w 286
/*    */     //   164: invokevirtual 78	java/lang/StringBuilder:append	(Ljava/lang/String;)Ljava/lang/StringBuilder;
/*    */     //   167: aload_1
/*    */     //   168: invokevirtual 193	com/claro/transfer/membresia/MembresiaTO:getCosto	()I
/*    */     //   171: iconst_1
/*    */     //   172: if_icmpne +9 -> 181
/*    */     //   175: ldc_w 288
/*    */     //   178: goto +6 -> 184
/*    */     //   181: ldc_w 290
/*    */     //   184: invokevirtual 78	java/lang/StringBuilder:append	(Ljava/lang/String;)Ljava/lang/StringBuilder;
/*    */     //   187: invokevirtual 92	java/lang/StringBuilder:toString	()Ljava/lang/String;
/*    */     //   190: astore 7
/*    */     //   192: aload 4
/*    */     //   194: aload_2
/*    */     //   195: lload 5
/*    */     //   197: aload 7
/*    */     //   199: bipush 37
/*    */     //   201: iconst_0
/*    */     //   202: aconst_null
/*    */     //   203: aload_1
/*    */     //   204: invokevirtual 102	com/claro/transfer/membresia/MembresiaTO:getCuenta	()Ljava/lang/String;
/*    */     //   207: aload_1
/*    */     //   208: invokevirtual 113	com/claro/transfer/membresia/MembresiaTO:getSecuencia	()I
/*    */     //   211: aload_1
/*    */     //   212: invokevirtual 130	com/claro/transfer/membresia/MembresiaTO:getTelefono	()Ljava/lang/String;
/*    */     //   215: aload_1
/*    */     //   216: invokevirtual 175	com/claro/transfer/membresia/MembresiaTO:getUsuario	()Ljava/lang/String;
/*    */     //   219: invokevirtual 292	com/claro/dao/PuntosDAO:insertaDetalle	(Ljava/sql/Connection;JLjava/lang/String;IILjava/lang/String;Ljava/lang/String;ILjava/lang/String;Ljava/lang/String;)Lcom/claro/transfer/MensajeTO;
/*    */     //   222: astore_3
/*    */     //   223: aload_3
/*    */     //   224: invokevirtual 269	com/claro/transfer/MensajeTO:getIdMensaje	()I
/*    */     //   227: ifeq +12 -> 239
/*    */     //   230: aload_2
/*    */     //   231: invokeinterface 296 1 0
/*    */     //   236: goto +169 -> 405
/*    */     //   239: aload_2
/*    */     //   240: invokeinterface 299 1 0
/*    */     //   245: goto +160 -> 405
/*    */     //   248: astore 4
/*    */     //   250: aload_0
/*    */     //   251: getfield 27	com/claro/dao/MembresiaDAO:error	Lorg/apache/log4j/Logger;
/*    */     //   254: ldc -50
/*    */     //   256: aload 4
/*    */     //   258: invokevirtual 208	org/apache/log4j/Logger:info	(Ljava/lang/Object;Ljava/lang/Throwable;)V
/*    */     //   261: aload_2
/*    */     //   262: ifnull +14 -> 276
/*    */     //   265: aload_2
/*    */     //   266: invokeinterface 296 1 0
/*    */     //   271: goto +5 -> 276
/*    */     //   274: astore 5
/*    */     //   276: new 59	com/claro/exception/CAException
/*    */     //   279: dup
/*    */     //   280: iconst_m1
/*    */     //   281: new 71	java/lang/StringBuilder
/*    */     //   284: dup
/*    */     //   285: ldc -45
/*    */     //   287: invokespecial 75	java/lang/StringBuilder:<init>	(Ljava/lang/String;)V
/*    */     //   290: aload 4
/*    */     //   292: invokevirtual 213	java/sql/SQLException:toString	()Ljava/lang/String;
/*    */     //   295: invokevirtual 78	java/lang/StringBuilder:append	(Ljava/lang/String;)Ljava/lang/StringBuilder;
/*    */     //   298: ldc -40
/*    */     //   300: invokevirtual 78	java/lang/StringBuilder:append	(Ljava/lang/String;)Ljava/lang/StringBuilder;
/*    */     //   303: invokevirtual 92	java/lang/StringBuilder:toString	()Ljava/lang/String;
/*    */     //   306: aload 4
/*    */     //   308: invokespecial 218	com/claro/exception/CAException:<init>	(ILjava/lang/String;Ljava/lang/Exception;)V
/*    */     //   311: athrow
/*    */     //   312: astore 4
/*    */     //   314: aload_0
/*    */     //   315: getfield 27	com/claro/dao/MembresiaDAO:error	Lorg/apache/log4j/Logger;
/*    */     //   318: ldc -35
/*    */     //   320: aload 4
/*    */     //   322: invokevirtual 208	org/apache/log4j/Logger:info	(Ljava/lang/Object;Ljava/lang/Throwable;)V
/*    */     //   325: aload_2
/*    */     //   326: ifnull +14 -> 340
/*    */     //   329: aload_2
/*    */     //   330: invokeinterface 296 1 0
/*    */     //   335: goto +5 -> 340
/*    */     //   338: astore 5
/*    */     //   340: new 59	com/claro/exception/CAException
/*    */     //   343: dup
/*    */     //   344: iconst_m1
/*    */     //   345: new 71	java/lang/StringBuilder
/*    */     //   348: dup
/*    */     //   349: ldc -33
/*    */     //   351: invokespecial 75	java/lang/StringBuilder:<init>	(Ljava/lang/String;)V
/*    */     //   354: aload 4
/*    */     //   356: invokevirtual 225	java/lang/Exception:toString	()Ljava/lang/String;
/*    */     //   359: invokevirtual 78	java/lang/StringBuilder:append	(Ljava/lang/String;)Ljava/lang/StringBuilder;
/*    */     //   362: ldc -40
/*    */     //   364: invokevirtual 78	java/lang/StringBuilder:append	(Ljava/lang/String;)Ljava/lang/StringBuilder;
/*    */     //   367: invokevirtual 92	java/lang/StringBuilder:toString	()Ljava/lang/String;
/*    */     //   370: aload 4
/*    */     //   372: invokespecial 218	com/claro/exception/CAException:<init>	(ILjava/lang/String;Ljava/lang/Exception;)V
/*    */     //   375: athrow
/*    */     //   376: astore 8
/*    */     //   378: aload_2
/*    */     //   379: ifnull +23 -> 402
/*    */     //   382: aload_2
/*    */     //   383: iconst_1
/*    */     //   384: invokeinterface 252 2 0
/*    */     //   389: aload_2
/*    */     //   390: invokeinterface 229 1 0
/*    */     //   395: aconst_null
/*    */     //   396: astore_2
/*    */     //   397: goto +5 -> 402
/*    */     //   400: astore 9
/*    */     //   402: aload 8
/*    */     //   404: athrow
/*    */     //   405: aload_2
/*    */     //   406: ifnull +23 -> 429
/*    */     //   409: aload_2
/*    */     //   410: iconst_1
/*    */     //   411: invokeinterface 252 2 0
/*    */     //   416: aload_2
/*    */     //   417: invokeinterface 229 1 0
/*    */     //   422: aconst_null
/*    */     //   423: astore_2
/*    */     //   424: goto +5 -> 429
/*    */     //   427: astore 9
/*    */     //   429: aload_3
/*    */     //   430: areturn
/*    */     // Line number table:
/*    */     //   Java source line #98	-> byte code offset #0
/*    */     //   Java source line #99	-> byte code offset #2
/*    */     //   Java source line #101	-> byte code offset #10
/*    */     //   Java source line #102	-> byte code offset #19
/*    */     //   Java source line #103	-> byte code offset #29
/*    */     //   Java source line #104	-> byte code offset #36
/*    */     //   Java source line #105	-> byte code offset #41
/*    */     //   Java source line #106	-> byte code offset #48
/*    */     //   Java source line #109	-> byte code offset #57
/*    */     //   Java source line #110	-> byte code offset #64
/*    */     //   Java source line #113	-> byte code offset #124
/*    */     //   Java source line #115	-> byte code offset #131
/*    */     //   Java source line #116	-> byte code offset #192
/*    */     //   Java source line #120	-> byte code offset #223
/*    */     //   Java source line #121	-> byte code offset #230
/*    */     //   Java source line #122	-> byte code offset #239
/*    */     //   Java source line #124	-> byte code offset #248
/*    */     //   Java source line #125	-> byte code offset #250
/*    */     //   Java source line #126	-> byte code offset #261
/*    */     //   Java source line #127	-> byte code offset #276
/*    */     //   Java source line #128	-> byte code offset #312
/*    */     //   Java source line #129	-> byte code offset #314
/*    */     //   Java source line #130	-> byte code offset #325
/*    */     //   Java source line #131	-> byte code offset #340
/*    */     //   Java source line #132	-> byte code offset #376
/*    */     //   Java source line #133	-> byte code offset #378
/*    */     //   Java source line #134	-> byte code offset #402
/*    */     //   Java source line #133	-> byte code offset #405
/*    */     //   Java source line #135	-> byte code offset #429
/*    */     // Local variable table:
/*    */     //   start	length	slot	name	signature
/*    */     //   0	431	0	this	MembresiaDAO
/*    */     //   0	431	1	membresiaTO	com.claro.transfer.membresia.MembresiaTO
/*    */     //   1	423	2	connection	java.sql.Connection
/*    */     //   9	421	3	mensajeTO	com.claro.transfer.MensajeTO
/*    */     //   17	176	4	puntosDAO	PuntosDAO
/*    */     //   248	59	4	e	java.sql.SQLException
/*    */     //   312	59	4	e	Exception
/*    */     //   39	157	5	fechaTransaccion	long
/*    */     //   274	1	5	localException1	Exception
/*    */     //   338	1	5	localException2	Exception
/*    */     //   190	8	7	referencia	String
/*    */     //   376	27	8	localObject	Object
/*    */     //   400	1	9	localException3	Exception
/*    */     //   427	1	9	localException4	Exception
/*    */     // Exception table:
/*    */     //   from	to	target	type
/*    */     //   10	245	248	java/sql/SQLException
/*    */     //   265	271	274	java/lang/Exception
/*    */     //   10	245	312	java/lang/Exception
/*    */     //   329	335	338	java/lang/Exception
/*    */     //   10	376	376	finally
/*    */     //   382	397	400	java/lang/Exception
/*    */     //   409	424	427	java/lang/Exception
/*    */   }
/*    */   
/*    */   /* Error */
/*    */   public com.claro.transfer.membresia.MembresiaTO consultaMembresia(String cuenta, int secuencia, java.util.Date fecha)
/*    */     throws com.claro.exception.CAException
/*    */   {
/*    */     // Byte code:
/*    */     //   0: aconst_null
/*    */     //   1: astore 4
/*    */     //   3: aconst_null
/*    */     //   4: astore 5
/*    */     //   6: aconst_null
/*    */     //   7: astore 6
/*    */     //   9: new 103	com/claro/transfer/membresia/MembresiaTO
/*    */     //   12: dup
/*    */     //   13: invokespecial 307	com/claro/transfer/membresia/MembresiaTO:<init>	()V
/*    */     //   16: astore 7
/*    */     //   18: new 71	java/lang/StringBuilder
/*    */     //   21: dup
/*    */     //   22: ldc_w 308
/*    */     //   25: invokespecial 75	java/lang/StringBuilder:<init>	(Ljava/lang/String;)V
/*    */     //   28: aload_0
/*    */     //   29: getfield 41	com/claro/dao/MembresiaDAO:schema_database	Ljava/lang/String;
/*    */     //   32: invokevirtual 78	java/lang/StringBuilder:append	(Ljava/lang/String;)Ljava/lang/StringBuilder;
/*    */     //   35: ldc_w 310
/*    */     //   38: invokevirtual 78	java/lang/StringBuilder:append	(Ljava/lang/String;)Ljava/lang/StringBuilder;
/*    */     //   41: ldc_w 312
/*    */     //   44: invokevirtual 78	java/lang/StringBuilder:append	(Ljava/lang/String;)Ljava/lang/StringBuilder;
/*    */     //   47: invokevirtual 92	java/lang/StringBuilder:toString	()Ljava/lang/String;
/*    */     //   50: astore 8
/*    */     //   52: invokestatic 29	com/claro/util/ServiceLocator:getInstance	()Lcom/claro/util/ServiceLocator;
/*    */     //   55: getstatic 64	com/claro/util/ServiceLocator:jdbcCirculoAzul	Ljava/lang/String;
/*    */     //   58: invokevirtual 67	com/claro/util/ServiceLocator:getConnection	(Ljava/lang/String;)Ljava/sql/Connection;
/*    */     //   61: astore 4
/*    */     //   63: aload 4
/*    */     //   65: aload 8
/*    */     //   67: invokeinterface 96 2 0
/*    */     //   72: astore 5
/*    */     //   74: aload 5
/*    */     //   76: iconst_1
/*    */     //   77: aload_1
/*    */     //   78: invokeinterface 107 3 0
/*    */     //   83: aload 5
/*    */     //   85: iconst_2
/*    */     //   86: iload_2
/*    */     //   87: invokeinterface 117 3 0
/*    */     //   92: aload_3
/*    */     //   93: ifnonnull +24 -> 117
/*    */     //   96: aload 5
/*    */     //   98: iconst_3
/*    */     //   99: new 178	java/sql/Date
/*    */     //   102: dup
/*    */     //   103: invokestatic 256	java/lang/System:currentTimeMillis	()J
/*    */     //   106: invokespecial 180	java/sql/Date:<init>	(J)V
/*    */     //   109: invokeinterface 183 3 0
/*    */     //   114: goto +22 -> 136
/*    */     //   117: aload 5
/*    */     //   119: iconst_3
/*    */     //   120: new 178	java/sql/Date
/*    */     //   123: dup
/*    */     //   124: aload_3
/*    */     //   125: invokevirtual 314	java/util/Date:getTime	()J
/*    */     //   128: invokespecial 180	java/sql/Date:<init>	(J)V
/*    */     //   131: invokeinterface 183 3 0
/*    */     //   136: aload 5
/*    */     //   138: invokeinterface 319 1 0
/*    */     //   143: astore 6
/*    */     //   145: aload 6
/*    */     //   147: invokeinterface 323 1 0
/*    */     //   152: ifeq +359 -> 511
/*    */     //   155: aload 7
/*    */     //   157: aload 6
/*    */     //   159: iconst_1
/*    */     //   160: invokeinterface 329 2 0
/*    */     //   165: invokevirtual 333	com/claro/transfer/membresia/MembresiaTO:setCuenta	(Ljava/lang/String;)V
/*    */     //   168: aload 7
/*    */     //   170: aload 6
/*    */     //   172: iconst_2
/*    */     //   173: invokeinterface 336 2 0
/*    */     //   178: invokevirtual 340	com/claro/transfer/membresia/MembresiaTO:setSecuencia	(I)V
/*    */     //   181: aload 7
/*    */     //   183: aload 6
/*    */     //   185: iconst_3
/*    */     //   186: invokeinterface 344 2 0
/*    */     //   191: invokevirtual 348	com/claro/transfer/membresia/MembresiaTO:setFechaOperacion	(Ljava/util/Date;)V
/*    */     //   194: aload 7
/*    */     //   196: aload 6
/*    */     //   198: iconst_4
/*    */     //   199: invokeinterface 329 2 0
/*    */     //   204: invokevirtual 352	com/claro/transfer/membresia/MembresiaTO:setNombreM2K	(Ljava/lang/String;)V
/*    */     //   207: aload 7
/*    */     //   209: aload 6
/*    */     //   211: iconst_5
/*    */     //   212: invokeinterface 329 2 0
/*    */     //   217: invokevirtual 355	com/claro/transfer/membresia/MembresiaTO:setFechaAltaM2K	(Ljava/lang/String;)V
/*    */     //   220: aload 7
/*    */     //   222: aload 6
/*    */     //   224: bipush 6
/*    */     //   226: invokeinterface 336 2 0
/*    */     //   231: invokevirtual 358	com/claro/transfer/membresia/MembresiaTO:setRegion	(I)V
/*    */     //   234: aload 7
/*    */     //   236: aload 6
/*    */     //   238: bipush 7
/*    */     //   240: invokeinterface 329 2 0
/*    */     //   245: invokevirtual 361	com/claro/transfer/membresia/MembresiaTO:setTelefono	(Ljava/lang/String;)V
/*    */     //   248: aload 7
/*    */     //   250: aload 6
/*    */     //   252: bipush 8
/*    */     //   254: invokeinterface 329 2 0
/*    */     //   259: invokevirtual 364	com/claro/transfer/membresia/MembresiaTO:setSegmento	(Ljava/lang/String;)V
/*    */     //   262: aload 7
/*    */     //   264: aload 6
/*    */     //   266: bipush 9
/*    */     //   268: invokeinterface 329 2 0
/*    */     //   273: invokevirtual 367	com/claro/transfer/membresia/MembresiaTO:setPlan	(Ljava/lang/String;)V
/*    */     //   276: aload 7
/*    */     //   278: aload 6
/*    */     //   280: bipush 10
/*    */     //   282: invokeinterface 329 2 0
/*    */     //   287: invokevirtual 370	com/claro/transfer/membresia/MembresiaTO:setDescPlan	(Ljava/lang/String;)V
/*    */     //   290: aload 7
/*    */     //   292: aload 6
/*    */     //   294: bipush 11
/*    */     //   296: invokeinterface 329 2 0
/*    */     //   301: invokevirtual 373	com/claro/transfer/membresia/MembresiaTO:setNombre	(Ljava/lang/String;)V
/*    */     //   304: aload 7
/*    */     //   306: aload 6
/*    */     //   308: bipush 12
/*    */     //   310: invokeinterface 329 2 0
/*    */     //   315: invokevirtual 376	com/claro/transfer/membresia/MembresiaTO:setApPaterno	(Ljava/lang/String;)V
/*    */     //   318: aload 7
/*    */     //   320: aload 6
/*    */     //   322: bipush 13
/*    */     //   324: invokeinterface 329 2 0
/*    */     //   329: invokevirtual 379	com/claro/transfer/membresia/MembresiaTO:setApMaterno	(Ljava/lang/String;)V
/*    */     //   332: aload 7
/*    */     //   334: aload 6
/*    */     //   336: bipush 14
/*    */     //   338: invokeinterface 329 2 0
/*    */     //   343: invokevirtual 382	com/claro/transfer/membresia/MembresiaTO:setTipoCalle	(Ljava/lang/String;)V
/*    */     //   346: aload 7
/*    */     //   348: aload 6
/*    */     //   350: bipush 15
/*    */     //   352: invokeinterface 329 2 0
/*    */     //   357: invokevirtual 385	com/claro/transfer/membresia/MembresiaTO:setCalle	(Ljava/lang/String;)V
/*    */     //   360: aload 7
/*    */     //   362: aload 6
/*    */     //   364: bipush 16
/*    */     //   366: invokeinterface 329 2 0
/*    */     //   371: invokevirtual 388	com/claro/transfer/membresia/MembresiaTO:setNumExterior	(Ljava/lang/String;)V
/*    */     //   374: aload 7
/*    */     //   376: aload 6
/*    */     //   378: bipush 17
/*    */     //   380: invokeinterface 329 2 0
/*    */     //   385: invokevirtual 391	com/claro/transfer/membresia/MembresiaTO:setNumInterior	(Ljava/lang/String;)V
/*    */     //   388: aload 7
/*    */     //   390: aload 6
/*    */     //   392: bipush 18
/*    */     //   394: invokeinterface 329 2 0
/*    */     //   399: invokevirtual 394	com/claro/transfer/membresia/MembresiaTO:setColonia	(Ljava/lang/String;)V
/*    */     //   402: aload 7
/*    */     //   404: aload 6
/*    */     //   406: bipush 19
/*    */     //   408: invokeinterface 329 2 0
/*    */     //   413: invokevirtual 397	com/claro/transfer/membresia/MembresiaTO:setCiudad	(Ljava/lang/String;)V
/*    */     //   416: aload 7
/*    */     //   418: aload 6
/*    */     //   420: bipush 20
/*    */     //   422: invokeinterface 329 2 0
/*    */     //   427: invokevirtual 400	com/claro/transfer/membresia/MembresiaTO:setEstado	(Ljava/lang/String;)V
/*    */     //   430: aload 7
/*    */     //   432: aload 6
/*    */     //   434: bipush 21
/*    */     //   436: invokeinterface 329 2 0
/*    */     //   441: invokevirtual 403	com/claro/transfer/membresia/MembresiaTO:setCodigoPostal	(Ljava/lang/String;)V
/*    */     //   444: aload 7
/*    */     //   446: aload 6
/*    */     //   448: bipush 22
/*    */     //   450: invokeinterface 329 2 0
/*    */     //   455: invokevirtual 406	com/claro/transfer/membresia/MembresiaTO:setUsuario	(Ljava/lang/String;)V
/*    */     //   458: aload 7
/*    */     //   460: aload 6
/*    */     //   462: bipush 23
/*    */     //   464: invokeinterface 329 2 0
/*    */     //   469: invokevirtual 264	com/claro/transfer/membresia/MembresiaTO:setEstatus	(Ljava/lang/String;)V
/*    */     //   472: aload 7
/*    */     //   474: aload 6
/*    */     //   476: bipush 24
/*    */     //   478: invokeinterface 329 2 0
/*    */     //   483: invokevirtual 409	com/claro/transfer/membresia/MembresiaTO:setMotivo	(Ljava/lang/String;)V
/*    */     //   486: aload 7
/*    */     //   488: aload 6
/*    */     //   490: bipush 25
/*    */     //   492: invokeinterface 336 2 0
/*    */     //   497: invokevirtual 412	com/claro/transfer/membresia/MembresiaTO:setCosto	(I)V
/*    */     //   500: aload 7
/*    */     //   502: iconst_0
/*    */     //   503: ldc -57
/*    */     //   505: invokevirtual 415	com/claro/transfer/membresia/MembresiaTO:agregaMensaje	(ILjava/lang/String;)V
/*    */     //   508: goto +181 -> 689
/*    */     //   511: aload 7
/*    */     //   513: iconst_1
/*    */     //   514: ldc_w 416
/*    */     //   517: invokevirtual 415	com/claro/transfer/membresia/MembresiaTO:agregaMensaje	(ILjava/lang/String;)V
/*    */     //   520: goto +169 -> 689
/*    */     //   523: astore 8
/*    */     //   525: aload_0
/*    */     //   526: getfield 27	com/claro/dao/MembresiaDAO:error	Lorg/apache/log4j/Logger;
/*    */     //   529: ldc_w 418
/*    */     //   532: aload 8
/*    */     //   534: invokevirtual 208	org/apache/log4j/Logger:info	(Ljava/lang/Object;Ljava/lang/Throwable;)V
/*    */     //   537: new 59	com/claro/exception/CAException
/*    */     //   540: dup
/*    */     //   541: iconst_m1
/*    */     //   542: new 71	java/lang/StringBuilder
/*    */     //   545: dup
/*    */     //   546: ldc -45
/*    */     //   548: invokespecial 75	java/lang/StringBuilder:<init>	(Ljava/lang/String;)V
/*    */     //   551: aload 8
/*    */     //   553: invokevirtual 213	java/sql/SQLException:toString	()Ljava/lang/String;
/*    */     //   556: invokevirtual 78	java/lang/StringBuilder:append	(Ljava/lang/String;)Ljava/lang/StringBuilder;
/*    */     //   559: ldc -40
/*    */     //   561: invokevirtual 78	java/lang/StringBuilder:append	(Ljava/lang/String;)Ljava/lang/StringBuilder;
/*    */     //   564: invokevirtual 92	java/lang/StringBuilder:toString	()Ljava/lang/String;
/*    */     //   567: aload 8
/*    */     //   569: invokespecial 218	com/claro/exception/CAException:<init>	(ILjava/lang/String;Ljava/lang/Exception;)V
/*    */     //   572: athrow
/*    */     //   573: astore 8
/*    */     //   575: aload_0
/*    */     //   576: getfield 27	com/claro/dao/MembresiaDAO:error	Lorg/apache/log4j/Logger;
/*    */     //   579: ldc_w 420
/*    */     //   582: aload 8
/*    */     //   584: invokevirtual 208	org/apache/log4j/Logger:info	(Ljava/lang/Object;Ljava/lang/Throwable;)V
/*    */     //   587: new 59	com/claro/exception/CAException
/*    */     //   590: dup
/*    */     //   591: iconst_m1
/*    */     //   592: new 71	java/lang/StringBuilder
/*    */     //   595: dup
/*    */     //   596: ldc_w 422
/*    */     //   599: invokespecial 75	java/lang/StringBuilder:<init>	(Ljava/lang/String;)V
/*    */     //   602: aload 8
/*    */     //   604: invokevirtual 225	java/lang/Exception:toString	()Ljava/lang/String;
/*    */     //   607: invokevirtual 78	java/lang/StringBuilder:append	(Ljava/lang/String;)Ljava/lang/StringBuilder;
/*    */     //   610: ldc -40
/*    */     //   612: invokevirtual 78	java/lang/StringBuilder:append	(Ljava/lang/String;)Ljava/lang/StringBuilder;
/*    */     //   615: invokevirtual 92	java/lang/StringBuilder:toString	()Ljava/lang/String;
/*    */     //   618: aload 8
/*    */     //   620: invokespecial 218	com/claro/exception/CAException:<init>	(ILjava/lang/String;Ljava/lang/Exception;)V
/*    */     //   623: athrow
/*    */     //   624: astore 9
/*    */     //   626: aload 6
/*    */     //   628: ifnull +18 -> 646
/*    */     //   631: aload 6
/*    */     //   633: invokeinterface 424 1 0
/*    */     //   638: aconst_null
/*    */     //   639: astore 6
/*    */     //   641: goto +5 -> 646
/*    */     //   644: astore 10
/*    */     //   646: aload 5
/*    */     //   648: ifnull +18 -> 666
/*    */     //   651: aload 5
/*    */     //   653: invokeinterface 226 1 0
/*    */     //   658: aconst_null
/*    */     //   659: astore 5
/*    */     //   661: goto +5 -> 666
/*    */     //   664: astore 10
/*    */     //   666: aload 4
/*    */     //   668: ifnull +18 -> 686
/*    */     //   671: aload 4
/*    */     //   673: invokeinterface 229 1 0
/*    */     //   678: aconst_null
/*    */     //   679: astore 4
/*    */     //   681: goto +5 -> 686
/*    */     //   684: astore 10
/*    */     //   686: aload 9
/*    */     //   688: athrow
/*    */     //   689: aload 6
/*    */     //   691: ifnull +18 -> 709
/*    */     //   694: aload 6
/*    */     //   696: invokeinterface 424 1 0
/*    */     //   701: aconst_null
/*    */     //   702: astore 6
/*    */     //   704: goto +5 -> 709
/*    */     //   707: astore 10
/*    */     //   709: aload 5
/*    */     //   711: ifnull +18 -> 729
/*    */     //   714: aload 5
/*    */     //   716: invokeinterface 226 1 0
/*    */     //   721: aconst_null
/*    */     //   722: astore 5
/*    */     //   724: goto +5 -> 729
/*    */     //   727: astore 10
/*    */     //   729: aload 4
/*    */     //   731: ifnull +18 -> 749
/*    */     //   734: aload 4
/*    */     //   736: invokeinterface 229 1 0
/*    */     //   741: aconst_null
/*    */     //   742: astore 4
/*    */     //   744: goto +5 -> 749
/*    */     //   747: astore 10
/*    */     //   749: aload 7
/*    */     //   751: areturn
/*    */     // Line number table:
/*    */     //   Java source line #139	-> byte code offset #0
/*    */     //   Java source line #140	-> byte code offset #3
/*    */     //   Java source line #141	-> byte code offset #6
/*    */     //   Java source line #142	-> byte code offset #9
/*    */     //   Java source line #144	-> byte code offset #18
/*    */     //   Java source line #145	-> byte code offset #28
/*    */     //   Java source line #146	-> byte code offset #41
/*    */     //   Java source line #144	-> byte code offset #47
/*    */     //   Java source line #147	-> byte code offset #52
/*    */     //   Java source line #148	-> byte code offset #63
/*    */     //   Java source line #149	-> byte code offset #74
/*    */     //   Java source line #150	-> byte code offset #83
/*    */     //   Java source line #151	-> byte code offset #92
/*    */     //   Java source line #152	-> byte code offset #96
/*    */     //   Java source line #153	-> byte code offset #117
/*    */     //   Java source line #154	-> byte code offset #136
/*    */     //   Java source line #155	-> byte code offset #145
/*    */     //   Java source line #156	-> byte code offset #155
/*    */     //   Java source line #157	-> byte code offset #168
/*    */     //   Java source line #158	-> byte code offset #181
/*    */     //   Java source line #159	-> byte code offset #194
/*    */     //   Java source line #160	-> byte code offset #207
/*    */     //   Java source line #161	-> byte code offset #220
/*    */     //   Java source line #162	-> byte code offset #234
/*    */     //   Java source line #163	-> byte code offset #248
/*    */     //   Java source line #164	-> byte code offset #262
/*    */     //   Java source line #165	-> byte code offset #276
/*    */     //   Java source line #166	-> byte code offset #290
/*    */     //   Java source line #167	-> byte code offset #304
/*    */     //   Java source line #168	-> byte code offset #318
/*    */     //   Java source line #169	-> byte code offset #332
/*    */     //   Java source line #170	-> byte code offset #346
/*    */     //   Java source line #171	-> byte code offset #360
/*    */     //   Java source line #172	-> byte code offset #374
/*    */     //   Java source line #173	-> byte code offset #388
/*    */     //   Java source line #174	-> byte code offset #402
/*    */     //   Java source line #175	-> byte code offset #416
/*    */     //   Java source line #176	-> byte code offset #430
/*    */     //   Java source line #177	-> byte code offset #444
/*    */     //   Java source line #178	-> byte code offset #458
/*    */     //   Java source line #179	-> byte code offset #472
/*    */     //   Java source line #180	-> byte code offset #486
/*    */     //   Java source line #181	-> byte code offset #500
/*    */     //   Java source line #182	-> byte code offset #511
/*    */     //   Java source line #184	-> byte code offset #523
/*    */     //   Java source line #185	-> byte code offset #525
/*    */     //   Java source line #186	-> byte code offset #537
/*    */     //   Java source line #187	-> byte code offset #573
/*    */     //   Java source line #188	-> byte code offset #575
/*    */     //   Java source line #189	-> byte code offset #587
/*    */     //   Java source line #190	-> byte code offset #624
/*    */     //   Java source line #191	-> byte code offset #626
/*    */     //   Java source line #192	-> byte code offset #646
/*    */     //   Java source line #193	-> byte code offset #666
/*    */     //   Java source line #194	-> byte code offset #686
/*    */     //   Java source line #191	-> byte code offset #689
/*    */     //   Java source line #192	-> byte code offset #709
/*    */     //   Java source line #193	-> byte code offset #729
/*    */     //   Java source line #195	-> byte code offset #749
/*    */     // Local variable table:
/*    */     //   start	length	slot	name	signature
/*    */     //   0	752	0	this	MembresiaDAO
/*    */     //   0	752	1	cuenta	String
/*    */     //   0	752	2	secuencia	int
/*    */     //   0	752	3	fecha	java.util.Date
/*    */     //   1	742	4	connection	java.sql.Connection
/*    */     //   4	719	5	statement	java.sql.PreparedStatement
/*    */     //   7	696	6	resultSet	java.sql.ResultSet
/*    */     //   16	734	7	membresiaTO	com.claro.transfer.membresia.MembresiaTO
/*    */     //   50	16	8	sQuery	String
/*    */     //   523	45	8	e	java.sql.SQLException
/*    */     //   573	46	8	e	Exception
/*    */     //   624	63	9	localObject	Object
/*    */     //   644	1	10	localException1	Exception
/*    */     //   664	1	10	localException2	Exception
/*    */     //   684	1	10	localException3	Exception
/*    */     //   707	1	10	localException4	Exception
/*    */     //   727	1	10	localException5	Exception
/*    */     //   747	1	10	localException6	Exception
/*    */     // Exception table:
/*    */     //   from	to	target	type
/*    */     //   18	520	523	java/sql/SQLException
/*    */     //   18	520	573	java/lang/Exception
/*    */     //   18	624	624	finally
/*    */     //   631	641	644	java/lang/Exception
/*    */     //   651	661	664	java/lang/Exception
/*    */     //   671	681	684	java/lang/Exception
/*    */     //   694	704	707	java/lang/Exception
/*    */     //   714	724	727	java/lang/Exception
/*    */     //   734	744	747	java/lang/Exception
/*    */   }
/*    */   
/*    */   /* Error */
/*    */   public java.util.ArrayList<com.claro.transfer.membresia.MembresiaTO> depuracionMembresia(java.util.ArrayList<com.claro.transfer.membresia.MembresiaTO> arregloMembresiaTO)
/*    */     throws com.claro.exception.CAException
/*    */   {
/*    */     // Byte code:
/*    */     //   0: aconst_null
/*    */     //   1: astore_2
/*    */     //   2: aconst_null
/*    */     //   3: astore_3
/*    */     //   4: new 437	java/util/ArrayList
/*    */     //   7: dup
/*    */     //   8: invokespecial 439	java/util/ArrayList:<init>	()V
/*    */     //   11: astore 4
/*    */     //   13: aload_1
/*    */     //   14: invokevirtual 440	java/util/ArrayList:listIterator	()Ljava/util/ListIterator;
/*    */     //   17: astore 5
/*    */     //   19: invokestatic 29	com/claro/util/ServiceLocator:getInstance	()Lcom/claro/util/ServiceLocator;
/*    */     //   22: getstatic 64	com/claro/util/ServiceLocator:jdbcCirculoAzul	Ljava/lang/String;
/*    */     //   25: invokevirtual 67	com/claro/util/ServiceLocator:getConnection	(Ljava/lang/String;)Ljava/sql/Connection;
/*    */     //   28: astore_2
/*    */     //   29: goto +208 -> 237
/*    */     //   32: aload 5
/*    */     //   34: invokeinterface 444 1 0
/*    */     //   39: checkcast 103	com/claro/transfer/membresia/MembresiaTO
/*    */     //   42: astore 6
/*    */     //   44: new 71	java/lang/StringBuilder
/*    */     //   47: dup
/*    */     //   48: ldc_w 449
/*    */     //   51: invokespecial 75	java/lang/StringBuilder:<init>	(Ljava/lang/String;)V
/*    */     //   54: aload_0
/*    */     //   55: getfield 41	com/claro/dao/MembresiaDAO:schema_database	Ljava/lang/String;
/*    */     //   58: invokevirtual 78	java/lang/StringBuilder:append	(Ljava/lang/String;)Ljava/lang/StringBuilder;
/*    */     //   61: ldc_w 451
/*    */     //   64: invokevirtual 78	java/lang/StringBuilder:append	(Ljava/lang/String;)Ljava/lang/StringBuilder;
/*    */     //   67: aload_0
/*    */     //   68: getfield 41	com/claro/dao/MembresiaDAO:schema_database	Ljava/lang/String;
/*    */     //   71: invokevirtual 78	java/lang/StringBuilder:append	(Ljava/lang/String;)Ljava/lang/StringBuilder;
/*    */     //   74: ldc_w 453
/*    */     //   77: invokevirtual 78	java/lang/StringBuilder:append	(Ljava/lang/String;)Ljava/lang/StringBuilder;
/*    */     //   80: aload_0
/*    */     //   81: getfield 41	com/claro/dao/MembresiaDAO:schema_database	Ljava/lang/String;
/*    */     //   84: invokevirtual 78	java/lang/StringBuilder:append	(Ljava/lang/String;)Ljava/lang/StringBuilder;
/*    */     //   87: ldc_w 455
/*    */     //   90: invokevirtual 78	java/lang/StringBuilder:append	(Ljava/lang/String;)Ljava/lang/StringBuilder;
/*    */     //   93: aload_0
/*    */     //   94: getfield 41	com/claro/dao/MembresiaDAO:schema_database	Ljava/lang/String;
/*    */     //   97: invokevirtual 78	java/lang/StringBuilder:append	(Ljava/lang/String;)Ljava/lang/StringBuilder;
/*    */     //   100: ldc_w 457
/*    */     //   103: invokevirtual 78	java/lang/StringBuilder:append	(Ljava/lang/String;)Ljava/lang/StringBuilder;
/*    */     //   106: ldc_w 459
/*    */     //   109: invokevirtual 78	java/lang/StringBuilder:append	(Ljava/lang/String;)Ljava/lang/StringBuilder;
/*    */     //   112: ldc_w 461
/*    */     //   115: invokevirtual 78	java/lang/StringBuilder:append	(Ljava/lang/String;)Ljava/lang/StringBuilder;
/*    */     //   118: ldc_w 463
/*    */     //   121: invokevirtual 78	java/lang/StringBuilder:append	(Ljava/lang/String;)Ljava/lang/StringBuilder;
/*    */     //   124: ldc_w 465
/*    */     //   127: invokevirtual 78	java/lang/StringBuilder:append	(Ljava/lang/String;)Ljava/lang/StringBuilder;
/*    */     //   130: invokevirtual 92	java/lang/StringBuilder:toString	()Ljava/lang/String;
/*    */     //   133: astore 7
/*    */     //   135: aload_2
/*    */     //   136: aload 7
/*    */     //   138: invokeinterface 96 2 0
/*    */     //   143: astore_3
/*    */     //   144: aload_3
/*    */     //   145: iconst_1
/*    */     //   146: aload 6
/*    */     //   148: invokevirtual 102	com/claro/transfer/membresia/MembresiaTO:getCuenta	()Ljava/lang/String;
/*    */     //   151: invokeinterface 107 3 0
/*    */     //   156: aload_3
/*    */     //   157: iconst_2
/*    */     //   158: aload 6
/*    */     //   160: invokevirtual 113	com/claro/transfer/membresia/MembresiaTO:getSecuencia	()I
/*    */     //   163: invokeinterface 117 3 0
/*    */     //   168: aload_3
/*    */     //   169: invokeinterface 319 1 0
/*    */     //   174: astore 8
/*    */     //   176: aload 8
/*    */     //   178: invokeinterface 323 1 0
/*    */     //   183: ifeq +35 -> 218
/*    */     //   186: aload 6
/*    */     //   188: aload 8
/*    */     //   190: iconst_3
/*    */     //   191: invokeinterface 329 2 0
/*    */     //   196: invokevirtual 367	com/claro/transfer/membresia/MembresiaTO:setPlan	(Ljava/lang/String;)V
/*    */     //   199: aload 4
/*    */     //   201: aload 6
/*    */     //   203: invokevirtual 467	java/util/ArrayList:add	(Ljava/lang/Object;)Z
/*    */     //   206: pop
/*    */     //   207: aload 6
/*    */     //   209: iconst_0
/*    */     //   210: ldc -57
/*    */     //   212: invokevirtual 415	com/claro/transfer/membresia/MembresiaTO:agregaMensaje	(ILjava/lang/String;)V
/*    */     //   215: goto +12 -> 227
/*    */     //   218: aload 6
/*    */     //   220: iconst_1
/*    */     //   221: ldc_w 471
/*    */     //   224: invokevirtual 415	com/claro/transfer/membresia/MembresiaTO:agregaMensaje	(ILjava/lang/String;)V
/*    */     //   227: aload 8
/*    */     //   229: invokeinterface 424 1 0
/*    */     //   234: aconst_null
/*    */     //   235: astore 8
/*    */     //   237: aload 5
/*    */     //   239: invokeinterface 473 1 0
/*    */     //   244: ifne -212 -> 32
/*    */     //   247: goto +146 -> 393
/*    */     //   250: astore 5
/*    */     //   252: aload_0
/*    */     //   253: getfield 27	com/claro/dao/MembresiaDAO:error	Lorg/apache/log4j/Logger;
/*    */     //   256: ldc_w 476
/*    */     //   259: aload 5
/*    */     //   261: invokevirtual 208	org/apache/log4j/Logger:info	(Ljava/lang/Object;Ljava/lang/Throwable;)V
/*    */     //   264: new 59	com/claro/exception/CAException
/*    */     //   267: dup
/*    */     //   268: iconst_m1
/*    */     //   269: new 71	java/lang/StringBuilder
/*    */     //   272: dup
/*    */     //   273: ldc_w 478
/*    */     //   276: invokespecial 75	java/lang/StringBuilder:<init>	(Ljava/lang/String;)V
/*    */     //   279: aload 5
/*    */     //   281: invokevirtual 213	java/sql/SQLException:toString	()Ljava/lang/String;
/*    */     //   284: invokevirtual 78	java/lang/StringBuilder:append	(Ljava/lang/String;)Ljava/lang/StringBuilder;
/*    */     //   287: ldc_w 480
/*    */     //   290: invokevirtual 78	java/lang/StringBuilder:append	(Ljava/lang/String;)Ljava/lang/StringBuilder;
/*    */     //   293: invokevirtual 92	java/lang/StringBuilder:toString	()Ljava/lang/String;
/*    */     //   296: aload 5
/*    */     //   298: invokespecial 218	com/claro/exception/CAException:<init>	(ILjava/lang/String;Ljava/lang/Exception;)V
/*    */     //   301: athrow
/*    */     //   302: astore 5
/*    */     //   304: aload_0
/*    */     //   305: getfield 27	com/claro/dao/MembresiaDAO:error	Lorg/apache/log4j/Logger;
/*    */     //   308: ldc_w 482
/*    */     //   311: aload 5
/*    */     //   313: invokevirtual 208	org/apache/log4j/Logger:info	(Ljava/lang/Object;Ljava/lang/Throwable;)V
/*    */     //   316: new 59	com/claro/exception/CAException
/*    */     //   319: dup
/*    */     //   320: iconst_m1
/*    */     //   321: new 71	java/lang/StringBuilder
/*    */     //   324: dup
/*    */     //   325: ldc_w 484
/*    */     //   328: invokespecial 75	java/lang/StringBuilder:<init>	(Ljava/lang/String;)V
/*    */     //   331: aload 5
/*    */     //   333: invokevirtual 225	java/lang/Exception:toString	()Ljava/lang/String;
/*    */     //   336: invokevirtual 78	java/lang/StringBuilder:append	(Ljava/lang/String;)Ljava/lang/StringBuilder;
/*    */     //   339: ldc_w 480
/*    */     //   342: invokevirtual 78	java/lang/StringBuilder:append	(Ljava/lang/String;)Ljava/lang/StringBuilder;
/*    */     //   345: invokevirtual 92	java/lang/StringBuilder:toString	()Ljava/lang/String;
/*    */     //   348: aload 5
/*    */     //   350: invokespecial 218	com/claro/exception/CAException:<init>	(ILjava/lang/String;Ljava/lang/Exception;)V
/*    */     //   353: athrow
/*    */     //   354: astore 9
/*    */     //   356: aload_3
/*    */     //   357: ifnull +16 -> 373
/*    */     //   360: aload_3
/*    */     //   361: invokeinterface 226 1 0
/*    */     //   366: aconst_null
/*    */     //   367: astore_3
/*    */     //   368: goto +5 -> 373
/*    */     //   371: astore 10
/*    */     //   373: aload_2
/*    */     //   374: ifnull +16 -> 390
/*    */     //   377: aload_2
/*    */     //   378: invokeinterface 229 1 0
/*    */     //   383: aconst_null
/*    */     //   384: astore_2
/*    */     //   385: goto +5 -> 390
/*    */     //   388: astore 10
/*    */     //   390: aload 9
/*    */     //   392: athrow
/*    */     //   393: aload_3
/*    */     //   394: ifnull +16 -> 410
/*    */     //   397: aload_3
/*    */     //   398: invokeinterface 226 1 0
/*    */     //   403: aconst_null
/*    */     //   404: astore_3
/*    */     //   405: goto +5 -> 410
/*    */     //   408: astore 10
/*    */     //   410: aload_2
/*    */     //   411: ifnull +16 -> 427
/*    */     //   414: aload_2
/*    */     //   415: invokeinterface 229 1 0
/*    */     //   420: aconst_null
/*    */     //   421: astore_2
/*    */     //   422: goto +5 -> 427
/*    */     //   425: astore 10
/*    */     //   427: aload 4
/*    */     //   429: areturn
/*    */     // Line number table:
/*    */     //   Java source line #200	-> byte code offset #0
/*    */     //   Java source line #201	-> byte code offset #2
/*    */     //   Java source line #203	-> byte code offset #4
/*    */     //   Java source line #207	-> byte code offset #13
/*    */     //   Java source line #208	-> byte code offset #19
/*    */     //   Java source line #210	-> byte code offset #29
/*    */     //   Java source line #211	-> byte code offset #32
/*    */     //   Java source line #214	-> byte code offset #44
/*    */     //   Java source line #215	-> byte code offset #54
/*    */     //   Java source line #216	-> byte code offset #80
/*    */     //   Java source line #217	-> byte code offset #106
/*    */     //   Java source line #218	-> byte code offset #112
/*    */     //   Java source line #219	-> byte code offset #118
/*    */     //   Java source line #220	-> byte code offset #124
/*    */     //   Java source line #214	-> byte code offset #130
/*    */     //   Java source line #223	-> byte code offset #135
/*    */     //   Java source line #224	-> byte code offset #144
/*    */     //   Java source line #225	-> byte code offset #156
/*    */     //   Java source line #227	-> byte code offset #168
/*    */     //   Java source line #228	-> byte code offset #176
/*    */     //   Java source line #229	-> byte code offset #186
/*    */     //   Java source line #230	-> byte code offset #199
/*    */     //   Java source line #231	-> byte code offset #207
/*    */     //   Java source line #233	-> byte code offset #218
/*    */     //   Java source line #235	-> byte code offset #227
/*    */     //   Java source line #236	-> byte code offset #234
/*    */     //   Java source line #210	-> byte code offset #237
/*    */     //   Java source line #238	-> byte code offset #250
/*    */     //   Java source line #239	-> byte code offset #252
/*    */     //   Java source line #240	-> byte code offset #264
/*    */     //   Java source line #241	-> byte code offset #302
/*    */     //   Java source line #242	-> byte code offset #304
/*    */     //   Java source line #243	-> byte code offset #316
/*    */     //   Java source line #244	-> byte code offset #354
/*    */     //   Java source line #245	-> byte code offset #356
/*    */     //   Java source line #246	-> byte code offset #373
/*    */     //   Java source line #247	-> byte code offset #390
/*    */     //   Java source line #245	-> byte code offset #393
/*    */     //   Java source line #246	-> byte code offset #410
/*    */     //   Java source line #248	-> byte code offset #427
/*    */     // Local variable table:
/*    */     //   start	length	slot	name	signature
/*    */     //   0	430	0	this	MembresiaDAO
/*    */     //   0	430	1	arregloMembresiaTO	java.util.ArrayList<com.claro.transfer.membresia.MembresiaTO>
/*    */     //   1	421	2	connection	java.sql.Connection
/*    */     //   3	402	3	statement	java.sql.PreparedStatement
/*    */     //   11	417	4	arregloMembresias	java.util.ArrayList<com.claro.transfer.membresia.MembresiaTO>
/*    */     //   17	221	5	iterator	java.util.ListIterator<com.claro.transfer.membresia.MembresiaTO>
/*    */     //   250	47	5	e	java.sql.SQLException
/*    */     //   302	47	5	e	Exception
/*    */     //   42	177	6	membresiaTO	com.claro.transfer.membresia.MembresiaTO
/*    */     //   133	4	7	sQuery	String
/*    */     //   174	62	8	resultSet	java.sql.ResultSet
/*    */     //   354	37	9	localObject	Object
/*    */     //   371	1	10	localException1	Exception
/*    */     //   388	1	10	localException2	Exception
/*    */     //   408	1	10	localException3	Exception
/*    */     //   425	1	10	localException4	Exception
/*    */     // Exception table:
/*    */     //   from	to	target	type
/*    */     //   13	247	250	java/sql/SQLException
/*    */     //   13	247	302	java/lang/Exception
/*    */     //   13	354	354	finally
/*    */     //   360	368	371	java/lang/Exception
/*    */     //   377	385	388	java/lang/Exception
/*    */     //   397	405	408	java/lang/Exception
/*    */     //   414	422	425	java/lang/Exception
/*    */   }
/*    */   
/*    */   /* Error */
/*    */   public boolean listaMembresia(java.util.ArrayList<com.claro.transfer.membresia.MembresiaTO> membresias, int idRegion)
/*    */     throws com.claro.exception.CAException
/*    */   {
/*    */     // Byte code:
/*    */     //   0: new 71	java/lang/StringBuilder
/*    */     //   3: dup
/*    */     //   4: ldc_w 497
/*    */     //   7: invokespecial 75	java/lang/StringBuilder:<init>	(Ljava/lang/String;)V
/*    */     //   10: iload_2
/*    */     //   11: invokevirtual 499	java/lang/StringBuilder:append	(I)Ljava/lang/StringBuilder;
/*    */     //   14: ldc_w 502
/*    */     //   17: invokevirtual 78	java/lang/StringBuilder:append	(Ljava/lang/String;)Ljava/lang/StringBuilder;
/*    */     //   20: invokevirtual 92	java/lang/StringBuilder:toString	()Ljava/lang/String;
/*    */     //   23: astore_3
/*    */     //   24: aconst_null
/*    */     //   25: astore 4
/*    */     //   27: iconst_0
/*    */     //   28: istore 5
/*    */     //   30: new 504	java/io/FileOutputStream
/*    */     //   33: dup
/*    */     //   34: aload_3
/*    */     //   35: invokespecial 506	java/io/FileOutputStream:<init>	(Ljava/lang/String;)V
/*    */     //   38: astore 4
/*    */     //   40: new 507	com/claro/dao/ConsultaCuentasCorreoDAO
/*    */     //   43: dup
/*    */     //   44: invokespecial 509	com/claro/dao/ConsultaCuentasCorreoDAO:<init>	()V
/*    */     //   47: astore 6
/*    */     //   49: aload 6
/*    */     //   51: bipush 8
/*    */     //   53: invokevirtual 510	com/claro/dao/ConsultaCuentasCorreoDAO:obtieneCuentasCorreoCargaCatalogos	(I)Ljava/util/Map;
/*    */     //   56: astore 7
/*    */     //   58: new 437	java/util/ArrayList
/*    */     //   61: dup
/*    */     //   62: invokespecial 439	java/util/ArrayList:<init>	()V
/*    */     //   65: astore 8
/*    */     //   67: aload_0
/*    */     //   68: aload_1
/*    */     //   69: invokevirtual 514	com/claro/dao/MembresiaDAO:depuracionMembresia	(Ljava/util/ArrayList;)Ljava/util/ArrayList;
/*    */     //   72: astore 8
/*    */     //   74: aload 8
/*    */     //   76: invokevirtual 516	java/util/ArrayList:size	()I
/*    */     //   79: ifgt +33 -> 112
/*    */     //   82: aload 7
/*    */     //   84: ldc_w 519
/*    */     //   87: ldc_w 521
/*    */     //   90: aconst_null
/*    */     //   91: invokestatic 523	com/claro/util/Utils:enviaCorreo	(Ljava/util/Map;Ljava/lang/String;Ljava/lang/String;Ljava/util/List;)Z
/*    */     //   94: pop
/*    */     //   95: aload 4
/*    */     //   97: ifnull +13 -> 110
/*    */     //   100: aload 4
/*    */     //   102: invokevirtual 529	java/io/FileOutputStream:close	()V
/*    */     //   105: goto +5 -> 110
/*    */     //   108: astore 13
/*    */     //   110: iconst_0
/*    */     //   111: ireturn
/*    */     //   112: new 530	java/io/PrintStream
/*    */     //   115: dup
/*    */     //   116: aload 4
/*    */     //   118: invokespecial 532	java/io/PrintStream:<init>	(Ljava/io/OutputStream;)V
/*    */     //   121: astore 9
/*    */     //   123: aload 8
/*    */     //   125: invokevirtual 440	java/util/ArrayList:listIterator	()Ljava/util/ListIterator;
/*    */     //   128: astore 10
/*    */     //   130: goto +86 -> 216
/*    */     //   133: aload 10
/*    */     //   135: invokeinterface 444 1 0
/*    */     //   140: checkcast 103	com/claro/transfer/membresia/MembresiaTO
/*    */     //   143: astore 11
/*    */     //   145: aload 9
/*    */     //   147: new 71	java/lang/StringBuilder
/*    */     //   150: dup
/*    */     //   151: aload 11
/*    */     //   153: invokevirtual 130	com/claro/transfer/membresia/MembresiaTO:getTelefono	()Ljava/lang/String;
/*    */     //   156: invokestatic 535	java/lang/String:valueOf	(Ljava/lang/Object;)Ljava/lang/String;
/*    */     //   159: invokespecial 75	java/lang/StringBuilder:<init>	(Ljava/lang/String;)V
/*    */     //   162: ldc_w 539
/*    */     //   165: invokevirtual 78	java/lang/StringBuilder:append	(Ljava/lang/String;)Ljava/lang/StringBuilder;
/*    */     //   168: aload 11
/*    */     //   170: invokevirtual 102	com/claro/transfer/membresia/MembresiaTO:getCuenta	()Ljava/lang/String;
/*    */     //   173: invokevirtual 78	java/lang/StringBuilder:append	(Ljava/lang/String;)Ljava/lang/StringBuilder;
/*    */     //   176: ldc_w 539
/*    */     //   179: invokevirtual 78	java/lang/StringBuilder:append	(Ljava/lang/String;)Ljava/lang/StringBuilder;
/*    */     //   182: aload 11
/*    */     //   184: invokevirtual 145	com/claro/transfer/membresia/MembresiaTO:getApPaterno	()Ljava/lang/String;
/*    */     //   187: invokevirtual 541	java/lang/String:trim	()Ljava/lang/String;
/*    */     //   190: invokevirtual 78	java/lang/StringBuilder:append	(Ljava/lang/String;)Ljava/lang/StringBuilder;
/*    */     //   193: ldc_w 286
/*    */     //   196: invokevirtual 78	java/lang/StringBuilder:append	(Ljava/lang/String;)Ljava/lang/StringBuilder;
/*    */     //   199: aload 11
/*    */     //   201: invokevirtual 148	com/claro/transfer/membresia/MembresiaTO:getApMaterno	()Ljava/lang/String;
/*    */     //   204: invokevirtual 541	java/lang/String:trim	()Ljava/lang/String;
/*    */     //   207: invokevirtual 78	java/lang/StringBuilder:append	(Ljava/lang/String;)Ljava/lang/StringBuilder;
/*    */     //   210: invokevirtual 92	java/lang/StringBuilder:toString	()Ljava/lang/String;
/*    */     //   213: invokevirtual 544	java/io/PrintStream:println	(Ljava/lang/String;)V
/*    */     //   216: aload 10
/*    */     //   218: invokeinterface 473 1 0
/*    */     //   223: ifne -90 -> 133
/*    */     //   226: aload 9
/*    */     //   228: invokevirtual 547	java/io/PrintStream:flush	()V
/*    */     //   231: new 437	java/util/ArrayList
/*    */     //   234: dup
/*    */     //   235: invokespecial 439	java/util/ArrayList:<init>	()V
/*    */     //   238: astore 11
/*    */     //   240: aload 11
/*    */     //   242: aload_3
/*    */     //   243: invokeinterface 550 2 0
/*    */     //   248: pop
/*    */     //   249: aload 7
/*    */     //   251: ldc_w 553
/*    */     //   254: ldc_w 555
/*    */     //   257: aload 11
/*    */     //   259: invokestatic 523	com/claro/util/Utils:enviaCorreo	(Ljava/util/Map;Ljava/lang/String;Ljava/lang/String;Ljava/util/List;)Z
/*    */     //   262: pop
/*    */     //   263: iconst_1
/*    */     //   264: istore 5
/*    */     //   266: goto +43 -> 309
/*    */     //   269: astore 6
/*    */     //   271: aload 4
/*    */     //   273: ifnull +51 -> 324
/*    */     //   276: aload 4
/*    */     //   278: invokevirtual 529	java/io/FileOutputStream:close	()V
/*    */     //   281: goto +43 -> 324
/*    */     //   284: astore 13
/*    */     //   286: goto +38 -> 324
/*    */     //   289: astore 12
/*    */     //   291: aload 4
/*    */     //   293: ifnull +13 -> 306
/*    */     //   296: aload 4
/*    */     //   298: invokevirtual 529	java/io/FileOutputStream:close	()V
/*    */     //   301: goto +5 -> 306
/*    */     //   304: astore 13
/*    */     //   306: aload 12
/*    */     //   308: athrow
/*    */     //   309: aload 4
/*    */     //   311: ifnull +13 -> 324
/*    */     //   314: aload 4
/*    */     //   316: invokevirtual 529	java/io/FileOutputStream:close	()V
/*    */     //   319: goto +5 -> 324
/*    */     //   322: astore 13
/*    */     //   324: iload 5
/*    */     //   326: ireturn
/*    */     // Line number table:
/*    */     //   Java source line #254	-> byte code offset #0
/*    */     //   Java source line #255	-> byte code offset #24
/*    */     //   Java source line #256	-> byte code offset #27
/*    */     //   Java source line #259	-> byte code offset #30
/*    */     //   Java source line #260	-> byte code offset #40
/*    */     //   Java source line #261	-> byte code offset #49
/*    */     //   Java source line #263	-> byte code offset #58
/*    */     //   Java source line #264	-> byte code offset #67
/*    */     //   Java source line #266	-> byte code offset #74
/*    */     //   Java source line #267	-> byte code offset #82
/*    */     //   Java source line #287	-> byte code offset #95
/*    */     //   Java source line #268	-> byte code offset #110
/*    */     //   Java source line #270	-> byte code offset #112
/*    */     //   Java source line #272	-> byte code offset #123
/*    */     //   Java source line #273	-> byte code offset #130
/*    */     //   Java source line #274	-> byte code offset #133
/*    */     //   Java source line #275	-> byte code offset #145
/*    */     //   Java source line #273	-> byte code offset #216
/*    */     //   Java source line #277	-> byte code offset #226
/*    */     //   Java source line #278	-> byte code offset #231
/*    */     //   Java source line #279	-> byte code offset #240
/*    */     //   Java source line #280	-> byte code offset #249
/*    */     //   Java source line #281	-> byte code offset #263
/*    */     //   Java source line #284	-> byte code offset #269
/*    */     //   Java source line #287	-> byte code offset #271
/*    */     //   Java source line #286	-> byte code offset #289
/*    */     //   Java source line #287	-> byte code offset #291
/*    */     //   Java source line #288	-> byte code offset #306
/*    */     //   Java source line #287	-> byte code offset #309
/*    */     //   Java source line #289	-> byte code offset #324
/*    */     // Local variable table:
/*    */     //   start	length	slot	name	signature
/*    */     //   0	327	0	this	MembresiaDAO
/*    */     //   0	327	1	membresias	java.util.ArrayList<com.claro.transfer.membresia.MembresiaTO>
/*    */     //   0	327	2	idRegion	int
/*    */     //   23	220	3	logInserts	String
/*    */     //   25	290	4	f1	java.io.FileOutputStream
/*    */     //   28	297	5	valor	boolean
/*    */     //   47	3	6	consultaCuentasCorreoDAO	ConsultaCuentasCorreoDAO
/*    */     //   269	1	6	localException	Exception
/*    */     //   56	194	7	parametrosCorreo	java.util.Map<String, String>
/*    */     //   65	59	8	membresiasDepuradas	java.util.ArrayList<com.claro.transfer.membresia.MembresiaTO>
/*    */     //   121	106	9	p1	java.io.PrintStream
/*    */     //   128	89	10	iterator	java.util.ListIterator<com.claro.transfer.membresia.MembresiaTO>
/*    */     //   143	57	11	membresiaTO	com.claro.transfer.membresia.MembresiaTO
/*    */     //   238	20	11	archivosLog	java.util.List<String>
/*    */     //   289	18	12	localObject	Object
/*    */     //   108	1	13	localIOException	java.io.IOException
/*    */     //   284	1	13	localIOException1	java.io.IOException
/*    */     //   304	1	13	localIOException2	java.io.IOException
/*    */     //   322	1	13	localIOException3	java.io.IOException
/*    */     // Exception table:
/*    */     //   from	to	target	type
/*    */     //   100	105	108	java/io/IOException
/*    */     //   30	95	269	java/lang/Exception
/*    */     //   112	266	269	java/lang/Exception
/*    */     //   276	281	284	java/io/IOException
/*    */     //   30	95	289	finally
/*    */     //   112	271	289	finally
/*    */     //   296	301	304	java/io/IOException
/*    */     //   314	319	322	java/io/IOException
/*    */   }
/*    */ }


/* Location:              /opt/trabajo/claro/Guatemala/IS/CO/ClaroClub.ear!/ClaroClubEJB.jar!/com/claro/dao/MembresiaDAO.class
 * Java compiler version: 6 (50.0)
 * JD-Core Version:       0.7.1
 */