/*    */ package com.claro.dao;
/*    */ 
/*    */ import com.claro.exception.CAException;
/*    */ import com.claro.transfer.ParametrosTO;
/*    */ import com.claro.transfer.PuntosTO;
/*    */ import com.claro.transfer.TelefonoTO;
/*    */ import com.claro.util.ServiceLocator;
/*    */ import java.sql.Connection;
/*    */ import org.apache.log4j.Logger;
/*    */ 
/*    */ 
/*    */ 
/*    */ 
/*    */ 
/*    */ 
/*    */ 
/*    */ 
/*    */ 
/*    */ 
/*    */ public class PuntitosDAO
/*    */ {
/* 22 */   protected final Logger logger = Logger.getLogger("loggerCirculoAzul");
/* 23 */   protected final Logger error = Logger.getLogger("loggerCirculoAzulError");
/*    */   private String schema_database;
/*    */   
/*    */   public PuntitosDAO()
/*    */   {
/*    */     try {
/* 29 */       this.schema_database = ServiceLocator.getInstance().getVariable(ServiceLocator.schema_database);
/*    */     } catch (Exception e) {
/* 31 */       this.error.error("PuntitosDAO", e);
/*    */     }
/*    */   }
/*    */   
/*    */ 
/*    */ 
/*    */ 
/*    */   public TelefonoTO procedimientoGeneral(ParametrosTO parametrosTO)
/*    */     throws CAException
/*    */   {
/* 41 */     Connection connection = null;
/* 42 */     TelefonoTO telefonoTO = null;
/*    */     try {
/* 44 */       connection = ServiceLocator.getInstance().getConnection(ServiceLocator.jdbcCirculoAzul);
/*    */       
/* 46 */       telefonoTO = consultaDatosPuntos(parametrosTO, connection);
/* 47 */       if (telefonoTO.getIdMensaje() == 1) {
/* 48 */         return telefonoTO;
/*    */       }
/*    */       
/* 51 */       if (telefonoTO.getPuntosTO().getPtosStatus().trim().equals("R")) {
/* 52 */         telefonoTO.agregaMensaje(2, "Los Puntos estan " + telefonoTO.getPuntosTO().getDescPtsReservados());
/* 53 */       } else if (telefonoTO.getPuntosTO().getPtosStatus().trim().equals("C")) {
/* 54 */         telefonoTO.agregaMensaje(2, "Los puntos estan congelados");
/*    */       }
/*    */     }
/*    */     catch (Exception e)
/*    */     {
/* 59 */       throw new CAException(-1, "ConsultaDAO.procedimientoGeneral[" + e.toString() + "]", e);
/*    */     } finally {
/* 61 */       if (connection != null) try { connection.close();connection = null; } catch (Exception localException2) {} } if (connection != null) try { connection.close();connection = null;
/*    */       } catch (Exception localException3) {}
/* 63 */     return telefonoTO;
/*    */   }
/*    */   
/*    */   /* Error */
/*    */   private TelefonoTO consultaDatosPuntos(ParametrosTO parametrosTO, Connection connection)
/*    */     throws CAException
/*    */   {
/*    */     // Byte code:
/*    */     //   0: new 73	com/claro/transfer/TelefonoTO
/*    */     //   3: dup
/*    */     //   4: invokespecial 147	com/claro/transfer/TelefonoTO:<init>	()V
/*    */     //   7: astore_3
/*    */     //   8: aload_1
/*    */     //   9: invokevirtual 148	com/claro/transfer/ParametrosTO:getCuenta	()Ljava/lang/String;
/*    */     //   12: ifnonnull +21 -> 33
/*    */     //   15: aload_1
/*    */     //   16: invokevirtual 151	com/claro/transfer/ParametrosTO:getTelefono	()Ljava/lang/String;
/*    */     //   19: ifnonnull +14 -> 33
/*    */     //   22: new 59	com/claro/exception/CAException
/*    */     //   25: dup
/*    */     //   26: iconst_m1
/*    */     //   27: ldc -102
/*    */     //   29: invokespecial 156	com/claro/exception/CAException:<init>	(ILjava/lang/String;)V
/*    */     //   32: athrow
/*    */     //   33: aconst_null
/*    */     //   34: astore 4
/*    */     //   36: new 158	java/lang/StringBuffer
/*    */     //   39: dup
/*    */     //   40: invokespecial 160	java/lang/StringBuffer:<init>	()V
/*    */     //   43: astore 5
/*    */     //   45: aload_1
/*    */     //   46: invokevirtual 148	com/claro/transfer/ParametrosTO:getCuenta	()Ljava/lang/String;
/*    */     //   49: ifnull +86 -> 135
/*    */     //   52: aload_1
/*    */     //   53: invokevirtual 151	com/claro/transfer/ParametrosTO:getTelefono	()Ljava/lang/String;
/*    */     //   56: ifnull +79 -> 135
/*    */     //   59: aload_1
/*    */     //   60: invokevirtual 148	com/claro/transfer/ParametrosTO:getCuenta	()Ljava/lang/String;
/*    */     //   63: invokevirtual 93	java/lang/String:trim	()Ljava/lang/String;
/*    */     //   66: ldc -95
/*    */     //   68: invokevirtual 100	java/lang/String:equals	(Ljava/lang/Object;)Z
/*    */     //   71: ifne +64 -> 135
/*    */     //   74: aload_1
/*    */     //   75: invokevirtual 151	com/claro/transfer/ParametrosTO:getTelefono	()Ljava/lang/String;
/*    */     //   78: invokevirtual 93	java/lang/String:trim	()Ljava/lang/String;
/*    */     //   81: ldc -95
/*    */     //   83: invokevirtual 100	java/lang/String:equals	(Ljava/lang/Object;)Z
/*    */     //   86: ifne +49 -> 135
/*    */     //   89: new 104	java/lang/StringBuilder
/*    */     //   92: dup
/*    */     //   93: ldc -93
/*    */     //   95: invokespecial 108	java/lang/StringBuilder:<init>	(Ljava/lang/String;)V
/*    */     //   98: aload_1
/*    */     //   99: invokevirtual 151	com/claro/transfer/ParametrosTO:getTelefono	()Ljava/lang/String;
/*    */     //   102: invokevirtual 114	java/lang/StringBuilder:append	(Ljava/lang/String;)Ljava/lang/StringBuilder;
/*    */     //   105: ldc -91
/*    */     //   107: invokevirtual 114	java/lang/StringBuilder:append	(Ljava/lang/String;)Ljava/lang/StringBuilder;
/*    */     //   110: ldc -89
/*    */     //   112: invokevirtual 114	java/lang/StringBuilder:append	(Ljava/lang/String;)Ljava/lang/StringBuilder;
/*    */     //   115: aload_1
/*    */     //   116: invokevirtual 148	com/claro/transfer/ParametrosTO:getCuenta	()Ljava/lang/String;
/*    */     //   119: invokevirtual 114	java/lang/StringBuilder:append	(Ljava/lang/String;)Ljava/lang/StringBuilder;
/*    */     //   122: ldc -87
/*    */     //   124: invokevirtual 114	java/lang/StringBuilder:append	(Ljava/lang/String;)Ljava/lang/StringBuilder;
/*    */     //   127: invokevirtual 118	java/lang/StringBuilder:toString	()Ljava/lang/String;
/*    */     //   130: astore 4
/*    */     //   132: goto +69 -> 201
/*    */     //   135: aload_1
/*    */     //   136: invokevirtual 148	com/claro/transfer/ParametrosTO:getCuenta	()Ljava/lang/String;
/*    */     //   139: ifnull +29 -> 168
/*    */     //   142: new 104	java/lang/StringBuilder
/*    */     //   145: dup
/*    */     //   146: ldc -89
/*    */     //   148: invokespecial 108	java/lang/StringBuilder:<init>	(Ljava/lang/String;)V
/*    */     //   151: aload_1
/*    */     //   152: invokevirtual 148	com/claro/transfer/ParametrosTO:getCuenta	()Ljava/lang/String;
/*    */     //   155: invokevirtual 114	java/lang/StringBuilder:append	(Ljava/lang/String;)Ljava/lang/StringBuilder;
/*    */     //   158: ldc -87
/*    */     //   160: invokevirtual 114	java/lang/StringBuilder:append	(Ljava/lang/String;)Ljava/lang/StringBuilder;
/*    */     //   163: invokevirtual 118	java/lang/StringBuilder:toString	()Ljava/lang/String;
/*    */     //   166: astore 4
/*    */     //   168: aload_1
/*    */     //   169: invokevirtual 151	com/claro/transfer/ParametrosTO:getTelefono	()Ljava/lang/String;
/*    */     //   172: ifnull +29 -> 201
/*    */     //   175: new 104	java/lang/StringBuilder
/*    */     //   178: dup
/*    */     //   179: ldc -93
/*    */     //   181: invokespecial 108	java/lang/StringBuilder:<init>	(Ljava/lang/String;)V
/*    */     //   184: aload_1
/*    */     //   185: invokevirtual 151	com/claro/transfer/ParametrosTO:getTelefono	()Ljava/lang/String;
/*    */     //   188: invokevirtual 114	java/lang/StringBuilder:append	(Ljava/lang/String;)Ljava/lang/StringBuilder;
/*    */     //   191: ldc -87
/*    */     //   193: invokevirtual 114	java/lang/StringBuilder:append	(Ljava/lang/String;)Ljava/lang/StringBuilder;
/*    */     //   196: invokevirtual 118	java/lang/StringBuilder:toString	()Ljava/lang/String;
/*    */     //   199: astore 4
/*    */     //   201: aload 5
/*    */     //   203: ldc -85
/*    */     //   205: invokevirtual 173	java/lang/StringBuffer:append	(Ljava/lang/String;)Ljava/lang/StringBuffer;
/*    */     //   208: pop
/*    */     //   209: aload 5
/*    */     //   211: ldc -80
/*    */     //   213: invokevirtual 173	java/lang/StringBuffer:append	(Ljava/lang/String;)Ljava/lang/StringBuffer;
/*    */     //   216: pop
/*    */     //   217: aload 5
/*    */     //   219: ldc -78
/*    */     //   221: invokevirtual 173	java/lang/StringBuffer:append	(Ljava/lang/String;)Ljava/lang/StringBuffer;
/*    */     //   224: pop
/*    */     //   225: aload 5
/*    */     //   227: ldc -76
/*    */     //   229: invokevirtual 173	java/lang/StringBuffer:append	(Ljava/lang/String;)Ljava/lang/StringBuffer;
/*    */     //   232: pop
/*    */     //   233: aload 5
/*    */     //   235: ldc -74
/*    */     //   237: invokevirtual 173	java/lang/StringBuffer:append	(Ljava/lang/String;)Ljava/lang/StringBuffer;
/*    */     //   240: pop
/*    */     //   241: aload 5
/*    */     //   243: ldc -72
/*    */     //   245: invokevirtual 173	java/lang/StringBuffer:append	(Ljava/lang/String;)Ljava/lang/StringBuffer;
/*    */     //   248: pop
/*    */     //   249: aload 5
/*    */     //   251: ldc -70
/*    */     //   253: invokevirtual 173	java/lang/StringBuffer:append	(Ljava/lang/String;)Ljava/lang/StringBuffer;
/*    */     //   256: pop
/*    */     //   257: aload 5
/*    */     //   259: ldc -68
/*    */     //   261: invokevirtual 173	java/lang/StringBuffer:append	(Ljava/lang/String;)Ljava/lang/StringBuffer;
/*    */     //   264: pop
/*    */     //   265: aload 5
/*    */     //   267: ldc -66
/*    */     //   269: invokevirtual 173	java/lang/StringBuffer:append	(Ljava/lang/String;)Ljava/lang/StringBuffer;
/*    */     //   272: pop
/*    */     //   273: aload 5
/*    */     //   275: ldc -64
/*    */     //   277: invokevirtual 173	java/lang/StringBuffer:append	(Ljava/lang/String;)Ljava/lang/StringBuffer;
/*    */     //   280: pop
/*    */     //   281: aload 5
/*    */     //   283: ldc -62
/*    */     //   285: invokevirtual 173	java/lang/StringBuffer:append	(Ljava/lang/String;)Ljava/lang/StringBuffer;
/*    */     //   288: pop
/*    */     //   289: aload 5
/*    */     //   291: ldc -60
/*    */     //   293: invokevirtual 173	java/lang/StringBuffer:append	(Ljava/lang/String;)Ljava/lang/StringBuffer;
/*    */     //   296: aload_0
/*    */     //   297: getfield 41	com/claro/dao/PuntitosDAO:schema_database	Ljava/lang/String;
/*    */     //   300: invokevirtual 173	java/lang/StringBuffer:append	(Ljava/lang/String;)Ljava/lang/StringBuffer;
/*    */     //   303: ldc -58
/*    */     //   305: invokevirtual 173	java/lang/StringBuffer:append	(Ljava/lang/String;)Ljava/lang/StringBuffer;
/*    */     //   308: aload_0
/*    */     //   309: getfield 41	com/claro/dao/PuntitosDAO:schema_database	Ljava/lang/String;
/*    */     //   312: invokevirtual 173	java/lang/StringBuffer:append	(Ljava/lang/String;)Ljava/lang/StringBuffer;
/*    */     //   315: ldc -56
/*    */     //   317: invokevirtual 173	java/lang/StringBuffer:append	(Ljava/lang/String;)Ljava/lang/StringBuffer;
/*    */     //   320: pop
/*    */     //   321: aload 5
/*    */     //   323: aload_0
/*    */     //   324: getfield 41	com/claro/dao/PuntitosDAO:schema_database	Ljava/lang/String;
/*    */     //   327: invokevirtual 173	java/lang/StringBuffer:append	(Ljava/lang/String;)Ljava/lang/StringBuffer;
/*    */     //   330: ldc -54
/*    */     //   332: invokevirtual 173	java/lang/StringBuffer:append	(Ljava/lang/String;)Ljava/lang/StringBuffer;
/*    */     //   335: aload_0
/*    */     //   336: getfield 41	com/claro/dao/PuntitosDAO:schema_database	Ljava/lang/String;
/*    */     //   339: invokevirtual 173	java/lang/StringBuffer:append	(Ljava/lang/String;)Ljava/lang/StringBuffer;
/*    */     //   342: ldc -52
/*    */     //   344: invokevirtual 173	java/lang/StringBuffer:append	(Ljava/lang/String;)Ljava/lang/StringBuffer;
/*    */     //   347: pop
/*    */     //   348: aload 5
/*    */     //   350: ldc -50
/*    */     //   352: invokevirtual 173	java/lang/StringBuffer:append	(Ljava/lang/String;)Ljava/lang/StringBuffer;
/*    */     //   355: aload 4
/*    */     //   357: invokevirtual 173	java/lang/StringBuffer:append	(Ljava/lang/String;)Ljava/lang/StringBuffer;
/*    */     //   360: pop
/*    */     //   361: aload 5
/*    */     //   363: ldc -48
/*    */     //   365: invokevirtual 173	java/lang/StringBuffer:append	(Ljava/lang/String;)Ljava/lang/StringBuffer;
/*    */     //   368: pop
/*    */     //   369: aload 5
/*    */     //   371: ldc -46
/*    */     //   373: invokevirtual 173	java/lang/StringBuffer:append	(Ljava/lang/String;)Ljava/lang/StringBuffer;
/*    */     //   376: pop
/*    */     //   377: aload 5
/*    */     //   379: ldc -44
/*    */     //   381: invokevirtual 173	java/lang/StringBuffer:append	(Ljava/lang/String;)Ljava/lang/StringBuffer;
/*    */     //   384: pop
/*    */     //   385: aload 5
/*    */     //   387: ldc -42
/*    */     //   389: invokevirtual 173	java/lang/StringBuffer:append	(Ljava/lang/String;)Ljava/lang/StringBuffer;
/*    */     //   392: pop
/*    */     //   393: aload 5
/*    */     //   395: ldc -40
/*    */     //   397: invokevirtual 173	java/lang/StringBuffer:append	(Ljava/lang/String;)Ljava/lang/StringBuffer;
/*    */     //   400: pop
/*    */     //   401: aload 5
/*    */     //   403: ldc -38
/*    */     //   405: invokevirtual 173	java/lang/StringBuffer:append	(Ljava/lang/String;)Ljava/lang/StringBuffer;
/*    */     //   408: pop
/*    */     //   409: aload 5
/*    */     //   411: ldc -36
/*    */     //   413: invokevirtual 173	java/lang/StringBuffer:append	(Ljava/lang/String;)Ljava/lang/StringBuffer;
/*    */     //   416: pop
/*    */     //   417: aload 5
/*    */     //   419: ldc -34
/*    */     //   421: invokevirtual 173	java/lang/StringBuffer:append	(Ljava/lang/String;)Ljava/lang/StringBuffer;
/*    */     //   424: pop
/*    */     //   425: aload 5
/*    */     //   427: ldc -32
/*    */     //   429: invokevirtual 173	java/lang/StringBuffer:append	(Ljava/lang/String;)Ljava/lang/StringBuffer;
/*    */     //   432: pop
/*    */     //   433: aload 5
/*    */     //   435: ldc -30
/*    */     //   437: invokevirtual 173	java/lang/StringBuffer:append	(Ljava/lang/String;)Ljava/lang/StringBuffer;
/*    */     //   440: pop
/*    */     //   441: aload 5
/*    */     //   443: ldc -28
/*    */     //   445: invokevirtual 173	java/lang/StringBuffer:append	(Ljava/lang/String;)Ljava/lang/StringBuffer;
/*    */     //   448: pop
/*    */     //   449: aload 5
/*    */     //   451: ldc -26
/*    */     //   453: invokevirtual 173	java/lang/StringBuffer:append	(Ljava/lang/String;)Ljava/lang/StringBuffer;
/*    */     //   456: pop
/*    */     //   457: aload 5
/*    */     //   459: ldc -24
/*    */     //   461: invokevirtual 173	java/lang/StringBuffer:append	(Ljava/lang/String;)Ljava/lang/StringBuffer;
/*    */     //   464: pop
/*    */     //   465: aload 5
/*    */     //   467: ldc -22
/*    */     //   469: invokevirtual 173	java/lang/StringBuffer:append	(Ljava/lang/String;)Ljava/lang/StringBuffer;
/*    */     //   472: pop
/*    */     //   473: aload 5
/*    */     //   475: ldc -20
/*    */     //   477: invokevirtual 173	java/lang/StringBuffer:append	(Ljava/lang/String;)Ljava/lang/StringBuffer;
/*    */     //   480: pop
/*    */     //   481: aconst_null
/*    */     //   482: astore 6
/*    */     //   484: aconst_null
/*    */     //   485: astore 7
/*    */     //   487: aconst_null
/*    */     //   488: astore 8
/*    */     //   490: aconst_null
/*    */     //   491: astore 9
/*    */     //   493: aconst_null
/*    */     //   494: astore 10
/*    */     //   496: aload_2
/*    */     //   497: sipush 1004
/*    */     //   500: sipush 1007
/*    */     //   503: invokeinterface 238 3 0
/*    */     //   508: astore 6
/*    */     //   510: aload 6
/*    */     //   512: aload 5
/*    */     //   514: invokevirtual 242	java/lang/StringBuffer:toString	()Ljava/lang/String;
/*    */     //   517: invokeinterface 243 2 0
/*    */     //   522: astore 8
/*    */     //   524: aload 8
/*    */     //   526: invokeinterface 249 1 0
/*    */     //   531: ifeq +541 -> 1072
/*    */     //   534: aload_3
/*    */     //   535: aload 8
/*    */     //   537: ldc -1
/*    */     //   539: invokeinterface 257 2 0
/*    */     //   544: invokevirtual 93	java/lang/String:trim	()Ljava/lang/String;
/*    */     //   547: invokevirtual 260	com/claro/transfer/TelefonoTO:setCuenta	(Ljava/lang/String;)V
/*    */     //   550: aload_3
/*    */     //   551: aload 8
/*    */     //   553: ldc_w 263
/*    */     //   556: invokeinterface 257 2 0
/*    */     //   561: invokevirtual 265	com/claro/transfer/TelefonoTO:setSecuencia	(Ljava/lang/String;)V
/*    */     //   564: aload_3
/*    */     //   565: aload 8
/*    */     //   567: ldc_w 268
/*    */     //   570: invokeinterface 257 2 0
/*    */     //   575: invokevirtual 93	java/lang/String:trim	()Ljava/lang/String;
/*    */     //   578: invokevirtual 270	com/claro/transfer/TelefonoTO:setCtaPadre	(Ljava/lang/String;)V
/*    */     //   581: aload_3
/*    */     //   582: aload 8
/*    */     //   584: ldc_w 273
/*    */     //   587: invokeinterface 257 2 0
/*    */     //   592: invokevirtual 275	com/claro/transfer/TelefonoTO:setTelefono	(Ljava/lang/String;)V
/*    */     //   595: aload_3
/*    */     //   596: aload 8
/*    */     //   598: ldc_w 278
/*    */     //   601: invokeinterface 280 2 0
/*    */     //   606: invokevirtual 284	com/claro/transfer/TelefonoTO:setFechaAlta	(Ljava/sql/Date;)V
/*    */     //   609: aload_3
/*    */     //   610: aload 8
/*    */     //   612: ldc_w 288
/*    */     //   615: invokeinterface 257 2 0
/*    */     //   620: invokevirtual 290	com/claro/transfer/TelefonoTO:setSistema	(Ljava/lang/String;)V
/*    */     //   623: aload_3
/*    */     //   624: aload 8
/*    */     //   626: ldc_w 293
/*    */     //   629: invokeinterface 295 2 0
/*    */     //   634: invokevirtual 299	com/claro/transfer/TelefonoTO:setRegion	(I)V
/*    */     //   637: aload_3
/*    */     //   638: aload 8
/*    */     //   640: ldc_w 303
/*    */     //   643: invokeinterface 257 2 0
/*    */     //   648: invokevirtual 305	com/claro/transfer/TelefonoTO:setCiclo	(Ljava/lang/String;)V
/*    */     //   651: aload_3
/*    */     //   652: aload 8
/*    */     //   654: ldc_w 308
/*    */     //   657: invokeinterface 257 2 0
/*    */     //   662: invokevirtual 310	com/claro/transfer/TelefonoTO:setPlan	(Ljava/lang/String;)V
/*    */     //   665: aload_3
/*    */     //   666: aload 8
/*    */     //   668: ldc_w 313
/*    */     //   671: invokeinterface 295 2 0
/*    */     //   676: invokevirtual 315	com/claro/transfer/TelefonoTO:setAddendum	(I)V
/*    */     //   679: aload_3
/*    */     //   680: aload 8
/*    */     //   682: ldc_w 318
/*    */     //   685: invokeinterface 280 2 0
/*    */     //   690: invokevirtual 320	com/claro/transfer/TelefonoTO:setFecFactura	(Ljava/sql/Date;)V
/*    */     //   693: aload_3
/*    */     //   694: aload 8
/*    */     //   696: ldc_w 323
/*    */     //   699: invokeinterface 257 2 0
/*    */     //   704: invokevirtual 325	com/claro/transfer/TelefonoTO:setTecnologia	(Ljava/lang/String;)V
/*    */     //   707: aload_3
/*    */     //   708: aload 8
/*    */     //   710: ldc_w 328
/*    */     //   713: invokeinterface 295 2 0
/*    */     //   718: invokevirtual 330	com/claro/transfer/TelefonoTO:setBonoEquipo	(I)V
/*    */     //   721: aload_3
/*    */     //   722: aload 8
/*    */     //   724: ldc_w 333
/*    */     //   727: invokeinterface 295 2 0
/*    */     //   732: invokevirtual 335	com/claro/transfer/TelefonoTO:setRenta	(I)V
/*    */     //   735: aload_3
/*    */     //   736: aload 8
/*    */     //   738: ldc_w 338
/*    */     //   741: invokeinterface 295 2 0
/*    */     //   746: invokevirtual 340	com/claro/transfer/TelefonoTO:setIdSegmento	(I)V
/*    */     //   749: aload_3
/*    */     //   750: aload 8
/*    */     //   752: ldc_w 343
/*    */     //   755: invokeinterface 257 2 0
/*    */     //   760: invokevirtual 345	com/claro/transfer/TelefonoTO:setSegmento	(Ljava/lang/String;)V
/*    */     //   763: aload_3
/*    */     //   764: aload 8
/*    */     //   766: ldc_w 348
/*    */     //   769: invokeinterface 257 2 0
/*    */     //   774: invokevirtual 350	com/claro/transfer/TelefonoTO:setSAnacr	(Ljava/lang/String;)V
/*    */     //   777: aload_3
/*    */     //   778: aload 8
/*    */     //   780: ldc_w 353
/*    */     //   783: invokeinterface 295 2 0
/*    */     //   788: invokevirtual 355	com/claro/transfer/TelefonoTO:setBanSubasta	(I)V
/*    */     //   791: new 88	com/claro/transfer/PuntosTO
/*    */     //   794: dup
/*    */     //   795: invokespecial 358	com/claro/transfer/PuntosTO:<init>	()V
/*    */     //   798: astore 10
/*    */     //   800: aload 10
/*    */     //   802: aload 8
/*    */     //   804: ldc_w 359
/*    */     //   807: invokeinterface 257 2 0
/*    */     //   812: invokevirtual 361	com/claro/transfer/PuntosTO:setPtosStatus	(Ljava/lang/String;)V
/*    */     //   815: aload 10
/*    */     //   817: aload 8
/*    */     //   819: ldc_w 364
/*    */     //   822: invokeinterface 295 2 0
/*    */     //   827: invokevirtual 366	com/claro/transfer/PuntosTO:setPtsRedimidos	(I)V
/*    */     //   830: aload 10
/*    */     //   832: aload 8
/*    */     //   834: ldc_w 369
/*    */     //   837: invokeinterface 295 2 0
/*    */     //   842: invokevirtual 371	com/claro/transfer/PuntosTO:setPtsTransferidos	(I)V
/*    */     //   845: aload 10
/*    */     //   847: aload 8
/*    */     //   849: ldc_w 374
/*    */     //   852: invokeinterface 295 2 0
/*    */     //   857: invokevirtual 376	com/claro/transfer/PuntosTO:setPtsVencidos	(I)V
/*    */     //   860: aload 10
/*    */     //   862: aload 8
/*    */     //   864: ldc_w 379
/*    */     //   867: invokeinterface 295 2 0
/*    */     //   872: invokevirtual 381	com/claro/transfer/PuntosTO:setPtsPorVencer	(I)V
/*    */     //   875: aload 10
/*    */     //   877: aload 8
/*    */     //   879: ldc_w 384
/*    */     //   882: invokeinterface 295 2 0
/*    */     //   887: invokevirtual 386	com/claro/transfer/PuntosTO:setPtsPorVencer1	(I)V
/*    */     //   890: aload 10
/*    */     //   892: aload 8
/*    */     //   894: ldc_w 389
/*    */     //   897: invokeinterface 295 2 0
/*    */     //   902: invokevirtual 391	com/claro/transfer/PuntosTO:setPtsPorVencer2	(I)V
/*    */     //   905: aload 10
/*    */     //   907: aload 8
/*    */     //   909: ldc_w 394
/*    */     //   912: invokeinterface 295 2 0
/*    */     //   917: invokevirtual 396	com/claro/transfer/PuntosTO:setPtsRenta	(I)V
/*    */     //   920: aload 10
/*    */     //   922: aload 8
/*    */     //   924: ldc_w 399
/*    */     //   927: invokeinterface 295 2 0
/*    */     //   932: invokevirtual 401	com/claro/transfer/PuntosTO:setPtsExcedentes	(I)V
/*    */     //   935: aload 10
/*    */     //   937: aload 8
/*    */     //   939: ldc_w 404
/*    */     //   942: invokeinterface 295 2 0
/*    */     //   947: invokevirtual 406	com/claro/transfer/PuntosTO:setPtsAntiguedad	(I)V
/*    */     //   950: aload 10
/*    */     //   952: aload 8
/*    */     //   954: ldc_w 409
/*    */     //   957: invokeinterface 295 2 0
/*    */     //   962: invokevirtual 411	com/claro/transfer/PuntosTO:setPtsPromocion	(I)V
/*    */     //   965: aload 10
/*    */     //   967: aload 8
/*    */     //   969: ldc_w 414
/*    */     //   972: invokeinterface 280 2 0
/*    */     //   977: invokevirtual 416	com/claro/transfer/PuntosTO:setFecVencer	(Ljava/sql/Date;)V
/*    */     //   980: aload 10
/*    */     //   982: aload 8
/*    */     //   984: ldc_w 419
/*    */     //   987: invokeinterface 280 2 0
/*    */     //   992: invokevirtual 421	com/claro/transfer/PuntosTO:setFecVencer2	(Ljava/sql/Date;)V
/*    */     //   995: aload 10
/*    */     //   997: aload 8
/*    */     //   999: ldc_w 424
/*    */     //   1002: invokeinterface 280 2 0
/*    */     //   1007: invokevirtual 426	com/claro/transfer/PuntosTO:setFecVencer1	(Ljava/sql/Date;)V
/*    */     //   1010: aload 10
/*    */     //   1012: aload 8
/*    */     //   1014: ldc_w 429
/*    */     //   1017: invokeinterface 280 2 0
/*    */     //   1022: invokevirtual 431	com/claro/transfer/PuntosTO:setFecVencidos	(Ljava/sql/Date;)V
/*    */     //   1025: aload 10
/*    */     //   1027: aload 8
/*    */     //   1029: ldc_w 434
/*    */     //   1032: invokeinterface 295 2 0
/*    */     //   1037: invokevirtual 436	com/claro/transfer/PuntosTO:setPtsSaldoAnt	(I)V
/*    */     //   1040: aload 10
/*    */     //   1042: aload 8
/*    */     //   1044: ldc_w 328
/*    */     //   1047: invokeinterface 295 2 0
/*    */     //   1052: invokevirtual 439	com/claro/transfer/PuntosTO:setBonoEquipo	(I)V
/*    */     //   1055: aload_3
/*    */     //   1056: aload 10
/*    */     //   1058: invokevirtual 440	com/claro/transfer/TelefonoTO:setPuntosTO	(Lcom/claro/transfer/PuntosTO;)V
/*    */     //   1061: aload_3
/*    */     //   1062: iconst_0
/*    */     //   1063: ldc_w 444
/*    */     //   1066: invokevirtual 121	com/claro/transfer/TelefonoTO:agregaMensaje	(ILjava/lang/String;)V
/*    */     //   1069: goto +177 -> 1246
/*    */     //   1072: aload_3
/*    */     //   1073: iconst_m1
/*    */     //   1074: ldc_w 446
/*    */     //   1077: invokevirtual 121	com/claro/transfer/TelefonoTO:agregaMensaje	(ILjava/lang/String;)V
/*    */     //   1080: goto +166 -> 1246
/*    */     //   1083: astore 11
/*    */     //   1085: new 59	com/claro/exception/CAException
/*    */     //   1088: dup
/*    */     //   1089: iconst_m1
/*    */     //   1090: new 104	java/lang/StringBuilder
/*    */     //   1093: dup
/*    */     //   1094: ldc_w 448
/*    */     //   1097: invokespecial 108	java/lang/StringBuilder:<init>	(Ljava/lang/String;)V
/*    */     //   1100: aload 11
/*    */     //   1102: invokevirtual 450	java/sql/SQLException:toString	()Ljava/lang/String;
/*    */     //   1105: invokevirtual 114	java/lang/StringBuilder:append	(Ljava/lang/String;)Ljava/lang/StringBuilder;
/*    */     //   1108: ldc -124
/*    */     //   1110: invokevirtual 114	java/lang/StringBuilder:append	(Ljava/lang/String;)Ljava/lang/StringBuilder;
/*    */     //   1113: invokevirtual 118	java/lang/StringBuilder:toString	()Ljava/lang/String;
/*    */     //   1116: aload 11
/*    */     //   1118: invokespecial 134	com/claro/exception/CAException:<init>	(ILjava/lang/String;Ljava/lang/Exception;)V
/*    */     //   1121: athrow
/*    */     //   1122: astore 11
/*    */     //   1124: new 59	com/claro/exception/CAException
/*    */     //   1127: dup
/*    */     //   1128: iconst_m1
/*    */     //   1129: new 104	java/lang/StringBuilder
/*    */     //   1132: dup
/*    */     //   1133: ldc_w 453
/*    */     //   1136: invokespecial 108	java/lang/StringBuilder:<init>	(Ljava/lang/String;)V
/*    */     //   1139: aload 11
/*    */     //   1141: invokevirtual 131	java/lang/Exception:toString	()Ljava/lang/String;
/*    */     //   1144: invokevirtual 114	java/lang/StringBuilder:append	(Ljava/lang/String;)Ljava/lang/StringBuilder;
/*    */     //   1147: ldc -124
/*    */     //   1149: invokevirtual 114	java/lang/StringBuilder:append	(Ljava/lang/String;)Ljava/lang/StringBuilder;
/*    */     //   1152: invokevirtual 118	java/lang/StringBuilder:toString	()Ljava/lang/String;
/*    */     //   1155: aload 11
/*    */     //   1157: invokespecial 134	com/claro/exception/CAException:<init>	(ILjava/lang/String;Ljava/lang/Exception;)V
/*    */     //   1160: athrow
/*    */     //   1161: astore 12
/*    */     //   1163: aload 8
/*    */     //   1165: ifnull +18 -> 1183
/*    */     //   1168: aload 8
/*    */     //   1170: invokeinterface 455 1 0
/*    */     //   1175: aconst_null
/*    */     //   1176: astore 8
/*    */     //   1178: goto +5 -> 1183
/*    */     //   1181: astore 13
/*    */     //   1183: aload 9
/*    */     //   1185: ifnull +18 -> 1203
/*    */     //   1188: aload 9
/*    */     //   1190: invokeinterface 455 1 0
/*    */     //   1195: aconst_null
/*    */     //   1196: astore 9
/*    */     //   1198: goto +5 -> 1203
/*    */     //   1201: astore 13
/*    */     //   1203: aload 6
/*    */     //   1205: ifnull +18 -> 1223
/*    */     //   1208: aload 6
/*    */     //   1210: invokeinterface 456 1 0
/*    */     //   1215: aconst_null
/*    */     //   1216: astore 6
/*    */     //   1218: goto +5 -> 1223
/*    */     //   1221: astore 13
/*    */     //   1223: aload 7
/*    */     //   1225: ifnull +18 -> 1243
/*    */     //   1228: aload 7
/*    */     //   1230: invokeinterface 456 1 0
/*    */     //   1235: aconst_null
/*    */     //   1236: astore 7
/*    */     //   1238: goto +5 -> 1243
/*    */     //   1241: astore 13
/*    */     //   1243: aload 12
/*    */     //   1245: athrow
/*    */     //   1246: aload 8
/*    */     //   1248: ifnull +18 -> 1266
/*    */     //   1251: aload 8
/*    */     //   1253: invokeinterface 455 1 0
/*    */     //   1258: aconst_null
/*    */     //   1259: astore 8
/*    */     //   1261: goto +5 -> 1266
/*    */     //   1264: astore 13
/*    */     //   1266: aload 9
/*    */     //   1268: ifnull +18 -> 1286
/*    */     //   1271: aload 9
/*    */     //   1273: invokeinterface 455 1 0
/*    */     //   1278: aconst_null
/*    */     //   1279: astore 9
/*    */     //   1281: goto +5 -> 1286
/*    */     //   1284: astore 13
/*    */     //   1286: aload 6
/*    */     //   1288: ifnull +18 -> 1306
/*    */     //   1291: aload 6
/*    */     //   1293: invokeinterface 456 1 0
/*    */     //   1298: aconst_null
/*    */     //   1299: astore 6
/*    */     //   1301: goto +5 -> 1306
/*    */     //   1304: astore 13
/*    */     //   1306: aload 7
/*    */     //   1308: ifnull +18 -> 1326
/*    */     //   1311: aload 7
/*    */     //   1313: invokeinterface 456 1 0
/*    */     //   1318: aconst_null
/*    */     //   1319: astore 7
/*    */     //   1321: goto +5 -> 1326
/*    */     //   1324: astore 13
/*    */     //   1326: aload_3
/*    */     //   1327: areturn
/*    */     // Line number table:
/*    */     //   Java source line #72	-> byte code offset #0
/*    */     //   Java source line #75	-> byte code offset #8
/*    */     //   Java source line #76	-> byte code offset #22
/*    */     //   Java source line #78	-> byte code offset #33
/*    */     //   Java source line #79	-> byte code offset #36
/*    */     //   Java source line #81	-> byte code offset #45
/*    */     //   Java source line #82	-> byte code offset #89
/*    */     //   Java source line #84	-> byte code offset #135
/*    */     //   Java source line #85	-> byte code offset #168
/*    */     //   Java source line #88	-> byte code offset #201
/*    */     //   Java source line #89	-> byte code offset #209
/*    */     //   Java source line #90	-> byte code offset #217
/*    */     //   Java source line #91	-> byte code offset #225
/*    */     //   Java source line #92	-> byte code offset #233
/*    */     //   Java source line #93	-> byte code offset #241
/*    */     //   Java source line #94	-> byte code offset #249
/*    */     //   Java source line #95	-> byte code offset #257
/*    */     //   Java source line #96	-> byte code offset #265
/*    */     //   Java source line #97	-> byte code offset #273
/*    */     //   Java source line #98	-> byte code offset #281
/*    */     //   Java source line #99	-> byte code offset #289
/*    */     //   Java source line #100	-> byte code offset #321
/*    */     //   Java source line #101	-> byte code offset #348
/*    */     //   Java source line #102	-> byte code offset #361
/*    */     //   Java source line #103	-> byte code offset #369
/*    */     //   Java source line #104	-> byte code offset #377
/*    */     //   Java source line #105	-> byte code offset #385
/*    */     //   Java source line #106	-> byte code offset #393
/*    */     //   Java source line #107	-> byte code offset #401
/*    */     //   Java source line #108	-> byte code offset #409
/*    */     //   Java source line #109	-> byte code offset #417
/*    */     //   Java source line #110	-> byte code offset #425
/*    */     //   Java source line #111	-> byte code offset #433
/*    */     //   Java source line #112	-> byte code offset #441
/*    */     //   Java source line #113	-> byte code offset #449
/*    */     //   Java source line #114	-> byte code offset #457
/*    */     //   Java source line #115	-> byte code offset #465
/*    */     //   Java source line #116	-> byte code offset #473
/*    */     //   Java source line #118	-> byte code offset #481
/*    */     //   Java source line #119	-> byte code offset #487
/*    */     //   Java source line #120	-> byte code offset #493
/*    */     //   Java source line #122	-> byte code offset #496
/*    */     //   Java source line #124	-> byte code offset #510
/*    */     //   Java source line #125	-> byte code offset #524
/*    */     //   Java source line #127	-> byte code offset #534
/*    */     //   Java source line #128	-> byte code offset #550
/*    */     //   Java source line #130	-> byte code offset #564
/*    */     //   Java source line #131	-> byte code offset #581
/*    */     //   Java source line #132	-> byte code offset #595
/*    */     //   Java source line #133	-> byte code offset #609
/*    */     //   Java source line #134	-> byte code offset #623
/*    */     //   Java source line #135	-> byte code offset #637
/*    */     //   Java source line #136	-> byte code offset #651
/*    */     //   Java source line #137	-> byte code offset #665
/*    */     //   Java source line #138	-> byte code offset #679
/*    */     //   Java source line #139	-> byte code offset #693
/*    */     //   Java source line #140	-> byte code offset #707
/*    */     //   Java source line #141	-> byte code offset #721
/*    */     //   Java source line #142	-> byte code offset #735
/*    */     //   Java source line #143	-> byte code offset #749
/*    */     //   Java source line #144	-> byte code offset #763
/*    */     //   Java source line #145	-> byte code offset #777
/*    */     //   Java source line #146	-> byte code offset #791
/*    */     //   Java source line #148	-> byte code offset #800
/*    */     //   Java source line #149	-> byte code offset #815
/*    */     //   Java source line #150	-> byte code offset #830
/*    */     //   Java source line #151	-> byte code offset #845
/*    */     //   Java source line #152	-> byte code offset #860
/*    */     //   Java source line #153	-> byte code offset #875
/*    */     //   Java source line #154	-> byte code offset #890
/*    */     //   Java source line #155	-> byte code offset #905
/*    */     //   Java source line #156	-> byte code offset #920
/*    */     //   Java source line #157	-> byte code offset #935
/*    */     //   Java source line #158	-> byte code offset #950
/*    */     //   Java source line #159	-> byte code offset #965
/*    */     //   Java source line #160	-> byte code offset #980
/*    */     //   Java source line #161	-> byte code offset #995
/*    */     //   Java source line #162	-> byte code offset #1010
/*    */     //   Java source line #163	-> byte code offset #1025
/*    */     //   Java source line #164	-> byte code offset #1040
/*    */     //   Java source line #165	-> byte code offset #1055
/*    */     //   Java source line #166	-> byte code offset #1061
/*    */     //   Java source line #168	-> byte code offset #1072
/*    */     //   Java source line #171	-> byte code offset #1083
/*    */     //   Java source line #172	-> byte code offset #1085
/*    */     //   Java source line #173	-> byte code offset #1122
/*    */     //   Java source line #174	-> byte code offset #1124
/*    */     //   Java source line #175	-> byte code offset #1161
/*    */     //   Java source line #176	-> byte code offset #1163
/*    */     //   Java source line #177	-> byte code offset #1183
/*    */     //   Java source line #178	-> byte code offset #1203
/*    */     //   Java source line #179	-> byte code offset #1223
/*    */     //   Java source line #180	-> byte code offset #1243
/*    */     //   Java source line #176	-> byte code offset #1246
/*    */     //   Java source line #177	-> byte code offset #1266
/*    */     //   Java source line #178	-> byte code offset #1286
/*    */     //   Java source line #179	-> byte code offset #1306
/*    */     //   Java source line #181	-> byte code offset #1326
/*    */     // Local variable table:
/*    */     //   start	length	slot	name	signature
/*    */     //   0	1328	0	this	PuntitosDAO
/*    */     //   0	1328	1	parametrosTO	ParametrosTO
/*    */     //   0	1328	2	connection	Connection
/*    */     //   7	1320	3	telefonoTO	TelefonoTO
/*    */     //   34	322	4	sBusqueda	String
/*    */     //   43	470	5	query	StringBuffer
/*    */     //   482	818	6	statement	java.sql.Statement
/*    */     //   485	835	7	statementFvta	java.sql.Statement
/*    */     //   488	772	8	resultSet	java.sql.ResultSet
/*    */     //   491	789	9	resultSetFvta	java.sql.ResultSet
/*    */     //   494	563	10	oPuntos	PuntosTO
/*    */     //   1083	34	11	e	java.sql.SQLException
/*    */     //   1122	34	11	e	Exception
/*    */     //   1161	83	12	localObject	Object
/*    */     //   1181	1	13	localException1	Exception
/*    */     //   1201	1	13	localException2	Exception
/*    */     //   1221	1	13	localException3	Exception
/*    */     //   1241	1	13	localException4	Exception
/*    */     //   1264	1	13	localException5	Exception
/*    */     //   1284	1	13	localException6	Exception
/*    */     //   1304	1	13	localException7	Exception
/*    */     //   1324	1	13	localException8	Exception
/*    */     // Exception table:
/*    */     //   from	to	target	type
/*    */     //   496	1080	1083	java/sql/SQLException
/*    */     //   496	1080	1122	java/lang/Exception
/*    */     //   496	1161	1161	finally
/*    */     //   1168	1178	1181	java/lang/Exception
/*    */     //   1188	1198	1201	java/lang/Exception
/*    */     //   1208	1218	1221	java/lang/Exception
/*    */     //   1228	1238	1241	java/lang/Exception
/*    */     //   1251	1261	1264	java/lang/Exception
/*    */     //   1271	1281	1284	java/lang/Exception
/*    */     //   1291	1301	1304	java/lang/Exception
/*    */     //   1311	1321	1324	java/lang/Exception
/*    */   }
/*    */   
/*    */   /* Error */
/*    */   public java.util.ArrayList<TelefonoTO> consultaLinea(TelefonoTO telefonoTO)
/*    */     throws Exception
/*    */   {
/*    */     // Byte code:
/*    */     //   0: aconst_null
/*    */     //   1: astore_2
/*    */     //   2: aconst_null
/*    */     //   3: astore_3
/*    */     //   4: aconst_null
/*    */     //   5: astore 4
/*    */     //   7: new 473	java/util/ArrayList
/*    */     //   10: dup
/*    */     //   11: invokespecial 475	java/util/ArrayList:<init>	()V
/*    */     //   14: astore 5
/*    */     //   16: invokestatic 29	com/claro/util/ServiceLocator:getInstance	()Lcom/claro/util/ServiceLocator;
/*    */     //   19: getstatic 61	com/claro/util/ServiceLocator:jdbcCirculoAzul	Ljava/lang/String;
/*    */     //   22: invokevirtual 64	com/claro/util/ServiceLocator:getConnection	(Ljava/lang/String;)Ljava/sql/Connection;
/*    */     //   25: astore_2
/*    */     //   26: ldc -95
/*    */     //   28: astore 6
/*    */     //   30: aload_1
/*    */     //   31: invokevirtual 476	com/claro/transfer/TelefonoTO:getTelefono	()Ljava/lang/String;
/*    */     //   34: ifnull +23 -> 57
/*    */     //   37: aload_1
/*    */     //   38: invokevirtual 476	com/claro/transfer/TelefonoTO:getTelefono	()Ljava/lang/String;
/*    */     //   41: ldc -95
/*    */     //   43: invokevirtual 477	java/lang/String:equalsIgnoreCase	(Ljava/lang/String;)Z
/*    */     //   46: ifne +11 -> 57
/*    */     //   49: ldc_w 481
/*    */     //   52: astore 6
/*    */     //   54: goto +8 -> 62
/*    */     //   57: ldc_w 483
/*    */     //   60: astore 6
/*    */     //   62: new 158	java/lang/StringBuffer
/*    */     //   65: dup
/*    */     //   66: invokespecial 160	java/lang/StringBuffer:<init>	()V
/*    */     //   69: astore 7
/*    */     //   71: aload 7
/*    */     //   73: ldc_w 485
/*    */     //   76: invokevirtual 173	java/lang/StringBuffer:append	(Ljava/lang/String;)Ljava/lang/StringBuffer;
/*    */     //   79: pop
/*    */     //   80: aload 7
/*    */     //   82: ldc_w 487
/*    */     //   85: invokevirtual 173	java/lang/StringBuffer:append	(Ljava/lang/String;)Ljava/lang/StringBuffer;
/*    */     //   88: pop
/*    */     //   89: aload 7
/*    */     //   91: ldc_w 489
/*    */     //   94: invokevirtual 173	java/lang/StringBuffer:append	(Ljava/lang/String;)Ljava/lang/StringBuffer;
/*    */     //   97: aload_0
/*    */     //   98: getfield 41	com/claro/dao/PuntitosDAO:schema_database	Ljava/lang/String;
/*    */     //   101: invokevirtual 173	java/lang/StringBuffer:append	(Ljava/lang/String;)Ljava/lang/StringBuffer;
/*    */     //   104: ldc_w 491
/*    */     //   107: invokevirtual 173	java/lang/StringBuffer:append	(Ljava/lang/String;)Ljava/lang/StringBuffer;
/*    */     //   110: aload 6
/*    */     //   112: invokevirtual 173	java/lang/StringBuffer:append	(Ljava/lang/String;)Ljava/lang/StringBuffer;
/*    */     //   115: pop
/*    */     //   116: aload_2
/*    */     //   117: aload 7
/*    */     //   119: invokevirtual 242	java/lang/StringBuffer:toString	()Ljava/lang/String;
/*    */     //   122: invokeinterface 493 2 0
/*    */     //   127: astore_3
/*    */     //   128: aload_1
/*    */     //   129: invokevirtual 476	com/claro/transfer/TelefonoTO:getTelefono	()Ljava/lang/String;
/*    */     //   132: ifnull +29 -> 161
/*    */     //   135: aload_1
/*    */     //   136: invokevirtual 476	com/claro/transfer/TelefonoTO:getTelefono	()Ljava/lang/String;
/*    */     //   139: ldc -95
/*    */     //   141: invokevirtual 477	java/lang/String:equalsIgnoreCase	(Ljava/lang/String;)Z
/*    */     //   144: ifne +17 -> 161
/*    */     //   147: aload_3
/*    */     //   148: iconst_1
/*    */     //   149: aload_1
/*    */     //   150: invokevirtual 476	com/claro/transfer/TelefonoTO:getTelefono	()Ljava/lang/String;
/*    */     //   153: invokeinterface 497 3 0
/*    */     //   158: goto +14 -> 172
/*    */     //   161: aload_3
/*    */     //   162: iconst_1
/*    */     //   163: aload_1
/*    */     //   164: invokevirtual 502	com/claro/transfer/TelefonoTO:getCuenta	()Ljava/lang/String;
/*    */     //   167: invokeinterface 497 3 0
/*    */     //   172: aload_3
/*    */     //   173: invokeinterface 503 1 0
/*    */     //   178: astore 4
/*    */     //   180: goto +185 -> 365
/*    */     //   183: new 73	com/claro/transfer/TelefonoTO
/*    */     //   186: dup
/*    */     //   187: invokespecial 147	com/claro/transfer/TelefonoTO:<init>	()V
/*    */     //   190: astore 8
/*    */     //   192: new 88	com/claro/transfer/PuntosTO
/*    */     //   195: dup
/*    */     //   196: invokespecial 358	com/claro/transfer/PuntosTO:<init>	()V
/*    */     //   199: astore 9
/*    */     //   201: aload 8
/*    */     //   203: aload 4
/*    */     //   205: iconst_1
/*    */     //   206: invokeinterface 506 2 0
/*    */     //   211: invokevirtual 275	com/claro/transfer/TelefonoTO:setTelefono	(Ljava/lang/String;)V
/*    */     //   214: aload 8
/*    */     //   216: aload 4
/*    */     //   218: iconst_2
/*    */     //   219: invokeinterface 506 2 0
/*    */     //   224: invokevirtual 260	com/claro/transfer/TelefonoTO:setCuenta	(Ljava/lang/String;)V
/*    */     //   227: aload 8
/*    */     //   229: aload 4
/*    */     //   231: iconst_3
/*    */     //   232: invokeinterface 509 2 0
/*    */     //   237: invokevirtual 299	com/claro/transfer/TelefonoTO:setRegion	(I)V
/*    */     //   240: aload 9
/*    */     //   242: aload 4
/*    */     //   244: iconst_4
/*    */     //   245: invokeinterface 506 2 0
/*    */     //   250: invokevirtual 512	com/claro/transfer/PuntosTO:setEstatusPuntos	(Ljava/lang/String;)V
/*    */     //   253: aload 8
/*    */     //   255: aload 4
/*    */     //   257: iconst_5
/*    */     //   258: invokeinterface 506 2 0
/*    */     //   263: invokevirtual 265	com/claro/transfer/TelefonoTO:setSecuencia	(Ljava/lang/String;)V
/*    */     //   266: aload 8
/*    */     //   268: aload 4
/*    */     //   270: bipush 6
/*    */     //   272: invokeinterface 506 2 0
/*    */     //   277: invokevirtual 310	com/claro/transfer/TelefonoTO:setPlan	(Ljava/lang/String;)V
/*    */     //   280: aload 8
/*    */     //   282: aload 4
/*    */     //   284: bipush 7
/*    */     //   286: invokeinterface 506 2 0
/*    */     //   291: invokevirtual 305	com/claro/transfer/TelefonoTO:setCiclo	(Ljava/lang/String;)V
/*    */     //   294: aload 8
/*    */     //   296: aload 4
/*    */     //   298: bipush 8
/*    */     //   300: invokeinterface 506 2 0
/*    */     //   305: invokevirtual 515	com/claro/transfer/TelefonoTO:setNickName	(Ljava/lang/String;)V
/*    */     //   308: aload 8
/*    */     //   310: aload 4
/*    */     //   312: bipush 9
/*    */     //   314: invokeinterface 509 2 0
/*    */     //   319: invokevirtual 315	com/claro/transfer/TelefonoTO:setAddendum	(I)V
/*    */     //   322: aload 8
/*    */     //   324: aload 4
/*    */     //   326: bipush 10
/*    */     //   328: invokeinterface 518 2 0
/*    */     //   333: invokevirtual 522	com/claro/transfer/TelefonoTO:setFechaExpira	(Ljava/sql/Timestamp;)V
/*    */     //   336: aload 8
/*    */     //   338: aload 4
/*    */     //   340: bipush 11
/*    */     //   342: invokeinterface 518 2 0
/*    */     //   347: invokevirtual 526	com/claro/transfer/TelefonoTO:setFechaAltaTime	(Ljava/sql/Timestamp;)V
/*    */     //   350: aload 8
/*    */     //   352: aload 9
/*    */     //   354: invokevirtual 440	com/claro/transfer/TelefonoTO:setPuntosTO	(Lcom/claro/transfer/PuntosTO;)V
/*    */     //   357: aload 5
/*    */     //   359: aload 8
/*    */     //   361: invokevirtual 529	java/util/ArrayList:add	(Ljava/lang/Object;)Z
/*    */     //   364: pop
/*    */     //   365: aload 4
/*    */     //   367: invokeinterface 249 1 0
/*    */     //   372: ifne -189 -> 183
/*    */     //   375: goto +98 -> 473
/*    */     //   378: astore 6
/*    */     //   380: new 47	java/lang/Exception
/*    */     //   383: dup
/*    */     //   384: new 104	java/lang/StringBuilder
/*    */     //   387: dup
/*    */     //   388: ldc_w 532
/*    */     //   391: invokespecial 108	java/lang/StringBuilder:<init>	(Ljava/lang/String;)V
/*    */     //   394: aload 6
/*    */     //   396: invokevirtual 131	java/lang/Exception:toString	()Ljava/lang/String;
/*    */     //   399: invokevirtual 114	java/lang/StringBuilder:append	(Ljava/lang/String;)Ljava/lang/StringBuilder;
/*    */     //   402: ldc -124
/*    */     //   404: invokevirtual 114	java/lang/StringBuilder:append	(Ljava/lang/String;)Ljava/lang/StringBuilder;
/*    */     //   407: invokevirtual 118	java/lang/StringBuilder:toString	()Ljava/lang/String;
/*    */     //   410: invokespecial 534	java/lang/Exception:<init>	(Ljava/lang/String;)V
/*    */     //   413: athrow
/*    */     //   414: astore 10
/*    */     //   416: aload 4
/*    */     //   418: ifnull +18 -> 436
/*    */     //   421: aload 4
/*    */     //   423: invokeinterface 455 1 0
/*    */     //   428: aconst_null
/*    */     //   429: astore 4
/*    */     //   431: goto +5 -> 436
/*    */     //   434: astore 11
/*    */     //   436: aload_3
/*    */     //   437: ifnull +16 -> 453
/*    */     //   440: aload_3
/*    */     //   441: invokeinterface 535 1 0
/*    */     //   446: aconst_null
/*    */     //   447: astore_3
/*    */     //   448: goto +5 -> 453
/*    */     //   451: astore 11
/*    */     //   453: aload_2
/*    */     //   454: ifnull +16 -> 470
/*    */     //   457: aload_2
/*    */     //   458: invokeinterface 78 1 0
/*    */     //   463: aconst_null
/*    */     //   464: astore_2
/*    */     //   465: goto +5 -> 470
/*    */     //   468: astore 11
/*    */     //   470: aload 10
/*    */     //   472: athrow
/*    */     //   473: aload 4
/*    */     //   475: ifnull +18 -> 493
/*    */     //   478: aload 4
/*    */     //   480: invokeinterface 455 1 0
/*    */     //   485: aconst_null
/*    */     //   486: astore 4
/*    */     //   488: goto +5 -> 493
/*    */     //   491: astore 11
/*    */     //   493: aload_3
/*    */     //   494: ifnull +16 -> 510
/*    */     //   497: aload_3
/*    */     //   498: invokeinterface 535 1 0
/*    */     //   503: aconst_null
/*    */     //   504: astore_3
/*    */     //   505: goto +5 -> 510
/*    */     //   508: astore 11
/*    */     //   510: aload_2
/*    */     //   511: ifnull +16 -> 527
/*    */     //   514: aload_2
/*    */     //   515: invokeinterface 78 1 0
/*    */     //   520: aconst_null
/*    */     //   521: astore_2
/*    */     //   522: goto +5 -> 527
/*    */     //   525: astore 11
/*    */     //   527: aload 5
/*    */     //   529: areturn
/*    */     // Line number table:
/*    */     //   Java source line #185	-> byte code offset #0
/*    */     //   Java source line #186	-> byte code offset #2
/*    */     //   Java source line #187	-> byte code offset #4
/*    */     //   Java source line #188	-> byte code offset #7
/*    */     //   Java source line #190	-> byte code offset #16
/*    */     //   Java source line #192	-> byte code offset #26
/*    */     //   Java source line #193	-> byte code offset #30
/*    */     //   Java source line #194	-> byte code offset #49
/*    */     //   Java source line #196	-> byte code offset #57
/*    */     //   Java source line #199	-> byte code offset #62
/*    */     //   Java source line #200	-> byte code offset #71
/*    */     //   Java source line #201	-> byte code offset #80
/*    */     //   Java source line #202	-> byte code offset #89
/*    */     //   Java source line #204	-> byte code offset #116
/*    */     //   Java source line #206	-> byte code offset #128
/*    */     //   Java source line #207	-> byte code offset #147
/*    */     //   Java source line #209	-> byte code offset #161
/*    */     //   Java source line #212	-> byte code offset #172
/*    */     //   Java source line #214	-> byte code offset #180
/*    */     //   Java source line #215	-> byte code offset #183
/*    */     //   Java source line #216	-> byte code offset #192
/*    */     //   Java source line #218	-> byte code offset #201
/*    */     //   Java source line #219	-> byte code offset #214
/*    */     //   Java source line #220	-> byte code offset #227
/*    */     //   Java source line #221	-> byte code offset #240
/*    */     //   Java source line #222	-> byte code offset #253
/*    */     //   Java source line #223	-> byte code offset #266
/*    */     //   Java source line #224	-> byte code offset #280
/*    */     //   Java source line #225	-> byte code offset #294
/*    */     //   Java source line #226	-> byte code offset #308
/*    */     //   Java source line #227	-> byte code offset #322
/*    */     //   Java source line #228	-> byte code offset #336
/*    */     //   Java source line #229	-> byte code offset #350
/*    */     //   Java source line #230	-> byte code offset #357
/*    */     //   Java source line #214	-> byte code offset #365
/*    */     //   Java source line #232	-> byte code offset #378
/*    */     //   Java source line #233	-> byte code offset #380
/*    */     //   Java source line #234	-> byte code offset #414
/*    */     //   Java source line #235	-> byte code offset #416
/*    */     //   Java source line #236	-> byte code offset #436
/*    */     //   Java source line #237	-> byte code offset #453
/*    */     //   Java source line #238	-> byte code offset #470
/*    */     //   Java source line #235	-> byte code offset #473
/*    */     //   Java source line #236	-> byte code offset #493
/*    */     //   Java source line #237	-> byte code offset #510
/*    */     //   Java source line #239	-> byte code offset #527
/*    */     // Local variable table:
/*    */     //   start	length	slot	name	signature
/*    */     //   0	530	0	this	PuntitosDAO
/*    */     //   0	530	1	telefonoTO	TelefonoTO
/*    */     //   1	521	2	oConn	Connection
/*    */     //   3	502	3	oStmt	java.sql.PreparedStatement
/*    */     //   5	482	4	oRset	java.sql.ResultSet
/*    */     //   14	514	5	lineas	java.util.ArrayList<TelefonoTO>
/*    */     //   28	83	6	where	String
/*    */     //   378	17	6	e	Exception
/*    */     //   69	49	7	query	StringBuffer
/*    */     //   190	170	8	telefono	TelefonoTO
/*    */     //   199	154	9	puntosTO	PuntosTO
/*    */     //   414	57	10	localObject	Object
/*    */     //   434	1	11	localException1	Exception
/*    */     //   451	1	11	localException2	Exception
/*    */     //   468	1	11	localException3	Exception
/*    */     //   491	1	11	localException4	Exception
/*    */     //   508	1	11	localException5	Exception
/*    */     //   525	1	11	localException6	Exception
/*    */     // Exception table:
/*    */     //   from	to	target	type
/*    */     //   16	375	378	java/lang/Exception
/*    */     //   16	414	414	finally
/*    */     //   421	431	434	java/lang/Exception
/*    */     //   440	448	451	java/lang/Exception
/*    */     //   457	465	468	java/lang/Exception
/*    */     //   478	488	491	java/lang/Exception
/*    */     //   497	505	508	java/lang/Exception
/*    */     //   514	522	525	java/lang/Exception
/*    */   }
/*    */   
/*    */   /* Error */
/*    */   public java.util.ArrayList<TelefonoTO> consultaReserva(TelefonoTO telefonoTO)
/*    */     throws Exception
/*    */   {
/*    */     // Byte code:
/*    */     //   0: aconst_null
/*    */     //   1: astore_2
/*    */     //   2: aconst_null
/*    */     //   3: astore_3
/*    */     //   4: aconst_null
/*    */     //   5: astore 4
/*    */     //   7: new 473	java/util/ArrayList
/*    */     //   10: dup
/*    */     //   11: invokespecial 475	java/util/ArrayList:<init>	()V
/*    */     //   14: astore 5
/*    */     //   16: invokestatic 29	com/claro/util/ServiceLocator:getInstance	()Lcom/claro/util/ServiceLocator;
/*    */     //   19: getstatic 61	com/claro/util/ServiceLocator:jdbcCirculoAzul	Ljava/lang/String;
/*    */     //   22: invokevirtual 64	com/claro/util/ServiceLocator:getConnection	(Ljava/lang/String;)Ljava/sql/Connection;
/*    */     //   25: astore_2
/*    */     //   26: new 158	java/lang/StringBuffer
/*    */     //   29: dup
/*    */     //   30: invokespecial 160	java/lang/StringBuffer:<init>	()V
/*    */     //   33: astore 6
/*    */     //   35: aload 6
/*    */     //   37: ldc_w 548
/*    */     //   40: invokevirtual 173	java/lang/StringBuffer:append	(Ljava/lang/String;)Ljava/lang/StringBuffer;
/*    */     //   43: pop
/*    */     //   44: aload 6
/*    */     //   46: ldc_w 550
/*    */     //   49: invokevirtual 173	java/lang/StringBuffer:append	(Ljava/lang/String;)Ljava/lang/StringBuffer;
/*    */     //   52: pop
/*    */     //   53: aload 6
/*    */     //   55: ldc_w 552
/*    */     //   58: invokevirtual 173	java/lang/StringBuffer:append	(Ljava/lang/String;)Ljava/lang/StringBuffer;
/*    */     //   61: pop
/*    */     //   62: aload 6
/*    */     //   64: ldc_w 489
/*    */     //   67: invokevirtual 173	java/lang/StringBuffer:append	(Ljava/lang/String;)Ljava/lang/StringBuffer;
/*    */     //   70: aload_0
/*    */     //   71: getfield 41	com/claro/dao/PuntitosDAO:schema_database	Ljava/lang/String;
/*    */     //   74: invokevirtual 173	java/lang/StringBuffer:append	(Ljava/lang/String;)Ljava/lang/StringBuffer;
/*    */     //   77: ldc_w 554
/*    */     //   80: invokevirtual 173	java/lang/StringBuffer:append	(Ljava/lang/String;)Ljava/lang/StringBuffer;
/*    */     //   83: pop
/*    */     //   84: aload 6
/*    */     //   86: ldc_w 556
/*    */     //   89: invokevirtual 173	java/lang/StringBuffer:append	(Ljava/lang/String;)Ljava/lang/StringBuffer;
/*    */     //   92: pop
/*    */     //   93: aload 6
/*    */     //   95: ldc_w 558
/*    */     //   98: invokevirtual 173	java/lang/StringBuffer:append	(Ljava/lang/String;)Ljava/lang/StringBuffer;
/*    */     //   101: pop
/*    */     //   102: aload_2
/*    */     //   103: aload 6
/*    */     //   105: invokevirtual 242	java/lang/StringBuffer:toString	()Ljava/lang/String;
/*    */     //   108: invokeinterface 493 2 0
/*    */     //   113: astore_3
/*    */     //   114: aload_3
/*    */     //   115: iconst_1
/*    */     //   116: aload_1
/*    */     //   117: invokevirtual 502	com/claro/transfer/TelefonoTO:getCuenta	()Ljava/lang/String;
/*    */     //   120: invokeinterface 497 3 0
/*    */     //   125: aload_3
/*    */     //   126: iconst_2
/*    */     //   127: aload_1
/*    */     //   128: invokevirtual 476	com/claro/transfer/TelefonoTO:getTelefono	()Ljava/lang/String;
/*    */     //   131: invokeinterface 497 3 0
/*    */     //   136: aload_3
/*    */     //   137: iconst_3
/*    */     //   138: aload_1
/*    */     //   139: invokevirtual 560	com/claro/transfer/TelefonoTO:getRegion	()I
/*    */     //   142: invokeinterface 563 3 0
/*    */     //   147: aload_3
/*    */     //   148: invokeinterface 503 1 0
/*    */     //   153: astore 4
/*    */     //   155: goto +242 -> 397
/*    */     //   158: new 73	com/claro/transfer/TelefonoTO
/*    */     //   161: dup
/*    */     //   162: invokespecial 147	com/claro/transfer/TelefonoTO:<init>	()V
/*    */     //   165: astore 7
/*    */     //   167: new 88	com/claro/transfer/PuntosTO
/*    */     //   170: dup
/*    */     //   171: invokespecial 358	com/claro/transfer/PuntosTO:<init>	()V
/*    */     //   174: astore 8
/*    */     //   176: aload 7
/*    */     //   178: aload 4
/*    */     //   180: iconst_1
/*    */     //   181: invokeinterface 506 2 0
/*    */     //   186: invokevirtual 567	com/claro/transfer/TelefonoTO:setFolio	(Ljava/lang/String;)V
/*    */     //   189: aload 7
/*    */     //   191: aload 4
/*    */     //   193: iconst_2
/*    */     //   194: invokeinterface 506 2 0
/*    */     //   199: invokevirtual 260	com/claro/transfer/TelefonoTO:setCuenta	(Ljava/lang/String;)V
/*    */     //   202: aload 7
/*    */     //   204: aload 4
/*    */     //   206: iconst_3
/*    */     //   207: invokeinterface 506 2 0
/*    */     //   212: invokevirtual 265	com/claro/transfer/TelefonoTO:setSecuencia	(Ljava/lang/String;)V
/*    */     //   215: aload 7
/*    */     //   217: aload 4
/*    */     //   219: iconst_4
/*    */     //   220: invokeinterface 509 2 0
/*    */     //   225: invokevirtual 299	com/claro/transfer/TelefonoTO:setRegion	(I)V
/*    */     //   228: aload 7
/*    */     //   230: aload 4
/*    */     //   232: iconst_5
/*    */     //   233: invokeinterface 506 2 0
/*    */     //   238: invokevirtual 310	com/claro/transfer/TelefonoTO:setPlan	(Ljava/lang/String;)V
/*    */     //   241: aload 8
/*    */     //   243: aload 4
/*    */     //   245: bipush 6
/*    */     //   247: invokeinterface 506 2 0
/*    */     //   252: invokevirtual 512	com/claro/transfer/PuntosTO:setEstatusPuntos	(Ljava/lang/String;)V
/*    */     //   255: aload 7
/*    */     //   257: aload 4
/*    */     //   259: bipush 7
/*    */     //   261: invokeinterface 506 2 0
/*    */     //   266: invokevirtual 275	com/claro/transfer/TelefonoTO:setTelefono	(Ljava/lang/String;)V
/*    */     //   269: aload 7
/*    */     //   271: aload 4
/*    */     //   273: bipush 8
/*    */     //   275: invokeinterface 506 2 0
/*    */     //   280: invokevirtual 570	com/claro/transfer/TelefonoTO:setDescripcionPlan	(Ljava/lang/String;)V
/*    */     //   283: aload 7
/*    */     //   285: aload 4
/*    */     //   287: bipush 9
/*    */     //   289: invokeinterface 506 2 0
/*    */     //   294: invokevirtual 573	com/claro/transfer/TelefonoTO:setMarca	(Ljava/lang/String;)V
/*    */     //   297: aload 7
/*    */     //   299: aload 4
/*    */     //   301: bipush 10
/*    */     //   303: invokeinterface 506 2 0
/*    */     //   308: invokevirtual 576	com/claro/transfer/TelefonoTO:setModelo	(Ljava/lang/String;)V
/*    */     //   311: aload 7
/*    */     //   313: aload 4
/*    */     //   315: bipush 11
/*    */     //   317: invokeinterface 518 2 0
/*    */     //   322: invokevirtual 522	com/claro/transfer/TelefonoTO:setFechaExpira	(Ljava/sql/Timestamp;)V
/*    */     //   325: aload 7
/*    */     //   327: aload 4
/*    */     //   329: bipush 12
/*    */     //   331: invokeinterface 506 2 0
/*    */     //   336: invokevirtual 579	com/claro/transfer/TelefonoTO:setTipoRedencion	(Ljava/lang/String;)V
/*    */     //   339: aload 7
/*    */     //   341: aload 4
/*    */     //   343: bipush 13
/*    */     //   345: invokeinterface 506 2 0
/*    */     //   350: invokevirtual 582	com/claro/transfer/TelefonoTO:setTipoProm	(Ljava/lang/String;)V
/*    */     //   353: aload 7
/*    */     //   355: aload 4
/*    */     //   357: bipush 14
/*    */     //   359: invokeinterface 518 2 0
/*    */     //   364: invokevirtual 526	com/claro/transfer/TelefonoTO:setFechaAltaTime	(Ljava/sql/Timestamp;)V
/*    */     //   367: aload 7
/*    */     //   369: aload 4
/*    */     //   371: ldc_w 585
/*    */     //   374: invokeinterface 257 2 0
/*    */     //   379: invokevirtual 587	com/claro/transfer/TelefonoTO:setFzaVta	(Ljava/lang/String;)V
/*    */     //   382: aload 7
/*    */     //   384: aload 8
/*    */     //   386: invokevirtual 440	com/claro/transfer/TelefonoTO:setPuntosTO	(Lcom/claro/transfer/PuntosTO;)V
/*    */     //   389: aload 5
/*    */     //   391: aload 7
/*    */     //   393: invokevirtual 529	java/util/ArrayList:add	(Ljava/lang/Object;)Z
/*    */     //   396: pop
/*    */     //   397: aload 4
/*    */     //   399: invokeinterface 249 1 0
/*    */     //   404: ifne -246 -> 158
/*    */     //   407: goto +98 -> 505
/*    */     //   410: astore 6
/*    */     //   412: new 47	java/lang/Exception
/*    */     //   415: dup
/*    */     //   416: new 104	java/lang/StringBuilder
/*    */     //   419: dup
/*    */     //   420: ldc_w 532
/*    */     //   423: invokespecial 108	java/lang/StringBuilder:<init>	(Ljava/lang/String;)V
/*    */     //   426: aload 6
/*    */     //   428: invokevirtual 131	java/lang/Exception:toString	()Ljava/lang/String;
/*    */     //   431: invokevirtual 114	java/lang/StringBuilder:append	(Ljava/lang/String;)Ljava/lang/StringBuilder;
/*    */     //   434: ldc -124
/*    */     //   436: invokevirtual 114	java/lang/StringBuilder:append	(Ljava/lang/String;)Ljava/lang/StringBuilder;
/*    */     //   439: invokevirtual 118	java/lang/StringBuilder:toString	()Ljava/lang/String;
/*    */     //   442: invokespecial 534	java/lang/Exception:<init>	(Ljava/lang/String;)V
/*    */     //   445: athrow
/*    */     //   446: astore 9
/*    */     //   448: aload 4
/*    */     //   450: ifnull +18 -> 468
/*    */     //   453: aload 4
/*    */     //   455: invokeinterface 455 1 0
/*    */     //   460: aconst_null
/*    */     //   461: astore 4
/*    */     //   463: goto +5 -> 468
/*    */     //   466: astore 10
/*    */     //   468: aload_3
/*    */     //   469: ifnull +16 -> 485
/*    */     //   472: aload_3
/*    */     //   473: invokeinterface 535 1 0
/*    */     //   478: aconst_null
/*    */     //   479: astore_3
/*    */     //   480: goto +5 -> 485
/*    */     //   483: astore 10
/*    */     //   485: aload_2
/*    */     //   486: ifnull +16 -> 502
/*    */     //   489: aload_2
/*    */     //   490: invokeinterface 78 1 0
/*    */     //   495: aconst_null
/*    */     //   496: astore_2
/*    */     //   497: goto +5 -> 502
/*    */     //   500: astore 10
/*    */     //   502: aload 9
/*    */     //   504: athrow
/*    */     //   505: aload 4
/*    */     //   507: ifnull +18 -> 525
/*    */     //   510: aload 4
/*    */     //   512: invokeinterface 455 1 0
/*    */     //   517: aconst_null
/*    */     //   518: astore 4
/*    */     //   520: goto +5 -> 525
/*    */     //   523: astore 10
/*    */     //   525: aload_3
/*    */     //   526: ifnull +16 -> 542
/*    */     //   529: aload_3
/*    */     //   530: invokeinterface 535 1 0
/*    */     //   535: aconst_null
/*    */     //   536: astore_3
/*    */     //   537: goto +5 -> 542
/*    */     //   540: astore 10
/*    */     //   542: aload_2
/*    */     //   543: ifnull +16 -> 559
/*    */     //   546: aload_2
/*    */     //   547: invokeinterface 78 1 0
/*    */     //   552: aconst_null
/*    */     //   553: astore_2
/*    */     //   554: goto +5 -> 559
/*    */     //   557: astore 10
/*    */     //   559: aload 5
/*    */     //   561: areturn
/*    */     // Line number table:
/*    */     //   Java source line #243	-> byte code offset #0
/*    */     //   Java source line #244	-> byte code offset #2
/*    */     //   Java source line #245	-> byte code offset #4
/*    */     //   Java source line #246	-> byte code offset #7
/*    */     //   Java source line #248	-> byte code offset #16
/*    */     //   Java source line #250	-> byte code offset #26
/*    */     //   Java source line #251	-> byte code offset #35
/*    */     //   Java source line #252	-> byte code offset #44
/*    */     //   Java source line #253	-> byte code offset #53
/*    */     //   Java source line #254	-> byte code offset #62
/*    */     //   Java source line #255	-> byte code offset #84
/*    */     //   Java source line #256	-> byte code offset #93
/*    */     //   Java source line #258	-> byte code offset #102
/*    */     //   Java source line #260	-> byte code offset #114
/*    */     //   Java source line #261	-> byte code offset #125
/*    */     //   Java source line #262	-> byte code offset #136
/*    */     //   Java source line #264	-> byte code offset #147
/*    */     //   Java source line #266	-> byte code offset #155
/*    */     //   Java source line #267	-> byte code offset #158
/*    */     //   Java source line #268	-> byte code offset #167
/*    */     //   Java source line #270	-> byte code offset #176
/*    */     //   Java source line #271	-> byte code offset #189
/*    */     //   Java source line #272	-> byte code offset #202
/*    */     //   Java source line #273	-> byte code offset #215
/*    */     //   Java source line #274	-> byte code offset #228
/*    */     //   Java source line #275	-> byte code offset #241
/*    */     //   Java source line #276	-> byte code offset #255
/*    */     //   Java source line #277	-> byte code offset #269
/*    */     //   Java source line #278	-> byte code offset #283
/*    */     //   Java source line #279	-> byte code offset #297
/*    */     //   Java source line #280	-> byte code offset #311
/*    */     //   Java source line #281	-> byte code offset #325
/*    */     //   Java source line #282	-> byte code offset #339
/*    */     //   Java source line #283	-> byte code offset #353
/*    */     //   Java source line #284	-> byte code offset #367
/*    */     //   Java source line #286	-> byte code offset #382
/*    */     //   Java source line #287	-> byte code offset #389
/*    */     //   Java source line #266	-> byte code offset #397
/*    */     //   Java source line #289	-> byte code offset #410
/*    */     //   Java source line #290	-> byte code offset #412
/*    */     //   Java source line #291	-> byte code offset #446
/*    */     //   Java source line #292	-> byte code offset #448
/*    */     //   Java source line #293	-> byte code offset #468
/*    */     //   Java source line #294	-> byte code offset #485
/*    */     //   Java source line #295	-> byte code offset #502
/*    */     //   Java source line #292	-> byte code offset #505
/*    */     //   Java source line #293	-> byte code offset #525
/*    */     //   Java source line #294	-> byte code offset #542
/*    */     //   Java source line #296	-> byte code offset #559
/*    */     // Local variable table:
/*    */     //   start	length	slot	name	signature
/*    */     //   0	562	0	this	PuntitosDAO
/*    */     //   0	562	1	telefonoTO	TelefonoTO
/*    */     //   1	553	2	oConn	Connection
/*    */     //   3	534	3	oStmt	java.sql.PreparedStatement
/*    */     //   5	514	4	oRset	java.sql.ResultSet
/*    */     //   14	546	5	lineas	java.util.ArrayList<TelefonoTO>
/*    */     //   33	71	6	query	StringBuffer
/*    */     //   410	17	6	e	Exception
/*    */     //   165	227	7	telefono	TelefonoTO
/*    */     //   174	211	8	puntosTO	PuntosTO
/*    */     //   446	57	9	localObject	Object
/*    */     //   466	1	10	localException1	Exception
/*    */     //   483	1	10	localException2	Exception
/*    */     //   500	1	10	localException3	Exception
/*    */     //   523	1	10	localException4	Exception
/*    */     //   540	1	10	localException5	Exception
/*    */     //   557	1	10	localException6	Exception
/*    */     // Exception table:
/*    */     //   from	to	target	type
/*    */     //   16	407	410	java/lang/Exception
/*    */     //   16	446	446	finally
/*    */     //   453	463	466	java/lang/Exception
/*    */     //   472	480	483	java/lang/Exception
/*    */     //   489	497	500	java/lang/Exception
/*    */     //   510	520	523	java/lang/Exception
/*    */     //   529	537	540	java/lang/Exception
/*    */     //   546	554	557	java/lang/Exception
/*    */   }
/*    */   
/*    */   /* Error */
/*    */   public boolean cancelaReserva(TelefonoTO telefonoTO)
/*    */     throws Exception
/*    */   {
/*    */     // Byte code:
/*    */     //   0: aconst_null
/*    */     //   1: astore_2
/*    */     //   2: aconst_null
/*    */     //   3: astore_3
/*    */     //   4: iconst_0
/*    */     //   5: istore 4
/*    */     //   7: new 158	java/lang/StringBuffer
/*    */     //   10: dup
/*    */     //   11: invokespecial 160	java/lang/StringBuffer:<init>	()V
/*    */     //   14: astore 5
/*    */     //   16: aload 5
/*    */     //   18: ldc_w 592
/*    */     //   21: invokevirtual 173	java/lang/StringBuffer:append	(Ljava/lang/String;)Ljava/lang/StringBuffer;
/*    */     //   24: aload_0
/*    */     //   25: getfield 41	com/claro/dao/PuntitosDAO:schema_database	Ljava/lang/String;
/*    */     //   28: invokevirtual 173	java/lang/StringBuffer:append	(Ljava/lang/String;)Ljava/lang/StringBuffer;
/*    */     //   31: ldc_w 594
/*    */     //   34: invokevirtual 173	java/lang/StringBuffer:append	(Ljava/lang/String;)Ljava/lang/StringBuffer;
/*    */     //   37: pop
/*    */     //   38: aload 5
/*    */     //   40: ldc_w 596
/*    */     //   43: invokevirtual 173	java/lang/StringBuffer:append	(Ljava/lang/String;)Ljava/lang/StringBuffer;
/*    */     //   46: pop
/*    */     //   47: new 158	java/lang/StringBuffer
/*    */     //   50: dup
/*    */     //   51: invokespecial 160	java/lang/StringBuffer:<init>	()V
/*    */     //   54: astore 6
/*    */     //   56: aload 6
/*    */     //   58: ldc_w 592
/*    */     //   61: invokevirtual 173	java/lang/StringBuffer:append	(Ljava/lang/String;)Ljava/lang/StringBuffer;
/*    */     //   64: aload_0
/*    */     //   65: getfield 41	com/claro/dao/PuntitosDAO:schema_database	Ljava/lang/String;
/*    */     //   68: invokevirtual 173	java/lang/StringBuffer:append	(Ljava/lang/String;)Ljava/lang/StringBuffer;
/*    */     //   71: ldc_w 598
/*    */     //   74: invokevirtual 173	java/lang/StringBuffer:append	(Ljava/lang/String;)Ljava/lang/StringBuffer;
/*    */     //   77: pop
/*    */     //   78: aload 6
/*    */     //   80: ldc_w 600
/*    */     //   83: invokevirtual 173	java/lang/StringBuffer:append	(Ljava/lang/String;)Ljava/lang/StringBuffer;
/*    */     //   86: pop
/*    */     //   87: invokestatic 29	com/claro/util/ServiceLocator:getInstance	()Lcom/claro/util/ServiceLocator;
/*    */     //   90: getstatic 61	com/claro/util/ServiceLocator:jdbcCirculoAzul	Ljava/lang/String;
/*    */     //   93: invokevirtual 64	com/claro/util/ServiceLocator:getConnection	(Ljava/lang/String;)Ljava/sql/Connection;
/*    */     //   96: astore_2
/*    */     //   97: aload_2
/*    */     //   98: iconst_0
/*    */     //   99: invokeinterface 602 2 0
/*    */     //   104: aload_2
/*    */     //   105: aload 5
/*    */     //   107: invokevirtual 242	java/lang/StringBuffer:toString	()Ljava/lang/String;
/*    */     //   110: invokeinterface 493 2 0
/*    */     //   115: astore_3
/*    */     //   116: aload_3
/*    */     //   117: iconst_1
/*    */     //   118: iconst_0
/*    */     //   119: invokeinterface 563 3 0
/*    */     //   124: aload_3
/*    */     //   125: iconst_2
/*    */     //   126: aload_1
/*    */     //   127: invokevirtual 476	com/claro/transfer/TelefonoTO:getTelefono	()Ljava/lang/String;
/*    */     //   130: invokeinterface 497 3 0
/*    */     //   135: aload_3
/*    */     //   136: iconst_3
/*    */     //   137: aload_1
/*    */     //   138: invokevirtual 560	com/claro/transfer/TelefonoTO:getRegion	()I
/*    */     //   141: invokeinterface 563 3 0
/*    */     //   146: aload_3
/*    */     //   147: iconst_4
/*    */     //   148: aload_1
/*    */     //   149: invokevirtual 502	com/claro/transfer/TelefonoTO:getCuenta	()Ljava/lang/String;
/*    */     //   152: invokeinterface 497 3 0
/*    */     //   157: aload_3
/*    */     //   158: invokeinterface 606 1 0
/*    */     //   163: pop
/*    */     //   164: aload_2
/*    */     //   165: aload 6
/*    */     //   167: invokevirtual 242	java/lang/StringBuffer:toString	()Ljava/lang/String;
/*    */     //   170: invokeinterface 493 2 0
/*    */     //   175: astore_3
/*    */     //   176: aload_3
/*    */     //   177: iconst_1
/*    */     //   178: ldc 125
/*    */     //   180: invokeinterface 497 3 0
/*    */     //   185: aload_3
/*    */     //   186: iconst_2
/*    */     //   187: aload_1
/*    */     //   188: invokevirtual 609	com/claro/transfer/TelefonoTO:getIdUsuario	()Ljava/lang/String;
/*    */     //   191: invokeinterface 497 3 0
/*    */     //   196: aload_3
/*    */     //   197: iconst_3
/*    */     //   198: aload_1
/*    */     //   199: invokevirtual 612	com/claro/transfer/TelefonoTO:getFechaAltaTime	()Ljava/sql/Timestamp;
/*    */     //   202: invokeinterface 616 3 0
/*    */     //   207: aload_3
/*    */     //   208: iconst_4
/*    */     //   209: aload_1
/*    */     //   210: invokevirtual 620	com/claro/transfer/TelefonoTO:getFolio	()Ljava/lang/String;
/*    */     //   213: invokeinterface 497 3 0
/*    */     //   218: aload_3
/*    */     //   219: invokeinterface 606 1 0
/*    */     //   224: pop
/*    */     //   225: aload_2
/*    */     //   226: invokeinterface 623 1 0
/*    */     //   231: iconst_1
/*    */     //   232: istore 4
/*    */     //   234: goto +84 -> 318
/*    */     //   237: astore 7
/*    */     //   239: aload_2
/*    */     //   240: invokeinterface 626 1 0
/*    */     //   245: new 47	java/lang/Exception
/*    */     //   248: dup
/*    */     //   249: new 104	java/lang/StringBuilder
/*    */     //   252: dup
/*    */     //   253: ldc_w 629
/*    */     //   256: invokespecial 108	java/lang/StringBuilder:<init>	(Ljava/lang/String;)V
/*    */     //   259: aload 7
/*    */     //   261: invokevirtual 131	java/lang/Exception:toString	()Ljava/lang/String;
/*    */     //   264: invokevirtual 114	java/lang/StringBuilder:append	(Ljava/lang/String;)Ljava/lang/StringBuilder;
/*    */     //   267: ldc -124
/*    */     //   269: invokevirtual 114	java/lang/StringBuilder:append	(Ljava/lang/String;)Ljava/lang/StringBuilder;
/*    */     //   272: invokevirtual 118	java/lang/StringBuilder:toString	()Ljava/lang/String;
/*    */     //   275: invokespecial 534	java/lang/Exception:<init>	(Ljava/lang/String;)V
/*    */     //   278: athrow
/*    */     //   279: astore 8
/*    */     //   281: aload_3
/*    */     //   282: ifnull +16 -> 298
/*    */     //   285: aload_3
/*    */     //   286: invokeinterface 535 1 0
/*    */     //   291: aconst_null
/*    */     //   292: astore_3
/*    */     //   293: goto +5 -> 298
/*    */     //   296: astore 9
/*    */     //   298: aload_2
/*    */     //   299: ifnull +16 -> 315
/*    */     //   302: aload_2
/*    */     //   303: invokeinterface 78 1 0
/*    */     //   308: aconst_null
/*    */     //   309: astore_2
/*    */     //   310: goto +5 -> 315
/*    */     //   313: astore 9
/*    */     //   315: aload 8
/*    */     //   317: athrow
/*    */     //   318: aload_3
/*    */     //   319: ifnull +16 -> 335
/*    */     //   322: aload_3
/*    */     //   323: invokeinterface 535 1 0
/*    */     //   328: aconst_null
/*    */     //   329: astore_3
/*    */     //   330: goto +5 -> 335
/*    */     //   333: astore 9
/*    */     //   335: aload_2
/*    */     //   336: ifnull +16 -> 352
/*    */     //   339: aload_2
/*    */     //   340: invokeinterface 78 1 0
/*    */     //   345: aconst_null
/*    */     //   346: astore_2
/*    */     //   347: goto +5 -> 352
/*    */     //   350: astore 9
/*    */     //   352: iload 4
/*    */     //   354: ireturn
/*    */     // Line number table:
/*    */     //   Java source line #300	-> byte code offset #0
/*    */     //   Java source line #301	-> byte code offset #2
/*    */     //   Java source line #302	-> byte code offset #4
/*    */     //   Java source line #304	-> byte code offset #7
/*    */     //   Java source line #305	-> byte code offset #16
/*    */     //   Java source line #306	-> byte code offset #38
/*    */     //   Java source line #308	-> byte code offset #47
/*    */     //   Java source line #309	-> byte code offset #56
/*    */     //   Java source line #310	-> byte code offset #78
/*    */     //   Java source line #313	-> byte code offset #87
/*    */     //   Java source line #314	-> byte code offset #97
/*    */     //   Java source line #315	-> byte code offset #104
/*    */     //   Java source line #317	-> byte code offset #116
/*    */     //   Java source line #318	-> byte code offset #124
/*    */     //   Java source line #319	-> byte code offset #135
/*    */     //   Java source line #320	-> byte code offset #146
/*    */     //   Java source line #322	-> byte code offset #157
/*    */     //   Java source line #324	-> byte code offset #164
/*    */     //   Java source line #326	-> byte code offset #176
/*    */     //   Java source line #327	-> byte code offset #185
/*    */     //   Java source line #328	-> byte code offset #196
/*    */     //   Java source line #329	-> byte code offset #207
/*    */     //   Java source line #331	-> byte code offset #218
/*    */     //   Java source line #333	-> byte code offset #225
/*    */     //   Java source line #334	-> byte code offset #231
/*    */     //   Java source line #335	-> byte code offset #237
/*    */     //   Java source line #336	-> byte code offset #239
/*    */     //   Java source line #337	-> byte code offset #245
/*    */     //   Java source line #338	-> byte code offset #279
/*    */     //   Java source line #339	-> byte code offset #281
/*    */     //   Java source line #340	-> byte code offset #298
/*    */     //   Java source line #341	-> byte code offset #315
/*    */     //   Java source line #339	-> byte code offset #318
/*    */     //   Java source line #340	-> byte code offset #335
/*    */     //   Java source line #342	-> byte code offset #352
/*    */     // Local variable table:
/*    */     //   start	length	slot	name	signature
/*    */     //   0	355	0	this	PuntitosDAO
/*    */     //   0	355	1	telefonoTO	TelefonoTO
/*    */     //   1	346	2	oConn	Connection
/*    */     //   3	327	3	oStmt	java.sql.PreparedStatement
/*    */     //   5	348	4	accion	boolean
/*    */     //   14	92	5	cancelReservLinea	StringBuffer
/*    */     //   54	112	6	cancelReservacion	StringBuffer
/*    */     //   237	23	7	e	Exception
/*    */     //   279	37	8	localObject	Object
/*    */     //   296	1	9	localException1	Exception
/*    */     //   313	1	9	localException2	Exception
/*    */     //   333	1	9	localException3	Exception
/*    */     //   350	1	9	localException4	Exception
/*    */     // Exception table:
/*    */     //   from	to	target	type
/*    */     //   87	234	237	java/lang/Exception
/*    */     //   87	279	279	finally
/*    */     //   285	293	296	java/lang/Exception
/*    */     //   302	310	313	java/lang/Exception
/*    */     //   322	330	333	java/lang/Exception
/*    */     //   339	347	350	java/lang/Exception
/*    */   }
/*    */   
/*    */   /* Error */
/*    */   public java.util.ArrayList<com.claro.transfer.PuntoVentaTO> consultaPtosVta(com.claro.transfer.PuntoVentaTO puntoVentaTO)
/*    */     throws Exception
/*    */   {
/*    */     // Byte code:
/*    */     //   0: aconst_null
/*    */     //   1: astore_2
/*    */     //   2: aconst_null
/*    */     //   3: astore_3
/*    */     //   4: aconst_null
/*    */     //   5: astore 4
/*    */     //   7: new 473	java/util/ArrayList
/*    */     //   10: dup
/*    */     //   11: invokespecial 475	java/util/ArrayList:<init>	()V
/*    */     //   14: astore 5
/*    */     //   16: invokestatic 29	com/claro/util/ServiceLocator:getInstance	()Lcom/claro/util/ServiceLocator;
/*    */     //   19: getstatic 61	com/claro/util/ServiceLocator:jdbcCirculoAzul	Ljava/lang/String;
/*    */     //   22: invokevirtual 64	com/claro/util/ServiceLocator:getConnection	(Ljava/lang/String;)Ljava/sql/Connection;
/*    */     //   25: astore_2
/*    */     //   26: ldc -95
/*    */     //   28: astore 6
/*    */     //   30: aload_1
/*    */     //   31: invokevirtual 638	com/claro/transfer/PuntoVentaTO:getSegmentoIP	()Ljava/lang/String;
/*    */     //   34: ifnull +15 -> 49
/*    */     //   37: aload_1
/*    */     //   38: invokevirtual 638	com/claro/transfer/PuntoVentaTO:getSegmentoIP	()Ljava/lang/String;
/*    */     //   41: ldc -95
/*    */     //   43: invokevirtual 477	java/lang/String:equalsIgnoreCase	(Ljava/lang/String;)Z
/*    */     //   46: ifeq +29 -> 75
/*    */     //   49: aload_1
/*    */     //   50: invokevirtual 643	com/claro/transfer/PuntoVentaTO:getIdPuntoVta	()Ljava/lang/String;
/*    */     //   53: ifnull +15 -> 68
/*    */     //   56: aload_1
/*    */     //   57: invokevirtual 643	com/claro/transfer/PuntoVentaTO:getIdPuntoVta	()Ljava/lang/String;
/*    */     //   60: ldc -95
/*    */     //   62: invokevirtual 477	java/lang/String:equalsIgnoreCase	(Ljava/lang/String;)Z
/*    */     //   65: ifeq +10 -> 75
/*    */     //   68: aload_1
/*    */     //   69: invokevirtual 646	com/claro/transfer/PuntoVentaTO:getIdRegion	()I
/*    */     //   72: ifle +8 -> 80
/*    */     //   75: ldc_w 649
/*    */     //   78: astore 6
/*    */     //   80: iconst_0
/*    */     //   81: istore 7
/*    */     //   83: iconst_0
/*    */     //   84: istore 8
/*    */     //   86: aload_1
/*    */     //   87: invokevirtual 643	com/claro/transfer/PuntoVentaTO:getIdPuntoVta	()Ljava/lang/String;
/*    */     //   90: ifnull +54 -> 144
/*    */     //   93: aload_1
/*    */     //   94: invokevirtual 643	com/claro/transfer/PuntoVentaTO:getIdPuntoVta	()Ljava/lang/String;
/*    */     //   97: ldc -95
/*    */     //   99: invokevirtual 477	java/lang/String:equalsIgnoreCase	(Ljava/lang/String;)Z
/*    */     //   102: ifne +42 -> 144
/*    */     //   105: new 104	java/lang/StringBuilder
/*    */     //   108: dup
/*    */     //   109: aload 6
/*    */     //   111: invokestatic 651	java/lang/String:valueOf	(Ljava/lang/Object;)Ljava/lang/String;
/*    */     //   114: invokespecial 108	java/lang/StringBuilder:<init>	(Ljava/lang/String;)V
/*    */     //   117: ldc_w 655
/*    */     //   120: invokevirtual 114	java/lang/StringBuilder:append	(Ljava/lang/String;)Ljava/lang/StringBuilder;
/*    */     //   123: aload_1
/*    */     //   124: invokevirtual 643	com/claro/transfer/PuntoVentaTO:getIdPuntoVta	()Ljava/lang/String;
/*    */     //   127: invokevirtual 114	java/lang/StringBuilder:append	(Ljava/lang/String;)Ljava/lang/StringBuilder;
/*    */     //   130: ldc_w 657
/*    */     //   133: invokevirtual 114	java/lang/StringBuilder:append	(Ljava/lang/String;)Ljava/lang/StringBuilder;
/*    */     //   136: invokevirtual 118	java/lang/StringBuilder:toString	()Ljava/lang/String;
/*    */     //   139: astore 6
/*    */     //   141: iconst_1
/*    */     //   142: istore 7
/*    */     //   144: aload_1
/*    */     //   145: invokevirtual 638	com/claro/transfer/PuntoVentaTO:getSegmentoIP	()Ljava/lang/String;
/*    */     //   148: ifnull +72 -> 220
/*    */     //   151: aload_1
/*    */     //   152: invokevirtual 638	com/claro/transfer/PuntoVentaTO:getSegmentoIP	()Ljava/lang/String;
/*    */     //   155: ldc -95
/*    */     //   157: invokevirtual 477	java/lang/String:equalsIgnoreCase	(Ljava/lang/String;)Z
/*    */     //   160: ifne +60 -> 220
/*    */     //   163: iload 7
/*    */     //   165: ifeq +29 -> 194
/*    */     //   168: new 104	java/lang/StringBuilder
/*    */     //   171: dup
/*    */     //   172: aload 6
/*    */     //   174: invokestatic 651	java/lang/String:valueOf	(Ljava/lang/Object;)Ljava/lang/String;
/*    */     //   177: invokespecial 108	java/lang/StringBuilder:<init>	(Ljava/lang/String;)V
/*    */     //   180: ldc_w 659
/*    */     //   183: invokevirtual 114	java/lang/StringBuilder:append	(Ljava/lang/String;)Ljava/lang/StringBuilder;
/*    */     //   186: invokevirtual 118	java/lang/StringBuilder:toString	()Ljava/lang/String;
/*    */     //   189: astore 6
/*    */     //   191: goto +26 -> 217
/*    */     //   194: new 104	java/lang/StringBuilder
/*    */     //   197: dup
/*    */     //   198: aload 6
/*    */     //   200: invokestatic 651	java/lang/String:valueOf	(Ljava/lang/Object;)Ljava/lang/String;
/*    */     //   203: invokespecial 108	java/lang/StringBuilder:<init>	(Ljava/lang/String;)V
/*    */     //   206: ldc_w 661
/*    */     //   209: invokevirtual 114	java/lang/StringBuilder:append	(Ljava/lang/String;)Ljava/lang/StringBuilder;
/*    */     //   212: invokevirtual 118	java/lang/StringBuilder:toString	()Ljava/lang/String;
/*    */     //   215: astore 6
/*    */     //   217: iconst_1
/*    */     //   218: istore 8
/*    */     //   220: aload_1
/*    */     //   221: invokevirtual 646	com/claro/transfer/PuntoVentaTO:getIdRegion	()I
/*    */     //   224: ifle +62 -> 286
/*    */     //   227: iload 7
/*    */     //   229: ifne +8 -> 237
/*    */     //   232: iload 8
/*    */     //   234: ifeq +29 -> 263
/*    */     //   237: new 104	java/lang/StringBuilder
/*    */     //   240: dup
/*    */     //   241: aload 6
/*    */     //   243: invokestatic 651	java/lang/String:valueOf	(Ljava/lang/Object;)Ljava/lang/String;
/*    */     //   246: invokespecial 108	java/lang/StringBuilder:<init>	(Ljava/lang/String;)V
/*    */     //   249: ldc_w 663
/*    */     //   252: invokevirtual 114	java/lang/StringBuilder:append	(Ljava/lang/String;)Ljava/lang/StringBuilder;
/*    */     //   255: invokevirtual 118	java/lang/StringBuilder:toString	()Ljava/lang/String;
/*    */     //   258: astore 6
/*    */     //   260: goto +26 -> 286
/*    */     //   263: new 104	java/lang/StringBuilder
/*    */     //   266: dup
/*    */     //   267: aload 6
/*    */     //   269: invokestatic 651	java/lang/String:valueOf	(Ljava/lang/Object;)Ljava/lang/String;
/*    */     //   272: invokespecial 108	java/lang/StringBuilder:<init>	(Ljava/lang/String;)V
/*    */     //   275: ldc_w 665
/*    */     //   278: invokevirtual 114	java/lang/StringBuilder:append	(Ljava/lang/String;)Ljava/lang/StringBuilder;
/*    */     //   281: invokevirtual 118	java/lang/StringBuilder:toString	()Ljava/lang/String;
/*    */     //   284: astore 6
/*    */     //   286: new 158	java/lang/StringBuffer
/*    */     //   289: dup
/*    */     //   290: invokespecial 160	java/lang/StringBuffer:<init>	()V
/*    */     //   293: astore 9
/*    */     //   295: aload 9
/*    */     //   297: ldc_w 667
/*    */     //   300: invokevirtual 173	java/lang/StringBuffer:append	(Ljava/lang/String;)Ljava/lang/StringBuffer;
/*    */     //   303: pop
/*    */     //   304: aload 9
/*    */     //   306: ldc_w 669
/*    */     //   309: invokevirtual 173	java/lang/StringBuffer:append	(Ljava/lang/String;)Ljava/lang/StringBuffer;
/*    */     //   312: aload_0
/*    */     //   313: getfield 41	com/claro/dao/PuntitosDAO:schema_database	Ljava/lang/String;
/*    */     //   316: invokevirtual 173	java/lang/StringBuffer:append	(Ljava/lang/String;)Ljava/lang/StringBuffer;
/*    */     //   319: ldc_w 671
/*    */     //   322: invokevirtual 173	java/lang/StringBuffer:append	(Ljava/lang/String;)Ljava/lang/StringBuffer;
/*    */     //   325: aload 6
/*    */     //   327: invokevirtual 173	java/lang/StringBuffer:append	(Ljava/lang/String;)Ljava/lang/StringBuffer;
/*    */     //   330: pop
/*    */     //   331: aload_2
/*    */     //   332: aload 9
/*    */     //   334: invokevirtual 242	java/lang/StringBuffer:toString	()Ljava/lang/String;
/*    */     //   337: invokeinterface 493 2 0
/*    */     //   342: astore_3
/*    */     //   343: iconst_0
/*    */     //   344: istore 10
/*    */     //   346: aload_1
/*    */     //   347: invokevirtual 638	com/claro/transfer/PuntoVentaTO:getSegmentoIP	()Ljava/lang/String;
/*    */     //   350: ifnull +30 -> 380
/*    */     //   353: aload_1
/*    */     //   354: invokevirtual 638	com/claro/transfer/PuntoVentaTO:getSegmentoIP	()Ljava/lang/String;
/*    */     //   357: ldc -95
/*    */     //   359: invokevirtual 477	java/lang/String:equalsIgnoreCase	(Ljava/lang/String;)Z
/*    */     //   362: ifne +18 -> 380
/*    */     //   365: iinc 10 1
/*    */     //   368: aload_3
/*    */     //   369: iload 10
/*    */     //   371: aload_1
/*    */     //   372: invokevirtual 638	com/claro/transfer/PuntoVentaTO:getSegmentoIP	()Ljava/lang/String;
/*    */     //   375: invokeinterface 497 3 0
/*    */     //   380: aload_1
/*    */     //   381: invokevirtual 646	com/claro/transfer/PuntoVentaTO:getIdRegion	()I
/*    */     //   384: ifle +18 -> 402
/*    */     //   387: iinc 10 1
/*    */     //   390: aload_3
/*    */     //   391: iload 10
/*    */     //   393: aload_1
/*    */     //   394: invokevirtual 646	com/claro/transfer/PuntoVentaTO:getIdRegion	()I
/*    */     //   397: invokeinterface 563 3 0
/*    */     //   402: aload_3
/*    */     //   403: invokeinterface 503 1 0
/*    */     //   408: astore 4
/*    */     //   410: goto +99 -> 509
/*    */     //   413: new 639	com/claro/transfer/PuntoVentaTO
/*    */     //   416: dup
/*    */     //   417: invokespecial 673	com/claro/transfer/PuntoVentaTO:<init>	()V
/*    */     //   420: astore 11
/*    */     //   422: aload 11
/*    */     //   424: aload 4
/*    */     //   426: iconst_1
/*    */     //   427: invokeinterface 506 2 0
/*    */     //   432: invokevirtual 674	com/claro/transfer/PuntoVentaTO:setIdPuntoVta	(Ljava/lang/String;)V
/*    */     //   435: aload 11
/*    */     //   437: aload 4
/*    */     //   439: iconst_2
/*    */     //   440: invokeinterface 506 2 0
/*    */     //   445: invokevirtual 677	com/claro/transfer/PuntoVentaTO:setSegmentoIP	(Ljava/lang/String;)V
/*    */     //   448: aload 11
/*    */     //   450: aload 4
/*    */     //   452: iconst_3
/*    */     //   453: invokeinterface 509 2 0
/*    */     //   458: invokevirtual 680	com/claro/transfer/PuntoVentaTO:setRangoInf	(I)V
/*    */     //   461: aload 11
/*    */     //   463: aload 4
/*    */     //   465: iconst_4
/*    */     //   466: invokeinterface 509 2 0
/*    */     //   471: invokevirtual 683	com/claro/transfer/PuntoVentaTO:setRangoSup	(I)V
/*    */     //   474: aload 11
/*    */     //   476: aload 4
/*    */     //   478: iconst_5
/*    */     //   479: invokeinterface 509 2 0
/*    */     //   484: invokevirtual 686	com/claro/transfer/PuntoVentaTO:setIdRegion	(I)V
/*    */     //   487: aload 11
/*    */     //   489: aload 4
/*    */     //   491: bipush 6
/*    */     //   493: invokeinterface 509 2 0
/*    */     //   498: invokevirtual 689	com/claro/transfer/PuntoVentaTO:setIvaProcentaje	(I)V
/*    */     //   501: aload 5
/*    */     //   503: aload 11
/*    */     //   505: invokevirtual 529	java/util/ArrayList:add	(Ljava/lang/Object;)Z
/*    */     //   508: pop
/*    */     //   509: aload 4
/*    */     //   511: invokeinterface 249 1 0
/*    */     //   516: ifne -103 -> 413
/*    */     //   519: goto +98 -> 617
/*    */     //   522: astore 6
/*    */     //   524: new 47	java/lang/Exception
/*    */     //   527: dup
/*    */     //   528: new 104	java/lang/StringBuilder
/*    */     //   531: dup
/*    */     //   532: ldc_w 532
/*    */     //   535: invokespecial 108	java/lang/StringBuilder:<init>	(Ljava/lang/String;)V
/*    */     //   538: aload 6
/*    */     //   540: invokevirtual 131	java/lang/Exception:toString	()Ljava/lang/String;
/*    */     //   543: invokevirtual 114	java/lang/StringBuilder:append	(Ljava/lang/String;)Ljava/lang/StringBuilder;
/*    */     //   546: ldc -124
/*    */     //   548: invokevirtual 114	java/lang/StringBuilder:append	(Ljava/lang/String;)Ljava/lang/StringBuilder;
/*    */     //   551: invokevirtual 118	java/lang/StringBuilder:toString	()Ljava/lang/String;
/*    */     //   554: invokespecial 534	java/lang/Exception:<init>	(Ljava/lang/String;)V
/*    */     //   557: athrow
/*    */     //   558: astore 12
/*    */     //   560: aload 4
/*    */     //   562: ifnull +18 -> 580
/*    */     //   565: aload 4
/*    */     //   567: invokeinterface 455 1 0
/*    */     //   572: aconst_null
/*    */     //   573: astore 4
/*    */     //   575: goto +5 -> 580
/*    */     //   578: astore 13
/*    */     //   580: aload_3
/*    */     //   581: ifnull +16 -> 597
/*    */     //   584: aload_3
/*    */     //   585: invokeinterface 535 1 0
/*    */     //   590: aconst_null
/*    */     //   591: astore_3
/*    */     //   592: goto +5 -> 597
/*    */     //   595: astore 13
/*    */     //   597: aload_2
/*    */     //   598: ifnull +16 -> 614
/*    */     //   601: aload_2
/*    */     //   602: invokeinterface 78 1 0
/*    */     //   607: aconst_null
/*    */     //   608: astore_2
/*    */     //   609: goto +5 -> 614
/*    */     //   612: astore 13
/*    */     //   614: aload 12
/*    */     //   616: athrow
/*    */     //   617: aload 4
/*    */     //   619: ifnull +18 -> 637
/*    */     //   622: aload 4
/*    */     //   624: invokeinterface 455 1 0
/*    */     //   629: aconst_null
/*    */     //   630: astore 4
/*    */     //   632: goto +5 -> 637
/*    */     //   635: astore 13
/*    */     //   637: aload_3
/*    */     //   638: ifnull +16 -> 654
/*    */     //   641: aload_3
/*    */     //   642: invokeinterface 535 1 0
/*    */     //   647: aconst_null
/*    */     //   648: astore_3
/*    */     //   649: goto +5 -> 654
/*    */     //   652: astore 13
/*    */     //   654: aload_2
/*    */     //   655: ifnull +16 -> 671
/*    */     //   658: aload_2
/*    */     //   659: invokeinterface 78 1 0
/*    */     //   664: aconst_null
/*    */     //   665: astore_2
/*    */     //   666: goto +5 -> 671
/*    */     //   669: astore 13
/*    */     //   671: aload 5
/*    */     //   673: areturn
/*    */     // Line number table:
/*    */     //   Java source line #346	-> byte code offset #0
/*    */     //   Java source line #347	-> byte code offset #2
/*    */     //   Java source line #348	-> byte code offset #4
/*    */     //   Java source line #349	-> byte code offset #7
/*    */     //   Java source line #351	-> byte code offset #16
/*    */     //   Java source line #353	-> byte code offset #26
/*    */     //   Java source line #354	-> byte code offset #30
/*    */     //   Java source line #355	-> byte code offset #49
/*    */     //   Java source line #356	-> byte code offset #68
/*    */     //   Java source line #357	-> byte code offset #75
/*    */     //   Java source line #358	-> byte code offset #80
/*    */     //   Java source line #359	-> byte code offset #86
/*    */     //   Java source line #360	-> byte code offset #105
/*    */     //   Java source line #362	-> byte code offset #144
/*    */     //   Java source line #363	-> byte code offset #163
/*    */     //   Java source line #365	-> byte code offset #220
/*    */     //   Java source line #366	-> byte code offset #227
/*    */     //   Java source line #369	-> byte code offset #286
/*    */     //   Java source line #370	-> byte code offset #295
/*    */     //   Java source line #371	-> byte code offset #304
/*    */     //   Java source line #373	-> byte code offset #331
/*    */     //   Java source line #376	-> byte code offset #343
/*    */     //   Java source line #377	-> byte code offset #346
/*    */     //   Java source line #378	-> byte code offset #368
/*    */     //   Java source line #380	-> byte code offset #380
/*    */     //   Java source line #382	-> byte code offset #402
/*    */     //   Java source line #384	-> byte code offset #410
/*    */     //   Java source line #385	-> byte code offset #413
/*    */     //   Java source line #386	-> byte code offset #422
/*    */     //   Java source line #387	-> byte code offset #435
/*    */     //   Java source line #388	-> byte code offset #448
/*    */     //   Java source line #389	-> byte code offset #461
/*    */     //   Java source line #390	-> byte code offset #474
/*    */     //   Java source line #391	-> byte code offset #487
/*    */     //   Java source line #392	-> byte code offset #501
/*    */     //   Java source line #384	-> byte code offset #509
/*    */     //   Java source line #394	-> byte code offset #522
/*    */     //   Java source line #395	-> byte code offset #524
/*    */     //   Java source line #396	-> byte code offset #558
/*    */     //   Java source line #397	-> byte code offset #560
/*    */     //   Java source line #398	-> byte code offset #580
/*    */     //   Java source line #399	-> byte code offset #597
/*    */     //   Java source line #400	-> byte code offset #614
/*    */     //   Java source line #397	-> byte code offset #617
/*    */     //   Java source line #398	-> byte code offset #637
/*    */     //   Java source line #399	-> byte code offset #654
/*    */     //   Java source line #401	-> byte code offset #671
/*    */     // Local variable table:
/*    */     //   start	length	slot	name	signature
/*    */     //   0	674	0	this	PuntitosDAO
/*    */     //   0	674	1	puntoVentaTO	com.claro.transfer.PuntoVentaTO
/*    */     //   1	665	2	oConn	Connection
/*    */     //   3	646	3	oStmt	java.sql.PreparedStatement
/*    */     //   5	626	4	oRset	java.sql.ResultSet
/*    */     //   14	658	5	puntosVenta	java.util.ArrayList<com.claro.transfer.PuntoVentaTO>
/*    */     //   28	298	6	where	String
/*    */     //   522	17	6	e	Exception
/*    */     //   81	147	7	ip	boolean
/*    */     //   84	149	8	vta	boolean
/*    */     //   293	40	9	query	StringBuffer
/*    */     //   344	48	10	i	int
/*    */     //   420	84	11	puntos	com.claro.transfer.PuntoVentaTO
/*    */     //   558	57	12	localObject	Object
/*    */     //   578	1	13	localException1	Exception
/*    */     //   595	1	13	localException2	Exception
/*    */     //   612	1	13	localException3	Exception
/*    */     //   635	1	13	localException4	Exception
/*    */     //   652	1	13	localException5	Exception
/*    */     //   669	1	13	localException6	Exception
/*    */     // Exception table:
/*    */     //   from	to	target	type
/*    */     //   16	519	522	java/lang/Exception
/*    */     //   16	558	558	finally
/*    */     //   565	575	578	java/lang/Exception
/*    */     //   584	592	595	java/lang/Exception
/*    */     //   601	609	612	java/lang/Exception
/*    */     //   622	632	635	java/lang/Exception
/*    */     //   641	649	652	java/lang/Exception
/*    */     //   658	666	669	java/lang/Exception
/*    */   }
/*    */   
/*    */   /* Error */
/*    */   public com.claro.transfer.PuntoVentaTO consultaPtoVta(Connection oConn, com.claro.transfer.PuntoVentaTO puntoVentaTO)
/*    */     throws Exception
/*    */   {
/*    */     // Byte code:
/*    */     //   0: aconst_null
/*    */     //   1: astore_3
/*    */     //   2: aconst_null
/*    */     //   3: astore 4
/*    */     //   5: new 639	com/claro/transfer/PuntoVentaTO
/*    */     //   8: dup
/*    */     //   9: invokespecial 673	com/claro/transfer/PuntoVentaTO:<init>	()V
/*    */     //   12: astore 5
/*    */     //   14: new 158	java/lang/StringBuffer
/*    */     //   17: dup
/*    */     //   18: invokespecial 160	java/lang/StringBuffer:<init>	()V
/*    */     //   21: astore 6
/*    */     //   23: aload 6
/*    */     //   25: ldc_w 667
/*    */     //   28: invokevirtual 173	java/lang/StringBuffer:append	(Ljava/lang/String;)Ljava/lang/StringBuffer;
/*    */     //   31: pop
/*    */     //   32: aload 6
/*    */     //   34: ldc_w 669
/*    */     //   37: invokevirtual 173	java/lang/StringBuffer:append	(Ljava/lang/String;)Ljava/lang/StringBuffer;
/*    */     //   40: aload_0
/*    */     //   41: getfield 41	com/claro/dao/PuntitosDAO:schema_database	Ljava/lang/String;
/*    */     //   44: invokevirtual 173	java/lang/StringBuffer:append	(Ljava/lang/String;)Ljava/lang/StringBuffer;
/*    */     //   47: ldc_w 703
/*    */     //   50: invokevirtual 173	java/lang/StringBuffer:append	(Ljava/lang/String;)Ljava/lang/StringBuffer;
/*    */     //   53: pop
/*    */     //   54: aload_1
/*    */     //   55: aload 6
/*    */     //   57: invokevirtual 242	java/lang/StringBuffer:toString	()Ljava/lang/String;
/*    */     //   60: invokeinterface 493 2 0
/*    */     //   65: astore_3
/*    */     //   66: aload_3
/*    */     //   67: iconst_1
/*    */     //   68: aload_2
/*    */     //   69: invokevirtual 643	com/claro/transfer/PuntoVentaTO:getIdPuntoVta	()Ljava/lang/String;
/*    */     //   72: invokeinterface 497 3 0
/*    */     //   77: aload_3
/*    */     //   78: invokeinterface 503 1 0
/*    */     //   83: astore 4
/*    */     //   85: goto +16 -> 101
/*    */     //   88: aload 5
/*    */     //   90: aload 4
/*    */     //   92: iconst_1
/*    */     //   93: invokeinterface 506 2 0
/*    */     //   98: invokevirtual 674	com/claro/transfer/PuntoVentaTO:setIdPuntoVta	(Ljava/lang/String;)V
/*    */     //   101: aload 4
/*    */     //   103: invokeinterface 249 1 0
/*    */     //   108: ifne -20 -> 88
/*    */     //   111: goto +81 -> 192
/*    */     //   114: astore 6
/*    */     //   116: new 47	java/lang/Exception
/*    */     //   119: dup
/*    */     //   120: new 104	java/lang/StringBuilder
/*    */     //   123: dup
/*    */     //   124: ldc_w 532
/*    */     //   127: invokespecial 108	java/lang/StringBuilder:<init>	(Ljava/lang/String;)V
/*    */     //   130: aload 6
/*    */     //   132: invokevirtual 131	java/lang/Exception:toString	()Ljava/lang/String;
/*    */     //   135: invokevirtual 114	java/lang/StringBuilder:append	(Ljava/lang/String;)Ljava/lang/StringBuilder;
/*    */     //   138: ldc -124
/*    */     //   140: invokevirtual 114	java/lang/StringBuilder:append	(Ljava/lang/String;)Ljava/lang/StringBuilder;
/*    */     //   143: invokevirtual 118	java/lang/StringBuilder:toString	()Ljava/lang/String;
/*    */     //   146: invokespecial 534	java/lang/Exception:<init>	(Ljava/lang/String;)V
/*    */     //   149: athrow
/*    */     //   150: astore 7
/*    */     //   152: aload 4
/*    */     //   154: ifnull +18 -> 172
/*    */     //   157: aload 4
/*    */     //   159: invokeinterface 455 1 0
/*    */     //   164: aconst_null
/*    */     //   165: astore 4
/*    */     //   167: goto +5 -> 172
/*    */     //   170: astore 8
/*    */     //   172: aload_3
/*    */     //   173: ifnull +16 -> 189
/*    */     //   176: aload_3
/*    */     //   177: invokeinterface 535 1 0
/*    */     //   182: aconst_null
/*    */     //   183: astore_3
/*    */     //   184: goto +5 -> 189
/*    */     //   187: astore 8
/*    */     //   189: aload 7
/*    */     //   191: athrow
/*    */     //   192: aload 4
/*    */     //   194: ifnull +18 -> 212
/*    */     //   197: aload 4
/*    */     //   199: invokeinterface 455 1 0
/*    */     //   204: aconst_null
/*    */     //   205: astore 4
/*    */     //   207: goto +5 -> 212
/*    */     //   210: astore 8
/*    */     //   212: aload_3
/*    */     //   213: ifnull +16 -> 229
/*    */     //   216: aload_3
/*    */     //   217: invokeinterface 535 1 0
/*    */     //   222: aconst_null
/*    */     //   223: astore_3
/*    */     //   224: goto +5 -> 229
/*    */     //   227: astore 8
/*    */     //   229: aload 5
/*    */     //   231: areturn
/*    */     // Line number table:
/*    */     //   Java source line #405	-> byte code offset #0
/*    */     //   Java source line #406	-> byte code offset #2
/*    */     //   Java source line #407	-> byte code offset #5
/*    */     //   Java source line #410	-> byte code offset #14
/*    */     //   Java source line #411	-> byte code offset #23
/*    */     //   Java source line #412	-> byte code offset #32
/*    */     //   Java source line #414	-> byte code offset #54
/*    */     //   Java source line #416	-> byte code offset #66
/*    */     //   Java source line #418	-> byte code offset #77
/*    */     //   Java source line #420	-> byte code offset #85
/*    */     //   Java source line #421	-> byte code offset #88
/*    */     //   Java source line #420	-> byte code offset #101
/*    */     //   Java source line #423	-> byte code offset #114
/*    */     //   Java source line #424	-> byte code offset #116
/*    */     //   Java source line #425	-> byte code offset #150
/*    */     //   Java source line #426	-> byte code offset #152
/*    */     //   Java source line #427	-> byte code offset #172
/*    */     //   Java source line #428	-> byte code offset #189
/*    */     //   Java source line #426	-> byte code offset #192
/*    */     //   Java source line #427	-> byte code offset #212
/*    */     //   Java source line #429	-> byte code offset #229
/*    */     // Local variable table:
/*    */     //   start	length	slot	name	signature
/*    */     //   0	232	0	this	PuntitosDAO
/*    */     //   0	232	1	oConn	Connection
/*    */     //   0	232	2	puntoVentaTO	com.claro.transfer.PuntoVentaTO
/*    */     //   1	223	3	oStmt	java.sql.PreparedStatement
/*    */     //   3	203	4	oRset	java.sql.ResultSet
/*    */     //   12	218	5	puntoVenta	com.claro.transfer.PuntoVentaTO
/*    */     //   21	35	6	query	StringBuffer
/*    */     //   114	17	6	e	Exception
/*    */     //   150	40	7	localObject	Object
/*    */     //   170	1	8	localException1	Exception
/*    */     //   187	1	8	localException2	Exception
/*    */     //   210	1	8	localException3	Exception
/*    */     //   227	1	8	localException4	Exception
/*    */     // Exception table:
/*    */     //   from	to	target	type
/*    */     //   14	111	114	java/lang/Exception
/*    */     //   14	150	150	finally
/*    */     //   157	167	170	java/lang/Exception
/*    */     //   176	184	187	java/lang/Exception
/*    */     //   197	207	210	java/lang/Exception
/*    */     //   216	224	227	java/lang/Exception
/*    */   }
/*    */   
/*    */   /* Error */
/*    */   public boolean agregaPtoVta(com.claro.transfer.PuntoVentaTO puntoVentaTO)
/*    */     throws Exception
/*    */   {
/*    */     // Byte code:
/*    */     //   0: aconst_null
/*    */     //   1: astore_2
/*    */     //   2: aconst_null
/*    */     //   3: astore_3
/*    */     //   4: iconst_0
/*    */     //   5: istore 4
/*    */     //   7: invokestatic 29	com/claro/util/ServiceLocator:getInstance	()Lcom/claro/util/ServiceLocator;
/*    */     //   10: getstatic 61	com/claro/util/ServiceLocator:jdbcCirculoAzul	Ljava/lang/String;
/*    */     //   13: invokevirtual 64	com/claro/util/ServiceLocator:getConnection	(Ljava/lang/String;)Ljava/sql/Connection;
/*    */     //   16: astore_2
/*    */     //   17: aload_0
/*    */     //   18: aload_2
/*    */     //   19: aload_1
/*    */     //   20: invokevirtual 708	com/claro/dao/PuntitosDAO:consultaPtoVta	(Ljava/sql/Connection;Lcom/claro/transfer/PuntoVentaTO;)Lcom/claro/transfer/PuntoVentaTO;
/*    */     //   23: astore 5
/*    */     //   25: aload 5
/*    */     //   27: invokevirtual 643	com/claro/transfer/PuntoVentaTO:getIdPuntoVta	()Ljava/lang/String;
/*    */     //   30: ifnonnull +210 -> 240
/*    */     //   33: new 158	java/lang/StringBuffer
/*    */     //   36: dup
/*    */     //   37: invokespecial 160	java/lang/StringBuffer:<init>	()V
/*    */     //   40: astore 6
/*    */     //   42: aload 6
/*    */     //   44: ldc_w 710
/*    */     //   47: invokevirtual 173	java/lang/StringBuffer:append	(Ljava/lang/String;)Ljava/lang/StringBuffer;
/*    */     //   50: aload_0
/*    */     //   51: getfield 41	com/claro/dao/PuntitosDAO:schema_database	Ljava/lang/String;
/*    */     //   54: invokevirtual 173	java/lang/StringBuffer:append	(Ljava/lang/String;)Ljava/lang/StringBuffer;
/*    */     //   57: ldc_w 712
/*    */     //   60: invokevirtual 173	java/lang/StringBuffer:append	(Ljava/lang/String;)Ljava/lang/StringBuffer;
/*    */     //   63: pop
/*    */     //   64: aload 6
/*    */     //   66: ldc_w 714
/*    */     //   69: invokevirtual 173	java/lang/StringBuffer:append	(Ljava/lang/String;)Ljava/lang/StringBuffer;
/*    */     //   72: pop
/*    */     //   73: aload_2
/*    */     //   74: aload 6
/*    */     //   76: invokevirtual 242	java/lang/StringBuffer:toString	()Ljava/lang/String;
/*    */     //   79: invokeinterface 493 2 0
/*    */     //   84: astore_3
/*    */     //   85: aload_3
/*    */     //   86: iconst_1
/*    */     //   87: aload_1
/*    */     //   88: invokevirtual 643	com/claro/transfer/PuntoVentaTO:getIdPuntoVta	()Ljava/lang/String;
/*    */     //   91: invokeinterface 497 3 0
/*    */     //   96: aload_3
/*    */     //   97: iconst_2
/*    */     //   98: aload_1
/*    */     //   99: invokevirtual 638	com/claro/transfer/PuntoVentaTO:getSegmentoIP	()Ljava/lang/String;
/*    */     //   102: invokeinterface 497 3 0
/*    */     //   107: aload_3
/*    */     //   108: iconst_3
/*    */     //   109: aload_1
/*    */     //   110: invokevirtual 716	com/claro/transfer/PuntoVentaTO:getRangoInf	()I
/*    */     //   113: invokeinterface 563 3 0
/*    */     //   118: aload_3
/*    */     //   119: iconst_4
/*    */     //   120: aload_1
/*    */     //   121: invokevirtual 719	com/claro/transfer/PuntoVentaTO:getRangoSup	()I
/*    */     //   124: invokeinterface 563 3 0
/*    */     //   129: aload_3
/*    */     //   130: iconst_5
/*    */     //   131: aload_1
/*    */     //   132: invokevirtual 646	com/claro/transfer/PuntoVentaTO:getIdRegion	()I
/*    */     //   135: invokeinterface 563 3 0
/*    */     //   140: aload_3
/*    */     //   141: bipush 6
/*    */     //   143: aload_1
/*    */     //   144: invokevirtual 722	com/claro/transfer/PuntoVentaTO:getIvaProcentaje	()I
/*    */     //   147: invokeinterface 563 3 0
/*    */     //   152: aload_3
/*    */     //   153: invokeinterface 606 1 0
/*    */     //   158: pop
/*    */     //   159: iconst_1
/*    */     //   160: istore 4
/*    */     //   162: goto +78 -> 240
/*    */     //   165: astore 5
/*    */     //   167: new 47	java/lang/Exception
/*    */     //   170: dup
/*    */     //   171: new 104	java/lang/StringBuilder
/*    */     //   174: dup
/*    */     //   175: ldc_w 629
/*    */     //   178: invokespecial 108	java/lang/StringBuilder:<init>	(Ljava/lang/String;)V
/*    */     //   181: aload 5
/*    */     //   183: invokevirtual 131	java/lang/Exception:toString	()Ljava/lang/String;
/*    */     //   186: invokevirtual 114	java/lang/StringBuilder:append	(Ljava/lang/String;)Ljava/lang/StringBuilder;
/*    */     //   189: ldc -124
/*    */     //   191: invokevirtual 114	java/lang/StringBuilder:append	(Ljava/lang/String;)Ljava/lang/StringBuilder;
/*    */     //   194: invokevirtual 118	java/lang/StringBuilder:toString	()Ljava/lang/String;
/*    */     //   197: invokespecial 534	java/lang/Exception:<init>	(Ljava/lang/String;)V
/*    */     //   200: athrow
/*    */     //   201: astore 7
/*    */     //   203: aload_3
/*    */     //   204: ifnull +16 -> 220
/*    */     //   207: aload_3
/*    */     //   208: invokeinterface 535 1 0
/*    */     //   213: aconst_null
/*    */     //   214: astore_3
/*    */     //   215: goto +5 -> 220
/*    */     //   218: astore 8
/*    */     //   220: aload_2
/*    */     //   221: ifnull +16 -> 237
/*    */     //   224: aload_2
/*    */     //   225: invokeinterface 78 1 0
/*    */     //   230: aconst_null
/*    */     //   231: astore_2
/*    */     //   232: goto +5 -> 237
/*    */     //   235: astore 8
/*    */     //   237: aload 7
/*    */     //   239: athrow
/*    */     //   240: aload_3
/*    */     //   241: ifnull +16 -> 257
/*    */     //   244: aload_3
/*    */     //   245: invokeinterface 535 1 0
/*    */     //   250: aconst_null
/*    */     //   251: astore_3
/*    */     //   252: goto +5 -> 257
/*    */     //   255: astore 8
/*    */     //   257: aload_2
/*    */     //   258: ifnull +16 -> 274
/*    */     //   261: aload_2
/*    */     //   262: invokeinterface 78 1 0
/*    */     //   267: aconst_null
/*    */     //   268: astore_2
/*    */     //   269: goto +5 -> 274
/*    */     //   272: astore 8
/*    */     //   274: iload 4
/*    */     //   276: ireturn
/*    */     // Line number table:
/*    */     //   Java source line #438	-> byte code offset #0
/*    */     //   Java source line #439	-> byte code offset #2
/*    */     //   Java source line #440	-> byte code offset #4
/*    */     //   Java source line #442	-> byte code offset #7
/*    */     //   Java source line #443	-> byte code offset #17
/*    */     //   Java source line #444	-> byte code offset #25
/*    */     //   Java source line #446	-> byte code offset #33
/*    */     //   Java source line #447	-> byte code offset #42
/*    */     //   Java source line #448	-> byte code offset #64
/*    */     //   Java source line #450	-> byte code offset #73
/*    */     //   Java source line #452	-> byte code offset #85
/*    */     //   Java source line #453	-> byte code offset #96
/*    */     //   Java source line #454	-> byte code offset #107
/*    */     //   Java source line #455	-> byte code offset #118
/*    */     //   Java source line #456	-> byte code offset #129
/*    */     //   Java source line #457	-> byte code offset #140
/*    */     //   Java source line #459	-> byte code offset #152
/*    */     //   Java source line #460	-> byte code offset #159
/*    */     //   Java source line #462	-> byte code offset #165
/*    */     //   Java source line #463	-> byte code offset #167
/*    */     //   Java source line #464	-> byte code offset #201
/*    */     //   Java source line #465	-> byte code offset #203
/*    */     //   Java source line #466	-> byte code offset #220
/*    */     //   Java source line #467	-> byte code offset #237
/*    */     //   Java source line #465	-> byte code offset #240
/*    */     //   Java source line #466	-> byte code offset #257
/*    */     //   Java source line #468	-> byte code offset #274
/*    */     // Local variable table:
/*    */     //   start	length	slot	name	signature
/*    */     //   0	277	0	this	PuntitosDAO
/*    */     //   0	277	1	puntoVentaTO	com.claro.transfer.PuntoVentaTO
/*    */     //   1	268	2	oConn	Connection
/*    */     //   3	249	3	oStmt	java.sql.PreparedStatement
/*    */     //   5	270	4	accion	boolean
/*    */     //   23	3	5	puntoVentaExiste	com.claro.transfer.PuntoVentaTO
/*    */     //   165	17	5	e	Exception
/*    */     //   40	35	6	query	StringBuffer
/*    */     //   201	37	7	localObject	Object
/*    */     //   218	1	8	localException1	Exception
/*    */     //   235	1	8	localException2	Exception
/*    */     //   255	1	8	localException3	Exception
/*    */     //   272	1	8	localException4	Exception
/*    */     // Exception table:
/*    */     //   from	to	target	type
/*    */     //   7	162	165	java/lang/Exception
/*    */     //   7	201	201	finally
/*    */     //   207	215	218	java/lang/Exception
/*    */     //   224	232	235	java/lang/Exception
/*    */     //   244	252	255	java/lang/Exception
/*    */     //   261	269	272	java/lang/Exception
/*    */   }
/*    */   
/*    */   /* Error */
/*    */   public boolean actualizaPtoVta(com.claro.transfer.PuntoVentaTO puntoVentaTO)
/*    */     throws Exception
/*    */   {
/*    */     // Byte code:
/*    */     //   0: aconst_null
/*    */     //   1: astore_2
/*    */     //   2: aconst_null
/*    */     //   3: astore_3
/*    */     //   4: iconst_0
/*    */     //   5: istore 4
/*    */     //   7: invokestatic 29	com/claro/util/ServiceLocator:getInstance	()Lcom/claro/util/ServiceLocator;
/*    */     //   10: getstatic 61	com/claro/util/ServiceLocator:jdbcCirculoAzul	Ljava/lang/String;
/*    */     //   13: invokevirtual 64	com/claro/util/ServiceLocator:getConnection	(Ljava/lang/String;)Ljava/sql/Connection;
/*    */     //   16: astore_2
/*    */     //   17: new 158	java/lang/StringBuffer
/*    */     //   20: dup
/*    */     //   21: invokespecial 160	java/lang/StringBuffer:<init>	()V
/*    */     //   24: astore 5
/*    */     //   26: aload 5
/*    */     //   28: ldc_w 727
/*    */     //   31: invokevirtual 173	java/lang/StringBuffer:append	(Ljava/lang/String;)Ljava/lang/StringBuffer;
/*    */     //   34: aload_0
/*    */     //   35: getfield 41	com/claro/dao/PuntitosDAO:schema_database	Ljava/lang/String;
/*    */     //   38: invokevirtual 173	java/lang/StringBuffer:append	(Ljava/lang/String;)Ljava/lang/StringBuffer;
/*    */     //   41: ldc_w 729
/*    */     //   44: invokevirtual 173	java/lang/StringBuffer:append	(Ljava/lang/String;)Ljava/lang/StringBuffer;
/*    */     //   47: pop
/*    */     //   48: aload 5
/*    */     //   50: ldc_w 731
/*    */     //   53: invokevirtual 173	java/lang/StringBuffer:append	(Ljava/lang/String;)Ljava/lang/StringBuffer;
/*    */     //   56: pop
/*    */     //   57: aload_2
/*    */     //   58: aload 5
/*    */     //   60: invokevirtual 242	java/lang/StringBuffer:toString	()Ljava/lang/String;
/*    */     //   63: invokeinterface 493 2 0
/*    */     //   68: astore_3
/*    */     //   69: aload_3
/*    */     //   70: iconst_1
/*    */     //   71: aload_1
/*    */     //   72: invokevirtual 638	com/claro/transfer/PuntoVentaTO:getSegmentoIP	()Ljava/lang/String;
/*    */     //   75: invokeinterface 497 3 0
/*    */     //   80: aload_3
/*    */     //   81: iconst_2
/*    */     //   82: aload_1
/*    */     //   83: invokevirtual 716	com/claro/transfer/PuntoVentaTO:getRangoInf	()I
/*    */     //   86: invokeinterface 563 3 0
/*    */     //   91: aload_3
/*    */     //   92: iconst_3
/*    */     //   93: aload_1
/*    */     //   94: invokevirtual 719	com/claro/transfer/PuntoVentaTO:getRangoSup	()I
/*    */     //   97: invokeinterface 563 3 0
/*    */     //   102: aload_3
/*    */     //   103: iconst_4
/*    */     //   104: aload_1
/*    */     //   105: invokevirtual 646	com/claro/transfer/PuntoVentaTO:getIdRegion	()I
/*    */     //   108: invokeinterface 563 3 0
/*    */     //   113: aload_3
/*    */     //   114: iconst_5
/*    */     //   115: aload_1
/*    */     //   116: invokevirtual 722	com/claro/transfer/PuntoVentaTO:getIvaProcentaje	()I
/*    */     //   119: invokeinterface 563 3 0
/*    */     //   124: aload_3
/*    */     //   125: bipush 6
/*    */     //   127: aload_1
/*    */     //   128: invokevirtual 643	com/claro/transfer/PuntoVentaTO:getIdPuntoVta	()Ljava/lang/String;
/*    */     //   131: invokeinterface 497 3 0
/*    */     //   136: aload_3
/*    */     //   137: invokeinterface 606 1 0
/*    */     //   142: pop
/*    */     //   143: iconst_1
/*    */     //   144: istore 4
/*    */     //   146: goto +78 -> 224
/*    */     //   149: astore 5
/*    */     //   151: new 47	java/lang/Exception
/*    */     //   154: dup
/*    */     //   155: new 104	java/lang/StringBuilder
/*    */     //   158: dup
/*    */     //   159: ldc_w 629
/*    */     //   162: invokespecial 108	java/lang/StringBuilder:<init>	(Ljava/lang/String;)V
/*    */     //   165: aload 5
/*    */     //   167: invokevirtual 131	java/lang/Exception:toString	()Ljava/lang/String;
/*    */     //   170: invokevirtual 114	java/lang/StringBuilder:append	(Ljava/lang/String;)Ljava/lang/StringBuilder;
/*    */     //   173: ldc -124
/*    */     //   175: invokevirtual 114	java/lang/StringBuilder:append	(Ljava/lang/String;)Ljava/lang/StringBuilder;
/*    */     //   178: invokevirtual 118	java/lang/StringBuilder:toString	()Ljava/lang/String;
/*    */     //   181: invokespecial 534	java/lang/Exception:<init>	(Ljava/lang/String;)V
/*    */     //   184: athrow
/*    */     //   185: astore 6
/*    */     //   187: aload_3
/*    */     //   188: ifnull +16 -> 204
/*    */     //   191: aload_3
/*    */     //   192: invokeinterface 535 1 0
/*    */     //   197: aconst_null
/*    */     //   198: astore_3
/*    */     //   199: goto +5 -> 204
/*    */     //   202: astore 7
/*    */     //   204: aload_2
/*    */     //   205: ifnull +16 -> 221
/*    */     //   208: aload_2
/*    */     //   209: invokeinterface 78 1 0
/*    */     //   214: aconst_null
/*    */     //   215: astore_2
/*    */     //   216: goto +5 -> 221
/*    */     //   219: astore 7
/*    */     //   221: aload 6
/*    */     //   223: athrow
/*    */     //   224: aload_3
/*    */     //   225: ifnull +16 -> 241
/*    */     //   228: aload_3
/*    */     //   229: invokeinterface 535 1 0
/*    */     //   234: aconst_null
/*    */     //   235: astore_3
/*    */     //   236: goto +5 -> 241
/*    */     //   239: astore 7
/*    */     //   241: aload_2
/*    */     //   242: ifnull +16 -> 258
/*    */     //   245: aload_2
/*    */     //   246: invokeinterface 78 1 0
/*    */     //   251: aconst_null
/*    */     //   252: astore_2
/*    */     //   253: goto +5 -> 258
/*    */     //   256: astore 7
/*    */     //   258: iload 4
/*    */     //   260: ireturn
/*    */     // Line number table:
/*    */     //   Java source line #472	-> byte code offset #0
/*    */     //   Java source line #473	-> byte code offset #2
/*    */     //   Java source line #474	-> byte code offset #4
/*    */     //   Java source line #476	-> byte code offset #7
/*    */     //   Java source line #478	-> byte code offset #17
/*    */     //   Java source line #479	-> byte code offset #26
/*    */     //   Java source line #480	-> byte code offset #48
/*    */     //   Java source line #482	-> byte code offset #57
/*    */     //   Java source line #484	-> byte code offset #69
/*    */     //   Java source line #485	-> byte code offset #80
/*    */     //   Java source line #486	-> byte code offset #91
/*    */     //   Java source line #487	-> byte code offset #102
/*    */     //   Java source line #488	-> byte code offset #113
/*    */     //   Java source line #489	-> byte code offset #124
/*    */     //   Java source line #491	-> byte code offset #136
/*    */     //   Java source line #492	-> byte code offset #143
/*    */     //   Java source line #493	-> byte code offset #149
/*    */     //   Java source line #494	-> byte code offset #151
/*    */     //   Java source line #495	-> byte code offset #185
/*    */     //   Java source line #496	-> byte code offset #187
/*    */     //   Java source line #497	-> byte code offset #204
/*    */     //   Java source line #498	-> byte code offset #221
/*    */     //   Java source line #496	-> byte code offset #224
/*    */     //   Java source line #497	-> byte code offset #241
/*    */     //   Java source line #499	-> byte code offset #258
/*    */     // Local variable table:
/*    */     //   start	length	slot	name	signature
/*    */     //   0	261	0	this	PuntitosDAO
/*    */     //   0	261	1	puntoVentaTO	com.claro.transfer.PuntoVentaTO
/*    */     //   1	252	2	oConn	Connection
/*    */     //   3	233	3	oStmt	java.sql.PreparedStatement
/*    */     //   5	254	4	accion	boolean
/*    */     //   24	35	5	query	StringBuffer
/*    */     //   149	17	5	e	Exception
/*    */     //   185	37	6	localObject	Object
/*    */     //   202	1	7	localException1	Exception
/*    */     //   219	1	7	localException2	Exception
/*    */     //   239	1	7	localException3	Exception
/*    */     //   256	1	7	localException4	Exception
/*    */     // Exception table:
/*    */     //   from	to	target	type
/*    */     //   7	146	149	java/lang/Exception
/*    */     //   7	185	185	finally
/*    */     //   191	199	202	java/lang/Exception
/*    */     //   208	216	219	java/lang/Exception
/*    */     //   228	236	239	java/lang/Exception
/*    */     //   245	253	256	java/lang/Exception
/*    */   }
/*    */   
/*    */   /* Error */
/*    */   public boolean eliminaPtoVta(com.claro.transfer.PuntoVentaTO puntoVentaTO)
/*    */     throws Exception
/*    */   {
/*    */     // Byte code:
/*    */     //   0: aconst_null
/*    */     //   1: astore_2
/*    */     //   2: aconst_null
/*    */     //   3: astore_3
/*    */     //   4: iconst_0
/*    */     //   5: istore 4
/*    */     //   7: invokestatic 29	com/claro/util/ServiceLocator:getInstance	()Lcom/claro/util/ServiceLocator;
/*    */     //   10: getstatic 61	com/claro/util/ServiceLocator:jdbcCirculoAzul	Ljava/lang/String;
/*    */     //   13: invokevirtual 64	com/claro/util/ServiceLocator:getConnection	(Ljava/lang/String;)Ljava/sql/Connection;
/*    */     //   16: astore_2
/*    */     //   17: new 158	java/lang/StringBuffer
/*    */     //   20: dup
/*    */     //   21: invokespecial 160	java/lang/StringBuffer:<init>	()V
/*    */     //   24: astore 5
/*    */     //   26: aload 5
/*    */     //   28: ldc_w 734
/*    */     //   31: invokevirtual 173	java/lang/StringBuffer:append	(Ljava/lang/String;)Ljava/lang/StringBuffer;
/*    */     //   34: aload_0
/*    */     //   35: getfield 41	com/claro/dao/PuntitosDAO:schema_database	Ljava/lang/String;
/*    */     //   38: invokevirtual 173	java/lang/StringBuffer:append	(Ljava/lang/String;)Ljava/lang/StringBuffer;
/*    */     //   41: ldc_w 703
/*    */     //   44: invokevirtual 173	java/lang/StringBuffer:append	(Ljava/lang/String;)Ljava/lang/StringBuffer;
/*    */     //   47: pop
/*    */     //   48: aload_2
/*    */     //   49: aload 5
/*    */     //   51: invokevirtual 242	java/lang/StringBuffer:toString	()Ljava/lang/String;
/*    */     //   54: invokeinterface 493 2 0
/*    */     //   59: astore_3
/*    */     //   60: aload_3
/*    */     //   61: iconst_1
/*    */     //   62: aload_1
/*    */     //   63: invokevirtual 643	com/claro/transfer/PuntoVentaTO:getIdPuntoVta	()Ljava/lang/String;
/*    */     //   66: invokeinterface 497 3 0
/*    */     //   71: aload_3
/*    */     //   72: invokeinterface 606 1 0
/*    */     //   77: pop
/*    */     //   78: iconst_1
/*    */     //   79: istore 4
/*    */     //   81: goto +78 -> 159
/*    */     //   84: astore 5
/*    */     //   86: new 47	java/lang/Exception
/*    */     //   89: dup
/*    */     //   90: new 104	java/lang/StringBuilder
/*    */     //   93: dup
/*    */     //   94: ldc_w 629
/*    */     //   97: invokespecial 108	java/lang/StringBuilder:<init>	(Ljava/lang/String;)V
/*    */     //   100: aload 5
/*    */     //   102: invokevirtual 131	java/lang/Exception:toString	()Ljava/lang/String;
/*    */     //   105: invokevirtual 114	java/lang/StringBuilder:append	(Ljava/lang/String;)Ljava/lang/StringBuilder;
/*    */     //   108: ldc -124
/*    */     //   110: invokevirtual 114	java/lang/StringBuilder:append	(Ljava/lang/String;)Ljava/lang/StringBuilder;
/*    */     //   113: invokevirtual 118	java/lang/StringBuilder:toString	()Ljava/lang/String;
/*    */     //   116: invokespecial 534	java/lang/Exception:<init>	(Ljava/lang/String;)V
/*    */     //   119: athrow
/*    */     //   120: astore 6
/*    */     //   122: aload_3
/*    */     //   123: ifnull +16 -> 139
/*    */     //   126: aload_3
/*    */     //   127: invokeinterface 535 1 0
/*    */     //   132: aconst_null
/*    */     //   133: astore_3
/*    */     //   134: goto +5 -> 139
/*    */     //   137: astore 7
/*    */     //   139: aload_2
/*    */     //   140: ifnull +16 -> 156
/*    */     //   143: aload_2
/*    */     //   144: invokeinterface 78 1 0
/*    */     //   149: aconst_null
/*    */     //   150: astore_2
/*    */     //   151: goto +5 -> 156
/*    */     //   154: astore 7
/*    */     //   156: aload 6
/*    */     //   158: athrow
/*    */     //   159: aload_3
/*    */     //   160: ifnull +16 -> 176
/*    */     //   163: aload_3
/*    */     //   164: invokeinterface 535 1 0
/*    */     //   169: aconst_null
/*    */     //   170: astore_3
/*    */     //   171: goto +5 -> 176
/*    */     //   174: astore 7
/*    */     //   176: aload_2
/*    */     //   177: ifnull +16 -> 193
/*    */     //   180: aload_2
/*    */     //   181: invokeinterface 78 1 0
/*    */     //   186: aconst_null
/*    */     //   187: astore_2
/*    */     //   188: goto +5 -> 193
/*    */     //   191: astore 7
/*    */     //   193: iload 4
/*    */     //   195: ireturn
/*    */     // Line number table:
/*    */     //   Java source line #503	-> byte code offset #0
/*    */     //   Java source line #504	-> byte code offset #2
/*    */     //   Java source line #505	-> byte code offset #4
/*    */     //   Java source line #507	-> byte code offset #7
/*    */     //   Java source line #509	-> byte code offset #17
/*    */     //   Java source line #510	-> byte code offset #26
/*    */     //   Java source line #511	-> byte code offset #48
/*    */     //   Java source line #513	-> byte code offset #60
/*    */     //   Java source line #515	-> byte code offset #71
/*    */     //   Java source line #516	-> byte code offset #78
/*    */     //   Java source line #517	-> byte code offset #84
/*    */     //   Java source line #518	-> byte code offset #86
/*    */     //   Java source line #519	-> byte code offset #120
/*    */     //   Java source line #520	-> byte code offset #122
/*    */     //   Java source line #521	-> byte code offset #139
/*    */     //   Java source line #522	-> byte code offset #156
/*    */     //   Java source line #520	-> byte code offset #159
/*    */     //   Java source line #521	-> byte code offset #176
/*    */     //   Java source line #523	-> byte code offset #193
/*    */     // Local variable table:
/*    */     //   start	length	slot	name	signature
/*    */     //   0	196	0	this	PuntitosDAO
/*    */     //   0	196	1	puntoVentaTO	com.claro.transfer.PuntoVentaTO
/*    */     //   1	187	2	oConn	Connection
/*    */     //   3	168	3	oStmt	java.sql.PreparedStatement
/*    */     //   5	189	4	accion	boolean
/*    */     //   24	26	5	query	StringBuffer
/*    */     //   84	17	5	e	Exception
/*    */     //   120	37	6	localObject	Object
/*    */     //   137	1	7	localException1	Exception
/*    */     //   154	1	7	localException2	Exception
/*    */     //   174	1	7	localException3	Exception
/*    */     //   191	1	7	localException4	Exception
/*    */     // Exception table:
/*    */     //   from	to	target	type
/*    */     //   7	81	84	java/lang/Exception
/*    */     //   7	120	120	finally
/*    */     //   126	134	137	java/lang/Exception
/*    */     //   143	151	154	java/lang/Exception
/*    */     //   163	171	174	java/lang/Exception
/*    */     //   180	188	191	java/lang/Exception
/*    */   }
/*    */ }


/* Location:              /opt/trabajo/claro/Guatemala/IS/CO/ClaroClub.ear!/ClaroClubEJB.jar!/com/claro/dao/PuntitosDAO.class
 * Java compiler version: 6 (50.0)
 * JD-Core Version:       0.7.1
 */