/*    */ package com.claro.dao;
/*    */ 
/*    */ import org.apache.log4j.Logger;
/*    */ 
/*    */ 
/*    */ 
/*    */ 
/*    */ 
/*    */ 
/*    */ 
/*    */ 
/*    */ public class RenunciaDAO
/*    */ {
/* 14 */   protected final Logger logger = Logger.getLogger("loggerCirculoAzul");
/* 15 */   protected final Logger error = Logger.getLogger("loggerCirculoAzulError");
/*    */   
/*    */   /* Error */
/*    */   public com.claro.transfer.MensajeTO reactivaPuntos(com.claro.transfer.ParametrosTO parametrosTO)
/*    */     throws com.claro.exception.CAException
/*    */   {
/*    */     // Byte code:
/*    */     //   0: new 36	com/claro/transfer/MensajeTO
/*    */     //   3: dup
/*    */     //   4: invokespecial 38	com/claro/transfer/MensajeTO:<init>	()V
/*    */     //   7: astore_2
/*    */     //   8: aconst_null
/*    */     //   9: astore_3
/*    */     //   10: new 39	com/claro/dao/PuntosDAO
/*    */     //   13: dup
/*    */     //   14: invokespecial 41	com/claro/dao/PuntosDAO:<init>	()V
/*    */     //   17: astore 4
/*    */     //   19: invokestatic 42	java/lang/System:currentTimeMillis	()J
/*    */     //   22: lstore 5
/*    */     //   24: aload 4
/*    */     //   26: aconst_null
/*    */     //   27: aload_1
/*    */     //   28: invokevirtual 48	com/claro/transfer/ParametrosTO:getCuenta	()Ljava/lang/String;
/*    */     //   31: aload_1
/*    */     //   32: invokevirtual 54	com/claro/transfer/ParametrosTO:getSecuencia	()I
/*    */     //   35: ldc 58
/*    */     //   37: invokevirtual 60	com/claro/dao/PuntosDAO:actualizaLinea	(Ljava/sql/Connection;Ljava/lang/String;ILjava/lang/String;)Lcom/claro/transfer/MensajeTO;
/*    */     //   40: astore_2
/*    */     //   41: invokestatic 64	com/claro/util/ServiceLocator:getInstance	()Lcom/claro/util/ServiceLocator;
/*    */     //   44: getstatic 70	com/claro/util/ServiceLocator:jdbcCirculoAzul	Ljava/lang/String;
/*    */     //   47: invokevirtual 74	com/claro/util/ServiceLocator:getConnection	(Ljava/lang/String;)Ljava/sql/Connection;
/*    */     //   50: astore_3
/*    */     //   51: aload_2
/*    */     //   52: invokevirtual 78	com/claro/transfer/MensajeTO:getIdMensaje	()I
/*    */     //   55: ifne +198 -> 253
/*    */     //   58: aload 4
/*    */     //   60: aload_3
/*    */     //   61: lload 5
/*    */     //   63: new 81	java/lang/StringBuilder
/*    */     //   66: dup
/*    */     //   67: ldc 83
/*    */     //   69: invokespecial 85	java/lang/StringBuilder:<init>	(Ljava/lang/String;)V
/*    */     //   72: getstatic 88	com/claro/util/Constantes:TIMEFORMAT	Ljava/text/SimpleDateFormat;
/*    */     //   75: new 94	java/util/Date
/*    */     //   78: dup
/*    */     //   79: lload 5
/*    */     //   81: invokespecial 96	java/util/Date:<init>	(J)V
/*    */     //   84: invokevirtual 99	java/text/SimpleDateFormat:format	(Ljava/util/Date;)Ljava/lang/String;
/*    */     //   87: invokevirtual 105	java/lang/StringBuilder:append	(Ljava/lang/String;)Ljava/lang/StringBuilder;
/*    */     //   90: ldc 109
/*    */     //   92: invokevirtual 105	java/lang/StringBuilder:append	(Ljava/lang/String;)Ljava/lang/StringBuilder;
/*    */     //   95: invokevirtual 111	java/lang/StringBuilder:toString	()Ljava/lang/String;
/*    */     //   98: bipush 48
/*    */     //   100: iconst_0
/*    */     //   101: aconst_null
/*    */     //   102: aload_1
/*    */     //   103: invokevirtual 48	com/claro/transfer/ParametrosTO:getCuenta	()Ljava/lang/String;
/*    */     //   106: aload_1
/*    */     //   107: invokevirtual 54	com/claro/transfer/ParametrosTO:getSecuencia	()I
/*    */     //   110: aload_1
/*    */     //   111: invokevirtual 114	com/claro/transfer/ParametrosTO:getTelefono	()Ljava/lang/String;
/*    */     //   114: aload_1
/*    */     //   115: invokevirtual 117	com/claro/transfer/ParametrosTO:getUsuariMovimiento	()Ljava/lang/String;
/*    */     //   118: invokevirtual 120	com/claro/dao/PuntosDAO:insertaDetalle	(Ljava/sql/Connection;JLjava/lang/String;IILjava/lang/String;Ljava/lang/String;ILjava/lang/String;Ljava/lang/String;)Lcom/claro/transfer/MensajeTO;
/*    */     //   121: astore_2
/*    */     //   122: goto +131 -> 253
/*    */     //   125: astore 5
/*    */     //   127: aload_0
/*    */     //   128: getfield 25	com/claro/dao/RenunciaDAO:error	Lorg/apache/log4j/Logger;
/*    */     //   131: ldc 124
/*    */     //   133: aload 5
/*    */     //   135: invokevirtual 126	org/apache/log4j/Logger:info	(Ljava/lang/Object;Ljava/lang/Throwable;)V
/*    */     //   138: new 34	com/claro/exception/CAException
/*    */     //   141: dup
/*    */     //   142: iconst_m1
/*    */     //   143: new 81	java/lang/StringBuilder
/*    */     //   146: dup
/*    */     //   147: ldc -126
/*    */     //   149: invokespecial 85	java/lang/StringBuilder:<init>	(Ljava/lang/String;)V
/*    */     //   152: aload 5
/*    */     //   154: invokevirtual 132	java/sql/SQLException:toString	()Ljava/lang/String;
/*    */     //   157: invokevirtual 105	java/lang/StringBuilder:append	(Ljava/lang/String;)Ljava/lang/StringBuilder;
/*    */     //   160: ldc -121
/*    */     //   162: invokevirtual 105	java/lang/StringBuilder:append	(Ljava/lang/String;)Ljava/lang/StringBuilder;
/*    */     //   165: invokevirtual 111	java/lang/StringBuilder:toString	()Ljava/lang/String;
/*    */     //   168: aload 5
/*    */     //   170: invokespecial 137	com/claro/exception/CAException:<init>	(ILjava/lang/String;Ljava/lang/Exception;)V
/*    */     //   173: athrow
/*    */     //   174: astore 5
/*    */     //   176: aload_0
/*    */     //   177: getfield 25	com/claro/dao/RenunciaDAO:error	Lorg/apache/log4j/Logger;
/*    */     //   180: ldc -116
/*    */     //   182: aload 5
/*    */     //   184: invokevirtual 126	org/apache/log4j/Logger:info	(Ljava/lang/Object;Ljava/lang/Throwable;)V
/*    */     //   187: new 34	com/claro/exception/CAException
/*    */     //   190: dup
/*    */     //   191: iconst_m1
/*    */     //   192: new 81	java/lang/StringBuilder
/*    */     //   195: dup
/*    */     //   196: ldc -114
/*    */     //   198: invokespecial 85	java/lang/StringBuilder:<init>	(Ljava/lang/String;)V
/*    */     //   201: aload 5
/*    */     //   203: invokevirtual 144	java/lang/Exception:toString	()Ljava/lang/String;
/*    */     //   206: invokevirtual 105	java/lang/StringBuilder:append	(Ljava/lang/String;)Ljava/lang/StringBuilder;
/*    */     //   209: ldc -121
/*    */     //   211: invokevirtual 105	java/lang/StringBuilder:append	(Ljava/lang/String;)Ljava/lang/StringBuilder;
/*    */     //   214: invokevirtual 111	java/lang/StringBuilder:toString	()Ljava/lang/String;
/*    */     //   217: aload 5
/*    */     //   219: invokespecial 137	com/claro/exception/CAException:<init>	(ILjava/lang/String;Ljava/lang/Exception;)V
/*    */     //   222: athrow
/*    */     //   223: astore 7
/*    */     //   225: aload 4
/*    */     //   227: ifnull +6 -> 233
/*    */     //   230: aconst_null
/*    */     //   231: astore 4
/*    */     //   233: aload_3
/*    */     //   234: ifnull +16 -> 250
/*    */     //   237: aload_3
/*    */     //   238: invokeinterface 147 1 0
/*    */     //   243: aconst_null
/*    */     //   244: astore_3
/*    */     //   245: goto +5 -> 250
/*    */     //   248: astore 8
/*    */     //   250: aload 7
/*    */     //   252: athrow
/*    */     //   253: aload 4
/*    */     //   255: ifnull +6 -> 261
/*    */     //   258: aconst_null
/*    */     //   259: astore 4
/*    */     //   261: aload_3
/*    */     //   262: ifnull +16 -> 278
/*    */     //   265: aload_3
/*    */     //   266: invokeinterface 147 1 0
/*    */     //   271: aconst_null
/*    */     //   272: astore_3
/*    */     //   273: goto +5 -> 278
/*    */     //   276: astore 8
/*    */     //   278: aload_2
/*    */     //   279: areturn
/*    */     // Line number table:
/*    */     //   Java source line #21	-> byte code offset #0
/*    */     //   Java source line #22	-> byte code offset #8
/*    */     //   Java source line #23	-> byte code offset #10
/*    */     //   Java source line #25	-> byte code offset #19
/*    */     //   Java source line #29	-> byte code offset #24
/*    */     //   Java source line #31	-> byte code offset #41
/*    */     //   Java source line #33	-> byte code offset #51
/*    */     //   Java source line #34	-> byte code offset #58
/*    */     //   Java source line #35	-> byte code offset #98
/*    */     //   Java source line #34	-> byte code offset #118
/*    */     //   Java source line #43	-> byte code offset #125
/*    */     //   Java source line #45	-> byte code offset #127
/*    */     //   Java source line #46	-> byte code offset #138
/*    */     //   Java source line #47	-> byte code offset #174
/*    */     //   Java source line #48	-> byte code offset #176
/*    */     //   Java source line #49	-> byte code offset #187
/*    */     //   Java source line #50	-> byte code offset #223
/*    */     //   Java source line #51	-> byte code offset #225
/*    */     //   Java source line #52	-> byte code offset #233
/*    */     //   Java source line #53	-> byte code offset #250
/*    */     //   Java source line #51	-> byte code offset #253
/*    */     //   Java source line #52	-> byte code offset #261
/*    */     //   Java source line #54	-> byte code offset #278
/*    */     // Local variable table:
/*    */     //   start	length	slot	name	signature
/*    */     //   0	280	0	this	RenunciaDAO
/*    */     //   0	280	1	parametrosTO	com.claro.transfer.ParametrosTO
/*    */     //   7	272	2	mensajeTO	com.claro.transfer.MensajeTO
/*    */     //   9	264	3	connection	java.sql.Connection
/*    */     //   17	243	4	puntosDAO	PuntosDAO
/*    */     //   22	58	5	fechaTransaccion	long
/*    */     //   125	44	5	e	java.sql.SQLException
/*    */     //   174	44	5	e	Exception
/*    */     //   223	28	7	localObject	Object
/*    */     //   248	1	8	localException1	Exception
/*    */     //   276	1	8	localException2	Exception
/*    */     // Exception table:
/*    */     //   from	to	target	type
/*    */     //   19	122	125	java/sql/SQLException
/*    */     //   19	122	174	java/lang/Exception
/*    */     //   19	223	223	finally
/*    */     //   237	245	248	java/lang/Exception
/*    */     //   265	273	276	java/lang/Exception
/*    */   }
/*    */   
/*    */   /* Error */
/*    */   public com.claro.transfer.MensajeTO renunciaPuntos(com.claro.transfer.ParametrosTO parametrosTO)
/*    */     throws com.claro.exception.CAException
/*    */   {
/*    */     // Byte code:
/*    */     //   0: new 36	com/claro/transfer/MensajeTO
/*    */     //   3: dup
/*    */     //   4: invokespecial 38	com/claro/transfer/MensajeTO:<init>	()V
/*    */     //   7: astore_2
/*    */     //   8: aconst_null
/*    */     //   9: astore_3
/*    */     //   10: new 39	com/claro/dao/PuntosDAO
/*    */     //   13: dup
/*    */     //   14: invokespecial 41	com/claro/dao/PuntosDAO:<init>	()V
/*    */     //   17: astore 4
/*    */     //   19: invokestatic 42	java/lang/System:currentTimeMillis	()J
/*    */     //   22: lstore 5
/*    */     //   24: aload 4
/*    */     //   26: aconst_null
/*    */     //   27: aload_1
/*    */     //   28: invokevirtual 48	com/claro/transfer/ParametrosTO:getCuenta	()Ljava/lang/String;
/*    */     //   31: aload_1
/*    */     //   32: invokevirtual 54	com/claro/transfer/ParametrosTO:getSecuencia	()I
/*    */     //   35: ldc -87
/*    */     //   37: invokevirtual 60	com/claro/dao/PuntosDAO:actualizaLinea	(Ljava/sql/Connection;Ljava/lang/String;ILjava/lang/String;)Lcom/claro/transfer/MensajeTO;
/*    */     //   40: astore_2
/*    */     //   41: invokestatic 64	com/claro/util/ServiceLocator:getInstance	()Lcom/claro/util/ServiceLocator;
/*    */     //   44: getstatic 70	com/claro/util/ServiceLocator:jdbcCirculoAzul	Ljava/lang/String;
/*    */     //   47: invokevirtual 74	com/claro/util/ServiceLocator:getConnection	(Ljava/lang/String;)Ljava/sql/Connection;
/*    */     //   50: astore_3
/*    */     //   51: aload_2
/*    */     //   52: invokevirtual 78	com/claro/transfer/MensajeTO:getIdMensaje	()I
/*    */     //   55: ifne +198 -> 253
/*    */     //   58: aload 4
/*    */     //   60: aload_3
/*    */     //   61: lload 5
/*    */     //   63: new 81	java/lang/StringBuilder
/*    */     //   66: dup
/*    */     //   67: ldc -85
/*    */     //   69: invokespecial 85	java/lang/StringBuilder:<init>	(Ljava/lang/String;)V
/*    */     //   72: getstatic 88	com/claro/util/Constantes:TIMEFORMAT	Ljava/text/SimpleDateFormat;
/*    */     //   75: new 94	java/util/Date
/*    */     //   78: dup
/*    */     //   79: lload 5
/*    */     //   81: invokespecial 96	java/util/Date:<init>	(J)V
/*    */     //   84: invokevirtual 99	java/text/SimpleDateFormat:format	(Ljava/util/Date;)Ljava/lang/String;
/*    */     //   87: invokevirtual 105	java/lang/StringBuilder:append	(Ljava/lang/String;)Ljava/lang/StringBuilder;
/*    */     //   90: ldc 109
/*    */     //   92: invokevirtual 105	java/lang/StringBuilder:append	(Ljava/lang/String;)Ljava/lang/StringBuilder;
/*    */     //   95: invokevirtual 111	java/lang/StringBuilder:toString	()Ljava/lang/String;
/*    */     //   98: bipush 49
/*    */     //   100: iconst_0
/*    */     //   101: aconst_null
/*    */     //   102: aload_1
/*    */     //   103: invokevirtual 48	com/claro/transfer/ParametrosTO:getCuenta	()Ljava/lang/String;
/*    */     //   106: aload_1
/*    */     //   107: invokevirtual 54	com/claro/transfer/ParametrosTO:getSecuencia	()I
/*    */     //   110: aload_1
/*    */     //   111: invokevirtual 114	com/claro/transfer/ParametrosTO:getTelefono	()Ljava/lang/String;
/*    */     //   114: aload_1
/*    */     //   115: invokevirtual 117	com/claro/transfer/ParametrosTO:getUsuariMovimiento	()Ljava/lang/String;
/*    */     //   118: invokevirtual 120	com/claro/dao/PuntosDAO:insertaDetalle	(Ljava/sql/Connection;JLjava/lang/String;IILjava/lang/String;Ljava/lang/String;ILjava/lang/String;Ljava/lang/String;)Lcom/claro/transfer/MensajeTO;
/*    */     //   121: astore_2
/*    */     //   122: goto +131 -> 253
/*    */     //   125: astore 5
/*    */     //   127: aload_0
/*    */     //   128: getfield 25	com/claro/dao/RenunciaDAO:error	Lorg/apache/log4j/Logger;
/*    */     //   131: ldc 124
/*    */     //   133: aload 5
/*    */     //   135: invokevirtual 126	org/apache/log4j/Logger:info	(Ljava/lang/Object;Ljava/lang/Throwable;)V
/*    */     //   138: new 34	com/claro/exception/CAException
/*    */     //   141: dup
/*    */     //   142: iconst_m1
/*    */     //   143: new 81	java/lang/StringBuilder
/*    */     //   146: dup
/*    */     //   147: ldc -126
/*    */     //   149: invokespecial 85	java/lang/StringBuilder:<init>	(Ljava/lang/String;)V
/*    */     //   152: aload 5
/*    */     //   154: invokevirtual 132	java/sql/SQLException:toString	()Ljava/lang/String;
/*    */     //   157: invokevirtual 105	java/lang/StringBuilder:append	(Ljava/lang/String;)Ljava/lang/StringBuilder;
/*    */     //   160: ldc -121
/*    */     //   162: invokevirtual 105	java/lang/StringBuilder:append	(Ljava/lang/String;)Ljava/lang/StringBuilder;
/*    */     //   165: invokevirtual 111	java/lang/StringBuilder:toString	()Ljava/lang/String;
/*    */     //   168: aload 5
/*    */     //   170: invokespecial 137	com/claro/exception/CAException:<init>	(ILjava/lang/String;Ljava/lang/Exception;)V
/*    */     //   173: athrow
/*    */     //   174: astore 5
/*    */     //   176: aload_0
/*    */     //   177: getfield 25	com/claro/dao/RenunciaDAO:error	Lorg/apache/log4j/Logger;
/*    */     //   180: ldc -116
/*    */     //   182: aload 5
/*    */     //   184: invokevirtual 126	org/apache/log4j/Logger:info	(Ljava/lang/Object;Ljava/lang/Throwable;)V
/*    */     //   187: new 34	com/claro/exception/CAException
/*    */     //   190: dup
/*    */     //   191: iconst_m1
/*    */     //   192: new 81	java/lang/StringBuilder
/*    */     //   195: dup
/*    */     //   196: ldc -114
/*    */     //   198: invokespecial 85	java/lang/StringBuilder:<init>	(Ljava/lang/String;)V
/*    */     //   201: aload 5
/*    */     //   203: invokevirtual 144	java/lang/Exception:toString	()Ljava/lang/String;
/*    */     //   206: invokevirtual 105	java/lang/StringBuilder:append	(Ljava/lang/String;)Ljava/lang/StringBuilder;
/*    */     //   209: ldc -121
/*    */     //   211: invokevirtual 105	java/lang/StringBuilder:append	(Ljava/lang/String;)Ljava/lang/StringBuilder;
/*    */     //   214: invokevirtual 111	java/lang/StringBuilder:toString	()Ljava/lang/String;
/*    */     //   217: aload 5
/*    */     //   219: invokespecial 137	com/claro/exception/CAException:<init>	(ILjava/lang/String;Ljava/lang/Exception;)V
/*    */     //   222: athrow
/*    */     //   223: astore 7
/*    */     //   225: aload 4
/*    */     //   227: ifnull +6 -> 233
/*    */     //   230: aconst_null
/*    */     //   231: astore 4
/*    */     //   233: aload_3
/*    */     //   234: ifnull +16 -> 250
/*    */     //   237: aload_3
/*    */     //   238: invokeinterface 147 1 0
/*    */     //   243: aconst_null
/*    */     //   244: astore_3
/*    */     //   245: goto +5 -> 250
/*    */     //   248: astore 8
/*    */     //   250: aload 7
/*    */     //   252: athrow
/*    */     //   253: aload 4
/*    */     //   255: ifnull +6 -> 261
/*    */     //   258: aconst_null
/*    */     //   259: astore 4
/*    */     //   261: aload_3
/*    */     //   262: ifnull +16 -> 278
/*    */     //   265: aload_3
/*    */     //   266: invokeinterface 147 1 0
/*    */     //   271: aconst_null
/*    */     //   272: astore_3
/*    */     //   273: goto +5 -> 278
/*    */     //   276: astore 8
/*    */     //   278: aload_2
/*    */     //   279: areturn
/*    */     // Line number table:
/*    */     //   Java source line #58	-> byte code offset #0
/*    */     //   Java source line #59	-> byte code offset #8
/*    */     //   Java source line #60	-> byte code offset #10
/*    */     //   Java source line #62	-> byte code offset #19
/*    */     //   Java source line #66	-> byte code offset #24
/*    */     //   Java source line #69	-> byte code offset #41
/*    */     //   Java source line #70	-> byte code offset #51
/*    */     //   Java source line #71	-> byte code offset #58
/*    */     //   Java source line #72	-> byte code offset #98
/*    */     //   Java source line #71	-> byte code offset #118
/*    */     //   Java source line #79	-> byte code offset #125
/*    */     //   Java source line #80	-> byte code offset #127
/*    */     //   Java source line #81	-> byte code offset #138
/*    */     //   Java source line #82	-> byte code offset #174
/*    */     //   Java source line #83	-> byte code offset #176
/*    */     //   Java source line #84	-> byte code offset #187
/*    */     //   Java source line #85	-> byte code offset #223
/*    */     //   Java source line #86	-> byte code offset #225
/*    */     //   Java source line #87	-> byte code offset #233
/*    */     //   Java source line #88	-> byte code offset #250
/*    */     //   Java source line #86	-> byte code offset #253
/*    */     //   Java source line #87	-> byte code offset #261
/*    */     //   Java source line #89	-> byte code offset #278
/*    */     // Local variable table:
/*    */     //   start	length	slot	name	signature
/*    */     //   0	280	0	this	RenunciaDAO
/*    */     //   0	280	1	parametrosTO	com.claro.transfer.ParametrosTO
/*    */     //   7	272	2	mensajeTO	com.claro.transfer.MensajeTO
/*    */     //   9	264	3	connection	java.sql.Connection
/*    */     //   17	243	4	puntosDAO	PuntosDAO
/*    */     //   22	58	5	fechaTransaccion	long
/*    */     //   125	44	5	e	java.sql.SQLException
/*    */     //   174	44	5	e	Exception
/*    */     //   223	28	7	localObject	Object
/*    */     //   248	1	8	localException1	Exception
/*    */     //   276	1	8	localException2	Exception
/*    */     // Exception table:
/*    */     //   from	to	target	type
/*    */     //   19	122	125	java/sql/SQLException
/*    */     //   19	122	174	java/lang/Exception
/*    */     //   19	223	223	finally
/*    */     //   237	245	248	java/lang/Exception
/*    */     //   265	273	276	java/lang/Exception
/*    */   }
/*    */ }


/* Location:              /opt/trabajo/claro/Guatemala/IS/CO/ClaroClub.ear!/ClaroClubEJB.jar!/com/claro/dao/RenunciaDAO.class
 * Java compiler version: 6 (50.0)
 * JD-Core Version:       0.7.1
 */