/*     */ package com.claro.dao;
/*     */ 
/*     */ import com.claro.exception.CAException;
/*     */ import com.claro.transfer.PrivilegioTO;
/*     */ import com.claro.util.ServiceLocator;
/*     */ import java.util.ArrayList;
/*     */ import java.util.List;
/*     */ import org.apache.log4j.Logger;
/*     */ 
/*     */ 
/*     */ 
/*     */ 
/*     */ 
/*     */ 
/*     */ 
/*     */ 
/*     */ 
/*     */ 
/*     */ 
/*     */ 
/*     */ 
/*     */ public class SeguridadDAO
/*     */ {
/*  24 */   protected final Logger logger = Logger.getLogger("loggerCirculoAzul");
/*  25 */   protected final Logger error = Logger.getLogger("loggerCirculoAzulError");
/*     */   private String schema_database;
/*     */   
/*     */   public SeguridadDAO()
/*     */   {
/*     */     try {
/*  31 */       this.schema_database = ServiceLocator.getInstance().getVariable(ServiceLocator.schema_database);
/*     */     } catch (Exception e) {
/*  33 */       this.error.error("SeguridadDAO", e);
/*     */     }
/*     */   }
/*     */   
/*     */   /* Error */
/*     */   public com.claro.transfer.PerfilTO getPrivilegiosPerfil(String idPerfil)
/*     */     throws CAException
/*     */   {
/*     */     // Byte code:
/*     */     //   0: new 61	com/claro/transfer/PerfilTO
/*     */     //   3: dup
/*     */     //   4: invokespecial 63	com/claro/transfer/PerfilTO:<init>	()V
/*     */     //   7: astore_2
/*     */     //   8: aconst_null
/*     */     //   9: astore_3
/*     */     //   10: aconst_null
/*     */     //   11: astore 4
/*     */     //   13: aconst_null
/*     */     //   14: astore 5
/*     */     //   16: new 64	java/lang/StringBuffer
/*     */     //   19: dup
/*     */     //   20: invokespecial 66	java/lang/StringBuffer:<init>	()V
/*     */     //   23: astore 6
/*     */     //   25: aload_0
/*     */     //   26: getfield 23	com/claro/dao/SeguridadDAO:logger	Lorg/apache/log4j/Logger;
/*     */     //   29: new 67	java/lang/StringBuilder
/*     */     //   32: dup
/*     */     //   33: ldc 69
/*     */     //   35: invokespecial 71	java/lang/StringBuilder:<init>	(Ljava/lang/String;)V
/*     */     //   38: getstatic 74	com/claro/util/Constantes:DATEFORMTALog	Ljava/text/SimpleDateFormat;
/*     */     //   41: new 80	java/util/Date
/*     */     //   44: dup
/*     */     //   45: invokespecial 82	java/util/Date:<init>	()V
/*     */     //   48: invokevirtual 83	java/text/SimpleDateFormat:format	(Ljava/util/Date;)Ljava/lang/String;
/*     */     //   51: invokevirtual 89	java/lang/StringBuilder:append	(Ljava/lang/String;)Ljava/lang/StringBuilder;
/*     */     //   54: ldc 93
/*     */     //   56: invokevirtual 89	java/lang/StringBuilder:append	(Ljava/lang/String;)Ljava/lang/StringBuilder;
/*     */     //   59: invokestatic 95	java/lang/System:currentTimeMillis	()J
/*     */     //   62: invokevirtual 101	java/lang/StringBuilder:append	(J)Ljava/lang/StringBuilder;
/*     */     //   65: invokevirtual 104	java/lang/StringBuilder:toString	()Ljava/lang/String;
/*     */     //   68: invokevirtual 108	org/apache/log4j/Logger:info	(Ljava/lang/Object;)V
/*     */     //   71: aload 6
/*     */     //   73: ldc 112
/*     */     //   75: invokevirtual 114	java/lang/StringBuffer:append	(Ljava/lang/String;)Ljava/lang/StringBuffer;
/*     */     //   78: pop
/*     */     //   79: aload 6
/*     */     //   81: ldc 117
/*     */     //   83: invokevirtual 114	java/lang/StringBuffer:append	(Ljava/lang/String;)Ljava/lang/StringBuffer;
/*     */     //   86: aload_0
/*     */     //   87: getfield 41	com/claro/dao/SeguridadDAO:schema_database	Ljava/lang/String;
/*     */     //   90: invokevirtual 114	java/lang/StringBuffer:append	(Ljava/lang/String;)Ljava/lang/StringBuffer;
/*     */     //   93: ldc 119
/*     */     //   95: invokevirtual 114	java/lang/StringBuffer:append	(Ljava/lang/String;)Ljava/lang/StringBuffer;
/*     */     //   98: pop
/*     */     //   99: aload 6
/*     */     //   101: aload_0
/*     */     //   102: getfield 41	com/claro/dao/SeguridadDAO:schema_database	Ljava/lang/String;
/*     */     //   105: invokevirtual 114	java/lang/StringBuffer:append	(Ljava/lang/String;)Ljava/lang/StringBuffer;
/*     */     //   108: ldc 121
/*     */     //   110: invokevirtual 114	java/lang/StringBuffer:append	(Ljava/lang/String;)Ljava/lang/StringBuffer;
/*     */     //   113: aload_0
/*     */     //   114: getfield 41	com/claro/dao/SeguridadDAO:schema_database	Ljava/lang/String;
/*     */     //   117: invokevirtual 114	java/lang/StringBuffer:append	(Ljava/lang/String;)Ljava/lang/StringBuffer;
/*     */     //   120: ldc 123
/*     */     //   122: invokevirtual 114	java/lang/StringBuffer:append	(Ljava/lang/String;)Ljava/lang/StringBuffer;
/*     */     //   125: pop
/*     */     //   126: aload 6
/*     */     //   128: ldc 125
/*     */     //   130: invokevirtual 114	java/lang/StringBuffer:append	(Ljava/lang/String;)Ljava/lang/StringBuffer;
/*     */     //   133: pop
/*     */     //   134: aload 6
/*     */     //   136: ldc 127
/*     */     //   138: invokevirtual 114	java/lang/StringBuffer:append	(Ljava/lang/String;)Ljava/lang/StringBuffer;
/*     */     //   141: pop
/*     */     //   142: aload 6
/*     */     //   144: ldc -127
/*     */     //   146: invokevirtual 114	java/lang/StringBuffer:append	(Ljava/lang/String;)Ljava/lang/StringBuffer;
/*     */     //   149: pop
/*     */     //   150: invokestatic 29	com/claro/util/ServiceLocator:getInstance	()Lcom/claro/util/ServiceLocator;
/*     */     //   153: getstatic 131	com/claro/util/ServiceLocator:jdbcCirculoAzul	Ljava/lang/String;
/*     */     //   156: invokevirtual 134	com/claro/util/ServiceLocator:getConnection	(Ljava/lang/String;)Ljava/sql/Connection;
/*     */     //   159: astore_3
/*     */     //   160: aload_3
/*     */     //   161: aload 6
/*     */     //   163: invokevirtual 138	java/lang/StringBuffer:toString	()Ljava/lang/String;
/*     */     //   166: invokeinterface 139 2 0
/*     */     //   171: astore 4
/*     */     //   173: aload 4
/*     */     //   175: iconst_1
/*     */     //   176: aload_1
/*     */     //   177: invokeinterface 145 3 0
/*     */     //   182: aload 4
/*     */     //   184: invokeinterface 151 1 0
/*     */     //   189: astore 5
/*     */     //   191: new 155	java/util/Hashtable
/*     */     //   194: dup
/*     */     //   195: invokespecial 157	java/util/Hashtable:<init>	()V
/*     */     //   198: astore 7
/*     */     //   200: goto +84 -> 284
/*     */     //   203: new 158	com/claro/transfer/PrivilegioTO
/*     */     //   206: dup
/*     */     //   207: invokespecial 160	com/claro/transfer/PrivilegioTO:<init>	()V
/*     */     //   210: astore 8
/*     */     //   212: aload 8
/*     */     //   214: aload 5
/*     */     //   216: ldc -95
/*     */     //   218: invokeinterface 163 2 0
/*     */     //   223: invokevirtual 169	com/claro/transfer/PrivilegioTO:setIdProceso	(I)V
/*     */     //   226: aload 8
/*     */     //   228: aload 5
/*     */     //   230: ldc -83
/*     */     //   232: invokeinterface 175 2 0
/*     */     //   237: invokevirtual 178	com/claro/transfer/PrivilegioTO:setNombre	(Ljava/lang/String;)V
/*     */     //   240: aload 8
/*     */     //   242: aload 5
/*     */     //   244: ldc -75
/*     */     //   246: invokeinterface 175 2 0
/*     */     //   251: invokevirtual 183	com/claro/transfer/PrivilegioTO:setDescripcion	(Ljava/lang/String;)V
/*     */     //   254: aload 8
/*     */     //   256: aload 5
/*     */     //   258: ldc -70
/*     */     //   260: invokeinterface 175 2 0
/*     */     //   265: invokevirtual 188	com/claro/transfer/PrivilegioTO:setTipo	(Ljava/lang/String;)V
/*     */     //   268: aload 7
/*     */     //   270: aload 8
/*     */     //   272: invokevirtual 191	com/claro/transfer/PrivilegioTO:getIdProceso	()I
/*     */     //   275: invokestatic 195	java/lang/Integer:toString	(I)Ljava/lang/String;
/*     */     //   278: aload 8
/*     */     //   280: invokevirtual 200	java/util/Hashtable:put	(Ljava/lang/Object;Ljava/lang/Object;)Ljava/lang/Object;
/*     */     //   283: pop
/*     */     //   284: aload 5
/*     */     //   286: invokeinterface 204 1 0
/*     */     //   291: ifne -88 -> 203
/*     */     //   294: aload_2
/*     */     //   295: aload 7
/*     */     //   297: invokevirtual 208	com/claro/transfer/PerfilTO:setPrivilegiosCa	(Ljava/util/Hashtable;)V
/*     */     //   300: aload 5
/*     */     //   302: ifnull +13 -> 315
/*     */     //   305: aload 5
/*     */     //   307: invokeinterface 212 1 0
/*     */     //   312: aconst_null
/*     */     //   313: astore 5
/*     */     //   315: aload 4
/*     */     //   317: ifnull +13 -> 330
/*     */     //   320: aload 4
/*     */     //   322: invokeinterface 215 1 0
/*     */     //   327: aconst_null
/*     */     //   328: astore 5
/*     */     //   330: new 64	java/lang/StringBuffer
/*     */     //   333: dup
/*     */     //   334: invokespecial 66	java/lang/StringBuffer:<init>	()V
/*     */     //   337: astore 6
/*     */     //   339: aload 6
/*     */     //   341: ldc 112
/*     */     //   343: invokevirtual 114	java/lang/StringBuffer:append	(Ljava/lang/String;)Ljava/lang/StringBuffer;
/*     */     //   346: pop
/*     */     //   347: aload 6
/*     */     //   349: ldc 117
/*     */     //   351: invokevirtual 114	java/lang/StringBuffer:append	(Ljava/lang/String;)Ljava/lang/StringBuffer;
/*     */     //   354: aload_0
/*     */     //   355: getfield 41	com/claro/dao/SeguridadDAO:schema_database	Ljava/lang/String;
/*     */     //   358: invokevirtual 114	java/lang/StringBuffer:append	(Ljava/lang/String;)Ljava/lang/StringBuffer;
/*     */     //   361: ldc 119
/*     */     //   363: invokevirtual 114	java/lang/StringBuffer:append	(Ljava/lang/String;)Ljava/lang/StringBuffer;
/*     */     //   366: pop
/*     */     //   367: aload 6
/*     */     //   369: aload_0
/*     */     //   370: getfield 41	com/claro/dao/SeguridadDAO:schema_database	Ljava/lang/String;
/*     */     //   373: invokevirtual 114	java/lang/StringBuffer:append	(Ljava/lang/String;)Ljava/lang/StringBuffer;
/*     */     //   376: ldc 121
/*     */     //   378: invokevirtual 114	java/lang/StringBuffer:append	(Ljava/lang/String;)Ljava/lang/StringBuffer;
/*     */     //   381: aload_0
/*     */     //   382: getfield 41	com/claro/dao/SeguridadDAO:schema_database	Ljava/lang/String;
/*     */     //   385: invokevirtual 114	java/lang/StringBuffer:append	(Ljava/lang/String;)Ljava/lang/StringBuffer;
/*     */     //   388: ldc 123
/*     */     //   390: invokevirtual 114	java/lang/StringBuffer:append	(Ljava/lang/String;)Ljava/lang/StringBuffer;
/*     */     //   393: pop
/*     */     //   394: aload 6
/*     */     //   396: ldc 125
/*     */     //   398: invokevirtual 114	java/lang/StringBuffer:append	(Ljava/lang/String;)Ljava/lang/StringBuffer;
/*     */     //   401: pop
/*     */     //   402: aload 6
/*     */     //   404: ldc -40
/*     */     //   406: invokevirtual 114	java/lang/StringBuffer:append	(Ljava/lang/String;)Ljava/lang/StringBuffer;
/*     */     //   409: pop
/*     */     //   410: aload 6
/*     */     //   412: ldc -127
/*     */     //   414: invokevirtual 114	java/lang/StringBuffer:append	(Ljava/lang/String;)Ljava/lang/StringBuffer;
/*     */     //   417: pop
/*     */     //   418: aload_3
/*     */     //   419: aload 6
/*     */     //   421: invokevirtual 138	java/lang/StringBuffer:toString	()Ljava/lang/String;
/*     */     //   424: invokeinterface 139 2 0
/*     */     //   429: astore 4
/*     */     //   431: aload 4
/*     */     //   433: iconst_1
/*     */     //   434: aload_1
/*     */     //   435: invokeinterface 145 3 0
/*     */     //   440: aload 4
/*     */     //   442: invokeinterface 151 1 0
/*     */     //   447: astore 5
/*     */     //   449: new 155	java/util/Hashtable
/*     */     //   452: dup
/*     */     //   453: invokespecial 157	java/util/Hashtable:<init>	()V
/*     */     //   456: astore 8
/*     */     //   458: goto +84 -> 542
/*     */     //   461: new 158	com/claro/transfer/PrivilegioTO
/*     */     //   464: dup
/*     */     //   465: invokespecial 160	com/claro/transfer/PrivilegioTO:<init>	()V
/*     */     //   468: astore 9
/*     */     //   470: aload 9
/*     */     //   472: aload 5
/*     */     //   474: ldc -95
/*     */     //   476: invokeinterface 163 2 0
/*     */     //   481: invokevirtual 169	com/claro/transfer/PrivilegioTO:setIdProceso	(I)V
/*     */     //   484: aload 9
/*     */     //   486: aload 5
/*     */     //   488: ldc -83
/*     */     //   490: invokeinterface 175 2 0
/*     */     //   495: invokevirtual 178	com/claro/transfer/PrivilegioTO:setNombre	(Ljava/lang/String;)V
/*     */     //   498: aload 9
/*     */     //   500: aload 5
/*     */     //   502: ldc -75
/*     */     //   504: invokeinterface 175 2 0
/*     */     //   509: invokevirtual 183	com/claro/transfer/PrivilegioTO:setDescripcion	(Ljava/lang/String;)V
/*     */     //   512: aload 9
/*     */     //   514: aload 5
/*     */     //   516: ldc -70
/*     */     //   518: invokeinterface 175 2 0
/*     */     //   523: invokevirtual 188	com/claro/transfer/PrivilegioTO:setTipo	(Ljava/lang/String;)V
/*     */     //   526: aload 8
/*     */     //   528: aload 9
/*     */     //   530: invokevirtual 191	com/claro/transfer/PrivilegioTO:getIdProceso	()I
/*     */     //   533: invokestatic 195	java/lang/Integer:toString	(I)Ljava/lang/String;
/*     */     //   536: aload 9
/*     */     //   538: invokevirtual 200	java/util/Hashtable:put	(Ljava/lang/Object;Ljava/lang/Object;)Ljava/lang/Object;
/*     */     //   541: pop
/*     */     //   542: aload 5
/*     */     //   544: invokeinterface 204 1 0
/*     */     //   549: ifne -88 -> 461
/*     */     //   552: aload_2
/*     */     //   553: aload 8
/*     */     //   555: invokevirtual 218	com/claro/transfer/PerfilTO:setPrivilegiosEcac	(Ljava/util/Hashtable;)V
/*     */     //   558: aload_0
/*     */     //   559: getfield 23	com/claro/dao/SeguridadDAO:logger	Lorg/apache/log4j/Logger;
/*     */     //   562: new 67	java/lang/StringBuilder
/*     */     //   565: dup
/*     */     //   566: ldc -35
/*     */     //   568: invokespecial 71	java/lang/StringBuilder:<init>	(Ljava/lang/String;)V
/*     */     //   571: getstatic 74	com/claro/util/Constantes:DATEFORMTALog	Ljava/text/SimpleDateFormat;
/*     */     //   574: new 80	java/util/Date
/*     */     //   577: dup
/*     */     //   578: invokespecial 82	java/util/Date:<init>	()V
/*     */     //   581: invokevirtual 83	java/text/SimpleDateFormat:format	(Ljava/util/Date;)Ljava/lang/String;
/*     */     //   584: invokevirtual 89	java/lang/StringBuilder:append	(Ljava/lang/String;)Ljava/lang/StringBuilder;
/*     */     //   587: ldc 93
/*     */     //   589: invokevirtual 89	java/lang/StringBuilder:append	(Ljava/lang/String;)Ljava/lang/StringBuilder;
/*     */     //   592: invokestatic 95	java/lang/System:currentTimeMillis	()J
/*     */     //   595: invokevirtual 101	java/lang/StringBuilder:append	(J)Ljava/lang/StringBuilder;
/*     */     //   598: invokevirtual 104	java/lang/StringBuilder:toString	()Ljava/lang/String;
/*     */     //   601: invokevirtual 108	org/apache/log4j/Logger:info	(Ljava/lang/Object;)V
/*     */     //   604: goto +155 -> 759
/*     */     //   607: astore 7
/*     */     //   609: aload_0
/*     */     //   610: getfield 27	com/claro/dao/SeguridadDAO:error	Lorg/apache/log4j/Logger;
/*     */     //   613: ldc -33
/*     */     //   615: aload 7
/*     */     //   617: invokevirtual 225	org/apache/log4j/Logger:info	(Ljava/lang/Object;Ljava/lang/Throwable;)V
/*     */     //   620: new 59	com/claro/exception/CAException
/*     */     //   623: dup
/*     */     //   624: iconst_m1
/*     */     //   625: new 67	java/lang/StringBuilder
/*     */     //   628: dup
/*     */     //   629: ldc -29
/*     */     //   631: invokespecial 71	java/lang/StringBuilder:<init>	(Ljava/lang/String;)V
/*     */     //   634: aload 7
/*     */     //   636: invokevirtual 229	java/sql/SQLException:toString	()Ljava/lang/String;
/*     */     //   639: invokevirtual 89	java/lang/StringBuilder:append	(Ljava/lang/String;)Ljava/lang/StringBuilder;
/*     */     //   642: ldc -24
/*     */     //   644: invokevirtual 89	java/lang/StringBuilder:append	(Ljava/lang/String;)Ljava/lang/StringBuilder;
/*     */     //   647: invokevirtual 104	java/lang/StringBuilder:toString	()Ljava/lang/String;
/*     */     //   650: aload 7
/*     */     //   652: invokespecial 234	com/claro/exception/CAException:<init>	(ILjava/lang/String;Ljava/lang/Exception;)V
/*     */     //   655: athrow
/*     */     //   656: astore 7
/*     */     //   658: aload_0
/*     */     //   659: getfield 27	com/claro/dao/SeguridadDAO:error	Lorg/apache/log4j/Logger;
/*     */     //   662: ldc -19
/*     */     //   664: aload 7
/*     */     //   666: invokevirtual 225	org/apache/log4j/Logger:info	(Ljava/lang/Object;Ljava/lang/Throwable;)V
/*     */     //   669: new 59	com/claro/exception/CAException
/*     */     //   672: dup
/*     */     //   673: iconst_m1
/*     */     //   674: new 67	java/lang/StringBuilder
/*     */     //   677: dup
/*     */     //   678: ldc -17
/*     */     //   680: invokespecial 71	java/lang/StringBuilder:<init>	(Ljava/lang/String;)V
/*     */     //   683: aload 7
/*     */     //   685: invokevirtual 241	java/lang/Exception:toString	()Ljava/lang/String;
/*     */     //   688: invokevirtual 89	java/lang/StringBuilder:append	(Ljava/lang/String;)Ljava/lang/StringBuilder;
/*     */     //   691: ldc -24
/*     */     //   693: invokevirtual 89	java/lang/StringBuilder:append	(Ljava/lang/String;)Ljava/lang/StringBuilder;
/*     */     //   696: invokevirtual 104	java/lang/StringBuilder:toString	()Ljava/lang/String;
/*     */     //   699: aload 7
/*     */     //   701: invokespecial 234	com/claro/exception/CAException:<init>	(ILjava/lang/String;Ljava/lang/Exception;)V
/*     */     //   704: athrow
/*     */     //   705: astore 10
/*     */     //   707: aload 5
/*     */     //   709: ifnull +15 -> 724
/*     */     //   712: aload 5
/*     */     //   714: invokeinterface 212 1 0
/*     */     //   719: goto +5 -> 724
/*     */     //   722: astore 11
/*     */     //   724: aload 4
/*     */     //   726: ifnull +15 -> 741
/*     */     //   729: aload 4
/*     */     //   731: invokeinterface 215 1 0
/*     */     //   736: goto +5 -> 741
/*     */     //   739: astore 11
/*     */     //   741: aload_3
/*     */     //   742: ifnull +14 -> 756
/*     */     //   745: aload_3
/*     */     //   746: invokeinterface 242 1 0
/*     */     //   751: goto +5 -> 756
/*     */     //   754: astore 11
/*     */     //   756: aload 10
/*     */     //   758: athrow
/*     */     //   759: aload 5
/*     */     //   761: ifnull +15 -> 776
/*     */     //   764: aload 5
/*     */     //   766: invokeinterface 212 1 0
/*     */     //   771: goto +5 -> 776
/*     */     //   774: astore 11
/*     */     //   776: aload 4
/*     */     //   778: ifnull +15 -> 793
/*     */     //   781: aload 4
/*     */     //   783: invokeinterface 215 1 0
/*     */     //   788: goto +5 -> 793
/*     */     //   791: astore 11
/*     */     //   793: aload_3
/*     */     //   794: ifnull +14 -> 808
/*     */     //   797: aload_3
/*     */     //   798: invokeinterface 242 1 0
/*     */     //   803: goto +5 -> 808
/*     */     //   806: astore 11
/*     */     //   808: aload_2
/*     */     //   809: areturn
/*     */     // Line number table:
/*     */     //   Java source line #40	-> byte code offset #0
/*     */     //   Java source line #41	-> byte code offset #8
/*     */     //   Java source line #42	-> byte code offset #10
/*     */     //   Java source line #43	-> byte code offset #13
/*     */     //   Java source line #44	-> byte code offset #16
/*     */     //   Java source line #47	-> byte code offset #25
/*     */     //   Java source line #50	-> byte code offset #71
/*     */     //   Java source line #51	-> byte code offset #79
/*     */     //   Java source line #52	-> byte code offset #99
/*     */     //   Java source line #53	-> byte code offset #126
/*     */     //   Java source line #54	-> byte code offset #134
/*     */     //   Java source line #55	-> byte code offset #142
/*     */     //   Java source line #57	-> byte code offset #150
/*     */     //   Java source line #59	-> byte code offset #160
/*     */     //   Java source line #60	-> byte code offset #173
/*     */     //   Java source line #61	-> byte code offset #182
/*     */     //   Java source line #62	-> byte code offset #191
/*     */     //   Java source line #64	-> byte code offset #200
/*     */     //   Java source line #65	-> byte code offset #203
/*     */     //   Java source line #66	-> byte code offset #212
/*     */     //   Java source line #67	-> byte code offset #226
/*     */     //   Java source line #68	-> byte code offset #240
/*     */     //   Java source line #69	-> byte code offset #254
/*     */     //   Java source line #70	-> byte code offset #268
/*     */     //   Java source line #64	-> byte code offset #284
/*     */     //   Java source line #72	-> byte code offset #294
/*     */     //   Java source line #74	-> byte code offset #300
/*     */     //   Java source line #75	-> byte code offset #315
/*     */     //   Java source line #76	-> byte code offset #330
/*     */     //   Java source line #79	-> byte code offset #339
/*     */     //   Java source line #80	-> byte code offset #347
/*     */     //   Java source line #81	-> byte code offset #367
/*     */     //   Java source line #82	-> byte code offset #394
/*     */     //   Java source line #83	-> byte code offset #402
/*     */     //   Java source line #84	-> byte code offset #410
/*     */     //   Java source line #86	-> byte code offset #418
/*     */     //   Java source line #87	-> byte code offset #431
/*     */     //   Java source line #88	-> byte code offset #440
/*     */     //   Java source line #89	-> byte code offset #449
/*     */     //   Java source line #91	-> byte code offset #458
/*     */     //   Java source line #92	-> byte code offset #461
/*     */     //   Java source line #93	-> byte code offset #470
/*     */     //   Java source line #94	-> byte code offset #484
/*     */     //   Java source line #95	-> byte code offset #498
/*     */     //   Java source line #96	-> byte code offset #512
/*     */     //   Java source line #97	-> byte code offset #526
/*     */     //   Java source line #91	-> byte code offset #542
/*     */     //   Java source line #99	-> byte code offset #552
/*     */     //   Java source line #101	-> byte code offset #558
/*     */     //   Java source line #103	-> byte code offset #607
/*     */     //   Java source line #104	-> byte code offset #609
/*     */     //   Java source line #105	-> byte code offset #620
/*     */     //   Java source line #107	-> byte code offset #656
/*     */     //   Java source line #108	-> byte code offset #658
/*     */     //   Java source line #109	-> byte code offset #669
/*     */     //   Java source line #110	-> byte code offset #705
/*     */     //   Java source line #111	-> byte code offset #707
/*     */     //   Java source line #112	-> byte code offset #724
/*     */     //   Java source line #113	-> byte code offset #741
/*     */     //   Java source line #114	-> byte code offset #756
/*     */     //   Java source line #111	-> byte code offset #759
/*     */     //   Java source line #112	-> byte code offset #776
/*     */     //   Java source line #113	-> byte code offset #793
/*     */     //   Java source line #115	-> byte code offset #808
/*     */     // Local variable table:
/*     */     //   start	length	slot	name	signature
/*     */     //   0	810	0	this	SeguridadDAO
/*     */     //   0	810	1	idPerfil	String
/*     */     //   7	802	2	perfilTO	com.claro.transfer.PerfilTO
/*     */     //   9	789	3	conn	java.sql.Connection
/*     */     //   11	771	4	stmt	java.sql.PreparedStatement
/*     */     //   14	751	5	rset	java.sql.ResultSet
/*     */     //   23	397	6	query	StringBuffer
/*     */     //   198	98	7	privilegiosCa	java.util.Hashtable<String, PrivilegioTO>
/*     */     //   607	44	7	e	java.sql.SQLException
/*     */     //   656	44	7	e	Exception
/*     */     //   210	69	8	privilegioTO	PrivilegioTO
/*     */     //   456	98	8	privilegiosEcac	java.util.Hashtable<String, PrivilegioTO>
/*     */     //   468	69	9	privilegioTO	PrivilegioTO
/*     */     //   705	52	10	localObject	Object
/*     */     //   722	1	11	localSQLException1	java.sql.SQLException
/*     */     //   739	1	11	localSQLException2	java.sql.SQLException
/*     */     //   754	1	11	localSQLException3	java.sql.SQLException
/*     */     //   774	1	11	localSQLException4	java.sql.SQLException
/*     */     //   791	1	11	localSQLException5	java.sql.SQLException
/*     */     //   806	1	11	localSQLException6	java.sql.SQLException
/*     */     // Exception table:
/*     */     //   from	to	target	type
/*     */     //   25	604	607	java/sql/SQLException
/*     */     //   25	604	656	java/lang/Exception
/*     */     //   25	705	705	finally
/*     */     //   712	719	722	java/sql/SQLException
/*     */     //   729	736	739	java/sql/SQLException
/*     */     //   745	751	754	java/sql/SQLException
/*     */     //   764	771	774	java/sql/SQLException
/*     */     //   781	788	791	java/sql/SQLException
/*     */     //   797	803	806	java/sql/SQLException
/*     */   }
/*     */   
/*     */   /* Error */
/*     */   public java.util.Map<String, PrivilegioTO> getprivilegiosCa()
/*     */     throws CAException
/*     */   {
/*     */     // Byte code:
/*     */     //   0: aconst_null
/*     */     //   1: astore_1
/*     */     //   2: aconst_null
/*     */     //   3: astore_2
/*     */     //   4: aconst_null
/*     */     //   5: astore_3
/*     */     //   6: aconst_null
/*     */     //   7: astore 4
/*     */     //   9: new 64	java/lang/StringBuffer
/*     */     //   12: dup
/*     */     //   13: invokespecial 66	java/lang/StringBuffer:<init>	()V
/*     */     //   16: astore 5
/*     */     //   18: aload 5
/*     */     //   20: ldc_w 270
/*     */     //   23: invokevirtual 114	java/lang/StringBuffer:append	(Ljava/lang/String;)Ljava/lang/StringBuffer;
/*     */     //   26: pop
/*     */     //   27: aload 5
/*     */     //   29: aload_0
/*     */     //   30: getfield 41	com/claro/dao/SeguridadDAO:schema_database	Ljava/lang/String;
/*     */     //   33: invokevirtual 114	java/lang/StringBuffer:append	(Ljava/lang/String;)Ljava/lang/StringBuffer;
/*     */     //   36: ldc_w 272
/*     */     //   39: invokevirtual 114	java/lang/StringBuffer:append	(Ljava/lang/String;)Ljava/lang/StringBuffer;
/*     */     //   42: pop
/*     */     //   43: aload 5
/*     */     //   45: ldc_w 274
/*     */     //   48: invokevirtual 114	java/lang/StringBuffer:append	(Ljava/lang/String;)Ljava/lang/StringBuffer;
/*     */     //   51: pop
/*     */     //   52: invokestatic 29	com/claro/util/ServiceLocator:getInstance	()Lcom/claro/util/ServiceLocator;
/*     */     //   55: getstatic 131	com/claro/util/ServiceLocator:jdbcCirculoAzul	Ljava/lang/String;
/*     */     //   58: invokevirtual 134	com/claro/util/ServiceLocator:getConnection	(Ljava/lang/String;)Ljava/sql/Connection;
/*     */     //   61: astore_1
/*     */     //   62: aload_1
/*     */     //   63: invokeinterface 276 1 0
/*     */     //   68: astore_2
/*     */     //   69: aload_2
/*     */     //   70: aload 5
/*     */     //   72: invokevirtual 138	java/lang/StringBuffer:toString	()Ljava/lang/String;
/*     */     //   75: invokeinterface 280 2 0
/*     */     //   80: astore_3
/*     */     //   81: new 285	java/util/HashMap
/*     */     //   84: dup
/*     */     //   85: invokespecial 287	java/util/HashMap:<init>	()V
/*     */     //   88: astore 4
/*     */     //   90: goto +66 -> 156
/*     */     //   93: new 158	com/claro/transfer/PrivilegioTO
/*     */     //   96: dup
/*     */     //   97: invokespecial 160	com/claro/transfer/PrivilegioTO:<init>	()V
/*     */     //   100: astore 6
/*     */     //   102: aload 6
/*     */     //   104: aload_3
/*     */     //   105: iconst_1
/*     */     //   106: invokeinterface 288 2 0
/*     */     //   111: invokevirtual 169	com/claro/transfer/PrivilegioTO:setIdProceso	(I)V
/*     */     //   114: aload 6
/*     */     //   116: aload_3
/*     */     //   117: iconst_2
/*     */     //   118: invokeinterface 291 2 0
/*     */     //   123: invokevirtual 178	com/claro/transfer/PrivilegioTO:setNombre	(Ljava/lang/String;)V
/*     */     //   126: aload 6
/*     */     //   128: aload_3
/*     */     //   129: iconst_3
/*     */     //   130: invokeinterface 291 2 0
/*     */     //   135: invokevirtual 183	com/claro/transfer/PrivilegioTO:setDescripcion	(Ljava/lang/String;)V
/*     */     //   138: aload 4
/*     */     //   140: aload 6
/*     */     //   142: invokevirtual 191	com/claro/transfer/PrivilegioTO:getIdProceso	()I
/*     */     //   145: invokestatic 293	java/lang/String:valueOf	(I)Ljava/lang/String;
/*     */     //   148: aload 6
/*     */     //   150: invokeinterface 296 3 0
/*     */     //   155: pop
/*     */     //   156: aload_3
/*     */     //   157: invokeinterface 204 1 0
/*     */     //   162: ifne -69 -> 93
/*     */     //   165: goto +127 -> 292
/*     */     //   168: astore 5
/*     */     //   170: aload_0
/*     */     //   171: getfield 27	com/claro/dao/SeguridadDAO:error	Lorg/apache/log4j/Logger;
/*     */     //   174: ldc_w 299
/*     */     //   177: aload 5
/*     */     //   179: invokevirtual 44	org/apache/log4j/Logger:error	(Ljava/lang/Object;Ljava/lang/Throwable;)V
/*     */     //   182: aload_3
/*     */     //   183: ifnull +16 -> 199
/*     */     //   186: aload_3
/*     */     //   187: invokeinterface 212 1 0
/*     */     //   192: aconst_null
/*     */     //   193: astore_3
/*     */     //   194: goto +5 -> 199
/*     */     //   197: astore 8
/*     */     //   199: aload_2
/*     */     //   200: ifnull +16 -> 216
/*     */     //   203: aload_2
/*     */     //   204: invokeinterface 301 1 0
/*     */     //   209: aconst_null
/*     */     //   210: astore_2
/*     */     //   211: goto +5 -> 216
/*     */     //   214: astore 8
/*     */     //   216: aload_1
/*     */     //   217: ifnull +126 -> 343
/*     */     //   220: aload_1
/*     */     //   221: invokeinterface 242 1 0
/*     */     //   226: aconst_null
/*     */     //   227: astore_1
/*     */     //   228: goto +115 -> 343
/*     */     //   231: astore 8
/*     */     //   233: goto +110 -> 343
/*     */     //   236: astore 7
/*     */     //   238: aload_3
/*     */     //   239: ifnull +16 -> 255
/*     */     //   242: aload_3
/*     */     //   243: invokeinterface 212 1 0
/*     */     //   248: aconst_null
/*     */     //   249: astore_3
/*     */     //   250: goto +5 -> 255
/*     */     //   253: astore 8
/*     */     //   255: aload_2
/*     */     //   256: ifnull +16 -> 272
/*     */     //   259: aload_2
/*     */     //   260: invokeinterface 301 1 0
/*     */     //   265: aconst_null
/*     */     //   266: astore_2
/*     */     //   267: goto +5 -> 272
/*     */     //   270: astore 8
/*     */     //   272: aload_1
/*     */     //   273: ifnull +16 -> 289
/*     */     //   276: aload_1
/*     */     //   277: invokeinterface 242 1 0
/*     */     //   282: aconst_null
/*     */     //   283: astore_1
/*     */     //   284: goto +5 -> 289
/*     */     //   287: astore 8
/*     */     //   289: aload 7
/*     */     //   291: athrow
/*     */     //   292: aload_3
/*     */     //   293: ifnull +16 -> 309
/*     */     //   296: aload_3
/*     */     //   297: invokeinterface 212 1 0
/*     */     //   302: aconst_null
/*     */     //   303: astore_3
/*     */     //   304: goto +5 -> 309
/*     */     //   307: astore 8
/*     */     //   309: aload_2
/*     */     //   310: ifnull +16 -> 326
/*     */     //   313: aload_2
/*     */     //   314: invokeinterface 301 1 0
/*     */     //   319: aconst_null
/*     */     //   320: astore_2
/*     */     //   321: goto +5 -> 326
/*     */     //   324: astore 8
/*     */     //   326: aload_1
/*     */     //   327: ifnull +16 -> 343
/*     */     //   330: aload_1
/*     */     //   331: invokeinterface 242 1 0
/*     */     //   336: aconst_null
/*     */     //   337: astore_1
/*     */     //   338: goto +5 -> 343
/*     */     //   341: astore 8
/*     */     //   343: aload 4
/*     */     //   345: areturn
/*     */     // Line number table:
/*     */     //   Java source line #119	-> byte code offset #0
/*     */     //   Java source line #120	-> byte code offset #2
/*     */     //   Java source line #121	-> byte code offset #4
/*     */     //   Java source line #122	-> byte code offset #6
/*     */     //   Java source line #124	-> byte code offset #9
/*     */     //   Java source line #125	-> byte code offset #18
/*     */     //   Java source line #126	-> byte code offset #27
/*     */     //   Java source line #127	-> byte code offset #43
/*     */     //   Java source line #128	-> byte code offset #52
/*     */     //   Java source line #129	-> byte code offset #62
/*     */     //   Java source line #130	-> byte code offset #69
/*     */     //   Java source line #131	-> byte code offset #81
/*     */     //   Java source line #132	-> byte code offset #90
/*     */     //   Java source line #133	-> byte code offset #93
/*     */     //   Java source line #134	-> byte code offset #102
/*     */     //   Java source line #135	-> byte code offset #114
/*     */     //   Java source line #136	-> byte code offset #126
/*     */     //   Java source line #137	-> byte code offset #138
/*     */     //   Java source line #132	-> byte code offset #156
/*     */     //   Java source line #139	-> byte code offset #168
/*     */     //   Java source line #140	-> byte code offset #170
/*     */     //   Java source line #142	-> byte code offset #182
/*     */     //   Java source line #143	-> byte code offset #199
/*     */     //   Java source line #144	-> byte code offset #216
/*     */     //   Java source line #141	-> byte code offset #236
/*     */     //   Java source line #142	-> byte code offset #238
/*     */     //   Java source line #143	-> byte code offset #255
/*     */     //   Java source line #144	-> byte code offset #272
/*     */     //   Java source line #145	-> byte code offset #289
/*     */     //   Java source line #142	-> byte code offset #292
/*     */     //   Java source line #143	-> byte code offset #309
/*     */     //   Java source line #144	-> byte code offset #326
/*     */     //   Java source line #146	-> byte code offset #343
/*     */     // Local variable table:
/*     */     //   start	length	slot	name	signature
/*     */     //   0	346	0	this	SeguridadDAO
/*     */     //   1	337	1	connection	java.sql.Connection
/*     */     //   3	318	2	statement	java.sql.Statement
/*     */     //   5	299	3	resultSet	java.sql.ResultSet
/*     */     //   7	337	4	privilegiosCa	java.util.Map<String, PrivilegioTO>
/*     */     //   16	55	5	sQuery	StringBuffer
/*     */     //   168	10	5	e	Exception
/*     */     //   100	49	6	privilegioTO	PrivilegioTO
/*     */     //   236	54	7	localObject	Object
/*     */     //   197	1	8	localException1	Exception
/*     */     //   214	1	8	localException2	Exception
/*     */     //   231	1	8	localException3	Exception
/*     */     //   253	1	8	localException4	Exception
/*     */     //   270	1	8	localException5	Exception
/*     */     //   287	1	8	localException6	Exception
/*     */     //   307	1	8	localException7	Exception
/*     */     //   324	1	8	localException8	Exception
/*     */     //   341	1	8	localException9	Exception
/*     */     // Exception table:
/*     */     //   from	to	target	type
/*     */     //   9	165	168	java/lang/Exception
/*     */     //   186	194	197	java/lang/Exception
/*     */     //   203	211	214	java/lang/Exception
/*     */     //   220	228	231	java/lang/Exception
/*     */     //   9	182	236	finally
/*     */     //   242	250	253	java/lang/Exception
/*     */     //   259	267	270	java/lang/Exception
/*     */     //   276	284	287	java/lang/Exception
/*     */     //   296	304	307	java/lang/Exception
/*     */     //   313	321	324	java/lang/Exception
/*     */     //   330	338	341	java/lang/Exception
/*     */   }
/*     */   
/*     */   public void actualizaPrivilegios(int idPerfil, List<PrivilegioTO> privilegios, String numEmpleado)
/*     */     throws CAException
/*     */   {
/* 151 */     actualizaPrivilegios(idPerfil, privilegios, numEmpleado, true);
/*     */   }
/*     */   
/*     */   public boolean actualizaPrivilegiosAsignacion(int idPerfil, int numMaxPtos, String numEmpleado)
/*     */     throws CAException
/*     */   {
/* 157 */     AsignacionDAO asignacion = new AsignacionDAO();
/* 158 */     int numPerfiles = asignacion.obtienePerfilesAsignacion(idPerfil, 0).size();
/*     */     
/* 160 */     if (numPerfiles == 0) {
/* 161 */       PrivilegioTO privilegioTO = null;
/* 162 */       List<PrivilegioTO> privilegios = new ArrayList(0);
/*     */       
/* 164 */       privilegioTO = new PrivilegioTO();
/* 165 */       privilegioTO.setIdProceso(25);
/* 166 */       privilegios.add(privilegioTO);
/*     */       
/* 168 */       privilegioTO = new PrivilegioTO();
/* 169 */       privilegioTO.setIdProceso(71);
/* 170 */       privilegios.add(privilegioTO);
/*     */       
/* 172 */       actualizaPrivilegios(idPerfil, privilegios, numEmpleado, false);
/* 173 */       insertaPerfilAsignacion(idPerfil, numMaxPtos);
/*     */       
/* 175 */       return true;
/*     */     }
/* 177 */     return false;
/*     */   }
/*     */   
/*     */   /* Error */
/*     */   private void actualizaPrivilegios(int idPerfil, List<PrivilegioTO> privilegios, String numEmpleado, boolean esModSeguridad)
/*     */     throws CAException
/*     */   {
/*     */     // Byte code:
/*     */     //   0: aconst_null
/*     */     //   1: astore 5
/*     */     //   3: aconst_null
/*     */     //   4: astore 6
/*     */     //   6: iconst_0
/*     */     //   7: istore 7
/*     */     //   9: new 64	java/lang/StringBuffer
/*     */     //   12: dup
/*     */     //   13: invokespecial 66	java/lang/StringBuffer:<init>	()V
/*     */     //   16: astore 8
/*     */     //   18: aload 8
/*     */     //   20: ldc_w 351
/*     */     //   23: invokevirtual 114	java/lang/StringBuffer:append	(Ljava/lang/String;)Ljava/lang/StringBuffer;
/*     */     //   26: aload_0
/*     */     //   27: getfield 41	com/claro/dao/SeguridadDAO:schema_database	Ljava/lang/String;
/*     */     //   30: invokevirtual 114	java/lang/StringBuffer:append	(Ljava/lang/String;)Ljava/lang/StringBuffer;
/*     */     //   33: ldc_w 353
/*     */     //   36: invokevirtual 114	java/lang/StringBuffer:append	(Ljava/lang/String;)Ljava/lang/StringBuffer;
/*     */     //   39: pop
/*     */     //   40: aload 8
/*     */     //   42: ldc_w 355
/*     */     //   45: invokevirtual 114	java/lang/StringBuffer:append	(Ljava/lang/String;)Ljava/lang/StringBuffer;
/*     */     //   48: pop
/*     */     //   49: invokestatic 29	com/claro/util/ServiceLocator:getInstance	()Lcom/claro/util/ServiceLocator;
/*     */     //   52: getstatic 131	com/claro/util/ServiceLocator:jdbcCirculoAzul	Ljava/lang/String;
/*     */     //   55: invokevirtual 134	com/claro/util/ServiceLocator:getConnection	(Ljava/lang/String;)Ljava/sql/Connection;
/*     */     //   58: astore 5
/*     */     //   60: aload 5
/*     */     //   62: iconst_0
/*     */     //   63: invokeinterface 357 2 0
/*     */     //   68: new 64	java/lang/StringBuffer
/*     */     //   71: dup
/*     */     //   72: invokespecial 66	java/lang/StringBuffer:<init>	()V
/*     */     //   75: astore 9
/*     */     //   77: aload 9
/*     */     //   79: ldc_w 361
/*     */     //   82: invokevirtual 114	java/lang/StringBuffer:append	(Ljava/lang/String;)Ljava/lang/StringBuffer;
/*     */     //   85: aload_0
/*     */     //   86: getfield 41	com/claro/dao/SeguridadDAO:schema_database	Ljava/lang/String;
/*     */     //   89: invokevirtual 114	java/lang/StringBuffer:append	(Ljava/lang/String;)Ljava/lang/StringBuffer;
/*     */     //   92: ldc_w 353
/*     */     //   95: invokevirtual 114	java/lang/StringBuffer:append	(Ljava/lang/String;)Ljava/lang/StringBuffer;
/*     */     //   98: pop
/*     */     //   99: aload 9
/*     */     //   101: ldc_w 363
/*     */     //   104: invokevirtual 114	java/lang/StringBuffer:append	(Ljava/lang/String;)Ljava/lang/StringBuffer;
/*     */     //   107: pop
/*     */     //   108: iload 4
/*     */     //   110: ifne +12 -> 122
/*     */     //   113: aload 9
/*     */     //   115: ldc_w 365
/*     */     //   118: invokevirtual 114	java/lang/StringBuffer:append	(Ljava/lang/String;)Ljava/lang/StringBuffer;
/*     */     //   121: pop
/*     */     //   122: aload 5
/*     */     //   124: aload 9
/*     */     //   126: invokevirtual 138	java/lang/StringBuffer:toString	()Ljava/lang/String;
/*     */     //   129: invokeinterface 139 2 0
/*     */     //   134: astore 6
/*     */     //   136: aload 6
/*     */     //   138: iconst_1
/*     */     //   139: iload_1
/*     */     //   140: invokeinterface 367 3 0
/*     */     //   145: iload 4
/*     */     //   147: ifne +23 -> 170
/*     */     //   150: aload 6
/*     */     //   152: iconst_2
/*     */     //   153: bipush 25
/*     */     //   155: invokeinterface 367 3 0
/*     */     //   160: aload 6
/*     */     //   162: iconst_3
/*     */     //   163: bipush 71
/*     */     //   165: invokeinterface 367 3 0
/*     */     //   170: aload 6
/*     */     //   172: invokeinterface 370 1 0
/*     */     //   177: pop
/*     */     //   178: aload 6
/*     */     //   180: ifnull +13 -> 193
/*     */     //   183: aload 6
/*     */     //   185: invokeinterface 215 1 0
/*     */     //   190: aconst_null
/*     */     //   191: astore 6
/*     */     //   193: aload_2
/*     */     //   194: invokeinterface 373 1 0
/*     */     //   199: astore 11
/*     */     //   201: goto +87 -> 288
/*     */     //   204: aload 11
/*     */     //   206: invokeinterface 377 1 0
/*     */     //   211: checkcast 158	com/claro/transfer/PrivilegioTO
/*     */     //   214: astore 10
/*     */     //   216: aload 10
/*     */     //   218: invokevirtual 191	com/claro/transfer/PrivilegioTO:getIdProceso	()I
/*     */     //   221: bipush 71
/*     */     //   223: if_icmpne +6 -> 229
/*     */     //   226: iconst_1
/*     */     //   227: istore 7
/*     */     //   229: aload 5
/*     */     //   231: aload 8
/*     */     //   233: invokevirtual 138	java/lang/StringBuffer:toString	()Ljava/lang/String;
/*     */     //   236: invokeinterface 139 2 0
/*     */     //   241: astore 6
/*     */     //   243: aload 6
/*     */     //   245: iconst_1
/*     */     //   246: iload_1
/*     */     //   247: invokeinterface 367 3 0
/*     */     //   252: aload 6
/*     */     //   254: iconst_2
/*     */     //   255: aload 10
/*     */     //   257: invokevirtual 191	com/claro/transfer/PrivilegioTO:getIdProceso	()I
/*     */     //   260: invokeinterface 367 3 0
/*     */     //   265: aload 6
/*     */     //   267: invokeinterface 370 1 0
/*     */     //   272: pop
/*     */     //   273: aload 6
/*     */     //   275: ifnull +13 -> 288
/*     */     //   278: aload 6
/*     */     //   280: invokeinterface 215 1 0
/*     */     //   285: aconst_null
/*     */     //   286: astore 6
/*     */     //   288: aload 11
/*     */     //   290: invokeinterface 382 1 0
/*     */     //   295: ifne -91 -> 204
/*     */     //   298: iload 7
/*     */     //   300: ifne +113 -> 413
/*     */     //   303: new 64	java/lang/StringBuffer
/*     */     //   306: dup
/*     */     //   307: invokespecial 66	java/lang/StringBuffer:<init>	()V
/*     */     //   310: astore 10
/*     */     //   312: aload 10
/*     */     //   314: ldc_w 361
/*     */     //   317: invokevirtual 114	java/lang/StringBuffer:append	(Ljava/lang/String;)Ljava/lang/StringBuffer;
/*     */     //   320: aload_0
/*     */     //   321: getfield 41	com/claro/dao/SeguridadDAO:schema_database	Ljava/lang/String;
/*     */     //   324: invokevirtual 114	java/lang/StringBuffer:append	(Ljava/lang/String;)Ljava/lang/StringBuffer;
/*     */     //   327: ldc_w 385
/*     */     //   330: invokevirtual 114	java/lang/StringBuffer:append	(Ljava/lang/String;)Ljava/lang/StringBuffer;
/*     */     //   333: pop
/*     */     //   334: aload 10
/*     */     //   336: ldc_w 363
/*     */     //   339: invokevirtual 114	java/lang/StringBuffer:append	(Ljava/lang/String;)Ljava/lang/StringBuffer;
/*     */     //   342: pop
/*     */     //   343: aload 5
/*     */     //   345: aload 10
/*     */     //   347: invokevirtual 138	java/lang/StringBuffer:toString	()Ljava/lang/String;
/*     */     //   350: invokeinterface 139 2 0
/*     */     //   355: astore 6
/*     */     //   357: aload 6
/*     */     //   359: iconst_1
/*     */     //   360: iload_1
/*     */     //   361: invokeinterface 367 3 0
/*     */     //   366: aload 6
/*     */     //   368: invokeinterface 370 1 0
/*     */     //   373: pop
/*     */     //   374: aload 6
/*     */     //   376: ifnull +37 -> 413
/*     */     //   379: aload 6
/*     */     //   381: invokeinterface 215 1 0
/*     */     //   386: aconst_null
/*     */     //   387: astore 6
/*     */     //   389: goto +24 -> 413
/*     */     //   392: astore 9
/*     */     //   394: aload 5
/*     */     //   396: invokeinterface 387 1 0
/*     */     //   401: aload_0
/*     */     //   402: getfield 27	com/claro/dao/SeguridadDAO:error	Lorg/apache/log4j/Logger;
/*     */     //   405: ldc_w 390
/*     */     //   408: aload 9
/*     */     //   410: invokevirtual 225	org/apache/log4j/Logger:info	(Ljava/lang/Object;Ljava/lang/Throwable;)V
/*     */     //   413: aload 6
/*     */     //   415: ifnull +13 -> 428
/*     */     //   418: aload 6
/*     */     //   420: invokeinterface 215 1 0
/*     */     //   425: aconst_null
/*     */     //   426: astore 6
/*     */     //   428: new 64	java/lang/StringBuffer
/*     */     //   431: dup
/*     */     //   432: invokespecial 66	java/lang/StringBuffer:<init>	()V
/*     */     //   435: astore 8
/*     */     //   437: aload 8
/*     */     //   439: ldc_w 392
/*     */     //   442: invokevirtual 114	java/lang/StringBuffer:append	(Ljava/lang/String;)Ljava/lang/StringBuffer;
/*     */     //   445: aload_0
/*     */     //   446: getfield 41	com/claro/dao/SeguridadDAO:schema_database	Ljava/lang/String;
/*     */     //   449: invokevirtual 114	java/lang/StringBuffer:append	(Ljava/lang/String;)Ljava/lang/StringBuffer;
/*     */     //   452: ldc_w 394
/*     */     //   455: invokevirtual 114	java/lang/StringBuffer:append	(Ljava/lang/String;)Ljava/lang/StringBuffer;
/*     */     //   458: pop
/*     */     //   459: aload 8
/*     */     //   461: ldc_w 396
/*     */     //   464: invokevirtual 114	java/lang/StringBuffer:append	(Ljava/lang/String;)Ljava/lang/StringBuffer;
/*     */     //   467: pop
/*     */     //   468: aload 5
/*     */     //   470: aload 8
/*     */     //   472: invokevirtual 138	java/lang/StringBuffer:toString	()Ljava/lang/String;
/*     */     //   475: invokeinterface 139 2 0
/*     */     //   480: astore 6
/*     */     //   482: aload 6
/*     */     //   484: iconst_1
/*     */     //   485: aload_3
/*     */     //   486: invokeinterface 145 3 0
/*     */     //   491: aload 6
/*     */     //   493: iconst_2
/*     */     //   494: new 398	java/sql/Timestamp
/*     */     //   497: dup
/*     */     //   498: invokestatic 95	java/lang/System:currentTimeMillis	()J
/*     */     //   501: invokespecial 400	java/sql/Timestamp:<init>	(J)V
/*     */     //   504: invokeinterface 403 3 0
/*     */     //   509: aload 6
/*     */     //   511: iconst_3
/*     */     //   512: iload_1
/*     */     //   513: invokeinterface 367 3 0
/*     */     //   518: aload 6
/*     */     //   520: invokeinterface 407 1 0
/*     */     //   525: pop
/*     */     //   526: aload 5
/*     */     //   528: invokeinterface 410 1 0
/*     */     //   533: aload 5
/*     */     //   535: iconst_1
/*     */     //   536: invokeinterface 357 2 0
/*     */     //   541: goto +93 -> 634
/*     */     //   544: astore 9
/*     */     //   546: aload_0
/*     */     //   547: getfield 27	com/claro/dao/SeguridadDAO:error	Lorg/apache/log4j/Logger;
/*     */     //   550: ldc_w 390
/*     */     //   553: aload 9
/*     */     //   555: invokevirtual 225	org/apache/log4j/Logger:info	(Ljava/lang/Object;Ljava/lang/Throwable;)V
/*     */     //   558: aload 6
/*     */     //   560: ifnull +15 -> 575
/*     */     //   563: aload 6
/*     */     //   565: invokeinterface 215 1 0
/*     */     //   570: goto +5 -> 575
/*     */     //   573: astore 13
/*     */     //   575: aload 5
/*     */     //   577: ifnull +91 -> 668
/*     */     //   580: aload 5
/*     */     //   582: invokeinterface 242 1 0
/*     */     //   587: goto +81 -> 668
/*     */     //   590: astore 13
/*     */     //   592: goto +76 -> 668
/*     */     //   595: astore 12
/*     */     //   597: aload 6
/*     */     //   599: ifnull +15 -> 614
/*     */     //   602: aload 6
/*     */     //   604: invokeinterface 215 1 0
/*     */     //   609: goto +5 -> 614
/*     */     //   612: astore 13
/*     */     //   614: aload 5
/*     */     //   616: ifnull +15 -> 631
/*     */     //   619: aload 5
/*     */     //   621: invokeinterface 242 1 0
/*     */     //   626: goto +5 -> 631
/*     */     //   629: astore 13
/*     */     //   631: aload 12
/*     */     //   633: athrow
/*     */     //   634: aload 6
/*     */     //   636: ifnull +15 -> 651
/*     */     //   639: aload 6
/*     */     //   641: invokeinterface 215 1 0
/*     */     //   646: goto +5 -> 651
/*     */     //   649: astore 13
/*     */     //   651: aload 5
/*     */     //   653: ifnull +15 -> 668
/*     */     //   656: aload 5
/*     */     //   658: invokeinterface 242 1 0
/*     */     //   663: goto +5 -> 668
/*     */     //   666: astore 13
/*     */     //   668: return
/*     */     // Line number table:
/*     */     //   Java source line #184	-> byte code offset #0
/*     */     //   Java source line #185	-> byte code offset #3
/*     */     //   Java source line #187	-> byte code offset #6
/*     */     //   Java source line #189	-> byte code offset #9
/*     */     //   Java source line #190	-> byte code offset #18
/*     */     //   Java source line #191	-> byte code offset #40
/*     */     //   Java source line #194	-> byte code offset #49
/*     */     //   Java source line #195	-> byte code offset #60
/*     */     //   Java source line #198	-> byte code offset #68
/*     */     //   Java source line #199	-> byte code offset #77
/*     */     //   Java source line #200	-> byte code offset #99
/*     */     //   Java source line #208	-> byte code offset #108
/*     */     //   Java source line #209	-> byte code offset #113
/*     */     //   Java source line #211	-> byte code offset #122
/*     */     //   Java source line #212	-> byte code offset #136
/*     */     //   Java source line #213	-> byte code offset #145
/*     */     //   Java source line #214	-> byte code offset #150
/*     */     //   Java source line #215	-> byte code offset #160
/*     */     //   Java source line #218	-> byte code offset #170
/*     */     //   Java source line #219	-> byte code offset #178
/*     */     //   Java source line #221	-> byte code offset #193
/*     */     //   Java source line #222	-> byte code offset #216
/*     */     //   Java source line #223	-> byte code offset #226
/*     */     //   Java source line #225	-> byte code offset #229
/*     */     //   Java source line #226	-> byte code offset #243
/*     */     //   Java source line #227	-> byte code offset #252
/*     */     //   Java source line #228	-> byte code offset #265
/*     */     //   Java source line #229	-> byte code offset #273
/*     */     //   Java source line #221	-> byte code offset #288
/*     */     //   Java source line #233	-> byte code offset #298
/*     */     //   Java source line #234	-> byte code offset #303
/*     */     //   Java source line #235	-> byte code offset #312
/*     */     //   Java source line #236	-> byte code offset #334
/*     */     //   Java source line #238	-> byte code offset #343
/*     */     //   Java source line #239	-> byte code offset #357
/*     */     //   Java source line #240	-> byte code offset #366
/*     */     //   Java source line #241	-> byte code offset #374
/*     */     //   Java source line #244	-> byte code offset #392
/*     */     //   Java source line #245	-> byte code offset #394
/*     */     //   Java source line #246	-> byte code offset #401
/*     */     //   Java source line #249	-> byte code offset #413
/*     */     //   Java source line #250	-> byte code offset #428
/*     */     //   Java source line #252	-> byte code offset #437
/*     */     //   Java source line #253	-> byte code offset #459
/*     */     //   Java source line #255	-> byte code offset #468
/*     */     //   Java source line #256	-> byte code offset #482
/*     */     //   Java source line #257	-> byte code offset #491
/*     */     //   Java source line #258	-> byte code offset #509
/*     */     //   Java source line #259	-> byte code offset #518
/*     */     //   Java source line #261	-> byte code offset #526
/*     */     //   Java source line #262	-> byte code offset #533
/*     */     //   Java source line #264	-> byte code offset #544
/*     */     //   Java source line #265	-> byte code offset #546
/*     */     //   Java source line #267	-> byte code offset #558
/*     */     //   Java source line #268	-> byte code offset #575
/*     */     //   Java source line #266	-> byte code offset #595
/*     */     //   Java source line #267	-> byte code offset #597
/*     */     //   Java source line #268	-> byte code offset #614
/*     */     //   Java source line #269	-> byte code offset #631
/*     */     //   Java source line #267	-> byte code offset #634
/*     */     //   Java source line #268	-> byte code offset #651
/*     */     //   Java source line #270	-> byte code offset #668
/*     */     // Local variable table:
/*     */     //   start	length	slot	name	signature
/*     */     //   0	669	0	this	SeguridadDAO
/*     */     //   0	669	1	idPerfil	int
/*     */     //   0	669	2	privilegios	List<PrivilegioTO>
/*     */     //   0	669	3	numEmpleado	String
/*     */     //   0	669	4	esModSeguridad	boolean
/*     */     //   1	656	5	conn	java.sql.Connection
/*     */     //   4	636	6	stmt	java.sql.PreparedStatement
/*     */     //   7	292	7	procesoAsignacion	boolean
/*     */     //   16	455	8	query	StringBuffer
/*     */     //   75	50	9	delete	StringBuffer
/*     */     //   392	17	9	e	java.sql.SQLException
/*     */     //   544	10	9	e	Exception
/*     */     //   214	42	10	privilegio	PrivilegioTO
/*     */     //   310	36	10	deletePerfilAsig	StringBuffer
/*     */     //   199	90	11	localIterator	java.util.Iterator
/*     */     //   595	37	12	localObject	Object
/*     */     //   573	1	13	localSQLException1	java.sql.SQLException
/*     */     //   590	1	13	localSQLException2	java.sql.SQLException
/*     */     //   612	1	13	localSQLException3	java.sql.SQLException
/*     */     //   629	1	13	localSQLException4	java.sql.SQLException
/*     */     //   649	1	13	localSQLException5	java.sql.SQLException
/*     */     //   666	1	13	localSQLException6	java.sql.SQLException
/*     */     // Exception table:
/*     */     //   from	to	target	type
/*     */     //   68	389	392	java/sql/SQLException
/*     */     //   49	541	544	java/lang/Exception
/*     */     //   563	570	573	java/sql/SQLException
/*     */     //   580	587	590	java/sql/SQLException
/*     */     //   49	558	595	finally
/*     */     //   602	609	612	java/sql/SQLException
/*     */     //   619	626	629	java/sql/SQLException
/*     */     //   639	646	649	java/sql/SQLException
/*     */     //   656	663	666	java/sql/SQLException
/*     */   }
/*     */   
/*     */   /* Error */
/*     */   private void insertaPerfilAsignacion(int idPerfil, int numPtos)
/*     */     throws CAException
/*     */   {
/*     */     // Byte code:
/*     */     //   0: aconst_null
/*     */     //   1: astore_3
/*     */     //   2: aconst_null
/*     */     //   3: astore 4
/*     */     //   5: new 64	java/lang/StringBuffer
/*     */     //   8: dup
/*     */     //   9: invokespecial 66	java/lang/StringBuffer:<init>	()V
/*     */     //   12: astore 5
/*     */     //   14: aload 5
/*     */     //   16: ldc_w 392
/*     */     //   19: invokevirtual 114	java/lang/StringBuffer:append	(Ljava/lang/String;)Ljava/lang/StringBuffer;
/*     */     //   22: aload_0
/*     */     //   23: getfield 41	com/claro/dao/SeguridadDAO:schema_database	Ljava/lang/String;
/*     */     //   26: invokevirtual 114	java/lang/StringBuffer:append	(Ljava/lang/String;)Ljava/lang/StringBuffer;
/*     */     //   29: ldc_w 385
/*     */     //   32: invokevirtual 114	java/lang/StringBuffer:append	(Ljava/lang/String;)Ljava/lang/StringBuffer;
/*     */     //   35: pop
/*     */     //   36: aload 5
/*     */     //   38: ldc_w 419
/*     */     //   41: invokevirtual 114	java/lang/StringBuffer:append	(Ljava/lang/String;)Ljava/lang/StringBuffer;
/*     */     //   44: pop
/*     */     //   45: invokestatic 29	com/claro/util/ServiceLocator:getInstance	()Lcom/claro/util/ServiceLocator;
/*     */     //   48: getstatic 131	com/claro/util/ServiceLocator:jdbcCirculoAzul	Ljava/lang/String;
/*     */     //   51: invokevirtual 134	com/claro/util/ServiceLocator:getConnection	(Ljava/lang/String;)Ljava/sql/Connection;
/*     */     //   54: astore_3
/*     */     //   55: aload_3
/*     */     //   56: aload 5
/*     */     //   58: invokevirtual 138	java/lang/StringBuffer:toString	()Ljava/lang/String;
/*     */     //   61: invokeinterface 139 2 0
/*     */     //   66: astore 4
/*     */     //   68: aload 4
/*     */     //   70: iconst_1
/*     */     //   71: iload_1
/*     */     //   72: invokeinterface 367 3 0
/*     */     //   77: aload 4
/*     */     //   79: iconst_2
/*     */     //   80: iload_2
/*     */     //   81: invokeinterface 367 3 0
/*     */     //   86: aload 4
/*     */     //   88: invokeinterface 370 1 0
/*     */     //   93: pop
/*     */     //   94: goto +91 -> 185
/*     */     //   97: astore 6
/*     */     //   99: aload_0
/*     */     //   100: getfield 27	com/claro/dao/SeguridadDAO:error	Lorg/apache/log4j/Logger;
/*     */     //   103: ldc_w 421
/*     */     //   106: aload 6
/*     */     //   108: invokevirtual 225	org/apache/log4j/Logger:info	(Ljava/lang/Object;Ljava/lang/Throwable;)V
/*     */     //   111: new 59	com/claro/exception/CAException
/*     */     //   114: dup
/*     */     //   115: iconst_m1
/*     */     //   116: new 67	java/lang/StringBuilder
/*     */     //   119: dup
/*     */     //   120: ldc_w 423
/*     */     //   123: invokespecial 71	java/lang/StringBuilder:<init>	(Ljava/lang/String;)V
/*     */     //   126: aload 6
/*     */     //   128: invokevirtual 241	java/lang/Exception:toString	()Ljava/lang/String;
/*     */     //   131: invokevirtual 89	java/lang/StringBuilder:append	(Ljava/lang/String;)Ljava/lang/StringBuilder;
/*     */     //   134: ldc -24
/*     */     //   136: invokevirtual 89	java/lang/StringBuilder:append	(Ljava/lang/String;)Ljava/lang/StringBuilder;
/*     */     //   139: invokevirtual 104	java/lang/StringBuilder:toString	()Ljava/lang/String;
/*     */     //   142: aload 6
/*     */     //   144: invokespecial 234	com/claro/exception/CAException:<init>	(ILjava/lang/String;Ljava/lang/Exception;)V
/*     */     //   147: athrow
/*     */     //   148: astore 7
/*     */     //   150: aload 4
/*     */     //   152: ifnull +15 -> 167
/*     */     //   155: aload 4
/*     */     //   157: invokeinterface 215 1 0
/*     */     //   162: goto +5 -> 167
/*     */     //   165: astore 8
/*     */     //   167: aload_3
/*     */     //   168: ifnull +14 -> 182
/*     */     //   171: aload_3
/*     */     //   172: invokeinterface 242 1 0
/*     */     //   177: goto +5 -> 182
/*     */     //   180: astore 8
/*     */     //   182: aload 7
/*     */     //   184: athrow
/*     */     //   185: aload 4
/*     */     //   187: ifnull +15 -> 202
/*     */     //   190: aload 4
/*     */     //   192: invokeinterface 215 1 0
/*     */     //   197: goto +5 -> 202
/*     */     //   200: astore 8
/*     */     //   202: aload_3
/*     */     //   203: ifnull +14 -> 217
/*     */     //   206: aload_3
/*     */     //   207: invokeinterface 242 1 0
/*     */     //   212: goto +5 -> 217
/*     */     //   215: astore 8
/*     */     //   217: return
/*     */     // Line number table:
/*     */     //   Java source line #275	-> byte code offset #0
/*     */     //   Java source line #276	-> byte code offset #2
/*     */     //   Java source line #278	-> byte code offset #5
/*     */     //   Java source line #279	-> byte code offset #14
/*     */     //   Java source line #280	-> byte code offset #36
/*     */     //   Java source line #283	-> byte code offset #45
/*     */     //   Java source line #285	-> byte code offset #55
/*     */     //   Java source line #286	-> byte code offset #68
/*     */     //   Java source line #287	-> byte code offset #77
/*     */     //   Java source line #288	-> byte code offset #86
/*     */     //   Java source line #290	-> byte code offset #97
/*     */     //   Java source line #291	-> byte code offset #99
/*     */     //   Java source line #292	-> byte code offset #111
/*     */     //   Java source line #293	-> byte code offset #148
/*     */     //   Java source line #294	-> byte code offset #150
/*     */     //   Java source line #295	-> byte code offset #167
/*     */     //   Java source line #296	-> byte code offset #182
/*     */     //   Java source line #294	-> byte code offset #185
/*     */     //   Java source line #295	-> byte code offset #202
/*     */     //   Java source line #297	-> byte code offset #217
/*     */     // Local variable table:
/*     */     //   start	length	slot	name	signature
/*     */     //   0	218	0	this	SeguridadDAO
/*     */     //   0	218	1	idPerfil	int
/*     */     //   0	218	2	numPtos	int
/*     */     //   1	206	3	conn	java.sql.Connection
/*     */     //   3	188	4	stmt	java.sql.PreparedStatement
/*     */     //   12	45	5	query	StringBuffer
/*     */     //   97	46	6	e	Exception
/*     */     //   148	35	7	localObject	Object
/*     */     //   165	1	8	localSQLException	java.sql.SQLException
/*     */     //   180	1	8	localSQLException1	java.sql.SQLException
/*     */     //   200	1	8	localSQLException2	java.sql.SQLException
/*     */     //   215	1	8	localSQLException3	java.sql.SQLException
/*     */     // Exception table:
/*     */     //   from	to	target	type
/*     */     //   45	94	97	java/lang/Exception
/*     */     //   45	148	148	finally
/*     */     //   155	162	165	java/sql/SQLException
/*     */     //   171	177	180	java/sql/SQLException
/*     */     //   190	197	200	java/sql/SQLException
/*     */     //   206	212	215	java/sql/SQLException
/*     */   }
/*     */   
/*     */   public boolean actualizaPerfilAsignacion(int idPerfil, int numMaxPtos, String numEmpleado)
/*     */     throws CAException
/*     */   {
/* 302 */     return actualizaPerfilAsignacion(idPerfil, numMaxPtos);
/*     */   }
/*     */   
/*     */   /* Error */
/*     */   private boolean actualizaPerfilAsignacion(int idPerfil, int numPtos)
/*     */     throws CAException
/*     */   {
/*     */     // Byte code:
/*     */     //   0: aconst_null
/*     */     //   1: astore_3
/*     */     //   2: aconst_null
/*     */     //   3: astore 4
/*     */     //   5: iconst_0
/*     */     //   6: istore 5
/*     */     //   8: new 64	java/lang/StringBuffer
/*     */     //   11: dup
/*     */     //   12: invokespecial 66	java/lang/StringBuffer:<init>	()V
/*     */     //   15: astore 6
/*     */     //   17: aload 6
/*     */     //   19: ldc_w 430
/*     */     //   22: invokevirtual 114	java/lang/StringBuffer:append	(Ljava/lang/String;)Ljava/lang/StringBuffer;
/*     */     //   25: aload_0
/*     */     //   26: getfield 41	com/claro/dao/SeguridadDAO:schema_database	Ljava/lang/String;
/*     */     //   29: invokevirtual 114	java/lang/StringBuffer:append	(Ljava/lang/String;)Ljava/lang/StringBuffer;
/*     */     //   32: ldc_w 385
/*     */     //   35: invokevirtual 114	java/lang/StringBuffer:append	(Ljava/lang/String;)Ljava/lang/StringBuffer;
/*     */     //   38: pop
/*     */     //   39: aload 6
/*     */     //   41: ldc_w 432
/*     */     //   44: invokevirtual 114	java/lang/StringBuffer:append	(Ljava/lang/String;)Ljava/lang/StringBuffer;
/*     */     //   47: pop
/*     */     //   48: aload 6
/*     */     //   50: ldc_w 434
/*     */     //   53: invokevirtual 114	java/lang/StringBuffer:append	(Ljava/lang/String;)Ljava/lang/StringBuffer;
/*     */     //   56: pop
/*     */     //   57: invokestatic 29	com/claro/util/ServiceLocator:getInstance	()Lcom/claro/util/ServiceLocator;
/*     */     //   60: getstatic 131	com/claro/util/ServiceLocator:jdbcCirculoAzul	Ljava/lang/String;
/*     */     //   63: invokevirtual 134	com/claro/util/ServiceLocator:getConnection	(Ljava/lang/String;)Ljava/sql/Connection;
/*     */     //   66: astore_3
/*     */     //   67: aload_3
/*     */     //   68: aload 6
/*     */     //   70: invokevirtual 138	java/lang/StringBuffer:toString	()Ljava/lang/String;
/*     */     //   73: invokeinterface 139 2 0
/*     */     //   78: astore 4
/*     */     //   80: aload 4
/*     */     //   82: iconst_1
/*     */     //   83: iload_2
/*     */     //   84: invokeinterface 367 3 0
/*     */     //   89: aload 4
/*     */     //   91: iconst_2
/*     */     //   92: iload_1
/*     */     //   93: invokeinterface 367 3 0
/*     */     //   98: aload 4
/*     */     //   100: invokeinterface 370 1 0
/*     */     //   105: ifle +97 -> 202
/*     */     //   108: iconst_1
/*     */     //   109: istore 5
/*     */     //   111: goto +91 -> 202
/*     */     //   114: astore 7
/*     */     //   116: aload_0
/*     */     //   117: getfield 27	com/claro/dao/SeguridadDAO:error	Lorg/apache/log4j/Logger;
/*     */     //   120: ldc_w 436
/*     */     //   123: aload 7
/*     */     //   125: invokevirtual 225	org/apache/log4j/Logger:info	(Ljava/lang/Object;Ljava/lang/Throwable;)V
/*     */     //   128: new 59	com/claro/exception/CAException
/*     */     //   131: dup
/*     */     //   132: iconst_m1
/*     */     //   133: new 67	java/lang/StringBuilder
/*     */     //   136: dup
/*     */     //   137: ldc_w 438
/*     */     //   140: invokespecial 71	java/lang/StringBuilder:<init>	(Ljava/lang/String;)V
/*     */     //   143: aload 7
/*     */     //   145: invokevirtual 241	java/lang/Exception:toString	()Ljava/lang/String;
/*     */     //   148: invokevirtual 89	java/lang/StringBuilder:append	(Ljava/lang/String;)Ljava/lang/StringBuilder;
/*     */     //   151: ldc -24
/*     */     //   153: invokevirtual 89	java/lang/StringBuilder:append	(Ljava/lang/String;)Ljava/lang/StringBuilder;
/*     */     //   156: invokevirtual 104	java/lang/StringBuilder:toString	()Ljava/lang/String;
/*     */     //   159: aload 7
/*     */     //   161: invokespecial 234	com/claro/exception/CAException:<init>	(ILjava/lang/String;Ljava/lang/Exception;)V
/*     */     //   164: athrow
/*     */     //   165: astore 8
/*     */     //   167: aload 4
/*     */     //   169: ifnull +15 -> 184
/*     */     //   172: aload 4
/*     */     //   174: invokeinterface 215 1 0
/*     */     //   179: goto +5 -> 184
/*     */     //   182: astore 9
/*     */     //   184: aload_3
/*     */     //   185: ifnull +14 -> 199
/*     */     //   188: aload_3
/*     */     //   189: invokeinterface 242 1 0
/*     */     //   194: goto +5 -> 199
/*     */     //   197: astore 9
/*     */     //   199: aload 8
/*     */     //   201: athrow
/*     */     //   202: aload 4
/*     */     //   204: ifnull +15 -> 219
/*     */     //   207: aload 4
/*     */     //   209: invokeinterface 215 1 0
/*     */     //   214: goto +5 -> 219
/*     */     //   217: astore 9
/*     */     //   219: aload_3
/*     */     //   220: ifnull +14 -> 234
/*     */     //   223: aload_3
/*     */     //   224: invokeinterface 242 1 0
/*     */     //   229: goto +5 -> 234
/*     */     //   232: astore 9
/*     */     //   234: iload 5
/*     */     //   236: ireturn
/*     */     // Line number table:
/*     */     //   Java source line #308	-> byte code offset #0
/*     */     //   Java source line #309	-> byte code offset #2
/*     */     //   Java source line #310	-> byte code offset #5
/*     */     //   Java source line #312	-> byte code offset #8
/*     */     //   Java source line #313	-> byte code offset #17
/*     */     //   Java source line #314	-> byte code offset #39
/*     */     //   Java source line #315	-> byte code offset #48
/*     */     //   Java source line #318	-> byte code offset #57
/*     */     //   Java source line #320	-> byte code offset #67
/*     */     //   Java source line #321	-> byte code offset #80
/*     */     //   Java source line #322	-> byte code offset #89
/*     */     //   Java source line #324	-> byte code offset #98
/*     */     //   Java source line #325	-> byte code offset #108
/*     */     //   Java source line #327	-> byte code offset #114
/*     */     //   Java source line #328	-> byte code offset #116
/*     */     //   Java source line #329	-> byte code offset #128
/*     */     //   Java source line #330	-> byte code offset #165
/*     */     //   Java source line #331	-> byte code offset #167
/*     */     //   Java source line #332	-> byte code offset #184
/*     */     //   Java source line #333	-> byte code offset #199
/*     */     //   Java source line #331	-> byte code offset #202
/*     */     //   Java source line #332	-> byte code offset #219
/*     */     //   Java source line #334	-> byte code offset #234
/*     */     // Local variable table:
/*     */     //   start	length	slot	name	signature
/*     */     //   0	237	0	this	SeguridadDAO
/*     */     //   0	237	1	idPerfil	int
/*     */     //   0	237	2	numPtos	int
/*     */     //   1	223	3	conn	java.sql.Connection
/*     */     //   3	205	4	stmt	java.sql.PreparedStatement
/*     */     //   6	229	5	seActualizo	boolean
/*     */     //   15	54	6	query	StringBuffer
/*     */     //   114	46	7	e	Exception
/*     */     //   165	35	8	localObject	Object
/*     */     //   182	1	9	localSQLException	java.sql.SQLException
/*     */     //   197	1	9	localSQLException1	java.sql.SQLException
/*     */     //   217	1	9	localSQLException2	java.sql.SQLException
/*     */     //   232	1	9	localSQLException3	java.sql.SQLException
/*     */     // Exception table:
/*     */     //   from	to	target	type
/*     */     //   57	111	114	java/lang/Exception
/*     */     //   57	165	165	finally
/*     */     //   172	179	182	java/sql/SQLException
/*     */     //   188	194	197	java/sql/SQLException
/*     */     //   207	214	217	java/sql/SQLException
/*     */     //   223	229	232	java/sql/SQLException
/*     */   }
/*     */   
/*     */   /* Error */
/*     */   public boolean eliminaPerfilAsignacion(int idPerfil)
/*     */     throws CAException
/*     */   {
/*     */     // Byte code:
/*     */     //   0: aconst_null
/*     */     //   1: astore_2
/*     */     //   2: aconst_null
/*     */     //   3: astore_3
/*     */     //   4: iconst_0
/*     */     //   5: istore 4
/*     */     //   7: new 64	java/lang/StringBuffer
/*     */     //   10: dup
/*     */     //   11: invokespecial 66	java/lang/StringBuffer:<init>	()V
/*     */     //   14: astore 5
/*     */     //   16: aload 5
/*     */     //   18: ldc_w 443
/*     */     //   21: invokevirtual 114	java/lang/StringBuffer:append	(Ljava/lang/String;)Ljava/lang/StringBuffer;
/*     */     //   24: aload_0
/*     */     //   25: getfield 41	com/claro/dao/SeguridadDAO:schema_database	Ljava/lang/String;
/*     */     //   28: invokevirtual 114	java/lang/StringBuffer:append	(Ljava/lang/String;)Ljava/lang/StringBuffer;
/*     */     //   31: ldc_w 385
/*     */     //   34: invokevirtual 114	java/lang/StringBuffer:append	(Ljava/lang/String;)Ljava/lang/StringBuffer;
/*     */     //   37: pop
/*     */     //   38: aload 5
/*     */     //   40: ldc_w 434
/*     */     //   43: invokevirtual 114	java/lang/StringBuffer:append	(Ljava/lang/String;)Ljava/lang/StringBuffer;
/*     */     //   46: pop
/*     */     //   47: invokestatic 29	com/claro/util/ServiceLocator:getInstance	()Lcom/claro/util/ServiceLocator;
/*     */     //   50: getstatic 131	com/claro/util/ServiceLocator:jdbcCirculoAzul	Ljava/lang/String;
/*     */     //   53: invokevirtual 134	com/claro/util/ServiceLocator:getConnection	(Ljava/lang/String;)Ljava/sql/Connection;
/*     */     //   56: astore_2
/*     */     //   57: aload_2
/*     */     //   58: aload 5
/*     */     //   60: invokevirtual 138	java/lang/StringBuffer:toString	()Ljava/lang/String;
/*     */     //   63: invokeinterface 139 2 0
/*     */     //   68: astore_3
/*     */     //   69: aload_3
/*     */     //   70: iconst_1
/*     */     //   71: iload_1
/*     */     //   72: invokeinterface 367 3 0
/*     */     //   77: aload_3
/*     */     //   78: invokeinterface 370 1 0
/*     */     //   83: ifle +95 -> 178
/*     */     //   86: iconst_1
/*     */     //   87: istore 4
/*     */     //   89: goto +89 -> 178
/*     */     //   92: astore 6
/*     */     //   94: aload_0
/*     */     //   95: getfield 27	com/claro/dao/SeguridadDAO:error	Lorg/apache/log4j/Logger;
/*     */     //   98: ldc_w 436
/*     */     //   101: aload 6
/*     */     //   103: invokevirtual 225	org/apache/log4j/Logger:info	(Ljava/lang/Object;Ljava/lang/Throwable;)V
/*     */     //   106: new 59	com/claro/exception/CAException
/*     */     //   109: dup
/*     */     //   110: iconst_m1
/*     */     //   111: new 67	java/lang/StringBuilder
/*     */     //   114: dup
/*     */     //   115: ldc_w 438
/*     */     //   118: invokespecial 71	java/lang/StringBuilder:<init>	(Ljava/lang/String;)V
/*     */     //   121: aload 6
/*     */     //   123: invokevirtual 241	java/lang/Exception:toString	()Ljava/lang/String;
/*     */     //   126: invokevirtual 89	java/lang/StringBuilder:append	(Ljava/lang/String;)Ljava/lang/StringBuilder;
/*     */     //   129: ldc -24
/*     */     //   131: invokevirtual 89	java/lang/StringBuilder:append	(Ljava/lang/String;)Ljava/lang/StringBuilder;
/*     */     //   134: invokevirtual 104	java/lang/StringBuilder:toString	()Ljava/lang/String;
/*     */     //   137: aload 6
/*     */     //   139: invokespecial 234	com/claro/exception/CAException:<init>	(ILjava/lang/String;Ljava/lang/Exception;)V
/*     */     //   142: athrow
/*     */     //   143: astore 7
/*     */     //   145: aload_3
/*     */     //   146: ifnull +14 -> 160
/*     */     //   149: aload_3
/*     */     //   150: invokeinterface 215 1 0
/*     */     //   155: goto +5 -> 160
/*     */     //   158: astore 8
/*     */     //   160: aload_2
/*     */     //   161: ifnull +14 -> 175
/*     */     //   164: aload_2
/*     */     //   165: invokeinterface 242 1 0
/*     */     //   170: goto +5 -> 175
/*     */     //   173: astore 8
/*     */     //   175: aload 7
/*     */     //   177: athrow
/*     */     //   178: aload_3
/*     */     //   179: ifnull +14 -> 193
/*     */     //   182: aload_3
/*     */     //   183: invokeinterface 215 1 0
/*     */     //   188: goto +5 -> 193
/*     */     //   191: astore 8
/*     */     //   193: aload_2
/*     */     //   194: ifnull +14 -> 208
/*     */     //   197: aload_2
/*     */     //   198: invokeinterface 242 1 0
/*     */     //   203: goto +5 -> 208
/*     */     //   206: astore 8
/*     */     //   208: iload 4
/*     */     //   210: ireturn
/*     */     // Line number table:
/*     */     //   Java source line #340	-> byte code offset #0
/*     */     //   Java source line #341	-> byte code offset #2
/*     */     //   Java source line #342	-> byte code offset #4
/*     */     //   Java source line #344	-> byte code offset #7
/*     */     //   Java source line #345	-> byte code offset #16
/*     */     //   Java source line #346	-> byte code offset #38
/*     */     //   Java source line #349	-> byte code offset #47
/*     */     //   Java source line #351	-> byte code offset #57
/*     */     //   Java source line #352	-> byte code offset #69
/*     */     //   Java source line #354	-> byte code offset #77
/*     */     //   Java source line #355	-> byte code offset #86
/*     */     //   Java source line #357	-> byte code offset #92
/*     */     //   Java source line #358	-> byte code offset #94
/*     */     //   Java source line #359	-> byte code offset #106
/*     */     //   Java source line #360	-> byte code offset #143
/*     */     //   Java source line #361	-> byte code offset #145
/*     */     //   Java source line #362	-> byte code offset #160
/*     */     //   Java source line #363	-> byte code offset #175
/*     */     //   Java source line #361	-> byte code offset #178
/*     */     //   Java source line #362	-> byte code offset #193
/*     */     //   Java source line #364	-> byte code offset #208
/*     */     // Local variable table:
/*     */     //   start	length	slot	name	signature
/*     */     //   0	211	0	this	SeguridadDAO
/*     */     //   0	211	1	idPerfil	int
/*     */     //   1	197	2	conn	java.sql.Connection
/*     */     //   3	180	3	stmt	java.sql.PreparedStatement
/*     */     //   5	204	4	seElimino	boolean
/*     */     //   14	45	5	query	StringBuffer
/*     */     //   92	46	6	e	Exception
/*     */     //   143	33	7	localObject	Object
/*     */     //   158	1	8	localSQLException	java.sql.SQLException
/*     */     //   173	1	8	localSQLException1	java.sql.SQLException
/*     */     //   191	1	8	localSQLException2	java.sql.SQLException
/*     */     //   206	1	8	localSQLException3	java.sql.SQLException
/*     */     // Exception table:
/*     */     //   from	to	target	type
/*     */     //   47	89	92	java/lang/Exception
/*     */     //   47	143	143	finally
/*     */     //   149	155	158	java/sql/SQLException
/*     */     //   164	170	173	java/sql/SQLException
/*     */     //   182	188	191	java/sql/SQLException
/*     */     //   197	203	206	java/sql/SQLException
/*     */   }
/*     */ }


/* Location:              /opt/trabajo/claro/Guatemala/IS/CO/ClaroClub.ear!/ClaroClubEJB.jar!/com/claro/dao/SeguridadDAO.class
 * Java compiler version: 6 (50.0)
 * JD-Core Version:       0.7.1
 */