/*     */ package com.claro.dao;
/*     */ 
/*     */ import com.claro.exception.CAException;
/*     */ import com.claro.transfer.MobileTO;
/*     */ import com.claro.transfer.ParametrosTO;
/*     */ import com.claro.transfer.PuntosTO;
/*     */ import com.claro.transfer.TelefonoTO;
/*     */ import com.claro.transfer.transpuntos.TransferenciaTO;
/*     */ import com.claro.util.ServiceLocator;
/*     */ import java.sql.Connection;
/*     */ import java.sql.SQLException;
/*     */ import org.apache.log4j.Logger;
/*     */ 
/*     */ public class TransferenciaAnexoDAO
/*     */   extends TranasferenciaDAO
/*     */ {
/*     */   /* Error */
/*     */   public TransferenciaTO transferirPuntosAnexo(TransferenciaTO _transfTO)
/*     */     throws CAException
/*     */   {
/*     */     // Byte code:
/*     */     //   0: aconst_null
/*     */     //   1: astore_2
/*     */     //   2: new 19	com/claro/transfer/PuntosTO
/*     */     //   5: dup
/*     */     //   6: invokespecial 21	com/claro/transfer/PuntosTO:<init>	()V
/*     */     //   9: astore_3
/*     */     //   10: new 22	com/claro/transfer/MensajeTO
/*     */     //   13: dup
/*     */     //   14: invokespecial 24	com/claro/transfer/MensajeTO:<init>	()V
/*     */     //   17: astore 4
/*     */     //   19: new 25	com/claro/dao/PuntosDAO
/*     */     //   22: dup
/*     */     //   23: invokespecial 27	com/claro/dao/PuntosDAO:<init>	()V
/*     */     //   26: astore 5
/*     */     //   28: bipush 7
/*     */     //   30: newarray <illegal type>
/*     */     //   32: astore 6
/*     */     //   34: iconst_0
/*     */     //   35: istore 7
/*     */     //   37: invokestatic 28	java/lang/System:currentTimeMillis	()J
/*     */     //   40: lstore 8
/*     */     //   42: aload_0
/*     */     //   43: getfield 34	com/claro/dao/TransferenciaAnexoDAO:logger	Lorg/apache/log4j/Logger;
/*     */     //   46: new 38	java/lang/StringBuilder
/*     */     //   49: dup
/*     */     //   50: ldc 40
/*     */     //   52: invokespecial 42	java/lang/StringBuilder:<init>	(Ljava/lang/String;)V
/*     */     //   55: getstatic 45	com/claro/util/Constantes:DATEFORMTALog	Ljava/text/SimpleDateFormat;
/*     */     //   58: new 51	java/util/Date
/*     */     //   61: dup
/*     */     //   62: invokespecial 53	java/util/Date:<init>	()V
/*     */     //   65: invokevirtual 54	java/text/SimpleDateFormat:format	(Ljava/util/Date;)Ljava/lang/String;
/*     */     //   68: invokevirtual 60	java/lang/StringBuilder:append	(Ljava/lang/String;)Ljava/lang/StringBuilder;
/*     */     //   71: ldc 64
/*     */     //   73: invokevirtual 60	java/lang/StringBuilder:append	(Ljava/lang/String;)Ljava/lang/StringBuilder;
/*     */     //   76: lload 8
/*     */     //   78: invokevirtual 66	java/lang/StringBuilder:append	(J)Ljava/lang/StringBuilder;
/*     */     //   81: invokevirtual 69	java/lang/StringBuilder:toString	()Ljava/lang/String;
/*     */     //   84: invokevirtual 73	org/apache/log4j/Logger:info	(Ljava/lang/Object;)V
/*     */     //   87: aload_0
/*     */     //   88: getfield 79	com/claro/dao/TransferenciaAnexoDAO:consultasPuntosDAO	Lcom/claro/dao/ConsultasDAO;
/*     */     //   91: aload_1
/*     */     //   92: invokevirtual 83	com/claro/transfer/transpuntos/TransferenciaTO:getCuentaOrigen	()Ljava/lang/String;
/*     */     //   95: aload_1
/*     */     //   96: invokevirtual 88	com/claro/transfer/transpuntos/TransferenciaTO:getSecuenciaOrigen	()I
/*     */     //   99: invokevirtual 92	com/claro/dao/ConsultasDAO:obtienePuntos	(Ljava/lang/String;I)Lcom/claro/transfer/PuntosTO;
/*     */     //   102: astore_3
/*     */     //   103: aload_3
/*     */     //   104: invokevirtual 98	com/claro/transfer/PuntosTO:getIdMensaje	()I
/*     */     //   107: ifeq +36 -> 143
/*     */     //   110: new 17	com/claro/exception/CAException
/*     */     //   113: dup
/*     */     //   114: iconst_m1
/*     */     //   115: new 38	java/lang/StringBuilder
/*     */     //   118: dup
/*     */     //   119: ldc 101
/*     */     //   121: invokespecial 42	java/lang/StringBuilder:<init>	(Ljava/lang/String;)V
/*     */     //   124: aload_1
/*     */     //   125: invokevirtual 103	com/claro/transfer/transpuntos/TransferenciaTO:getTelefonoOrigen	()Ljava/lang/String;
/*     */     //   128: invokevirtual 60	java/lang/StringBuilder:append	(Ljava/lang/String;)Ljava/lang/StringBuilder;
/*     */     //   131: ldc 106
/*     */     //   133: invokevirtual 60	java/lang/StringBuilder:append	(Ljava/lang/String;)Ljava/lang/StringBuilder;
/*     */     //   136: invokevirtual 69	java/lang/StringBuilder:toString	()Ljava/lang/String;
/*     */     //   139: invokespecial 108	com/claro/exception/CAException:<init>	(ILjava/lang/String;)V
/*     */     //   142: athrow
/*     */     //   143: aload_1
/*     */     //   144: invokevirtual 111	com/claro/transfer/transpuntos/TransferenciaTO:getPuntosTrasnferidos	()I
/*     */     //   147: istore 7
/*     */     //   149: aload_1
/*     */     //   150: aload_3
/*     */     //   151: invokevirtual 114	com/claro/transfer/PuntosTO:getPtosDisponibles	()I
/*     */     //   154: invokevirtual 117	com/claro/transfer/transpuntos/TransferenciaTO:setPtosDisponiblesOrigen	(I)V
/*     */     //   157: aload 6
/*     */     //   159: iconst_0
/*     */     //   160: aload_3
/*     */     //   161: invokevirtual 121	com/claro/transfer/PuntosTO:getPtsPorVencer	()I
/*     */     //   164: iastore
/*     */     //   165: aload 6
/*     */     //   167: iconst_1
/*     */     //   168: aload_3
/*     */     //   169: invokevirtual 124	com/claro/transfer/PuntosTO:getPtsPorVencer1	()I
/*     */     //   172: iastore
/*     */     //   173: aload 6
/*     */     //   175: iconst_2
/*     */     //   176: aload_3
/*     */     //   177: invokevirtual 127	com/claro/transfer/PuntosTO:getPtsPorVencer2	()I
/*     */     //   180: iastore
/*     */     //   181: aload 6
/*     */     //   183: iconst_3
/*     */     //   184: aload_3
/*     */     //   185: invokevirtual 130	com/claro/transfer/PuntosTO:getPtsPromocion	()I
/*     */     //   188: iastore
/*     */     //   189: aload 6
/*     */     //   191: iconst_4
/*     */     //   192: aload_3
/*     */     //   193: invokevirtual 133	com/claro/transfer/PuntosTO:getPtsAntiguedad	()I
/*     */     //   196: iastore
/*     */     //   197: aload 6
/*     */     //   199: iconst_5
/*     */     //   200: aload_3
/*     */     //   201: invokevirtual 136	com/claro/transfer/PuntosTO:getPtsExcedentes	()I
/*     */     //   204: iastore
/*     */     //   205: aload 6
/*     */     //   207: bipush 6
/*     */     //   209: aload_3
/*     */     //   210: invokevirtual 139	com/claro/transfer/PuntosTO:getPtsRenta	()I
/*     */     //   213: iastore
/*     */     //   214: iconst_0
/*     */     //   215: istore 10
/*     */     //   217: goto +62 -> 279
/*     */     //   220: aload 6
/*     */     //   222: iload 10
/*     */     //   224: iaload
/*     */     //   225: ifle +51 -> 276
/*     */     //   228: aload 6
/*     */     //   230: iload 10
/*     */     //   232: iaload
/*     */     //   233: iload 7
/*     */     //   235: if_icmpge +22 -> 257
/*     */     //   238: iload 7
/*     */     //   240: aload 6
/*     */     //   242: iload 10
/*     */     //   244: iaload
/*     */     //   245: isub
/*     */     //   246: istore 7
/*     */     //   248: aload 6
/*     */     //   250: iload 10
/*     */     //   252: iconst_0
/*     */     //   253: iastore
/*     */     //   254: goto +22 -> 276
/*     */     //   257: aload 6
/*     */     //   259: iload 10
/*     */     //   261: aload 6
/*     */     //   263: iload 10
/*     */     //   265: iaload
/*     */     //   266: iload 7
/*     */     //   268: isub
/*     */     //   269: iastore
/*     */     //   270: iconst_0
/*     */     //   271: istore 7
/*     */     //   273: goto +13 -> 286
/*     */     //   276: iinc 10 1
/*     */     //   279: iload 10
/*     */     //   281: bipush 7
/*     */     //   283: if_icmplt -63 -> 220
/*     */     //   286: iload 7
/*     */     //   288: ifeq +12 -> 300
/*     */     //   291: iload 7
/*     */     //   293: aload_1
/*     */     //   294: invokevirtual 111	com/claro/transfer/transpuntos/TransferenciaTO:getPuntosTrasnferidos	()I
/*     */     //   297: isub
/*     */     //   298: istore 7
/*     */     //   300: aload_0
/*     */     //   301: aload 6
/*     */     //   303: aload_3
/*     */     //   304: invokespecial 142	com/claro/dao/TransferenciaAnexoDAO:actualizaInfoPuntos	([ILcom/claro/transfer/PuntosTO;)V
/*     */     //   307: aload_0
/*     */     //   308: aload_1
/*     */     //   309: invokespecial 146	com/claro/dao/TransferenciaAnexoDAO:validaInfoTransferenciaAnexo	(Lcom/claro/transfer/transpuntos/TransferenciaTO;)Lcom/claro/transfer/TelefonoTO;
/*     */     //   312: astore 10
/*     */     //   314: aload_1
/*     */     //   315: aload 10
/*     */     //   317: invokevirtual 150	com/claro/transfer/TelefonoTO:getMobileTO	()Lcom/claro/transfer/MobileTO;
/*     */     //   320: invokevirtual 156	com/claro/transfer/MobileTO:getSecuencia	()Ljava/lang/String;
/*     */     //   323: invokestatic 161	java/lang/Integer:parseInt	(Ljava/lang/String;)I
/*     */     //   326: invokevirtual 167	com/claro/transfer/transpuntos/TransferenciaTO:setSecuenciaDestino	(I)V
/*     */     //   329: invokestatic 170	com/claro/util/ServiceLocator:getInstance	()Lcom/claro/util/ServiceLocator;
/*     */     //   332: getstatic 176	com/claro/util/ServiceLocator:jdbcCirculoAzul	Ljava/lang/String;
/*     */     //   335: invokevirtual 180	com/claro/util/ServiceLocator:getConnection	(Ljava/lang/String;)Ljava/sql/Connection;
/*     */     //   338: astore_2
/*     */     //   339: aload_2
/*     */     //   340: iconst_0
/*     */     //   341: invokeinterface 184 2 0
/*     */     //   346: aload_0
/*     */     //   347: aload_2
/*     */     //   348: aload_3
/*     */     //   349: aload_1
/*     */     //   350: invokevirtual 83	com/claro/transfer/transpuntos/TransferenciaTO:getCuentaOrigen	()Ljava/lang/String;
/*     */     //   353: aload_1
/*     */     //   354: invokevirtual 88	com/claro/transfer/transpuntos/TransferenciaTO:getSecuenciaOrigen	()I
/*     */     //   357: invokespecial 190	com/claro/dao/TransferenciaAnexoDAO:actualizaTotalesOrigenAnexo	(Ljava/sql/Connection;Lcom/claro/transfer/PuntosTO;Ljava/lang/String;I)Z
/*     */     //   360: ifne +42 -> 402
/*     */     //   363: aload_2
/*     */     //   364: invokeinterface 194 1 0
/*     */     //   369: new 17	com/claro/exception/CAException
/*     */     //   372: dup
/*     */     //   373: iconst_m1
/*     */     //   374: new 38	java/lang/StringBuilder
/*     */     //   377: dup
/*     */     //   378: ldc -59
/*     */     //   380: invokespecial 42	java/lang/StringBuilder:<init>	(Ljava/lang/String;)V
/*     */     //   383: aload_1
/*     */     //   384: invokevirtual 103	com/claro/transfer/transpuntos/TransferenciaTO:getTelefonoOrigen	()Ljava/lang/String;
/*     */     //   387: invokevirtual 60	java/lang/StringBuilder:append	(Ljava/lang/String;)Ljava/lang/StringBuilder;
/*     */     //   390: ldc 106
/*     */     //   392: invokevirtual 60	java/lang/StringBuilder:append	(Ljava/lang/String;)Ljava/lang/StringBuilder;
/*     */     //   395: invokevirtual 69	java/lang/StringBuilder:toString	()Ljava/lang/String;
/*     */     //   398: invokespecial 108	com/claro/exception/CAException:<init>	(ILjava/lang/String;)V
/*     */     //   401: athrow
/*     */     //   402: aload_0
/*     */     //   403: aload_2
/*     */     //   404: aload 10
/*     */     //   406: invokevirtual 199	com/claro/transfer/TelefonoTO:getPuntosTO	()Lcom/claro/transfer/PuntosTO;
/*     */     //   409: invokevirtual 136	com/claro/transfer/PuntosTO:getPtsExcedentes	()I
/*     */     //   412: aload_1
/*     */     //   413: invokevirtual 111	com/claro/transfer/transpuntos/TransferenciaTO:getPuntosTrasnferidos	()I
/*     */     //   416: aload 10
/*     */     //   418: invokevirtual 203	com/claro/transfer/TelefonoTO:getCuenta	()Ljava/lang/String;
/*     */     //   421: aload 10
/*     */     //   423: invokevirtual 206	com/claro/transfer/TelefonoTO:getSecuencia	()Ljava/lang/String;
/*     */     //   426: invokespecial 207	com/claro/dao/TransferenciaAnexoDAO:transferir	(Ljava/sql/Connection;IILjava/lang/String;Ljava/lang/String;)Z
/*     */     //   429: ifne +42 -> 471
/*     */     //   432: aload_2
/*     */     //   433: invokeinterface 194 1 0
/*     */     //   438: new 17	com/claro/exception/CAException
/*     */     //   441: dup
/*     */     //   442: iconst_m1
/*     */     //   443: new 38	java/lang/StringBuilder
/*     */     //   446: dup
/*     */     //   447: ldc -45
/*     */     //   449: invokespecial 42	java/lang/StringBuilder:<init>	(Ljava/lang/String;)V
/*     */     //   452: aload_1
/*     */     //   453: invokevirtual 103	com/claro/transfer/transpuntos/TransferenciaTO:getTelefonoOrigen	()Ljava/lang/String;
/*     */     //   456: invokevirtual 60	java/lang/StringBuilder:append	(Ljava/lang/String;)Ljava/lang/StringBuilder;
/*     */     //   459: ldc 106
/*     */     //   461: invokevirtual 60	java/lang/StringBuilder:append	(Ljava/lang/String;)Ljava/lang/StringBuilder;
/*     */     //   464: invokevirtual 69	java/lang/StringBuilder:toString	()Ljava/lang/String;
/*     */     //   467: invokespecial 108	com/claro/exception/CAException:<init>	(ILjava/lang/String;)V
/*     */     //   470: athrow
/*     */     //   471: aload 10
/*     */     //   473: invokevirtual 199	com/claro/transfer/TelefonoTO:getPuntosTO	()Lcom/claro/transfer/PuntosTO;
/*     */     //   476: aload 10
/*     */     //   478: invokevirtual 199	com/claro/transfer/TelefonoTO:getPuntosTO	()Lcom/claro/transfer/PuntosTO;
/*     */     //   481: invokevirtual 136	com/claro/transfer/PuntosTO:getPtsExcedentes	()I
/*     */     //   484: aload_1
/*     */     //   485: invokevirtual 111	com/claro/transfer/transpuntos/TransferenciaTO:getPuntosTrasnferidos	()I
/*     */     //   488: iadd
/*     */     //   489: invokevirtual 213	com/claro/transfer/PuntosTO:setPtsExcedentes	(I)V
/*     */     //   492: aload_0
/*     */     //   493: aload_2
/*     */     //   494: aload_1
/*     */     //   495: iconst_1
/*     */     //   496: iconst_0
/*     */     //   497: invokevirtual 216	com/claro/dao/TransferenciaAnexoDAO:guardarDetalleLinea	(Ljava/sql/Connection;Lcom/claro/transfer/transpuntos/TransferenciaTO;IZ)Z
/*     */     //   500: ifne +42 -> 542
/*     */     //   503: aload_2
/*     */     //   504: invokeinterface 194 1 0
/*     */     //   509: new 17	com/claro/exception/CAException
/*     */     //   512: dup
/*     */     //   513: iconst_m1
/*     */     //   514: new 38	java/lang/StringBuilder
/*     */     //   517: dup
/*     */     //   518: ldc -36
/*     */     //   520: invokespecial 42	java/lang/StringBuilder:<init>	(Ljava/lang/String;)V
/*     */     //   523: aload_1
/*     */     //   524: invokevirtual 103	com/claro/transfer/transpuntos/TransferenciaTO:getTelefonoOrigen	()Ljava/lang/String;
/*     */     //   527: invokevirtual 60	java/lang/StringBuilder:append	(Ljava/lang/String;)Ljava/lang/StringBuilder;
/*     */     //   530: ldc 106
/*     */     //   532: invokevirtual 60	java/lang/StringBuilder:append	(Ljava/lang/String;)Ljava/lang/StringBuilder;
/*     */     //   535: invokevirtual 69	java/lang/StringBuilder:toString	()Ljava/lang/String;
/*     */     //   538: invokespecial 108	com/claro/exception/CAException:<init>	(ILjava/lang/String;)V
/*     */     //   541: athrow
/*     */     //   542: aload_0
/*     */     //   543: aload_1
/*     */     //   544: invokevirtual 111	com/claro/transfer/transpuntos/TransferenciaTO:getPuntosTrasnferidos	()I
/*     */     //   547: ldc -34
/*     */     //   549: aload_1
/*     */     //   550: invokevirtual 224	com/claro/transfer/transpuntos/TransferenciaTO:getCuentaDestino	()Ljava/lang/String;
/*     */     //   553: aload_1
/*     */     //   554: invokevirtual 227	com/claro/transfer/transpuntos/TransferenciaTO:getIdUsuario	()Ljava/lang/String;
/*     */     //   557: aload_1
/*     */     //   558: invokevirtual 230	com/claro/transfer/transpuntos/TransferenciaTO:getComentario	()Ljava/lang/String;
/*     */     //   561: iconst_1
/*     */     //   562: iconst_0
/*     */     //   563: invokevirtual 233	com/claro/dao/TransferenciaAnexoDAO:crearComentario	(ILjava/lang/String;Ljava/lang/String;Ljava/lang/String;Ljava/lang/String;IZ)Ljava/lang/String;
/*     */     //   566: astore 11
/*     */     //   568: aload 5
/*     */     //   570: aload_2
/*     */     //   571: aload_1
/*     */     //   572: invokevirtual 237	com/claro/transfer/transpuntos/TransferenciaTO:getRegionOrigen	()I
/*     */     //   575: aload_1
/*     */     //   576: invokevirtual 240	com/claro/transfer/transpuntos/TransferenciaTO:getCuentaLineaOrigen	()Ljava/lang/String;
/*     */     //   579: aload_1
/*     */     //   580: invokevirtual 227	com/claro/transfer/transpuntos/TransferenciaTO:getIdUsuario	()Ljava/lang/String;
/*     */     //   583: invokestatic 28	java/lang/System:currentTimeMillis	()J
/*     */     //   586: aload 11
/*     */     //   588: invokevirtual 243	com/claro/dao/PuntosDAO:insertaComentarioTMP	(Ljava/sql/Connection;ILjava/lang/String;Ljava/lang/String;JLjava/lang/String;)Lcom/claro/transfer/MensajeTO;
/*     */     //   591: astore 4
/*     */     //   593: aload 4
/*     */     //   595: invokevirtual 247	com/claro/transfer/MensajeTO:getIdMensaje	()I
/*     */     //   598: ifeq +20 -> 618
/*     */     //   601: aload_2
/*     */     //   602: invokeinterface 194 1 0
/*     */     //   607: new 17	com/claro/exception/CAException
/*     */     //   610: dup
/*     */     //   611: iconst_m1
/*     */     //   612: ldc -8
/*     */     //   614: invokespecial 108	com/claro/exception/CAException:<init>	(ILjava/lang/String;)V
/*     */     //   617: athrow
/*     */     //   618: aload_0
/*     */     //   619: aload_2
/*     */     //   620: aload_1
/*     */     //   621: iconst_2
/*     */     //   622: iconst_0
/*     */     //   623: invokevirtual 216	com/claro/dao/TransferenciaAnexoDAO:guardarDetalleLinea	(Ljava/sql/Connection;Lcom/claro/transfer/transpuntos/TransferenciaTO;IZ)Z
/*     */     //   626: ifne +42 -> 668
/*     */     //   629: aload_2
/*     */     //   630: invokeinterface 194 1 0
/*     */     //   635: new 17	com/claro/exception/CAException
/*     */     //   638: dup
/*     */     //   639: iconst_m1
/*     */     //   640: new 38	java/lang/StringBuilder
/*     */     //   643: dup
/*     */     //   644: ldc -6
/*     */     //   646: invokespecial 42	java/lang/StringBuilder:<init>	(Ljava/lang/String;)V
/*     */     //   649: aload_1
/*     */     //   650: invokevirtual 252	com/claro/transfer/transpuntos/TransferenciaTO:getTelefonoDestino	()Ljava/lang/String;
/*     */     //   653: invokevirtual 60	java/lang/StringBuilder:append	(Ljava/lang/String;)Ljava/lang/StringBuilder;
/*     */     //   656: ldc 106
/*     */     //   658: invokevirtual 60	java/lang/StringBuilder:append	(Ljava/lang/String;)Ljava/lang/StringBuilder;
/*     */     //   661: invokevirtual 69	java/lang/StringBuilder:toString	()Ljava/lang/String;
/*     */     //   664: invokespecial 108	com/claro/exception/CAException:<init>	(ILjava/lang/String;)V
/*     */     //   667: athrow
/*     */     //   668: aload_0
/*     */     //   669: aload_1
/*     */     //   670: invokevirtual 111	com/claro/transfer/transpuntos/TransferenciaTO:getPuntosTrasnferidos	()I
/*     */     //   673: aload_1
/*     */     //   674: invokevirtual 83	com/claro/transfer/transpuntos/TransferenciaTO:getCuentaOrigen	()Ljava/lang/String;
/*     */     //   677: ldc -34
/*     */     //   679: aload_1
/*     */     //   680: invokevirtual 227	com/claro/transfer/transpuntos/TransferenciaTO:getIdUsuario	()Ljava/lang/String;
/*     */     //   683: aload_1
/*     */     //   684: invokevirtual 230	com/claro/transfer/transpuntos/TransferenciaTO:getComentario	()Ljava/lang/String;
/*     */     //   687: iconst_2
/*     */     //   688: iconst_0
/*     */     //   689: invokevirtual 233	com/claro/dao/TransferenciaAnexoDAO:crearComentario	(ILjava/lang/String;Ljava/lang/String;Ljava/lang/String;Ljava/lang/String;IZ)Ljava/lang/String;
/*     */     //   692: astore 12
/*     */     //   694: aload 5
/*     */     //   696: aload_2
/*     */     //   697: aload 10
/*     */     //   699: invokevirtual 255	com/claro/transfer/TelefonoTO:getRegion	()I
/*     */     //   702: aload 10
/*     */     //   704: invokevirtual 203	com/claro/transfer/TelefonoTO:getCuenta	()Ljava/lang/String;
/*     */     //   707: aload_1
/*     */     //   708: invokevirtual 227	com/claro/transfer/transpuntos/TransferenciaTO:getIdUsuario	()Ljava/lang/String;
/*     */     //   711: invokestatic 28	java/lang/System:currentTimeMillis	()J
/*     */     //   714: aload 12
/*     */     //   716: invokevirtual 243	com/claro/dao/PuntosDAO:insertaComentarioTMP	(Ljava/sql/Connection;ILjava/lang/String;Ljava/lang/String;JLjava/lang/String;)Lcom/claro/transfer/MensajeTO;
/*     */     //   719: astore 4
/*     */     //   721: aload 4
/*     */     //   723: invokevirtual 247	com/claro/transfer/MensajeTO:getIdMensaje	()I
/*     */     //   726: ifeq +21 -> 747
/*     */     //   729: aload_2
/*     */     //   730: invokeinterface 194 1 0
/*     */     //   735: new 17	com/claro/exception/CAException
/*     */     //   738: dup
/*     */     //   739: iconst_m1
/*     */     //   740: ldc_w 258
/*     */     //   743: invokespecial 108	com/claro/exception/CAException:<init>	(ILjava/lang/String;)V
/*     */     //   746: athrow
/*     */     //   747: aload_1
/*     */     //   748: aload_3
/*     */     //   749: invokevirtual 260	com/claro/transfer/transpuntos/TransferenciaTO:setPuntosOrigenTO	(Lcom/claro/transfer/PuntosTO;)V
/*     */     //   752: aload_1
/*     */     //   753: aload 10
/*     */     //   755: invokevirtual 264	com/claro/transfer/transpuntos/TransferenciaTO:setTelefonoTO	(Lcom/claro/transfer/TelefonoTO;)V
/*     */     //   758: aload_2
/*     */     //   759: invokeinterface 268 1 0
/*     */     //   764: aload_0
/*     */     //   765: getfield 34	com/claro/dao/TransferenciaAnexoDAO:logger	Lorg/apache/log4j/Logger;
/*     */     //   768: new 38	java/lang/StringBuilder
/*     */     //   771: dup
/*     */     //   772: ldc_w 271
/*     */     //   775: invokespecial 42	java/lang/StringBuilder:<init>	(Ljava/lang/String;)V
/*     */     //   778: getstatic 45	com/claro/util/Constantes:DATEFORMTALog	Ljava/text/SimpleDateFormat;
/*     */     //   781: new 51	java/util/Date
/*     */     //   784: dup
/*     */     //   785: invokespecial 53	java/util/Date:<init>	()V
/*     */     //   788: invokevirtual 54	java/text/SimpleDateFormat:format	(Ljava/util/Date;)Ljava/lang/String;
/*     */     //   791: invokevirtual 60	java/lang/StringBuilder:append	(Ljava/lang/String;)Ljava/lang/StringBuilder;
/*     */     //   794: ldc 64
/*     */     //   796: invokevirtual 60	java/lang/StringBuilder:append	(Ljava/lang/String;)Ljava/lang/StringBuilder;
/*     */     //   799: invokestatic 28	java/lang/System:currentTimeMillis	()J
/*     */     //   802: lload 8
/*     */     //   804: lsub
/*     */     //   805: invokevirtual 66	java/lang/StringBuilder:append	(J)Ljava/lang/StringBuilder;
/*     */     //   808: invokevirtual 69	java/lang/StringBuilder:toString	()Ljava/lang/String;
/*     */     //   811: invokevirtual 73	org/apache/log4j/Logger:info	(Ljava/lang/Object;)V
/*     */     //   814: goto +174 -> 988
/*     */     //   817: astore 8
/*     */     //   819: aload_2
/*     */     //   820: ifnull +14 -> 834
/*     */     //   823: aload_2
/*     */     //   824: invokeinterface 194 1 0
/*     */     //   829: goto +5 -> 834
/*     */     //   832: astore 9
/*     */     //   834: aload 8
/*     */     //   836: invokevirtual 273	java/sql/SQLException:printStackTrace	()V
/*     */     //   839: aload_0
/*     */     //   840: getfield 278	com/claro/dao/TransferenciaAnexoDAO:error	Lorg/apache/log4j/Logger;
/*     */     //   843: ldc_w 281
/*     */     //   846: aload 8
/*     */     //   848: invokevirtual 283	org/apache/log4j/Logger:info	(Ljava/lang/Object;Ljava/lang/Throwable;)V
/*     */     //   851: new 17	com/claro/exception/CAException
/*     */     //   854: dup
/*     */     //   855: iconst_m1
/*     */     //   856: new 38	java/lang/StringBuilder
/*     */     //   859: dup
/*     */     //   860: ldc_w 286
/*     */     //   863: invokespecial 42	java/lang/StringBuilder:<init>	(Ljava/lang/String;)V
/*     */     //   866: aload 8
/*     */     //   868: invokevirtual 288	java/sql/SQLException:toString	()Ljava/lang/String;
/*     */     //   871: invokevirtual 60	java/lang/StringBuilder:append	(Ljava/lang/String;)Ljava/lang/StringBuilder;
/*     */     //   874: ldc 106
/*     */     //   876: invokevirtual 60	java/lang/StringBuilder:append	(Ljava/lang/String;)Ljava/lang/StringBuilder;
/*     */     //   879: invokevirtual 69	java/lang/StringBuilder:toString	()Ljava/lang/String;
/*     */     //   882: aload 8
/*     */     //   884: invokespecial 289	com/claro/exception/CAException:<init>	(ILjava/lang/String;Ljava/lang/Exception;)V
/*     */     //   887: athrow
/*     */     //   888: astore 8
/*     */     //   890: aload_2
/*     */     //   891: ifnull +14 -> 905
/*     */     //   894: aload_2
/*     */     //   895: invokeinterface 194 1 0
/*     */     //   900: goto +5 -> 905
/*     */     //   903: astore 9
/*     */     //   905: aload 8
/*     */     //   907: invokevirtual 292	java/lang/Exception:printStackTrace	()V
/*     */     //   910: aload_0
/*     */     //   911: getfield 278	com/claro/dao/TransferenciaAnexoDAO:error	Lorg/apache/log4j/Logger;
/*     */     //   914: ldc_w 281
/*     */     //   917: aload 8
/*     */     //   919: invokevirtual 283	org/apache/log4j/Logger:info	(Ljava/lang/Object;Ljava/lang/Throwable;)V
/*     */     //   922: new 17	com/claro/exception/CAException
/*     */     //   925: dup
/*     */     //   926: iconst_m1
/*     */     //   927: new 38	java/lang/StringBuilder
/*     */     //   930: dup
/*     */     //   931: ldc_w 286
/*     */     //   934: invokespecial 42	java/lang/StringBuilder:<init>	(Ljava/lang/String;)V
/*     */     //   937: aload 8
/*     */     //   939: invokevirtual 295	java/lang/Exception:toString	()Ljava/lang/String;
/*     */     //   942: invokevirtual 60	java/lang/StringBuilder:append	(Ljava/lang/String;)Ljava/lang/StringBuilder;
/*     */     //   945: ldc 106
/*     */     //   947: invokevirtual 60	java/lang/StringBuilder:append	(Ljava/lang/String;)Ljava/lang/StringBuilder;
/*     */     //   950: invokevirtual 69	java/lang/StringBuilder:toString	()Ljava/lang/String;
/*     */     //   953: aload 8
/*     */     //   955: invokespecial 289	com/claro/exception/CAException:<init>	(ILjava/lang/String;Ljava/lang/Exception;)V
/*     */     //   958: athrow
/*     */     //   959: astore 13
/*     */     //   961: aload_2
/*     */     //   962: ifnull +23 -> 985
/*     */     //   965: aload_2
/*     */     //   966: iconst_1
/*     */     //   967: invokeinterface 184 2 0
/*     */     //   972: aload_2
/*     */     //   973: invokeinterface 296 1 0
/*     */     //   978: aconst_null
/*     */     //   979: astore_2
/*     */     //   980: goto +5 -> 985
/*     */     //   983: astore 14
/*     */     //   985: aload 13
/*     */     //   987: athrow
/*     */     //   988: aload_2
/*     */     //   989: ifnull +23 -> 1012
/*     */     //   992: aload_2
/*     */     //   993: iconst_1
/*     */     //   994: invokeinterface 184 2 0
/*     */     //   999: aload_2
/*     */     //   1000: invokeinterface 296 1 0
/*     */     //   1005: aconst_null
/*     */     //   1006: astore_2
/*     */     //   1007: goto +5 -> 1012
/*     */     //   1010: astore 14
/*     */     //   1012: aload_1
/*     */     //   1013: areturn
/*     */     // Line number table:
/*     */     //   Java source line #34	-> byte code offset #0
/*     */     //   Java source line #35	-> byte code offset #2
/*     */     //   Java source line #36	-> byte code offset #10
/*     */     //   Java source line #37	-> byte code offset #19
/*     */     //   Java source line #38	-> byte code offset #28
/*     */     //   Java source line #39	-> byte code offset #34
/*     */     //   Java source line #43	-> byte code offset #37
/*     */     //   Java source line #44	-> byte code offset #42
/*     */     //   Java source line #47	-> byte code offset #87
/*     */     //   Java source line #46	-> byte code offset #102
/*     */     //   Java source line #49	-> byte code offset #103
/*     */     //   Java source line #50	-> byte code offset #110
/*     */     //   Java source line #51	-> byte code offset #115
/*     */     //   Java source line #52	-> byte code offset #124
/*     */     //   Java source line #51	-> byte code offset #136
/*     */     //   Java source line #50	-> byte code offset #139
/*     */     //   Java source line #54	-> byte code offset #143
/*     */     //   Java source line #56	-> byte code offset #149
/*     */     //   Java source line #58	-> byte code offset #157
/*     */     //   Java source line #59	-> byte code offset #165
/*     */     //   Java source line #60	-> byte code offset #173
/*     */     //   Java source line #61	-> byte code offset #181
/*     */     //   Java source line #62	-> byte code offset #189
/*     */     //   Java source line #63	-> byte code offset #197
/*     */     //   Java source line #64	-> byte code offset #205
/*     */     //   Java source line #66	-> byte code offset #214
/*     */     //   Java source line #67	-> byte code offset #220
/*     */     //   Java source line #68	-> byte code offset #228
/*     */     //   Java source line #70	-> byte code offset #238
/*     */     //   Java source line #71	-> byte code offset #248
/*     */     //   Java source line #74	-> byte code offset #257
/*     */     //   Java source line #75	-> byte code offset #270
/*     */     //   Java source line #76	-> byte code offset #273
/*     */     //   Java source line #66	-> byte code offset #276
/*     */     //   Java source line #81	-> byte code offset #286
/*     */     //   Java source line #84	-> byte code offset #291
/*     */     //   Java source line #88	-> byte code offset #300
/*     */     //   Java source line #91	-> byte code offset #307
/*     */     //   Java source line #92	-> byte code offset #314
/*     */     //   Java source line #94	-> byte code offset #329
/*     */     //   Java source line #95	-> byte code offset #339
/*     */     //   Java source line #98	-> byte code offset #346
/*     */     //   Java source line #99	-> byte code offset #349
/*     */     //   Java source line #98	-> byte code offset #357
/*     */     //   Java source line #100	-> byte code offset #363
/*     */     //   Java source line #101	-> byte code offset #369
/*     */     //   Java source line #102	-> byte code offset #383
/*     */     //   Java source line #101	-> byte code offset #398
/*     */     //   Java source line #107	-> byte code offset #402
/*     */     //   Java source line #108	-> byte code offset #412
/*     */     //   Java source line #107	-> byte code offset #426
/*     */     //   Java source line #109	-> byte code offset #432
/*     */     //   Java source line #110	-> byte code offset #438
/*     */     //   Java source line #111	-> byte code offset #452
/*     */     //   Java source line #110	-> byte code offset #467
/*     */     //   Java source line #115	-> byte code offset #471
/*     */     //   Java source line #116	-> byte code offset #476
/*     */     //   Java source line #115	-> byte code offset #489
/*     */     //   Java source line #120	-> byte code offset #492
/*     */     //   Java source line #121	-> byte code offset #503
/*     */     //   Java source line #122	-> byte code offset #509
/*     */     //   Java source line #123	-> byte code offset #514
/*     */     //   Java source line #122	-> byte code offset #538
/*     */     //   Java source line #127	-> byte code offset #542
/*     */     //   Java source line #128	-> byte code offset #549
/*     */     //   Java source line #127	-> byte code offset #563
/*     */     //   Java source line #130	-> byte code offset #568
/*     */     //   Java source line #131	-> byte code offset #579
/*     */     //   Java source line #130	-> byte code offset #588
/*     */     //   Java source line #133	-> byte code offset #593
/*     */     //   Java source line #134	-> byte code offset #601
/*     */     //   Java source line #135	-> byte code offset #607
/*     */     //   Java source line #140	-> byte code offset #618
/*     */     //   Java source line #141	-> byte code offset #629
/*     */     //   Java source line #142	-> byte code offset #635
/*     */     //   Java source line #143	-> byte code offset #640
/*     */     //   Java source line #144	-> byte code offset #649
/*     */     //   Java source line #143	-> byte code offset #661
/*     */     //   Java source line #142	-> byte code offset #664
/*     */     //   Java source line #148	-> byte code offset #668
/*     */     //   Java source line #149	-> byte code offset #673
/*     */     //   Java source line #148	-> byte code offset #689
/*     */     //   Java source line #151	-> byte code offset #694
/*     */     //   Java source line #152	-> byte code offset #707
/*     */     //   Java source line #151	-> byte code offset #716
/*     */     //   Java source line #154	-> byte code offset #721
/*     */     //   Java source line #155	-> byte code offset #729
/*     */     //   Java source line #156	-> byte code offset #735
/*     */     //   Java source line #160	-> byte code offset #747
/*     */     //   Java source line #163	-> byte code offset #752
/*     */     //   Java source line #165	-> byte code offset #758
/*     */     //   Java source line #167	-> byte code offset #764
/*     */     //   Java source line #169	-> byte code offset #817
/*     */     //   Java source line #170	-> byte code offset #819
/*     */     //   Java source line #171	-> byte code offset #834
/*     */     //   Java source line #172	-> byte code offset #839
/*     */     //   Java source line #173	-> byte code offset #851
/*     */     //   Java source line #174	-> byte code offset #856
/*     */     //   Java source line #173	-> byte code offset #884
/*     */     //   Java source line #175	-> byte code offset #888
/*     */     //   Java source line #176	-> byte code offset #890
/*     */     //   Java source line #177	-> byte code offset #905
/*     */     //   Java source line #178	-> byte code offset #910
/*     */     //   Java source line #179	-> byte code offset #922
/*     */     //   Java source line #180	-> byte code offset #927
/*     */     //   Java source line #179	-> byte code offset #955
/*     */     //   Java source line #181	-> byte code offset #959
/*     */     //   Java source line #182	-> byte code offset #961
/*     */     //   Java source line #184	-> byte code offset #965
/*     */     //   Java source line #185	-> byte code offset #972
/*     */     //   Java source line #186	-> byte code offset #978
/*     */     //   Java source line #187	-> byte code offset #983
/*     */     //   Java source line #189	-> byte code offset #985
/*     */     //   Java source line #182	-> byte code offset #988
/*     */     //   Java source line #184	-> byte code offset #992
/*     */     //   Java source line #185	-> byte code offset #999
/*     */     //   Java source line #186	-> byte code offset #1005
/*     */     //   Java source line #187	-> byte code offset #1010
/*     */     //   Java source line #191	-> byte code offset #1012
/*     */     // Local variable table:
/*     */     //   start	length	slot	name	signature
/*     */     //   0	1014	0	this	TransferenciaAnexoDAO
/*     */     //   0	1014	1	_transfTO	TransferenciaTO
/*     */     //   1	1006	2	cnx	Connection
/*     */     //   9	740	3	puntosOrigenTO	PuntosTO
/*     */     //   17	705	4	msgTO	com.claro.transfer.MensajeTO
/*     */     //   26	669	5	ptsDAO	PuntosDAO
/*     */     //   32	270	6	arrTiposPuntos	int[]
/*     */     //   35	264	7	puntosTrasnferidos	int
/*     */     //   40	763	8	inicioProceso	long
/*     */     //   817	66	8	se	SQLException
/*     */     //   888	66	8	e	Exception
/*     */     //   832	1	9	localException1	Exception
/*     */     //   903	1	9	localException2	Exception
/*     */     //   215	65	10	i	int
/*     */     //   312	442	10	phoneDestinoTO	TelefonoTO
/*     */     //   566	21	11	comntOrigen	String
/*     */     //   692	23	12	comntDestino	String
/*     */     //   959	27	13	localObject	Object
/*     */     //   983	1	14	localException3	Exception
/*     */     //   1010	1	14	localException4	Exception
/*     */     // Exception table:
/*     */     //   from	to	target	type
/*     */     //   37	814	817	java/sql/SQLException
/*     */     //   823	829	832	java/lang/Exception
/*     */     //   37	814	888	java/lang/Exception
/*     */     //   894	900	903	java/lang/Exception
/*     */     //   37	959	959	finally
/*     */     //   965	980	983	java/lang/Exception
/*     */     //   992	1007	1010	java/lang/Exception
/*     */   }
/*     */   
/*     */   /* Error */
/*     */   private boolean validaPlan(Connection _cnx, String _idPlan, int _region)
/*     */     throws CAException
/*     */   {
/*     */     // Byte code:
/*     */     //   0: aconst_null
/*     */     //   1: astore 4
/*     */     //   3: aconst_null
/*     */     //   4: astore 5
/*     */     //   6: iconst_0
/*     */     //   7: istore 6
/*     */     //   9: aload_1
/*     */     //   10: new 38	java/lang/StringBuilder
/*     */     //   13: dup
/*     */     //   14: ldc_w 332
/*     */     //   17: invokespecial 42	java/lang/StringBuilder:<init>	(Ljava/lang/String;)V
/*     */     //   20: aload_0
/*     */     //   21: getfield 334	com/claro/dao/TransferenciaAnexoDAO:schema_database	Ljava/lang/String;
/*     */     //   24: invokevirtual 60	java/lang/StringBuilder:append	(Ljava/lang/String;)Ljava/lang/StringBuilder;
/*     */     //   27: ldc_w 337
/*     */     //   30: invokevirtual 60	java/lang/StringBuilder:append	(Ljava/lang/String;)Ljava/lang/StringBuilder;
/*     */     //   33: ldc_w 339
/*     */     //   36: invokevirtual 60	java/lang/StringBuilder:append	(Ljava/lang/String;)Ljava/lang/StringBuilder;
/*     */     //   39: aload_0
/*     */     //   40: getfield 334	com/claro/dao/TransferenciaAnexoDAO:schema_database	Ljava/lang/String;
/*     */     //   43: invokevirtual 60	java/lang/StringBuilder:append	(Ljava/lang/String;)Ljava/lang/StringBuilder;
/*     */     //   46: ldc_w 341
/*     */     //   49: invokevirtual 60	java/lang/StringBuilder:append	(Ljava/lang/String;)Ljava/lang/StringBuilder;
/*     */     //   52: ldc_w 343
/*     */     //   55: invokevirtual 60	java/lang/StringBuilder:append	(Ljava/lang/String;)Ljava/lang/StringBuilder;
/*     */     //   58: ldc_w 345
/*     */     //   61: invokevirtual 60	java/lang/StringBuilder:append	(Ljava/lang/String;)Ljava/lang/StringBuilder;
/*     */     //   64: ldc_w 347
/*     */     //   67: invokevirtual 60	java/lang/StringBuilder:append	(Ljava/lang/String;)Ljava/lang/StringBuilder;
/*     */     //   70: invokevirtual 69	java/lang/StringBuilder:toString	()Ljava/lang/String;
/*     */     //   73: invokeinterface 349 2 0
/*     */     //   78: astore 4
/*     */     //   80: aload 4
/*     */     //   82: iconst_1
/*     */     //   83: aload_2
/*     */     //   84: invokeinterface 353 3 0
/*     */     //   89: aload 4
/*     */     //   91: iconst_2
/*     */     //   92: iload_3
/*     */     //   93: invokeinterface 358 3 0
/*     */     //   98: aload 4
/*     */     //   100: invokeinterface 362 1 0
/*     */     //   105: astore 5
/*     */     //   107: aload 5
/*     */     //   109: invokeinterface 366 1 0
/*     */     //   114: ifeq +166 -> 280
/*     */     //   117: iconst_1
/*     */     //   118: istore 6
/*     */     //   120: goto +160 -> 280
/*     */     //   123: astore 7
/*     */     //   125: aload 7
/*     */     //   127: invokevirtual 273	java/sql/SQLException:printStackTrace	()V
/*     */     //   130: aload_0
/*     */     //   131: getfield 278	com/claro/dao/TransferenciaAnexoDAO:error	Lorg/apache/log4j/Logger;
/*     */     //   134: ldc_w 372
/*     */     //   137: aload 7
/*     */     //   139: invokevirtual 283	org/apache/log4j/Logger:info	(Ljava/lang/Object;Ljava/lang/Throwable;)V
/*     */     //   142: new 17	com/claro/exception/CAException
/*     */     //   145: dup
/*     */     //   146: iconst_m1
/*     */     //   147: new 38	java/lang/StringBuilder
/*     */     //   150: dup
/*     */     //   151: ldc_w 374
/*     */     //   154: invokespecial 42	java/lang/StringBuilder:<init>	(Ljava/lang/String;)V
/*     */     //   157: aload 7
/*     */     //   159: invokevirtual 288	java/sql/SQLException:toString	()Ljava/lang/String;
/*     */     //   162: invokevirtual 60	java/lang/StringBuilder:append	(Ljava/lang/String;)Ljava/lang/StringBuilder;
/*     */     //   165: ldc 106
/*     */     //   167: invokevirtual 60	java/lang/StringBuilder:append	(Ljava/lang/String;)Ljava/lang/StringBuilder;
/*     */     //   170: invokevirtual 69	java/lang/StringBuilder:toString	()Ljava/lang/String;
/*     */     //   173: aload 7
/*     */     //   175: invokespecial 289	com/claro/exception/CAException:<init>	(ILjava/lang/String;Ljava/lang/Exception;)V
/*     */     //   178: athrow
/*     */     //   179: astore 7
/*     */     //   181: aload 7
/*     */     //   183: invokevirtual 292	java/lang/Exception:printStackTrace	()V
/*     */     //   186: aload_0
/*     */     //   187: getfield 278	com/claro/dao/TransferenciaAnexoDAO:error	Lorg/apache/log4j/Logger;
/*     */     //   190: ldc_w 372
/*     */     //   193: aload 7
/*     */     //   195: invokevirtual 283	org/apache/log4j/Logger:info	(Ljava/lang/Object;Ljava/lang/Throwable;)V
/*     */     //   198: new 17	com/claro/exception/CAException
/*     */     //   201: dup
/*     */     //   202: iconst_m1
/*     */     //   203: new 38	java/lang/StringBuilder
/*     */     //   206: dup
/*     */     //   207: ldc_w 374
/*     */     //   210: invokespecial 42	java/lang/StringBuilder:<init>	(Ljava/lang/String;)V
/*     */     //   213: aload 7
/*     */     //   215: invokevirtual 295	java/lang/Exception:toString	()Ljava/lang/String;
/*     */     //   218: invokevirtual 60	java/lang/StringBuilder:append	(Ljava/lang/String;)Ljava/lang/StringBuilder;
/*     */     //   221: ldc 106
/*     */     //   223: invokevirtual 60	java/lang/StringBuilder:append	(Ljava/lang/String;)Ljava/lang/StringBuilder;
/*     */     //   226: invokevirtual 69	java/lang/StringBuilder:toString	()Ljava/lang/String;
/*     */     //   229: aload 7
/*     */     //   231: invokespecial 289	com/claro/exception/CAException:<init>	(ILjava/lang/String;Ljava/lang/Exception;)V
/*     */     //   234: athrow
/*     */     //   235: astore 8
/*     */     //   237: aload 5
/*     */     //   239: ifnull +18 -> 257
/*     */     //   242: aload 5
/*     */     //   244: invokeinterface 376 1 0
/*     */     //   249: aconst_null
/*     */     //   250: astore 5
/*     */     //   252: goto +5 -> 257
/*     */     //   255: astore 9
/*     */     //   257: aload 4
/*     */     //   259: ifnull +18 -> 277
/*     */     //   262: aload 4
/*     */     //   264: invokeinterface 377 1 0
/*     */     //   269: aconst_null
/*     */     //   270: astore 4
/*     */     //   272: goto +5 -> 277
/*     */     //   275: astore 9
/*     */     //   277: aload 8
/*     */     //   279: athrow
/*     */     //   280: aload 5
/*     */     //   282: ifnull +18 -> 300
/*     */     //   285: aload 5
/*     */     //   287: invokeinterface 376 1 0
/*     */     //   292: aconst_null
/*     */     //   293: astore 5
/*     */     //   295: goto +5 -> 300
/*     */     //   298: astore 9
/*     */     //   300: aload 4
/*     */     //   302: ifnull +18 -> 320
/*     */     //   305: aload 4
/*     */     //   307: invokeinterface 377 1 0
/*     */     //   312: aconst_null
/*     */     //   313: astore 4
/*     */     //   315: goto +5 -> 320
/*     */     //   318: astore 9
/*     */     //   320: iload 6
/*     */     //   322: ireturn
/*     */     // Line number table:
/*     */     //   Java source line #203	-> byte code offset #0
/*     */     //   Java source line #204	-> byte code offset #3
/*     */     //   Java source line #205	-> byte code offset #6
/*     */     //   Java source line #208	-> byte code offset #9
/*     */     //   Java source line #209	-> byte code offset #10
/*     */     //   Java source line #210	-> byte code offset #20
/*     */     //   Java source line #211	-> byte code offset #33
/*     */     //   Java source line #212	-> byte code offset #52
/*     */     //   Java source line #213	-> byte code offset #58
/*     */     //   Java source line #214	-> byte code offset #64
/*     */     //   Java source line #209	-> byte code offset #70
/*     */     //   Java source line #208	-> byte code offset #73
/*     */     //   Java source line #216	-> byte code offset #80
/*     */     //   Java source line #217	-> byte code offset #89
/*     */     //   Java source line #219	-> byte code offset #98
/*     */     //   Java source line #221	-> byte code offset #107
/*     */     //   Java source line #222	-> byte code offset #117
/*     */     //   Java source line #225	-> byte code offset #123
/*     */     //   Java source line #226	-> byte code offset #125
/*     */     //   Java source line #227	-> byte code offset #130
/*     */     //   Java source line #228	-> byte code offset #142
/*     */     //   Java source line #229	-> byte code offset #147
/*     */     //   Java source line #228	-> byte code offset #175
/*     */     //   Java source line #230	-> byte code offset #179
/*     */     //   Java source line #231	-> byte code offset #181
/*     */     //   Java source line #232	-> byte code offset #186
/*     */     //   Java source line #233	-> byte code offset #198
/*     */     //   Java source line #234	-> byte code offset #203
/*     */     //   Java source line #233	-> byte code offset #231
/*     */     //   Java source line #235	-> byte code offset #235
/*     */     //   Java source line #236	-> byte code offset #237
/*     */     //   Java source line #237	-> byte code offset #257
/*     */     //   Java source line #238	-> byte code offset #277
/*     */     //   Java source line #236	-> byte code offset #280
/*     */     //   Java source line #237	-> byte code offset #300
/*     */     //   Java source line #240	-> byte code offset #320
/*     */     // Local variable table:
/*     */     //   start	length	slot	name	signature
/*     */     //   0	323	0	this	TransferenciaAnexoDAO
/*     */     //   0	323	1	_cnx	Connection
/*     */     //   0	323	2	_idPlan	String
/*     */     //   0	323	3	_region	int
/*     */     //   1	313	4	ps	java.sql.PreparedStatement
/*     */     //   4	290	5	rs	java.sql.ResultSet
/*     */     //   7	314	6	existe	boolean
/*     */     //   123	51	7	se	SQLException
/*     */     //   179	51	7	e	Exception
/*     */     //   235	43	8	localObject	Object
/*     */     //   255	1	9	localException1	Exception
/*     */     //   275	1	9	localException2	Exception
/*     */     //   298	1	9	localException3	Exception
/*     */     //   318	1	9	localException4	Exception
/*     */     // Exception table:
/*     */     //   from	to	target	type
/*     */     //   9	120	123	java/sql/SQLException
/*     */     //   9	120	179	java/lang/Exception
/*     */     //   9	235	235	finally
/*     */     //   242	252	255	java/lang/Exception
/*     */     //   262	272	275	java/lang/Exception
/*     */     //   285	295	298	java/lang/Exception
/*     */     //   305	315	318	java/lang/Exception
/*     */   }
/*     */   
/*     */   private TelefonoTO validaInfoTransferenciaAnexo(TransferenciaTO _transfTO)
/*     */     throws CAException
/*     */   {
/* 251 */     Connection cnx = null;
/* 252 */     MobileTO mobileDestinoTO = null;
/* 253 */     TelefonoTO phoneDestinoTO = new TelefonoTO();
/* 254 */     ParametrosTO paramsTO = null;
/*     */     try
/*     */     {
/* 257 */       paramsTO = new ParametrosTO();
/* 258 */       paramsTO.setTelefono(_transfTO.getTelefonoDestino());
/* 259 */       paramsTO.setCuenta(_transfTO.getCuentaDestino());
/* 260 */       paramsTO.setRegion(_transfTO.getRegionDestino());
/*     */       
/* 262 */       mobileDestinoTO = this.m2kDAO.consultaDatosM2K(paramsTO);
/*     */       
/* 264 */       cnx = ServiceLocator.getInstance().getConnection(ServiceLocator.jdbcCirculoAzul);
/*     */       
/* 266 */       this.consultasPuntosDAO.consultaDatosPuntos(paramsTO, phoneDestinoTO, mobileDestinoTO, cnx);
/*     */       
/* 268 */       phoneDestinoTO.setMobileTO(mobileDestinoTO);
/*     */       
/* 270 */       if (_transfTO.getPuntosTrasnferidos() > _transfTO.getPtosDisponiblesOrigen()) {
/* 271 */         throw new CAException(-1, 
/* 272 */           "LOS PUNTOS A TRANSFERIR SON MAYORES A LOS DISPONIBLES.");
/*     */       }
/* 274 */       if (!mobileDestinoTO.getCuentaPadre().equals(_transfTO.getCuentaPadreOrigen())) {
/* 275 */         throw new CAException(-1, "LAS CUENTAS NO ESTAN CONSOLIDADAS.");
/*     */       }
/* 277 */       if (!validaPlan(cnx, mobileDestinoTO.getPlanM2K(), _transfTO.getRegionDestino())) {
/* 278 */         throw new CAException(-1, "EL PLAN DE LA LINEA DESTINO NO ES PLAN ANEXO.");
/*     */       }
/* 280 */       if (!_transfTO.getCuentaOrigen().equals(_transfTO.getCuentaLineaOrigen())) {
/* 281 */         throw new CAException(-1, "CUENTA ORIGEN INCONSISTENTE EN M2K Y PUNTOS.");
/*     */       }
/* 283 */       if (!_transfTO.getEstatusLineaOrigen().equals("AC")) {
/* 284 */         throw new CAException(-1, 
/* 285 */           "NO SE PUEDE REALIZAR LA TRANSFERENCIA SI LA LINEA ORIGEN ESTA INACTIVA.");
/*     */       }
/* 287 */       if (_transfTO.getPtosDisponiblesOrigen() <= 0) {
/* 288 */         throw new CAException(-1, "CUENTA ORIGEN INCONSISTENTE EN CANTIDAD DE PUNTOS.");
/*     */       }
/* 290 */       if ((!mobileDestinoTO.getCuenta().equals(_transfTO.getCuentaDestino())) || 
/* 291 */         (!mobileDestinoTO.getTelefono().equals(_transfTO.getTelefonoDestino())))
/* 292 */         throw new CAException(-1, 
/* 293 */           "CUENTA Y/O TELEFONO DESTINO INCONSISTENTE EN M2K.");
/*     */     } catch (SQLException se) {
/* 295 */       se = se;
/* 296 */       se.printStackTrace();
/* 297 */       this.error.info("Exception.validaInfoTransferenciaAnexo:", se);
/* 298 */       throw new CAException(-1, 
/* 299 */         "TransferenciaAnexoDAO.validaInfoTransferenciaAnexo[" + se.toString() + "]", se);
/* 300 */     } catch (Exception e) { e = e;
/* 301 */       e.printStackTrace();
/* 302 */       this.error.info("Exception.validaInfoTransferenciaAnexo:", e);
/* 303 */       throw new CAException(-1, 
/* 304 */         "TransferenciaAnexoDAO.validaInfoTransferenciaAnexo[" + e.toString() + "]", e);
/* 305 */     } finally { localObject = finally;
/* 306 */       if (cnx != null) try { cnx.close();cnx = null; } catch (Exception localException1) {}
/* 307 */       throw ((Throwable)localObject);
/*     */     }
/* 306 */     if (cnx != null) try { cnx.close();cnx = null;
/*     */       }
/*     */       catch (Exception localException2) {}
/* 309 */     return phoneDestinoTO;
/*     */   }
/*     */   
/*     */ 
/*     */ 
/*     */ 
/*     */ 
/*     */   private void actualizaInfoPuntos(int[] _arrTiposPuntos, PuntosTO puntosOrigenTO)
/*     */     throws CAException
/*     */   {
/* 319 */     puntosOrigenTO.setPtsPorVencer(_arrTiposPuntos[0]);
/* 320 */     puntosOrigenTO.setPtsPorVencer1(_arrTiposPuntos[1]);
/* 321 */     puntosOrigenTO.setPtsPorVencer2(_arrTiposPuntos[2]);
/* 322 */     puntosOrigenTO.setPtsPromocion(_arrTiposPuntos[3]);
/* 323 */     puntosOrigenTO.setPtsAntiguedad(_arrTiposPuntos[4]);
/* 324 */     puntosOrigenTO.setPtsExcedentes(_arrTiposPuntos[5]);
/* 325 */     puntosOrigenTO.setPtsRenta(_arrTiposPuntos[6]);
/*     */   }
/*     */   
/*     */   /* Error */
/*     */   private boolean actualizaTotalesOrigenAnexo(Connection _cnx, PuntosTO _puntosTO, String _cuenta, int _secuencia)
/*     */     throws CAException
/*     */   {
/*     */     // Byte code:
/*     */     //   0: aconst_null
/*     */     //   1: astore 5
/*     */     //   3: iconst_0
/*     */     //   4: istore 6
/*     */     //   6: aload_1
/*     */     //   7: new 38	java/lang/StringBuilder
/*     */     //   10: dup
/*     */     //   11: ldc_w 489
/*     */     //   14: invokespecial 42	java/lang/StringBuilder:<init>	(Ljava/lang/String;)V
/*     */     //   17: aload_0
/*     */     //   18: getfield 334	com/claro/dao/TransferenciaAnexoDAO:schema_database	Ljava/lang/String;
/*     */     //   21: invokevirtual 60	java/lang/StringBuilder:append	(Ljava/lang/String;)Ljava/lang/StringBuilder;
/*     */     //   24: ldc_w 491
/*     */     //   27: invokevirtual 60	java/lang/StringBuilder:append	(Ljava/lang/String;)Ljava/lang/StringBuilder;
/*     */     //   30: ldc_w 493
/*     */     //   33: invokevirtual 60	java/lang/StringBuilder:append	(Ljava/lang/String;)Ljava/lang/StringBuilder;
/*     */     //   36: ldc_w 495
/*     */     //   39: invokevirtual 60	java/lang/StringBuilder:append	(Ljava/lang/String;)Ljava/lang/StringBuilder;
/*     */     //   42: ldc_w 497
/*     */     //   45: invokevirtual 60	java/lang/StringBuilder:append	(Ljava/lang/String;)Ljava/lang/StringBuilder;
/*     */     //   48: ldc_w 499
/*     */     //   51: invokevirtual 60	java/lang/StringBuilder:append	(Ljava/lang/String;)Ljava/lang/StringBuilder;
/*     */     //   54: ldc_w 501
/*     */     //   57: invokevirtual 60	java/lang/StringBuilder:append	(Ljava/lang/String;)Ljava/lang/StringBuilder;
/*     */     //   60: ldc_w 503
/*     */     //   63: invokevirtual 60	java/lang/StringBuilder:append	(Ljava/lang/String;)Ljava/lang/StringBuilder;
/*     */     //   66: ldc_w 505
/*     */     //   69: invokevirtual 60	java/lang/StringBuilder:append	(Ljava/lang/String;)Ljava/lang/StringBuilder;
/*     */     //   72: ldc_w 507
/*     */     //   75: invokevirtual 60	java/lang/StringBuilder:append	(Ljava/lang/String;)Ljava/lang/StringBuilder;
/*     */     //   78: ldc_w 509
/*     */     //   81: invokevirtual 60	java/lang/StringBuilder:append	(Ljava/lang/String;)Ljava/lang/StringBuilder;
/*     */     //   84: invokevirtual 69	java/lang/StringBuilder:toString	()Ljava/lang/String;
/*     */     //   87: invokeinterface 349 2 0
/*     */     //   92: astore 5
/*     */     //   94: aload 5
/*     */     //   96: iconst_1
/*     */     //   97: aload_2
/*     */     //   98: invokevirtual 121	com/claro/transfer/PuntosTO:getPtsPorVencer	()I
/*     */     //   101: invokeinterface 358 3 0
/*     */     //   106: aload 5
/*     */     //   108: iconst_2
/*     */     //   109: aload_2
/*     */     //   110: invokevirtual 124	com/claro/transfer/PuntosTO:getPtsPorVencer1	()I
/*     */     //   113: invokeinterface 358 3 0
/*     */     //   118: aload 5
/*     */     //   120: iconst_3
/*     */     //   121: aload_2
/*     */     //   122: invokevirtual 127	com/claro/transfer/PuntosTO:getPtsPorVencer2	()I
/*     */     //   125: invokeinterface 358 3 0
/*     */     //   130: aload 5
/*     */     //   132: iconst_4
/*     */     //   133: aload_2
/*     */     //   134: invokevirtual 130	com/claro/transfer/PuntosTO:getPtsPromocion	()I
/*     */     //   137: invokeinterface 358 3 0
/*     */     //   142: aload 5
/*     */     //   144: iconst_5
/*     */     //   145: aload_2
/*     */     //   146: invokevirtual 133	com/claro/transfer/PuntosTO:getPtsAntiguedad	()I
/*     */     //   149: invokeinterface 358 3 0
/*     */     //   154: aload 5
/*     */     //   156: bipush 6
/*     */     //   158: aload_2
/*     */     //   159: invokevirtual 136	com/claro/transfer/PuntosTO:getPtsExcedentes	()I
/*     */     //   162: invokeinterface 358 3 0
/*     */     //   167: aload 5
/*     */     //   169: bipush 7
/*     */     //   171: aload_2
/*     */     //   172: invokevirtual 139	com/claro/transfer/PuntosTO:getPtsRenta	()I
/*     */     //   175: invokeinterface 358 3 0
/*     */     //   180: aload 5
/*     */     //   182: bipush 8
/*     */     //   184: aload_3
/*     */     //   185: invokeinterface 353 3 0
/*     */     //   190: aload 5
/*     */     //   192: bipush 9
/*     */     //   194: iload 4
/*     */     //   196: invokeinterface 358 3 0
/*     */     //   201: aload 5
/*     */     //   203: invokeinterface 511 1 0
/*     */     //   208: istore 6
/*     */     //   210: goto +140 -> 350
/*     */     //   213: astore 7
/*     */     //   215: aload 7
/*     */     //   217: invokevirtual 273	java/sql/SQLException:printStackTrace	()V
/*     */     //   220: aload_0
/*     */     //   221: getfield 278	com/claro/dao/TransferenciaAnexoDAO:error	Lorg/apache/log4j/Logger;
/*     */     //   224: ldc_w 514
/*     */     //   227: aload 7
/*     */     //   229: invokevirtual 283	org/apache/log4j/Logger:info	(Ljava/lang/Object;Ljava/lang/Throwable;)V
/*     */     //   232: new 17	com/claro/exception/CAException
/*     */     //   235: dup
/*     */     //   236: iconst_m1
/*     */     //   237: new 38	java/lang/StringBuilder
/*     */     //   240: dup
/*     */     //   241: ldc_w 516
/*     */     //   244: invokespecial 42	java/lang/StringBuilder:<init>	(Ljava/lang/String;)V
/*     */     //   247: aload 7
/*     */     //   249: invokevirtual 288	java/sql/SQLException:toString	()Ljava/lang/String;
/*     */     //   252: invokevirtual 60	java/lang/StringBuilder:append	(Ljava/lang/String;)Ljava/lang/StringBuilder;
/*     */     //   255: ldc 106
/*     */     //   257: invokevirtual 60	java/lang/StringBuilder:append	(Ljava/lang/String;)Ljava/lang/StringBuilder;
/*     */     //   260: invokevirtual 69	java/lang/StringBuilder:toString	()Ljava/lang/String;
/*     */     //   263: aload 7
/*     */     //   265: invokespecial 289	com/claro/exception/CAException:<init>	(ILjava/lang/String;Ljava/lang/Exception;)V
/*     */     //   268: athrow
/*     */     //   269: astore 7
/*     */     //   271: aload 7
/*     */     //   273: invokevirtual 292	java/lang/Exception:printStackTrace	()V
/*     */     //   276: aload_0
/*     */     //   277: getfield 278	com/claro/dao/TransferenciaAnexoDAO:error	Lorg/apache/log4j/Logger;
/*     */     //   280: ldc_w 514
/*     */     //   283: aload 7
/*     */     //   285: invokevirtual 283	org/apache/log4j/Logger:info	(Ljava/lang/Object;Ljava/lang/Throwable;)V
/*     */     //   288: new 17	com/claro/exception/CAException
/*     */     //   291: dup
/*     */     //   292: iconst_m1
/*     */     //   293: new 38	java/lang/StringBuilder
/*     */     //   296: dup
/*     */     //   297: ldc_w 516
/*     */     //   300: invokespecial 42	java/lang/StringBuilder:<init>	(Ljava/lang/String;)V
/*     */     //   303: aload 7
/*     */     //   305: invokevirtual 295	java/lang/Exception:toString	()Ljava/lang/String;
/*     */     //   308: invokevirtual 60	java/lang/StringBuilder:append	(Ljava/lang/String;)Ljava/lang/StringBuilder;
/*     */     //   311: ldc 106
/*     */     //   313: invokevirtual 60	java/lang/StringBuilder:append	(Ljava/lang/String;)Ljava/lang/StringBuilder;
/*     */     //   316: invokevirtual 69	java/lang/StringBuilder:toString	()Ljava/lang/String;
/*     */     //   319: aload 7
/*     */     //   321: invokespecial 289	com/claro/exception/CAException:<init>	(ILjava/lang/String;Ljava/lang/Exception;)V
/*     */     //   324: athrow
/*     */     //   325: astore 8
/*     */     //   327: aload 5
/*     */     //   329: ifnull +18 -> 347
/*     */     //   332: aload 5
/*     */     //   334: invokeinterface 377 1 0
/*     */     //   339: aconst_null
/*     */     //   340: astore 5
/*     */     //   342: goto +5 -> 347
/*     */     //   345: astore 9
/*     */     //   347: aload 8
/*     */     //   349: athrow
/*     */     //   350: aload 5
/*     */     //   352: ifnull +18 -> 370
/*     */     //   355: aload 5
/*     */     //   357: invokeinterface 377 1 0
/*     */     //   362: aconst_null
/*     */     //   363: astore 5
/*     */     //   365: goto +5 -> 370
/*     */     //   368: astore 9
/*     */     //   370: iload 6
/*     */     //   372: ifle +5 -> 377
/*     */     //   375: iconst_1
/*     */     //   376: ireturn
/*     */     //   377: iconst_0
/*     */     //   378: ireturn
/*     */     // Line number table:
/*     */     //   Java source line #339	-> byte code offset #0
/*     */     //   Java source line #340	-> byte code offset #3
/*     */     //   Java source line #343	-> byte code offset #6
/*     */     //   Java source line #344	-> byte code offset #7
/*     */     //   Java source line #345	-> byte code offset #30
/*     */     //   Java source line #346	-> byte code offset #36
/*     */     //   Java source line #347	-> byte code offset #42
/*     */     //   Java source line #348	-> byte code offset #48
/*     */     //   Java source line #349	-> byte code offset #54
/*     */     //   Java source line #350	-> byte code offset #60
/*     */     //   Java source line #351	-> byte code offset #66
/*     */     //   Java source line #352	-> byte code offset #72
/*     */     //   Java source line #353	-> byte code offset #78
/*     */     //   Java source line #344	-> byte code offset #84
/*     */     //   Java source line #343	-> byte code offset #87
/*     */     //   Java source line #355	-> byte code offset #94
/*     */     //   Java source line #356	-> byte code offset #106
/*     */     //   Java source line #357	-> byte code offset #118
/*     */     //   Java source line #358	-> byte code offset #130
/*     */     //   Java source line #359	-> byte code offset #142
/*     */     //   Java source line #360	-> byte code offset #154
/*     */     //   Java source line #361	-> byte code offset #167
/*     */     //   Java source line #362	-> byte code offset #180
/*     */     //   Java source line #363	-> byte code offset #190
/*     */     //   Java source line #365	-> byte code offset #201
/*     */     //   Java source line #367	-> byte code offset #213
/*     */     //   Java source line #368	-> byte code offset #215
/*     */     //   Java source line #369	-> byte code offset #220
/*     */     //   Java source line #370	-> byte code offset #232
/*     */     //   Java source line #371	-> byte code offset #237
/*     */     //   Java source line #370	-> byte code offset #265
/*     */     //   Java source line #372	-> byte code offset #269
/*     */     //   Java source line #373	-> byte code offset #271
/*     */     //   Java source line #374	-> byte code offset #276
/*     */     //   Java source line #375	-> byte code offset #288
/*     */     //   Java source line #376	-> byte code offset #293
/*     */     //   Java source line #375	-> byte code offset #321
/*     */     //   Java source line #377	-> byte code offset #325
/*     */     //   Java source line #378	-> byte code offset #327
/*     */     //   Java source line #379	-> byte code offset #347
/*     */     //   Java source line #378	-> byte code offset #350
/*     */     //   Java source line #381	-> byte code offset #370
/*     */     // Local variable table:
/*     */     //   start	length	slot	name	signature
/*     */     //   0	379	0	this	TransferenciaAnexoDAO
/*     */     //   0	379	1	_cnx	Connection
/*     */     //   0	379	2	_puntosTO	PuntosTO
/*     */     //   0	379	3	_cuenta	String
/*     */     //   0	379	4	_secuencia	int
/*     */     //   1	363	5	ps	java.sql.PreparedStatement
/*     */     //   4	367	6	rows	int
/*     */     //   213	51	7	se	SQLException
/*     */     //   269	51	7	e	Exception
/*     */     //   325	23	8	localObject	Object
/*     */     //   345	1	9	localException1	Exception
/*     */     //   368	1	9	localException2	Exception
/*     */     // Exception table:
/*     */     //   from	to	target	type
/*     */     //   6	210	213	java/sql/SQLException
/*     */     //   6	210	269	java/lang/Exception
/*     */     //   6	325	325	finally
/*     */     //   332	342	345	java/lang/Exception
/*     */     //   355	365	368	java/lang/Exception
/*     */   }
/*     */   
/*     */   /* Error */
/*     */   private boolean transferir(Connection _cnx, int _ptsExcedentes, int _ptsTransf, String _cuenta, String _secuencia)
/*     */     throws CAException
/*     */   {
/*     */     // Byte code:
/*     */     //   0: aconst_null
/*     */     //   1: astore 6
/*     */     //   3: iconst_0
/*     */     //   4: istore 7
/*     */     //   6: iconst_0
/*     */     //   7: istore 8
/*     */     //   9: iload_2
/*     */     //   10: iload_3
/*     */     //   11: iadd
/*     */     //   12: istore 8
/*     */     //   14: aload_1
/*     */     //   15: new 38	java/lang/StringBuilder
/*     */     //   18: dup
/*     */     //   19: ldc_w 489
/*     */     //   22: invokespecial 42	java/lang/StringBuilder:<init>	(Ljava/lang/String;)V
/*     */     //   25: aload_0
/*     */     //   26: getfield 334	com/claro/dao/TransferenciaAnexoDAO:schema_database	Ljava/lang/String;
/*     */     //   29: invokevirtual 60	java/lang/StringBuilder:append	(Ljava/lang/String;)Ljava/lang/StringBuilder;
/*     */     //   32: ldc_w 491
/*     */     //   35: invokevirtual 60	java/lang/StringBuilder:append	(Ljava/lang/String;)Ljava/lang/StringBuilder;
/*     */     //   38: ldc_w 522
/*     */     //   41: invokevirtual 60	java/lang/StringBuilder:append	(Ljava/lang/String;)Ljava/lang/StringBuilder;
/*     */     //   44: ldc_w 524
/*     */     //   47: invokevirtual 60	java/lang/StringBuilder:append	(Ljava/lang/String;)Ljava/lang/StringBuilder;
/*     */     //   50: ldc_w 509
/*     */     //   53: invokevirtual 60	java/lang/StringBuilder:append	(Ljava/lang/String;)Ljava/lang/StringBuilder;
/*     */     //   56: invokevirtual 69	java/lang/StringBuilder:toString	()Ljava/lang/String;
/*     */     //   59: invokeinterface 349 2 0
/*     */     //   64: astore 6
/*     */     //   66: aload 6
/*     */     //   68: iconst_1
/*     */     //   69: iload 8
/*     */     //   71: invokeinterface 358 3 0
/*     */     //   76: aload 6
/*     */     //   78: iconst_2
/*     */     //   79: aload 4
/*     */     //   81: invokeinterface 353 3 0
/*     */     //   86: aload 6
/*     */     //   88: iconst_3
/*     */     //   89: aload 5
/*     */     //   91: invokeinterface 353 3 0
/*     */     //   96: aload 6
/*     */     //   98: invokeinterface 511 1 0
/*     */     //   103: istore 7
/*     */     //   105: goto +140 -> 245
/*     */     //   108: astore 9
/*     */     //   110: aload 9
/*     */     //   112: invokevirtual 273	java/sql/SQLException:printStackTrace	()V
/*     */     //   115: aload_0
/*     */     //   116: getfield 278	com/claro/dao/TransferenciaAnexoDAO:error	Lorg/apache/log4j/Logger;
/*     */     //   119: ldc_w 526
/*     */     //   122: aload 9
/*     */     //   124: invokevirtual 283	org/apache/log4j/Logger:info	(Ljava/lang/Object;Ljava/lang/Throwable;)V
/*     */     //   127: new 17	com/claro/exception/CAException
/*     */     //   130: dup
/*     */     //   131: iconst_m1
/*     */     //   132: new 38	java/lang/StringBuilder
/*     */     //   135: dup
/*     */     //   136: ldc_w 528
/*     */     //   139: invokespecial 42	java/lang/StringBuilder:<init>	(Ljava/lang/String;)V
/*     */     //   142: aload 9
/*     */     //   144: invokevirtual 288	java/sql/SQLException:toString	()Ljava/lang/String;
/*     */     //   147: invokevirtual 60	java/lang/StringBuilder:append	(Ljava/lang/String;)Ljava/lang/StringBuilder;
/*     */     //   150: ldc 106
/*     */     //   152: invokevirtual 60	java/lang/StringBuilder:append	(Ljava/lang/String;)Ljava/lang/StringBuilder;
/*     */     //   155: invokevirtual 69	java/lang/StringBuilder:toString	()Ljava/lang/String;
/*     */     //   158: aload 9
/*     */     //   160: invokespecial 289	com/claro/exception/CAException:<init>	(ILjava/lang/String;Ljava/lang/Exception;)V
/*     */     //   163: athrow
/*     */     //   164: astore 9
/*     */     //   166: aload 9
/*     */     //   168: invokevirtual 292	java/lang/Exception:printStackTrace	()V
/*     */     //   171: aload_0
/*     */     //   172: getfield 278	com/claro/dao/TransferenciaAnexoDAO:error	Lorg/apache/log4j/Logger;
/*     */     //   175: ldc_w 526
/*     */     //   178: aload 9
/*     */     //   180: invokevirtual 283	org/apache/log4j/Logger:info	(Ljava/lang/Object;Ljava/lang/Throwable;)V
/*     */     //   183: new 17	com/claro/exception/CAException
/*     */     //   186: dup
/*     */     //   187: iconst_m1
/*     */     //   188: new 38	java/lang/StringBuilder
/*     */     //   191: dup
/*     */     //   192: ldc_w 528
/*     */     //   195: invokespecial 42	java/lang/StringBuilder:<init>	(Ljava/lang/String;)V
/*     */     //   198: aload 9
/*     */     //   200: invokevirtual 295	java/lang/Exception:toString	()Ljava/lang/String;
/*     */     //   203: invokevirtual 60	java/lang/StringBuilder:append	(Ljava/lang/String;)Ljava/lang/StringBuilder;
/*     */     //   206: ldc 106
/*     */     //   208: invokevirtual 60	java/lang/StringBuilder:append	(Ljava/lang/String;)Ljava/lang/StringBuilder;
/*     */     //   211: invokevirtual 69	java/lang/StringBuilder:toString	()Ljava/lang/String;
/*     */     //   214: aload 9
/*     */     //   216: invokespecial 289	com/claro/exception/CAException:<init>	(ILjava/lang/String;Ljava/lang/Exception;)V
/*     */     //   219: athrow
/*     */     //   220: astore 10
/*     */     //   222: aload 6
/*     */     //   224: ifnull +18 -> 242
/*     */     //   227: aload 6
/*     */     //   229: invokeinterface 377 1 0
/*     */     //   234: aconst_null
/*     */     //   235: astore 6
/*     */     //   237: goto +5 -> 242
/*     */     //   240: astore 11
/*     */     //   242: aload 10
/*     */     //   244: athrow
/*     */     //   245: aload 6
/*     */     //   247: ifnull +18 -> 265
/*     */     //   250: aload 6
/*     */     //   252: invokeinterface 377 1 0
/*     */     //   257: aconst_null
/*     */     //   258: astore 6
/*     */     //   260: goto +5 -> 265
/*     */     //   263: astore 11
/*     */     //   265: iload 7
/*     */     //   267: ifle +5 -> 272
/*     */     //   270: iconst_1
/*     */     //   271: ireturn
/*     */     //   272: iconst_0
/*     */     //   273: ireturn
/*     */     // Line number table:
/*     */     //   Java source line #396	-> byte code offset #0
/*     */     //   Java source line #397	-> byte code offset #3
/*     */     //   Java source line #400	-> byte code offset #9
/*     */     //   Java source line #402	-> byte code offset #14
/*     */     //   Java source line #403	-> byte code offset #15
/*     */     //   Java source line #404	-> byte code offset #38
/*     */     //   Java source line #405	-> byte code offset #44
/*     */     //   Java source line #406	-> byte code offset #50
/*     */     //   Java source line #403	-> byte code offset #56
/*     */     //   Java source line #402	-> byte code offset #59
/*     */     //   Java source line #408	-> byte code offset #66
/*     */     //   Java source line #409	-> byte code offset #76
/*     */     //   Java source line #410	-> byte code offset #86
/*     */     //   Java source line #412	-> byte code offset #96
/*     */     //   Java source line #414	-> byte code offset #108
/*     */     //   Java source line #415	-> byte code offset #110
/*     */     //   Java source line #416	-> byte code offset #115
/*     */     //   Java source line #417	-> byte code offset #127
/*     */     //   Java source line #418	-> byte code offset #132
/*     */     //   Java source line #417	-> byte code offset #160
/*     */     //   Java source line #419	-> byte code offset #164
/*     */     //   Java source line #420	-> byte code offset #166
/*     */     //   Java source line #421	-> byte code offset #171
/*     */     //   Java source line #422	-> byte code offset #183
/*     */     //   Java source line #423	-> byte code offset #188
/*     */     //   Java source line #422	-> byte code offset #216
/*     */     //   Java source line #424	-> byte code offset #220
/*     */     //   Java source line #425	-> byte code offset #222
/*     */     //   Java source line #426	-> byte code offset #242
/*     */     //   Java source line #425	-> byte code offset #245
/*     */     //   Java source line #428	-> byte code offset #265
/*     */     // Local variable table:
/*     */     //   start	length	slot	name	signature
/*     */     //   0	274	0	this	TransferenciaAnexoDAO
/*     */     //   0	274	1	_cnx	Connection
/*     */     //   0	274	2	_ptsExcedentes	int
/*     */     //   0	274	3	_ptsTransf	int
/*     */     //   0	274	4	_cuenta	String
/*     */     //   0	274	5	_secuencia	String
/*     */     //   1	258	6	ps	java.sql.PreparedStatement
/*     */     //   4	262	7	rows	int
/*     */     //   7	63	8	sumaPts	int
/*     */     //   108	51	9	se	SQLException
/*     */     //   164	51	9	e	Exception
/*     */     //   220	23	10	localObject	Object
/*     */     //   240	1	11	localException1	Exception
/*     */     //   263	1	11	localException2	Exception
/*     */     // Exception table:
/*     */     //   from	to	target	type
/*     */     //   9	105	108	java/sql/SQLException
/*     */     //   9	105	164	java/lang/Exception
/*     */     //   9	220	220	finally
/*     */     //   227	237	240	java/lang/Exception
/*     */     //   250	260	263	java/lang/Exception
/*     */   }
/*     */ }


/* Location:              /opt/trabajo/claro/Guatemala/IS/CO/ClaroClub.ear!/ClaroClubEJB.jar!/com/claro/dao/TransferenciaAnexoDAO.class
 * Java compiler version: 6 (50.0)
 * JD-Core Version:       0.7.1
 */