/*     */ package com.claro.dao;
/*     */ 
/*     */ import com.claro.exception.CAException;
/*     */ import com.claro.transfer.UsuarioTO;
/*     */ import com.claro.util.Constantes;
/*     */ import com.claro.util.ServiceLocator;
/*     */ import java.sql.Connection;
/*     */ import java.sql.PreparedStatement;
/*     */ import java.sql.ResultSet;
/*     */ import java.sql.SQLException;
/*     */ import java.text.SimpleDateFormat;
/*     */ import java.util.Date;
/*     */ import org.apache.log4j.Logger;
/*     */ 
/*     */ 
/*     */ 
/*     */ 
/*     */ 
/*     */ 
/*     */ 
/*     */ public class UsuarioDAO
/*     */ {
/*  23 */   protected final Logger logger = Logger.getLogger("loggerCirculoAzul");
/*  24 */   protected final Logger error = Logger.getLogger("loggerCirculoAzulError");
/*     */   private String schema_database;
/*     */   
/*     */   public UsuarioDAO()
/*     */   {
/*     */     try {
/*  30 */       this.schema_database = ServiceLocator.getInstance().getVariable(ServiceLocator.schema_database);
/*     */     } catch (Exception e) {
/*  32 */       this.error.error("UsuarioDAO", e);
/*     */     }
/*     */   }
/*     */   
/*     */   /* Error */
/*     */   public UsuarioTO consultaEmpleado(String numEmpleado, String sIP, String passActual, boolean validaPwd)
/*     */     throws CAException
/*     */   {
/*     */     // Byte code:
/*     */     //   0: aload_1
/*     */     //   1: ifnonnull +14 -> 15
/*     */     //   4: new 59	com/claro/exception/CAException
/*     */     //   7: dup
/*     */     //   8: iconst_m1
/*     */     //   9: ldc 61
/*     */     //   11: invokespecial 63	com/claro/exception/CAException:<init>	(ILjava/lang/String;)V
/*     */     //   14: athrow
/*     */     //   15: aconst_null
/*     */     //   16: astore 5
/*     */     //   18: aconst_null
/*     */     //   19: astore 6
/*     */     //   21: aconst_null
/*     */     //   22: astore 7
/*     */     //   24: new 66	java/lang/StringBuffer
/*     */     //   27: dup
/*     */     //   28: invokespecial 68	java/lang/StringBuffer:<init>	()V
/*     */     //   31: astore 8
/*     */     //   33: aload 8
/*     */     //   35: ldc 69
/*     */     //   37: invokevirtual 71	java/lang/StringBuffer:append	(Ljava/lang/String;)Ljava/lang/StringBuffer;
/*     */     //   40: pop
/*     */     //   41: aload 8
/*     */     //   43: ldc 75
/*     */     //   45: invokevirtual 71	java/lang/StringBuffer:append	(Ljava/lang/String;)Ljava/lang/StringBuffer;
/*     */     //   48: aload_0
/*     */     //   49: getfield 41	com/claro/dao/UsuarioDAO:schema_database	Ljava/lang/String;
/*     */     //   52: invokevirtual 71	java/lang/StringBuffer:append	(Ljava/lang/String;)Ljava/lang/StringBuffer;
/*     */     //   55: ldc 77
/*     */     //   57: invokevirtual 71	java/lang/StringBuffer:append	(Ljava/lang/String;)Ljava/lang/StringBuffer;
/*     */     //   60: aload_0
/*     */     //   61: getfield 41	com/claro/dao/UsuarioDAO:schema_database	Ljava/lang/String;
/*     */     //   64: invokevirtual 71	java/lang/StringBuffer:append	(Ljava/lang/String;)Ljava/lang/StringBuffer;
/*     */     //   67: ldc 79
/*     */     //   69: invokevirtual 71	java/lang/StringBuffer:append	(Ljava/lang/String;)Ljava/lang/StringBuffer;
/*     */     //   72: pop
/*     */     //   73: aload 8
/*     */     //   75: ldc 81
/*     */     //   77: invokevirtual 71	java/lang/StringBuffer:append	(Ljava/lang/String;)Ljava/lang/StringBuffer;
/*     */     //   80: pop
/*     */     //   81: new 83	com/claro/transfer/UsuarioTO
/*     */     //   84: dup
/*     */     //   85: invokespecial 85	com/claro/transfer/UsuarioTO:<init>	()V
/*     */     //   88: astore 9
/*     */     //   90: invokestatic 86	java/lang/System:currentTimeMillis	()J
/*     */     //   93: lstore 10
/*     */     //   95: aload_0
/*     */     //   96: getfield 23	com/claro/dao/UsuarioDAO:logger	Lorg/apache/log4j/Logger;
/*     */     //   99: new 92	java/lang/StringBuilder
/*     */     //   102: dup
/*     */     //   103: ldc 94
/*     */     //   105: invokespecial 96	java/lang/StringBuilder:<init>	(Ljava/lang/String;)V
/*     */     //   108: getstatic 99	com/claro/util/Constantes:DATEFORMTALog	Ljava/text/SimpleDateFormat;
/*     */     //   111: new 105	java/util/Date
/*     */     //   114: dup
/*     */     //   115: invokespecial 107	java/util/Date:<init>	()V
/*     */     //   118: invokevirtual 108	java/text/SimpleDateFormat:format	(Ljava/util/Date;)Ljava/lang/String;
/*     */     //   121: invokevirtual 114	java/lang/StringBuilder:append	(Ljava/lang/String;)Ljava/lang/StringBuilder;
/*     */     //   124: ldc 117
/*     */     //   126: invokevirtual 114	java/lang/StringBuilder:append	(Ljava/lang/String;)Ljava/lang/StringBuilder;
/*     */     //   129: lload 10
/*     */     //   131: invokevirtual 119	java/lang/StringBuilder:append	(J)Ljava/lang/StringBuilder;
/*     */     //   134: invokevirtual 122	java/lang/StringBuilder:toString	()Ljava/lang/String;
/*     */     //   137: invokevirtual 126	org/apache/log4j/Logger:info	(Ljava/lang/Object;)V
/*     */     //   140: aload_0
/*     */     //   141: getfield 23	com/claro/dao/UsuarioDAO:logger	Lorg/apache/log4j/Logger;
/*     */     //   144: new 92	java/lang/StringBuilder
/*     */     //   147: dup
/*     */     //   148: ldc -126
/*     */     //   150: invokespecial 96	java/lang/StringBuilder:<init>	(Ljava/lang/String;)V
/*     */     //   153: getstatic 99	com/claro/util/Constantes:DATEFORMTALog	Ljava/text/SimpleDateFormat;
/*     */     //   156: new 105	java/util/Date
/*     */     //   159: dup
/*     */     //   160: invokespecial 107	java/util/Date:<init>	()V
/*     */     //   163: invokevirtual 108	java/text/SimpleDateFormat:format	(Ljava/util/Date;)Ljava/lang/String;
/*     */     //   166: invokevirtual 114	java/lang/StringBuilder:append	(Ljava/lang/String;)Ljava/lang/StringBuilder;
/*     */     //   169: ldc 117
/*     */     //   171: invokevirtual 114	java/lang/StringBuilder:append	(Ljava/lang/String;)Ljava/lang/StringBuilder;
/*     */     //   174: lload 10
/*     */     //   176: invokevirtual 119	java/lang/StringBuilder:append	(J)Ljava/lang/StringBuilder;
/*     */     //   179: invokevirtual 122	java/lang/StringBuilder:toString	()Ljava/lang/String;
/*     */     //   182: invokevirtual 126	org/apache/log4j/Logger:info	(Ljava/lang/Object;)V
/*     */     //   185: invokestatic 29	com/claro/util/ServiceLocator:getInstance	()Lcom/claro/util/ServiceLocator;
/*     */     //   188: getstatic 132	com/claro/util/ServiceLocator:jdbcCirculoAzul	Ljava/lang/String;
/*     */     //   191: invokevirtual 135	com/claro/util/ServiceLocator:getConnection	(Ljava/lang/String;)Ljava/sql/Connection;
/*     */     //   194: astore 5
/*     */     //   196: aload_0
/*     */     //   197: getfield 23	com/claro/dao/UsuarioDAO:logger	Lorg/apache/log4j/Logger;
/*     */     //   200: new 92	java/lang/StringBuilder
/*     */     //   203: dup
/*     */     //   204: ldc -117
/*     */     //   206: invokespecial 96	java/lang/StringBuilder:<init>	(Ljava/lang/String;)V
/*     */     //   209: getstatic 99	com/claro/util/Constantes:DATEFORMTALog	Ljava/text/SimpleDateFormat;
/*     */     //   212: new 105	java/util/Date
/*     */     //   215: dup
/*     */     //   216: invokespecial 107	java/util/Date:<init>	()V
/*     */     //   219: invokevirtual 108	java/text/SimpleDateFormat:format	(Ljava/util/Date;)Ljava/lang/String;
/*     */     //   222: invokevirtual 114	java/lang/StringBuilder:append	(Ljava/lang/String;)Ljava/lang/StringBuilder;
/*     */     //   225: ldc 117
/*     */     //   227: invokevirtual 114	java/lang/StringBuilder:append	(Ljava/lang/String;)Ljava/lang/StringBuilder;
/*     */     //   230: invokestatic 86	java/lang/System:currentTimeMillis	()J
/*     */     //   233: lload 10
/*     */     //   235: lsub
/*     */     //   236: invokevirtual 119	java/lang/StringBuilder:append	(J)Ljava/lang/StringBuilder;
/*     */     //   239: invokevirtual 122	java/lang/StringBuilder:toString	()Ljava/lang/String;
/*     */     //   242: invokevirtual 126	org/apache/log4j/Logger:info	(Ljava/lang/Object;)V
/*     */     //   245: invokestatic 86	java/lang/System:currentTimeMillis	()J
/*     */     //   248: lstore 12
/*     */     //   250: aload_0
/*     */     //   251: getfield 23	com/claro/dao/UsuarioDAO:logger	Lorg/apache/log4j/Logger;
/*     */     //   254: new 92	java/lang/StringBuilder
/*     */     //   257: dup
/*     */     //   258: ldc -115
/*     */     //   260: invokespecial 96	java/lang/StringBuilder:<init>	(Ljava/lang/String;)V
/*     */     //   263: getstatic 99	com/claro/util/Constantes:DATEFORMTALog	Ljava/text/SimpleDateFormat;
/*     */     //   266: new 105	java/util/Date
/*     */     //   269: dup
/*     */     //   270: invokespecial 107	java/util/Date:<init>	()V
/*     */     //   273: invokevirtual 108	java/text/SimpleDateFormat:format	(Ljava/util/Date;)Ljava/lang/String;
/*     */     //   276: invokevirtual 114	java/lang/StringBuilder:append	(Ljava/lang/String;)Ljava/lang/StringBuilder;
/*     */     //   279: ldc 117
/*     */     //   281: invokevirtual 114	java/lang/StringBuilder:append	(Ljava/lang/String;)Ljava/lang/StringBuilder;
/*     */     //   284: lload 12
/*     */     //   286: invokevirtual 119	java/lang/StringBuilder:append	(J)Ljava/lang/StringBuilder;
/*     */     //   289: invokevirtual 122	java/lang/StringBuilder:toString	()Ljava/lang/String;
/*     */     //   292: invokevirtual 126	org/apache/log4j/Logger:info	(Ljava/lang/Object;)V
/*     */     //   295: aload 5
/*     */     //   297: aload 8
/*     */     //   299: invokevirtual 143	java/lang/StringBuffer:toString	()Ljava/lang/String;
/*     */     //   302: invokeinterface 144 2 0
/*     */     //   307: astore 6
/*     */     //   309: aload 6
/*     */     //   311: iconst_1
/*     */     //   312: aload_1
/*     */     //   313: invokeinterface 150 3 0
/*     */     //   318: aload 6
/*     */     //   320: invokeinterface 155 1 0
/*     */     //   325: astore 7
/*     */     //   327: aload 7
/*     */     //   329: invokeinterface 159 1 0
/*     */     //   334: ifeq +451 -> 785
/*     */     //   337: aload 9
/*     */     //   339: aload_1
/*     */     //   340: invokevirtual 165	com/claro/transfer/UsuarioTO:setNumEmpleado	(Ljava/lang/String;)V
/*     */     //   343: aload 9
/*     */     //   345: aload 7
/*     */     //   347: iconst_1
/*     */     //   348: invokeinterface 168 2 0
/*     */     //   353: invokevirtual 172	com/claro/transfer/UsuarioTO:setIdUsuario	(Ljava/lang/String;)V
/*     */     //   356: aload 9
/*     */     //   358: aload 7
/*     */     //   360: iconst_2
/*     */     //   361: invokeinterface 168 2 0
/*     */     //   366: invokevirtual 175	com/claro/transfer/UsuarioTO:setNombre	(Ljava/lang/String;)V
/*     */     //   369: aload 9
/*     */     //   371: aload 7
/*     */     //   373: iconst_3
/*     */     //   374: invokeinterface 168 2 0
/*     */     //   379: invokevirtual 178	com/claro/transfer/UsuarioTO:setPassword	(Ljava/lang/String;)V
/*     */     //   382: aload 9
/*     */     //   384: aload 7
/*     */     //   386: bipush 10
/*     */     //   388: invokeinterface 168 2 0
/*     */     //   393: invokevirtual 181	com/claro/transfer/UsuarioTO:setStatus	(Ljava/lang/String;)V
/*     */     //   396: aload 7
/*     */     //   398: iconst_5
/*     */     //   399: invokeinterface 184 2 0
/*     */     //   404: istore 14
/*     */     //   406: aload 9
/*     */     //   408: new 188	com/claro/dao/ConsultasDAO
/*     */     //   411: dup
/*     */     //   412: invokespecial 190	com/claro/dao/ConsultasDAO:<init>	()V
/*     */     //   415: aload_2
/*     */     //   416: aload 5
/*     */     //   418: invokevirtual 191	com/claro/dao/ConsultasDAO:obtienePuntoVenta	(Ljava/lang/String;Ljava/sql/Connection;)Lcom/claro/transfer/PuntoVentaTO;
/*     */     //   421: invokevirtual 195	com/claro/transfer/UsuarioTO:setPuntoVentaTO	(Lcom/claro/transfer/PuntoVentaTO;)V
/*     */     //   424: iload 4
/*     */     //   426: ifeq +240 -> 666
/*     */     //   429: aload 9
/*     */     //   431: invokevirtual 199	com/claro/transfer/UsuarioTO:getPassword	()Ljava/lang/String;
/*     */     //   434: aload_3
/*     */     //   435: invokevirtual 202	java/lang/String:equals	(Ljava/lang/Object;)Z
/*     */     //   438: ifne +46 -> 484
/*     */     //   441: aload 9
/*     */     //   443: invokevirtual 208	com/claro/transfer/UsuarioTO:getStatus	()Ljava/lang/String;
/*     */     //   446: ldc -45
/*     */     //   448: invokevirtual 202	java/lang/String:equals	(Ljava/lang/Object;)Z
/*     */     //   451: ifeq +33 -> 484
/*     */     //   454: aload 9
/*     */     //   456: iconst_m1
/*     */     //   457: new 92	java/lang/StringBuilder
/*     */     //   460: dup
/*     */     //   461: ldc -43
/*     */     //   463: invokespecial 96	java/lang/StringBuilder:<init>	(Ljava/lang/String;)V
/*     */     //   466: aload_1
/*     */     //   467: invokevirtual 114	java/lang/StringBuilder:append	(Ljava/lang/String;)Ljava/lang/StringBuilder;
/*     */     //   470: ldc -41
/*     */     //   472: invokevirtual 114	java/lang/StringBuilder:append	(Ljava/lang/String;)Ljava/lang/StringBuilder;
/*     */     //   475: invokevirtual 122	java/lang/StringBuilder:toString	()Ljava/lang/String;
/*     */     //   478: invokevirtual 217	com/claro/transfer/UsuarioTO:agregaMensaje	(ILjava/lang/String;)V
/*     */     //   481: goto +333 -> 814
/*     */     //   484: aload 9
/*     */     //   486: invokevirtual 199	com/claro/transfer/UsuarioTO:getPassword	()Ljava/lang/String;
/*     */     //   489: aload_3
/*     */     //   490: invokevirtual 202	java/lang/String:equals	(Ljava/lang/Object;)Z
/*     */     //   493: ifeq +135 -> 628
/*     */     //   496: aload 9
/*     */     //   498: invokevirtual 208	com/claro/transfer/UsuarioTO:getStatus	()Ljava/lang/String;
/*     */     //   501: ldc -45
/*     */     //   503: invokevirtual 202	java/lang/String:equals	(Ljava/lang/Object;)Z
/*     */     //   506: ifeq +122 -> 628
/*     */     //   509: new 220	com/claro/transfer/PerfilTO
/*     */     //   512: dup
/*     */     //   513: invokespecial 222	com/claro/transfer/PerfilTO:<init>	()V
/*     */     //   516: astore 15
/*     */     //   518: aload 15
/*     */     //   520: iload 14
/*     */     //   522: invokevirtual 223	com/claro/transfer/PerfilTO:setIdPerfilN	(I)V
/*     */     //   525: aload 15
/*     */     //   527: aload 7
/*     */     //   529: bipush 6
/*     */     //   531: invokeinterface 184 2 0
/*     */     //   536: invokevirtual 227	com/claro/transfer/PerfilTO:setNivelAutorizacion	(I)V
/*     */     //   539: aload 15
/*     */     //   541: aload 7
/*     */     //   543: bipush 7
/*     */     //   545: invokeinterface 168 2 0
/*     */     //   550: invokevirtual 230	com/claro/transfer/PerfilTO:setIdPuesto	(Ljava/lang/String;)V
/*     */     //   553: aload 15
/*     */     //   555: aload 7
/*     */     //   557: bipush 8
/*     */     //   559: invokeinterface 168 2 0
/*     */     //   564: invokevirtual 233	com/claro/transfer/PerfilTO:setDescripcion	(Ljava/lang/String;)V
/*     */     //   567: aload 15
/*     */     //   569: aload 7
/*     */     //   571: bipush 9
/*     */     //   573: invokeinterface 184 2 0
/*     */     //   578: invokevirtual 236	com/claro/transfer/PerfilTO:setRegion	(I)V
/*     */     //   581: aload_0
/*     */     //   582: iload 14
/*     */     //   584: invokevirtual 239	com/claro/dao/UsuarioDAO:getPrivilegiosCirculoAzulEcac	(I)Lcom/claro/transfer/PerfilTO;
/*     */     //   587: astore 16
/*     */     //   589: aload 15
/*     */     //   591: aload 16
/*     */     //   593: invokevirtual 243	com/claro/transfer/PerfilTO:getPrivilegiosCa	()Ljava/util/Hashtable;
/*     */     //   596: invokevirtual 247	com/claro/transfer/PerfilTO:setPrivilegiosCa	(Ljava/util/Hashtable;)V
/*     */     //   599: aload 15
/*     */     //   601: aload 16
/*     */     //   603: invokevirtual 251	com/claro/transfer/PerfilTO:getPrivilegiosEcac	()Ljava/util/Hashtable;
/*     */     //   606: invokevirtual 254	com/claro/transfer/PerfilTO:setPrivilegiosEcac	(Ljava/util/Hashtable;)V
/*     */     //   609: aload 9
/*     */     //   611: aload 15
/*     */     //   613: invokevirtual 257	com/claro/transfer/UsuarioTO:setPerfilTO	(Lcom/claro/transfer/PerfilTO;)V
/*     */     //   616: aload 9
/*     */     //   618: iconst_0
/*     */     //   619: ldc_w 261
/*     */     //   622: invokevirtual 217	com/claro/transfer/UsuarioTO:agregaMensaje	(ILjava/lang/String;)V
/*     */     //   625: goto +189 -> 814
/*     */     //   628: aload 9
/*     */     //   630: iconst_m1
/*     */     //   631: new 92	java/lang/StringBuilder
/*     */     //   634: dup
/*     */     //   635: ldc_w 263
/*     */     //   638: invokespecial 96	java/lang/StringBuilder:<init>	(Ljava/lang/String;)V
/*     */     //   641: aload_1
/*     */     //   642: invokevirtual 114	java/lang/StringBuilder:append	(Ljava/lang/String;)Ljava/lang/StringBuilder;
/*     */     //   645: ldc_w 265
/*     */     //   648: invokevirtual 114	java/lang/StringBuilder:append	(Ljava/lang/String;)Ljava/lang/StringBuilder;
/*     */     //   651: ldc_w 267
/*     */     //   654: invokevirtual 114	java/lang/StringBuilder:append	(Ljava/lang/String;)Ljava/lang/StringBuilder;
/*     */     //   657: invokevirtual 122	java/lang/StringBuilder:toString	()Ljava/lang/String;
/*     */     //   660: invokevirtual 217	com/claro/transfer/UsuarioTO:agregaMensaje	(ILjava/lang/String;)V
/*     */     //   663: goto +151 -> 814
/*     */     //   666: new 220	com/claro/transfer/PerfilTO
/*     */     //   669: dup
/*     */     //   670: invokespecial 222	com/claro/transfer/PerfilTO:<init>	()V
/*     */     //   673: astore 15
/*     */     //   675: aload 15
/*     */     //   677: iload 14
/*     */     //   679: invokevirtual 223	com/claro/transfer/PerfilTO:setIdPerfilN	(I)V
/*     */     //   682: aload 15
/*     */     //   684: aload 7
/*     */     //   686: bipush 6
/*     */     //   688: invokeinterface 184 2 0
/*     */     //   693: invokevirtual 227	com/claro/transfer/PerfilTO:setNivelAutorizacion	(I)V
/*     */     //   696: aload 15
/*     */     //   698: aload 7
/*     */     //   700: bipush 7
/*     */     //   702: invokeinterface 168 2 0
/*     */     //   707: invokevirtual 230	com/claro/transfer/PerfilTO:setIdPuesto	(Ljava/lang/String;)V
/*     */     //   710: aload 15
/*     */     //   712: aload 7
/*     */     //   714: bipush 8
/*     */     //   716: invokeinterface 168 2 0
/*     */     //   721: invokevirtual 233	com/claro/transfer/PerfilTO:setDescripcion	(Ljava/lang/String;)V
/*     */     //   724: aload 15
/*     */     //   726: aload 7
/*     */     //   728: bipush 9
/*     */     //   730: invokeinterface 184 2 0
/*     */     //   735: invokevirtual 236	com/claro/transfer/PerfilTO:setRegion	(I)V
/*     */     //   738: aload_0
/*     */     //   739: iload 14
/*     */     //   741: invokevirtual 239	com/claro/dao/UsuarioDAO:getPrivilegiosCirculoAzulEcac	(I)Lcom/claro/transfer/PerfilTO;
/*     */     //   744: astore 16
/*     */     //   746: aload 15
/*     */     //   748: aload 16
/*     */     //   750: invokevirtual 243	com/claro/transfer/PerfilTO:getPrivilegiosCa	()Ljava/util/Hashtable;
/*     */     //   753: invokevirtual 247	com/claro/transfer/PerfilTO:setPrivilegiosCa	(Ljava/util/Hashtable;)V
/*     */     //   756: aload 15
/*     */     //   758: aload 16
/*     */     //   760: invokevirtual 251	com/claro/transfer/PerfilTO:getPrivilegiosEcac	()Ljava/util/Hashtable;
/*     */     //   763: invokevirtual 254	com/claro/transfer/PerfilTO:setPrivilegiosEcac	(Ljava/util/Hashtable;)V
/*     */     //   766: aload 9
/*     */     //   768: aload 15
/*     */     //   770: invokevirtual 257	com/claro/transfer/UsuarioTO:setPerfilTO	(Lcom/claro/transfer/PerfilTO;)V
/*     */     //   773: aload 9
/*     */     //   775: iconst_0
/*     */     //   776: ldc_w 261
/*     */     //   779: invokevirtual 217	com/claro/transfer/UsuarioTO:agregaMensaje	(ILjava/lang/String;)V
/*     */     //   782: goto +32 -> 814
/*     */     //   785: aload 9
/*     */     //   787: iconst_m1
/*     */     //   788: new 92	java/lang/StringBuilder
/*     */     //   791: dup
/*     */     //   792: ldc_w 269
/*     */     //   795: invokespecial 96	java/lang/StringBuilder:<init>	(Ljava/lang/String;)V
/*     */     //   798: aload_1
/*     */     //   799: invokevirtual 114	java/lang/StringBuilder:append	(Ljava/lang/String;)Ljava/lang/StringBuilder;
/*     */     //   802: ldc_w 271
/*     */     //   805: invokevirtual 114	java/lang/StringBuilder:append	(Ljava/lang/String;)Ljava/lang/StringBuilder;
/*     */     //   808: invokevirtual 122	java/lang/StringBuilder:toString	()Ljava/lang/String;
/*     */     //   811: invokevirtual 217	com/claro/transfer/UsuarioTO:agregaMensaje	(ILjava/lang/String;)V
/*     */     //   814: aload_0
/*     */     //   815: getfield 23	com/claro/dao/UsuarioDAO:logger	Lorg/apache/log4j/Logger;
/*     */     //   818: new 92	java/lang/StringBuilder
/*     */     //   821: dup
/*     */     //   822: ldc_w 273
/*     */     //   825: invokespecial 96	java/lang/StringBuilder:<init>	(Ljava/lang/String;)V
/*     */     //   828: getstatic 99	com/claro/util/Constantes:DATEFORMTALog	Ljava/text/SimpleDateFormat;
/*     */     //   831: new 105	java/util/Date
/*     */     //   834: dup
/*     */     //   835: invokespecial 107	java/util/Date:<init>	()V
/*     */     //   838: invokevirtual 108	java/text/SimpleDateFormat:format	(Ljava/util/Date;)Ljava/lang/String;
/*     */     //   841: invokevirtual 114	java/lang/StringBuilder:append	(Ljava/lang/String;)Ljava/lang/StringBuilder;
/*     */     //   844: ldc 117
/*     */     //   846: invokevirtual 114	java/lang/StringBuilder:append	(Ljava/lang/String;)Ljava/lang/StringBuilder;
/*     */     //   849: invokestatic 86	java/lang/System:currentTimeMillis	()J
/*     */     //   852: lload 12
/*     */     //   854: lsub
/*     */     //   855: invokevirtual 119	java/lang/StringBuilder:append	(J)Ljava/lang/StringBuilder;
/*     */     //   858: invokevirtual 122	java/lang/StringBuilder:toString	()Ljava/lang/String;
/*     */     //   861: invokevirtual 126	org/apache/log4j/Logger:info	(Ljava/lang/Object;)V
/*     */     //   864: aload_0
/*     */     //   865: getfield 23	com/claro/dao/UsuarioDAO:logger	Lorg/apache/log4j/Logger;
/*     */     //   868: new 92	java/lang/StringBuilder
/*     */     //   871: dup
/*     */     //   872: ldc_w 275
/*     */     //   875: invokespecial 96	java/lang/StringBuilder:<init>	(Ljava/lang/String;)V
/*     */     //   878: getstatic 99	com/claro/util/Constantes:DATEFORMTALog	Ljava/text/SimpleDateFormat;
/*     */     //   881: new 105	java/util/Date
/*     */     //   884: dup
/*     */     //   885: invokespecial 107	java/util/Date:<init>	()V
/*     */     //   888: invokevirtual 108	java/text/SimpleDateFormat:format	(Ljava/util/Date;)Ljava/lang/String;
/*     */     //   891: invokevirtual 114	java/lang/StringBuilder:append	(Ljava/lang/String;)Ljava/lang/StringBuilder;
/*     */     //   894: ldc 117
/*     */     //   896: invokevirtual 114	java/lang/StringBuilder:append	(Ljava/lang/String;)Ljava/lang/StringBuilder;
/*     */     //   899: invokestatic 86	java/lang/System:currentTimeMillis	()J
/*     */     //   902: lload 10
/*     */     //   904: lsub
/*     */     //   905: invokevirtual 119	java/lang/StringBuilder:append	(J)Ljava/lang/StringBuilder;
/*     */     //   908: invokevirtual 122	java/lang/StringBuilder:toString	()Ljava/lang/String;
/*     */     //   911: invokevirtual 126	org/apache/log4j/Logger:info	(Ljava/lang/Object;)V
/*     */     //   914: goto +170 -> 1084
/*     */     //   917: astore 10
/*     */     //   919: aload_0
/*     */     //   920: getfield 27	com/claro/dao/UsuarioDAO:error	Lorg/apache/log4j/Logger;
/*     */     //   923: ldc_w 277
/*     */     //   926: aload 10
/*     */     //   928: invokevirtual 279	org/apache/log4j/Logger:info	(Ljava/lang/Object;Ljava/lang/Throwable;)V
/*     */     //   931: new 59	com/claro/exception/CAException
/*     */     //   934: dup
/*     */     //   935: iconst_m1
/*     */     //   936: new 92	java/lang/StringBuilder
/*     */     //   939: dup
/*     */     //   940: ldc_w 281
/*     */     //   943: invokespecial 96	java/lang/StringBuilder:<init>	(Ljava/lang/String;)V
/*     */     //   946: aload 10
/*     */     //   948: invokevirtual 283	java/sql/SQLException:toString	()Ljava/lang/String;
/*     */     //   951: invokevirtual 114	java/lang/StringBuilder:append	(Ljava/lang/String;)Ljava/lang/StringBuilder;
/*     */     //   954: ldc -41
/*     */     //   956: invokevirtual 114	java/lang/StringBuilder:append	(Ljava/lang/String;)Ljava/lang/StringBuilder;
/*     */     //   959: invokevirtual 122	java/lang/StringBuilder:toString	()Ljava/lang/String;
/*     */     //   962: aload 10
/*     */     //   964: invokespecial 286	com/claro/exception/CAException:<init>	(ILjava/lang/String;Ljava/lang/Exception;)V
/*     */     //   967: athrow
/*     */     //   968: astore 10
/*     */     //   970: aload_0
/*     */     //   971: getfield 27	com/claro/dao/UsuarioDAO:error	Lorg/apache/log4j/Logger;
/*     */     //   974: ldc_w 289
/*     */     //   977: aload 10
/*     */     //   979: invokevirtual 279	org/apache/log4j/Logger:info	(Ljava/lang/Object;Ljava/lang/Throwable;)V
/*     */     //   982: new 59	com/claro/exception/CAException
/*     */     //   985: dup
/*     */     //   986: iconst_m1
/*     */     //   987: new 92	java/lang/StringBuilder
/*     */     //   990: dup
/*     */     //   991: ldc_w 291
/*     */     //   994: invokespecial 96	java/lang/StringBuilder:<init>	(Ljava/lang/String;)V
/*     */     //   997: aload 10
/*     */     //   999: invokevirtual 293	java/lang/Exception:toString	()Ljava/lang/String;
/*     */     //   1002: invokevirtual 114	java/lang/StringBuilder:append	(Ljava/lang/String;)Ljava/lang/StringBuilder;
/*     */     //   1005: ldc -41
/*     */     //   1007: invokevirtual 114	java/lang/StringBuilder:append	(Ljava/lang/String;)Ljava/lang/StringBuilder;
/*     */     //   1010: invokevirtual 122	java/lang/StringBuilder:toString	()Ljava/lang/String;
/*     */     //   1013: aload 10
/*     */     //   1015: invokespecial 286	com/claro/exception/CAException:<init>	(ILjava/lang/String;Ljava/lang/Exception;)V
/*     */     //   1018: athrow
/*     */     //   1019: astore 17
/*     */     //   1021: aload 7
/*     */     //   1023: ifnull +18 -> 1041
/*     */     //   1026: aload 7
/*     */     //   1028: invokeinterface 294 1 0
/*     */     //   1033: aconst_null
/*     */     //   1034: astore 7
/*     */     //   1036: goto +5 -> 1041
/*     */     //   1039: astore 18
/*     */     //   1041: aload 6
/*     */     //   1043: ifnull +18 -> 1061
/*     */     //   1046: aload 6
/*     */     //   1048: invokeinterface 297 1 0
/*     */     //   1053: aconst_null
/*     */     //   1054: astore 6
/*     */     //   1056: goto +5 -> 1061
/*     */     //   1059: astore 18
/*     */     //   1061: aload 5
/*     */     //   1063: ifnull +18 -> 1081
/*     */     //   1066: aload 5
/*     */     //   1068: invokeinterface 298 1 0
/*     */     //   1073: aconst_null
/*     */     //   1074: astore 5
/*     */     //   1076: goto +5 -> 1081
/*     */     //   1079: astore 18
/*     */     //   1081: aload 17
/*     */     //   1083: athrow
/*     */     //   1084: aload 7
/*     */     //   1086: ifnull +18 -> 1104
/*     */     //   1089: aload 7
/*     */     //   1091: invokeinterface 294 1 0
/*     */     //   1096: aconst_null
/*     */     //   1097: astore 7
/*     */     //   1099: goto +5 -> 1104
/*     */     //   1102: astore 18
/*     */     //   1104: aload 6
/*     */     //   1106: ifnull +18 -> 1124
/*     */     //   1109: aload 6
/*     */     //   1111: invokeinterface 297 1 0
/*     */     //   1116: aconst_null
/*     */     //   1117: astore 6
/*     */     //   1119: goto +5 -> 1124
/*     */     //   1122: astore 18
/*     */     //   1124: aload 5
/*     */     //   1126: ifnull +18 -> 1144
/*     */     //   1129: aload 5
/*     */     //   1131: invokeinterface 298 1 0
/*     */     //   1136: aconst_null
/*     */     //   1137: astore 5
/*     */     //   1139: goto +5 -> 1144
/*     */     //   1142: astore 18
/*     */     //   1144: aload 9
/*     */     //   1146: areturn
/*     */     // Line number table:
/*     */     //   Java source line #43	-> byte code offset #0
/*     */     //   Java source line #45	-> byte code offset #15
/*     */     //   Java source line #46	-> byte code offset #18
/*     */     //   Java source line #47	-> byte code offset #21
/*     */     //   Java source line #49	-> byte code offset #24
/*     */     //   Java source line #50	-> byte code offset #33
/*     */     //   Java source line #51	-> byte code offset #41
/*     */     //   Java source line #52	-> byte code offset #73
/*     */     //   Java source line #55	-> byte code offset #81
/*     */     //   Java source line #57	-> byte code offset #90
/*     */     //   Java source line #58	-> byte code offset #95
/*     */     //   Java source line #59	-> byte code offset #140
/*     */     //   Java source line #60	-> byte code offset #185
/*     */     //   Java source line #61	-> byte code offset #196
/*     */     //   Java source line #62	-> byte code offset #245
/*     */     //   Java source line #63	-> byte code offset #250
/*     */     //   Java source line #64	-> byte code offset #295
/*     */     //   Java source line #65	-> byte code offset #309
/*     */     //   Java source line #66	-> byte code offset #318
/*     */     //   Java source line #67	-> byte code offset #327
/*     */     //   Java source line #68	-> byte code offset #337
/*     */     //   Java source line #69	-> byte code offset #343
/*     */     //   Java source line #70	-> byte code offset #356
/*     */     //   Java source line #71	-> byte code offset #369
/*     */     //   Java source line #72	-> byte code offset #382
/*     */     //   Java source line #74	-> byte code offset #396
/*     */     //   Java source line #76	-> byte code offset #406
/*     */     //   Java source line #78	-> byte code offset #424
/*     */     //   Java source line #79	-> byte code offset #429
/*     */     //   Java source line #80	-> byte code offset #454
/*     */     //   Java source line #81	-> byte code offset #484
/*     */     //   Java source line #83	-> byte code offset #509
/*     */     //   Java source line #84	-> byte code offset #518
/*     */     //   Java source line #85	-> byte code offset #525
/*     */     //   Java source line #86	-> byte code offset #539
/*     */     //   Java source line #87	-> byte code offset #553
/*     */     //   Java source line #88	-> byte code offset #567
/*     */     //   Java source line #90	-> byte code offset #581
/*     */     //   Java source line #91	-> byte code offset #589
/*     */     //   Java source line #92	-> byte code offset #599
/*     */     //   Java source line #94	-> byte code offset #609
/*     */     //   Java source line #95	-> byte code offset #616
/*     */     //   Java source line #97	-> byte code offset #628
/*     */     //   Java source line #98	-> byte code offset #651
/*     */     //   Java source line #97	-> byte code offset #660
/*     */     //   Java source line #101	-> byte code offset #666
/*     */     //   Java source line #102	-> byte code offset #675
/*     */     //   Java source line #103	-> byte code offset #682
/*     */     //   Java source line #104	-> byte code offset #696
/*     */     //   Java source line #105	-> byte code offset #710
/*     */     //   Java source line #106	-> byte code offset #724
/*     */     //   Java source line #108	-> byte code offset #738
/*     */     //   Java source line #109	-> byte code offset #746
/*     */     //   Java source line #110	-> byte code offset #756
/*     */     //   Java source line #112	-> byte code offset #766
/*     */     //   Java source line #113	-> byte code offset #773
/*     */     //   Java source line #116	-> byte code offset #785
/*     */     //   Java source line #119	-> byte code offset #814
/*     */     //   Java source line #120	-> byte code offset #864
/*     */     //   Java source line #121	-> byte code offset #917
/*     */     //   Java source line #122	-> byte code offset #919
/*     */     //   Java source line #123	-> byte code offset #931
/*     */     //   Java source line #124	-> byte code offset #968
/*     */     //   Java source line #125	-> byte code offset #970
/*     */     //   Java source line #126	-> byte code offset #982
/*     */     //   Java source line #127	-> byte code offset #1019
/*     */     //   Java source line #128	-> byte code offset #1021
/*     */     //   Java source line #129	-> byte code offset #1041
/*     */     //   Java source line #130	-> byte code offset #1061
/*     */     //   Java source line #131	-> byte code offset #1081
/*     */     //   Java source line #128	-> byte code offset #1084
/*     */     //   Java source line #129	-> byte code offset #1104
/*     */     //   Java source line #130	-> byte code offset #1124
/*     */     //   Java source line #132	-> byte code offset #1144
/*     */     // Local variable table:
/*     */     //   start	length	slot	name	signature
/*     */     //   0	1147	0	this	UsuarioDAO
/*     */     //   0	1147	1	numEmpleado	String
/*     */     //   0	1147	2	sIP	String
/*     */     //   0	1147	3	passActual	String
/*     */     //   0	1147	4	validaPwd	boolean
/*     */     //   16	1122	5	connection	Connection
/*     */     //   19	1099	6	preparedStatement	PreparedStatement
/*     */     //   22	1076	7	resultSet	ResultSet
/*     */     //   31	267	8	sQuery	StringBuffer
/*     */     //   88	1057	9	usuarioTO	UsuarioTO
/*     */     //   93	810	10	inicioProceso	long
/*     */     //   917	46	10	e	SQLException
/*     */     //   968	46	10	e	Exception
/*     */     //   248	605	12	inicioConsulta	long
/*     */     //   404	336	14	idPerfiln	int
/*     */     //   516	96	15	perfilTO	com.claro.transfer.PerfilTO
/*     */     //   673	96	15	perfilTO	com.claro.transfer.PerfilTO
/*     */     //   587	15	16	perfiles	com.claro.transfer.PerfilTO
/*     */     //   744	15	16	perfiles	com.claro.transfer.PerfilTO
/*     */     //   1019	63	17	localObject	Object
/*     */     //   1039	1	18	localException1	Exception
/*     */     //   1059	1	18	localException2	Exception
/*     */     //   1079	1	18	localException3	Exception
/*     */     //   1102	1	18	localException4	Exception
/*     */     //   1122	1	18	localException5	Exception
/*     */     //   1142	1	18	localException6	Exception
/*     */     // Exception table:
/*     */     //   from	to	target	type
/*     */     //   90	914	917	java/sql/SQLException
/*     */     //   90	914	968	java/lang/Exception
/*     */     //   90	1019	1019	finally
/*     */     //   1026	1036	1039	java/lang/Exception
/*     */     //   1046	1056	1059	java/lang/Exception
/*     */     //   1066	1076	1079	java/lang/Exception
/*     */     //   1089	1099	1102	java/lang/Exception
/*     */     //   1109	1119	1122	java/lang/Exception
/*     */     //   1129	1139	1142	java/lang/Exception
/*     */   }
/*     */   
/*     */   /* Error */
/*     */   public com.claro.transfer.PerfilTO getPrivilegiosCirculoAzulEcac(int idPerfiln)
/*     */     throws CAException
/*     */   {
/*     */     // Byte code:
/*     */     //   0: new 220	com/claro/transfer/PerfilTO
/*     */     //   3: dup
/*     */     //   4: invokespecial 222	com/claro/transfer/PerfilTO:<init>	()V
/*     */     //   7: astore_2
/*     */     //   8: aconst_null
/*     */     //   9: astore_3
/*     */     //   10: aconst_null
/*     */     //   11: astore 4
/*     */     //   13: aconst_null
/*     */     //   14: astore 5
/*     */     //   16: new 66	java/lang/StringBuffer
/*     */     //   19: dup
/*     */     //   20: invokespecial 68	java/lang/StringBuffer:<init>	()V
/*     */     //   23: astore 6
/*     */     //   25: new 66	java/lang/StringBuffer
/*     */     //   28: dup
/*     */     //   29: invokespecial 68	java/lang/StringBuffer:<init>	()V
/*     */     //   32: astore 6
/*     */     //   34: aload 6
/*     */     //   36: ldc_w 325
/*     */     //   39: invokevirtual 71	java/lang/StringBuffer:append	(Ljava/lang/String;)Ljava/lang/StringBuffer;
/*     */     //   42: pop
/*     */     //   43: aload 6
/*     */     //   45: ldc 75
/*     */     //   47: invokevirtual 71	java/lang/StringBuffer:append	(Ljava/lang/String;)Ljava/lang/StringBuffer;
/*     */     //   50: aload_0
/*     */     //   51: getfield 41	com/claro/dao/UsuarioDAO:schema_database	Ljava/lang/String;
/*     */     //   54: invokevirtual 71	java/lang/StringBuffer:append	(Ljava/lang/String;)Ljava/lang/StringBuffer;
/*     */     //   57: ldc_w 327
/*     */     //   60: invokevirtual 71	java/lang/StringBuffer:append	(Ljava/lang/String;)Ljava/lang/StringBuffer;
/*     */     //   63: pop
/*     */     //   64: aload 6
/*     */     //   66: aload_0
/*     */     //   67: getfield 41	com/claro/dao/UsuarioDAO:schema_database	Ljava/lang/String;
/*     */     //   70: invokevirtual 71	java/lang/StringBuffer:append	(Ljava/lang/String;)Ljava/lang/StringBuffer;
/*     */     //   73: ldc_w 329
/*     */     //   76: invokevirtual 71	java/lang/StringBuffer:append	(Ljava/lang/String;)Ljava/lang/StringBuffer;
/*     */     //   79: pop
/*     */     //   80: aload 6
/*     */     //   82: ldc_w 331
/*     */     //   85: invokevirtual 71	java/lang/StringBuffer:append	(Ljava/lang/String;)Ljava/lang/StringBuffer;
/*     */     //   88: pop
/*     */     //   89: aload 6
/*     */     //   91: ldc_w 333
/*     */     //   94: invokevirtual 71	java/lang/StringBuffer:append	(Ljava/lang/String;)Ljava/lang/StringBuffer;
/*     */     //   97: pop
/*     */     //   98: invokestatic 29	com/claro/util/ServiceLocator:getInstance	()Lcom/claro/util/ServiceLocator;
/*     */     //   101: getstatic 132	com/claro/util/ServiceLocator:jdbcCirculoAzul	Ljava/lang/String;
/*     */     //   104: invokevirtual 135	com/claro/util/ServiceLocator:getConnection	(Ljava/lang/String;)Ljava/sql/Connection;
/*     */     //   107: astore_3
/*     */     //   108: aload_3
/*     */     //   109: aload 6
/*     */     //   111: invokevirtual 143	java/lang/StringBuffer:toString	()Ljava/lang/String;
/*     */     //   114: invokeinterface 144 2 0
/*     */     //   119: astore 4
/*     */     //   121: aload 4
/*     */     //   123: iconst_1
/*     */     //   124: iload_1
/*     */     //   125: invokeinterface 335 3 0
/*     */     //   130: aload 4
/*     */     //   132: invokeinterface 155 1 0
/*     */     //   137: astore 5
/*     */     //   139: new 339	java/util/Hashtable
/*     */     //   142: dup
/*     */     //   143: invokespecial 341	java/util/Hashtable:<init>	()V
/*     */     //   146: astore 7
/*     */     //   148: goto +80 -> 228
/*     */     //   151: new 342	com/claro/transfer/PrivilegioTO
/*     */     //   154: dup
/*     */     //   155: invokespecial 344	com/claro/transfer/PrivilegioTO:<init>	()V
/*     */     //   158: astore 8
/*     */     //   160: aload 8
/*     */     //   162: aload 5
/*     */     //   164: iconst_1
/*     */     //   165: invokeinterface 184 2 0
/*     */     //   170: invokevirtual 345	com/claro/transfer/PrivilegioTO:setIdProceso	(I)V
/*     */     //   173: aload 8
/*     */     //   175: aload 5
/*     */     //   177: iconst_2
/*     */     //   178: invokeinterface 168 2 0
/*     */     //   183: invokevirtual 348	com/claro/transfer/PrivilegioTO:setNombre	(Ljava/lang/String;)V
/*     */     //   186: aload 8
/*     */     //   188: aload 5
/*     */     //   190: iconst_3
/*     */     //   191: invokeinterface 168 2 0
/*     */     //   196: invokevirtual 349	com/claro/transfer/PrivilegioTO:setTipo	(Ljava/lang/String;)V
/*     */     //   199: aload 8
/*     */     //   201: aload 5
/*     */     //   203: iconst_4
/*     */     //   204: invokeinterface 168 2 0
/*     */     //   209: invokevirtual 352	com/claro/transfer/PrivilegioTO:setEstatus	(Ljava/lang/String;)V
/*     */     //   212: aload 7
/*     */     //   214: aload 8
/*     */     //   216: invokevirtual 355	com/claro/transfer/PrivilegioTO:getIdProceso	()I
/*     */     //   219: invokestatic 359	java/lang/String:valueOf	(I)Ljava/lang/String;
/*     */     //   222: aload 8
/*     */     //   224: invokevirtual 362	java/util/Hashtable:put	(Ljava/lang/Object;Ljava/lang/Object;)Ljava/lang/Object;
/*     */     //   227: pop
/*     */     //   228: aload 5
/*     */     //   230: invokeinterface 159 1 0
/*     */     //   235: ifne -84 -> 151
/*     */     //   238: aload_2
/*     */     //   239: aload 7
/*     */     //   241: invokevirtual 247	com/claro/transfer/PerfilTO:setPrivilegiosCa	(Ljava/util/Hashtable;)V
/*     */     //   244: aload 5
/*     */     //   246: ifnull +13 -> 259
/*     */     //   249: aload 5
/*     */     //   251: invokeinterface 294 1 0
/*     */     //   256: aconst_null
/*     */     //   257: astore 5
/*     */     //   259: aload 4
/*     */     //   261: ifnull +13 -> 274
/*     */     //   264: aload 4
/*     */     //   266: invokeinterface 297 1 0
/*     */     //   271: aconst_null
/*     */     //   272: astore 4
/*     */     //   274: new 66	java/lang/StringBuffer
/*     */     //   277: dup
/*     */     //   278: invokespecial 68	java/lang/StringBuffer:<init>	()V
/*     */     //   281: astore 6
/*     */     //   283: aload 6
/*     */     //   285: ldc_w 325
/*     */     //   288: invokevirtual 71	java/lang/StringBuffer:append	(Ljava/lang/String;)Ljava/lang/StringBuffer;
/*     */     //   291: pop
/*     */     //   292: aload 6
/*     */     //   294: ldc 75
/*     */     //   296: invokevirtual 71	java/lang/StringBuffer:append	(Ljava/lang/String;)Ljava/lang/StringBuffer;
/*     */     //   299: aload_0
/*     */     //   300: getfield 41	com/claro/dao/UsuarioDAO:schema_database	Ljava/lang/String;
/*     */     //   303: invokevirtual 71	java/lang/StringBuffer:append	(Ljava/lang/String;)Ljava/lang/StringBuffer;
/*     */     //   306: ldc_w 327
/*     */     //   309: invokevirtual 71	java/lang/StringBuffer:append	(Ljava/lang/String;)Ljava/lang/StringBuffer;
/*     */     //   312: pop
/*     */     //   313: aload 6
/*     */     //   315: aload_0
/*     */     //   316: getfield 41	com/claro/dao/UsuarioDAO:schema_database	Ljava/lang/String;
/*     */     //   319: invokevirtual 71	java/lang/StringBuffer:append	(Ljava/lang/String;)Ljava/lang/StringBuffer;
/*     */     //   322: ldc_w 329
/*     */     //   325: invokevirtual 71	java/lang/StringBuffer:append	(Ljava/lang/String;)Ljava/lang/StringBuffer;
/*     */     //   328: pop
/*     */     //   329: aload 6
/*     */     //   331: ldc_w 331
/*     */     //   334: invokevirtual 71	java/lang/StringBuffer:append	(Ljava/lang/String;)Ljava/lang/StringBuffer;
/*     */     //   337: pop
/*     */     //   338: aload 6
/*     */     //   340: ldc_w 366
/*     */     //   343: invokevirtual 71	java/lang/StringBuffer:append	(Ljava/lang/String;)Ljava/lang/StringBuffer;
/*     */     //   346: pop
/*     */     //   347: aload_3
/*     */     //   348: aload 6
/*     */     //   350: invokevirtual 143	java/lang/StringBuffer:toString	()Ljava/lang/String;
/*     */     //   353: invokeinterface 144 2 0
/*     */     //   358: astore 4
/*     */     //   360: aload 4
/*     */     //   362: iconst_1
/*     */     //   363: iload_1
/*     */     //   364: invokeinterface 335 3 0
/*     */     //   369: aload 4
/*     */     //   371: invokeinterface 155 1 0
/*     */     //   376: astore 5
/*     */     //   378: new 339	java/util/Hashtable
/*     */     //   381: dup
/*     */     //   382: invokespecial 341	java/util/Hashtable:<init>	()V
/*     */     //   385: astore 8
/*     */     //   387: goto +80 -> 467
/*     */     //   390: new 342	com/claro/transfer/PrivilegioTO
/*     */     //   393: dup
/*     */     //   394: invokespecial 344	com/claro/transfer/PrivilegioTO:<init>	()V
/*     */     //   397: astore 9
/*     */     //   399: aload 9
/*     */     //   401: aload 5
/*     */     //   403: iconst_1
/*     */     //   404: invokeinterface 184 2 0
/*     */     //   409: invokevirtual 345	com/claro/transfer/PrivilegioTO:setIdProceso	(I)V
/*     */     //   412: aload 9
/*     */     //   414: aload 5
/*     */     //   416: iconst_2
/*     */     //   417: invokeinterface 168 2 0
/*     */     //   422: invokevirtual 348	com/claro/transfer/PrivilegioTO:setNombre	(Ljava/lang/String;)V
/*     */     //   425: aload 9
/*     */     //   427: aload 5
/*     */     //   429: iconst_3
/*     */     //   430: invokeinterface 168 2 0
/*     */     //   435: invokevirtual 349	com/claro/transfer/PrivilegioTO:setTipo	(Ljava/lang/String;)V
/*     */     //   438: aload 9
/*     */     //   440: aload 5
/*     */     //   442: iconst_4
/*     */     //   443: invokeinterface 168 2 0
/*     */     //   448: invokevirtual 352	com/claro/transfer/PrivilegioTO:setEstatus	(Ljava/lang/String;)V
/*     */     //   451: aload 8
/*     */     //   453: aload 9
/*     */     //   455: invokevirtual 355	com/claro/transfer/PrivilegioTO:getIdProceso	()I
/*     */     //   458: invokestatic 359	java/lang/String:valueOf	(I)Ljava/lang/String;
/*     */     //   461: aload 9
/*     */     //   463: invokevirtual 362	java/util/Hashtable:put	(Ljava/lang/Object;Ljava/lang/Object;)Ljava/lang/Object;
/*     */     //   466: pop
/*     */     //   467: aload 5
/*     */     //   469: invokeinterface 159 1 0
/*     */     //   474: ifne -84 -> 390
/*     */     //   477: aload_2
/*     */     //   478: aload 8
/*     */     //   480: invokevirtual 254	com/claro/transfer/PerfilTO:setPrivilegiosEcac	(Ljava/util/Hashtable;)V
/*     */     //   483: goto +167 -> 650
/*     */     //   486: astore 7
/*     */     //   488: aload_0
/*     */     //   489: getfield 27	com/claro/dao/UsuarioDAO:error	Lorg/apache/log4j/Logger;
/*     */     //   492: ldc_w 368
/*     */     //   495: aload 7
/*     */     //   497: invokevirtual 279	org/apache/log4j/Logger:info	(Ljava/lang/Object;Ljava/lang/Throwable;)V
/*     */     //   500: new 59	com/claro/exception/CAException
/*     */     //   503: dup
/*     */     //   504: iconst_m1
/*     */     //   505: new 92	java/lang/StringBuilder
/*     */     //   508: dup
/*     */     //   509: ldc_w 370
/*     */     //   512: invokespecial 96	java/lang/StringBuilder:<init>	(Ljava/lang/String;)V
/*     */     //   515: aload 7
/*     */     //   517: invokevirtual 283	java/sql/SQLException:toString	()Ljava/lang/String;
/*     */     //   520: invokevirtual 114	java/lang/StringBuilder:append	(Ljava/lang/String;)Ljava/lang/StringBuilder;
/*     */     //   523: ldc -41
/*     */     //   525: invokevirtual 114	java/lang/StringBuilder:append	(Ljava/lang/String;)Ljava/lang/StringBuilder;
/*     */     //   528: invokevirtual 122	java/lang/StringBuilder:toString	()Ljava/lang/String;
/*     */     //   531: aload 7
/*     */     //   533: invokespecial 286	com/claro/exception/CAException:<init>	(ILjava/lang/String;Ljava/lang/Exception;)V
/*     */     //   536: athrow
/*     */     //   537: astore 7
/*     */     //   539: aload_0
/*     */     //   540: getfield 27	com/claro/dao/UsuarioDAO:error	Lorg/apache/log4j/Logger;
/*     */     //   543: ldc_w 368
/*     */     //   546: aload 7
/*     */     //   548: invokevirtual 279	org/apache/log4j/Logger:info	(Ljava/lang/Object;Ljava/lang/Throwable;)V
/*     */     //   551: new 59	com/claro/exception/CAException
/*     */     //   554: dup
/*     */     //   555: iconst_m1
/*     */     //   556: new 92	java/lang/StringBuilder
/*     */     //   559: dup
/*     */     //   560: ldc_w 370
/*     */     //   563: invokespecial 96	java/lang/StringBuilder:<init>	(Ljava/lang/String;)V
/*     */     //   566: aload 7
/*     */     //   568: invokevirtual 293	java/lang/Exception:toString	()Ljava/lang/String;
/*     */     //   571: invokevirtual 114	java/lang/StringBuilder:append	(Ljava/lang/String;)Ljava/lang/StringBuilder;
/*     */     //   574: ldc -41
/*     */     //   576: invokevirtual 114	java/lang/StringBuilder:append	(Ljava/lang/String;)Ljava/lang/StringBuilder;
/*     */     //   579: invokevirtual 122	java/lang/StringBuilder:toString	()Ljava/lang/String;
/*     */     //   582: aload 7
/*     */     //   584: invokespecial 286	com/claro/exception/CAException:<init>	(ILjava/lang/String;Ljava/lang/Exception;)V
/*     */     //   587: athrow
/*     */     //   588: astore 10
/*     */     //   590: aload 5
/*     */     //   592: ifnull +18 -> 610
/*     */     //   595: aload 5
/*     */     //   597: invokeinterface 294 1 0
/*     */     //   602: aconst_null
/*     */     //   603: astore 5
/*     */     //   605: goto +5 -> 610
/*     */     //   608: astore 11
/*     */     //   610: aload 4
/*     */     //   612: ifnull +18 -> 630
/*     */     //   615: aload 4
/*     */     //   617: invokeinterface 297 1 0
/*     */     //   622: aconst_null
/*     */     //   623: astore 4
/*     */     //   625: goto +5 -> 630
/*     */     //   628: astore 11
/*     */     //   630: aload_3
/*     */     //   631: ifnull +16 -> 647
/*     */     //   634: aload_3
/*     */     //   635: invokeinterface 298 1 0
/*     */     //   640: aconst_null
/*     */     //   641: astore_3
/*     */     //   642: goto +5 -> 647
/*     */     //   645: astore 11
/*     */     //   647: aload 10
/*     */     //   649: athrow
/*     */     //   650: aload 5
/*     */     //   652: ifnull +18 -> 670
/*     */     //   655: aload 5
/*     */     //   657: invokeinterface 294 1 0
/*     */     //   662: aconst_null
/*     */     //   663: astore 5
/*     */     //   665: goto +5 -> 670
/*     */     //   668: astore 11
/*     */     //   670: aload 4
/*     */     //   672: ifnull +18 -> 690
/*     */     //   675: aload 4
/*     */     //   677: invokeinterface 297 1 0
/*     */     //   682: aconst_null
/*     */     //   683: astore 4
/*     */     //   685: goto +5 -> 690
/*     */     //   688: astore 11
/*     */     //   690: aload_3
/*     */     //   691: ifnull +16 -> 707
/*     */     //   694: aload_3
/*     */     //   695: invokeinterface 298 1 0
/*     */     //   700: aconst_null
/*     */     //   701: astore_3
/*     */     //   702: goto +5 -> 707
/*     */     //   705: astore 11
/*     */     //   707: aload_2
/*     */     //   708: areturn
/*     */     // Line number table:
/*     */     //   Java source line #137	-> byte code offset #0
/*     */     //   Java source line #138	-> byte code offset #8
/*     */     //   Java source line #139	-> byte code offset #10
/*     */     //   Java source line #140	-> byte code offset #13
/*     */     //   Java source line #141	-> byte code offset #16
/*     */     //   Java source line #145	-> byte code offset #25
/*     */     //   Java source line #146	-> byte code offset #34
/*     */     //   Java source line #147	-> byte code offset #43
/*     */     //   Java source line #148	-> byte code offset #64
/*     */     //   Java source line #149	-> byte code offset #80
/*     */     //   Java source line #150	-> byte code offset #89
/*     */     //   Java source line #152	-> byte code offset #98
/*     */     //   Java source line #153	-> byte code offset #108
/*     */     //   Java source line #155	-> byte code offset #121
/*     */     //   Java source line #156	-> byte code offset #130
/*     */     //   Java source line #158	-> byte code offset #139
/*     */     //   Java source line #159	-> byte code offset #148
/*     */     //   Java source line #160	-> byte code offset #151
/*     */     //   Java source line #161	-> byte code offset #160
/*     */     //   Java source line #162	-> byte code offset #173
/*     */     //   Java source line #163	-> byte code offset #186
/*     */     //   Java source line #164	-> byte code offset #199
/*     */     //   Java source line #165	-> byte code offset #212
/*     */     //   Java source line #159	-> byte code offset #228
/*     */     //   Java source line #167	-> byte code offset #238
/*     */     //   Java source line #168	-> byte code offset #244
/*     */     //   Java source line #169	-> byte code offset #259
/*     */     //   Java source line #172	-> byte code offset #274
/*     */     //   Java source line #173	-> byte code offset #283
/*     */     //   Java source line #174	-> byte code offset #292
/*     */     //   Java source line #175	-> byte code offset #313
/*     */     //   Java source line #176	-> byte code offset #329
/*     */     //   Java source line #177	-> byte code offset #338
/*     */     //   Java source line #179	-> byte code offset #347
/*     */     //   Java source line #180	-> byte code offset #360
/*     */     //   Java source line #181	-> byte code offset #369
/*     */     //   Java source line #183	-> byte code offset #378
/*     */     //   Java source line #184	-> byte code offset #387
/*     */     //   Java source line #185	-> byte code offset #390
/*     */     //   Java source line #186	-> byte code offset #399
/*     */     //   Java source line #187	-> byte code offset #412
/*     */     //   Java source line #188	-> byte code offset #425
/*     */     //   Java source line #189	-> byte code offset #438
/*     */     //   Java source line #190	-> byte code offset #451
/*     */     //   Java source line #184	-> byte code offset #467
/*     */     //   Java source line #192	-> byte code offset #477
/*     */     //   Java source line #193	-> byte code offset #486
/*     */     //   Java source line #194	-> byte code offset #488
/*     */     //   Java source line #195	-> byte code offset #500
/*     */     //   Java source line #196	-> byte code offset #537
/*     */     //   Java source line #197	-> byte code offset #539
/*     */     //   Java source line #198	-> byte code offset #551
/*     */     //   Java source line #199	-> byte code offset #588
/*     */     //   Java source line #200	-> byte code offset #590
/*     */     //   Java source line #201	-> byte code offset #610
/*     */     //   Java source line #202	-> byte code offset #630
/*     */     //   Java source line #203	-> byte code offset #647
/*     */     //   Java source line #200	-> byte code offset #650
/*     */     //   Java source line #201	-> byte code offset #670
/*     */     //   Java source line #202	-> byte code offset #690
/*     */     //   Java source line #205	-> byte code offset #707
/*     */     // Local variable table:
/*     */     //   start	length	slot	name	signature
/*     */     //   0	709	0	this	UsuarioDAO
/*     */     //   0	709	1	idPerfiln	int
/*     */     //   7	701	2	perfilTO	com.claro.transfer.PerfilTO
/*     */     //   9	693	3	conn	Connection
/*     */     //   11	673	4	stmt	PreparedStatement
/*     */     //   14	650	5	resultSet	ResultSet
/*     */     //   23	326	6	sQuery	StringBuffer
/*     */     //   146	94	7	privilegiosCa	java.util.Hashtable<String, com.claro.transfer.PrivilegioTO>
/*     */     //   486	46	7	e	SQLException
/*     */     //   537	46	7	e	Exception
/*     */     //   158	65	8	privilegioTO	com.claro.transfer.PrivilegioTO
/*     */     //   385	94	8	privilegiosEcac	java.util.Hashtable<String, com.claro.transfer.PrivilegioTO>
/*     */     //   397	65	9	privilegioTO	com.claro.transfer.PrivilegioTO
/*     */     //   588	60	10	localObject	Object
/*     */     //   608	1	11	localException1	Exception
/*     */     //   628	1	11	localException2	Exception
/*     */     //   645	1	11	localException3	Exception
/*     */     //   668	1	11	localException4	Exception
/*     */     //   688	1	11	localException5	Exception
/*     */     //   705	1	11	localException6	Exception
/*     */     // Exception table:
/*     */     //   from	to	target	type
/*     */     //   25	483	486	java/sql/SQLException
/*     */     //   25	483	537	java/lang/Exception
/*     */     //   25	588	588	finally
/*     */     //   595	605	608	java/lang/Exception
/*     */     //   615	625	628	java/lang/Exception
/*     */     //   634	642	645	java/lang/Exception
/*     */     //   655	665	668	java/lang/Exception
/*     */     //   675	685	688	java/lang/Exception
/*     */     //   694	702	705	java/lang/Exception
/*     */   }
/*     */   
/*     */   public UsuarioTO validaUserPerfil(String lClave, String sIP)
/*     */     throws CAException
/*     */   {
/* 209 */     Connection connection = null;
/* 210 */     PreparedStatement preparedStatement = null;
/* 211 */     ResultSet resultSet = null;
/*     */     try {
/* 213 */       if ((lClave == null) || (lClave.equals(null)) || (lClave.equals("")))
/* 214 */         throw new CAException(-1, "Debe ingresar su CLAVE de usuario.");
/* 215 */       if ((sIP == null) || (sIP.equals(null)) || (sIP.equals(""))) {
/* 216 */         throw new CAException(-1, "Error al obtener la Direccion IP de la PC.");
/*     */       }
/*     */       
/*     */ 
/* 220 */       String sQuery = "SELECT IDUSUARIO, NOMBRE, IDPERFIL FROM " + this.schema_database + "PTO_CTLUSUARIOS WHERE IDUSUARIO = ?  AND STATUS ='A' ";
/* 221 */       long inicioProceso = System.currentTimeMillis();
/* 222 */       this.logger.info("validaUserPerfil|Inicio Proceso|" + Constantes.DATEFORMTALog.format(new Date()) + "|" + inicioProceso);
/* 223 */       this.logger.info("validaUserPerfil|Antes de Conexion|" + Constantes.DATEFORMTALog.format(new Date()) + "|" + inicioProceso);
/* 224 */       connection = ServiceLocator.getInstance().getConnection(ServiceLocator.jdbcCirculoAzul);
/* 225 */       this.logger.info("validaUserPerfil|Despues de Conexion|" + Constantes.DATEFORMTALog.format(new Date()) + "|" + (System.currentTimeMillis() - inicioProceso));
/* 226 */       long inicioConsulta = System.currentTimeMillis();
/* 227 */       this.logger.info("validaUserPerfil|InicioConsulta|" + Constantes.DATEFORMTALog.format(new Date()) + "|" + inicioConsulta);
/* 228 */       connection = ServiceLocator.getInstance().getConnection(ServiceLocator.jdbcCirculoAzul);
/* 229 */       preparedStatement = connection.prepareStatement(sQuery);
/* 230 */       preparedStatement.setString(1, lClave.toUpperCase());
/* 231 */       resultSet = preparedStatement.executeQuery();
/*     */       
/* 233 */       if (resultSet.next()) {
/* 234 */         UsuarioTO usuarioTO = new UsuarioTO();
/* 235 */         usuarioTO.setIdUsuario(resultSet.getString(1));
/* 236 */         usuarioTO.setNombre(resultSet.getString(2));
/*     */         
/*     */ 
/* 239 */         usuarioTO.setPuntoVentaTO(new ConsultasDAO().obtienePuntoVenta(sIP, connection));
/* 240 */         this.logger.info("validaUserPerfil|FinConsulta|" + Constantes.DATEFORMTALog.format(new Date()) + "|" + (System.currentTimeMillis() - inicioConsulta));
/* 241 */         this.logger.info("validaUserPerfil|FinProceso|" + Constantes.DATEFORMTALog.format(new Date()) + "|" + (System.currentTimeMillis() - inicioProceso));
/* 242 */         return usuarioTO; }
/* 243 */       throw new CAException(-1, "La clave de Usuario no se encuentra en el Sistema de Puntos.");
/*     */     }
/*     */     catch (SQLException e)
/*     */     {
/* 247 */       this.error.info("SQLException.validaUserPerfil:", e);
/* 248 */       throw new CAException(-1, "SQLException.validaUserPerfil[" + e.toString() + "]", e);
/*     */     } catch (Exception e) {
/* 250 */       this.error.info("Exception.validaUserPerfil:", e);
/* 251 */       throw new CAException(-1, "UsuarioDAO.validaUserPerfil[" + e.toString() + "]", e);
/*     */     } finally {
/* 253 */       if (resultSet != null) try { resultSet.close();resultSet = null; } catch (Exception localException4) {}
/* 254 */       if (preparedStatement != null) try { preparedStatement.close();preparedStatement = null; } catch (Exception localException5) {}
/* 255 */       if (connection != null) try { connection.close();connection = null;
/*     */         }
/*     */         catch (Exception localException6) {}
/*     */     }
/*     */   }
/*     */   
/*     */   /* Error */
/*     */   public boolean agregaUsuario(UsuarioTO usuarioTO)
/*     */     throws Exception
/*     */   {
/*     */     // Byte code:
/*     */     //   0: iconst_0
/*     */     //   1: istore_2
/*     */     //   2: aconst_null
/*     */     //   3: astore_3
/*     */     //   4: aconst_null
/*     */     //   5: astore 4
/*     */     //   7: aconst_null
/*     */     //   8: astore 5
/*     */     //   10: invokestatic 29	com/claro/util/ServiceLocator:getInstance	()Lcom/claro/util/ServiceLocator;
/*     */     //   13: getstatic 132	com/claro/util/ServiceLocator:jdbcCirculoAzul	Ljava/lang/String;
/*     */     //   16: invokevirtual 135	com/claro/util/ServiceLocator:getConnection	(Ljava/lang/String;)Ljava/sql/Connection;
/*     */     //   19: astore_3
/*     */     //   20: new 66	java/lang/StringBuffer
/*     */     //   23: dup
/*     */     //   24: invokespecial 68	java/lang/StringBuffer:<init>	()V
/*     */     //   27: astore 6
/*     */     //   29: aload 6
/*     */     //   31: ldc_w 421
/*     */     //   34: invokevirtual 71	java/lang/StringBuffer:append	(Ljava/lang/String;)Ljava/lang/StringBuffer;
/*     */     //   37: aload_0
/*     */     //   38: getfield 41	com/claro/dao/UsuarioDAO:schema_database	Ljava/lang/String;
/*     */     //   41: invokevirtual 71	java/lang/StringBuffer:append	(Ljava/lang/String;)Ljava/lang/StringBuffer;
/*     */     //   44: ldc_w 423
/*     */     //   47: invokevirtual 71	java/lang/StringBuffer:append	(Ljava/lang/String;)Ljava/lang/StringBuffer;
/*     */     //   50: pop
/*     */     //   51: aload 6
/*     */     //   53: ldc_w 425
/*     */     //   56: invokevirtual 71	java/lang/StringBuffer:append	(Ljava/lang/String;)Ljava/lang/StringBuffer;
/*     */     //   59: pop
/*     */     //   60: aload_3
/*     */     //   61: aload 6
/*     */     //   63: invokevirtual 143	java/lang/StringBuffer:toString	()Ljava/lang/String;
/*     */     //   66: invokeinterface 144 2 0
/*     */     //   71: astore 4
/*     */     //   73: aload 4
/*     */     //   75: iconst_1
/*     */     //   76: aload_1
/*     */     //   77: invokevirtual 427	com/claro/transfer/UsuarioTO:getIdUsuario	()Ljava/lang/String;
/*     */     //   80: invokeinterface 150 3 0
/*     */     //   85: aload 4
/*     */     //   87: invokeinterface 155 1 0
/*     */     //   92: astore 5
/*     */     //   94: iconst_0
/*     */     //   95: istore 7
/*     */     //   97: aload 5
/*     */     //   99: invokeinterface 159 1 0
/*     */     //   104: ifeq +6 -> 110
/*     */     //   107: iconst_1
/*     */     //   108: istore 7
/*     */     //   110: iload 7
/*     */     //   112: ifeq +14 -> 126
/*     */     //   115: new 47	java/lang/Exception
/*     */     //   118: dup
/*     */     //   119: ldc_w 430
/*     */     //   122: invokespecial 432	java/lang/Exception:<init>	(Ljava/lang/String;)V
/*     */     //   125: athrow
/*     */     //   126: new 66	java/lang/StringBuffer
/*     */     //   129: dup
/*     */     //   130: invokespecial 68	java/lang/StringBuffer:<init>	()V
/*     */     //   133: astore 6
/*     */     //   135: aload 6
/*     */     //   137: ldc_w 433
/*     */     //   140: invokevirtual 71	java/lang/StringBuffer:append	(Ljava/lang/String;)Ljava/lang/StringBuffer;
/*     */     //   143: aload_0
/*     */     //   144: getfield 41	com/claro/dao/UsuarioDAO:schema_database	Ljava/lang/String;
/*     */     //   147: invokevirtual 71	java/lang/StringBuffer:append	(Ljava/lang/String;)Ljava/lang/StringBuffer;
/*     */     //   150: ldc_w 435
/*     */     //   153: invokevirtual 71	java/lang/StringBuffer:append	(Ljava/lang/String;)Ljava/lang/StringBuffer;
/*     */     //   156: pop
/*     */     //   157: aload 6
/*     */     //   159: ldc_w 437
/*     */     //   162: invokevirtual 71	java/lang/StringBuffer:append	(Ljava/lang/String;)Ljava/lang/StringBuffer;
/*     */     //   165: pop
/*     */     //   166: aload 6
/*     */     //   168: ldc_w 439
/*     */     //   171: invokevirtual 71	java/lang/StringBuffer:append	(Ljava/lang/String;)Ljava/lang/StringBuffer;
/*     */     //   174: pop
/*     */     //   175: aload_3
/*     */     //   176: aload 6
/*     */     //   178: invokevirtual 143	java/lang/StringBuffer:toString	()Ljava/lang/String;
/*     */     //   181: invokeinterface 144 2 0
/*     */     //   186: astore 4
/*     */     //   188: aload 4
/*     */     //   190: iconst_1
/*     */     //   191: aload_1
/*     */     //   192: invokevirtual 441	com/claro/transfer/UsuarioTO:getNumEmpleado	()Ljava/lang/String;
/*     */     //   195: invokeinterface 150 3 0
/*     */     //   200: aload 4
/*     */     //   202: iconst_2
/*     */     //   203: aload_1
/*     */     //   204: invokevirtual 427	com/claro/transfer/UsuarioTO:getIdUsuario	()Ljava/lang/String;
/*     */     //   207: invokeinterface 150 3 0
/*     */     //   212: aload 4
/*     */     //   214: iconst_3
/*     */     //   215: aload_1
/*     */     //   216: invokevirtual 444	com/claro/transfer/UsuarioTO:getNombre	()Ljava/lang/String;
/*     */     //   219: invokeinterface 150 3 0
/*     */     //   224: aload 4
/*     */     //   226: iconst_4
/*     */     //   227: aload_1
/*     */     //   228: invokevirtual 199	com/claro/transfer/UsuarioTO:getPassword	()Ljava/lang/String;
/*     */     //   231: invokeinterface 150 3 0
/*     */     //   236: aload 4
/*     */     //   238: iconst_5
/*     */     //   239: aload_1
/*     */     //   240: invokevirtual 208	com/claro/transfer/UsuarioTO:getStatus	()Ljava/lang/String;
/*     */     //   243: invokeinterface 150 3 0
/*     */     //   248: aload 4
/*     */     //   250: bipush 6
/*     */     //   252: aload_1
/*     */     //   253: invokevirtual 447	com/claro/transfer/UsuarioTO:getIdUsuarioCaptura	()Ljava/lang/String;
/*     */     //   256: invokeinterface 150 3 0
/*     */     //   261: aload 4
/*     */     //   263: bipush 7
/*     */     //   265: aload_1
/*     */     //   266: invokevirtual 450	com/claro/transfer/UsuarioTO:getFechaUpdate	()Ljava/sql/Timestamp;
/*     */     //   269: invokeinterface 454 3 0
/*     */     //   274: aload 4
/*     */     //   276: bipush 8
/*     */     //   278: aload_1
/*     */     //   279: invokevirtual 458	com/claro/transfer/UsuarioTO:getSistemaAdmin	()Ljava/lang/String;
/*     */     //   282: invokeinterface 150 3 0
/*     */     //   287: aload 4
/*     */     //   289: bipush 9
/*     */     //   291: aload_1
/*     */     //   292: invokevirtual 461	com/claro/transfer/UsuarioTO:getFechaAdmin	()Ljava/sql/Timestamp;
/*     */     //   295: invokeinterface 454 3 0
/*     */     //   300: aload 4
/*     */     //   302: bipush 10
/*     */     //   304: aload_1
/*     */     //   305: invokevirtual 464	com/claro/transfer/UsuarioTO:getPerfilTO	()Lcom/claro/transfer/PerfilTO;
/*     */     //   308: invokevirtual 468	com/claro/transfer/PerfilTO:getIdPerfilN	()I
/*     */     //   311: invokeinterface 335 3 0
/*     */     //   316: aload 4
/*     */     //   318: bipush 11
/*     */     //   320: aload_1
/*     */     //   321: invokevirtual 464	com/claro/transfer/UsuarioTO:getPerfilTO	()Lcom/claro/transfer/PerfilTO;
/*     */     //   324: invokevirtual 471	com/claro/transfer/PerfilTO:getIdPuesto	()Ljava/lang/String;
/*     */     //   327: invokeinterface 150 3 0
/*     */     //   332: aload 4
/*     */     //   334: invokeinterface 474 1 0
/*     */     //   339: pop
/*     */     //   340: goto +96 -> 436
/*     */     //   343: astore 6
/*     */     //   345: new 47	java/lang/Exception
/*     */     //   348: dup
/*     */     //   349: new 92	java/lang/StringBuilder
/*     */     //   352: dup
/*     */     //   353: ldc_w 477
/*     */     //   356: invokespecial 96	java/lang/StringBuilder:<init>	(Ljava/lang/String;)V
/*     */     //   359: aload 6
/*     */     //   361: invokevirtual 293	java/lang/Exception:toString	()Ljava/lang/String;
/*     */     //   364: invokevirtual 114	java/lang/StringBuilder:append	(Ljava/lang/String;)Ljava/lang/StringBuilder;
/*     */     //   367: invokevirtual 122	java/lang/StringBuilder:toString	()Ljava/lang/String;
/*     */     //   370: invokespecial 432	java/lang/Exception:<init>	(Ljava/lang/String;)V
/*     */     //   373: athrow
/*     */     //   374: astore 8
/*     */     //   376: aload 4
/*     */     //   378: ifnull +18 -> 396
/*     */     //   381: aload 4
/*     */     //   383: invokeinterface 297 1 0
/*     */     //   388: aconst_null
/*     */     //   389: astore 4
/*     */     //   391: goto +5 -> 396
/*     */     //   394: astore 9
/*     */     //   396: aload 5
/*     */     //   398: ifnull +18 -> 416
/*     */     //   401: aload 5
/*     */     //   403: invokeinterface 294 1 0
/*     */     //   408: aconst_null
/*     */     //   409: astore 5
/*     */     //   411: goto +5 -> 416
/*     */     //   414: astore 9
/*     */     //   416: aload_3
/*     */     //   417: ifnull +16 -> 433
/*     */     //   420: aload_3
/*     */     //   421: invokeinterface 298 1 0
/*     */     //   426: aconst_null
/*     */     //   427: astore_3
/*     */     //   428: goto +5 -> 433
/*     */     //   431: astore 9
/*     */     //   433: aload 8
/*     */     //   435: athrow
/*     */     //   436: aload 4
/*     */     //   438: ifnull +18 -> 456
/*     */     //   441: aload 4
/*     */     //   443: invokeinterface 297 1 0
/*     */     //   448: aconst_null
/*     */     //   449: astore 4
/*     */     //   451: goto +5 -> 456
/*     */     //   454: astore 9
/*     */     //   456: aload 5
/*     */     //   458: ifnull +18 -> 476
/*     */     //   461: aload 5
/*     */     //   463: invokeinterface 294 1 0
/*     */     //   468: aconst_null
/*     */     //   469: astore 5
/*     */     //   471: goto +5 -> 476
/*     */     //   474: astore 9
/*     */     //   476: aload_3
/*     */     //   477: ifnull +16 -> 493
/*     */     //   480: aload_3
/*     */     //   481: invokeinterface 298 1 0
/*     */     //   486: aconst_null
/*     */     //   487: astore_3
/*     */     //   488: goto +5 -> 493
/*     */     //   491: astore 9
/*     */     //   493: iload_2
/*     */     //   494: ireturn
/*     */     // Line number table:
/*     */     //   Java source line #267	-> byte code offset #0
/*     */     //   Java source line #268	-> byte code offset #2
/*     */     //   Java source line #269	-> byte code offset #4
/*     */     //   Java source line #270	-> byte code offset #7
/*     */     //   Java source line #272	-> byte code offset #10
/*     */     //   Java source line #274	-> byte code offset #20
/*     */     //   Java source line #276	-> byte code offset #29
/*     */     //   Java source line #277	-> byte code offset #51
/*     */     //   Java source line #279	-> byte code offset #60
/*     */     //   Java source line #280	-> byte code offset #73
/*     */     //   Java source line #282	-> byte code offset #85
/*     */     //   Java source line #283	-> byte code offset #94
/*     */     //   Java source line #284	-> byte code offset #97
/*     */     //   Java source line #285	-> byte code offset #107
/*     */     //   Java source line #289	-> byte code offset #110
/*     */     //   Java source line #290	-> byte code offset #115
/*     */     //   Java source line #293	-> byte code offset #126
/*     */     //   Java source line #294	-> byte code offset #135
/*     */     //   Java source line #295	-> byte code offset #157
/*     */     //   Java source line #296	-> byte code offset #166
/*     */     //   Java source line #298	-> byte code offset #175
/*     */     //   Java source line #299	-> byte code offset #188
/*     */     //   Java source line #300	-> byte code offset #200
/*     */     //   Java source line #301	-> byte code offset #212
/*     */     //   Java source line #302	-> byte code offset #224
/*     */     //   Java source line #303	-> byte code offset #236
/*     */     //   Java source line #304	-> byte code offset #248
/*     */     //   Java source line #305	-> byte code offset #261
/*     */     //   Java source line #306	-> byte code offset #274
/*     */     //   Java source line #307	-> byte code offset #287
/*     */     //   Java source line #308	-> byte code offset #300
/*     */     //   Java source line #309	-> byte code offset #316
/*     */     //   Java source line #310	-> byte code offset #332
/*     */     //   Java source line #311	-> byte code offset #343
/*     */     //   Java source line #312	-> byte code offset #345
/*     */     //   Java source line #313	-> byte code offset #374
/*     */     //   Java source line #314	-> byte code offset #376
/*     */     //   Java source line #315	-> byte code offset #396
/*     */     //   Java source line #316	-> byte code offset #416
/*     */     //   Java source line #317	-> byte code offset #433
/*     */     //   Java source line #314	-> byte code offset #436
/*     */     //   Java source line #315	-> byte code offset #456
/*     */     //   Java source line #316	-> byte code offset #476
/*     */     //   Java source line #318	-> byte code offset #493
/*     */     // Local variable table:
/*     */     //   start	length	slot	name	signature
/*     */     //   0	495	0	this	UsuarioDAO
/*     */     //   0	495	1	usuarioTO	UsuarioTO
/*     */     //   1	493	2	accion	boolean
/*     */     //   3	485	3	conn	Connection
/*     */     //   5	445	4	prepStat	PreparedStatement
/*     */     //   8	462	5	resultSet	ResultSet
/*     */     //   27	150	6	query	StringBuffer
/*     */     //   343	17	6	ex	Exception
/*     */     //   95	16	7	existeIdUsuario	boolean
/*     */     //   374	60	8	localObject	Object
/*     */     //   394	1	9	localException1	Exception
/*     */     //   414	1	9	localException2	Exception
/*     */     //   431	1	9	localException3	Exception
/*     */     //   454	1	9	localException4	Exception
/*     */     //   474	1	9	localException5	Exception
/*     */     //   491	1	9	localException6	Exception
/*     */     // Exception table:
/*     */     //   from	to	target	type
/*     */     //   10	340	343	java/lang/Exception
/*     */     //   10	374	374	finally
/*     */     //   381	391	394	java/lang/Exception
/*     */     //   401	411	414	java/lang/Exception
/*     */     //   420	428	431	java/lang/Exception
/*     */     //   441	451	454	java/lang/Exception
/*     */     //   461	471	474	java/lang/Exception
/*     */     //   480	488	491	java/lang/Exception
/*     */   }
/*     */   
/*     */   /* Error */
/*     */   public boolean actualizaUsuario(UsuarioTO usuarioCA, UsuarioTO usuarioModificado, int perfilAnterior)
/*     */     throws Exception
/*     */   {
/*     */     // Byte code:
/*     */     //   0: iconst_0
/*     */     //   1: istore 4
/*     */     //   3: aconst_null
/*     */     //   4: astore 5
/*     */     //   6: aconst_null
/*     */     //   7: astore 6
/*     */     //   9: invokestatic 29	com/claro/util/ServiceLocator:getInstance	()Lcom/claro/util/ServiceLocator;
/*     */     //   12: getstatic 132	com/claro/util/ServiceLocator:jdbcCirculoAzul	Ljava/lang/String;
/*     */     //   15: invokevirtual 135	com/claro/util/ServiceLocator:getConnection	(Ljava/lang/String;)Ljava/sql/Connection;
/*     */     //   18: astore 5
/*     */     //   20: new 66	java/lang/StringBuffer
/*     */     //   23: dup
/*     */     //   24: invokespecial 68	java/lang/StringBuffer:<init>	()V
/*     */     //   27: astore 7
/*     */     //   29: aload_2
/*     */     //   30: invokevirtual 199	com/claro/transfer/UsuarioTO:getPassword	()Ljava/lang/String;
/*     */     //   33: ifnull +228 -> 261
/*     */     //   36: aload 7
/*     */     //   38: ldc_w 486
/*     */     //   41: invokevirtual 71	java/lang/StringBuffer:append	(Ljava/lang/String;)Ljava/lang/StringBuffer;
/*     */     //   44: aload_0
/*     */     //   45: getfield 41	com/claro/dao/UsuarioDAO:schema_database	Ljava/lang/String;
/*     */     //   48: invokevirtual 71	java/lang/StringBuffer:append	(Ljava/lang/String;)Ljava/lang/StringBuffer;
/*     */     //   51: ldc_w 488
/*     */     //   54: invokevirtual 71	java/lang/StringBuffer:append	(Ljava/lang/String;)Ljava/lang/StringBuffer;
/*     */     //   57: pop
/*     */     //   58: aload 7
/*     */     //   60: ldc_w 490
/*     */     //   63: invokevirtual 71	java/lang/StringBuffer:append	(Ljava/lang/String;)Ljava/lang/StringBuffer;
/*     */     //   66: pop
/*     */     //   67: aload 7
/*     */     //   69: ldc_w 492
/*     */     //   72: invokevirtual 71	java/lang/StringBuffer:append	(Ljava/lang/String;)Ljava/lang/StringBuffer;
/*     */     //   75: pop
/*     */     //   76: aload 7
/*     */     //   78: ldc_w 494
/*     */     //   81: invokevirtual 71	java/lang/StringBuffer:append	(Ljava/lang/String;)Ljava/lang/StringBuffer;
/*     */     //   84: pop
/*     */     //   85: aload 5
/*     */     //   87: aload 7
/*     */     //   89: invokevirtual 143	java/lang/StringBuffer:toString	()Ljava/lang/String;
/*     */     //   92: invokeinterface 144 2 0
/*     */     //   97: astore 6
/*     */     //   99: aload 6
/*     */     //   101: iconst_1
/*     */     //   102: aload_2
/*     */     //   103: invokevirtual 427	com/claro/transfer/UsuarioTO:getIdUsuario	()Ljava/lang/String;
/*     */     //   106: invokeinterface 150 3 0
/*     */     //   111: aload 6
/*     */     //   113: iconst_2
/*     */     //   114: aload_2
/*     */     //   115: invokevirtual 444	com/claro/transfer/UsuarioTO:getNombre	()Ljava/lang/String;
/*     */     //   118: invokeinterface 150 3 0
/*     */     //   123: aload 6
/*     */     //   125: iconst_3
/*     */     //   126: aconst_null
/*     */     //   127: invokeinterface 150 3 0
/*     */     //   132: aload 6
/*     */     //   134: iconst_4
/*     */     //   135: aload_2
/*     */     //   136: invokevirtual 208	com/claro/transfer/UsuarioTO:getStatus	()Ljava/lang/String;
/*     */     //   139: invokeinterface 150 3 0
/*     */     //   144: aload 6
/*     */     //   146: iconst_5
/*     */     //   147: aload_2
/*     */     //   148: invokevirtual 447	com/claro/transfer/UsuarioTO:getIdUsuarioCaptura	()Ljava/lang/String;
/*     */     //   151: invokeinterface 150 3 0
/*     */     //   156: aload 6
/*     */     //   158: bipush 6
/*     */     //   160: aload_2
/*     */     //   161: invokevirtual 450	com/claro/transfer/UsuarioTO:getFechaUpdate	()Ljava/sql/Timestamp;
/*     */     //   164: invokeinterface 454 3 0
/*     */     //   169: aload 6
/*     */     //   171: bipush 7
/*     */     //   173: aload_2
/*     */     //   174: invokevirtual 464	com/claro/transfer/UsuarioTO:getPerfilTO	()Lcom/claro/transfer/PerfilTO;
/*     */     //   177: invokevirtual 468	com/claro/transfer/PerfilTO:getIdPerfilN	()I
/*     */     //   180: invokeinterface 335 3 0
/*     */     //   185: aload 6
/*     */     //   187: bipush 8
/*     */     //   189: aload_2
/*     */     //   190: invokevirtual 464	com/claro/transfer/UsuarioTO:getPerfilTO	()Lcom/claro/transfer/PerfilTO;
/*     */     //   193: invokevirtual 471	com/claro/transfer/PerfilTO:getIdPuesto	()Ljava/lang/String;
/*     */     //   196: invokeinterface 150 3 0
/*     */     //   201: aload 6
/*     */     //   203: bipush 9
/*     */     //   205: aload_2
/*     */     //   206: invokevirtual 199	com/claro/transfer/UsuarioTO:getPassword	()Ljava/lang/String;
/*     */     //   209: invokevirtual 496	java/lang/String:trim	()Ljava/lang/String;
/*     */     //   212: invokeinterface 150 3 0
/*     */     //   217: aload 6
/*     */     //   219: bipush 10
/*     */     //   221: ldc_w 499
/*     */     //   224: invokeinterface 150 3 0
/*     */     //   229: aload 6
/*     */     //   231: bipush 11
/*     */     //   233: aload_2
/*     */     //   234: invokevirtual 441	com/claro/transfer/UsuarioTO:getNumEmpleado	()Ljava/lang/String;
/*     */     //   237: invokeinterface 150 3 0
/*     */     //   242: aload 6
/*     */     //   244: invokeinterface 474 1 0
/*     */     //   249: pop
/*     */     //   250: aload_2
/*     */     //   251: iconst_0
/*     */     //   252: ldc_w 261
/*     */     //   255: invokevirtual 217	com/claro/transfer/UsuarioTO:agregaMensaje	(ILjava/lang/String;)V
/*     */     //   258: goto +178 -> 436
/*     */     //   261: aload 7
/*     */     //   263: ldc_w 486
/*     */     //   266: invokevirtual 71	java/lang/StringBuffer:append	(Ljava/lang/String;)Ljava/lang/StringBuffer;
/*     */     //   269: aload_0
/*     */     //   270: getfield 41	com/claro/dao/UsuarioDAO:schema_database	Ljava/lang/String;
/*     */     //   273: invokevirtual 71	java/lang/StringBuffer:append	(Ljava/lang/String;)Ljava/lang/StringBuffer;
/*     */     //   276: ldc_w 501
/*     */     //   279: invokevirtual 71	java/lang/StringBuffer:append	(Ljava/lang/String;)Ljava/lang/StringBuffer;
/*     */     //   282: pop
/*     */     //   283: aload 7
/*     */     //   285: ldc_w 503
/*     */     //   288: invokevirtual 71	java/lang/StringBuffer:append	(Ljava/lang/String;)Ljava/lang/StringBuffer;
/*     */     //   291: pop
/*     */     //   292: aload 7
/*     */     //   294: ldc_w 494
/*     */     //   297: invokevirtual 71	java/lang/StringBuffer:append	(Ljava/lang/String;)Ljava/lang/StringBuffer;
/*     */     //   300: pop
/*     */     //   301: aload 5
/*     */     //   303: aload 7
/*     */     //   305: invokevirtual 143	java/lang/StringBuffer:toString	()Ljava/lang/String;
/*     */     //   308: invokeinterface 144 2 0
/*     */     //   313: astore 6
/*     */     //   315: aload 6
/*     */     //   317: iconst_1
/*     */     //   318: aload_2
/*     */     //   319: invokevirtual 427	com/claro/transfer/UsuarioTO:getIdUsuario	()Ljava/lang/String;
/*     */     //   322: invokeinterface 150 3 0
/*     */     //   327: aload 6
/*     */     //   329: iconst_2
/*     */     //   330: aload_2
/*     */     //   331: invokevirtual 444	com/claro/transfer/UsuarioTO:getNombre	()Ljava/lang/String;
/*     */     //   334: invokeinterface 150 3 0
/*     */     //   339: aload 6
/*     */     //   341: iconst_3
/*     */     //   342: aload_2
/*     */     //   343: invokevirtual 208	com/claro/transfer/UsuarioTO:getStatus	()Ljava/lang/String;
/*     */     //   346: invokeinterface 150 3 0
/*     */     //   351: aload 6
/*     */     //   353: iconst_4
/*     */     //   354: aload_2
/*     */     //   355: invokevirtual 447	com/claro/transfer/UsuarioTO:getIdUsuarioCaptura	()Ljava/lang/String;
/*     */     //   358: invokeinterface 150 3 0
/*     */     //   363: aload 6
/*     */     //   365: iconst_5
/*     */     //   366: aload_2
/*     */     //   367: invokevirtual 450	com/claro/transfer/UsuarioTO:getFechaUpdate	()Ljava/sql/Timestamp;
/*     */     //   370: invokeinterface 454 3 0
/*     */     //   375: aload 6
/*     */     //   377: bipush 6
/*     */     //   379: aload_2
/*     */     //   380: invokevirtual 464	com/claro/transfer/UsuarioTO:getPerfilTO	()Lcom/claro/transfer/PerfilTO;
/*     */     //   383: invokevirtual 468	com/claro/transfer/PerfilTO:getIdPerfilN	()I
/*     */     //   386: invokeinterface 335 3 0
/*     */     //   391: aload 6
/*     */     //   393: bipush 7
/*     */     //   395: aload_2
/*     */     //   396: invokevirtual 464	com/claro/transfer/UsuarioTO:getPerfilTO	()Lcom/claro/transfer/PerfilTO;
/*     */     //   399: invokevirtual 471	com/claro/transfer/PerfilTO:getIdPuesto	()Ljava/lang/String;
/*     */     //   402: invokeinterface 150 3 0
/*     */     //   407: aload 6
/*     */     //   409: bipush 8
/*     */     //   411: aload_2
/*     */     //   412: invokevirtual 441	com/claro/transfer/UsuarioTO:getNumEmpleado	()Ljava/lang/String;
/*     */     //   415: invokeinterface 150 3 0
/*     */     //   420: aload 6
/*     */     //   422: invokeinterface 505 1 0
/*     */     //   427: pop
/*     */     //   428: aload_2
/*     */     //   429: iconst_0
/*     */     //   430: ldc_w 261
/*     */     //   433: invokevirtual 217	com/claro/transfer/UsuarioTO:agregaMensaje	(ILjava/lang/String;)V
/*     */     //   436: aload_2
/*     */     //   437: invokevirtual 464	com/claro/transfer/UsuarioTO:getPerfilTO	()Lcom/claro/transfer/PerfilTO;
/*     */     //   440: invokevirtual 468	com/claro/transfer/PerfilTO:getIdPerfilN	()I
/*     */     //   443: iload_3
/*     */     //   444: if_icmpeq +225 -> 669
/*     */     //   447: aload 6
/*     */     //   449: ifnull +13 -> 462
/*     */     //   452: aload 6
/*     */     //   454: invokeinterface 297 1 0
/*     */     //   459: aconst_null
/*     */     //   460: astore 6
/*     */     //   462: new 66	java/lang/StringBuffer
/*     */     //   465: dup
/*     */     //   466: invokespecial 68	java/lang/StringBuffer:<init>	()V
/*     */     //   469: astore 7
/*     */     //   471: aload 7
/*     */     //   473: ldc_w 508
/*     */     //   476: invokevirtual 71	java/lang/StringBuffer:append	(Ljava/lang/String;)Ljava/lang/StringBuffer;
/*     */     //   479: aload_0
/*     */     //   480: getfield 41	com/claro/dao/UsuarioDAO:schema_database	Ljava/lang/String;
/*     */     //   483: invokevirtual 71	java/lang/StringBuffer:append	(Ljava/lang/String;)Ljava/lang/StringBuffer;
/*     */     //   486: ldc_w 510
/*     */     //   489: invokevirtual 71	java/lang/StringBuffer:append	(Ljava/lang/String;)Ljava/lang/StringBuffer;
/*     */     //   492: pop
/*     */     //   493: aload 7
/*     */     //   495: ldc_w 512
/*     */     //   498: invokevirtual 71	java/lang/StringBuffer:append	(Ljava/lang/String;)Ljava/lang/StringBuffer;
/*     */     //   501: pop
/*     */     //   502: aload 5
/*     */     //   504: aload 7
/*     */     //   506: invokevirtual 143	java/lang/StringBuffer:toString	()Ljava/lang/String;
/*     */     //   509: invokeinterface 144 2 0
/*     */     //   514: astore 6
/*     */     //   516: aload 6
/*     */     //   518: iconst_1
/*     */     //   519: aload_2
/*     */     //   520: invokevirtual 441	com/claro/transfer/UsuarioTO:getNumEmpleado	()Ljava/lang/String;
/*     */     //   523: invokeinterface 150 3 0
/*     */     //   528: aload 6
/*     */     //   530: iconst_2
/*     */     //   531: new 514	java/sql/Timestamp
/*     */     //   534: dup
/*     */     //   535: invokestatic 86	java/lang/System:currentTimeMillis	()J
/*     */     //   538: invokespecial 516	java/sql/Timestamp:<init>	(J)V
/*     */     //   541: invokeinterface 454 3 0
/*     */     //   546: aload 6
/*     */     //   548: iconst_3
/*     */     //   549: aload_1
/*     */     //   550: invokevirtual 441	com/claro/transfer/UsuarioTO:getNumEmpleado	()Ljava/lang/String;
/*     */     //   553: invokeinterface 150 3 0
/*     */     //   558: aload 6
/*     */     //   560: iconst_4
/*     */     //   561: iload_3
/*     */     //   562: invokeinterface 335 3 0
/*     */     //   567: aload 6
/*     */     //   569: iconst_5
/*     */     //   570: aload_2
/*     */     //   571: invokevirtual 464	com/claro/transfer/UsuarioTO:getPerfilTO	()Lcom/claro/transfer/PerfilTO;
/*     */     //   574: invokevirtual 468	com/claro/transfer/PerfilTO:getIdPerfilN	()I
/*     */     //   577: invokeinterface 335 3 0
/*     */     //   582: aload 6
/*     */     //   584: invokeinterface 505 1 0
/*     */     //   589: pop
/*     */     //   590: goto +79 -> 669
/*     */     //   593: astore 7
/*     */     //   595: new 47	java/lang/Exception
/*     */     //   598: dup
/*     */     //   599: new 92	java/lang/StringBuilder
/*     */     //   602: dup
/*     */     //   603: ldc_w 477
/*     */     //   606: invokespecial 96	java/lang/StringBuilder:<init>	(Ljava/lang/String;)V
/*     */     //   609: aload 7
/*     */     //   611: invokevirtual 293	java/lang/Exception:toString	()Ljava/lang/String;
/*     */     //   614: invokevirtual 114	java/lang/StringBuilder:append	(Ljava/lang/String;)Ljava/lang/StringBuilder;
/*     */     //   617: invokevirtual 122	java/lang/StringBuilder:toString	()Ljava/lang/String;
/*     */     //   620: invokespecial 432	java/lang/Exception:<init>	(Ljava/lang/String;)V
/*     */     //   623: athrow
/*     */     //   624: astore 8
/*     */     //   626: aload 6
/*     */     //   628: ifnull +18 -> 646
/*     */     //   631: aload 6
/*     */     //   633: invokeinterface 297 1 0
/*     */     //   638: aconst_null
/*     */     //   639: astore 6
/*     */     //   641: goto +5 -> 646
/*     */     //   644: astore 9
/*     */     //   646: aload 5
/*     */     //   648: ifnull +18 -> 666
/*     */     //   651: aload 5
/*     */     //   653: invokeinterface 298 1 0
/*     */     //   658: aconst_null
/*     */     //   659: astore 5
/*     */     //   661: goto +5 -> 666
/*     */     //   664: astore 9
/*     */     //   666: aload 8
/*     */     //   668: athrow
/*     */     //   669: aload 6
/*     */     //   671: ifnull +18 -> 689
/*     */     //   674: aload 6
/*     */     //   676: invokeinterface 297 1 0
/*     */     //   681: aconst_null
/*     */     //   682: astore 6
/*     */     //   684: goto +5 -> 689
/*     */     //   687: astore 9
/*     */     //   689: aload 5
/*     */     //   691: ifnull +18 -> 709
/*     */     //   694: aload 5
/*     */     //   696: invokeinterface 298 1 0
/*     */     //   701: aconst_null
/*     */     //   702: astore 5
/*     */     //   704: goto +5 -> 709
/*     */     //   707: astore 9
/*     */     //   709: iload 4
/*     */     //   711: ireturn
/*     */     // Line number table:
/*     */     //   Java source line #329	-> byte code offset #0
/*     */     //   Java source line #330	-> byte code offset #3
/*     */     //   Java source line #331	-> byte code offset #6
/*     */     //   Java source line #334	-> byte code offset #9
/*     */     //   Java source line #336	-> byte code offset #20
/*     */     //   Java source line #338	-> byte code offset #29
/*     */     //   Java source line #339	-> byte code offset #36
/*     */     //   Java source line #340	-> byte code offset #58
/*     */     //   Java source line #341	-> byte code offset #67
/*     */     //   Java source line #342	-> byte code offset #76
/*     */     //   Java source line #344	-> byte code offset #85
/*     */     //   Java source line #346	-> byte code offset #99
/*     */     //   Java source line #347	-> byte code offset #111
/*     */     //   Java source line #348	-> byte code offset #123
/*     */     //   Java source line #349	-> byte code offset #132
/*     */     //   Java source line #350	-> byte code offset #144
/*     */     //   Java source line #351	-> byte code offset #156
/*     */     //   Java source line #352	-> byte code offset #169
/*     */     //   Java source line #353	-> byte code offset #185
/*     */     //   Java source line #354	-> byte code offset #201
/*     */     //   Java source line #355	-> byte code offset #217
/*     */     //   Java source line #356	-> byte code offset #229
/*     */     //   Java source line #357	-> byte code offset #242
/*     */     //   Java source line #358	-> byte code offset #250
/*     */     //   Java source line #361	-> byte code offset #261
/*     */     //   Java source line #362	-> byte code offset #283
/*     */     //   Java source line #363	-> byte code offset #292
/*     */     //   Java source line #365	-> byte code offset #301
/*     */     //   Java source line #367	-> byte code offset #315
/*     */     //   Java source line #368	-> byte code offset #327
/*     */     //   Java source line #369	-> byte code offset #339
/*     */     //   Java source line #370	-> byte code offset #351
/*     */     //   Java source line #371	-> byte code offset #363
/*     */     //   Java source line #372	-> byte code offset #375
/*     */     //   Java source line #373	-> byte code offset #391
/*     */     //   Java source line #374	-> byte code offset #407
/*     */     //   Java source line #375	-> byte code offset #420
/*     */     //   Java source line #376	-> byte code offset #428
/*     */     //   Java source line #380	-> byte code offset #436
/*     */     //   Java source line #381	-> byte code offset #447
/*     */     //   Java source line #383	-> byte code offset #462
/*     */     //   Java source line #384	-> byte code offset #471
/*     */     //   Java source line #385	-> byte code offset #493
/*     */     //   Java source line #387	-> byte code offset #502
/*     */     //   Java source line #388	-> byte code offset #516
/*     */     //   Java source line #389	-> byte code offset #528
/*     */     //   Java source line #390	-> byte code offset #546
/*     */     //   Java source line #391	-> byte code offset #558
/*     */     //   Java source line #392	-> byte code offset #567
/*     */     //   Java source line #394	-> byte code offset #582
/*     */     //   Java source line #401	-> byte code offset #593
/*     */     //   Java source line #402	-> byte code offset #595
/*     */     //   Java source line #403	-> byte code offset #624
/*     */     //   Java source line #404	-> byte code offset #626
/*     */     //   Java source line #405	-> byte code offset #646
/*     */     //   Java source line #406	-> byte code offset #666
/*     */     //   Java source line #404	-> byte code offset #669
/*     */     //   Java source line #405	-> byte code offset #689
/*     */     //   Java source line #407	-> byte code offset #709
/*     */     // Local variable table:
/*     */     //   start	length	slot	name	signature
/*     */     //   0	712	0	this	UsuarioDAO
/*     */     //   0	712	1	usuarioCA	UsuarioTO
/*     */     //   0	712	2	usuarioModificado	UsuarioTO
/*     */     //   0	712	3	perfilAnterior	int
/*     */     //   1	709	4	accion	boolean
/*     */     //   4	699	5	conn	Connection
/*     */     //   7	676	6	prepStat	PreparedStatement
/*     */     //   27	478	7	query	StringBuffer
/*     */     //   593	17	7	ex	Exception
/*     */     //   624	43	8	localObject	Object
/*     */     //   644	1	9	localException1	Exception
/*     */     //   664	1	9	localException2	Exception
/*     */     //   687	1	9	localException3	Exception
/*     */     //   707	1	9	localException4	Exception
/*     */     // Exception table:
/*     */     //   from	to	target	type
/*     */     //   9	590	593	java/lang/Exception
/*     */     //   9	624	624	finally
/*     */     //   631	641	644	java/lang/Exception
/*     */     //   651	661	664	java/lang/Exception
/*     */     //   674	684	687	java/lang/Exception
/*     */     //   694	704	707	java/lang/Exception
/*     */   }
/*     */   
/*     */   /* Error */
/*     */   public boolean eliminaUsuario(UsuarioTO usuarioTO)
/*     */     throws Exception
/*     */   {
/*     */     // Byte code:
/*     */     //   0: iconst_0
/*     */     //   1: istore_2
/*     */     //   2: aconst_null
/*     */     //   3: astore_3
/*     */     //   4: aconst_null
/*     */     //   5: astore 4
/*     */     //   7: invokestatic 29	com/claro/util/ServiceLocator:getInstance	()Lcom/claro/util/ServiceLocator;
/*     */     //   10: getstatic 132	com/claro/util/ServiceLocator:jdbcCirculoAzul	Ljava/lang/String;
/*     */     //   13: invokevirtual 135	com/claro/util/ServiceLocator:getConnection	(Ljava/lang/String;)Ljava/sql/Connection;
/*     */     //   16: astore_3
/*     */     //   17: new 66	java/lang/StringBuffer
/*     */     //   20: dup
/*     */     //   21: invokespecial 68	java/lang/StringBuffer:<init>	()V
/*     */     //   24: astore 5
/*     */     //   26: aload 5
/*     */     //   28: ldc_w 486
/*     */     //   31: invokevirtual 71	java/lang/StringBuffer:append	(Ljava/lang/String;)Ljava/lang/StringBuffer;
/*     */     //   34: aload_0
/*     */     //   35: getfield 41	com/claro/dao/UsuarioDAO:schema_database	Ljava/lang/String;
/*     */     //   38: invokevirtual 71	java/lang/StringBuffer:append	(Ljava/lang/String;)Ljava/lang/StringBuffer;
/*     */     //   41: ldc_w 523
/*     */     //   44: invokevirtual 71	java/lang/StringBuffer:append	(Ljava/lang/String;)Ljava/lang/StringBuffer;
/*     */     //   47: pop
/*     */     //   48: aload 5
/*     */     //   50: ldc_w 494
/*     */     //   53: invokevirtual 71	java/lang/StringBuffer:append	(Ljava/lang/String;)Ljava/lang/StringBuffer;
/*     */     //   56: pop
/*     */     //   57: aload_3
/*     */     //   58: aload 5
/*     */     //   60: invokevirtual 143	java/lang/StringBuffer:toString	()Ljava/lang/String;
/*     */     //   63: invokeinterface 144 2 0
/*     */     //   68: astore 4
/*     */     //   70: aload 4
/*     */     //   72: iconst_1
/*     */     //   73: aload_1
/*     */     //   74: invokevirtual 441	com/claro/transfer/UsuarioTO:getNumEmpleado	()Ljava/lang/String;
/*     */     //   77: invokeinterface 150 3 0
/*     */     //   82: aload 4
/*     */     //   84: invokeinterface 474 1 0
/*     */     //   89: pop
/*     */     //   90: goto +76 -> 166
/*     */     //   93: astore 5
/*     */     //   95: new 47	java/lang/Exception
/*     */     //   98: dup
/*     */     //   99: new 92	java/lang/StringBuilder
/*     */     //   102: dup
/*     */     //   103: ldc_w 477
/*     */     //   106: invokespecial 96	java/lang/StringBuilder:<init>	(Ljava/lang/String;)V
/*     */     //   109: aload 5
/*     */     //   111: invokevirtual 293	java/lang/Exception:toString	()Ljava/lang/String;
/*     */     //   114: invokevirtual 114	java/lang/StringBuilder:append	(Ljava/lang/String;)Ljava/lang/StringBuilder;
/*     */     //   117: invokevirtual 122	java/lang/StringBuilder:toString	()Ljava/lang/String;
/*     */     //   120: invokespecial 432	java/lang/Exception:<init>	(Ljava/lang/String;)V
/*     */     //   123: athrow
/*     */     //   124: astore 6
/*     */     //   126: aload 4
/*     */     //   128: ifnull +18 -> 146
/*     */     //   131: aload 4
/*     */     //   133: invokeinterface 297 1 0
/*     */     //   138: aconst_null
/*     */     //   139: astore 4
/*     */     //   141: goto +5 -> 146
/*     */     //   144: astore 7
/*     */     //   146: aload_3
/*     */     //   147: ifnull +16 -> 163
/*     */     //   150: aload_3
/*     */     //   151: invokeinterface 298 1 0
/*     */     //   156: aconst_null
/*     */     //   157: astore_3
/*     */     //   158: goto +5 -> 163
/*     */     //   161: astore 7
/*     */     //   163: aload 6
/*     */     //   165: athrow
/*     */     //   166: aload 4
/*     */     //   168: ifnull +18 -> 186
/*     */     //   171: aload 4
/*     */     //   173: invokeinterface 297 1 0
/*     */     //   178: aconst_null
/*     */     //   179: astore 4
/*     */     //   181: goto +5 -> 186
/*     */     //   184: astore 7
/*     */     //   186: aload_3
/*     */     //   187: ifnull +16 -> 203
/*     */     //   190: aload_3
/*     */     //   191: invokeinterface 298 1 0
/*     */     //   196: aconst_null
/*     */     //   197: astore_3
/*     */     //   198: goto +5 -> 203
/*     */     //   201: astore 7
/*     */     //   203: iload_2
/*     */     //   204: ireturn
/*     */     // Line number table:
/*     */     //   Java source line #418	-> byte code offset #0
/*     */     //   Java source line #419	-> byte code offset #2
/*     */     //   Java source line #420	-> byte code offset #4
/*     */     //   Java source line #422	-> byte code offset #7
/*     */     //   Java source line #424	-> byte code offset #17
/*     */     //   Java source line #428	-> byte code offset #26
/*     */     //   Java source line #429	-> byte code offset #48
/*     */     //   Java source line #431	-> byte code offset #57
/*     */     //   Java source line #432	-> byte code offset #70
/*     */     //   Java source line #433	-> byte code offset #82
/*     */     //   Java source line #434	-> byte code offset #93
/*     */     //   Java source line #435	-> byte code offset #95
/*     */     //   Java source line #436	-> byte code offset #124
/*     */     //   Java source line #437	-> byte code offset #126
/*     */     //   Java source line #438	-> byte code offset #146
/*     */     //   Java source line #439	-> byte code offset #163
/*     */     //   Java source line #437	-> byte code offset #166
/*     */     //   Java source line #438	-> byte code offset #186
/*     */     //   Java source line #440	-> byte code offset #203
/*     */     // Local variable table:
/*     */     //   start	length	slot	name	signature
/*     */     //   0	205	0	this	UsuarioDAO
/*     */     //   0	205	1	usuarioTO	UsuarioTO
/*     */     //   1	203	2	accion	boolean
/*     */     //   3	195	3	conn	Connection
/*     */     //   5	175	4	prepStat	PreparedStatement
/*     */     //   24	35	5	query	StringBuffer
/*     */     //   93	17	5	ex	Exception
/*     */     //   124	40	6	localObject	Object
/*     */     //   144	1	7	localException1	Exception
/*     */     //   161	1	7	localException2	Exception
/*     */     //   184	1	7	localException3	Exception
/*     */     //   201	1	7	localException4	Exception
/*     */     // Exception table:
/*     */     //   from	to	target	type
/*     */     //   7	90	93	java/lang/Exception
/*     */     //   7	124	124	finally
/*     */     //   131	141	144	java/lang/Exception
/*     */     //   150	158	161	java/lang/Exception
/*     */     //   171	181	184	java/lang/Exception
/*     */     //   190	198	201	java/lang/Exception
/*     */   }
/*     */   
/*     */   /* Error */
/*     */   public UsuarioTO consultaUsuario(UsuarioTO usuarioTO)
/*     */     throws Exception
/*     */   {
/*     */     // Byte code:
/*     */     //   0: aconst_null
/*     */     //   1: astore_2
/*     */     //   2: aconst_null
/*     */     //   3: astore_3
/*     */     //   4: aconst_null
/*     */     //   5: astore 4
/*     */     //   7: invokestatic 29	com/claro/util/ServiceLocator:getInstance	()Lcom/claro/util/ServiceLocator;
/*     */     //   10: getstatic 132	com/claro/util/ServiceLocator:jdbcCirculoAzul	Ljava/lang/String;
/*     */     //   13: invokevirtual 135	com/claro/util/ServiceLocator:getConnection	(Ljava/lang/String;)Ljava/sql/Connection;
/*     */     //   16: astore_2
/*     */     //   17: new 66	java/lang/StringBuffer
/*     */     //   20: dup
/*     */     //   21: invokespecial 68	java/lang/StringBuffer:<init>	()V
/*     */     //   24: astore 5
/*     */     //   26: aload 5
/*     */     //   28: ldc_w 527
/*     */     //   31: invokevirtual 71	java/lang/StringBuffer:append	(Ljava/lang/String;)Ljava/lang/StringBuffer;
/*     */     //   34: pop
/*     */     //   35: aload 5
/*     */     //   37: ldc_w 529
/*     */     //   40: invokevirtual 71	java/lang/StringBuffer:append	(Ljava/lang/String;)Ljava/lang/StringBuffer;
/*     */     //   43: pop
/*     */     //   44: aload 5
/*     */     //   46: ldc 75
/*     */     //   48: invokevirtual 71	java/lang/StringBuffer:append	(Ljava/lang/String;)Ljava/lang/StringBuffer;
/*     */     //   51: aload_0
/*     */     //   52: getfield 41	com/claro/dao/UsuarioDAO:schema_database	Ljava/lang/String;
/*     */     //   55: invokevirtual 71	java/lang/StringBuffer:append	(Ljava/lang/String;)Ljava/lang/StringBuffer;
/*     */     //   58: ldc_w 531
/*     */     //   61: invokevirtual 71	java/lang/StringBuffer:append	(Ljava/lang/String;)Ljava/lang/StringBuffer;
/*     */     //   64: pop
/*     */     //   65: aload 5
/*     */     //   67: ldc_w 533
/*     */     //   70: invokevirtual 71	java/lang/StringBuffer:append	(Ljava/lang/String;)Ljava/lang/StringBuffer;
/*     */     //   73: aload_0
/*     */     //   74: getfield 41	com/claro/dao/UsuarioDAO:schema_database	Ljava/lang/String;
/*     */     //   77: invokevirtual 71	java/lang/StringBuffer:append	(Ljava/lang/String;)Ljava/lang/StringBuffer;
/*     */     //   80: ldc_w 535
/*     */     //   83: invokevirtual 71	java/lang/StringBuffer:append	(Ljava/lang/String;)Ljava/lang/StringBuffer;
/*     */     //   86: pop
/*     */     //   87: aload 5
/*     */     //   89: ldc_w 537
/*     */     //   92: invokevirtual 71	java/lang/StringBuffer:append	(Ljava/lang/String;)Ljava/lang/StringBuffer;
/*     */     //   95: pop
/*     */     //   96: aload_2
/*     */     //   97: aload 5
/*     */     //   99: invokevirtual 143	java/lang/StringBuffer:toString	()Ljava/lang/String;
/*     */     //   102: invokeinterface 144 2 0
/*     */     //   107: astore_3
/*     */     //   108: aload_3
/*     */     //   109: iconst_1
/*     */     //   110: aload_1
/*     */     //   111: invokevirtual 441	com/claro/transfer/UsuarioTO:getNumEmpleado	()Ljava/lang/String;
/*     */     //   114: invokeinterface 150 3 0
/*     */     //   119: aload_3
/*     */     //   120: invokeinterface 155 1 0
/*     */     //   125: astore 4
/*     */     //   127: aload 4
/*     */     //   129: invokeinterface 159 1 0
/*     */     //   134: ifeq +174 -> 308
/*     */     //   137: aload_1
/*     */     //   138: aload_1
/*     */     //   139: invokevirtual 441	com/claro/transfer/UsuarioTO:getNumEmpleado	()Ljava/lang/String;
/*     */     //   142: invokevirtual 165	com/claro/transfer/UsuarioTO:setNumEmpleado	(Ljava/lang/String;)V
/*     */     //   145: aload_1
/*     */     //   146: aload 4
/*     */     //   148: iconst_1
/*     */     //   149: invokeinterface 168 2 0
/*     */     //   154: invokevirtual 172	com/claro/transfer/UsuarioTO:setIdUsuario	(Ljava/lang/String;)V
/*     */     //   157: aload_1
/*     */     //   158: aload 4
/*     */     //   160: iconst_2
/*     */     //   161: invokeinterface 168 2 0
/*     */     //   166: invokevirtual 175	com/claro/transfer/UsuarioTO:setNombre	(Ljava/lang/String;)V
/*     */     //   169: aload_1
/*     */     //   170: aload 4
/*     */     //   172: iconst_3
/*     */     //   173: invokeinterface 168 2 0
/*     */     //   178: invokevirtual 178	com/claro/transfer/UsuarioTO:setPassword	(Ljava/lang/String;)V
/*     */     //   181: aload_1
/*     */     //   182: aload 4
/*     */     //   184: iconst_4
/*     */     //   185: invokeinterface 168 2 0
/*     */     //   190: invokevirtual 181	com/claro/transfer/UsuarioTO:setStatus	(Ljava/lang/String;)V
/*     */     //   193: aload_1
/*     */     //   194: aload 4
/*     */     //   196: iconst_5
/*     */     //   197: invokeinterface 184 2 0
/*     */     //   202: invokestatic 539	java/lang/Integer:valueOf	(I)Ljava/lang/Integer;
/*     */     //   205: invokevirtual 544	com/claro/transfer/UsuarioTO:setContadorPMP	(Ljava/lang/Integer;)V
/*     */     //   208: aload 4
/*     */     //   210: bipush 6
/*     */     //   212: invokeinterface 184 2 0
/*     */     //   217: istore 6
/*     */     //   219: new 220	com/claro/transfer/PerfilTO
/*     */     //   222: dup
/*     */     //   223: invokespecial 222	com/claro/transfer/PerfilTO:<init>	()V
/*     */     //   226: astore 7
/*     */     //   228: aload 7
/*     */     //   230: iload 6
/*     */     //   232: invokevirtual 223	com/claro/transfer/PerfilTO:setIdPerfilN	(I)V
/*     */     //   235: aload 7
/*     */     //   237: aload 4
/*     */     //   239: bipush 7
/*     */     //   241: invokeinterface 168 2 0
/*     */     //   246: invokevirtual 230	com/claro/transfer/PerfilTO:setIdPuesto	(Ljava/lang/String;)V
/*     */     //   249: aload 7
/*     */     //   251: aload 4
/*     */     //   253: bipush 8
/*     */     //   255: invokeinterface 168 2 0
/*     */     //   260: invokevirtual 233	com/claro/transfer/PerfilTO:setDescripcion	(Ljava/lang/String;)V
/*     */     //   263: aload 7
/*     */     //   265: aload 4
/*     */     //   267: bipush 9
/*     */     //   269: invokeinterface 184 2 0
/*     */     //   274: invokevirtual 236	com/claro/transfer/PerfilTO:setRegion	(I)V
/*     */     //   277: aload 7
/*     */     //   279: aload 4
/*     */     //   281: bipush 10
/*     */     //   283: invokeinterface 184 2 0
/*     */     //   288: invokevirtual 227	com/claro/transfer/PerfilTO:setNivelAutorizacion	(I)V
/*     */     //   291: aload_1
/*     */     //   292: aload 7
/*     */     //   294: invokevirtual 257	com/claro/transfer/UsuarioTO:setPerfilTO	(Lcom/claro/transfer/PerfilTO;)V
/*     */     //   297: aload_1
/*     */     //   298: iconst_0
/*     */     //   299: ldc_w 261
/*     */     //   302: invokevirtual 217	com/claro/transfer/UsuarioTO:agregaMensaje	(ILjava/lang/String;)V
/*     */     //   305: goto +132 -> 437
/*     */     //   308: aload_1
/*     */     //   309: iconst_m1
/*     */     //   310: new 92	java/lang/StringBuilder
/*     */     //   313: dup
/*     */     //   314: ldc_w 269
/*     */     //   317: invokespecial 96	java/lang/StringBuilder:<init>	(Ljava/lang/String;)V
/*     */     //   320: aload_1
/*     */     //   321: invokevirtual 441	com/claro/transfer/UsuarioTO:getNumEmpleado	()Ljava/lang/String;
/*     */     //   324: invokevirtual 114	java/lang/StringBuilder:append	(Ljava/lang/String;)Ljava/lang/StringBuilder;
/*     */     //   327: ldc_w 548
/*     */     //   330: invokevirtual 114	java/lang/StringBuilder:append	(Ljava/lang/String;)Ljava/lang/StringBuilder;
/*     */     //   333: invokevirtual 122	java/lang/StringBuilder:toString	()Ljava/lang/String;
/*     */     //   336: invokevirtual 217	com/claro/transfer/UsuarioTO:agregaMensaje	(ILjava/lang/String;)V
/*     */     //   339: goto +98 -> 437
/*     */     //   342: astore 5
/*     */     //   344: new 47	java/lang/Exception
/*     */     //   347: dup
/*     */     //   348: new 92	java/lang/StringBuilder
/*     */     //   351: dup
/*     */     //   352: ldc_w 550
/*     */     //   355: invokespecial 96	java/lang/StringBuilder:<init>	(Ljava/lang/String;)V
/*     */     //   358: aload 5
/*     */     //   360: invokevirtual 293	java/lang/Exception:toString	()Ljava/lang/String;
/*     */     //   363: invokevirtual 114	java/lang/StringBuilder:append	(Ljava/lang/String;)Ljava/lang/StringBuilder;
/*     */     //   366: ldc -41
/*     */     //   368: invokevirtual 114	java/lang/StringBuilder:append	(Ljava/lang/String;)Ljava/lang/StringBuilder;
/*     */     //   371: invokevirtual 122	java/lang/StringBuilder:toString	()Ljava/lang/String;
/*     */     //   374: invokespecial 432	java/lang/Exception:<init>	(Ljava/lang/String;)V
/*     */     //   377: athrow
/*     */     //   378: astore 8
/*     */     //   380: aload 4
/*     */     //   382: ifnull +18 -> 400
/*     */     //   385: aload 4
/*     */     //   387: invokeinterface 294 1 0
/*     */     //   392: aconst_null
/*     */     //   393: astore 4
/*     */     //   395: goto +5 -> 400
/*     */     //   398: astore 9
/*     */     //   400: aload_3
/*     */     //   401: ifnull +16 -> 417
/*     */     //   404: aload_3
/*     */     //   405: invokeinterface 297 1 0
/*     */     //   410: aconst_null
/*     */     //   411: astore_3
/*     */     //   412: goto +5 -> 417
/*     */     //   415: astore 9
/*     */     //   417: aload_2
/*     */     //   418: ifnull +16 -> 434
/*     */     //   421: aload_2
/*     */     //   422: invokeinterface 298 1 0
/*     */     //   427: aconst_null
/*     */     //   428: astore_2
/*     */     //   429: goto +5 -> 434
/*     */     //   432: astore 9
/*     */     //   434: aload 8
/*     */     //   436: athrow
/*     */     //   437: aload 4
/*     */     //   439: ifnull +18 -> 457
/*     */     //   442: aload 4
/*     */     //   444: invokeinterface 294 1 0
/*     */     //   449: aconst_null
/*     */     //   450: astore 4
/*     */     //   452: goto +5 -> 457
/*     */     //   455: astore 9
/*     */     //   457: aload_3
/*     */     //   458: ifnull +16 -> 474
/*     */     //   461: aload_3
/*     */     //   462: invokeinterface 297 1 0
/*     */     //   467: aconst_null
/*     */     //   468: astore_3
/*     */     //   469: goto +5 -> 474
/*     */     //   472: astore 9
/*     */     //   474: aload_2
/*     */     //   475: ifnull +16 -> 491
/*     */     //   478: aload_2
/*     */     //   479: invokeinterface 298 1 0
/*     */     //   484: aconst_null
/*     */     //   485: astore_2
/*     */     //   486: goto +5 -> 491
/*     */     //   489: astore 9
/*     */     //   491: aload_1
/*     */     //   492: areturn
/*     */     // Line number table:
/*     */     //   Java source line #451	-> byte code offset #0
/*     */     //   Java source line #452	-> byte code offset #2
/*     */     //   Java source line #453	-> byte code offset #4
/*     */     //   Java source line #455	-> byte code offset #7
/*     */     //   Java source line #457	-> byte code offset #17
/*     */     //   Java source line #458	-> byte code offset #26
/*     */     //   Java source line #459	-> byte code offset #35
/*     */     //   Java source line #460	-> byte code offset #44
/*     */     //   Java source line #461	-> byte code offset #65
/*     */     //   Java source line #462	-> byte code offset #87
/*     */     //   Java source line #464	-> byte code offset #96
/*     */     //   Java source line #465	-> byte code offset #108
/*     */     //   Java source line #466	-> byte code offset #119
/*     */     //   Java source line #467	-> byte code offset #127
/*     */     //   Java source line #468	-> byte code offset #137
/*     */     //   Java source line #469	-> byte code offset #145
/*     */     //   Java source line #470	-> byte code offset #157
/*     */     //   Java source line #471	-> byte code offset #169
/*     */     //   Java source line #472	-> byte code offset #181
/*     */     //   Java source line #473	-> byte code offset #193
/*     */     //   Java source line #475	-> byte code offset #208
/*     */     //   Java source line #476	-> byte code offset #219
/*     */     //   Java source line #477	-> byte code offset #228
/*     */     //   Java source line #478	-> byte code offset #235
/*     */     //   Java source line #479	-> byte code offset #249
/*     */     //   Java source line #480	-> byte code offset #263
/*     */     //   Java source line #481	-> byte code offset #277
/*     */     //   Java source line #483	-> byte code offset #291
/*     */     //   Java source line #484	-> byte code offset #297
/*     */     //   Java source line #486	-> byte code offset #308
/*     */     //   Java source line #488	-> byte code offset #342
/*     */     //   Java source line #489	-> byte code offset #344
/*     */     //   Java source line #490	-> byte code offset #378
/*     */     //   Java source line #491	-> byte code offset #380
/*     */     //   Java source line #492	-> byte code offset #400
/*     */     //   Java source line #493	-> byte code offset #417
/*     */     //   Java source line #494	-> byte code offset #434
/*     */     //   Java source line #491	-> byte code offset #437
/*     */     //   Java source line #492	-> byte code offset #457
/*     */     //   Java source line #493	-> byte code offset #474
/*     */     //   Java source line #495	-> byte code offset #491
/*     */     // Local variable table:
/*     */     //   start	length	slot	name	signature
/*     */     //   0	493	0	this	UsuarioDAO
/*     */     //   0	493	1	usuarioTO	UsuarioTO
/*     */     //   1	485	2	conn	Connection
/*     */     //   3	466	3	prepStat	PreparedStatement
/*     */     //   5	446	4	resultSet	ResultSet
/*     */     //   24	74	5	query	StringBuffer
/*     */     //   342	17	5	e	Exception
/*     */     //   217	14	6	idPerfiln	int
/*     */     //   226	67	7	perfilTO	com.claro.transfer.PerfilTO
/*     */     //   378	57	8	localObject	Object
/*     */     //   398	1	9	localException1	Exception
/*     */     //   415	1	9	localException2	Exception
/*     */     //   432	1	9	localException3	Exception
/*     */     //   455	1	9	localException4	Exception
/*     */     //   472	1	9	localException5	Exception
/*     */     //   489	1	9	localException6	Exception
/*     */     // Exception table:
/*     */     //   from	to	target	type
/*     */     //   7	339	342	java/lang/Exception
/*     */     //   7	378	378	finally
/*     */     //   385	395	398	java/lang/Exception
/*     */     //   404	412	415	java/lang/Exception
/*     */     //   421	429	432	java/lang/Exception
/*     */     //   442	452	455	java/lang/Exception
/*     */     //   461	469	472	java/lang/Exception
/*     */     //   478	486	489	java/lang/Exception
/*     */   }
/*     */   
/*     */   /* Error */
/*     */   public java.util.ArrayList<UsuarioTO> consultaUsuarios(UsuarioTO user, int max)
/*     */     throws CAException
/*     */   {
/*     */     // Byte code:
/*     */     //   0: aconst_null
/*     */     //   1: astore_3
/*     */     //   2: aconst_null
/*     */     //   3: astore 4
/*     */     //   5: aconst_null
/*     */     //   6: astore 5
/*     */     //   8: new 556	java/util/ArrayList
/*     */     //   11: dup
/*     */     //   12: invokespecial 558	java/util/ArrayList:<init>	()V
/*     */     //   15: astore 6
/*     */     //   17: invokestatic 29	com/claro/util/ServiceLocator:getInstance	()Lcom/claro/util/ServiceLocator;
/*     */     //   20: getstatic 132	com/claro/util/ServiceLocator:jdbcCirculoAzul	Ljava/lang/String;
/*     */     //   23: invokevirtual 135	com/claro/util/ServiceLocator:getConnection	(Ljava/lang/String;)Ljava/sql/Connection;
/*     */     //   26: astore_3
/*     */     //   27: new 66	java/lang/StringBuffer
/*     */     //   30: dup
/*     */     //   31: invokespecial 68	java/lang/StringBuffer:<init>	()V
/*     */     //   34: astore 7
/*     */     //   36: aload 7
/*     */     //   38: ldc_w 559
/*     */     //   41: invokevirtual 71	java/lang/StringBuffer:append	(Ljava/lang/String;)Ljava/lang/StringBuffer;
/*     */     //   44: pop
/*     */     //   45: aload 7
/*     */     //   47: ldc_w 561
/*     */     //   50: invokevirtual 71	java/lang/StringBuffer:append	(Ljava/lang/String;)Ljava/lang/StringBuffer;
/*     */     //   53: pop
/*     */     //   54: aload 7
/*     */     //   56: ldc 75
/*     */     //   58: invokevirtual 71	java/lang/StringBuffer:append	(Ljava/lang/String;)Ljava/lang/StringBuffer;
/*     */     //   61: aload_0
/*     */     //   62: getfield 41	com/claro/dao/UsuarioDAO:schema_database	Ljava/lang/String;
/*     */     //   65: invokevirtual 71	java/lang/StringBuffer:append	(Ljava/lang/String;)Ljava/lang/StringBuffer;
/*     */     //   68: ldc_w 563
/*     */     //   71: invokevirtual 71	java/lang/StringBuffer:append	(Ljava/lang/String;)Ljava/lang/StringBuffer;
/*     */     //   74: pop
/*     */     //   75: aload 7
/*     */     //   77: ldc_w 565
/*     */     //   80: invokevirtual 71	java/lang/StringBuffer:append	(Ljava/lang/String;)Ljava/lang/StringBuffer;
/*     */     //   83: pop
/*     */     //   84: aload_1
/*     */     //   85: invokevirtual 441	com/claro/transfer/UsuarioTO:getNumEmpleado	()Ljava/lang/String;
/*     */     //   88: ifnull +7 -> 95
/*     */     //   91: iconst_1
/*     */     //   92: goto +4 -> 96
/*     */     //   95: iconst_0
/*     */     //   96: ldc_w 383
/*     */     //   99: aload_1
/*     */     //   100: invokevirtual 441	com/claro/transfer/UsuarioTO:getNumEmpleado	()Ljava/lang/String;
/*     */     //   103: invokevirtual 202	java/lang/String:equals	(Ljava/lang/Object;)Z
/*     */     //   106: ifeq +7 -> 113
/*     */     //   109: iconst_0
/*     */     //   110: goto +4 -> 114
/*     */     //   113: iconst_1
/*     */     //   114: iand
/*     */     //   115: ifeq +12 -> 127
/*     */     //   118: aload 7
/*     */     //   120: ldc_w 567
/*     */     //   123: invokevirtual 71	java/lang/StringBuffer:append	(Ljava/lang/String;)Ljava/lang/StringBuffer;
/*     */     //   126: pop
/*     */     //   127: aload_1
/*     */     //   128: invokevirtual 427	com/claro/transfer/UsuarioTO:getIdUsuario	()Ljava/lang/String;
/*     */     //   131: ifnull +7 -> 138
/*     */     //   134: iconst_1
/*     */     //   135: goto +4 -> 139
/*     */     //   138: iconst_0
/*     */     //   139: ldc_w 383
/*     */     //   142: aload_1
/*     */     //   143: invokevirtual 427	com/claro/transfer/UsuarioTO:getIdUsuario	()Ljava/lang/String;
/*     */     //   146: invokevirtual 202	java/lang/String:equals	(Ljava/lang/Object;)Z
/*     */     //   149: ifeq +7 -> 156
/*     */     //   152: iconst_0
/*     */     //   153: goto +4 -> 157
/*     */     //   156: iconst_1
/*     */     //   157: iand
/*     */     //   158: ifeq +12 -> 170
/*     */     //   161: aload 7
/*     */     //   163: ldc_w 569
/*     */     //   166: invokevirtual 71	java/lang/StringBuffer:append	(Ljava/lang/String;)Ljava/lang/StringBuffer;
/*     */     //   169: pop
/*     */     //   170: aload_1
/*     */     //   171: invokevirtual 571	com/claro/transfer/UsuarioTO:getPerfil	()Ljava/lang/String;
/*     */     //   174: ifnull +7 -> 181
/*     */     //   177: iconst_1
/*     */     //   178: goto +4 -> 182
/*     */     //   181: iconst_0
/*     */     //   182: ldc_w 383
/*     */     //   185: aload_1
/*     */     //   186: invokevirtual 571	com/claro/transfer/UsuarioTO:getPerfil	()Ljava/lang/String;
/*     */     //   189: invokevirtual 202	java/lang/String:equals	(Ljava/lang/Object;)Z
/*     */     //   192: ifeq +7 -> 199
/*     */     //   195: iconst_0
/*     */     //   196: goto +4 -> 200
/*     */     //   199: iconst_1
/*     */     //   200: iand
/*     */     //   201: ifeq +12 -> 213
/*     */     //   204: aload 7
/*     */     //   206: ldc_w 574
/*     */     //   209: invokevirtual 71	java/lang/StringBuffer:append	(Ljava/lang/String;)Ljava/lang/StringBuffer;
/*     */     //   212: pop
/*     */     //   213: aload_1
/*     */     //   214: invokevirtual 208	com/claro/transfer/UsuarioTO:getStatus	()Ljava/lang/String;
/*     */     //   217: ifnull +7 -> 224
/*     */     //   220: iconst_1
/*     */     //   221: goto +4 -> 225
/*     */     //   224: iconst_0
/*     */     //   225: ldc_w 383
/*     */     //   228: aload_1
/*     */     //   229: invokevirtual 208	com/claro/transfer/UsuarioTO:getStatus	()Ljava/lang/String;
/*     */     //   232: invokevirtual 202	java/lang/String:equals	(Ljava/lang/Object;)Z
/*     */     //   235: ifeq +7 -> 242
/*     */     //   238: iconst_0
/*     */     //   239: goto +4 -> 243
/*     */     //   242: iconst_1
/*     */     //   243: iand
/*     */     //   244: ifeq +12 -> 256
/*     */     //   247: aload 7
/*     */     //   249: ldc_w 576
/*     */     //   252: invokevirtual 71	java/lang/StringBuffer:append	(Ljava/lang/String;)Ljava/lang/StringBuffer;
/*     */     //   255: pop
/*     */     //   256: aload_1
/*     */     //   257: invokevirtual 461	com/claro/transfer/UsuarioTO:getFechaAdmin	()Ljava/sql/Timestamp;
/*     */     //   260: ifnull +7 -> 267
/*     */     //   263: iconst_1
/*     */     //   264: goto +4 -> 268
/*     */     //   267: iconst_0
/*     */     //   268: ldc_w 383
/*     */     //   271: aload_1
/*     */     //   272: invokevirtual 461	com/claro/transfer/UsuarioTO:getFechaAdmin	()Ljava/sql/Timestamp;
/*     */     //   275: invokevirtual 202	java/lang/String:equals	(Ljava/lang/Object;)Z
/*     */     //   278: ifeq +7 -> 285
/*     */     //   281: iconst_0
/*     */     //   282: goto +4 -> 286
/*     */     //   285: iconst_1
/*     */     //   286: iand
/*     */     //   287: aload_1
/*     */     //   288: invokevirtual 450	com/claro/transfer/UsuarioTO:getFechaUpdate	()Ljava/sql/Timestamp;
/*     */     //   291: ifnull +7 -> 298
/*     */     //   294: iconst_1
/*     */     //   295: goto +4 -> 299
/*     */     //   298: iconst_0
/*     */     //   299: iand
/*     */     //   300: ldc_w 383
/*     */     //   303: aload_1
/*     */     //   304: invokevirtual 450	com/claro/transfer/UsuarioTO:getFechaUpdate	()Ljava/sql/Timestamp;
/*     */     //   307: invokevirtual 202	java/lang/String:equals	(Ljava/lang/Object;)Z
/*     */     //   310: ifeq +7 -> 317
/*     */     //   313: iconst_0
/*     */     //   314: goto +4 -> 318
/*     */     //   317: iconst_1
/*     */     //   318: iand
/*     */     //   319: ifeq +12 -> 331
/*     */     //   322: aload 7
/*     */     //   324: ldc_w 578
/*     */     //   327: invokevirtual 71	java/lang/StringBuffer:append	(Ljava/lang/String;)Ljava/lang/StringBuffer;
/*     */     //   330: pop
/*     */     //   331: aload_3
/*     */     //   332: aload 7
/*     */     //   334: invokevirtual 143	java/lang/StringBuffer:toString	()Ljava/lang/String;
/*     */     //   337: invokeinterface 144 2 0
/*     */     //   342: astore 4
/*     */     //   344: iconst_1
/*     */     //   345: istore 8
/*     */     //   347: aload_1
/*     */     //   348: invokevirtual 441	com/claro/transfer/UsuarioTO:getNumEmpleado	()Ljava/lang/String;
/*     */     //   351: ifnull +7 -> 358
/*     */     //   354: iconst_1
/*     */     //   355: goto +4 -> 359
/*     */     //   358: iconst_0
/*     */     //   359: ldc_w 383
/*     */     //   362: aload_1
/*     */     //   363: invokevirtual 441	com/claro/transfer/UsuarioTO:getNumEmpleado	()Ljava/lang/String;
/*     */     //   366: invokevirtual 202	java/lang/String:equals	(Ljava/lang/Object;)Z
/*     */     //   369: ifeq +7 -> 376
/*     */     //   372: iconst_0
/*     */     //   373: goto +4 -> 377
/*     */     //   376: iconst_1
/*     */     //   377: iand
/*     */     //   378: ifeq +19 -> 397
/*     */     //   381: aload 4
/*     */     //   383: iload 8
/*     */     //   385: iinc 8 1
/*     */     //   388: aload_1
/*     */     //   389: invokevirtual 441	com/claro/transfer/UsuarioTO:getNumEmpleado	()Ljava/lang/String;
/*     */     //   392: invokeinterface 150 3 0
/*     */     //   397: aload_1
/*     */     //   398: invokevirtual 427	com/claro/transfer/UsuarioTO:getIdUsuario	()Ljava/lang/String;
/*     */     //   401: ifnull +7 -> 408
/*     */     //   404: iconst_1
/*     */     //   405: goto +4 -> 409
/*     */     //   408: iconst_0
/*     */     //   409: ldc_w 383
/*     */     //   412: aload_1
/*     */     //   413: invokevirtual 427	com/claro/transfer/UsuarioTO:getIdUsuario	()Ljava/lang/String;
/*     */     //   416: invokevirtual 202	java/lang/String:equals	(Ljava/lang/Object;)Z
/*     */     //   419: ifeq +7 -> 426
/*     */     //   422: iconst_0
/*     */     //   423: goto +4 -> 427
/*     */     //   426: iconst_1
/*     */     //   427: iand
/*     */     //   428: ifeq +19 -> 447
/*     */     //   431: aload 4
/*     */     //   433: iload 8
/*     */     //   435: iinc 8 1
/*     */     //   438: aload_1
/*     */     //   439: invokevirtual 427	com/claro/transfer/UsuarioTO:getIdUsuario	()Ljava/lang/String;
/*     */     //   442: invokeinterface 150 3 0
/*     */     //   447: aload_1
/*     */     //   448: invokevirtual 571	com/claro/transfer/UsuarioTO:getPerfil	()Ljava/lang/String;
/*     */     //   451: ifnull +7 -> 458
/*     */     //   454: iconst_1
/*     */     //   455: goto +4 -> 459
/*     */     //   458: iconst_0
/*     */     //   459: ldc_w 383
/*     */     //   462: aload_1
/*     */     //   463: invokevirtual 571	com/claro/transfer/UsuarioTO:getPerfil	()Ljava/lang/String;
/*     */     //   466: invokevirtual 202	java/lang/String:equals	(Ljava/lang/Object;)Z
/*     */     //   469: ifeq +7 -> 476
/*     */     //   472: iconst_0
/*     */     //   473: goto +4 -> 477
/*     */     //   476: iconst_1
/*     */     //   477: iand
/*     */     //   478: ifeq +19 -> 497
/*     */     //   481: aload 4
/*     */     //   483: iload 8
/*     */     //   485: iinc 8 1
/*     */     //   488: aload_1
/*     */     //   489: invokevirtual 571	com/claro/transfer/UsuarioTO:getPerfil	()Ljava/lang/String;
/*     */     //   492: invokeinterface 150 3 0
/*     */     //   497: aload_1
/*     */     //   498: invokevirtual 208	com/claro/transfer/UsuarioTO:getStatus	()Ljava/lang/String;
/*     */     //   501: ifnull +7 -> 508
/*     */     //   504: iconst_1
/*     */     //   505: goto +4 -> 509
/*     */     //   508: iconst_0
/*     */     //   509: ldc_w 383
/*     */     //   512: aload_1
/*     */     //   513: invokevirtual 208	com/claro/transfer/UsuarioTO:getStatus	()Ljava/lang/String;
/*     */     //   516: invokevirtual 202	java/lang/String:equals	(Ljava/lang/Object;)Z
/*     */     //   519: ifeq +7 -> 526
/*     */     //   522: iconst_0
/*     */     //   523: goto +4 -> 527
/*     */     //   526: iconst_1
/*     */     //   527: iand
/*     */     //   528: ifeq +19 -> 547
/*     */     //   531: aload 4
/*     */     //   533: iload 8
/*     */     //   535: iinc 8 1
/*     */     //   538: aload_1
/*     */     //   539: invokevirtual 208	com/claro/transfer/UsuarioTO:getStatus	()Ljava/lang/String;
/*     */     //   542: invokeinterface 150 3 0
/*     */     //   547: aload 4
/*     */     //   549: invokeinterface 155 1 0
/*     */     //   554: astore 5
/*     */     //   556: iload_2
/*     */     //   557: ifne +5 -> 562
/*     */     //   560: iconst_m1
/*     */     //   561: istore_2
/*     */     //   562: iconst_0
/*     */     //   563: istore 9
/*     */     //   565: goto +167 -> 732
/*     */     //   568: iload 9
/*     */     //   570: iload_2
/*     */     //   571: if_icmpne +6 -> 577
/*     */     //   574: goto +270 -> 844
/*     */     //   577: iinc 9 1
/*     */     //   580: new 83	com/claro/transfer/UsuarioTO
/*     */     //   583: dup
/*     */     //   584: invokespecial 85	com/claro/transfer/UsuarioTO:<init>	()V
/*     */     //   587: astore 10
/*     */     //   589: aload 10
/*     */     //   591: aload 5
/*     */     //   593: ldc_w 580
/*     */     //   596: invokeinterface 582 2 0
/*     */     //   601: invokevirtual 165	com/claro/transfer/UsuarioTO:setNumEmpleado	(Ljava/lang/String;)V
/*     */     //   604: aload 10
/*     */     //   606: aload 5
/*     */     //   608: ldc_w 584
/*     */     //   611: invokeinterface 582 2 0
/*     */     //   616: invokevirtual 172	com/claro/transfer/UsuarioTO:setIdUsuario	(Ljava/lang/String;)V
/*     */     //   619: aload 10
/*     */     //   621: aload 5
/*     */     //   623: ldc_w 586
/*     */     //   626: invokeinterface 582 2 0
/*     */     //   631: invokevirtual 175	com/claro/transfer/UsuarioTO:setNombre	(Ljava/lang/String;)V
/*     */     //   634: aload 10
/*     */     //   636: aload 5
/*     */     //   638: ldc_w 588
/*     */     //   641: invokeinterface 582 2 0
/*     */     //   646: invokevirtual 590	com/claro/transfer/UsuarioTO:setPerfil	(Ljava/lang/String;)V
/*     */     //   649: aload 10
/*     */     //   651: aload 5
/*     */     //   653: ldc_w 593
/*     */     //   656: invokeinterface 582 2 0
/*     */     //   661: invokevirtual 181	com/claro/transfer/UsuarioTO:setStatus	(Ljava/lang/String;)V
/*     */     //   664: aload 10
/*     */     //   666: aload 5
/*     */     //   668: ldc_w 595
/*     */     //   671: invokeinterface 582 2 0
/*     */     //   676: invokevirtual 597	com/claro/transfer/UsuarioTO:setIdUsuarioCaptura	(Ljava/lang/String;)V
/*     */     //   679: aload 10
/*     */     //   681: aload 5
/*     */     //   683: ldc_w 600
/*     */     //   686: invokeinterface 602 2 0
/*     */     //   691: invokevirtual 606	com/claro/transfer/UsuarioTO:setFechaUpdate	(Ljava/sql/Timestamp;)V
/*     */     //   694: aload 10
/*     */     //   696: aload 5
/*     */     //   698: ldc_w 610
/*     */     //   701: invokeinterface 602 2 0
/*     */     //   706: invokevirtual 612	com/claro/transfer/UsuarioTO:setFechaAdmin	(Ljava/sql/Timestamp;)V
/*     */     //   709: aload 10
/*     */     //   711: aload 5
/*     */     //   713: ldc_w 615
/*     */     //   716: invokeinterface 582 2 0
/*     */     //   721: invokevirtual 617	com/claro/transfer/UsuarioTO:setSistemaAdmin	(Ljava/lang/String;)V
/*     */     //   724: aload 6
/*     */     //   726: aload 10
/*     */     //   728: invokevirtual 620	java/util/ArrayList:add	(Ljava/lang/Object;)Z
/*     */     //   731: pop
/*     */     //   732: aload 5
/*     */     //   734: invokeinterface 159 1 0
/*     */     //   739: ifne -171 -> 568
/*     */     //   742: goto +102 -> 844
/*     */     //   745: astore 7
/*     */     //   747: new 59	com/claro/exception/CAException
/*     */     //   750: dup
/*     */     //   751: iconst_0
/*     */     //   752: new 92	java/lang/StringBuilder
/*     */     //   755: dup
/*     */     //   756: ldc_w 623
/*     */     //   759: invokespecial 96	java/lang/StringBuilder:<init>	(Ljava/lang/String;)V
/*     */     //   762: aload 7
/*     */     //   764: invokevirtual 293	java/lang/Exception:toString	()Ljava/lang/String;
/*     */     //   767: invokevirtual 114	java/lang/StringBuilder:append	(Ljava/lang/String;)Ljava/lang/StringBuilder;
/*     */     //   770: ldc -41
/*     */     //   772: invokevirtual 114	java/lang/StringBuilder:append	(Ljava/lang/String;)Ljava/lang/StringBuilder;
/*     */     //   775: invokevirtual 122	java/lang/StringBuilder:toString	()Ljava/lang/String;
/*     */     //   778: invokespecial 63	com/claro/exception/CAException:<init>	(ILjava/lang/String;)V
/*     */     //   781: athrow
/*     */     //   782: astore 11
/*     */     //   784: aload 5
/*     */     //   786: ifnull +18 -> 804
/*     */     //   789: aload 5
/*     */     //   791: invokeinterface 294 1 0
/*     */     //   796: aconst_null
/*     */     //   797: astore 5
/*     */     //   799: goto +5 -> 804
/*     */     //   802: astore 12
/*     */     //   804: aload 4
/*     */     //   806: ifnull +18 -> 824
/*     */     //   809: aload 4
/*     */     //   811: invokeinterface 297 1 0
/*     */     //   816: aconst_null
/*     */     //   817: astore 4
/*     */     //   819: goto +5 -> 824
/*     */     //   822: astore 12
/*     */     //   824: aload_3
/*     */     //   825: ifnull +16 -> 841
/*     */     //   828: aload_3
/*     */     //   829: invokeinterface 298 1 0
/*     */     //   834: aconst_null
/*     */     //   835: astore_3
/*     */     //   836: goto +5 -> 841
/*     */     //   839: astore 12
/*     */     //   841: aload 11
/*     */     //   843: athrow
/*     */     //   844: aload 5
/*     */     //   846: ifnull +18 -> 864
/*     */     //   849: aload 5
/*     */     //   851: invokeinterface 294 1 0
/*     */     //   856: aconst_null
/*     */     //   857: astore 5
/*     */     //   859: goto +5 -> 864
/*     */     //   862: astore 12
/*     */     //   864: aload 4
/*     */     //   866: ifnull +18 -> 884
/*     */     //   869: aload 4
/*     */     //   871: invokeinterface 297 1 0
/*     */     //   876: aconst_null
/*     */     //   877: astore 4
/*     */     //   879: goto +5 -> 884
/*     */     //   882: astore 12
/*     */     //   884: aload_3
/*     */     //   885: ifnull +16 -> 901
/*     */     //   888: aload_3
/*     */     //   889: invokeinterface 298 1 0
/*     */     //   894: aconst_null
/*     */     //   895: astore_3
/*     */     //   896: goto +5 -> 901
/*     */     //   899: astore 12
/*     */     //   901: aload 6
/*     */     //   903: areturn
/*     */     // Line number table:
/*     */     //   Java source line #510	-> byte code offset #0
/*     */     //   Java source line #511	-> byte code offset #2
/*     */     //   Java source line #512	-> byte code offset #5
/*     */     //   Java source line #513	-> byte code offset #8
/*     */     //   Java source line #515	-> byte code offset #17
/*     */     //   Java source line #517	-> byte code offset #27
/*     */     //   Java source line #518	-> byte code offset #36
/*     */     //   Java source line #519	-> byte code offset #45
/*     */     //   Java source line #520	-> byte code offset #54
/*     */     //   Java source line #521	-> byte code offset #75
/*     */     //   Java source line #522	-> byte code offset #84
/*     */     //   Java source line #523	-> byte code offset #118
/*     */     //   Java source line #525	-> byte code offset #127
/*     */     //   Java source line #526	-> byte code offset #161
/*     */     //   Java source line #528	-> byte code offset #170
/*     */     //   Java source line #529	-> byte code offset #204
/*     */     //   Java source line #531	-> byte code offset #213
/*     */     //   Java source line #532	-> byte code offset #247
/*     */     //   Java source line #536	-> byte code offset #256
/*     */     //   Java source line #537	-> byte code offset #287
/*     */     //   Java source line #538	-> byte code offset #322
/*     */     //   Java source line #541	-> byte code offset #331
/*     */     //   Java source line #542	-> byte code offset #344
/*     */     //   Java source line #543	-> byte code offset #347
/*     */     //   Java source line #544	-> byte code offset #381
/*     */     //   Java source line #545	-> byte code offset #397
/*     */     //   Java source line #546	-> byte code offset #431
/*     */     //   Java source line #547	-> byte code offset #447
/*     */     //   Java source line #548	-> byte code offset #481
/*     */     //   Java source line #549	-> byte code offset #497
/*     */     //   Java source line #550	-> byte code offset #531
/*     */     //   Java source line #553	-> byte code offset #547
/*     */     //   Java source line #554	-> byte code offset #556
/*     */     //   Java source line #555	-> byte code offset #560
/*     */     //   Java source line #557	-> byte code offset #562
/*     */     //   Java source line #558	-> byte code offset #565
/*     */     //   Java source line #559	-> byte code offset #568
/*     */     //   Java source line #560	-> byte code offset #574
/*     */     //   Java source line #562	-> byte code offset #577
/*     */     //   Java source line #563	-> byte code offset #580
/*     */     //   Java source line #564	-> byte code offset #589
/*     */     //   Java source line #565	-> byte code offset #604
/*     */     //   Java source line #566	-> byte code offset #619
/*     */     //   Java source line #567	-> byte code offset #634
/*     */     //   Java source line #568	-> byte code offset #649
/*     */     //   Java source line #569	-> byte code offset #664
/*     */     //   Java source line #570	-> byte code offset #679
/*     */     //   Java source line #571	-> byte code offset #694
/*     */     //   Java source line #572	-> byte code offset #709
/*     */     //   Java source line #573	-> byte code offset #724
/*     */     //   Java source line #558	-> byte code offset #732
/*     */     //   Java source line #575	-> byte code offset #745
/*     */     //   Java source line #576	-> byte code offset #747
/*     */     //   Java source line #577	-> byte code offset #782
/*     */     //   Java source line #578	-> byte code offset #784
/*     */     //   Java source line #579	-> byte code offset #804
/*     */     //   Java source line #580	-> byte code offset #824
/*     */     //   Java source line #581	-> byte code offset #841
/*     */     //   Java source line #578	-> byte code offset #844
/*     */     //   Java source line #579	-> byte code offset #864
/*     */     //   Java source line #580	-> byte code offset #884
/*     */     //   Java source line #583	-> byte code offset #901
/*     */     // Local variable table:
/*     */     //   start	length	slot	name	signature
/*     */     //   0	904	0	this	UsuarioDAO
/*     */     //   0	904	1	user	UsuarioTO
/*     */     //   0	904	2	max	int
/*     */     //   1	895	3	conn	Connection
/*     */     //   3	875	4	prepStat	PreparedStatement
/*     */     //   6	852	5	resultSet	ResultSet
/*     */     //   15	887	6	lista	java.util.ArrayList<UsuarioTO>
/*     */     //   34	299	7	query	StringBuffer
/*     */     //   745	18	7	e	Exception
/*     */     //   345	189	8	cont	int
/*     */     //   563	15	9	contador	int
/*     */     //   587	140	10	userTemp	UsuarioTO
/*     */     //   782	60	11	localObject	Object
/*     */     //   802	1	12	localException1	Exception
/*     */     //   822	1	12	localException2	Exception
/*     */     //   839	1	12	localException3	Exception
/*     */     //   862	1	12	localException4	Exception
/*     */     //   882	1	12	localException5	Exception
/*     */     //   899	1	12	localException6	Exception
/*     */     // Exception table:
/*     */     //   from	to	target	type
/*     */     //   17	742	745	java/lang/Exception
/*     */     //   17	782	782	finally
/*     */     //   789	799	802	java/lang/Exception
/*     */     //   809	819	822	java/lang/Exception
/*     */     //   828	836	839	java/lang/Exception
/*     */     //   849	859	862	java/lang/Exception
/*     */     //   869	879	882	java/lang/Exception
/*     */     //   888	896	899	java/lang/Exception
/*     */   }
/*     */   
/*     */   /* Error */
/*     */   public boolean existeUsuario(UsuarioTO usuarioTO)
/*     */     throws Exception
/*     */   {
/*     */     // Byte code:
/*     */     //   0: aconst_null
/*     */     //   1: astore_2
/*     */     //   2: aconst_null
/*     */     //   3: astore_3
/*     */     //   4: aconst_null
/*     */     //   5: astore 4
/*     */     //   7: iconst_0
/*     */     //   8: istore 5
/*     */     //   10: invokestatic 29	com/claro/util/ServiceLocator:getInstance	()Lcom/claro/util/ServiceLocator;
/*     */     //   13: getstatic 132	com/claro/util/ServiceLocator:jdbcCirculoAzul	Ljava/lang/String;
/*     */     //   16: invokevirtual 135	com/claro/util/ServiceLocator:getConnection	(Ljava/lang/String;)Ljava/sql/Connection;
/*     */     //   19: astore_2
/*     */     //   20: new 66	java/lang/StringBuffer
/*     */     //   23: dup
/*     */     //   24: invokespecial 68	java/lang/StringBuffer:<init>	()V
/*     */     //   27: astore 6
/*     */     //   29: aload 6
/*     */     //   31: ldc_w 634
/*     */     //   34: invokevirtual 71	java/lang/StringBuffer:append	(Ljava/lang/String;)Ljava/lang/StringBuffer;
/*     */     //   37: pop
/*     */     //   38: aload 6
/*     */     //   40: ldc 75
/*     */     //   42: invokevirtual 71	java/lang/StringBuffer:append	(Ljava/lang/String;)Ljava/lang/StringBuffer;
/*     */     //   45: aload_0
/*     */     //   46: getfield 41	com/claro/dao/UsuarioDAO:schema_database	Ljava/lang/String;
/*     */     //   49: invokevirtual 71	java/lang/StringBuffer:append	(Ljava/lang/String;)Ljava/lang/StringBuffer;
/*     */     //   52: ldc_w 423
/*     */     //   55: invokevirtual 71	java/lang/StringBuffer:append	(Ljava/lang/String;)Ljava/lang/StringBuffer;
/*     */     //   58: pop
/*     */     //   59: aload 6
/*     */     //   61: ldc_w 636
/*     */     //   64: invokevirtual 71	java/lang/StringBuffer:append	(Ljava/lang/String;)Ljava/lang/StringBuffer;
/*     */     //   67: pop
/*     */     //   68: aload_2
/*     */     //   69: aload 6
/*     */     //   71: invokevirtual 143	java/lang/StringBuffer:toString	()Ljava/lang/String;
/*     */     //   74: invokeinterface 144 2 0
/*     */     //   79: astore_3
/*     */     //   80: aload_3
/*     */     //   81: iconst_1
/*     */     //   82: aload_1
/*     */     //   83: invokevirtual 441	com/claro/transfer/UsuarioTO:getNumEmpleado	()Ljava/lang/String;
/*     */     //   86: invokeinterface 150 3 0
/*     */     //   91: aload_3
/*     */     //   92: invokeinterface 155 1 0
/*     */     //   97: astore 4
/*     */     //   99: aload 4
/*     */     //   101: invokeinterface 159 1 0
/*     */     //   106: ifeq +104 -> 210
/*     */     //   109: iconst_1
/*     */     //   110: istore 5
/*     */     //   112: goto +98 -> 210
/*     */     //   115: astore 6
/*     */     //   117: new 47	java/lang/Exception
/*     */     //   120: dup
/*     */     //   121: new 92	java/lang/StringBuilder
/*     */     //   124: dup
/*     */     //   125: ldc_w 638
/*     */     //   128: invokespecial 96	java/lang/StringBuilder:<init>	(Ljava/lang/String;)V
/*     */     //   131: aload 6
/*     */     //   133: invokevirtual 293	java/lang/Exception:toString	()Ljava/lang/String;
/*     */     //   136: invokevirtual 114	java/lang/StringBuilder:append	(Ljava/lang/String;)Ljava/lang/StringBuilder;
/*     */     //   139: ldc -41
/*     */     //   141: invokevirtual 114	java/lang/StringBuilder:append	(Ljava/lang/String;)Ljava/lang/StringBuilder;
/*     */     //   144: invokevirtual 122	java/lang/StringBuilder:toString	()Ljava/lang/String;
/*     */     //   147: invokespecial 432	java/lang/Exception:<init>	(Ljava/lang/String;)V
/*     */     //   150: athrow
/*     */     //   151: astore 7
/*     */     //   153: aload 4
/*     */     //   155: ifnull +18 -> 173
/*     */     //   158: aload 4
/*     */     //   160: invokeinterface 294 1 0
/*     */     //   165: aconst_null
/*     */     //   166: astore 4
/*     */     //   168: goto +5 -> 173
/*     */     //   171: astore 8
/*     */     //   173: aload_3
/*     */     //   174: ifnull +16 -> 190
/*     */     //   177: aload_3
/*     */     //   178: invokeinterface 297 1 0
/*     */     //   183: aconst_null
/*     */     //   184: astore_3
/*     */     //   185: goto +5 -> 190
/*     */     //   188: astore 8
/*     */     //   190: aload_2
/*     */     //   191: ifnull +16 -> 207
/*     */     //   194: aload_2
/*     */     //   195: invokeinterface 298 1 0
/*     */     //   200: aconst_null
/*     */     //   201: astore_2
/*     */     //   202: goto +5 -> 207
/*     */     //   205: astore 8
/*     */     //   207: aload 7
/*     */     //   209: athrow
/*     */     //   210: aload 4
/*     */     //   212: ifnull +18 -> 230
/*     */     //   215: aload 4
/*     */     //   217: invokeinterface 294 1 0
/*     */     //   222: aconst_null
/*     */     //   223: astore 4
/*     */     //   225: goto +5 -> 230
/*     */     //   228: astore 8
/*     */     //   230: aload_3
/*     */     //   231: ifnull +16 -> 247
/*     */     //   234: aload_3
/*     */     //   235: invokeinterface 297 1 0
/*     */     //   240: aconst_null
/*     */     //   241: astore_3
/*     */     //   242: goto +5 -> 247
/*     */     //   245: astore 8
/*     */     //   247: aload_2
/*     */     //   248: ifnull +16 -> 264
/*     */     //   251: aload_2
/*     */     //   252: invokeinterface 298 1 0
/*     */     //   257: aconst_null
/*     */     //   258: astore_2
/*     */     //   259: goto +5 -> 264
/*     */     //   262: astore 8
/*     */     //   264: iload 5
/*     */     //   266: ireturn
/*     */     // Line number table:
/*     */     //   Java source line #595	-> byte code offset #0
/*     */     //   Java source line #596	-> byte code offset #2
/*     */     //   Java source line #597	-> byte code offset #4
/*     */     //   Java source line #598	-> byte code offset #7
/*     */     //   Java source line #600	-> byte code offset #10
/*     */     //   Java source line #602	-> byte code offset #20
/*     */     //   Java source line #603	-> byte code offset #29
/*     */     //   Java source line #604	-> byte code offset #38
/*     */     //   Java source line #605	-> byte code offset #59
/*     */     //   Java source line #607	-> byte code offset #68
/*     */     //   Java source line #608	-> byte code offset #80
/*     */     //   Java source line #609	-> byte code offset #91
/*     */     //   Java source line #610	-> byte code offset #99
/*     */     //   Java source line #611	-> byte code offset #109
/*     */     //   Java source line #613	-> byte code offset #115
/*     */     //   Java source line #614	-> byte code offset #117
/*     */     //   Java source line #615	-> byte code offset #151
/*     */     //   Java source line #616	-> byte code offset #153
/*     */     //   Java source line #617	-> byte code offset #173
/*     */     //   Java source line #618	-> byte code offset #190
/*     */     //   Java source line #619	-> byte code offset #207
/*     */     //   Java source line #616	-> byte code offset #210
/*     */     //   Java source line #617	-> byte code offset #230
/*     */     //   Java source line #618	-> byte code offset #247
/*     */     //   Java source line #620	-> byte code offset #264
/*     */     // Local variable table:
/*     */     //   start	length	slot	name	signature
/*     */     //   0	267	0	this	UsuarioDAO
/*     */     //   0	267	1	usuarioTO	UsuarioTO
/*     */     //   1	258	2	conn	Connection
/*     */     //   3	239	3	prepStat	PreparedStatement
/*     */     //   5	219	4	resultSet	ResultSet
/*     */     //   8	257	5	existe	boolean
/*     */     //   27	43	6	query	StringBuffer
/*     */     //   115	17	6	e	Exception
/*     */     //   151	57	7	localObject	Object
/*     */     //   171	1	8	localException1	Exception
/*     */     //   188	1	8	localException2	Exception
/*     */     //   205	1	8	localException3	Exception
/*     */     //   228	1	8	localException4	Exception
/*     */     //   245	1	8	localException5	Exception
/*     */     //   262	1	8	localException6	Exception
/*     */     // Exception table:
/*     */     //   from	to	target	type
/*     */     //   10	112	115	java/lang/Exception
/*     */     //   10	151	151	finally
/*     */     //   158	168	171	java/lang/Exception
/*     */     //   177	185	188	java/lang/Exception
/*     */     //   194	202	205	java/lang/Exception
/*     */     //   215	225	228	java/lang/Exception
/*     */     //   234	242	245	java/lang/Exception
/*     */     //   251	259	262	java/lang/Exception
/*     */   }
/*     */   
/*     */   /* Error */
/*     */   public void fechaAcceso(UsuarioTO usuarioTO)
/*     */     throws Exception
/*     */   {
/*     */     // Byte code:
/*     */     //   0: aconst_null
/*     */     //   1: astore_2
/*     */     //   2: aconst_null
/*     */     //   3: astore_3
/*     */     //   4: invokestatic 29	com/claro/util/ServiceLocator:getInstance	()Lcom/claro/util/ServiceLocator;
/*     */     //   7: getstatic 132	com/claro/util/ServiceLocator:jdbcCirculoAzul	Ljava/lang/String;
/*     */     //   10: invokevirtual 135	com/claro/util/ServiceLocator:getConnection	(Ljava/lang/String;)Ljava/sql/Connection;
/*     */     //   13: astore_2
/*     */     //   14: new 66	java/lang/StringBuffer
/*     */     //   17: dup
/*     */     //   18: invokespecial 68	java/lang/StringBuffer:<init>	()V
/*     */     //   21: astore 4
/*     */     //   23: aload 4
/*     */     //   25: ldc_w 486
/*     */     //   28: invokevirtual 71	java/lang/StringBuffer:append	(Ljava/lang/String;)Ljava/lang/StringBuffer;
/*     */     //   31: aload_0
/*     */     //   32: getfield 41	com/claro/dao/UsuarioDAO:schema_database	Ljava/lang/String;
/*     */     //   35: invokevirtual 71	java/lang/StringBuffer:append	(Ljava/lang/String;)Ljava/lang/StringBuffer;
/*     */     //   38: ldc_w 643
/*     */     //   41: invokevirtual 71	java/lang/StringBuffer:append	(Ljava/lang/String;)Ljava/lang/StringBuffer;
/*     */     //   44: pop
/*     */     //   45: aload 4
/*     */     //   47: ldc_w 494
/*     */     //   50: invokevirtual 71	java/lang/StringBuffer:append	(Ljava/lang/String;)Ljava/lang/StringBuffer;
/*     */     //   53: pop
/*     */     //   54: aload_2
/*     */     //   55: aload 4
/*     */     //   57: invokevirtual 143	java/lang/StringBuffer:toString	()Ljava/lang/String;
/*     */     //   60: invokeinterface 144 2 0
/*     */     //   65: astore_3
/*     */     //   66: aload_3
/*     */     //   67: iconst_1
/*     */     //   68: aload_1
/*     */     //   69: invokevirtual 441	com/claro/transfer/UsuarioTO:getNumEmpleado	()Ljava/lang/String;
/*     */     //   72: invokeinterface 150 3 0
/*     */     //   77: aload_3
/*     */     //   78: invokeinterface 474 1 0
/*     */     //   83: pop
/*     */     //   84: goto +73 -> 157
/*     */     //   87: astore 4
/*     */     //   89: new 47	java/lang/Exception
/*     */     //   92: dup
/*     */     //   93: new 92	java/lang/StringBuilder
/*     */     //   96: dup
/*     */     //   97: ldc_w 645
/*     */     //   100: invokespecial 96	java/lang/StringBuilder:<init>	(Ljava/lang/String;)V
/*     */     //   103: aload 4
/*     */     //   105: invokevirtual 293	java/lang/Exception:toString	()Ljava/lang/String;
/*     */     //   108: invokevirtual 114	java/lang/StringBuilder:append	(Ljava/lang/String;)Ljava/lang/StringBuilder;
/*     */     //   111: invokevirtual 122	java/lang/StringBuilder:toString	()Ljava/lang/String;
/*     */     //   114: invokespecial 432	java/lang/Exception:<init>	(Ljava/lang/String;)V
/*     */     //   117: athrow
/*     */     //   118: astore 5
/*     */     //   120: aload_3
/*     */     //   121: ifnull +16 -> 137
/*     */     //   124: aload_3
/*     */     //   125: invokeinterface 297 1 0
/*     */     //   130: aconst_null
/*     */     //   131: astore_3
/*     */     //   132: goto +5 -> 137
/*     */     //   135: astore 6
/*     */     //   137: aload_2
/*     */     //   138: ifnull +16 -> 154
/*     */     //   141: aload_2
/*     */     //   142: invokeinterface 298 1 0
/*     */     //   147: aconst_null
/*     */     //   148: astore_2
/*     */     //   149: goto +5 -> 154
/*     */     //   152: astore 6
/*     */     //   154: aload 5
/*     */     //   156: athrow
/*     */     //   157: aload_3
/*     */     //   158: ifnull +16 -> 174
/*     */     //   161: aload_3
/*     */     //   162: invokeinterface 297 1 0
/*     */     //   167: aconst_null
/*     */     //   168: astore_3
/*     */     //   169: goto +5 -> 174
/*     */     //   172: astore 6
/*     */     //   174: aload_2
/*     */     //   175: ifnull +16 -> 191
/*     */     //   178: aload_2
/*     */     //   179: invokeinterface 298 1 0
/*     */     //   184: aconst_null
/*     */     //   185: astore_2
/*     */     //   186: goto +5 -> 191
/*     */     //   189: astore 6
/*     */     //   191: return
/*     */     // Line number table:
/*     */     //   Java source line #624	-> byte code offset #0
/*     */     //   Java source line #625	-> byte code offset #2
/*     */     //   Java source line #627	-> byte code offset #4
/*     */     //   Java source line #629	-> byte code offset #14
/*     */     //   Java source line #631	-> byte code offset #23
/*     */     //   Java source line #632	-> byte code offset #45
/*     */     //   Java source line #634	-> byte code offset #54
/*     */     //   Java source line #635	-> byte code offset #66
/*     */     //   Java source line #636	-> byte code offset #77
/*     */     //   Java source line #638	-> byte code offset #87
/*     */     //   Java source line #639	-> byte code offset #89
/*     */     //   Java source line #640	-> byte code offset #118
/*     */     //   Java source line #641	-> byte code offset #120
/*     */     //   Java source line #642	-> byte code offset #137
/*     */     //   Java source line #643	-> byte code offset #154
/*     */     //   Java source line #641	-> byte code offset #157
/*     */     //   Java source line #642	-> byte code offset #174
/*     */     //   Java source line #644	-> byte code offset #191
/*     */     // Local variable table:
/*     */     //   start	length	slot	name	signature
/*     */     //   0	192	0	this	UsuarioDAO
/*     */     //   0	192	1	usuarioTO	UsuarioTO
/*     */     //   1	185	2	conn	Connection
/*     */     //   3	166	3	prepStat	PreparedStatement
/*     */     //   21	35	4	query	StringBuffer
/*     */     //   87	17	4	ex	Exception
/*     */     //   118	37	5	localObject	Object
/*     */     //   135	1	6	localException1	Exception
/*     */     //   152	1	6	localException2	Exception
/*     */     //   172	1	6	localException3	Exception
/*     */     //   189	1	6	localException4	Exception
/*     */     // Exception table:
/*     */     //   from	to	target	type
/*     */     //   4	84	87	java/lang/Exception
/*     */     //   4	118	118	finally
/*     */     //   124	132	135	java/lang/Exception
/*     */     //   141	149	152	java/lang/Exception
/*     */     //   161	169	172	java/lang/Exception
/*     */     //   178	186	189	java/lang/Exception
/*     */   }
/*     */   
/*     */   /* Error */
/*     */   public boolean ValidaCambioPass(UsuarioTO usuarioTO)
/*     */     throws Exception
/*     */   {
/*     */     // Byte code:
/*     */     //   0: aconst_null
/*     */     //   1: astore_2
/*     */     //   2: aconst_null
/*     */     //   3: astore_3
/*     */     //   4: aconst_null
/*     */     //   5: astore 4
/*     */     //   7: iconst_0
/*     */     //   8: istore 5
/*     */     //   10: invokestatic 29	com/claro/util/ServiceLocator:getInstance	()Lcom/claro/util/ServiceLocator;
/*     */     //   13: getstatic 132	com/claro/util/ServiceLocator:jdbcCirculoAzul	Ljava/lang/String;
/*     */     //   16: invokevirtual 135	com/claro/util/ServiceLocator:getConnection	(Ljava/lang/String;)Ljava/sql/Connection;
/*     */     //   19: astore_2
/*     */     //   20: new 66	java/lang/StringBuffer
/*     */     //   23: dup
/*     */     //   24: invokespecial 68	java/lang/StringBuffer:<init>	()V
/*     */     //   27: astore 6
/*     */     //   29: aload 6
/*     */     //   31: ldc_w 648
/*     */     //   34: invokevirtual 71	java/lang/StringBuffer:append	(Ljava/lang/String;)Ljava/lang/StringBuffer;
/*     */     //   37: aload_0
/*     */     //   38: getfield 41	com/claro/dao/UsuarioDAO:schema_database	Ljava/lang/String;
/*     */     //   41: invokevirtual 71	java/lang/StringBuffer:append	(Ljava/lang/String;)Ljava/lang/StringBuffer;
/*     */     //   44: ldc_w 650
/*     */     //   47: invokevirtual 71	java/lang/StringBuffer:append	(Ljava/lang/String;)Ljava/lang/StringBuffer;
/*     */     //   50: pop
/*     */     //   51: aload 6
/*     */     //   53: ldc_w 652
/*     */     //   56: invokevirtual 71	java/lang/StringBuffer:append	(Ljava/lang/String;)Ljava/lang/StringBuffer;
/*     */     //   59: pop
/*     */     //   60: aload_2
/*     */     //   61: aload 6
/*     */     //   63: invokevirtual 143	java/lang/StringBuffer:toString	()Ljava/lang/String;
/*     */     //   66: invokeinterface 144 2 0
/*     */     //   71: astore_3
/*     */     //   72: aload_3
/*     */     //   73: iconst_1
/*     */     //   74: aload_1
/*     */     //   75: invokevirtual 441	com/claro/transfer/UsuarioTO:getNumEmpleado	()Ljava/lang/String;
/*     */     //   78: invokeinterface 150 3 0
/*     */     //   83: aload_3
/*     */     //   84: invokeinterface 155 1 0
/*     */     //   89: astore 4
/*     */     //   91: aload 4
/*     */     //   93: invokeinterface 159 1 0
/*     */     //   98: ifeq +105 -> 203
/*     */     //   101: iconst_1
/*     */     //   102: istore 5
/*     */     //   104: goto +99 -> 203
/*     */     //   107: astore 6
/*     */     //   109: new 47	java/lang/Exception
/*     */     //   112: dup
/*     */     //   113: new 92	java/lang/StringBuilder
/*     */     //   116: dup
/*     */     //   117: ldc_w 654
/*     */     //   120: invokespecial 96	java/lang/StringBuilder:<init>	(Ljava/lang/String;)V
/*     */     //   123: aload 6
/*     */     //   125: invokevirtual 293	java/lang/Exception:toString	()Ljava/lang/String;
/*     */     //   128: invokevirtual 114	java/lang/StringBuilder:append	(Ljava/lang/String;)Ljava/lang/StringBuilder;
/*     */     //   131: ldc_w 656
/*     */     //   134: invokevirtual 114	java/lang/StringBuilder:append	(Ljava/lang/String;)Ljava/lang/StringBuilder;
/*     */     //   137: invokevirtual 122	java/lang/StringBuilder:toString	()Ljava/lang/String;
/*     */     //   140: invokespecial 432	java/lang/Exception:<init>	(Ljava/lang/String;)V
/*     */     //   143: athrow
/*     */     //   144: astore 7
/*     */     //   146: aload_3
/*     */     //   147: ifnull +16 -> 163
/*     */     //   150: aload_3
/*     */     //   151: invokeinterface 297 1 0
/*     */     //   156: aconst_null
/*     */     //   157: astore_3
/*     */     //   158: goto +5 -> 163
/*     */     //   161: astore 8
/*     */     //   163: aload_2
/*     */     //   164: ifnull +16 -> 180
/*     */     //   167: aload_2
/*     */     //   168: invokeinterface 298 1 0
/*     */     //   173: aconst_null
/*     */     //   174: astore_2
/*     */     //   175: goto +5 -> 180
/*     */     //   178: astore 8
/*     */     //   180: aload 4
/*     */     //   182: ifnull +18 -> 200
/*     */     //   185: aload 4
/*     */     //   187: invokeinterface 294 1 0
/*     */     //   192: aconst_null
/*     */     //   193: astore 4
/*     */     //   195: goto +5 -> 200
/*     */     //   198: astore 8
/*     */     //   200: aload 7
/*     */     //   202: athrow
/*     */     //   203: aload_3
/*     */     //   204: ifnull +16 -> 220
/*     */     //   207: aload_3
/*     */     //   208: invokeinterface 297 1 0
/*     */     //   213: aconst_null
/*     */     //   214: astore_3
/*     */     //   215: goto +5 -> 220
/*     */     //   218: astore 8
/*     */     //   220: aload_2
/*     */     //   221: ifnull +16 -> 237
/*     */     //   224: aload_2
/*     */     //   225: invokeinterface 298 1 0
/*     */     //   230: aconst_null
/*     */     //   231: astore_2
/*     */     //   232: goto +5 -> 237
/*     */     //   235: astore 8
/*     */     //   237: aload 4
/*     */     //   239: ifnull +18 -> 257
/*     */     //   242: aload 4
/*     */     //   244: invokeinterface 294 1 0
/*     */     //   249: aconst_null
/*     */     //   250: astore 4
/*     */     //   252: goto +5 -> 257
/*     */     //   255: astore 8
/*     */     //   257: iload 5
/*     */     //   259: ireturn
/*     */     // Line number table:
/*     */     //   Java source line #652	-> byte code offset #0
/*     */     //   Java source line #653	-> byte code offset #2
/*     */     //   Java source line #654	-> byte code offset #4
/*     */     //   Java source line #655	-> byte code offset #7
/*     */     //   Java source line #657	-> byte code offset #10
/*     */     //   Java source line #659	-> byte code offset #20
/*     */     //   Java source line #661	-> byte code offset #29
/*     */     //   Java source line #662	-> byte code offset #51
/*     */     //   Java source line #664	-> byte code offset #60
/*     */     //   Java source line #665	-> byte code offset #72
/*     */     //   Java source line #667	-> byte code offset #83
/*     */     //   Java source line #668	-> byte code offset #91
/*     */     //   Java source line #669	-> byte code offset #101
/*     */     //   Java source line #671	-> byte code offset #107
/*     */     //   Java source line #672	-> byte code offset #109
/*     */     //   Java source line #673	-> byte code offset #131
/*     */     //   Java source line #672	-> byte code offset #140
/*     */     //   Java source line #674	-> byte code offset #144
/*     */     //   Java source line #675	-> byte code offset #146
/*     */     //   Java source line #676	-> byte code offset #163
/*     */     //   Java source line #677	-> byte code offset #180
/*     */     //   Java source line #678	-> byte code offset #200
/*     */     //   Java source line #675	-> byte code offset #203
/*     */     //   Java source line #676	-> byte code offset #220
/*     */     //   Java source line #677	-> byte code offset #237
/*     */     //   Java source line #679	-> byte code offset #257
/*     */     // Local variable table:
/*     */     //   start	length	slot	name	signature
/*     */     //   0	260	0	this	UsuarioDAO
/*     */     //   0	260	1	usuarioTO	UsuarioTO
/*     */     //   1	231	2	conn	Connection
/*     */     //   3	212	3	prepStat	PreparedStatement
/*     */     //   5	246	4	resultSet	ResultSet
/*     */     //   8	250	5	CambioPass	boolean
/*     */     //   27	35	6	query	StringBuffer
/*     */     //   107	17	6	ex	Exception
/*     */     //   144	57	7	localObject	Object
/*     */     //   161	1	8	localException1	Exception
/*     */     //   178	1	8	localException2	Exception
/*     */     //   198	1	8	localException3	Exception
/*     */     //   218	1	8	localException4	Exception
/*     */     //   235	1	8	localException5	Exception
/*     */     //   255	1	8	localException6	Exception
/*     */     // Exception table:
/*     */     //   from	to	target	type
/*     */     //   10	104	107	java/lang/Exception
/*     */     //   10	144	144	finally
/*     */     //   150	158	161	java/lang/Exception
/*     */     //   167	175	178	java/lang/Exception
/*     */     //   185	195	198	java/lang/Exception
/*     */     //   207	215	218	java/lang/Exception
/*     */     //   224	232	235	java/lang/Exception
/*     */     //   242	252	255	java/lang/Exception
/*     */   }
/*     */ }


/* Location:              /opt/trabajo/claro/Guatemala/IS/CO/ClaroClub.ear!/ClaroClubEJB.jar!/com/claro/dao/UsuarioDAO.class
 * Java compiler version: 6 (50.0)
 * JD-Core Version:       0.7.1
 */